Compiled from "XPVacuumBlockEntity.java"
public class com.enderio.machines.common.blockentity.XPVacuumBlockEntity extends com.enderio.machines.common.blockentity.base.VacuumMachineBlockEntity<net.minecraft.world.entity.ExperienceOrb> {
  private static final com.enderio.machines.common.io.fluid.TankAccess TANK;
    descriptor: Lcom/enderio/machines/common/io/fluid/TankAccess;

  public com.enderio.machines.common.blockentity.XPVacuumBlockEntity(net.minecraft.world.level.block.entity.BlockEntityType<?>, net.minecraft.core.BlockPos, net.minecraft.world.level.block.state.BlockState);
    descriptor: (Lnet/minecraft/world/level/block/entity/BlockEntityType;Lnet/minecraft/core/BlockPos;Lnet/minecraft/world/level/block/state/BlockState;)V
    Code:
       0: aload_0
       1: aload_1
       2: aload_2
       3: aload_3
       4: ldc           #35                 // class net/minecraft/world/entity/ExperienceOrb
       6: invokespecial #38                 // Method com/enderio/machines/common/blockentity/base/VacuumMachineBlockEntity."<init>":(Lnet/minecraft/world/level/block/entity/BlockEntityType;Lnet/minecraft/core/BlockPos;Lnet/minecraft/world/level/block/state/BlockState;Ljava/lang/Class;)V
       9: aload_0
      10: new           #40                 // class com/enderio/core/common/network/slot/IntegerNetworkDataSlot
      13: dup
      14: aload_0
      15: invokedynamic #59,  0             // InvokeDynamic #0:get:(Lcom/enderio/machines/common/blockentity/XPVacuumBlockEntity;)Ljava/util/function/Supplier;
      20: aload_0
      21: invokedynamic #71,  0             // InvokeDynamic #1:accept:(Lcom/enderio/machines/common/blockentity/XPVacuumBlockEntity;)Ljava/util/function/Consumer;
      26: invokespecial #74                 // Method com/enderio/core/common/network/slot/IntegerNetworkDataSlot."<init>":(Ljava/util/function/Supplier;Ljava/util/function/Consumer;)V
      29: invokevirtual #78                 // Method addDataSlot:(Lcom/enderio/core/common/network/slot/NetworkDataSlot;)V
      32: return

  public java.lang.String getColor();
    descriptor: ()Ljava/lang/String;
    Code:
       0: getstatic     #95                 // Field com/enderio/machines/common/config/MachinesConfig.CLIENT:Lcom/enderio/machines/common/config/client/MachinesClientConfig;
       3: getfield      #101                // Field com/enderio/machines/common/config/client/MachinesClientConfig.BLOCKS:Lcom/enderio/machines/common/config/client/MachinesClientBlocksConfig;
       6: getfield      #107                // Field com/enderio/machines/common/config/client/MachinesClientBlocksConfig.XP_VACUUM_RANGE_COLOR:Lnet/minecraftforge/common/ForgeConfigSpec$ConfigValue;
       9: invokevirtual #109                // Method net/minecraftforge/common/ForgeConfigSpec$ConfigValue.get:()Ljava/lang/Object;
      12: checkcast     #111                // class java/lang/String
      15: areturn

  public net.minecraft.world.inventory.AbstractContainerMenu m_7208_(int, net.minecraft.world.entity.player.Inventory, net.minecraft.world.entity.player.Player);
    descriptor: (ILnet/minecraft/world/entity/player/Inventory;Lnet/minecraft/world/entity/player/Player;)Lnet/minecraft/world/inventory/AbstractContainerMenu;
    Code:
       0: new           #115                // class com/enderio/machines/common/menu/XPVacuumMenu
       3: dup
       4: aload_0
       5: aload_2
       6: iload_1
       7: invokespecial #118                // Method com/enderio/machines/common/menu/XPVacuumMenu."<init>":(Lcom/enderio/machines/common/blockentity/XPVacuumBlockEntity;Lnet/minecraft/world/entity/player/Inventory;I)V
      10: areturn

  public void handleEntity(net.minecraft.world.entity.ExperienceOrb);
    descriptor: (Lnet/minecraft/world/entity/ExperienceOrb;)V
    Code:
       0: getstatic     #128                // Field TANK:Lcom/enderio/machines/common/io/fluid/TankAccess;
       3: aload_0
       4: new           #130                // class net/minecraftforge/fluids/FluidStack
       7: dup
       8: getstatic     #136                // Field com/enderio/base/common/init/EIOFluids.XP_JUICE:Lcom/tterrag/registrate/util/entry/FluidEntry;
      11: invokevirtual #142                // Method com/tterrag/registrate/util/entry/FluidEntry.getSource:()Lnet/minecraftforge/fluids/ForgeFlowingFluid;
      14: aload_1
      15: invokevirtual #146                // Method net/minecraft/world/entity/ExperienceOrb.m_20801_:()I
      18: getstatic     #151                // Field com/enderio/base/common/util/ExperienceUtil.EXP_TO_FLUID:I
      21: imul
      22: invokespecial #154                // Method net/minecraftforge/fluids/FluidStack."<init>":(Lnet/minecraft/world/level/material/Fluid;I)V
      25: getstatic     #158                // Field net/minecraftforge/fluids/capability/IFluidHandler$FluidAction.EXECUTE:Lnet/minecraftforge/fluids/capability/IFluidHandler$FluidAction;
      28: invokevirtual #164                // Method com/enderio/machines/common/io/fluid/TankAccess.fill:(Lcom/enderio/machines/common/blockentity/base/MachineBlockEntity;Lnet/minecraftforge/fluids/FluidStack;Lnet/minecraftforge/fluids/capability/IFluidHandler$FluidAction;)I
      31: istore_2
      32: iload_2
      33: aload_1
      34: invokevirtual #146                // Method net/minecraft/world/entity/ExperienceOrb.m_20801_:()I
      37: getstatic     #151                // Field com/enderio/base/common/util/ExperienceUtil.EXP_TO_FLUID:I
      40: imul
      41: if_icmpne     51
      44: aload_1
      45: invokevirtual #168                // Method net/minecraft/world/entity/ExperienceOrb.m_146870_:()V
      48: goto          69
      51: aload_1
      52: dup
      53: getfield      #171                // Field net/minecraft/world/entity/ExperienceOrb.f_20770_:I
      56: i2f
      57: iload_2
      58: i2f
      59: getstatic     #151                // Field com/enderio/base/common/util/ExperienceUtil.EXP_TO_FLUID:I
      62: i2f
      63: fdiv
      64: fsub
      65: f2i
      66: putfield      #171                // Field net/minecraft/world/entity/ExperienceOrb.f_20770_:I
      69: return

  public com.enderio.machines.common.io.fluid.MachineTankLayout getTankLayout();
    descriptor: ()Lcom/enderio/machines/common/io/fluid/MachineTankLayout;
    Code:
       0: new           #20                 // class com/enderio/machines/common/io/fluid/MachineTankLayout$Builder
       3: dup
       4: invokespecial #179                // Method com/enderio/machines/common/io/fluid/MachineTankLayout$Builder."<init>":()V
       7: getstatic     #128                // Field TANK:Lcom/enderio/machines/common/io/fluid/TankAccess;
      10: ldc           #180                // int 2147483647
      12: invokevirtual #184                // Method com/enderio/machines/common/io/fluid/MachineTankLayout$Builder.tank:(Lcom/enderio/machines/common/io/fluid/TankAccess;I)Lcom/enderio/machines/common/io/fluid/MachineTankLayout$Builder;
      15: invokevirtual #187                // Method com/enderio/machines/common/io/fluid/MachineTankLayout$Builder.build:()Lcom/enderio/machines/common/io/fluid/MachineTankLayout;
      18: areturn

  protected com.enderio.machines.common.io.fluid.MachineFluidHandler createFluidHandler(com.enderio.machines.common.io.fluid.MachineTankLayout);
    descriptor: (Lcom/enderio/machines/common/io/fluid/MachineTankLayout;)Lcom/enderio/machines/common/io/fluid/MachineFluidHandler;
    Code:
       0: new           #8                  // class com/enderio/machines/common/blockentity/XPVacuumBlockEntity$1
       3: dup
       4: aload_0
       5: aload_0
       6: invokevirtual #193                // Method getIOConfig:()Lcom/enderio/api/io/IIOConfig;
       9: aload_0
      10: invokevirtual #195                // Method getTankLayout:()Lcom/enderio/machines/common/io/fluid/MachineTankLayout;
      13: invokespecial #198                // Method com/enderio/machines/common/blockentity/XPVacuumBlockEntity$1."<init>":(Lcom/enderio/machines/common/blockentity/XPVacuumBlockEntity;Lcom/enderio/api/io/IIOConfig;Lcom/enderio/machines/common/io/fluid/MachineTankLayout;)V
      16: areturn

  public com.enderio.machines.common.io.fluid.MachineFluidTank getFluidTank();
    descriptor: ()Lcom/enderio/machines/common/io/fluid/MachineFluidTank;
    Code:
       0: getstatic     #128                // Field TANK:Lcom/enderio/machines/common/io/fluid/TankAccess;
       3: aload_0
       4: invokevirtual #206                // Method com/enderio/machines/common/io/fluid/TankAccess.getTank:(Lcom/enderio/machines/common/blockentity/base/MachineBlockEntity;)Lcom/enderio/machines/common/io/fluid/MachineFluidTank;
       7: areturn

  public void handleEntity(net.minecraft.world.entity.Entity);
    descriptor: (Lnet/minecraft/world/entity/Entity;)V
    Code:
       0: aload_0
       1: aload_1
       2: checkcast     #35                 // class net/minecraft/world/entity/ExperienceOrb
       5: invokevirtual #209                // Method handleEntity:(Lnet/minecraft/world/entity/ExperienceOrb;)V
       8: return

  private void lambda$new$1(java.lang.Integer);
    descriptor: (Ljava/lang/Integer;)V
    Code:
       0: getstatic     #128                // Field TANK:Lcom/enderio/machines/common/io/fluid/TankAccess;
       3: aload_0
       4: new           #130                // class net/minecraftforge/fluids/FluidStack
       7: dup
       8: getstatic     #136                // Field com/enderio/base/common/init/EIOFluids.XP_JUICE:Lcom/tterrag/registrate/util/entry/FluidEntry;
      11: invokevirtual #142                // Method com/tterrag/registrate/util/entry/FluidEntry.getSource:()Lnet/minecraftforge/fluids/ForgeFlowingFluid;
      14: aload_1
      15: invokevirtual #214                // Method java/lang/Integer.intValue:()I
      18: invokespecial #154                // Method net/minecraftforge/fluids/FluidStack."<init>":(Lnet/minecraft/world/level/material/Fluid;I)V
      21: invokevirtual #218                // Method com/enderio/machines/common/io/fluid/TankAccess.setFluid:(Lcom/enderio/machines/common/blockentity/base/MachineBlockEntity;Lnet/minecraftforge/fluids/FluidStack;)V
      24: return

  private java.lang.Integer lambda$new$0();
    descriptor: ()Ljava/lang/Integer;
    Code:
       0: getstatic     #128                // Field TANK:Lcom/enderio/machines/common/io/fluid/TankAccess;
       3: aload_0
       4: invokevirtual #224                // Method com/enderio/machines/common/io/fluid/TankAccess.getFluidAmount:(Lcom/enderio/machines/common/blockentity/base/MachineBlockEntity;)I
       7: invokestatic  #228                // Method java/lang/Integer.valueOf:(I)Ljava/lang/Integer;
      10: areturn

  static {};
    descriptor: ()V
    Code:
       0: new           #160                // class com/enderio/machines/common/io/fluid/TankAccess
       3: dup
       4: invokespecial #230                // Method com/enderio/machines/common/io/fluid/TankAccess."<init>":()V
       7: putstatic     #128                // Field TANK:Lcom/enderio/machines/common/io/fluid/TankAccess;
      10: return
}
