Compiled from "ClientEventHandler.java"
public class reliquary.handler.ClientEventHandler {
  private static final int KEY_UNKNOWN;
    descriptor: I

  public static final net.minecraft.client.KeyMapping FORTUNE_COIN_TOGGLE_KEYBIND;
    descriptor: Lnet/minecraft/client/KeyMapping;

  private static final java.lang.String VOID_TEAR_MODE_TRANSLATION;
    descriptor: Ljava/lang/String;

  public static final net.minecraft.client.model.geom.ModelLayerLocation WITCH_HAT_LAYER;
    descriptor: Lnet/minecraft/client/model/geom/ModelLayerLocation;

  public static final net.minecraft.client.model.geom.ModelLayerLocation MOB_CHARM_BELT_LAYER;
    descriptor: Lnet/minecraft/client/model/geom/ModelLayerLocation;

  private static final java.util.List<net.minecraft.util.Tuple<reliquary.client.gui.components.Component, reliquary.client.gui.hud.HUDPosition>> hudComponents;
    descriptor: Ljava/util/List;

  private reliquary.handler.ClientEventHandler();
    descriptor: ()V
    Code:
       0: aload_0
       1: invokespecial #123                // Method java/lang/Object."<init>":()V
       4: return

  public static void registerHandlers();
    descriptor: ()V
    Code:
       0: invokestatic  #132                // Method net/minecraftforge/fml/javafmlmod/FMLJavaModLoadingContext.get:()Lnet/minecraftforge/fml/javafmlmod/FMLJavaModLoadingContext;
       3: invokevirtual #136                // Method net/minecraftforge/fml/javafmlmod/FMLJavaModLoadingContext.getModEventBus:()Lnet/minecraftforge/eventbus/api/IEventBus;
       6: astore_0
       7: aload_0
       8: invokedynamic #155,  0            // InvokeDynamic #0:accept:()Ljava/util/function/Consumer;
      13: invokeinterface #161,  2          // InterfaceMethod net/minecraftforge/eventbus/api/IEventBus.addListener:(Ljava/util/function/Consumer;)V
      18: aload_0
      19: invokedynamic #168,  0            // InvokeDynamic #1:accept:()Ljava/util/function/Consumer;
      24: invokeinterface #161,  2          // InterfaceMethod net/minecraftforge/eventbus/api/IEventBus.addListener:(Ljava/util/function/Consumer;)V
      29: aload_0
      30: invokedynamic #175,  0            // InvokeDynamic #2:accept:()Ljava/util/function/Consumer;
      35: invokeinterface #161,  2          // InterfaceMethod net/minecraftforge/eventbus/api/IEventBus.addListener:(Ljava/util/function/Consumer;)V
      40: aload_0
      41: invokedynamic #182,  0            // InvokeDynamic #3:accept:()Ljava/util/function/Consumer;
      46: invokeinterface #161,  2          // InterfaceMethod net/minecraftforge/eventbus/api/IEventBus.addListener:(Ljava/util/function/Consumer;)V
      51: aload_0
      52: invokedynamic #191,  0            // InvokeDynamic #4:accept:()Ljava/util/function/Consumer;
      57: invokeinterface #161,  2          // InterfaceMethod net/minecraftforge/eventbus/api/IEventBus.addListener:(Ljava/util/function/Consumer;)V
      62: aload_0
      63: invokedynamic #198,  0            // InvokeDynamic #5:accept:()Ljava/util/function/Consumer;
      68: invokeinterface #161,  2          // InterfaceMethod net/minecraftforge/eventbus/api/IEventBus.addListener:(Ljava/util/function/Consumer;)V
      73: getstatic     #204                // Field net/minecraftforge/common/MinecraftForge.EVENT_BUS:Lnet/minecraftforge/eventbus/api/IEventBus;
      76: astore_1
      77: aload_1
      78: invokedynamic #211,  0            // InvokeDynamic #6:accept:()Ljava/util/function/Consumer;
      83: invokeinterface #161,  2          // InterfaceMethod net/minecraftforge/eventbus/api/IEventBus.addListener:(Ljava/util/function/Consumer;)V
      88: aload_1
      89: invokedynamic #218,  0            // InvokeDynamic #7:accept:()Ljava/util/function/Consumer;
      94: invokeinterface #161,  2          // InterfaceMethod net/minecraftforge/eventbus/api/IEventBus.addListener:(Ljava/util/function/Consumer;)V
      99: aload_1
     100: invokedynamic #225,  0            // InvokeDynamic #8:accept:()Ljava/util/function/Consumer;
     105: invokeinterface #161,  2          // InterfaceMethod net/minecraftforge/eventbus/api/IEventBus.addListener:(Ljava/util/function/Consumer;)V
     110: return

  private static void onRenderLiving(net.minecraftforge.client.event.RenderLivingEvent$Pre<net.minecraft.world.entity.player.Player, net.minecraft.client.model.PlayerModel<net.minecraft.world.entity.player.Player>>);
    descriptor: (Lnet/minecraftforge/client/event/RenderLivingEvent$Pre;)V
    Code:
       0: aload_0
       1: invokevirtual #232                // Method net/minecraftforge/client/event/RenderLivingEvent$Pre.getEntity:()Lnet/minecraft/world/entity/LivingEntity;
       4: astore_2
       5: aload_2
       6: instanceof    #234                // class net/minecraft/world/entity/player/Player
       9: ifeq          82
      12: aload_2
      13: checkcast     #234                // class net/minecraft/world/entity/player/Player
      16: astore_1
      17: aload_1
      18: getstatic     #240                // Field net/minecraft/world/InteractionHand.OFF_HAND:Lnet/minecraft/world/InteractionHand;
      21: invokevirtual #244                // Method net/minecraft/world/entity/player/Player.m_21120_:(Lnet/minecraft/world/InteractionHand;)Lnet/minecraft/world/item/ItemStack;
      24: invokevirtual #250                // Method net/minecraft/world/item/ItemStack.m_41720_:()Lnet/minecraft/world/item/Item;
      27: getstatic     #256                // Field reliquary/init/ModItems.HANDGUN:Lnet/minecraftforge/registries/RegistryObject;
      30: invokevirtual #261                // Method net/minecraftforge/registries/RegistryObject.get:()Lnet/minecraftforge/registries/IForgeRegistryEntry;
      33: if_acmpne     40
      36: iconst_1
      37: goto          41
      40: iconst_0
      41: istore_2
      42: aload_1
      43: getstatic     #264                // Field net/minecraft/world/InteractionHand.MAIN_HAND:Lnet/minecraft/world/InteractionHand;
      46: invokevirtual #244                // Method net/minecraft/world/entity/player/Player.m_21120_:(Lnet/minecraft/world/InteractionHand;)Lnet/minecraft/world/item/ItemStack;
      49: invokevirtual #250                // Method net/minecraft/world/item/ItemStack.m_41720_:()Lnet/minecraft/world/item/Item;
      52: getstatic     #256                // Field reliquary/init/ModItems.HANDGUN:Lnet/minecraftforge/registries/RegistryObject;
      55: invokevirtual #261                // Method net/minecraftforge/registries/RegistryObject.get:()Lnet/minecraftforge/registries/IForgeRegistryEntry;
      58: if_acmpne     65
      61: iconst_1
      62: goto          66
      65: iconst_0
      66: istore_3
      67: iload_2
      68: ifne          75
      71: iload_3
      72: ifeq          82
      75: aload_0
      76: aload_1
      77: iload_2
      78: iload_3
      79: invokestatic  #268                // Method setHandgunArmPoses:(Lnet/minecraftforge/client/event/RenderLivingEvent$Pre;Lnet/minecraft/world/entity/player/Player;ZZ)V
      82: return

  private static void registerLayer(net.minecraftforge.client.event.EntityRenderersEvent$RegisterLayerDefinitions);
    descriptor: (Lnet/minecraftforge/client/event/EntityRenderersEvent$RegisterLayerDefinitions;)V
    Code:
       0: aload_0
       1: getstatic     #278                // Field WITCH_HAT_LAYER:Lnet/minecraft/client/model/geom/ModelLayerLocation;
       4: invokedynamic #291,  0            // InvokeDynamic #9:get:()Ljava/util/function/Supplier;
       9: invokevirtual #295                // Method net/minecraftforge/client/event/EntityRenderersEvent$RegisterLayerDefinitions.registerLayerDefinition:(Lnet/minecraft/client/model/geom/ModelLayerLocation;Ljava/util/function/Supplier;)V
      12: aload_0
      13: getstatic     #297                // Field MOB_CHARM_BELT_LAYER:Lnet/minecraft/client/model/geom/ModelLayerLocation;
      16: invokedynamic #302,  0            // InvokeDynamic #10:get:()Ljava/util/function/Supplier;
      21: invokevirtual #295                // Method net/minecraftforge/client/event/EntityRenderersEvent$RegisterLayerDefinitions.registerLayerDefinition:(Lnet/minecraft/client/model/geom/ModelLayerLocation;Ljava/util/function/Supplier;)V
      24: return

  private static void setHandgunArmPoses(net.minecraftforge.client.event.RenderLivingEvent$Pre<net.minecraft.world.entity.player.Player, net.minecraft.client.model.PlayerModel<net.minecraft.world.entity.player.Player>>, net.minecraft.world.entity.player.Player, boolean, boolean);
    descriptor: (Lnet/minecraftforge/client/event/RenderLivingEvent$Pre;Lnet/minecraft/world/entity/player/Player;ZZ)V
    Code:
       0: aload_0
       1: invokevirtual #308                // Method net/minecraftforge/client/event/RenderLivingEvent$Pre.getRenderer:()Lnet/minecraft/client/renderer/entity/LivingEntityRenderer;
       4: invokevirtual #314                // Method net/minecraft/client/renderer/entity/LivingEntityRenderer.m_7200_:()Lnet/minecraft/client/model/EntityModel;
       7: checkcast     #316                // class net/minecraft/client/model/PlayerModel
      10: astore        4
      12: aload_1
      13: iload_3
      14: iload_2
      15: invokestatic  #320                // Method isHandgunActive:(Lnet/minecraft/world/entity/player/Player;ZZ)Z
      18: ifeq          143
      21: aload_1
      22: iload_3
      23: iload_2
      24: invokestatic  #324                // Method getActiveHandgunHand:(Lnet/minecraft/world/entity/player/Player;ZZ)Lnet/minecraft/world/InteractionHand;
      27: astore        5
      29: aload_1
      30: invokevirtual #328                // Method net/minecraft/world/entity/player/Player.m_5737_:()Lnet/minecraft/world/entity/HumanoidArm;
      33: astore        6
      35: aload         5
      37: getstatic     #264                // Field net/minecraft/world/InteractionHand.MAIN_HAND:Lnet/minecraft/world/InteractionHand;
      40: if_acmpne     51
      43: aload         6
      45: getstatic     #334                // Field net/minecraft/world/entity/HumanoidArm.RIGHT:Lnet/minecraft/world/entity/HumanoidArm;
      48: if_acmpeq     67
      51: aload         5
      53: getstatic     #240                // Field net/minecraft/world/InteractionHand.OFF_HAND:Lnet/minecraft/world/InteractionHand;
      56: if_acmpne     89
      59: aload         6
      61: getstatic     #337                // Field net/minecraft/world/entity/HumanoidArm.LEFT:Lnet/minecraft/world/entity/HumanoidArm;
      64: if_acmpne     89
      67: aload         4
      69: getfield      #341                // Field net/minecraft/client/model/PlayerModel.f_102816_:Lnet/minecraft/client/model/HumanoidModel$ArmPose;
      72: getstatic     #344                // Field net/minecraft/client/model/HumanoidModel$ArmPose.BOW_AND_ARROW:Lnet/minecraft/client/model/HumanoidModel$ArmPose;
      75: if_acmpeq     89
      78: aload         4
      80: getstatic     #344                // Field net/minecraft/client/model/HumanoidModel$ArmPose.BOW_AND_ARROW:Lnet/minecraft/client/model/HumanoidModel$ArmPose;
      83: putfield      #341                // Field net/minecraft/client/model/PlayerModel.f_102816_:Lnet/minecraft/client/model/HumanoidModel$ArmPose;
      86: goto          140
      89: aload         5
      91: getstatic     #240                // Field net/minecraft/world/InteractionHand.OFF_HAND:Lnet/minecraft/world/InteractionHand;
      94: if_acmpne     105
      97: aload         6
      99: getstatic     #334                // Field net/minecraft/world/entity/HumanoidArm.RIGHT:Lnet/minecraft/world/entity/HumanoidArm;
     102: if_acmpeq     121
     105: aload         5
     107: getstatic     #264                // Field net/minecraft/world/InteractionHand.MAIN_HAND:Lnet/minecraft/world/InteractionHand;
     110: if_acmpne     140
     113: aload         6
     115: getstatic     #337                // Field net/minecraft/world/entity/HumanoidArm.LEFT:Lnet/minecraft/world/entity/HumanoidArm;
     118: if_acmpne     140
     121: aload         4
     123: getfield      #347                // Field net/minecraft/client/model/PlayerModel.f_102815_:Lnet/minecraft/client/model/HumanoidModel$ArmPose;
     126: getstatic     #344                // Field net/minecraft/client/model/HumanoidModel$ArmPose.BOW_AND_ARROW:Lnet/minecraft/client/model/HumanoidModel$ArmPose;
     129: if_acmpeq     140
     132: aload         4
     134: getstatic     #344                // Field net/minecraft/client/model/HumanoidModel$ArmPose.BOW_AND_ARROW:Lnet/minecraft/client/model/HumanoidModel$ArmPose;
     137: putfield      #347                // Field net/minecraft/client/model/PlayerModel.f_102815_:Lnet/minecraft/client/model/HumanoidModel$ArmPose;
     140: goto          181
     143: aload         4
     145: getfield      #341                // Field net/minecraft/client/model/PlayerModel.f_102816_:Lnet/minecraft/client/model/HumanoidModel$ArmPose;
     148: getstatic     #344                // Field net/minecraft/client/model/HumanoidModel$ArmPose.BOW_AND_ARROW:Lnet/minecraft/client/model/HumanoidModel$ArmPose;
     151: if_acmpne     162
     154: aload         4
     156: getstatic     #350                // Field net/minecraft/client/model/HumanoidModel$ArmPose.ITEM:Lnet/minecraft/client/model/HumanoidModel$ArmPose;
     159: putfield      #341                // Field net/minecraft/client/model/PlayerModel.f_102816_:Lnet/minecraft/client/model/HumanoidModel$ArmPose;
     162: aload         4
     164: getfield      #347                // Field net/minecraft/client/model/PlayerModel.f_102815_:Lnet/minecraft/client/model/HumanoidModel$ArmPose;
     167: getstatic     #344                // Field net/minecraft/client/model/HumanoidModel$ArmPose.BOW_AND_ARROW:Lnet/minecraft/client/model/HumanoidModel$ArmPose;
     170: if_acmpne     181
     173: aload         4
     175: getstatic     #350                // Field net/minecraft/client/model/HumanoidModel$ArmPose.ITEM:Lnet/minecraft/client/model/HumanoidModel$ArmPose;
     178: putfield      #347                // Field net/minecraft/client/model/PlayerModel.f_102815_:Lnet/minecraft/client/model/HumanoidModel$ArmPose;
     181: return

  private static net.minecraft.world.InteractionHand getActiveHandgunHand(net.minecraft.world.entity.player.Player, boolean, boolean);
    descriptor: (Lnet/minecraft/world/entity/player/Player;ZZ)Lnet/minecraft/world/InteractionHand;
    Code:
       0: iload_1
       1: iload_2
       2: if_icmpeq     19
       5: iload_1
       6: ifeq          15
       9: getstatic     #264                // Field net/minecraft/world/InteractionHand.MAIN_HAND:Lnet/minecraft/world/InteractionHand;
      12: goto          18
      15: getstatic     #240                // Field net/minecraft/world/InteractionHand.OFF_HAND:Lnet/minecraft/world/InteractionHand;
      18: areturn
      19: aload_0
      20: getfield      #359                // Field net/minecraft/world/entity/player/Player.f_19853_:Lnet/minecraft/world/level/Level;
      23: aload_0
      24: invokevirtual #363                // Method net/minecraft/world/entity/player/Player.m_21205_:()Lnet/minecraft/world/item/ItemStack;
      27: invokestatic  #367                // Method isValidTimeFrame:(Lnet/minecraft/world/level/Level;Lnet/minecraft/world/item/ItemStack;)Z
      30: istore_3
      31: aload_0
      32: getfield      #359                // Field net/minecraft/world/entity/player/Player.f_19853_:Lnet/minecraft/world/level/Level;
      35: aload_0
      36: invokevirtual #370                // Method net/minecraft/world/entity/player/Player.m_21206_:()Lnet/minecraft/world/item/ItemStack;
      39: invokestatic  #367                // Method isValidTimeFrame:(Lnet/minecraft/world/level/Level;Lnet/minecraft/world/item/ItemStack;)Z
      42: istore        4
      44: iload_3
      45: iload         4
      47: if_icmpeq     64
      50: iload_3
      51: ifeq          60
      54: getstatic     #264                // Field net/minecraft/world/InteractionHand.MAIN_HAND:Lnet/minecraft/world/InteractionHand;
      57: goto          63
      60: getstatic     #240                // Field net/minecraft/world/InteractionHand.OFF_HAND:Lnet/minecraft/world/InteractionHand;
      63: areturn
      64: getstatic     #256                // Field reliquary/init/ModItems.HANDGUN:Lnet/minecraftforge/registries/RegistryObject;
      67: invokevirtual #261                // Method net/minecraftforge/registries/RegistryObject.get:()Lnet/minecraftforge/registries/IForgeRegistryEntry;
      70: checkcast     #372                // class reliquary/items/HandgunItem
      73: aload_0
      74: invokevirtual #363                // Method net/minecraft/world/entity/player/Player.m_21205_:()Lnet/minecraft/world/item/ItemStack;
      77: invokevirtual #376                // Method reliquary/items/HandgunItem.getCooldown:(Lnet/minecraft/world/item/ItemStack;)J
      80: getstatic     #256                // Field reliquary/init/ModItems.HANDGUN:Lnet/minecraftforge/registries/RegistryObject;
      83: invokevirtual #261                // Method net/minecraftforge/registries/RegistryObject.get:()Lnet/minecraftforge/registries/IForgeRegistryEntry;
      86: checkcast     #372                // class reliquary/items/HandgunItem
      89: aload_0
      90: invokevirtual #370                // Method net/minecraft/world/entity/player/Player.m_21206_:()Lnet/minecraft/world/item/ItemStack;
      93: invokevirtual #376                // Method reliquary/items/HandgunItem.getCooldown:(Lnet/minecraft/world/item/ItemStack;)J
      96: lcmp
      97: ifge          106
     100: getstatic     #264                // Field net/minecraft/world/InteractionHand.MAIN_HAND:Lnet/minecraft/world/InteractionHand;
     103: goto          109
     106: getstatic     #240                // Field net/minecraft/world/InteractionHand.OFF_HAND:Lnet/minecraft/world/InteractionHand;
     109: areturn

  private static boolean isHandgunActive(net.minecraft.world.entity.player.Player, boolean, boolean);
    descriptor: (Lnet/minecraft/world/entity/player/Player;ZZ)Z
    Code:
       0: iload_1
       1: ifeq          18
       4: aload_0
       5: getfield      #359                // Field net/minecraft/world/entity/player/Player.f_19853_:Lnet/minecraft/world/level/Level;
       8: aload_0
       9: invokevirtual #363                // Method net/minecraft/world/entity/player/Player.m_21205_:()Lnet/minecraft/world/item/ItemStack;
      12: invokestatic  #367                // Method isValidTimeFrame:(Lnet/minecraft/world/level/Level;Lnet/minecraft/world/item/ItemStack;)Z
      15: ifne          36
      18: iload_2
      19: ifeq          40
      22: aload_0
      23: getfield      #359                // Field net/minecraft/world/entity/player/Player.f_19853_:Lnet/minecraft/world/level/Level;
      26: aload_0
      27: invokevirtual #370                // Method net/minecraft/world/entity/player/Player.m_21206_:()Lnet/minecraft/world/item/ItemStack;
      30: invokestatic  #367                // Method isValidTimeFrame:(Lnet/minecraft/world/level/Level;Lnet/minecraft/world/item/ItemStack;)Z
      33: ifeq          40
      36: iconst_1
      37: goto          41
      40: iconst_0
      41: ireturn

  private static boolean isValidTimeFrame(net.minecraft.world.level.Level, net.minecraft.world.item.ItemStack);
    descriptor: (Lnet/minecraft/world/level/Level;Lnet/minecraft/world/item/ItemStack;)Z
    Code:
       0: getstatic     #256                // Field reliquary/init/ModItems.HANDGUN:Lnet/minecraftforge/registries/RegistryObject;
       3: invokevirtual #261                // Method net/minecraftforge/registries/RegistryObject.get:()Lnet/minecraftforge/registries/IForgeRegistryEntry;
       6: checkcast     #372                // class reliquary/items/HandgunItem
       9: aload_1
      10: invokevirtual #376                // Method reliquary/items/HandgunItem.getCooldown:(Lnet/minecraft/world/item/ItemStack;)J
      13: ldc2_w        #379                // long 5l
      16: ladd
      17: lstore_2
      18: lload_2
      19: aload_0
      20: invokevirtual #386                // Method net/minecraft/world/level/Level.m_46467_:()J
      23: lsub
      24: getstatic     #256                // Field reliquary/init/ModItems.HANDGUN:Lnet/minecraftforge/registries/RegistryObject;
      27: invokevirtual #261                // Method net/minecraftforge/registries/RegistryObject.get:()Lnet/minecraftforge/registries/IForgeRegistryEntry;
      30: checkcast     #372                // class reliquary/items/HandgunItem
      33: aload_1
      34: invokevirtual #390                // Method reliquary/items/HandgunItem.m_8105_:(Lnet/minecraft/world/item/ItemStack;)I
      37: i2l
      38: lcmp
      39: ifgt          55
      42: lload_2
      43: aload_0
      44: invokevirtual #386                // Method net/minecraft/world/level/Level.m_46467_:()J
      47: lcmp
      48: iflt          55
      51: iconst_1
      52: goto          56
      55: iconst_0
      56: ireturn

  private static void onRenderTick(net.minecraftforge.event.TickEvent$RenderTickEvent);
    descriptor: (Lnet/minecraftforge/event/TickEvent$RenderTickEvent;)V
    Code:
       0: invokestatic  #401                // Method net/minecraft/client/Minecraft.m_91087_:()Lnet/minecraft/client/Minecraft;
       3: astore_1
       4: aload_1
       5: getfield      #405                // Field net/minecraft/client/Minecraft.f_91080_:Lnet/minecraft/client/gui/screens/Screen;
       8: ifnonnull     31
      11: invokestatic  #409                // Method net/minecraft/client/Minecraft.m_91404_:()Z
      14: ifeq          31
      17: aload_1
      18: invokevirtual #412                // Method net/minecraft/client/Minecraft.m_91302_:()Z
      21: ifeq          31
      24: aload_1
      25: getfield      #416                // Field net/minecraft/client/Minecraft.f_91074_:Lnet/minecraft/client/player/LocalPlayer;
      28: ifnonnull     32
      31: return
      32: getstatic     #418                // Field hudComponents:Ljava/util/List;
      35: invokeinterface #423,  1          // InterfaceMethod java/util/List.isEmpty:()Z
      40: ifeq          46
      43: invokestatic  #426                // Method initHUDComponents:()V
      46: new           #428                // class com/mojang/blaze3d/vertex/PoseStack
      49: dup
      50: invokespecial #429                // Method com/mojang/blaze3d/vertex/PoseStack."<init>":()V
      53: invokestatic  #433                // Method renderHUDComponents:(Lcom/mojang/blaze3d/vertex/PoseStack;)V
      56: return

  private static void onMouseScrolled(net.minecraftforge.client.event.InputEvent$MouseScrollEvent);
    descriptor: (Lnet/minecraftforge/client/event/InputEvent$MouseScrollEvent;)V
    Code:
       0: invokestatic  #401                // Method net/minecraft/client/Minecraft.m_91087_:()Lnet/minecraft/client/Minecraft;
       3: astore_1
       4: aload_1
       5: getfield      #405                // Field net/minecraft/client/Minecraft.f_91080_:Lnet/minecraft/client/gui/screens/Screen;
       8: ifnonnull     17
      11: invokestatic  #441                // Method net/minecraft/client/gui/screens/Screen.m_96638_:()Z
      14: ifne          18
      17: return
      18: aload_1
      19: getfield      #416                // Field net/minecraft/client/Minecraft.f_91074_:Lnet/minecraft/client/player/LocalPlayer;
      22: astore_2
      23: aload_2
      24: ifnonnull     28
      27: return
      28: aload_2
      29: invokevirtual #444                // Method net/minecraft/client/player/LocalPlayer.m_21205_:()Lnet/minecraft/world/item/ItemStack;
      32: astore_3
      33: aload_0
      34: invokevirtual #448                // Method net/minecraftforge/client/event/InputEvent$MouseScrollEvent.getScrollDelta:()D
      37: dstore        4
      39: aload_3
      40: invokevirtual #250                // Method net/minecraft/world/item/ItemStack.m_41720_:()Lnet/minecraft/world/item/Item;
      43: astore        7
      45: aload         7
      47: instanceof    #450                // class reliquary/items/util/IScrollableItem
      50: ifeq          94
      53: aload         7
      55: checkcast     #450                // class reliquary/items/util/IScrollableItem
      58: astore        6
      60: aload         6
      62: aload_3
      63: aload_2
      64: dload         4
      66: invokeinterface #453,  5          // InterfaceMethod reliquary/items/util/IScrollableItem.onMouseScrolled:(Lnet/minecraft/world/item/ItemStack;Lnet/minecraft/world/entity/player/Player;D)Lnet/minecraft/world/InteractionResult;
      71: getstatic     #459                // Field net/minecraft/world/InteractionResult.PASS:Lnet/minecraft/world/InteractionResult;
      74: if_acmpne     94
      77: new           #461                // class reliquary/network/ScrolledItemPacket
      80: dup
      81: dload         4
      83: invokespecial #464                // Method reliquary/network/ScrolledItemPacket."<init>":(D)V
      86: invokestatic  #469                // Method reliquary/network/PacketHandler.sendToServer:(Ljava/lang/Object;)V
      89: aload_0
      90: iconst_1
      91: invokevirtual #473                // Method net/minecraftforge/client/event/InputEvent$MouseScrollEvent.setCanceled:(Z)V
      94: return

  private static void renderHUDComponents(com.mojang.blaze3d.vertex.PoseStack);
    descriptor: (Lcom/mojang/blaze3d/vertex/PoseStack;)V
    Code:
       0: getstatic     #418                // Field hudComponents:Ljava/util/List;
       3: invokeinterface #484,  1          // InterfaceMethod java/util/List.iterator:()Ljava/util/Iterator;
       8: astore_1
       9: aload_1
      10: invokeinterface #489,  1          // InterfaceMethod java/util/Iterator.hasNext:()Z
      15: ifeq          49
      18: aload_1
      19: invokeinterface #492,  1          // InterfaceMethod java/util/Iterator.next:()Ljava/lang/Object;
      24: checkcast     #494                // class net/minecraft/util/Tuple
      27: astore_2
      28: aload_0
      29: aload_2
      30: invokevirtual #497                // Method net/minecraft/util/Tuple.m_14418_:()Ljava/lang/Object;
      33: checkcast     #499                // class reliquary/client/gui/components/Component
      36: aload_2
      37: invokevirtual #502                // Method net/minecraft/util/Tuple.m_14419_:()Ljava/lang/Object;
      40: checkcast     #504                // class reliquary/client/gui/hud/HUDPosition
      43: invokestatic  #510                // Method reliquary/client/gui/hud/HUDRenderrer.render:(Lcom/mojang/blaze3d/vertex/PoseStack;Lreliquary/client/gui/components/Component;Lreliquary/client/gui/hud/HUDPosition;)V
      46: goto          9
      49: return

  private static void initHUDComponents();
    descriptor: ()V
    Code:
       0: getstatic     #418                // Field hudComponents:Ljava/util/List;
       3: new           #494                // class net/minecraft/util/Tuple
       6: dup
       7: new           #517                // class reliquary/client/gui/hud/ChargeableItemInfoPane
      10: dup
      11: getstatic     #520                // Field reliquary/init/ModItems.ALKAHESTRY_TOME:Lnet/minecraftforge/registries/RegistryObject;
      14: invokevirtual #261                // Method net/minecraftforge/registries/RegistryObject.get:()Lnet/minecraftforge/registries/IForgeRegistryEntry;
      17: checkcast     #522                // class net/minecraft/world/item/Item
      20: getstatic     #526                // Field reliquary/reference/Settings.CLIENT:Lreliquary/reference/Settings$Client;
      23: getfield      #530                // Field reliquary/reference/Settings$Client.hudPositions:Lreliquary/reference/Settings$Client$HudPos;
      26: getfield      #534                // Field reliquary/reference/Settings$Client$HudPos.alkahestryTome:Lnet/minecraftforge/common/ForgeConfigSpec$EnumValue;
      29: invokevirtual #536                // Method net/minecraftforge/common/ForgeConfigSpec$EnumValue.get:()Ljava/lang/Object;
      32: checkcast     #504                // class reliquary/client/gui/hud/HUDPosition
      35: new           #246                // class net/minecraft/world/item/ItemStack
      38: dup
      39: getstatic     #542                // Field net/minecraft/world/item/Items.f_42451_:Lnet/minecraft/world/item/Item;
      42: invokespecial #545                // Method net/minecraft/world/item/ItemStack."<init>":(Lnet/minecraft/world/level/ItemLike;)V
      45: invokedynamic #557,  0            // InvokeDynamic #11:apply:()Ljava/util/function/Function;
      50: invokespecial #560                // Method reliquary/client/gui/hud/ChargeableItemInfoPane."<init>":(Lnet/minecraft/world/item/Item;Lreliquary/client/gui/hud/HUDPosition;Lnet/minecraft/world/item/ItemStack;Ljava/util/function/Function;)V
      53: getstatic     #526                // Field reliquary/reference/Settings.CLIENT:Lreliquary/reference/Settings$Client;
      56: getfield      #530                // Field reliquary/reference/Settings$Client.hudPositions:Lreliquary/reference/Settings$Client$HudPos;
      59: getfield      #534                // Field reliquary/reference/Settings$Client$HudPos.alkahestryTome:Lnet/minecraftforge/common/ForgeConfigSpec$EnumValue;
      62: invokevirtual #536                // Method net/minecraftforge/common/ForgeConfigSpec$EnumValue.get:()Ljava/lang/Object;
      65: checkcast     #504                // class reliquary/client/gui/hud/HUDPosition
      68: invokespecial #563                // Method net/minecraft/util/Tuple."<init>":(Ljava/lang/Object;Ljava/lang/Object;)V
      71: invokeinterface #567,  2          // InterfaceMethod java/util/List.add:(Ljava/lang/Object;)Z
      76: pop
      77: getstatic     #418                // Field hudComponents:Ljava/util/List;
      80: new           #494                // class net/minecraft/util/Tuple
      83: dup
      84: new           #517                // class reliquary/client/gui/hud/ChargeableItemInfoPane
      87: dup
      88: getstatic     #570                // Field reliquary/init/ModItems.DESTRUCTION_CATALYST:Lnet/minecraftforge/registries/RegistryObject;
      91: invokevirtual #261                // Method net/minecraftforge/registries/RegistryObject.get:()Lnet/minecraftforge/registries/IForgeRegistryEntry;
      94: checkcast     #522                // class net/minecraft/world/item/Item
      97: getstatic     #526                // Field reliquary/reference/Settings.CLIENT:Lreliquary/reference/Settings$Client;
     100: getfield      #530                // Field reliquary/reference/Settings$Client.hudPositions:Lreliquary/reference/Settings$Client$HudPos;
     103: getfield      #573                // Field reliquary/reference/Settings$Client$HudPos.destructionCatalyst:Lnet/minecraftforge/common/ForgeConfigSpec$EnumValue;
     106: invokevirtual #536                // Method net/minecraftforge/common/ForgeConfigSpec$EnumValue.get:()Ljava/lang/Object;
     109: checkcast     #504                // class reliquary/client/gui/hud/HUDPosition
     112: new           #246                // class net/minecraft/world/item/ItemStack
     115: dup
     116: getstatic     #576                // Field net/minecraft/world/item/Items.f_42403_:Lnet/minecraft/world/item/Item;
     119: invokespecial #545                // Method net/minecraft/world/item/ItemStack."<init>":(Lnet/minecraft/world/level/ItemLike;)V
     122: invokedynamic #581,  0            // InvokeDynamic #12:apply:()Ljava/util/function/Function;
     127: invokespecial #560                // Method reliquary/client/gui/hud/ChargeableItemInfoPane."<init>":(Lnet/minecraft/world/item/Item;Lreliquary/client/gui/hud/HUDPosition;Lnet/minecraft/world/item/ItemStack;Ljava/util/function/Function;)V
     130: getstatic     #526                // Field reliquary/reference/Settings.CLIENT:Lreliquary/reference/Settings$Client;
     133: getfield      #530                // Field reliquary/reference/Settings$Client.hudPositions:Lreliquary/reference/Settings$Client$HudPos;
     136: getfield      #573                // Field reliquary/reference/Settings$Client$HudPos.destructionCatalyst:Lnet/minecraftforge/common/ForgeConfigSpec$EnumValue;
     139: invokevirtual #536                // Method net/minecraftforge/common/ForgeConfigSpec$EnumValue.get:()Ljava/lang/Object;
     142: checkcast     #504                // class reliquary/client/gui/hud/HUDPosition
     145: invokespecial #563                // Method net/minecraft/util/Tuple."<init>":(Ljava/lang/Object;Ljava/lang/Object;)V
     148: invokeinterface #567,  2          // InterfaceMethod java/util/List.add:(Ljava/lang/Object;)Z
     153: pop
     154: getstatic     #418                // Field hudComponents:Ljava/util/List;
     157: new           #494                // class net/minecraft/util/Tuple
     160: dup
     161: new           #517                // class reliquary/client/gui/hud/ChargeableItemInfoPane
     164: dup
     165: getstatic     #584                // Field reliquary/init/ModItems.MIDAS_TOUCHSTONE:Lnet/minecraftforge/registries/RegistryObject;
     168: invokevirtual #261                // Method net/minecraftforge/registries/RegistryObject.get:()Lnet/minecraftforge/registries/IForgeRegistryEntry;
     171: checkcast     #522                // class net/minecraft/world/item/Item
     174: getstatic     #526                // Field reliquary/reference/Settings.CLIENT:Lreliquary/reference/Settings$Client;
     177: getfield      #530                // Field reliquary/reference/Settings$Client.hudPositions:Lreliquary/reference/Settings$Client$HudPos;
     180: getfield      #587                // Field reliquary/reference/Settings$Client$HudPos.midasTouchstone:Lnet/minecraftforge/common/ForgeConfigSpec$EnumValue;
     183: invokevirtual #536                // Method net/minecraftforge/common/ForgeConfigSpec$EnumValue.get:()Ljava/lang/Object;
     186: checkcast     #504                // class reliquary/client/gui/hud/HUDPosition
     189: new           #246                // class net/minecraft/world/item/ItemStack
     192: dup
     193: getstatic     #590                // Field net/minecraft/world/item/Items.f_42525_:Lnet/minecraft/world/item/Item;
     196: invokespecial #545                // Method net/minecraft/world/item/ItemStack."<init>":(Lnet/minecraft/world/level/ItemLike;)V
     199: invokedynamic #595,  0            // InvokeDynamic #13:apply:()Ljava/util/function/Function;
     204: invokespecial #560                // Method reliquary/client/gui/hud/ChargeableItemInfoPane."<init>":(Lnet/minecraft/world/item/Item;Lreliquary/client/gui/hud/HUDPosition;Lnet/minecraft/world/item/ItemStack;Ljava/util/function/Function;)V
     207: getstatic     #526                // Field reliquary/reference/Settings.CLIENT:Lreliquary/reference/Settings$Client;
     210: getfield      #530                // Field reliquary/reference/Settings$Client.hudPositions:Lreliquary/reference/Settings$Client$HudPos;
     213: getfield      #587                // Field reliquary/reference/Settings$Client$HudPos.midasTouchstone:Lnet/minecraftforge/common/ForgeConfigSpec$EnumValue;
     216: invokevirtual #536                // Method net/minecraftforge/common/ForgeConfigSpec$EnumValue.get:()Ljava/lang/Object;
     219: checkcast     #504                // class reliquary/client/gui/hud/HUDPosition
     222: invokespecial #563                // Method net/minecraft/util/Tuple."<init>":(Ljava/lang/Object;Ljava/lang/Object;)V
     225: invokeinterface #567,  2          // InterfaceMethod java/util/List.add:(Ljava/lang/Object;)Z
     230: pop
     231: getstatic     #418                // Field hudComponents:Ljava/util/List;
     234: new           #494                // class net/minecraft/util/Tuple
     237: dup
     238: new           #517                // class reliquary/client/gui/hud/ChargeableItemInfoPane
     241: dup
     242: getstatic     #598                // Field reliquary/init/ModItems.INFERNAL_CHALICE:Lnet/minecraftforge/registries/RegistryObject;
     245: invokevirtual #261                // Method net/minecraftforge/registries/RegistryObject.get:()Lnet/minecraftforge/registries/IForgeRegistryEntry;
     248: checkcast     #522                // class net/minecraft/world/item/Item
     251: getstatic     #526                // Field reliquary/reference/Settings.CLIENT:Lreliquary/reference/Settings$Client;
     254: getfield      #530                // Field reliquary/reference/Settings$Client.hudPositions:Lreliquary/reference/Settings$Client$HudPos;
     257: getfield      #601                // Field reliquary/reference/Settings$Client$HudPos.infernalChalice:Lnet/minecraftforge/common/ForgeConfigSpec$EnumValue;
     260: invokevirtual #536                // Method net/minecraftforge/common/ForgeConfigSpec$EnumValue.get:()Ljava/lang/Object;
     263: checkcast     #504                // class reliquary/client/gui/hud/HUDPosition
     266: new           #246                // class net/minecraft/world/item/ItemStack
     269: dup
     270: getstatic     #604                // Field net/minecraft/world/item/Items.f_42448_:Lnet/minecraft/world/item/Item;
     273: invokespecial #545                // Method net/minecraft/world/item/ItemStack."<init>":(Lnet/minecraft/world/level/ItemLike;)V
     276: invokedynamic #609,  0            // InvokeDynamic #14:apply:()Ljava/util/function/Function;
     281: ldc_w         #611                // String CC3024
     284: invokestatic  #616                // Method reliquary/reference/Colors.get:(Ljava/lang/String;)I
     287: invokespecial #619                // Method reliquary/client/gui/hud/ChargeableItemInfoPane."<init>":(Lnet/minecraft/world/item/Item;Lreliquary/client/gui/hud/HUDPosition;Lnet/minecraft/world/item/ItemStack;Ljava/util/function/Function;I)V
     290: getstatic     #526                // Field reliquary/reference/Settings.CLIENT:Lreliquary/reference/Settings$Client;
     293: getfield      #530                // Field reliquary/reference/Settings$Client.hudPositions:Lreliquary/reference/Settings$Client$HudPos;
     296: getfield      #601                // Field reliquary/reference/Settings$Client$HudPos.infernalChalice:Lnet/minecraftforge/common/ForgeConfigSpec$EnumValue;
     299: invokevirtual #536                // Method net/minecraftforge/common/ForgeConfigSpec$EnumValue.get:()Ljava/lang/Object;
     302: checkcast     #504                // class reliquary/client/gui/hud/HUDPosition
     305: invokespecial #563                // Method net/minecraft/util/Tuple."<init>":(Ljava/lang/Object;Ljava/lang/Object;)V
     308: invokeinterface #567,  2          // InterfaceMethod java/util/List.add:(Ljava/lang/Object;)Z
     313: pop
     314: getstatic     #418                // Field hudComponents:Ljava/util/List;
     317: new           #494                // class net/minecraft/util/Tuple
     320: dup
     321: new           #517                // class reliquary/client/gui/hud/ChargeableItemInfoPane
     324: dup
     325: getstatic     #622                // Field reliquary/init/ModItems.ICE_MAGUS_ROD:Lnet/minecraftforge/registries/RegistryObject;
     328: invokevirtual #261                // Method net/minecraftforge/registries/RegistryObject.get:()Lnet/minecraftforge/registries/IForgeRegistryEntry;
     331: checkcast     #522                // class net/minecraft/world/item/Item
     334: getstatic     #526                // Field reliquary/reference/Settings.CLIENT:Lreliquary/reference/Settings$Client;
     337: getfield      #530                // Field reliquary/reference/Settings$Client.hudPositions:Lreliquary/reference/Settings$Client$HudPos;
     340: getfield      #625                // Field reliquary/reference/Settings$Client$HudPos.iceMagusRod:Lnet/minecraftforge/common/ForgeConfigSpec$EnumValue;
     343: invokevirtual #536                // Method net/minecraftforge/common/ForgeConfigSpec$EnumValue.get:()Ljava/lang/Object;
     346: checkcast     #504                // class reliquary/client/gui/hud/HUDPosition
     349: new           #246                // class net/minecraft/world/item/ItemStack
     352: dup
     353: getstatic     #628                // Field net/minecraft/world/item/Items.f_42452_:Lnet/minecraft/world/item/Item;
     356: invokespecial #545                // Method net/minecraft/world/item/ItemStack."<init>":(Lnet/minecraft/world/level/ItemLike;)V
     359: invokedynamic #633,  0            // InvokeDynamic #15:apply:()Ljava/util/function/Function;
     364: invokespecial #560                // Method reliquary/client/gui/hud/ChargeableItemInfoPane."<init>":(Lnet/minecraft/world/item/Item;Lreliquary/client/gui/hud/HUDPosition;Lnet/minecraft/world/item/ItemStack;Ljava/util/function/Function;)V
     367: getstatic     #526                // Field reliquary/reference/Settings.CLIENT:Lreliquary/reference/Settings$Client;
     370: getfield      #530                // Field reliquary/reference/Settings$Client.hudPositions:Lreliquary/reference/Settings$Client$HudPos;
     373: getfield      #625                // Field reliquary/reference/Settings$Client$HudPos.iceMagusRod:Lnet/minecraftforge/common/ForgeConfigSpec$EnumValue;
     376: invokevirtual #536                // Method net/minecraftforge/common/ForgeConfigSpec$EnumValue.get:()Ljava/lang/Object;
     379: checkcast     #504                // class reliquary/client/gui/hud/HUDPosition
     382: invokespecial #563                // Method net/minecraft/util/Tuple."<init>":(Ljava/lang/Object;Ljava/lang/Object;)V
     385: invokeinterface #567,  2          // InterfaceMethod java/util/List.add:(Ljava/lang/Object;)Z
     390: pop
     391: getstatic     #418                // Field hudComponents:Ljava/util/List;
     394: new           #494                // class net/minecraft/util/Tuple
     397: dup
     398: new           #517                // class reliquary/client/gui/hud/ChargeableItemInfoPane
     401: dup
     402: getstatic     #636                // Field reliquary/init/ModItems.GLACIAL_STAFF:Lnet/minecraftforge/registries/RegistryObject;
     405: invokevirtual #261                // Method net/minecraftforge/registries/RegistryObject.get:()Lnet/minecraftforge/registries/IForgeRegistryEntry;
     408: checkcast     #522                // class net/minecraft/world/item/Item
     411: getstatic     #526                // Field reliquary/reference/Settings.CLIENT:Lreliquary/reference/Settings$Client;
     414: getfield      #530                // Field reliquary/reference/Settings$Client.hudPositions:Lreliquary/reference/Settings$Client$HudPos;
     417: getfield      #639                // Field reliquary/reference/Settings$Client$HudPos.glacialStaff:Lnet/minecraftforge/common/ForgeConfigSpec$EnumValue;
     420: invokevirtual #536                // Method net/minecraftforge/common/ForgeConfigSpec$EnumValue.get:()Ljava/lang/Object;
     423: checkcast     #504                // class reliquary/client/gui/hud/HUDPosition
     426: new           #246                // class net/minecraft/world/item/ItemStack
     429: dup
     430: getstatic     #628                // Field net/minecraft/world/item/Items.f_42452_:Lnet/minecraft/world/item/Item;
     433: invokespecial #545                // Method net/minecraft/world/item/ItemStack."<init>":(Lnet/minecraft/world/level/ItemLike;)V
     436: invokedynamic #644,  0            // InvokeDynamic #16:apply:()Ljava/util/function/Function;
     441: invokespecial #560                // Method reliquary/client/gui/hud/ChargeableItemInfoPane."<init>":(Lnet/minecraft/world/item/Item;Lreliquary/client/gui/hud/HUDPosition;Lnet/minecraft/world/item/ItemStack;Ljava/util/function/Function;)V
     444: getstatic     #526                // Field reliquary/reference/Settings.CLIENT:Lreliquary/reference/Settings$Client;
     447: getfield      #530                // Field reliquary/reference/Settings$Client.hudPositions:Lreliquary/reference/Settings$Client$HudPos;
     450: getfield      #639                // Field reliquary/reference/Settings$Client$HudPos.glacialStaff:Lnet/minecraftforge/common/ForgeConfigSpec$EnumValue;
     453: invokevirtual #536                // Method net/minecraftforge/common/ForgeConfigSpec$EnumValue.get:()Ljava/lang/Object;
     456: checkcast     #504                // class reliquary/client/gui/hud/HUDPosition
     459: invokespecial #563                // Method net/minecraft/util/Tuple."<init>":(Ljava/lang/Object;Ljava/lang/Object;)V
     462: invokeinterface #567,  2          // InterfaceMethod java/util/List.add:(Ljava/lang/Object;)Z
     467: pop
     468: getstatic     #418                // Field hudComponents:Ljava/util/List;
     471: new           #494                // class net/minecraft/util/Tuple
     474: dup
     475: new           #517                // class reliquary/client/gui/hud/ChargeableItemInfoPane
     478: dup
     479: getstatic     #647                // Field reliquary/init/ModItems.ENDER_STAFF:Lnet/minecraftforge/registries/RegistryObject;
     482: invokevirtual #261                // Method net/minecraftforge/registries/RegistryObject.get:()Lnet/minecraftforge/registries/IForgeRegistryEntry;
     485: checkcast     #522                // class net/minecraft/world/item/Item
     488: getstatic     #526                // Field reliquary/reference/Settings.CLIENT:Lreliquary/reference/Settings$Client;
     491: getfield      #530                // Field reliquary/reference/Settings$Client.hudPositions:Lreliquary/reference/Settings$Client$HudPos;
     494: getfield      #650                // Field reliquary/reference/Settings$Client$HudPos.enderStaff:Lnet/minecraftforge/common/ForgeConfigSpec$EnumValue;
     497: invokevirtual #536                // Method net/minecraftforge/common/ForgeConfigSpec$EnumValue.get:()Ljava/lang/Object;
     500: checkcast     #504                // class reliquary/client/gui/hud/HUDPosition
     503: invokedynamic #657,  0            // InvokeDynamic #17:apply:()Ljava/util/function/Function;
     508: getstatic     #661                // Field reliquary/items/EnderStaffItem$Mode.CAST:Lreliquary/items/EnderStaffItem$Mode;
     511: invokevirtual #665                // Method reliquary/items/EnderStaffItem$Mode.m_7912_:()Ljava/lang/String;
     514: new           #667                // class reliquary/client/gui/hud/ChargePane
     517: dup
     518: getstatic     #647                // Field reliquary/init/ModItems.ENDER_STAFF:Lnet/minecraftforge/registries/RegistryObject;
     521: invokevirtual #261                // Method net/minecraftforge/registries/RegistryObject.get:()Lnet/minecraftforge/registries/IForgeRegistryEntry;
     524: checkcast     #522                // class net/minecraft/world/item/Item
     527: new           #246                // class net/minecraft/world/item/ItemStack
     530: dup
     531: getstatic     #670                // Field net/minecraft/world/item/Items.f_42584_:Lnet/minecraft/world/item/Item;
     534: invokespecial #545                // Method net/minecraft/world/item/ItemStack."<init>":(Lnet/minecraft/world/level/ItemLike;)V
     537: invokedynamic #675,  0            // InvokeDynamic #18:apply:()Ljava/util/function/Function;
     542: invokespecial #678                // Method reliquary/client/gui/hud/ChargePane."<init>":(Lnet/minecraft/world/item/Item;Lnet/minecraft/world/item/ItemStack;Ljava/util/function/Function;)V
     545: getstatic     #681                // Field reliquary/items/EnderStaffItem$Mode.NODE_WARP:Lreliquary/items/EnderStaffItem$Mode;
     548: invokevirtual #665                // Method reliquary/items/EnderStaffItem$Mode.m_7912_:()Ljava/lang/String;
     551: new           #667                // class reliquary/client/gui/hud/ChargePane
     554: dup
     555: getstatic     #647                // Field reliquary/init/ModItems.ENDER_STAFF:Lnet/minecraftforge/registries/RegistryObject;
     558: invokevirtual #261                // Method net/minecraftforge/registries/RegistryObject.get:()Lnet/minecraftforge/registries/IForgeRegistryEntry;
     561: checkcast     #522                // class net/minecraft/world/item/Item
     564: new           #246                // class net/minecraft/world/item/ItemStack
     567: dup
     568: getstatic     #686                // Field reliquary/init/ModBlocks.WRAITH_NODE:Lnet/minecraftforge/registries/RegistryObject;
     571: invokevirtual #261                // Method net/minecraftforge/registries/RegistryObject.get:()Lnet/minecraftforge/registries/IForgeRegistryEntry;
     574: checkcast     #688                // class net/minecraft/world/level/ItemLike
     577: invokespecial #545                // Method net/minecraft/world/item/ItemStack."<init>":(Lnet/minecraft/world/level/ItemLike;)V
     580: invokedynamic #693,  0            // InvokeDynamic #19:apply:()Ljava/util/function/Function;
     585: invokespecial #678                // Method reliquary/client/gui/hud/ChargePane."<init>":(Lnet/minecraft/world/item/Item;Lnet/minecraft/world/item/ItemStack;Ljava/util/function/Function;)V
     588: getstatic     #696                // Field reliquary/items/EnderStaffItem$Mode.LONG_CAST:Lreliquary/items/EnderStaffItem$Mode;
     591: invokevirtual #665                // Method reliquary/items/EnderStaffItem$Mode.m_7912_:()Ljava/lang/String;
     594: new           #667                // class reliquary/client/gui/hud/ChargePane
     597: dup
     598: getstatic     #647                // Field reliquary/init/ModItems.ENDER_STAFF:Lnet/minecraftforge/registries/RegistryObject;
     601: invokevirtual #261                // Method net/minecraftforge/registries/RegistryObject.get:()Lnet/minecraftforge/registries/IForgeRegistryEntry;
     604: checkcast     #522                // class net/minecraft/world/item/Item
     607: new           #246                // class net/minecraft/world/item/ItemStack
     610: dup
     611: getstatic     #699                // Field net/minecraft/world/item/Items.f_42545_:Lnet/minecraft/world/item/Item;
     614: invokespecial #545                // Method net/minecraft/world/item/ItemStack."<init>":(Lnet/minecraft/world/level/ItemLike;)V
     617: invokedynamic #704,  0            // InvokeDynamic #20:apply:()Ljava/util/function/Function;
     622: invokespecial #678                // Method reliquary/client/gui/hud/ChargePane."<init>":(Lnet/minecraft/world/item/Item;Lnet/minecraft/world/item/ItemStack;Ljava/util/function/Function;)V
     625: invokestatic  #710                // InterfaceMethod java/util/Map.of:(Ljava/lang/Object;Ljava/lang/Object;Ljava/lang/Object;Ljava/lang/Object;Ljava/lang/Object;Ljava/lang/Object;)Ljava/util/Map;
     628: invokespecial #713                // Method reliquary/client/gui/hud/ChargeableItemInfoPane."<init>":(Lnet/minecraft/world/item/Item;Lreliquary/client/gui/hud/HUDPosition;Ljava/util/function/Function;Ljava/util/Map;)V
     631: getstatic     #526                // Field reliquary/reference/Settings.CLIENT:Lreliquary/reference/Settings$Client;
     634: getfield      #530                // Field reliquary/reference/Settings$Client.hudPositions:Lreliquary/reference/Settings$Client$HudPos;
     637: getfield      #650                // Field reliquary/reference/Settings$Client$HudPos.enderStaff:Lnet/minecraftforge/common/ForgeConfigSpec$EnumValue;
     640: invokevirtual #536                // Method net/minecraftforge/common/ForgeConfigSpec$EnumValue.get:()Ljava/lang/Object;
     643: checkcast     #504                // class reliquary/client/gui/hud/HUDPosition
     646: invokespecial #563                // Method net/minecraft/util/Tuple."<init>":(Ljava/lang/Object;Ljava/lang/Object;)V
     649: invokeinterface #567,  2          // InterfaceMethod java/util/List.add:(Ljava/lang/Object;)Z
     654: pop
     655: getstatic     #418                // Field hudComponents:Ljava/util/List;
     658: new           #494                // class net/minecraft/util/Tuple
     661: dup
     662: new           #517                // class reliquary/client/gui/hud/ChargeableItemInfoPane
     665: dup
     666: getstatic     #716                // Field reliquary/init/ModItems.PYROMANCER_STAFF:Lnet/minecraftforge/registries/RegistryObject;
     669: invokevirtual #261                // Method net/minecraftforge/registries/RegistryObject.get:()Lnet/minecraftforge/registries/IForgeRegistryEntry;
     672: checkcast     #522                // class net/minecraft/world/item/Item
     675: getstatic     #526                // Field reliquary/reference/Settings.CLIENT:Lreliquary/reference/Settings$Client;
     678: getfield      #530                // Field reliquary/reference/Settings$Client.hudPositions:Lreliquary/reference/Settings$Client$HudPos;
     681: getfield      #719                // Field reliquary/reference/Settings$Client$HudPos.pyromancerStaff:Lnet/minecraftforge/common/ForgeConfigSpec$EnumValue;
     684: invokevirtual #536                // Method net/minecraftforge/common/ForgeConfigSpec$EnumValue.get:()Ljava/lang/Object;
     687: checkcast     #504                // class reliquary/client/gui/hud/HUDPosition
     690: invokedynamic #724,  0            // InvokeDynamic #21:apply:()Ljava/util/function/Function;
     695: getstatic     #728                // Field reliquary/items/PyromancerStaffItem$Mode.BLAZE:Lreliquary/items/PyromancerStaffItem$Mode;
     698: invokevirtual #729                // Method reliquary/items/PyromancerStaffItem$Mode.m_7912_:()Ljava/lang/String;
     701: new           #667                // class reliquary/client/gui/hud/ChargePane
     704: dup
     705: getstatic     #716                // Field reliquary/init/ModItems.PYROMANCER_STAFF:Lnet/minecraftforge/registries/RegistryObject;
     708: invokevirtual #261                // Method net/minecraftforge/registries/RegistryObject.get:()Lnet/minecraftforge/registries/IForgeRegistryEntry;
     711: checkcast     #522                // class net/minecraft/world/item/Item
     714: new           #246                // class net/minecraft/world/item/ItemStack
     717: dup
     718: getstatic     #732                // Field net/minecraft/world/item/Items.f_42593_:Lnet/minecraft/world/item/Item;
     721: invokespecial #545                // Method net/minecraft/world/item/ItemStack."<init>":(Lnet/minecraft/world/level/ItemLike;)V
     724: invokedynamic #737,  0            // InvokeDynamic #22:apply:()Ljava/util/function/Function;
     729: invokespecial #678                // Method reliquary/client/gui/hud/ChargePane."<init>":(Lnet/minecraft/world/item/Item;Lnet/minecraft/world/item/ItemStack;Ljava/util/function/Function;)V
     732: getstatic     #740                // Field reliquary/items/PyromancerStaffItem$Mode.FIRE_CHARGE:Lreliquary/items/PyromancerStaffItem$Mode;
     735: invokevirtual #729                // Method reliquary/items/PyromancerStaffItem$Mode.m_7912_:()Ljava/lang/String;
     738: new           #667                // class reliquary/client/gui/hud/ChargePane
     741: dup
     742: getstatic     #716                // Field reliquary/init/ModItems.PYROMANCER_STAFF:Lnet/minecraftforge/registries/RegistryObject;
     745: invokevirtual #261                // Method net/minecraftforge/registries/RegistryObject.get:()Lnet/minecraftforge/registries/IForgeRegistryEntry;
     748: checkcast     #522                // class net/minecraft/world/item/Item
     751: new           #246                // class net/minecraft/world/item/ItemStack
     754: dup
     755: getstatic     #743                // Field net/minecraft/world/item/Items.f_42613_:Lnet/minecraft/world/item/Item;
     758: invokespecial #545                // Method net/minecraft/world/item/ItemStack."<init>":(Lnet/minecraft/world/level/ItemLike;)V
     761: invokedynamic #748,  0            // InvokeDynamic #23:apply:()Ljava/util/function/Function;
     766: invokespecial #678                // Method reliquary/client/gui/hud/ChargePane."<init>":(Lnet/minecraft/world/item/Item;Lnet/minecraft/world/item/ItemStack;Ljava/util/function/Function;)V
     769: getstatic     #751                // Field reliquary/items/PyromancerStaffItem$Mode.ERUPTION:Lreliquary/items/PyromancerStaffItem$Mode;
     772: invokevirtual #729                // Method reliquary/items/PyromancerStaffItem$Mode.m_7912_:()Ljava/lang/String;
     775: getstatic     #754                // Field reliquary/client/gui/components/Box$Alignment.RIGHT:Lreliquary/client/gui/components/Box$Alignment;
     778: iconst_2
     779: anewarray     #499                // class reliquary/client/gui/components/Component
     782: dup
     783: iconst_0
     784: new           #756                // class reliquary/client/gui/components/TextPane
     787: dup
     788: ldc_w         #758                // String ERUPT
     791: invokespecial #761                // Method reliquary/client/gui/components/TextPane."<init>":(Ljava/lang/String;)V
     794: aastore
     795: dup
     796: iconst_1
     797: new           #667                // class reliquary/client/gui/hud/ChargePane
     800: dup
     801: getstatic     #716                // Field reliquary/init/ModItems.PYROMANCER_STAFF:Lnet/minecraftforge/registries/RegistryObject;
     804: invokevirtual #261                // Method net/minecraftforge/registries/RegistryObject.get:()Lnet/minecraftforge/registries/IForgeRegistryEntry;
     807: checkcast     #522                // class net/minecraft/world/item/Item
     810: new           #246                // class net/minecraft/world/item/ItemStack
     813: dup
     814: getstatic     #732                // Field net/minecraft/world/item/Items.f_42593_:Lnet/minecraft/world/item/Item;
     817: invokespecial #545                // Method net/minecraft/world/item/ItemStack."<init>":(Lnet/minecraft/world/level/ItemLike;)V
     820: invokedynamic #766,  0            // InvokeDynamic #24:apply:()Ljava/util/function/Function;
     825: invokespecial #678                // Method reliquary/client/gui/hud/ChargePane."<init>":(Lnet/minecraft/world/item/Item;Lnet/minecraft/world/item/ItemStack;Ljava/util/function/Function;)V
     828: aastore
     829: invokestatic  #770                // Method reliquary/client/gui/components/Box.createVertical:(Lreliquary/client/gui/components/Box$Alignment;[Lreliquary/client/gui/components/Component;)Lreliquary/client/gui/components/Box;
     832: getstatic     #773                // Field reliquary/items/PyromancerStaffItem$Mode.FLINT_AND_STEEL:Lreliquary/items/PyromancerStaffItem$Mode;
     835: invokevirtual #729                // Method reliquary/items/PyromancerStaffItem$Mode.m_7912_:()Ljava/lang/String;
     838: new           #775                // class reliquary/client/gui/components/ItemStackPane
     841: dup
     842: getstatic     #778                // Field net/minecraft/world/item/Items.f_42409_:Lnet/minecraft/world/item/Item;
     845: invokespecial #781                // Method reliquary/client/gui/components/ItemStackPane."<init>":(Lnet/minecraft/world/item/Item;)V
     848: invokestatic  #784                // InterfaceMethod java/util/Map.of:(Ljava/lang/Object;Ljava/lang/Object;Ljava/lang/Object;Ljava/lang/Object;Ljava/lang/Object;Ljava/lang/Object;Ljava/lang/Object;Ljava/lang/Object;)Ljava/util/Map;
     851: invokespecial #713                // Method reliquary/client/gui/hud/ChargeableItemInfoPane."<init>":(Lnet/minecraft/world/item/Item;Lreliquary/client/gui/hud/HUDPosition;Ljava/util/function/Function;Ljava/util/Map;)V
     854: getstatic     #526                // Field reliquary/reference/Settings.CLIENT:Lreliquary/reference/Settings$Client;
     857: getfield      #530                // Field reliquary/reference/Settings$Client.hudPositions:Lreliquary/reference/Settings$Client$HudPos;
     860: getfield      #719                // Field reliquary/reference/Settings$Client$HudPos.pyromancerStaff:Lnet/minecraftforge/common/ForgeConfigSpec$EnumValue;
     863: invokevirtual #536                // Method net/minecraftforge/common/ForgeConfigSpec$EnumValue.get:()Ljava/lang/Object;
     866: checkcast     #504                // class reliquary/client/gui/hud/HUDPosition
     869: invokespecial #563                // Method net/minecraft/util/Tuple."<init>":(Ljava/lang/Object;Ljava/lang/Object;)V
     872: invokeinterface #567,  2          // InterfaceMethod java/util/List.add:(Ljava/lang/Object;)Z
     877: pop
     878: new           #667                // class reliquary/client/gui/hud/ChargePane
     881: dup
     882: getstatic     #787                // Field reliquary/init/ModItems.RENDING_GALE:Lnet/minecraftforge/registries/RegistryObject;
     885: invokevirtual #261                // Method net/minecraftforge/registries/RegistryObject.get:()Lnet/minecraftforge/registries/IForgeRegistryEntry;
     888: checkcast     #522                // class net/minecraft/world/item/Item
     891: new           #246                // class net/minecraft/world/item/ItemStack
     894: dup
     895: getstatic     #790                // Field net/minecraft/world/item/Items.f_42402_:Lnet/minecraft/world/item/Item;
     898: invokespecial #545                // Method net/minecraft/world/item/ItemStack."<init>":(Lnet/minecraft/world/level/ItemLike;)V
     901: invokedynamic #795,  0            // InvokeDynamic #25:apply:()Ljava/util/function/Function;
     906: invokespecial #678                // Method reliquary/client/gui/hud/ChargePane."<init>":(Lnet/minecraft/world/item/Item;Lnet/minecraft/world/item/ItemStack;Ljava/util/function/Function;)V
     909: astore_0
     910: getstatic     #418                // Field hudComponents:Ljava/util/List;
     913: new           #494                // class net/minecraft/util/Tuple
     916: dup
     917: new           #517                // class reliquary/client/gui/hud/ChargeableItemInfoPane
     920: dup
     921: getstatic     #787                // Field reliquary/init/ModItems.RENDING_GALE:Lnet/minecraftforge/registries/RegistryObject;
     924: invokevirtual #261                // Method net/minecraftforge/registries/RegistryObject.get:()Lnet/minecraftforge/registries/IForgeRegistryEntry;
     927: checkcast     #522                // class net/minecraft/world/item/Item
     930: getstatic     #526                // Field reliquary/reference/Settings.CLIENT:Lreliquary/reference/Settings$Client;
     933: getfield      #530                // Field reliquary/reference/Settings$Client.hudPositions:Lreliquary/reference/Settings$Client$HudPos;
     936: getfield      #798                // Field reliquary/reference/Settings$Client$HudPos.rendingGale:Lnet/minecraftforge/common/ForgeConfigSpec$EnumValue;
     939: invokevirtual #536                // Method net/minecraftforge/common/ForgeConfigSpec$EnumValue.get:()Ljava/lang/Object;
     942: checkcast     #504                // class reliquary/client/gui/hud/HUDPosition
     945: invokedynamic #803,  0            // InvokeDynamic #26:apply:()Ljava/util/function/Function;
     950: getstatic     #807                // Field reliquary/items/RendingGaleItem$Mode.PUSH:Lreliquary/items/RendingGaleItem$Mode;
     953: invokevirtual #808                // Method reliquary/items/RendingGaleItem$Mode.m_7912_:()Ljava/lang/String;
     956: getstatic     #754                // Field reliquary/client/gui/components/Box$Alignment.RIGHT:Lreliquary/client/gui/components/Box$Alignment;
     959: iconst_2
     960: anewarray     #499                // class reliquary/client/gui/components/Component
     963: dup
     964: iconst_0
     965: new           #756                // class reliquary/client/gui/components/TextPane
     968: dup
     969: ldc_w         #809                // String PUSH
     972: invokespecial #761                // Method reliquary/client/gui/components/TextPane."<init>":(Ljava/lang/String;)V
     975: aastore
     976: dup
     977: iconst_1
     978: aload_0
     979: aastore
     980: invokestatic  #770                // Method reliquary/client/gui/components/Box.createVertical:(Lreliquary/client/gui/components/Box$Alignment;[Lreliquary/client/gui/components/Component;)Lreliquary/client/gui/components/Box;
     983: getstatic     #812                // Field reliquary/items/RendingGaleItem$Mode.PULL:Lreliquary/items/RendingGaleItem$Mode;
     986: invokevirtual #808                // Method reliquary/items/RendingGaleItem$Mode.m_7912_:()Ljava/lang/String;
     989: getstatic     #754                // Field reliquary/client/gui/components/Box$Alignment.RIGHT:Lreliquary/client/gui/components/Box$Alignment;
     992: iconst_2
     993: anewarray     #499                // class reliquary/client/gui/components/Component
     996: dup
     997: iconst_0
     998: new           #756                // class reliquary/client/gui/components/TextPane
    1001: dup
    1002: ldc_w         #813                // String PULL
    1005: invokespecial #761                // Method reliquary/client/gui/components/TextPane."<init>":(Ljava/lang/String;)V
    1008: aastore
    1009: dup
    1010: iconst_1
    1011: aload_0
    1012: aastore
    1013: invokestatic  #770                // Method reliquary/client/gui/components/Box.createVertical:(Lreliquary/client/gui/components/Box$Alignment;[Lreliquary/client/gui/components/Component;)Lreliquary/client/gui/components/Box;
    1016: getstatic     #816                // Field reliquary/items/RendingGaleItem$Mode.BOLT:Lreliquary/items/RendingGaleItem$Mode;
    1019: invokevirtual #808                // Method reliquary/items/RendingGaleItem$Mode.m_7912_:()Ljava/lang/String;
    1022: getstatic     #754                // Field reliquary/client/gui/components/Box$Alignment.RIGHT:Lreliquary/client/gui/components/Box$Alignment;
    1025: iconst_2
    1026: anewarray     #499                // class reliquary/client/gui/components/Component
    1029: dup
    1030: iconst_0
    1031: new           #756                // class reliquary/client/gui/components/TextPane
    1034: dup
    1035: ldc_w         #817                // String BOLT
    1038: invokespecial #761                // Method reliquary/client/gui/components/TextPane."<init>":(Ljava/lang/String;)V
    1041: aastore
    1042: dup
    1043: iconst_1
    1044: aload_0
    1045: aastore
    1046: invokestatic  #770                // Method reliquary/client/gui/components/Box.createVertical:(Lreliquary/client/gui/components/Box$Alignment;[Lreliquary/client/gui/components/Component;)Lreliquary/client/gui/components/Box;
    1049: getstatic     #820                // Field reliquary/items/RendingGaleItem$Mode.FLIGHT:Lreliquary/items/RendingGaleItem$Mode;
    1052: invokevirtual #808                // Method reliquary/items/RendingGaleItem$Mode.m_7912_:()Ljava/lang/String;
    1055: getstatic     #754                // Field reliquary/client/gui/components/Box$Alignment.RIGHT:Lreliquary/client/gui/components/Box$Alignment;
    1058: iconst_2
    1059: anewarray     #499                // class reliquary/client/gui/components/Component
    1062: dup
    1063: iconst_0
    1064: new           #756                // class reliquary/client/gui/components/TextPane
    1067: dup
    1068: ldc_w         #821                // String FLIGHT
    1071: invokespecial #761                // Method reliquary/client/gui/components/TextPane."<init>":(Ljava/lang/String;)V
    1074: aastore
    1075: dup
    1076: iconst_1
    1077: aload_0
    1078: aastore
    1079: invokestatic  #770                // Method reliquary/client/gui/components/Box.createVertical:(Lreliquary/client/gui/components/Box$Alignment;[Lreliquary/client/gui/components/Component;)Lreliquary/client/gui/components/Box;
    1082: invokestatic  #784                // InterfaceMethod java/util/Map.of:(Ljava/lang/Object;Ljava/lang/Object;Ljava/lang/Object;Ljava/lang/Object;Ljava/lang/Object;Ljava/lang/Object;Ljava/lang/Object;Ljava/lang/Object;)Ljava/util/Map;
    1085: invokespecial #713                // Method reliquary/client/gui/hud/ChargeableItemInfoPane."<init>":(Lnet/minecraft/world/item/Item;Lreliquary/client/gui/hud/HUDPosition;Ljava/util/function/Function;Ljava/util/Map;)V
    1088: getstatic     #526                // Field reliquary/reference/Settings.CLIENT:Lreliquary/reference/Settings$Client;
    1091: getfield      #530                // Field reliquary/reference/Settings$Client.hudPositions:Lreliquary/reference/Settings$Client$HudPos;
    1094: getfield      #798                // Field reliquary/reference/Settings$Client$HudPos.rendingGale:Lnet/minecraftforge/common/ForgeConfigSpec$EnumValue;
    1097: invokevirtual #536                // Method net/minecraftforge/common/ForgeConfigSpec$EnumValue.get:()Ljava/lang/Object;
    1100: checkcast     #504                // class reliquary/client/gui/hud/HUDPosition
    1103: invokespecial #563                // Method net/minecraft/util/Tuple."<init>":(Ljava/lang/Object;Ljava/lang/Object;)V
    1106: invokeinterface #567,  2          // InterfaceMethod java/util/List.add:(Ljava/lang/Object;)Z
    1111: pop
    1112: new           #823                // class reliquary/client/gui/hud/DynamicChargePane
    1115: dup
    1116: getstatic     #826                // Field reliquary/init/ModItems.VOID_TEAR:Lnet/minecraftforge/registries/RegistryObject;
    1119: invokevirtual #261                // Method net/minecraftforge/registries/RegistryObject.get:()Lnet/minecraftforge/registries/IForgeRegistryEntry;
    1122: checkcast     #522                // class net/minecraft/world/item/Item
    1125: invokedynamic #835,  0            // InvokeDynamic #27:apply:()Ljava/util/function/UnaryOperator;
    1130: invokedynamic #840,  0            // InvokeDynamic #28:apply:()Ljava/util/function/Function;
    1135: invokespecial #843                // Method reliquary/client/gui/hud/DynamicChargePane."<init>":(Lnet/minecraft/world/item/Item;Ljava/util/function/UnaryOperator;Ljava/util/function/Function;)V
    1138: astore_1
    1139: getstatic     #418                // Field hudComponents:Ljava/util/List;
    1142: new           #494                // class net/minecraft/util/Tuple
    1145: dup
    1146: new           #7                  // class reliquary/handler/ClientEventHandler$1
    1149: dup
    1150: getstatic     #826                // Field reliquary/init/ModItems.VOID_TEAR:Lnet/minecraftforge/registries/RegistryObject;
    1153: invokevirtual #261                // Method net/minecraftforge/registries/RegistryObject.get:()Lnet/minecraftforge/registries/IForgeRegistryEntry;
    1156: checkcast     #522                // class net/minecraft/world/item/Item
    1159: getstatic     #526                // Field reliquary/reference/Settings.CLIENT:Lreliquary/reference/Settings$Client;
    1162: getfield      #530                // Field reliquary/reference/Settings$Client.hudPositions:Lreliquary/reference/Settings$Client$HudPos;
    1165: getfield      #846                // Field reliquary/reference/Settings$Client$HudPos.voidTear:Lnet/minecraftforge/common/ForgeConfigSpec$EnumValue;
    1168: invokevirtual #536                // Method net/minecraftforge/common/ForgeConfigSpec$EnumValue.get:()Ljava/lang/Object;
    1171: checkcast     #504                // class reliquary/client/gui/hud/HUDPosition
    1174: invokedynamic #851,  0            // InvokeDynamic #29:apply:()Ljava/util/function/Function;
    1179: getstatic     #855                // Field reliquary/items/VoidTearItem$Mode.FULL_INVENTORY:Lreliquary/items/VoidTearItem$Mode;
    1182: invokevirtual #856                // Method reliquary/items/VoidTearItem$Mode.m_7912_:()Ljava/lang/String;
    1185: getstatic     #754                // Field reliquary/client/gui/components/Box$Alignment.RIGHT:Lreliquary/client/gui/components/Box$Alignment;
    1188: iconst_2
    1189: anewarray     #499                // class reliquary/client/gui/components/Component
    1192: dup
    1193: iconst_0
    1194: new           #756                // class reliquary/client/gui/components/TextPane
    1197: dup
    1198: getstatic     #855                // Field reliquary/items/VoidTearItem$Mode.FULL_INVENTORY:Lreliquary/items/VoidTearItem$Mode;
    1201: invokevirtual #856                // Method reliquary/items/VoidTearItem$Mode.m_7912_:()Ljava/lang/String;
    1204: invokevirtual #861                // Method java/lang/String.toLowerCase:()Ljava/lang/String;
    1207: invokedynamic #873,  0            // InvokeDynamic #30:makeConcatWithConstants:(Ljava/lang/String;)Ljava/lang/String;
    1212: iconst_0
    1213: anewarray     #4                  // class java/lang/Object
    1216: invokestatic  #879                // Method reliquary/util/LanguageHelper.getLocalization:(Ljava/lang/String;[Ljava/lang/Object;)Ljava/lang/String;
    1219: invokespecial #761                // Method reliquary/client/gui/components/TextPane."<init>":(Ljava/lang/String;)V
    1222: aastore
    1223: dup
    1224: iconst_1
    1225: aload_1
    1226: aastore
    1227: invokestatic  #770                // Method reliquary/client/gui/components/Box.createVertical:(Lreliquary/client/gui/components/Box$Alignment;[Lreliquary/client/gui/components/Component;)Lreliquary/client/gui/components/Box;
    1230: getstatic     #882                // Field reliquary/items/VoidTearItem$Mode.NO_REFILL:Lreliquary/items/VoidTearItem$Mode;
    1233: invokevirtual #856                // Method reliquary/items/VoidTearItem$Mode.m_7912_:()Ljava/lang/String;
    1236: getstatic     #754                // Field reliquary/client/gui/components/Box$Alignment.RIGHT:Lreliquary/client/gui/components/Box$Alignment;
    1239: iconst_2
    1240: anewarray     #499                // class reliquary/client/gui/components/Component
    1243: dup
    1244: iconst_0
    1245: new           #756                // class reliquary/client/gui/components/TextPane
    1248: dup
    1249: getstatic     #882                // Field reliquary/items/VoidTearItem$Mode.NO_REFILL:Lreliquary/items/VoidTearItem$Mode;
    1252: invokevirtual #856                // Method reliquary/items/VoidTearItem$Mode.m_7912_:()Ljava/lang/String;
    1255: invokevirtual #861                // Method java/lang/String.toLowerCase:()Ljava/lang/String;
    1258: invokedynamic #873,  0            // InvokeDynamic #30:makeConcatWithConstants:(Ljava/lang/String;)Ljava/lang/String;
    1263: iconst_0
    1264: anewarray     #4                  // class java/lang/Object
    1267: invokestatic  #879                // Method reliquary/util/LanguageHelper.getLocalization:(Ljava/lang/String;[Ljava/lang/Object;)Ljava/lang/String;
    1270: invokespecial #761                // Method reliquary/client/gui/components/TextPane."<init>":(Ljava/lang/String;)V
    1273: aastore
    1274: dup
    1275: iconst_1
    1276: aload_1
    1277: aastore
    1278: invokestatic  #770                // Method reliquary/client/gui/components/Box.createVertical:(Lreliquary/client/gui/components/Box$Alignment;[Lreliquary/client/gui/components/Component;)Lreliquary/client/gui/components/Box;
    1281: getstatic     #885                // Field reliquary/items/VoidTearItem$Mode.ONE_STACK:Lreliquary/items/VoidTearItem$Mode;
    1284: invokevirtual #856                // Method reliquary/items/VoidTearItem$Mode.m_7912_:()Ljava/lang/String;
    1287: getstatic     #754                // Field reliquary/client/gui/components/Box$Alignment.RIGHT:Lreliquary/client/gui/components/Box$Alignment;
    1290: iconst_2
    1291: anewarray     #499                // class reliquary/client/gui/components/Component
    1294: dup
    1295: iconst_0
    1296: new           #756                // class reliquary/client/gui/components/TextPane
    1299: dup
    1300: getstatic     #885                // Field reliquary/items/VoidTearItem$Mode.ONE_STACK:Lreliquary/items/VoidTearItem$Mode;
    1303: invokevirtual #856                // Method reliquary/items/VoidTearItem$Mode.m_7912_:()Ljava/lang/String;
    1306: invokevirtual #861                // Method java/lang/String.toLowerCase:()Ljava/lang/String;
    1309: invokedynamic #873,  0            // InvokeDynamic #30:makeConcatWithConstants:(Ljava/lang/String;)Ljava/lang/String;
    1314: iconst_0
    1315: anewarray     #4                  // class java/lang/Object
    1318: invokestatic  #879                // Method reliquary/util/LanguageHelper.getLocalization:(Ljava/lang/String;[Ljava/lang/Object;)Ljava/lang/String;
    1321: invokespecial #761                // Method reliquary/client/gui/components/TextPane."<init>":(Ljava/lang/String;)V
    1324: aastore
    1325: dup
    1326: iconst_1
    1327: aload_1
    1328: aastore
    1329: invokestatic  #770                // Method reliquary/client/gui/components/Box.createVertical:(Lreliquary/client/gui/components/Box$Alignment;[Lreliquary/client/gui/components/Component;)Lreliquary/client/gui/components/Box;
    1332: invokestatic  #710                // InterfaceMethod java/util/Map.of:(Ljava/lang/Object;Ljava/lang/Object;Ljava/lang/Object;Ljava/lang/Object;Ljava/lang/Object;Ljava/lang/Object;)Ljava/util/Map;
    1335: invokespecial #886                // Method reliquary/handler/ClientEventHandler$1."<init>":(Lnet/minecraft/world/item/Item;Lreliquary/client/gui/hud/HUDPosition;Ljava/util/function/Function;Ljava/util/Map;)V
    1338: getstatic     #526                // Field reliquary/reference/Settings.CLIENT:Lreliquary/reference/Settings$Client;
    1341: getfield      #530                // Field reliquary/reference/Settings$Client.hudPositions:Lreliquary/reference/Settings$Client$HudPos;
    1344: getfield      #846                // Field reliquary/reference/Settings$Client$HudPos.voidTear:Lnet/minecraftforge/common/ForgeConfigSpec$EnumValue;
    1347: invokevirtual #536                // Method net/minecraftforge/common/ForgeConfigSpec$EnumValue.get:()Ljava/lang/Object;
    1350: checkcast     #504                // class reliquary/client/gui/hud/HUDPosition
    1353: invokespecial #563                // Method net/minecraft/util/Tuple."<init>":(Ljava/lang/Object;Ljava/lang/Object;)V
    1356: invokeinterface #567,  2          // InterfaceMethod java/util/List.add:(Ljava/lang/Object;)Z
    1361: pop
    1362: getstatic     #418                // Field hudComponents:Ljava/util/List;
    1365: new           #494                // class net/minecraft/util/Tuple
    1368: dup
    1369: new           #517                // class reliquary/client/gui/hud/ChargeableItemInfoPane
    1372: dup
    1373: getstatic     #889                // Field reliquary/init/ModItems.HARVEST_ROD:Lnet/minecraftforge/registries/RegistryObject;
    1376: invokevirtual #261                // Method net/minecraftforge/registries/RegistryObject.get:()Lnet/minecraftforge/registries/IForgeRegistryEntry;
    1379: checkcast     #522                // class net/minecraft/world/item/Item
    1382: getstatic     #526                // Field reliquary/reference/Settings.CLIENT:Lreliquary/reference/Settings$Client;
    1385: getfield      #530                // Field reliquary/reference/Settings$Client.hudPositions:Lreliquary/reference/Settings$Client$HudPos;
    1388: getfield      #892                // Field reliquary/reference/Settings$Client$HudPos.harvestRod:Lnet/minecraftforge/common/ForgeConfigSpec$EnumValue;
    1391: invokevirtual #536                // Method net/minecraftforge/common/ForgeConfigSpec$EnumValue.get:()Ljava/lang/Object;
    1394: checkcast     #504                // class reliquary/client/gui/hud/HUDPosition
    1397: invokedynamic #897,  0            // InvokeDynamic #31:apply:()Ljava/util/function/Function;
    1402: getstatic     #901                // Field reliquary/items/HarvestRodItem$Mode.BONE_MEAL:Lreliquary/items/HarvestRodItem$Mode;
    1405: invokevirtual #902                // Method reliquary/items/HarvestRodItem$Mode.m_7912_:()Ljava/lang/String;
    1408: new           #667                // class reliquary/client/gui/hud/ChargePane
    1411: dup
    1412: getstatic     #889                // Field reliquary/init/ModItems.HARVEST_ROD:Lnet/minecraftforge/registries/RegistryObject;
    1415: invokevirtual #261                // Method net/minecraftforge/registries/RegistryObject.get:()Lnet/minecraftforge/registries/IForgeRegistryEntry;
    1418: checkcast     #522                // class net/minecraft/world/item/Item
    1421: new           #246                // class net/minecraft/world/item/ItemStack
    1424: dup
    1425: getstatic     #905                // Field net/minecraft/world/item/Items.f_42499_:Lnet/minecraft/world/item/Item;
    1428: invokespecial #545                // Method net/minecraft/world/item/ItemStack."<init>":(Lnet/minecraft/world/level/ItemLike;)V
    1431: invokedynamic #910,  0            // InvokeDynamic #32:apply:()Ljava/util/function/Function;
    1436: invokespecial #678                // Method reliquary/client/gui/hud/ChargePane."<init>":(Lnet/minecraft/world/item/Item;Lnet/minecraft/world/item/ItemStack;Ljava/util/function/Function;)V
    1439: getstatic     #913                // Field reliquary/items/HarvestRodItem$Mode.HOE:Lreliquary/items/HarvestRodItem$Mode;
    1442: invokevirtual #902                // Method reliquary/items/HarvestRodItem$Mode.m_7912_:()Ljava/lang/String;
    1445: new           #775                // class reliquary/client/gui/components/ItemStackPane
    1448: dup
    1449: getstatic     #916                // Field net/minecraft/world/item/Items.f_42424_:Lnet/minecraft/world/item/Item;
    1452: invokespecial #781                // Method reliquary/client/gui/components/ItemStackPane."<init>":(Lnet/minecraft/world/item/Item;)V
    1455: ldc_w         #918                // String dynamic
    1458: new           #823                // class reliquary/client/gui/hud/DynamicChargePane
    1461: dup
    1462: getstatic     #889                // Field reliquary/init/ModItems.HARVEST_ROD:Lnet/minecraftforge/registries/RegistryObject;
    1465: invokevirtual #261                // Method net/minecraftforge/registries/RegistryObject.get:()Lnet/minecraftforge/registries/IForgeRegistryEntry;
    1468: checkcast     #522                // class net/minecraft/world/item/Item
    1471: invokedynamic #923,  0            // InvokeDynamic #33:apply:()Ljava/util/function/UnaryOperator;
    1476: invokedynamic #928,  0            // InvokeDynamic #34:apply:()Ljava/util/function/Function;
    1481: invokespecial #843                // Method reliquary/client/gui/hud/DynamicChargePane."<init>":(Lnet/minecraft/world/item/Item;Ljava/util/function/UnaryOperator;Ljava/util/function/Function;)V
    1484: invokestatic  #710                // InterfaceMethod java/util/Map.of:(Ljava/lang/Object;Ljava/lang/Object;Ljava/lang/Object;Ljava/lang/Object;Ljava/lang/Object;Ljava/lang/Object;)Ljava/util/Map;
    1487: invokespecial #713                // Method reliquary/client/gui/hud/ChargeableItemInfoPane."<init>":(Lnet/minecraft/world/item/Item;Lreliquary/client/gui/hud/HUDPosition;Ljava/util/function/Function;Ljava/util/Map;)V
    1490: getstatic     #526                // Field reliquary/reference/Settings.CLIENT:Lreliquary/reference/Settings$Client;
    1493: getfield      #530                // Field reliquary/reference/Settings$Client.hudPositions:Lreliquary/reference/Settings$Client$HudPos;
    1496: getfield      #892                // Field reliquary/reference/Settings$Client$HudPos.harvestRod:Lnet/minecraftforge/common/ForgeConfigSpec$EnumValue;
    1499: invokevirtual #536                // Method net/minecraftforge/common/ForgeConfigSpec$EnumValue.get:()Ljava/lang/Object;
    1502: checkcast     #504                // class reliquary/client/gui/hud/HUDPosition
    1505: invokespecial #563                // Method net/minecraft/util/Tuple."<init>":(Ljava/lang/Object;Ljava/lang/Object;)V
    1508: invokeinterface #567,  2          // InterfaceMethod java/util/List.add:(Ljava/lang/Object;)Z
    1513: pop
    1514: getstatic     #418                // Field hudComponents:Ljava/util/List;
    1517: new           #494                // class net/minecraft/util/Tuple
    1520: dup
    1521: new           #517                // class reliquary/client/gui/hud/ChargeableItemInfoPane
    1524: dup
    1525: getstatic     #931                // Field reliquary/init/ModItems.SOJOURNER_STAFF:Lnet/minecraftforge/registries/RegistryObject;
    1528: invokevirtual #261                // Method net/minecraftforge/registries/RegistryObject.get:()Lnet/minecraftforge/registries/IForgeRegistryEntry;
    1531: checkcast     #522                // class net/minecraft/world/item/Item
    1534: getstatic     #526                // Field reliquary/reference/Settings.CLIENT:Lreliquary/reference/Settings$Client;
    1537: getfield      #530                // Field reliquary/reference/Settings$Client.hudPositions:Lreliquary/reference/Settings$Client$HudPos;
    1540: getfield      #934                // Field reliquary/reference/Settings$Client$HudPos.sojournerStaff:Lnet/minecraftforge/common/ForgeConfigSpec$EnumValue;
    1543: invokevirtual #536                // Method net/minecraftforge/common/ForgeConfigSpec$EnumValue.get:()Ljava/lang/Object;
    1546: checkcast     #504                // class reliquary/client/gui/hud/HUDPosition
    1549: invokedynamic #939,  0            // InvokeDynamic #35:apply:()Ljava/util/function/Function;
    1554: ldc_w         #918                // String dynamic
    1557: new           #823                // class reliquary/client/gui/hud/DynamicChargePane
    1560: dup
    1561: getstatic     #931                // Field reliquary/init/ModItems.SOJOURNER_STAFF:Lnet/minecraftforge/registries/RegistryObject;
    1564: invokevirtual #261                // Method net/minecraftforge/registries/RegistryObject.get:()Lnet/minecraftforge/registries/IForgeRegistryEntry;
    1567: checkcast     #522                // class net/minecraft/world/item/Item
    1570: getstatic     #931                // Field reliquary/init/ModItems.SOJOURNER_STAFF:Lnet/minecraftforge/registries/RegistryObject;
    1573: invokevirtual #261                // Method net/minecraftforge/registries/RegistryObject.get:()Lnet/minecraftforge/registries/IForgeRegistryEntry;
    1576: checkcast     #941                // class reliquary/items/SojournerStaffItem
    1579: dup
    1580: invokestatic  #946                // Method java/util/Objects.requireNonNull:(Ljava/lang/Object;)Ljava/lang/Object;
    1583: pop
    1584: invokedynamic #953,  0            // InvokeDynamic #36:apply:(Lreliquary/items/SojournerStaffItem;)Ljava/util/function/UnaryOperator;
    1589: getstatic     #931                // Field reliquary/init/ModItems.SOJOURNER_STAFF:Lnet/minecraftforge/registries/RegistryObject;
    1592: invokevirtual #261                // Method net/minecraftforge/registries/RegistryObject.get:()Lnet/minecraftforge/registries/IForgeRegistryEntry;
    1595: checkcast     #941                // class reliquary/items/SojournerStaffItem
    1598: dup
    1599: invokestatic  #946                // Method java/util/Objects.requireNonNull:(Ljava/lang/Object;)Ljava/lang/Object;
    1602: pop
    1603: invokedynamic #960,  0            // InvokeDynamic #37:apply:(Lreliquary/items/SojournerStaffItem;)Ljava/util/function/Function;
    1608: invokespecial #843                // Method reliquary/client/gui/hud/DynamicChargePane."<init>":(Lnet/minecraft/world/item/Item;Ljava/util/function/UnaryOperator;Ljava/util/function/Function;)V
    1611: invokestatic  #963                // InterfaceMethod java/util/Map.of:(Ljava/lang/Object;Ljava/lang/Object;)Ljava/util/Map;
    1614: invokespecial #713                // Method reliquary/client/gui/hud/ChargeableItemInfoPane."<init>":(Lnet/minecraft/world/item/Item;Lreliquary/client/gui/hud/HUDPosition;Ljava/util/function/Function;Ljava/util/Map;)V
    1617: getstatic     #526                // Field reliquary/reference/Settings.CLIENT:Lreliquary/reference/Settings$Client;
    1620: getfield      #530                // Field reliquary/reference/Settings$Client.hudPositions:Lreliquary/reference/Settings$Client$HudPos;
    1623: getfield      #934                // Field reliquary/reference/Settings$Client$HudPos.sojournerStaff:Lnet/minecraftforge/common/ForgeConfigSpec$EnumValue;
    1626: invokevirtual #536                // Method net/minecraftforge/common/ForgeConfigSpec$EnumValue.get:()Ljava/lang/Object;
    1629: checkcast     #504                // class reliquary/client/gui/hud/HUDPosition
    1632: invokespecial #563                // Method net/minecraft/util/Tuple."<init>":(Ljava/lang/Object;Ljava/lang/Object;)V
    1635: invokeinterface #567,  2          // InterfaceMethod java/util/List.add:(Ljava/lang/Object;)Z
    1640: pop
    1641: getstatic     #418                // Field hudComponents:Ljava/util/List;
    1644: new           #494                // class net/minecraft/util/Tuple
    1647: dup
    1648: new           #965                // class reliquary/client/gui/hud/HeroMedallionPane
    1651: dup
    1652: invokespecial #966                // Method reliquary/client/gui/hud/HeroMedallionPane."<init>":()V
    1655: getstatic     #526                // Field reliquary/reference/Settings.CLIENT:Lreliquary/reference/Settings$Client;
    1658: getfield      #530                // Field reliquary/reference/Settings$Client.hudPositions:Lreliquary/reference/Settings$Client$HudPos;
    1661: getfield      #969                // Field reliquary/reference/Settings$Client$HudPos.heroMedallion:Lnet/minecraftforge/common/ForgeConfigSpec$EnumValue;
    1664: invokevirtual #536                // Method net/minecraftforge/common/ForgeConfigSpec$EnumValue.get:()Ljava/lang/Object;
    1667: checkcast     #504                // class reliquary/client/gui/hud/HUDPosition
    1670: invokespecial #563                // Method net/minecraft/util/Tuple."<init>":(Ljava/lang/Object;Ljava/lang/Object;)V
    1673: invokeinterface #567,  2          // InterfaceMethod java/util/List.add:(Ljava/lang/Object;)Z
    1678: pop
    1679: getstatic     #418                // Field hudComponents:Ljava/util/List;
    1682: new           #494                // class net/minecraft/util/Tuple
    1685: dup
    1686: getstatic     #754                // Field reliquary/client/gui/components/Box$Alignment.RIGHT:Lreliquary/client/gui/components/Box$Alignment;
    1689: iconst_2
    1690: anewarray     #499                // class reliquary/client/gui/components/Component
    1693: dup
    1694: iconst_0
    1695: new           #971                // class reliquary/client/gui/hud/HandgunPane
    1698: dup
    1699: getstatic     #240                // Field net/minecraft/world/InteractionHand.OFF_HAND:Lnet/minecraft/world/InteractionHand;
    1702: invokespecial #974                // Method reliquary/client/gui/hud/HandgunPane."<init>":(Lnet/minecraft/world/InteractionHand;)V
    1705: aastore
    1706: dup
    1707: iconst_1
    1708: new           #971                // class reliquary/client/gui/hud/HandgunPane
    1711: dup
    1712: getstatic     #264                // Field net/minecraft/world/InteractionHand.MAIN_HAND:Lnet/minecraft/world/InteractionHand;
    1715: invokespecial #974                // Method reliquary/client/gui/hud/HandgunPane."<init>":(Lnet/minecraft/world/InteractionHand;)V
    1718: aastore
    1719: invokestatic  #770                // Method reliquary/client/gui/components/Box.createVertical:(Lreliquary/client/gui/components/Box$Alignment;[Lreliquary/client/gui/components/Component;)Lreliquary/client/gui/components/Box;
    1722: getstatic     #526                // Field reliquary/reference/Settings.CLIENT:Lreliquary/reference/Settings$Client;
    1725: getfield      #530                // Field reliquary/reference/Settings$Client.hudPositions:Lreliquary/reference/Settings$Client$HudPos;
    1728: getfield      #976                // Field reliquary/reference/Settings$Client$HudPos.handgun:Lnet/minecraftforge/common/ForgeConfigSpec$EnumValue;
    1731: invokevirtual #536                // Method net/minecraftforge/common/ForgeConfigSpec$EnumValue.get:()Ljava/lang/Object;
    1734: checkcast     #504                // class reliquary/client/gui/hud/HUDPosition
    1737: invokespecial #563                // Method net/minecraft/util/Tuple."<init>":(Ljava/lang/Object;Ljava/lang/Object;)V
    1740: invokeinterface #567,  2          // InterfaceMethod java/util/List.add:(Ljava/lang/Object;)Z
    1745: pop
    1746: getstatic     #418                // Field hudComponents:Ljava/util/List;
    1749: new           #494                // class net/minecraft/util/Tuple
    1752: dup
    1753: new           #978                // class reliquary/client/gui/hud/CharmPane
    1756: dup
    1757: invokespecial #979                // Method reliquary/client/gui/hud/CharmPane."<init>":()V
    1760: getstatic     #526                // Field reliquary/reference/Settings.CLIENT:Lreliquary/reference/Settings$Client;
    1763: getfield      #530                // Field reliquary/reference/Settings$Client.hudPositions:Lreliquary/reference/Settings$Client$HudPos;
    1766: getfield      #982                // Field reliquary/reference/Settings$Client$HudPos.mobCharm:Lnet/minecraftforge/common/ForgeConfigSpec$EnumValue;
    1769: invokevirtual #536                // Method net/minecraftforge/common/ForgeConfigSpec$EnumValue.get:()Ljava/lang/Object;
    1772: checkcast     #504                // class reliquary/client/gui/hud/HUDPosition
    1775: invokespecial #563                // Method net/minecraft/util/Tuple."<init>":(Ljava/lang/Object;Ljava/lang/Object;)V
    1778: invokeinterface #567,  2          // InterfaceMethod java/util/List.add:(Ljava/lang/Object;)Z
    1783: pop
    1784: return

  private static void registerEntityRenderers(net.minecraftforge.client.event.EntityRenderersEvent$RegisterRenderers);
    descriptor: (Lnet/minecraftforge/client/event/EntityRenderersEvent$RegisterRenderers;)V
    Code:
       0: aload_0
       1: getstatic     #989                // Field reliquary/init/ModBlocks.APOTHECARY_MORTAR_TILE_TYPE:Lnet/minecraftforge/registries/RegistryObject;
       4: invokevirtual #261                // Method net/minecraftforge/registries/RegistryObject.get:()Lnet/minecraftforge/registries/IForgeRegistryEntry;
       7: checkcast     #991                // class net/minecraft/world/level/block/entity/BlockEntityType
      10: invokedynamic #1001,  0           // InvokeDynamic #38:m_173570_:()Lnet/minecraft/client/renderer/blockentity/BlockEntityRendererProvider;
      15: invokevirtual #1005               // Method net/minecraftforge/client/event/EntityRenderersEvent$RegisterRenderers.registerBlockEntityRenderer:(Lnet/minecraft/world/level/block/entity/BlockEntityType;Lnet/minecraft/client/renderer/blockentity/BlockEntityRendererProvider;)V
      18: aload_0
      19: getstatic     #1008               // Field reliquary/init/ModBlocks.PEDESTAL_TILE_TYPE:Lnet/minecraftforge/registries/RegistryObject;
      22: invokevirtual #261                // Method net/minecraftforge/registries/RegistryObject.get:()Lnet/minecraftforge/registries/IForgeRegistryEntry;
      25: checkcast     #991                // class net/minecraft/world/level/block/entity/BlockEntityType
      28: invokedynamic #1013,  0           // InvokeDynamic #39:m_173570_:()Lnet/minecraft/client/renderer/blockentity/BlockEntityRendererProvider;
      33: invokevirtual #1005               // Method net/minecraftforge/client/event/EntityRenderersEvent$RegisterRenderers.registerBlockEntityRenderer:(Lnet/minecraft/world/level/block/entity/BlockEntityType;Lnet/minecraft/client/renderer/blockentity/BlockEntityRendererProvider;)V
      36: aload_0
      37: getstatic     #1016               // Field reliquary/init/ModBlocks.PASSIVE_PEDESTAL_TILE_TYPE:Lnet/minecraftforge/registries/RegistryObject;
      40: invokevirtual #261                // Method net/minecraftforge/registries/RegistryObject.get:()Lnet/minecraftforge/registries/IForgeRegistryEntry;
      43: checkcast     #991                // class net/minecraft/world/level/block/entity/BlockEntityType
      46: invokedynamic #1021,  0           // InvokeDynamic #40:m_173570_:()Lnet/minecraft/client/renderer/blockentity/BlockEntityRendererProvider;
      51: invokevirtual #1005               // Method net/minecraftforge/client/event/EntityRenderersEvent$RegisterRenderers.registerBlockEntityRenderer:(Lnet/minecraft/world/level/block/entity/BlockEntityType;Lnet/minecraft/client/renderer/blockentity/BlockEntityRendererProvider;)V
      54: aload_0
      55: getstatic     #1026               // Field reliquary/init/ModEntities.LYSSA_HOOK:Lnet/minecraftforge/registries/RegistryObject;
      58: invokevirtual #261                // Method net/minecraftforge/registries/RegistryObject.get:()Lnet/minecraftforge/registries/IForgeRegistryEntry;
      61: checkcast     #1028               // class net/minecraft/world/entity/EntityType
      64: invokedynamic #1040,  0           // InvokeDynamic #41:m_174009_:()Lnet/minecraft/client/renderer/entity/EntityRendererProvider;
      69: invokevirtual #1044               // Method net/minecraftforge/client/event/EntityRenderersEvent$RegisterRenderers.registerEntityRenderer:(Lnet/minecraft/world/entity/EntityType;Lnet/minecraft/client/renderer/entity/EntityRendererProvider;)V
      72: aload_0
      73: getstatic     #1047               // Field reliquary/init/ModEntities.BLAZE_SHOT:Lnet/minecraftforge/registries/RegistryObject;
      76: invokevirtual #261                // Method net/minecraftforge/registries/RegistryObject.get:()Lnet/minecraftforge/registries/IForgeRegistryEntry;
      79: checkcast     #1028               // class net/minecraft/world/entity/EntityType
      82: invokedynamic #1052,  0           // InvokeDynamic #42:m_174009_:()Lnet/minecraft/client/renderer/entity/EntityRendererProvider;
      87: invokevirtual #1044               // Method net/minecraftforge/client/event/EntityRenderersEvent$RegisterRenderers.registerEntityRenderer:(Lnet/minecraft/world/entity/EntityType;Lnet/minecraft/client/renderer/entity/EntityRendererProvider;)V
      90: aload_0
      91: getstatic     #1055               // Field reliquary/init/ModEntities.BUSTER_SHOT:Lnet/minecraftforge/registries/RegistryObject;
      94: invokevirtual #261                // Method net/minecraftforge/registries/RegistryObject.get:()Lnet/minecraftforge/registries/IForgeRegistryEntry;
      97: checkcast     #1028               // class net/minecraft/world/entity/EntityType
     100: invokedynamic #1052,  0           // InvokeDynamic #42:m_174009_:()Lnet/minecraft/client/renderer/entity/EntityRendererProvider;
     105: invokevirtual #1044               // Method net/minecraftforge/client/event/EntityRenderersEvent$RegisterRenderers.registerEntityRenderer:(Lnet/minecraft/world/entity/EntityType;Lnet/minecraft/client/renderer/entity/EntityRendererProvider;)V
     108: aload_0
     109: getstatic     #1058               // Field reliquary/init/ModEntities.CONCUSSIVE_SHOT:Lnet/minecraftforge/registries/RegistryObject;
     112: invokevirtual #261                // Method net/minecraftforge/registries/RegistryObject.get:()Lnet/minecraftforge/registries/IForgeRegistryEntry;
     115: checkcast     #1028               // class net/minecraft/world/entity/EntityType
     118: invokedynamic #1052,  0           // InvokeDynamic #42:m_174009_:()Lnet/minecraft/client/renderer/entity/EntityRendererProvider;
     123: invokevirtual #1044               // Method net/minecraftforge/client/event/EntityRenderersEvent$RegisterRenderers.registerEntityRenderer:(Lnet/minecraft/world/entity/EntityType;Lnet/minecraft/client/renderer/entity/EntityRendererProvider;)V
     126: aload_0
     127: getstatic     #1061               // Field reliquary/init/ModEntities.ENDER_SHOT:Lnet/minecraftforge/registries/RegistryObject;
     130: invokevirtual #261                // Method net/minecraftforge/registries/RegistryObject.get:()Lnet/minecraftforge/registries/IForgeRegistryEntry;
     133: checkcast     #1028               // class net/minecraft/world/entity/EntityType
     136: invokedynamic #1052,  0           // InvokeDynamic #42:m_174009_:()Lnet/minecraft/client/renderer/entity/EntityRendererProvider;
     141: invokevirtual #1044               // Method net/minecraftforge/client/event/EntityRenderersEvent$RegisterRenderers.registerEntityRenderer:(Lnet/minecraft/world/entity/EntityType;Lnet/minecraft/client/renderer/entity/EntityRendererProvider;)V
     144: aload_0
     145: getstatic     #1064               // Field reliquary/init/ModEntities.EXORCISM_SHOT:Lnet/minecraftforge/registries/RegistryObject;
     148: invokevirtual #261                // Method net/minecraftforge/registries/RegistryObject.get:()Lnet/minecraftforge/registries/IForgeRegistryEntry;
     151: checkcast     #1028               // class net/minecraft/world/entity/EntityType
     154: invokedynamic #1052,  0           // InvokeDynamic #42:m_174009_:()Lnet/minecraft/client/renderer/entity/EntityRendererProvider;
     159: invokevirtual #1044               // Method net/minecraftforge/client/event/EntityRenderersEvent$RegisterRenderers.registerEntityRenderer:(Lnet/minecraft/world/entity/EntityType;Lnet/minecraft/client/renderer/entity/EntityRendererProvider;)V
     162: aload_0
     163: getstatic     #1067               // Field reliquary/init/ModEntities.NEUTRAL_SHOT:Lnet/minecraftforge/registries/RegistryObject;
     166: invokevirtual #261                // Method net/minecraftforge/registries/RegistryObject.get:()Lnet/minecraftforge/registries/IForgeRegistryEntry;
     169: checkcast     #1028               // class net/minecraft/world/entity/EntityType
     172: invokedynamic #1052,  0           // InvokeDynamic #42:m_174009_:()Lnet/minecraft/client/renderer/entity/EntityRendererProvider;
     177: invokevirtual #1044               // Method net/minecraftforge/client/event/EntityRenderersEvent$RegisterRenderers.registerEntityRenderer:(Lnet/minecraft/world/entity/EntityType;Lnet/minecraft/client/renderer/entity/EntityRendererProvider;)V
     180: aload_0
     181: getstatic     #1070               // Field reliquary/init/ModEntities.SEEKER_SHOT:Lnet/minecraftforge/registries/RegistryObject;
     184: invokevirtual #261                // Method net/minecraftforge/registries/RegistryObject.get:()Lnet/minecraftforge/registries/IForgeRegistryEntry;
     187: checkcast     #1028               // class net/minecraft/world/entity/EntityType
     190: invokedynamic #1052,  0           // InvokeDynamic #42:m_174009_:()Lnet/minecraft/client/renderer/entity/EntityRendererProvider;
     195: invokevirtual #1044               // Method net/minecraftforge/client/event/EntityRenderersEvent$RegisterRenderers.registerEntityRenderer:(Lnet/minecraft/world/entity/EntityType;Lnet/minecraft/client/renderer/entity/EntityRendererProvider;)V
     198: aload_0
     199: getstatic     #1073               // Field reliquary/init/ModEntities.SAND_SHOT:Lnet/minecraftforge/registries/RegistryObject;
     202: invokevirtual #261                // Method net/minecraftforge/registries/RegistryObject.get:()Lnet/minecraftforge/registries/IForgeRegistryEntry;
     205: checkcast     #1028               // class net/minecraft/world/entity/EntityType
     208: invokedynamic #1052,  0           // InvokeDynamic #42:m_174009_:()Lnet/minecraft/client/renderer/entity/EntityRendererProvider;
     213: invokevirtual #1044               // Method net/minecraftforge/client/event/EntityRenderersEvent$RegisterRenderers.registerEntityRenderer:(Lnet/minecraft/world/entity/EntityType;Lnet/minecraft/client/renderer/entity/EntityRendererProvider;)V
     216: aload_0
     217: getstatic     #1076               // Field reliquary/init/ModEntities.STORM_SHOT:Lnet/minecraftforge/registries/RegistryObject;
     220: invokevirtual #261                // Method net/minecraftforge/registries/RegistryObject.get:()Lnet/minecraftforge/registries/IForgeRegistryEntry;
     223: checkcast     #1028               // class net/minecraft/world/entity/EntityType
     226: invokedynamic #1052,  0           // InvokeDynamic #42:m_174009_:()Lnet/minecraft/client/renderer/entity/EntityRendererProvider;
     231: invokevirtual #1044               // Method net/minecraftforge/client/event/EntityRenderersEvent$RegisterRenderers.registerEntityRenderer:(Lnet/minecraft/world/entity/EntityType;Lnet/minecraft/client/renderer/entity/EntityRendererProvider;)V
     234: aload_0
     235: getstatic     #1079               // Field reliquary/init/ModEntities.TIPPED_ARROW:Lnet/minecraftforge/registries/RegistryObject;
     238: invokevirtual #261                // Method net/minecraftforge/registries/RegistryObject.get:()Lnet/minecraftforge/registries/IForgeRegistryEntry;
     241: checkcast     #1028               // class net/minecraft/world/entity/EntityType
     244: invokedynamic #1084,  0           // InvokeDynamic #43:m_174009_:()Lnet/minecraft/client/renderer/entity/EntityRendererProvider;
     249: invokevirtual #1044               // Method net/minecraftforge/client/event/EntityRenderersEvent$RegisterRenderers.registerEntityRenderer:(Lnet/minecraft/world/entity/EntityType;Lnet/minecraft/client/renderer/entity/EntityRendererProvider;)V
     252: aload_0
     253: getstatic     #1087               // Field reliquary/init/ModEntities.GLOWING_WATER:Lnet/minecraftforge/registries/RegistryObject;
     256: invokevirtual #261                // Method net/minecraftforge/registries/RegistryObject.get:()Lnet/minecraftforge/registries/IForgeRegistryEntry;
     259: checkcast     #1028               // class net/minecraft/world/entity/EntityType
     262: invokedynamic #1092,  0           // InvokeDynamic #44:m_174009_:()Lnet/minecraft/client/renderer/entity/EntityRendererProvider;
     267: invokevirtual #1044               // Method net/minecraftforge/client/event/EntityRenderersEvent$RegisterRenderers.registerEntityRenderer:(Lnet/minecraft/world/entity/EntityType;Lnet/minecraft/client/renderer/entity/EntityRendererProvider;)V
     270: aload_0
     271: getstatic     #1095               // Field reliquary/init/ModEntities.APHRODITE_POTION:Lnet/minecraftforge/registries/RegistryObject;
     274: invokevirtual #261                // Method net/minecraftforge/registries/RegistryObject.get:()Lnet/minecraftforge/registries/IForgeRegistryEntry;
     277: checkcast     #1028               // class net/minecraft/world/entity/EntityType
     280: invokedynamic #1092,  0           // InvokeDynamic #44:m_174009_:()Lnet/minecraft/client/renderer/entity/EntityRendererProvider;
     285: invokevirtual #1044               // Method net/minecraftforge/client/event/EntityRenderersEvent$RegisterRenderers.registerEntityRenderer:(Lnet/minecraft/world/entity/EntityType;Lnet/minecraft/client/renderer/entity/EntityRendererProvider;)V
     288: aload_0
     289: getstatic     #1098               // Field reliquary/init/ModEntities.FERTILE_POTION:Lnet/minecraftforge/registries/RegistryObject;
     292: invokevirtual #261                // Method net/minecraftforge/registries/RegistryObject.get:()Lnet/minecraftforge/registries/IForgeRegistryEntry;
     295: checkcast     #1028               // class net/minecraft/world/entity/EntityType
     298: invokedynamic #1092,  0           // InvokeDynamic #44:m_174009_:()Lnet/minecraft/client/renderer/entity/EntityRendererProvider;
     303: invokevirtual #1044               // Method net/minecraftforge/client/event/EntityRenderersEvent$RegisterRenderers.registerEntityRenderer:(Lnet/minecraft/world/entity/EntityType;Lnet/minecraft/client/renderer/entity/EntityRendererProvider;)V
     306: aload_0
     307: getstatic     #1101               // Field reliquary/init/ModEntities.HOLY_HAND_GRENADE:Lnet/minecraftforge/registries/RegistryObject;
     310: invokevirtual #261                // Method net/minecraftforge/registries/RegistryObject.get:()Lnet/minecraftforge/registries/IForgeRegistryEntry;
     313: checkcast     #1028               // class net/minecraft/world/entity/EntityType
     316: invokedynamic #1092,  0           // InvokeDynamic #44:m_174009_:()Lnet/minecraft/client/renderer/entity/EntityRendererProvider;
     321: invokevirtual #1044               // Method net/minecraftforge/client/event/EntityRenderersEvent$RegisterRenderers.registerEntityRenderer:(Lnet/minecraft/world/entity/EntityType;Lnet/minecraft/client/renderer/entity/EntityRendererProvider;)V
     324: aload_0
     325: getstatic     #1104               // Field reliquary/init/ModEntities.KRAKEN_SLIME:Lnet/minecraftforge/registries/RegistryObject;
     328: invokevirtual #261                // Method net/minecraftforge/registries/RegistryObject.get:()Lnet/minecraftforge/registries/IForgeRegistryEntry;
     331: checkcast     #1028               // class net/minecraft/world/entity/EntityType
     334: invokedynamic #1092,  0           // InvokeDynamic #44:m_174009_:()Lnet/minecraft/client/renderer/entity/EntityRendererProvider;
     339: invokevirtual #1044               // Method net/minecraftforge/client/event/EntityRenderersEvent$RegisterRenderers.registerEntityRenderer:(Lnet/minecraft/world/entity/EntityType;Lnet/minecraft/client/renderer/entity/EntityRendererProvider;)V
     342: aload_0
     343: getstatic     #1107               // Field reliquary/init/ModEntities.SPECIAL_SNOWBALL:Lnet/minecraftforge/registries/RegistryObject;
     346: invokevirtual #261                // Method net/minecraftforge/registries/RegistryObject.get:()Lnet/minecraftforge/registries/IForgeRegistryEntry;
     349: checkcast     #1028               // class net/minecraft/world/entity/EntityType
     352: invokedynamic #1092,  0           // InvokeDynamic #44:m_174009_:()Lnet/minecraft/client/renderer/entity/EntityRendererProvider;
     357: invokevirtual #1044               // Method net/minecraftforge/client/event/EntityRenderersEvent$RegisterRenderers.registerEntityRenderer:(Lnet/minecraft/world/entity/EntityType;Lnet/minecraft/client/renderer/entity/EntityRendererProvider;)V
     360: aload_0
     361: getstatic     #1110               // Field reliquary/init/ModEntities.ENDER_STAFF_PROJECTILE:Lnet/minecraftforge/registries/RegistryObject;
     364: invokevirtual #261                // Method net/minecraftforge/registries/RegistryObject.get:()Lnet/minecraftforge/registries/IForgeRegistryEntry;
     367: checkcast     #1028               // class net/minecraft/world/entity/EntityType
     370: invokedynamic #1092,  0           // InvokeDynamic #44:m_174009_:()Lnet/minecraft/client/renderer/entity/EntityRendererProvider;
     375: invokevirtual #1044               // Method net/minecraftforge/client/event/EntityRenderersEvent$RegisterRenderers.registerEntityRenderer:(Lnet/minecraft/world/entity/EntityType;Lnet/minecraft/client/renderer/entity/EntityRendererProvider;)V
     378: aload_0
     379: getstatic     #1113               // Field reliquary/init/ModEntities.THROWN_POTION:Lnet/minecraftforge/registries/RegistryObject;
     382: invokevirtual #261                // Method net/minecraftforge/registries/RegistryObject.get:()Lnet/minecraftforge/registries/IForgeRegistryEntry;
     385: checkcast     #1028               // class net/minecraft/world/entity/EntityType
     388: invokedynamic #1092,  0           // InvokeDynamic #44:m_174009_:()Lnet/minecraft/client/renderer/entity/EntityRendererProvider;
     393: invokevirtual #1044               // Method net/minecraftforge/client/event/EntityRenderersEvent$RegisterRenderers.registerEntityRenderer:(Lnet/minecraft/world/entity/EntityType;Lnet/minecraft/client/renderer/entity/EntityRendererProvider;)V
     396: return

  private static void clientSetup(net.minecraftforge.fml.event.lifecycle.FMLClientSetupEvent);
    descriptor: (Lnet/minecraftforge/fml/event/lifecycle/FMLClientSetupEvent;)V
    Code:
       0: aload_0
       1: invokedynamic #1123,  0           // InvokeDynamic #45:run:()Ljava/lang/Runnable;
       6: invokevirtual #1129               // Method net/minecraftforge/fml/event/lifecycle/FMLClientSetupEvent.enqueueWork:(Ljava/lang/Runnable;)Ljava/util/concurrent/CompletableFuture;
       9: pop
      10: aload_0
      11: invokedynamic #1134,  0           // InvokeDynamic #46:run:()Ljava/lang/Runnable;
      16: invokevirtual #1129               // Method net/minecraftforge/fml/event/lifecycle/FMLClientSetupEvent.enqueueWork:(Ljava/lang/Runnable;)Ljava/util/concurrent/CompletableFuture;
      19: pop
      20: aload_0
      21: invokedynamic #1139,  0           // InvokeDynamic #47:run:()Ljava/lang/Runnable;
      26: invokevirtual #1129               // Method net/minecraftforge/fml/event/lifecycle/FMLClientSetupEvent.enqueueWork:(Ljava/lang/Runnable;)Ljava/util/concurrent/CompletableFuture;
      29: pop
      30: aload_0
      31: invokedynamic #1144,  0           // InvokeDynamic #48:run:()Ljava/lang/Runnable;
      36: invokevirtual #1129               // Method net/minecraftforge/fml/event/lifecycle/FMLClientSetupEvent.enqueueWork:(Ljava/lang/Runnable;)Ljava/util/concurrent/CompletableFuture;
      39: pop
      40: aload_0
      41: invokedynamic #1149,  0           // InvokeDynamic #49:run:()Ljava/lang/Runnable;
      46: invokevirtual #1129               // Method net/minecraftforge/fml/event/lifecycle/FMLClientSetupEvent.enqueueWork:(Ljava/lang/Runnable;)Ljava/util/concurrent/CompletableFuture;
      49: pop
      50: getstatic     #1152               // Field reliquary/init/ModBlocks.FERTILE_LILY_PAD:Lnet/minecraftforge/registries/RegistryObject;
      53: invokevirtual #261                // Method net/minecraftforge/registries/RegistryObject.get:()Lnet/minecraftforge/registries/IForgeRegistryEntry;
      56: checkcast     #1154               // class net/minecraft/world/level/block/Block
      59: invokestatic  #1160               // Method net/minecraft/client/renderer/RenderType.m_110463_:()Lnet/minecraft/client/renderer/RenderType;
      62: invokestatic  #1166               // Method net/minecraft/client/renderer/ItemBlockRenderTypes.setRenderLayer:(Lnet/minecraft/world/level/block/Block;Lnet/minecraft/client/renderer/RenderType;)V
      65: getstatic     #1169               // Field reliquary/init/ModBlocks.INTERDICTION_TORCH:Lnet/minecraftforge/registries/RegistryObject;
      68: invokevirtual #261                // Method net/minecraftforge/registries/RegistryObject.get:()Lnet/minecraftforge/registries/IForgeRegistryEntry;
      71: checkcast     #1154               // class net/minecraft/world/level/block/Block
      74: invokestatic  #1160               // Method net/minecraft/client/renderer/RenderType.m_110463_:()Lnet/minecraft/client/renderer/RenderType;
      77: invokestatic  #1166               // Method net/minecraft/client/renderer/ItemBlockRenderTypes.setRenderLayer:(Lnet/minecraft/world/level/block/Block;Lnet/minecraft/client/renderer/RenderType;)V
      80: getstatic     #1172               // Field reliquary/init/ModBlocks.WALL_INTERDICTION_TORCH:Lnet/minecraftforge/registries/RegistryObject;
      83: invokevirtual #261                // Method net/minecraftforge/registries/RegistryObject.get:()Lnet/minecraftforge/registries/IForgeRegistryEntry;
      86: checkcast     #1154               // class net/minecraft/world/level/block/Block
      89: invokestatic  #1160               // Method net/minecraft/client/renderer/RenderType.m_110463_:()Lnet/minecraft/client/renderer/RenderType;
      92: invokestatic  #1166               // Method net/minecraft/client/renderer/ItemBlockRenderTypes.setRenderLayer:(Lnet/minecraft/world/level/block/Block;Lnet/minecraft/client/renderer/RenderType;)V
      95: return

  private static void registerPropertyToItems(net.minecraft.resources.ResourceLocation, net.minecraft.client.renderer.item.ItemPropertyFunction, net.minecraft.world.item.Item...);
    descriptor: (Lnet/minecraft/resources/ResourceLocation;Lnet/minecraft/client/renderer/item/ItemPropertyFunction;[Lnet/minecraft/world/item/Item;)V
    Code:
       0: aload_2
       1: astore_3
       2: aload_3
       3: arraylength
       4: istore        4
       6: iconst_0
       7: istore        5
       9: iload         5
      11: iload         4
      13: if_icmpge     35
      16: aload_3
      17: iload         5
      19: aaload
      20: astore        6
      22: aload         6
      24: aload_0
      25: aload_1
      26: invokestatic  #1183               // Method net/minecraft/client/renderer/item/ItemProperties.register:(Lnet/minecraft/world/item/Item;Lnet/minecraft/resources/ResourceLocation;Lnet/minecraft/client/renderer/item/ItemPropertyFunction;)V
      29: iinc          5, 1
      32: goto          9
      35: return

  private static boolean isPotionAttached(net.minecraft.world.item.ItemStack);
    descriptor: (Lnet/minecraft/world/item/ItemStack;)Z
    Code:
       0: aload_0
       1: invokestatic  #1197               // Method reliquary/util/potions/XRPotionHelper.getPotionEffectsFromStack:(Lnet/minecraft/world/item/ItemStack;)Ljava/util/List;
       4: invokeinterface #423,  1          // InterfaceMethod java/util/List.isEmpty:()Z
       9: ifne          16
      12: iconst_1
      13: goto          17
      16: iconst_0
      17: ireturn

  private static void loadComplete(net.minecraftforge.fml.event.lifecycle.FMLLoadCompleteEvent);
    descriptor: (Lnet/minecraftforge/fml/event/lifecycle/FMLLoadCompleteEvent;)V
    Code:
       0: aload_0
       1: invokedynamic #1202,  0           // InvokeDynamic #50:run:()Ljava/lang/Runnable;
       6: invokevirtual #1205               // Method net/minecraftforge/fml/event/lifecycle/FMLLoadCompleteEvent.enqueueWork:(Ljava/lang/Runnable;)Ljava/util/concurrent/CompletableFuture;
       9: pop
      10: return

  private static void lambda$loadComplete$36();
    descriptor: ()V
    Code:
       0: invokestatic  #1211               // Method reliquary/client/init/ModItemColors.init:()V
       3: invokestatic  #1214               // Method reliquary/client/init/ModBlockColors.init:()V
       6: ldc_w         #1216               // class net/minecraft/world/item/FishingRodItem
       9: invokedynamic #1223,  0           // InvokeDynamic #51:get:()Ljava/util/function/Supplier;
      14: invokestatic  #1229               // Method reliquary/client/registry/PedestalClientRegistry.registerItemRenderer:(Ljava/lang/Class;Ljava/util/function/Supplier;)V
      17: getstatic     #204                // Field net/minecraftforge/common/MinecraftForge.EVENT_BUS:Lnet/minecraftforge/eventbus/api/IEventBus;
      20: invokedynamic #1238,  0           // InvokeDynamic #52:accept:()Ljava/util/function/Consumer;
      25: invokeinterface #161,  2          // InterfaceMethod net/minecraftforge/eventbus/api/IEventBus.addListener:(Ljava/util/function/Consumer;)V
      30: return

  private static void lambda$clientSetup$35();
    descriptor: ()V
    Code:
       0: new           #1240               // class net/minecraft/resources/ResourceLocation
       3: dup
       4: ldc_w         #1242               // String reliquary
       7: ldc_w         #1244               // String potion
      10: invokespecial #1247               // Method net/minecraft/resources/ResourceLocation."<init>":(Ljava/lang/String;Ljava/lang/String;)V
      13: invokedynamic #1257,  0           // InvokeDynamic #53:m_141951_:()Lnet/minecraft/client/renderer/item/ItemPropertyFunction;
      18: bipush        18
      20: anewarray     #522                // class net/minecraft/world/item/Item
      23: dup
      24: iconst_0
      25: getstatic     #1260               // Field reliquary/init/ModItems.BLAZE_BULLET:Lnet/minecraftforge/registries/RegistryObject;
      28: invokevirtual #261                // Method net/minecraftforge/registries/RegistryObject.get:()Lnet/minecraftforge/registries/IForgeRegistryEntry;
      31: checkcast     #522                // class net/minecraft/world/item/Item
      34: aastore
      35: dup
      36: iconst_1
      37: getstatic     #1263               // Field reliquary/init/ModItems.BUSTER_BULLET:Lnet/minecraftforge/registries/RegistryObject;
      40: invokevirtual #261                // Method net/minecraftforge/registries/RegistryObject.get:()Lnet/minecraftforge/registries/IForgeRegistryEntry;
      43: checkcast     #522                // class net/minecraft/world/item/Item
      46: aastore
      47: dup
      48: iconst_2
      49: getstatic     #1266               // Field reliquary/init/ModItems.CONCUSSIVE_BULLET:Lnet/minecraftforge/registries/RegistryObject;
      52: invokevirtual #261                // Method net/minecraftforge/registries/RegistryObject.get:()Lnet/minecraftforge/registries/IForgeRegistryEntry;
      55: checkcast     #522                // class net/minecraft/world/item/Item
      58: aastore
      59: dup
      60: iconst_3
      61: getstatic     #1269               // Field reliquary/init/ModItems.ENDER_BULLET:Lnet/minecraftforge/registries/RegistryObject;
      64: invokevirtual #261                // Method net/minecraftforge/registries/RegistryObject.get:()Lnet/minecraftforge/registries/IForgeRegistryEntry;
      67: checkcast     #522                // class net/minecraft/world/item/Item
      70: aastore
      71: dup
      72: iconst_4
      73: getstatic     #1272               // Field reliquary/init/ModItems.EXORCISM_BULLET:Lnet/minecraftforge/registries/RegistryObject;
      76: invokevirtual #261                // Method net/minecraftforge/registries/RegistryObject.get:()Lnet/minecraftforge/registries/IForgeRegistryEntry;
      79: checkcast     #522                // class net/minecraft/world/item/Item
      82: aastore
      83: dup
      84: iconst_5
      85: getstatic     #1275               // Field reliquary/init/ModItems.NEUTRAL_BULLET:Lnet/minecraftforge/registries/RegistryObject;
      88: invokevirtual #261                // Method net/minecraftforge/registries/RegistryObject.get:()Lnet/minecraftforge/registries/IForgeRegistryEntry;
      91: checkcast     #522                // class net/minecraft/world/item/Item
      94: aastore
      95: dup
      96: bipush        6
      98: getstatic     #1278               // Field reliquary/init/ModItems.SAND_BULLET:Lnet/minecraftforge/registries/RegistryObject;
     101: invokevirtual #261                // Method net/minecraftforge/registries/RegistryObject.get:()Lnet/minecraftforge/registries/IForgeRegistryEntry;
     104: checkcast     #522                // class net/minecraft/world/item/Item
     107: aastore
     108: dup
     109: bipush        7
     111: getstatic     #1281               // Field reliquary/init/ModItems.SEEKER_BULLET:Lnet/minecraftforge/registries/RegistryObject;
     114: invokevirtual #261                // Method net/minecraftforge/registries/RegistryObject.get:()Lnet/minecraftforge/registries/IForgeRegistryEntry;
     117: checkcast     #522                // class net/minecraft/world/item/Item
     120: aastore
     121: dup
     122: bipush        8
     124: getstatic     #1284               // Field reliquary/init/ModItems.STORM_BULLET:Lnet/minecraftforge/registries/RegistryObject;
     127: invokevirtual #261                // Method net/minecraftforge/registries/RegistryObject.get:()Lnet/minecraftforge/registries/IForgeRegistryEntry;
     130: checkcast     #522                // class net/minecraft/world/item/Item
     133: aastore
     134: dup
     135: bipush        9
     137: getstatic     #1287               // Field reliquary/init/ModItems.BLAZE_MAGAZINE:Lnet/minecraftforge/registries/RegistryObject;
     140: invokevirtual #261                // Method net/minecraftforge/registries/RegistryObject.get:()Lnet/minecraftforge/registries/IForgeRegistryEntry;
     143: checkcast     #522                // class net/minecraft/world/item/Item
     146: aastore
     147: dup
     148: bipush        10
     150: getstatic     #1290               // Field reliquary/init/ModItems.BUSTER_MAGAZINE:Lnet/minecraftforge/registries/RegistryObject;
     153: invokevirtual #261                // Method net/minecraftforge/registries/RegistryObject.get:()Lnet/minecraftforge/registries/IForgeRegistryEntry;
     156: checkcast     #522                // class net/minecraft/world/item/Item
     159: aastore
     160: dup
     161: bipush        11
     163: getstatic     #1293               // Field reliquary/init/ModItems.CONCUSSIVE_MAGAZINE:Lnet/minecraftforge/registries/RegistryObject;
     166: invokevirtual #261                // Method net/minecraftforge/registries/RegistryObject.get:()Lnet/minecraftforge/registries/IForgeRegistryEntry;
     169: checkcast     #522                // class net/minecraft/world/item/Item
     172: aastore
     173: dup
     174: bipush        12
     176: getstatic     #1296               // Field reliquary/init/ModItems.ENDER_MAGAZINE:Lnet/minecraftforge/registries/RegistryObject;
     179: invokevirtual #261                // Method net/minecraftforge/registries/RegistryObject.get:()Lnet/minecraftforge/registries/IForgeRegistryEntry;
     182: checkcast     #522                // class net/minecraft/world/item/Item
     185: aastore
     186: dup
     187: bipush        13
     189: getstatic     #1299               // Field reliquary/init/ModItems.EXORCISM_MAGAZINE:Lnet/minecraftforge/registries/RegistryObject;
     192: invokevirtual #261                // Method net/minecraftforge/registries/RegistryObject.get:()Lnet/minecraftforge/registries/IForgeRegistryEntry;
     195: checkcast     #522                // class net/minecraft/world/item/Item
     198: aastore
     199: dup
     200: bipush        14
     202: getstatic     #1302               // Field reliquary/init/ModItems.NEUTRAL_MAGAZINE:Lnet/minecraftforge/registries/RegistryObject;
     205: invokevirtual #261                // Method net/minecraftforge/registries/RegistryObject.get:()Lnet/minecraftforge/registries/IForgeRegistryEntry;
     208: checkcast     #522                // class net/minecraft/world/item/Item
     211: aastore
     212: dup
     213: bipush        15
     215: getstatic     #1305               // Field reliquary/init/ModItems.SAND_MAGAZINE:Lnet/minecraftforge/registries/RegistryObject;
     218: invokevirtual #261                // Method net/minecraftforge/registries/RegistryObject.get:()Lnet/minecraftforge/registries/IForgeRegistryEntry;
     221: checkcast     #522                // class net/minecraft/world/item/Item
     224: aastore
     225: dup
     226: bipush        16
     228: getstatic     #1308               // Field reliquary/init/ModItems.SEEKER_MAGAZINE:Lnet/minecraftforge/registries/RegistryObject;
     231: invokevirtual #261                // Method net/minecraftforge/registries/RegistryObject.get:()Lnet/minecraftforge/registries/IForgeRegistryEntry;
     234: checkcast     #522                // class net/minecraft/world/item/Item
     237: aastore
     238: dup
     239: bipush        17
     241: getstatic     #1311               // Field reliquary/init/ModItems.STORM_MAGAZINE:Lnet/minecraftforge/registries/RegistryObject;
     244: invokevirtual #261                // Method net/minecraftforge/registries/RegistryObject.get:()Lnet/minecraftforge/registries/IForgeRegistryEntry;
     247: checkcast     #522                // class net/minecraft/world/item/Item
     250: aastore
     251: invokestatic  #1313               // Method registerPropertyToItems:(Lnet/minecraft/resources/ResourceLocation;Lnet/minecraft/client/renderer/item/ItemPropertyFunction;[Lnet/minecraft/world/item/Item;)V
     254: return

  private static float lambda$clientSetup$34(net.minecraft.world.item.ItemStack, net.minecraft.client.multiplayer.ClientLevel, net.minecraft.world.entity.LivingEntity, int);
    descriptor: (Lnet/minecraft/world/item/ItemStack;Lnet/minecraft/client/multiplayer/ClientLevel;Lnet/minecraft/world/entity/LivingEntity;I)F
    Code:
       0: aload_0
       1: invokestatic  #1315               // Method isPotionAttached:(Lnet/minecraft/world/item/ItemStack;)Z
       4: ifeq          11
       7: fconst_1
       8: goto          12
      11: fconst_0
      12: freturn

  private static void lambda$clientSetup$33();
    descriptor: ()V
    Code:
       0: getstatic     #826                // Field reliquary/init/ModItems.VOID_TEAR:Lnet/minecraftforge/registries/RegistryObject;
       3: invokevirtual #261                // Method net/minecraftforge/registries/RegistryObject.get:()Lnet/minecraftforge/registries/IForgeRegistryEntry;
       6: checkcast     #522                // class net/minecraft/world/item/Item
       9: new           #1240               // class net/minecraft/resources/ResourceLocation
      12: dup
      13: ldc_w         #1321               // String empty
      16: invokespecial #1322               // Method net/minecraft/resources/ResourceLocation."<init>":(Ljava/lang/String;)V
      19: invokedynamic #1327,  0           // InvokeDynamic #54:m_141951_:()Lnet/minecraft/client/renderer/item/ItemPropertyFunction;
      24: invokestatic  #1183               // Method net/minecraft/client/renderer/item/ItemProperties.register:(Lnet/minecraft/world/item/Item;Lnet/minecraft/resources/ResourceLocation;Lnet/minecraft/client/renderer/item/ItemPropertyFunction;)V
      27: return

  private static float lambda$clientSetup$32(net.minecraft.world.item.ItemStack, net.minecraft.client.multiplayer.ClientLevel, net.minecraft.world.entity.LivingEntity, int);
    descriptor: (Lnet/minecraft/world/item/ItemStack;Lnet/minecraft/client/multiplayer/ClientLevel;Lnet/minecraft/world/entity/LivingEntity;I)F
    Code:
       0: aload_0
       1: iconst_1
       2: invokestatic  #1330               // Method reliquary/items/VoidTearItem.isEmpty:(Lnet/minecraft/world/item/ItemStack;Z)Z
       5: ifeq          12
       8: fconst_1
       9: goto          13
      12: fconst_0
      13: freturn

  private static void lambda$clientSetup$31();
    descriptor: ()V
    Code:
       0: getstatic     #1335               // Field reliquary/init/ModItems.INFERNAL_TEAR:Lnet/minecraftforge/registries/RegistryObject;
       3: invokevirtual #261                // Method net/minecraftforge/registries/RegistryObject.get:()Lnet/minecraftforge/registries/IForgeRegistryEntry;
       6: checkcast     #522                // class net/minecraft/world/item/Item
       9: new           #1240               // class net/minecraft/resources/ResourceLocation
      12: dup
      13: ldc_w         #1321               // String empty
      16: invokespecial #1322               // Method net/minecraft/resources/ResourceLocation."<init>":(Ljava/lang/String;)V
      19: invokedynamic #1340,  0           // InvokeDynamic #55:m_141951_:()Lnet/minecraft/client/renderer/item/ItemPropertyFunction;
      24: invokestatic  #1183               // Method net/minecraft/client/renderer/item/ItemProperties.register:(Lnet/minecraft/world/item/Item;Lnet/minecraft/resources/ResourceLocation;Lnet/minecraft/client/renderer/item/ItemPropertyFunction;)V
      27: return

  private static float lambda$clientSetup$30(net.minecraft.world.item.ItemStack, net.minecraft.client.multiplayer.ClientLevel, net.minecraft.world.entity.LivingEntity, int);
    descriptor: (Lnet/minecraft/world/item/ItemStack;Lnet/minecraft/client/multiplayer/ClientLevel;Lnet/minecraft/world/entity/LivingEntity;I)F
    Code:
       0: aload_0
       1: invokestatic  #1345               // Method reliquary/items/InfernalTearItem.getStackFromTear:(Lnet/minecraft/world/item/ItemStack;)Lnet/minecraft/world/item/ItemStack;
       4: invokevirtual #1348               // Method net/minecraft/world/item/ItemStack.m_41619_:()Z
       7: ifeq          14
      10: fconst_1
      11: goto          15
      14: fconst_0
      15: freturn

  private static void lambda$clientSetup$29();
    descriptor: ()V
    Code:
       0: getstatic     #1351               // Field reliquary/init/ModItems.ROD_OF_LYSSA:Lnet/minecraftforge/registries/RegistryObject;
       3: invokevirtual #261                // Method net/minecraftforge/registries/RegistryObject.get:()Lnet/minecraftforge/registries/IForgeRegistryEntry;
       6: checkcast     #522                // class net/minecraft/world/item/Item
       9: new           #1240               // class net/minecraft/resources/ResourceLocation
      12: dup
      13: ldc_w         #1353               // String cast
      16: invokespecial #1322               // Method net/minecraft/resources/ResourceLocation."<init>":(Ljava/lang/String;)V
      19: invokedynamic #1358,  0           // InvokeDynamic #56:m_141951_:()Lnet/minecraft/client/renderer/item/ItemPropertyFunction;
      24: invokestatic  #1183               // Method net/minecraft/client/renderer/item/ItemProperties.register:(Lnet/minecraft/world/item/Item;Lnet/minecraft/resources/ResourceLocation;Lnet/minecraft/client/renderer/item/ItemPropertyFunction;)V
      27: return

  private static float lambda$clientSetup$28(net.minecraft.world.item.ItemStack, net.minecraft.client.multiplayer.ClientLevel, net.minecraft.world.entity.LivingEntity, int);
    descriptor: (Lnet/minecraft/world/item/ItemStack;Lnet/minecraft/client/multiplayer/ClientLevel;Lnet/minecraft/world/entity/LivingEntity;I)F
    Code:
       0: aload_2
       1: ifnonnull     6
       4: fconst_0
       5: freturn
       6: aload_1
       7: ifnonnull     12
      10: fconst_0
      11: freturn
      12: aload_0
      13: invokestatic  #1363               // Method reliquary/items/RodOfLyssaItem.getHookEntityId:(Lnet/minecraft/world/item/ItemStack;)I
      16: istore        4
      18: aload_2
      19: invokevirtual #1366               // Method net/minecraft/world/entity/LivingEntity.m_21205_:()Lnet/minecraft/world/item/ItemStack;
      22: aload_0
      23: if_acmpeq     34
      26: aload_2
      27: invokevirtual #1367               // Method net/minecraft/world/entity/LivingEntity.m_21206_:()Lnet/minecraft/world/item/ItemStack;
      30: aload_0
      31: if_acmpne     52
      34: iload         4
      36: ifle          52
      39: aload_1
      40: iload         4
      42: invokevirtual #1373               // Method net/minecraft/client/multiplayer/ClientLevel.m_6815_:(I)Lnet/minecraft/world/entity/Entity;
      45: ifnull        52
      48: fconst_1
      49: goto          53
      52: fconst_0
      53: freturn

  private static void lambda$clientSetup$27();
    descriptor: ()V
    Code:
       0: getstatic     #1376               // Field FORTUNE_COIN_TOGGLE_KEYBIND:Lnet/minecraft/client/KeyMapping;
       3: invokestatic  #1382               // Method net/minecraftforge/client/ClientRegistry.registerKeyBinding:(Lnet/minecraft/client/KeyMapping;)V
       6: return

  private static net.minecraft.client.renderer.blockentity.BlockEntityRenderer lambda$registerEntityRenderers$26(net.minecraft.client.renderer.blockentity.BlockEntityRendererProvider$Context);
    descriptor: (Lnet/minecraft/client/renderer/blockentity/BlockEntityRendererProvider$Context;)Lnet/minecraft/client/renderer/blockentity/BlockEntityRenderer;
    Code:
       0: new           #1384               // class reliquary/client/render/PassivePedestalRenderer
       3: dup
       4: invokespecial #1385               // Method reliquary/client/render/PassivePedestalRenderer."<init>":()V
       7: areturn

  private static net.minecraft.client.renderer.blockentity.BlockEntityRenderer lambda$registerEntityRenderers$25(net.minecraft.client.renderer.blockentity.BlockEntityRendererProvider$Context);
    descriptor: (Lnet/minecraft/client/renderer/blockentity/BlockEntityRendererProvider$Context;)Lnet/minecraft/client/renderer/blockentity/BlockEntityRenderer;
    Code:
       0: new           #1389               // class reliquary/client/render/PedestalRenderer
       3: dup
       4: invokespecial #1390               // Method reliquary/client/render/PedestalRenderer."<init>":()V
       7: areturn

  private static net.minecraft.client.renderer.blockentity.BlockEntityRenderer lambda$registerEntityRenderers$24(net.minecraft.client.renderer.blockentity.BlockEntityRendererProvider$Context);
    descriptor: (Lnet/minecraft/client/renderer/blockentity/BlockEntityRendererProvider$Context;)Lnet/minecraft/client/renderer/blockentity/BlockEntityRenderer;
    Code:
       0: new           #1392               // class reliquary/client/render/ApothecaryMortarRenderer
       3: dup
       4: invokespecial #1393               // Method reliquary/client/render/ApothecaryMortarRenderer."<init>":()V
       7: areturn

  private static java.lang.String lambda$initHUDComponents$23(net.minecraft.world.item.ItemStack);
    descriptor: (Lnet/minecraft/world/item/ItemStack;)Ljava/lang/String;
    Code:
       0: ldc_w         #918                // String dynamic
       3: areturn

  private static java.lang.Integer lambda$initHUDComponents$22(net.minecraft.world.item.ItemStack);
    descriptor: (Lnet/minecraft/world/item/ItemStack;)Ljava/lang/Integer;
    Code:
       0: getstatic     #889                // Field reliquary/init/ModItems.HARVEST_ROD:Lnet/minecraftforge/registries/RegistryObject;
       3: invokevirtual #261                // Method net/minecraftforge/registries/RegistryObject.get:()Lnet/minecraftforge/registries/IForgeRegistryEntry;
       6: checkcast     #66                 // class reliquary/items/HarvestRodItem
       9: aload_0
      10: getstatic     #889                // Field reliquary/init/ModItems.HARVEST_ROD:Lnet/minecraftforge/registries/RegistryObject;
      13: invokevirtual #261                // Method net/minecraftforge/registries/RegistryObject.get:()Lnet/minecraftforge/registries/IForgeRegistryEntry;
      16: checkcast     #66                 // class reliquary/items/HarvestRodItem
      19: aload_0
      20: invokevirtual #1399               // Method reliquary/items/HarvestRodItem.getCurrentPlantableSlot:(Lnet/minecraft/world/item/ItemStack;)B
      23: iconst_1
      24: invokevirtual #1403               // Method reliquary/items/HarvestRodItem.getPlantableQuantity:(Lnet/minecraft/world/item/ItemStack;IZ)I
      27: invokestatic  #1409               // Method java/lang/Integer.valueOf:(I)Ljava/lang/Integer;
      30: areturn

  private static net.minecraft.world.item.ItemStack lambda$initHUDComponents$21(net.minecraft.world.item.ItemStack);
    descriptor: (Lnet/minecraft/world/item/ItemStack;)Lnet/minecraft/world/item/ItemStack;
    Code:
       0: getstatic     #889                // Field reliquary/init/ModItems.HARVEST_ROD:Lnet/minecraftforge/registries/RegistryObject;
       3: invokevirtual #261                // Method net/minecraftforge/registries/RegistryObject.get:()Lnet/minecraftforge/registries/IForgeRegistryEntry;
       6: checkcast     #66                 // class reliquary/items/HarvestRodItem
       9: aload_0
      10: iconst_1
      11: invokevirtual #1413               // Method reliquary/items/HarvestRodItem.getCurrentPlantable:(Lnet/minecraft/world/item/ItemStack;Z)Lnet/minecraft/world/item/ItemStack;
      14: areturn

  private static java.lang.Integer lambda$initHUDComponents$20(net.minecraft.world.item.ItemStack);
    descriptor: (Lnet/minecraft/world/item/ItemStack;)Ljava/lang/Integer;
    Code:
       0: getstatic     #889                // Field reliquary/init/ModItems.HARVEST_ROD:Lnet/minecraftforge/registries/RegistryObject;
       3: invokevirtual #261                // Method net/minecraftforge/registries/RegistryObject.get:()Lnet/minecraftforge/registries/IForgeRegistryEntry;
       6: checkcast     #66                 // class reliquary/items/HarvestRodItem
       9: aload_0
      10: iconst_1
      11: invokevirtual #1417               // Method reliquary/items/HarvestRodItem.getBoneMealCount:(Lnet/minecraft/world/item/ItemStack;Z)I
      14: invokestatic  #1409               // Method java/lang/Integer.valueOf:(I)Ljava/lang/Integer;
      17: areturn

  private static java.lang.String lambda$initHUDComponents$19(net.minecraft.world.item.ItemStack);
    descriptor: (Lnet/minecraft/world/item/ItemStack;)Ljava/lang/String;
    Code:
       0: getstatic     #889                // Field reliquary/init/ModItems.HARVEST_ROD:Lnet/minecraftforge/registries/RegistryObject;
       3: invokevirtual #261                // Method net/minecraftforge/registries/RegistryObject.get:()Lnet/minecraftforge/registries/IForgeRegistryEntry;
       6: checkcast     #66                 // class reliquary/items/HarvestRodItem
       9: aload_0
      10: invokevirtual #1421               // Method reliquary/items/HarvestRodItem.getMode:(Lnet/minecraft/world/item/ItemStack;)Lreliquary/items/HarvestRodItem$Mode;
      13: invokevirtual #902                // Method reliquary/items/HarvestRodItem$Mode.m_7912_:()Ljava/lang/String;
      16: areturn

  private static java.lang.String lambda$initHUDComponents$18(net.minecraft.world.item.ItemStack);
    descriptor: (Lnet/minecraft/world/item/ItemStack;)Ljava/lang/String;
    Code:
       0: getstatic     #826                // Field reliquary/init/ModItems.VOID_TEAR:Lnet/minecraftforge/registries/RegistryObject;
       3: invokevirtual #261                // Method net/minecraftforge/registries/RegistryObject.get:()Lnet/minecraftforge/registries/IForgeRegistryEntry;
       6: checkcast     #62                 // class reliquary/items/VoidTearItem
       9: aload_0
      10: invokevirtual #1424               // Method reliquary/items/VoidTearItem.getMode:(Lnet/minecraft/world/item/ItemStack;)Lreliquary/items/VoidTearItem$Mode;
      13: invokevirtual #856                // Method reliquary/items/VoidTearItem$Mode.m_7912_:()Ljava/lang/String;
      16: areturn

  private static java.lang.Integer lambda$initHUDComponents$17(net.minecraft.world.item.ItemStack);
    descriptor: (Lnet/minecraft/world/item/ItemStack;)Ljava/lang/Integer;
    Code:
       0: aload_0
       1: iconst_1
       2: invokestatic  #1427               // Method reliquary/items/VoidTearItem.getTearContents:(Lnet/minecraft/world/item/ItemStack;Z)Lnet/minecraft/world/item/ItemStack;
       5: invokevirtual #1431               // Method net/minecraft/world/item/ItemStack.m_41613_:()I
       8: invokestatic  #1409               // Method java/lang/Integer.valueOf:(I)Ljava/lang/Integer;
      11: areturn

  private static net.minecraft.world.item.ItemStack lambda$initHUDComponents$16(net.minecraft.world.item.ItemStack);
    descriptor: (Lnet/minecraft/world/item/ItemStack;)Lnet/minecraft/world/item/ItemStack;
    Code:
       0: aload_0
       1: iconst_1
       2: invokestatic  #1427               // Method reliquary/items/VoidTearItem.getTearContents:(Lnet/minecraft/world/item/ItemStack;Z)Lnet/minecraft/world/item/ItemStack;
       5: areturn

  private static java.lang.String lambda$initHUDComponents$15(net.minecraft.world.item.ItemStack);
    descriptor: (Lnet/minecraft/world/item/ItemStack;)Ljava/lang/String;
    Code:
       0: getstatic     #787                // Field reliquary/init/ModItems.RENDING_GALE:Lnet/minecraftforge/registries/RegistryObject;
       3: invokevirtual #261                // Method net/minecraftforge/registries/RegistryObject.get:()Lnet/minecraftforge/registries/IForgeRegistryEntry;
       6: checkcast     #58                 // class reliquary/items/RendingGaleItem
       9: aload_0
      10: invokevirtual #1434               // Method reliquary/items/RendingGaleItem.getMode:(Lnet/minecraft/world/item/ItemStack;)Lreliquary/items/RendingGaleItem$Mode;
      13: invokevirtual #808                // Method reliquary/items/RendingGaleItem$Mode.m_7912_:()Ljava/lang/String;
      16: areturn

  private static java.lang.Integer lambda$initHUDComponents$14(net.minecraft.world.item.ItemStack);
    descriptor: (Lnet/minecraft/world/item/ItemStack;)Ljava/lang/Integer;
    Code:
       0: getstatic     #787                // Field reliquary/init/ModItems.RENDING_GALE:Lnet/minecraftforge/registries/RegistryObject;
       3: invokevirtual #261                // Method net/minecraftforge/registries/RegistryObject.get:()Lnet/minecraftforge/registries/IForgeRegistryEntry;
       6: checkcast     #58                 // class reliquary/items/RendingGaleItem
       9: aload_0
      10: invokestatic  #401                // Method net/minecraft/client/Minecraft.m_91087_:()Lnet/minecraft/client/Minecraft;
      13: getfield      #416                // Field net/minecraft/client/Minecraft.f_91074_:Lnet/minecraft/client/player/LocalPlayer;
      16: invokevirtual #1438               // Method reliquary/items/RendingGaleItem.getFeatherCountClient:(Lnet/minecraft/world/item/ItemStack;Lnet/minecraft/world/entity/player/Player;)I
      19: bipush        100
      21: idiv
      22: invokestatic  #1409               // Method java/lang/Integer.valueOf:(I)Ljava/lang/Integer;
      25: areturn

  private static java.lang.Integer lambda$initHUDComponents$13(net.minecraft.world.item.ItemStack);
    descriptor: (Lnet/minecraft/world/item/ItemStack;)Ljava/lang/Integer;
    Code:
       0: getstatic     #716                // Field reliquary/init/ModItems.PYROMANCER_STAFF:Lnet/minecraftforge/registries/RegistryObject;
       3: invokevirtual #261                // Method net/minecraftforge/registries/RegistryObject.get:()Lnet/minecraftforge/registries/IForgeRegistryEntry;
       6: checkcast     #49                 // class reliquary/items/PyromancerStaffItem
       9: aload_0
      10: getstatic     #732                // Field net/minecraft/world/item/Items.f_42593_:Lnet/minecraft/world/item/Item;
      13: invokevirtual #1442               // Method reliquary/items/PyromancerStaffItem.getInternalStorageItemCount:(Lnet/minecraft/world/item/ItemStack;Lnet/minecraft/world/item/Item;)I
      16: invokestatic  #1409               // Method java/lang/Integer.valueOf:(I)Ljava/lang/Integer;
      19: areturn

  private static java.lang.Integer lambda$initHUDComponents$12(net.minecraft.world.item.ItemStack);
    descriptor: (Lnet/minecraft/world/item/ItemStack;)Ljava/lang/Integer;
    Code:
       0: getstatic     #716                // Field reliquary/init/ModItems.PYROMANCER_STAFF:Lnet/minecraftforge/registries/RegistryObject;
       3: invokevirtual #261                // Method net/minecraftforge/registries/RegistryObject.get:()Lnet/minecraftforge/registries/IForgeRegistryEntry;
       6: checkcast     #49                 // class reliquary/items/PyromancerStaffItem
       9: aload_0
      10: getstatic     #743                // Field net/minecraft/world/item/Items.f_42613_:Lnet/minecraft/world/item/Item;
      13: invokevirtual #1442               // Method reliquary/items/PyromancerStaffItem.getInternalStorageItemCount:(Lnet/minecraft/world/item/ItemStack;Lnet/minecraft/world/item/Item;)I
      16: invokestatic  #1409               // Method java/lang/Integer.valueOf:(I)Ljava/lang/Integer;
      19: areturn

  private static java.lang.Integer lambda$initHUDComponents$11(net.minecraft.world.item.ItemStack);
    descriptor: (Lnet/minecraft/world/item/ItemStack;)Ljava/lang/Integer;
    Code:
       0: getstatic     #716                // Field reliquary/init/ModItems.PYROMANCER_STAFF:Lnet/minecraftforge/registries/RegistryObject;
       3: invokevirtual #261                // Method net/minecraftforge/registries/RegistryObject.get:()Lnet/minecraftforge/registries/IForgeRegistryEntry;
       6: checkcast     #49                 // class reliquary/items/PyromancerStaffItem
       9: aload_0
      10: getstatic     #732                // Field net/minecraft/world/item/Items.f_42593_:Lnet/minecraft/world/item/Item;
      13: invokevirtual #1442               // Method reliquary/items/PyromancerStaffItem.getInternalStorageItemCount:(Lnet/minecraft/world/item/ItemStack;Lnet/minecraft/world/item/Item;)I
      16: invokestatic  #1409               // Method java/lang/Integer.valueOf:(I)Ljava/lang/Integer;
      19: areturn

  private static java.lang.String lambda$initHUDComponents$10(net.minecraft.world.item.ItemStack);
    descriptor: (Lnet/minecraft/world/item/ItemStack;)Ljava/lang/String;
    Code:
       0: getstatic     #716                // Field reliquary/init/ModItems.PYROMANCER_STAFF:Lnet/minecraftforge/registries/RegistryObject;
       3: invokevirtual #261                // Method net/minecraftforge/registries/RegistryObject.get:()Lnet/minecraftforge/registries/IForgeRegistryEntry;
       6: checkcast     #49                 // class reliquary/items/PyromancerStaffItem
       9: aload_0
      10: invokevirtual #1445               // Method reliquary/items/PyromancerStaffItem.getMode:(Lnet/minecraft/world/item/ItemStack;)Lreliquary/items/PyromancerStaffItem$Mode;
      13: invokevirtual #729                // Method reliquary/items/PyromancerStaffItem$Mode.m_7912_:()Ljava/lang/String;
      16: areturn

  private static java.lang.Integer lambda$initHUDComponents$9(net.minecraft.world.item.ItemStack);
    descriptor: (Lnet/minecraft/world/item/ItemStack;)Ljava/lang/Integer;
    Code:
       0: getstatic     #647                // Field reliquary/init/ModItems.ENDER_STAFF:Lnet/minecraftforge/registries/RegistryObject;
       3: invokevirtual #261                // Method net/minecraftforge/registries/RegistryObject.get:()Lnet/minecraftforge/registries/IForgeRegistryEntry;
       6: checkcast     #44                 // class reliquary/items/EnderStaffItem
       9: aload_0
      10: iconst_1
      11: invokevirtual #1448               // Method reliquary/items/EnderStaffItem.getPearlCount:(Lnet/minecraft/world/item/ItemStack;Z)I
      14: invokestatic  #1409               // Method java/lang/Integer.valueOf:(I)Ljava/lang/Integer;
      17: areturn

  private static java.lang.Integer lambda$initHUDComponents$8(net.minecraft.world.item.ItemStack);
    descriptor: (Lnet/minecraft/world/item/ItemStack;)Ljava/lang/Integer;
    Code:
       0: getstatic     #647                // Field reliquary/init/ModItems.ENDER_STAFF:Lnet/minecraftforge/registries/RegistryObject;
       3: invokevirtual #261                // Method net/minecraftforge/registries/RegistryObject.get:()Lnet/minecraftforge/registries/IForgeRegistryEntry;
       6: checkcast     #44                 // class reliquary/items/EnderStaffItem
       9: aload_0
      10: iconst_1
      11: invokevirtual #1448               // Method reliquary/items/EnderStaffItem.getPearlCount:(Lnet/minecraft/world/item/ItemStack;Z)I
      14: invokestatic  #1409               // Method java/lang/Integer.valueOf:(I)Ljava/lang/Integer;
      17: areturn

  private static java.lang.Integer lambda$initHUDComponents$7(net.minecraft.world.item.ItemStack);
    descriptor: (Lnet/minecraft/world/item/ItemStack;)Ljava/lang/Integer;
    Code:
       0: getstatic     #647                // Field reliquary/init/ModItems.ENDER_STAFF:Lnet/minecraftforge/registries/RegistryObject;
       3: invokevirtual #261                // Method net/minecraftforge/registries/RegistryObject.get:()Lnet/minecraftforge/registries/IForgeRegistryEntry;
       6: checkcast     #44                 // class reliquary/items/EnderStaffItem
       9: aload_0
      10: iconst_1
      11: invokevirtual #1448               // Method reliquary/items/EnderStaffItem.getPearlCount:(Lnet/minecraft/world/item/ItemStack;Z)I
      14: invokestatic  #1409               // Method java/lang/Integer.valueOf:(I)Ljava/lang/Integer;
      17: areturn

  private static java.lang.String lambda$initHUDComponents$6(net.minecraft.world.item.ItemStack);
    descriptor: (Lnet/minecraft/world/item/ItemStack;)Ljava/lang/String;
    Code:
       0: getstatic     #647                // Field reliquary/init/ModItems.ENDER_STAFF:Lnet/minecraftforge/registries/RegistryObject;
       3: invokevirtual #261                // Method net/minecraftforge/registries/RegistryObject.get:()Lnet/minecraftforge/registries/IForgeRegistryEntry;
       6: checkcast     #44                 // class reliquary/items/EnderStaffItem
       9: aload_0
      10: invokevirtual #1451               // Method reliquary/items/EnderStaffItem.getMode:(Lnet/minecraft/world/item/ItemStack;)Lreliquary/items/EnderStaffItem$Mode;
      13: invokevirtual #665                // Method reliquary/items/EnderStaffItem$Mode.m_7912_:()Ljava/lang/String;
      16: areturn

  private static java.lang.Integer lambda$initHUDComponents$5(net.minecraft.world.item.ItemStack);
    descriptor: (Lnet/minecraft/world/item/ItemStack;)Ljava/lang/Integer;
    Code:
       0: ldc_w         #1453               // String snowballs
       3: aload_0
       4: invokestatic  #1459               // Method reliquary/util/NBTHelper.getInt:(Ljava/lang/String;Lnet/minecraft/world/item/ItemStack;)I
       7: invokestatic  #1409               // Method java/lang/Integer.valueOf:(I)Ljava/lang/Integer;
      10: areturn

  private static java.lang.Integer lambda$initHUDComponents$4(net.minecraft.world.item.ItemStack);
    descriptor: (Lnet/minecraft/world/item/ItemStack;)Ljava/lang/Integer;
    Code:
       0: ldc_w         #1453               // String snowballs
       3: aload_0
       4: invokestatic  #1459               // Method reliquary/util/NBTHelper.getInt:(Ljava/lang/String;Lnet/minecraft/world/item/ItemStack;)I
       7: invokestatic  #1409               // Method java/lang/Integer.valueOf:(I)Ljava/lang/Integer;
      10: areturn

  private static java.lang.Integer lambda$initHUDComponents$3(net.minecraft.world.item.ItemStack);
    descriptor: (Lnet/minecraft/world/item/ItemStack;)Ljava/lang/Integer;
    Code:
       0: ldc_w         #1461               // String fluidStacks
       3: aload_0
       4: invokestatic  #1459               // Method reliquary/util/NBTHelper.getInt:(Ljava/lang/String;Lnet/minecraft/world/item/ItemStack;)I
       7: sipush        1000
      10: idiv
      11: invokestatic  #1409               // Method java/lang/Integer.valueOf:(I)Ljava/lang/Integer;
      14: areturn

  private static java.lang.Integer lambda$initHUDComponents$2(net.minecraft.world.item.ItemStack);
    descriptor: (Lnet/minecraft/world/item/ItemStack;)Ljava/lang/Integer;
    Code:
       0: ldc_w         #1463               // String glowstone
       3: aload_0
       4: invokestatic  #1459               // Method reliquary/util/NBTHelper.getInt:(Ljava/lang/String;Lnet/minecraft/world/item/ItemStack;)I
       7: invokestatic  #1409               // Method java/lang/Integer.valueOf:(I)Ljava/lang/Integer;
      10: areturn

  private static java.lang.Integer lambda$initHUDComponents$1(net.minecraft.world.item.ItemStack);
    descriptor: (Lnet/minecraft/world/item/ItemStack;)Ljava/lang/Integer;
    Code:
       0: ldc_w         #1465               // String gunpowder
       3: aload_0
       4: invokestatic  #1459               // Method reliquary/util/NBTHelper.getInt:(Ljava/lang/String;Lnet/minecraft/world/item/ItemStack;)I
       7: invokestatic  #1409               // Method java/lang/Integer.valueOf:(I)Ljava/lang/Integer;
      10: areturn

  private static java.lang.Integer lambda$initHUDComponents$0(net.minecraft.world.item.ItemStack);
    descriptor: (Lnet/minecraft/world/item/ItemStack;)Ljava/lang/Integer;
    Code:
       0: ldc_w         #1467               // String charge
       3: aload_0
       4: invokestatic  #1459               // Method reliquary/util/NBTHelper.getInt:(Ljava/lang/String;Lnet/minecraft/world/item/ItemStack;)I
       7: invokestatic  #1409               // Method java/lang/Integer.valueOf:(I)Ljava/lang/Integer;
      10: areturn

  static {};
    descriptor: ()V
    Code:
       0: new           #1470               // class net/minecraft/client/KeyMapping
       3: dup
       4: ldc_w         #1472               // String keybind.reliquary.fortune_coin
       7: getstatic     #1478               // Field net/minecraftforge/client/settings/KeyConflictContext.UNIVERSAL:Lnet/minecraftforge/client/settings/KeyConflictContext;
      10: getstatic     #1482               // Field com/mojang/blaze3d/platform/InputConstants$Type.KEYSYM:Lcom/mojang/blaze3d/platform/InputConstants$Type;
      13: iconst_m1
      14: invokevirtual #1486               // Method com/mojang/blaze3d/platform/InputConstants$Type.m_84895_:(I)Lcom/mojang/blaze3d/platform/InputConstants$Key;
      17: ldc_w         #1488               // String keybind.reliquary.category
      20: invokespecial #1491               // Method net/minecraft/client/KeyMapping."<init>":(Ljava/lang/String;Lnet/minecraftforge/client/settings/IKeyConflictContext;Lcom/mojang/blaze3d/platform/InputConstants$Key;Ljava/lang/String;)V
      23: putstatic     #1376               // Field FORTUNE_COIN_TOGGLE_KEYBIND:Lnet/minecraft/client/KeyMapping;
      26: new           #1493               // class net/minecraft/client/model/geom/ModelLayerLocation
      29: dup
      30: new           #1240               // class net/minecraft/resources/ResourceLocation
      33: dup
      34: ldc_w         #1242               // String reliquary
      37: ldc_w         #1495               // String witch_hat
      40: invokespecial #1247               // Method net/minecraft/resources/ResourceLocation."<init>":(Ljava/lang/String;Ljava/lang/String;)V
      43: ldc_w         #1497               // String main
      46: invokespecial #1500               // Method net/minecraft/client/model/geom/ModelLayerLocation."<init>":(Lnet/minecraft/resources/ResourceLocation;Ljava/lang/String;)V
      49: putstatic     #278                // Field WITCH_HAT_LAYER:Lnet/minecraft/client/model/geom/ModelLayerLocation;
      52: new           #1493               // class net/minecraft/client/model/geom/ModelLayerLocation
      55: dup
      56: new           #1240               // class net/minecraft/resources/ResourceLocation
      59: dup
      60: ldc_w         #1242               // String reliquary
      63: ldc_w         #1502               // String mob_charm_belt
      66: invokespecial #1247               // Method net/minecraft/resources/ResourceLocation."<init>":(Ljava/lang/String;Ljava/lang/String;)V
      69: ldc_w         #1497               // String main
      72: invokespecial #1500               // Method net/minecraft/client/model/geom/ModelLayerLocation."<init>":(Lnet/minecraft/resources/ResourceLocation;Ljava/lang/String;)V
      75: putstatic     #297                // Field MOB_CHARM_BELT_LAYER:Lnet/minecraft/client/model/geom/ModelLayerLocation;
      78: invokestatic  #1508               // Method com/google/common/collect/Lists.newArrayList:()Ljava/util/ArrayList;
      81: putstatic     #418                // Field hudComponents:Ljava/util/List;
      84: return
}
