Compiled from "FortuneCoinItem.java"
public class xreliquary.items.FortuneCoinItem extends xreliquary.items.ItemBase implements xreliquary.api.IPedestalActionItem,xreliquary.items.util.IBaubleItem {
  private static final java.lang.String PREVENT_REMOTE_MOVEMENT;
    descriptor: Ljava/lang/String;

  private static final java.lang.String ALLOW_MACHINE_MOVEMENT;
    descriptor: Ljava/lang/String;

  private static final java.util.Set<xreliquary.items.FortuneCoinItem$IFortuneCoinPickupChecker> pickupCheckers;
    descriptor: Ljava/util/Set;

  public static void addFortuneCoinPickupChecker(xreliquary.items.FortuneCoinItem$IFortuneCoinPickupChecker);
    descriptor: (Lxreliquary/items/FortuneCoinItem$IFortuneCoinPickupChecker;)V
    Code:
       0: getstatic     #50                 // Field pickupCheckers:Ljava/util/Set;
       3: aload_0
       4: invokeinterface #56,  2           // InterfaceMethod java/util/Set.add:(Ljava/lang/Object;)Z
       9: pop
      10: return

  public xreliquary.items.FortuneCoinItem();
    descriptor: ()V
    Code:
       0: aload_0
       1: new           #17                 // class net/minecraft/item/Item$Properties
       4: dup
       5: invokespecial #62                 // Method net/minecraft/item/Item$Properties."<init>":()V
       8: iconst_1
       9: invokevirtual #66                 // Method net/minecraft/item/Item$Properties.func_200917_a:(I)Lnet/minecraft/item/Item$Properties;
      12: invokespecial #69                 // Method xreliquary/items/ItemBase."<init>":(Lnet/minecraft/item/Item$Properties;)V
      15: return

  public void onEquipped(java.lang.String, net.minecraft.entity.LivingEntity);
    descriptor: (Ljava/lang/String;Lnet/minecraft/entity/LivingEntity;)V
    Code:
       0: aload_2
       1: getfield      #79                 // Field net/minecraft/entity/LivingEntity.field_70170_p:Lnet/minecraft/world/World;
       4: getfield      #85                 // Field net/minecraft/world/World.field_72995_K:Z
       7: ifeq          38
      10: aload_2
      11: getstatic     #91                 // Field net/minecraft/util/SoundEvents.field_187604_bf:Lnet/minecraft/util/SoundEvent;
      14: ldc           #92                 // float 0.1f
      16: ldc           #93                 // float 0.5f
      18: aload_2
      19: getfield      #79                 // Field net/minecraft/entity/LivingEntity.field_70170_p:Lnet/minecraft/world/World;
      22: getfield      #97                 // Field net/minecraft/world/World.field_73012_v:Ljava/util/Random;
      25: invokestatic  #103                // Method xreliquary/util/RandHelper.getRandomMinusOneToOne:(Ljava/util/Random;)F
      28: ldc           #104                // float 0.7f
      30: fmul
      31: ldc           #105                // float 2.2f
      33: fadd
      34: fmul
      35: invokevirtual #109                // Method net/minecraft/entity/LivingEntity.func_184185_a:(Lnet/minecraft/util/SoundEvent;FF)V
      38: return

  public xreliquary.items.util.IBaubleItem$Type getBaubleType();
    descriptor: ()Lxreliquary/items/util/IBaubleItem$Type;
    Code:
       0: getstatic     #118                // Field xreliquary/items/util/IBaubleItem$Type.NECKLACE:Lxreliquary/items/util/IBaubleItem$Type;
       3: areturn

  public void onWornTick(net.minecraft.item.ItemStack, net.minecraft.entity.LivingEntity);
    descriptor: (Lnet/minecraft/item/ItemStack;Lnet/minecraft/entity/LivingEntity;)V
    Code:
       0: aload_0
       1: aload_1
       2: aload_2
       3: getfield      #79                 // Field net/minecraft/entity/LivingEntity.field_70170_p:Lnet/minecraft/world/World;
       6: aload_2
       7: iconst_0
       8: iconst_0
       9: invokevirtual #124                // Method func_77663_a:(Lnet/minecraft/item/ItemStack;Lnet/minecraft/world/World;Lnet/minecraft/entity/Entity;IZ)V
      12: return

  protected void addMoreInformation(net.minecraft.item.ItemStack, net.minecraft.world.World, java.util.List<net.minecraft.util.text.ITextComponent>);
    descriptor: (Lnet/minecraft/item/ItemStack;Lnet/minecraft/world/World;Ljava/util/List;)V
    Code:
       0: new           #136                // class java/lang/StringBuilder
       3: dup
       4: invokespecial #137                // Method java/lang/StringBuilder."<init>":()V
       7: aload_0
       8: invokevirtual #141                // Method func_77658_a:()Ljava/lang/String;
      11: invokevirtual #145                // Method java/lang/StringBuilder.append:(Ljava/lang/String;)Ljava/lang/StringBuilder;
      14: ldc           #147                // String .tooltip2
      16: invokevirtual #145                // Method java/lang/StringBuilder.append:(Ljava/lang/String;)Ljava/lang/StringBuilder;
      19: invokevirtual #150                // Method java/lang/StringBuilder.toString:()Ljava/lang/String;
      22: aload_3
      23: invokestatic  #156                // Method xreliquary/util/LanguageHelper.formatTooltip:(Ljava/lang/String;Ljava/util/List;)V
      26: return

  protected boolean hasMoreInformation(net.minecraft.item.ItemStack);
    descriptor: (Lnet/minecraft/item/ItemStack;)Z
    Code:
       0: iconst_1
       1: ireturn

  public net.minecraft.item.Rarity func_77613_e(net.minecraft.item.ItemStack);
    descriptor: (Lnet/minecraft/item/ItemStack;)Lnet/minecraft/item/Rarity;
    Code:
       0: getstatic     #170                // Field net/minecraft/item/Rarity.EPIC:Lnet/minecraft/item/Rarity;
       3: areturn

  public boolean func_77636_d(net.minecraft.item.ItemStack);
    descriptor: (Lnet/minecraft/item/ItemStack;)Z
    Code:
       0: aload_1
       1: invokestatic  #174                // Method isEnabled:(Lnet/minecraft/item/ItemStack;)Z
       4: ireturn

  public static boolean isEnabled(net.minecraft.item.ItemStack);
    descriptor: (Lnet/minecraft/item/ItemStack;)Z
    Code:
       0: ldc           #176                // String enabled
       2: aload_0
       3: invokestatic  #182                // Method xreliquary/util/NBTHelper.getBoolean:(Ljava/lang/String;Lnet/minecraft/item/ItemStack;)Z
       6: ireturn

  public void func_77663_a(net.minecraft.item.ItemStack, net.minecraft.world.World, net.minecraft.entity.Entity, int, boolean);
    descriptor: (Lnet/minecraft/item/ItemStack;Lnet/minecraft/world/World;Lnet/minecraft/entity/Entity;IZ)V
    Code:
       0: aload_2
       1: getfield      #85                 // Field net/minecraft/world/World.field_72995_K:Z
       4: ifne          20
       7: aload_2
       8: invokevirtual #186                // Method net/minecraft/world/World.func_82737_E:()J
      11: ldc2_w        #187                // long 2l
      14: lrem
      15: lconst_0
      16: lcmp
      17: ifeq          21
      20: return
      21: aload_1
      22: invokestatic  #174                // Method isEnabled:(Lnet/minecraft/item/ItemStack;)Z
      25: ifne          29
      28: return
      29: aconst_null
      30: astore        6
      32: aload_3
      33: instanceof    #190                // class net/minecraft/entity/player/PlayerEntity
      36: ifeq          45
      39: aload_3
      40: checkcast     #190                // class net/minecraft/entity/player/PlayerEntity
      43: astore        6
      45: aload         6
      47: ifnull        58
      50: aload         6
      52: invokevirtual #194                // Method net/minecraft/entity/player/PlayerEntity.func_175149_v:()Z
      55: ifeq          59
      58: return
      59: aload_0
      60: aload_2
      61: aload         6
      63: aload_0
      64: invokespecial #198                // Method getStandardPullDistance:()D
      67: invokespecial #202                // Method scanForEntitiesInRange:(Lnet/minecraft/world/World;Lnet/minecraft/entity/player/PlayerEntity;D)V
      70: return

  private void scanForEntitiesInRange(net.minecraft.world.World, net.minecraft.entity.player.PlayerEntity, double);
    descriptor: (Lnet/minecraft/world/World;Lnet/minecraft/entity/player/PlayerEntity;D)V
    Code:
       0: aload_0
       1: aload_1
       2: aload_2
       3: invokevirtual #212                // Method net/minecraft/entity/player/PlayerEntity.func_233580_cy_:()Lnet/minecraft/util/math/BlockPos;
       6: invokespecial #216                // Method getDisablePositions:(Lnet/minecraft/world/World;Lnet/minecraft/util/math/BlockPos;)Ljava/util/List;
       9: astore        5
      11: aload_1
      12: ldc           #218                // class net/minecraft/entity/item/ItemEntity
      14: aload_2
      15: invokevirtual #222                // Method net/minecraft/entity/player/PlayerEntity.func_174813_aQ:()Lnet/minecraft/util/math/AxisAlignedBB;
      18: dload_3
      19: invokevirtual #228                // Method net/minecraft/util/math/AxisAlignedBB.func_186662_g:(D)Lnet/minecraft/util/math/AxisAlignedBB;
      22: invokevirtual #232                // Method net/minecraft/world/World.func_217357_a:(Ljava/lang/Class;Lnet/minecraft/util/math/AxisAlignedBB;)Ljava/util/List;
      25: astore        6
      27: aload         6
      29: invokeinterface #238,  1          // InterfaceMethod java/util/List.iterator:()Ljava/util/Iterator;
      34: astore        7
      36: aload         7
      38: invokeinterface #243,  1          // InterfaceMethod java/util/Iterator.hasNext:()Z
      43: ifeq          116
      46: aload         7
      48: invokeinterface #247,  1          // InterfaceMethod java/util/Iterator.next:()Ljava/lang/Object;
      53: checkcast     #218                // class net/minecraft/entity/item/ItemEntity
      56: astore        8
      58: aload_0
      59: aload         8
      61: aload         5
      63: iconst_0
      64: invokespecial #251                // Method canPickupItem:(Lnet/minecraft/entity/item/ItemEntity;Ljava/util/List;Z)Z
      67: ifeq          113
      70: aload_0
      71: aload         8
      73: invokevirtual #255                // Method net/minecraft/entity/item/ItemEntity.func_92059_d:()Lnet/minecraft/item/ItemStack;
      76: aload_2
      77: invokespecial #259                // Method checkForRoom:(Lnet/minecraft/item/ItemStack;Lnet/minecraft/entity/player/PlayerEntity;)Z
      80: ifeq          113
      83: aload         8
      85: iconst_0
      86: invokevirtual #263                // Method net/minecraft/entity/item/ItemEntity.func_174867_a:(I)V
      89: aload_2
      90: aload         8
      92: invokevirtual #267                // Method net/minecraft/entity/player/PlayerEntity.func_70032_d:(Lnet/minecraft/entity/Entity;)F
      95: f2d
      96: ldc2_w        #268                // double 1.5d
      99: dcmpl
     100: iflt          113
     103: aload_0
     104: aload         8
     106: aload_2
     107: invokespecial #273                // Method teleportEntityToPlayer:(Lnet/minecraft/entity/Entity;Lnet/minecraft/entity/player/PlayerEntity;)V
     110: goto          116
     113: goto          36
     116: aload_1
     117: ldc_w         #275                // class net/minecraft/entity/item/ExperienceOrbEntity
     120: aload_2
     121: invokevirtual #222                // Method net/minecraft/entity/player/PlayerEntity.func_174813_aQ:()Lnet/minecraft/util/math/AxisAlignedBB;
     124: dload_3
     125: invokevirtual #228                // Method net/minecraft/util/math/AxisAlignedBB.func_186662_g:(D)Lnet/minecraft/util/math/AxisAlignedBB;
     128: invokevirtual #232                // Method net/minecraft/world/World.func_217357_a:(Ljava/lang/Class;Lnet/minecraft/util/math/AxisAlignedBB;)Ljava/util/List;
     131: astore        7
     133: aload         7
     135: invokeinterface #238,  1          // InterfaceMethod java/util/List.iterator:()Ljava/util/Iterator;
     140: astore        8
     142: aload         8
     144: invokeinterface #243,  1          // InterfaceMethod java/util/Iterator.hasNext:()Z
     149: ifeq          203
     152: aload         8
     154: invokeinterface #247,  1          // InterfaceMethod java/util/Iterator.next:()Ljava/lang/Object;
     159: checkcast     #275                // class net/minecraft/entity/item/ExperienceOrbEntity
     162: astore        9
     164: aload_2
     165: getfield      #278                // Field net/minecraft/entity/player/PlayerEntity.field_71090_bL:I
     168: ifle          176
     171: aload_2
     172: iconst_0
     173: putfield      #278                // Field net/minecraft/entity/player/PlayerEntity.field_71090_bL:I
     176: aload_2
     177: aload         9
     179: invokevirtual #267                // Method net/minecraft/entity/player/PlayerEntity.func_70032_d:(Lnet/minecraft/entity/Entity;)F
     182: f2d
     183: ldc2_w        #268                // double 1.5d
     186: dcmpl
     187: iflt          200
     190: aload_0
     191: aload         9
     193: aload_2
     194: invokespecial #273                // Method teleportEntityToPlayer:(Lnet/minecraft/entity/Entity;Lnet/minecraft/entity/player/PlayerEntity;)V
     197: goto          203
     200: goto          142
     203: return

  private boolean canPickupItem(net.minecraft.entity.item.ItemEntity, java.util.List<net.minecraft.util.math.BlockPos>, boolean);
    descriptor: (Lnet/minecraft/entity/item/ItemEntity;Ljava/util/List;Z)Z
    Code:
       0: aload_1
       1: invokevirtual #295                // Method net/minecraft/entity/item/ItemEntity.getPersistentData:()Lnet/minecraft/nbt/CompoundNBT;
       4: astore        4
       6: aload         4
       8: ldc           #40                 // String PreventRemoteMovement
      10: invokevirtual #301                // Method net/minecraft/nbt/CompoundNBT.func_74767_n:(Ljava/lang/String;)Z
      13: ifeq          32
      16: iload_3
      17: ifeq          30
      20: aload         4
      22: ldc           #43                 // String AllowMachineRemoteMovement
      24: invokevirtual #301                // Method net/minecraft/nbt/CompoundNBT.func_74767_n:(Ljava/lang/String;)Z
      27: ifne          32
      30: iconst_0
      31: ireturn
      32: aload_0
      33: aload_1
      34: aload_2
      35: invokespecial #305                // Method isInDisabledRange:(Lnet/minecraft/entity/item/ItemEntity;Ljava/util/List;)Z
      38: ifeq          43
      41: iconst_0
      42: ireturn
      43: getstatic     #50                 // Field pickupCheckers:Ljava/util/Set;
      46: invokeinterface #306,  1          // InterfaceMethod java/util/Set.iterator:()Ljava/util/Iterator;
      51: astore        5
      53: aload         5
      55: invokeinterface #243,  1          // InterfaceMethod java/util/Iterator.hasNext:()Z
      60: ifeq          91
      63: aload         5
      65: invokeinterface #247,  1          // InterfaceMethod java/util/Iterator.next:()Ljava/lang/Object;
      70: checkcast     #11                 // class xreliquary/items/FortuneCoinItem$IFortuneCoinPickupChecker
      73: astore        6
      75: aload         6
      77: aload_1
      78: invokeinterface #310,  2          // InterfaceMethod xreliquary/items/FortuneCoinItem$IFortuneCoinPickupChecker.canPickup:(Lnet/minecraft/entity/item/ItemEntity;)Z
      83: ifne          88
      86: iconst_0
      87: ireturn
      88: goto          53
      91: iconst_1
      92: ireturn

  private boolean isInDisabledRange(net.minecraft.entity.item.ItemEntity, java.util.List<net.minecraft.util.math.BlockPos>);
    descriptor: (Lnet/minecraft/entity/item/ItemEntity;Ljava/util/List;)Z
    Code:
       0: aload_2
       1: invokeinterface #238,  1          // InterfaceMethod java/util/List.iterator:()Ljava/util/Iterator;
       6: astore_3
       7: aload_3
       8: invokeinterface #243,  1          // InterfaceMethod java/util/Iterator.hasNext:()Z
      13: ifeq          92
      16: aload_3
      17: invokeinterface #247,  1          // InterfaceMethod java/util/Iterator.next:()Ljava/lang/Object;
      22: checkcast     #317                // class net/minecraft/util/math/BlockPos
      25: astore        4
      27: aload_1
      28: invokevirtual #318                // Method net/minecraft/entity/item/ItemEntity.func_233580_cy_:()Lnet/minecraft/util/math/BlockPos;
      31: invokevirtual #322                // Method net/minecraft/util/math/BlockPos.func_177958_n:()I
      34: aload         4
      36: invokevirtual #322                // Method net/minecraft/util/math/BlockPos.func_177958_n:()I
      39: isub
      40: invokestatic  #328                // Method java/lang/Math.abs:(I)I
      43: iconst_5
      44: if_icmpge     89
      47: aload_1
      48: invokevirtual #318                // Method net/minecraft/entity/item/ItemEntity.func_233580_cy_:()Lnet/minecraft/util/math/BlockPos;
      51: invokevirtual #331                // Method net/minecraft/util/math/BlockPos.func_177956_o:()I
      54: aload         4
      56: invokevirtual #331                // Method net/minecraft/util/math/BlockPos.func_177956_o:()I
      59: isub
      60: invokestatic  #328                // Method java/lang/Math.abs:(I)I
      63: iconst_5
      64: if_icmpge     89
      67: aload_1
      68: invokevirtual #318                // Method net/minecraft/entity/item/ItemEntity.func_233580_cy_:()Lnet/minecraft/util/math/BlockPos;
      71: invokevirtual #334                // Method net/minecraft/util/math/BlockPos.func_177952_p:()I
      74: aload         4
      76: invokevirtual #334                // Method net/minecraft/util/math/BlockPos.func_177952_p:()I
      79: isub
      80: invokestatic  #328                // Method java/lang/Math.abs:(I)I
      83: iconst_5
      84: if_icmpge     89
      87: iconst_1
      88: ireturn
      89: goto          7
      92: iconst_0
      93: ireturn

  private java.util.List<net.minecraft.util.math.BlockPos> getDisablePositions(net.minecraft.world.World, net.minecraft.util.math.BlockPos);
    descriptor: (Lnet/minecraft/world/World;Lnet/minecraft/util/math/BlockPos;)Ljava/util/List;
    Code:
       0: new           #339                // class java/util/ArrayList
       3: dup
       4: invokespecial #340                // Method java/util/ArrayList."<init>":()V
       7: astore_3
       8: aload_1
       9: invokevirtual #344                // Method net/minecraft/world/World.func_234923_W_:()Lnet/minecraft/util/RegistryKey;
      12: invokevirtual #350                // Method net/minecraft/util/RegistryKey.getRegistryName:()Lnet/minecraft/util/ResourceLocation;
      15: aload_2
      16: bipush        10
      18: invokestatic  #356                // Method xreliquary/pedestal/PedestalRegistry.getPositionsInRange:(Lnet/minecraft/util/ResourceLocation;Lnet/minecraft/util/math/BlockPos;I)Ljava/util/List;
      21: astore        4
      23: aload         4
      25: invokeinterface #238,  1          // InterfaceMethod java/util/List.iterator:()Ljava/util/Iterator;
      30: astore        5
      32: aload         5
      34: invokeinterface #243,  1          // InterfaceMethod java/util/Iterator.hasNext:()Z
      39: ifeq          130
      42: aload         5
      44: invokeinterface #247,  1          // InterfaceMethod java/util/Iterator.next:()Ljava/lang/Object;
      49: checkcast     #317                // class net/minecraft/util/math/BlockPos
      52: astore        6
      54: aload_1
      55: aload         6
      57: invokevirtual #360                // Method net/minecraft/world/World.func_175625_s:(Lnet/minecraft/util/math/BlockPos;)Lnet/minecraft/tileentity/TileEntity;
      60: astore        7
      62: aload         7
      64: instanceof    #362                // class xreliquary/blocks/tile/PedestalTileEntity
      67: ifeq          127
      70: aload         7
      72: checkcast     #362                // class xreliquary/blocks/tile/PedestalTileEntity
      75: astore        8
      77: aload         8
      79: invokevirtual #365                // Method xreliquary/blocks/tile/PedestalTileEntity.switchedOn:()Z
      82: ifeq          127
      85: aload         8
      87: iconst_0
      88: invokevirtual #369                // Method xreliquary/blocks/tile/PedestalTileEntity.func_70301_a:(I)Lnet/minecraft/item/ItemStack;
      91: astore        9
      93: aload         9
      95: invokevirtual #374                // Method net/minecraft/item/ItemStack.func_190926_b:()Z
      98: ifne          127
     101: aload         9
     103: invokevirtual #378                // Method net/minecraft/item/ItemStack.func_77973_b:()Lnet/minecraft/item/Item;
     106: aload_0
     107: if_acmpne     127
     110: aload         9
     112: invokestatic  #174                // Method isEnabled:(Lnet/minecraft/item/ItemStack;)Z
     115: ifne          127
     118: aload_3
     119: aload         6
     121: invokeinterface #379,  2          // InterfaceMethod java/util/List.add:(Ljava/lang/Object;)Z
     126: pop
     127: goto          32
     130: aload_3
     131: areturn

  private void teleportEntityToPlayer(net.minecraft.entity.Entity, net.minecraft.entity.player.PlayerEntity);
    descriptor: (Lnet/minecraft/entity/Entity;Lnet/minecraft/entity/player/PlayerEntity;)V
    Code:
       0: aload_2
       1: getfield      #387                // Field net/minecraft/entity/player/PlayerEntity.field_70170_p:Lnet/minecraft/world/World;
       4: getstatic     #393                // Field net/minecraft/particles/ParticleTypes.field_197625_r:Lnet/minecraft/particles/BasicParticleType;
       7: aload_1
       8: invokevirtual #398                // Method net/minecraft/entity/Entity.func_226277_ct_:()D
      11: ldc2_w        #399                // double 0.5d
      14: dadd
      15: aload_2
      16: getfield      #387                // Field net/minecraft/entity/player/PlayerEntity.field_70170_p:Lnet/minecraft/world/World;
      19: getfield      #97                 // Field net/minecraft/world/World.field_73012_v:Ljava/util/Random;
      22: invokevirtual #405                // Method java/util/Random.nextGaussian:()D
      25: ldc2_w        #406                // double 8.0d
      28: ddiv
      29: dadd
      30: aload_1
      31: invokevirtual #410                // Method net/minecraft/entity/Entity.func_226278_cu_:()D
      34: ldc2_w        #411                // double 0.2d
      37: dadd
      38: aload_1
      39: invokevirtual #415                // Method net/minecraft/entity/Entity.func_226281_cx_:()D
      42: ldc2_w        #399                // double 0.5d
      45: dadd
      46: aload_2
      47: getfield      #387                // Field net/minecraft/entity/player/PlayerEntity.field_70170_p:Lnet/minecraft/world/World;
      50: getfield      #97                 // Field net/minecraft/world/World.field_73012_v:Ljava/util/Random;
      53: invokevirtual #405                // Method java/util/Random.nextGaussian:()D
      56: ldc2_w        #406                // double 8.0d
      59: ddiv
      60: dadd
      61: ldc2_w        #416                // double 0.9d
      64: ldc2_w        #416                // double 0.9d
      67: dconst_0
      68: invokevirtual #421                // Method net/minecraft/world/World.func_195594_a:(Lnet/minecraft/particles/IParticleData;DDDDDD)V
      71: aload_2
      72: invokevirtual #425                // Method net/minecraft/entity/player/PlayerEntity.func_70040_Z:()Lnet/minecraft/util/math/vector/Vector3d;
      75: pop
      76: aload_2
      77: invokevirtual #426                // Method net/minecraft/entity/player/PlayerEntity.func_226277_ct_:()D
      80: aload_2
      81: invokevirtual #425                // Method net/minecraft/entity/player/PlayerEntity.func_70040_Z:()Lnet/minecraft/util/math/vector/Vector3d;
      84: getfield      #431                // Field net/minecraft/util/math/vector/Vector3d.field_72450_a:D
      87: ldc2_w        #411                // double 0.2d
      90: dmul
      91: dadd
      92: dstore_3
      93: aload_2
      94: invokevirtual #432                // Method net/minecraft/entity/player/PlayerEntity.func_226278_cu_:()D
      97: dstore        5
      99: aload_2
     100: invokevirtual #433                // Method net/minecraft/entity/player/PlayerEntity.func_226281_cx_:()D
     103: aload_2
     104: invokevirtual #425                // Method net/minecraft/entity/player/PlayerEntity.func_70040_Z:()Lnet/minecraft/util/math/vector/Vector3d;
     107: getfield      #436                // Field net/minecraft/util/math/vector/Vector3d.field_72449_c:D
     110: ldc2_w        #411                // double 0.2d
     113: dmul
     114: dadd
     115: dstore        7
     117: aload_1
     118: dload_3
     119: dload         5
     121: dload         7
     123: invokevirtual #440                // Method net/minecraft/entity/Entity.func_70107_b:(DDD)V
     126: return

  private boolean checkForRoom(net.minecraft.item.ItemStack, net.minecraft.entity.player.PlayerEntity);
    descriptor: (Lnet/minecraft/item/ItemStack;Lnet/minecraft/entity/player/PlayerEntity;)Z
    Code:
       0: aload_1
       1: invokevirtual #446                // Method net/minecraft/item/ItemStack.func_190916_E:()I
       4: istore_3
       5: aload_2
       6: getfield      #450                // Field net/minecraft/entity/player/PlayerEntity.field_71071_by:Lnet/minecraft/entity/player/PlayerInventory;
       9: getfield      #456                // Field net/minecraft/entity/player/PlayerInventory.field_70462_a:Lnet/minecraft/util/NonNullList;
      12: invokevirtual #459                // Method net/minecraft/util/NonNullList.iterator:()Ljava/util/Iterator;
      15: astore        4
      17: aload         4
      19: invokeinterface #243,  1          // InterfaceMethod java/util/Iterator.hasNext:()Z
      24: ifeq          161
      27: aload         4
      29: invokeinterface #247,  1          // InterfaceMethod java/util/Iterator.next:()Ljava/lang/Object;
      34: checkcast     #371                // class net/minecraft/item/ItemStack
      37: astore        5
      39: aload         5
      41: invokevirtual #374                // Method net/minecraft/item/ItemStack.func_190926_b:()Z
      44: ifeq          49
      47: iconst_1
      48: ireturn
      49: aload         5
      51: invokevirtual #378                // Method net/minecraft/item/ItemStack.func_77973_b:()Lnet/minecraft/item/Item;
      54: aload_1
      55: invokevirtual #378                // Method net/minecraft/item/ItemStack.func_77973_b:()Lnet/minecraft/item/Item;
      58: if_acmpne     107
      61: aload         5
      63: invokevirtual #462                // Method net/minecraft/item/ItemStack.func_77952_i:()I
      66: aload_1
      67: invokevirtual #462                // Method net/minecraft/item/ItemStack.func_77952_i:()I
      70: if_icmpne     107
      73: aload         5
      75: invokevirtual #446                // Method net/minecraft/item/ItemStack.func_190916_E:()I
      78: iload_3
      79: iadd
      80: aload         5
      82: invokevirtual #465                // Method net/minecraft/item/ItemStack.func_77976_d:()I
      85: if_icmpgt     90
      88: iconst_1
      89: ireturn
      90: iload_3
      91: aload         5
      93: invokevirtual #465                // Method net/minecraft/item/ItemStack.func_77976_d:()I
      96: aload         5
      98: invokevirtual #446                // Method net/minecraft/item/ItemStack.func_190916_E:()I
     101: isub
     102: isub
     103: istore_3
     104: goto          158
     107: aload         5
     109: invokevirtual #378                // Method net/minecraft/item/ItemStack.func_77973_b:()Lnet/minecraft/item/Item;
     112: getstatic     #471                // Field xreliquary/init/ModItems.VOID_TEAR:Lnet/minecraftforge/fml/RegistryObject;
     115: invokevirtual #477                // Method net/minecraftforge/fml/RegistryObject.get:()Lnet/minecraftforge/registries/IForgeRegistryEntry;
     118: if_acmpne     158
     121: getstatic     #471                // Field xreliquary/init/ModItems.VOID_TEAR:Lnet/minecraftforge/fml/RegistryObject;
     124: invokevirtual #477                // Method net/minecraftforge/fml/RegistryObject.get:()Lnet/minecraftforge/registries/IForgeRegistryEntry;
     127: checkcast     #479                // class xreliquary/items/VoidTearItem
     130: aload         5
     132: invokevirtual #480                // Method xreliquary/items/VoidTearItem.isEnabled:(Lnet/minecraft/item/ItemStack;)Z
     135: ifeq          158
     138: getstatic     #471                // Field xreliquary/init/ModItems.VOID_TEAR:Lnet/minecraftforge/fml/RegistryObject;
     141: invokevirtual #477                // Method net/minecraftforge/fml/RegistryObject.get:()Lnet/minecraftforge/registries/IForgeRegistryEntry;
     144: checkcast     #479                // class xreliquary/items/VoidTearItem
     147: aload_1
     148: aload         5
     150: invokevirtual #484                // Method xreliquary/items/VoidTearItem.canAbsorbStack:(Lnet/minecraft/item/ItemStack;Lnet/minecraft/item/ItemStack;)Z
     153: ifeq          158
     156: iconst_1
     157: ireturn
     158: goto          17
     161: iconst_0
     162: ireturn

  public void onUsingTick(net.minecraft.item.ItemStack, net.minecraft.entity.LivingEntity, int);
    descriptor: (Lnet/minecraft/item/ItemStack;Lnet/minecraft/entity/LivingEntity;I)V
    Code:
       0: aload_2
       1: instanceof    #190                // class net/minecraft/entity/player/PlayerEntity
       4: ifne          8
       7: return
       8: aload_2
       9: checkcast     #190                // class net/minecraft/entity/player/PlayerEntity
      12: astore        4
      14: aload_0
      15: aload         4
      17: getfield      #387                // Field net/minecraft/entity/player/PlayerEntity.field_70170_p:Lnet/minecraft/world/World;
      20: aload         4
      22: aload_0
      23: invokespecial #492                // Method getLongRangePullDistance:()D
      26: invokespecial #202                // Method scanForEntitiesInRange:(Lnet/minecraft/world/World;Lnet/minecraft/entity/player/PlayerEntity;D)V
      29: return

  private double getLongRangePullDistance();
    descriptor: ()D
    Code:
       0: getstatic     #497                // Field xreliquary/reference/Settings.COMMON:Lxreliquary/reference/Settings$Common;
       3: getfield      #500                // Field xreliquary/reference/Settings$Common.items:Lxreliquary/reference/Settings$Common$ItemSettings;
       6: getfield      #504                // Field xreliquary/reference/Settings$Common$ItemSettings.fortuneCoin:Lxreliquary/reference/Settings$Common$ItemSettings$FortuneCoinSettings;
       9: getfield      #508                // Field xreliquary/reference/Settings$Common$ItemSettings$FortuneCoinSettings.longRangePullDistance:Lnet/minecraftforge/common/ForgeConfigSpec$IntValue;
      12: invokevirtual #510                // Method net/minecraftforge/common/ForgeConfigSpec$IntValue.get:()Ljava/lang/Object;
      15: checkcast     #512                // class java/lang/Integer
      18: invokevirtual #515                // Method java/lang/Integer.intValue:()I
      21: i2d
      22: dreturn

  private double getStandardPullDistance();
    descriptor: ()D
    Code:
       0: getstatic     #497                // Field xreliquary/reference/Settings.COMMON:Lxreliquary/reference/Settings$Common;
       3: getfield      #500                // Field xreliquary/reference/Settings$Common.items:Lxreliquary/reference/Settings$Common$ItemSettings;
       6: getfield      #504                // Field xreliquary/reference/Settings$Common$ItemSettings.fortuneCoin:Lxreliquary/reference/Settings$Common$ItemSettings$FortuneCoinSettings;
       9: getfield      #518                // Field xreliquary/reference/Settings$Common$ItemSettings$FortuneCoinSettings.standardPullDistance:Lnet/minecraftforge/common/ForgeConfigSpec$IntValue;
      12: invokevirtual #510                // Method net/minecraftforge/common/ForgeConfigSpec$IntValue.get:()Ljava/lang/Object;
      15: checkcast     #512                // class java/lang/Integer
      18: invokevirtual #515                // Method java/lang/Integer.intValue:()I
      21: i2d
      22: dreturn

  public int func_77626_a(net.minecraft.item.ItemStack);
    descriptor: (Lnet/minecraft/item/ItemStack;)I
    Code:
       0: bipush        64
       2: ireturn

  public net.minecraft.item.UseAction func_77661_b(net.minecraft.item.ItemStack);
    descriptor: (Lnet/minecraft/item/ItemStack;)Lnet/minecraft/item/UseAction;
    Code:
       0: getstatic     #528                // Field net/minecraft/item/UseAction.BLOCK:Lnet/minecraft/item/UseAction;
       3: areturn

  public net.minecraft.util.ActionResult<net.minecraft.item.ItemStack> func_77659_a(net.minecraft.world.World, net.minecraft.entity.player.PlayerEntity, net.minecraft.util.Hand);
    descriptor: (Lnet/minecraft/world/World;Lnet/minecraft/entity/player/PlayerEntity;Lnet/minecraft/util/Hand;)Lnet/minecraft/util/ActionResult;
    Code:
       0: aload_2
       1: aload_3
       2: invokevirtual #535                // Method net/minecraft/entity/player/PlayerEntity.func_184586_b:(Lnet/minecraft/util/Hand;)Lnet/minecraft/item/ItemStack;
       5: astore        4
       7: aload_2
       8: invokevirtual #538                // Method net/minecraft/entity/player/PlayerEntity.func_225608_bj_:()Z
      11: ifeq          63
      14: aload_0
      15: aload         4
      17: invokevirtual #542                // Method toggle:(Lnet/minecraft/item/ItemStack;)V
      20: aload_2
      21: getfield      #387                // Field net/minecraft/entity/player/PlayerEntity.field_70170_p:Lnet/minecraft/world/World;
      24: aconst_null
      25: aload_2
      26: invokevirtual #212                // Method net/minecraft/entity/player/PlayerEntity.func_233580_cy_:()Lnet/minecraft/util/math/BlockPos;
      29: getstatic     #91                 // Field net/minecraft/util/SoundEvents.field_187604_bf:Lnet/minecraft/util/SoundEvent;
      32: getstatic     #548                // Field net/minecraft/util/SoundCategory.PLAYERS:Lnet/minecraft/util/SoundCategory;
      35: ldc           #92                 // float 0.1f
      37: ldc           #93                 // float 0.5f
      39: aload_2
      40: getfield      #387                // Field net/minecraft/entity/player/PlayerEntity.field_70170_p:Lnet/minecraft/world/World;
      43: getfield      #97                 // Field net/minecraft/world/World.field_73012_v:Ljava/util/Random;
      46: invokestatic  #103                // Method xreliquary/util/RandHelper.getRandomMinusOneToOne:(Ljava/util/Random;)F
      49: ldc           #104                // float 0.7f
      51: fmul
      52: ldc_w         #549                // float 1.8f
      55: fadd
      56: fmul
      57: invokevirtual #553                // Method net/minecraft/world/World.func_184133_a:(Lnet/minecraft/entity/player/PlayerEntity;Lnet/minecraft/util/math/BlockPos;Lnet/minecraft/util/SoundEvent;Lnet/minecraft/util/SoundCategory;FF)V
      60: goto          68
      63: aload_2
      64: aload_3
      65: invokevirtual #557                // Method net/minecraft/entity/player/PlayerEntity.func_184598_c:(Lnet/minecraft/util/Hand;)V
      68: new           #559                // class net/minecraft/util/ActionResult
      71: dup
      72: getstatic     #565                // Field net/minecraft/util/ActionResultType.SUCCESS:Lnet/minecraft/util/ActionResultType;
      75: aload         4
      77: invokespecial #568                // Method net/minecraft/util/ActionResult."<init>":(Lnet/minecraft/util/ActionResultType;Ljava/lang/Object;)V
      80: areturn

  public void update(net.minecraft.item.ItemStack, xreliquary.api.IPedestal);
    descriptor: (Lnet/minecraft/item/ItemStack;Lxreliquary/api/IPedestal;)V
    Code:
       0: aload_2
       1: invokeinterface #578,  1          // InterfaceMethod xreliquary/api/IPedestal.getTheWorld:()Lnet/minecraft/world/World;
       6: astore_3
       7: aload_3
       8: getfield      #85                 // Field net/minecraft/world/World.field_72995_K:Z
      11: ifeq          15
      14: return
      15: aload_1
      16: invokestatic  #174                // Method isEnabled:(Lnet/minecraft/item/ItemStack;)Z
      19: ifeq          46
      22: aload_2
      23: invokeinterface #581,  1          // InterfaceMethod xreliquary/api/IPedestal.getBlockPos:()Lnet/minecraft/util/math/BlockPos;
      28: astore        4
      30: aload_0
      31: aload_2
      32: aload_3
      33: aload         4
      35: invokespecial #585                // Method pickupItems:(Lxreliquary/api/IPedestal;Lnet/minecraft/world/World;Lnet/minecraft/util/math/BlockPos;)V
      38: aload_0
      39: aload_2
      40: aload_3
      41: aload         4
      43: invokespecial #588                // Method pickupXp:(Lxreliquary/api/IPedestal;Lnet/minecraft/world/World;Lnet/minecraft/util/math/BlockPos;)V
      46: return

  private void pickupItems(xreliquary.api.IPedestal, net.minecraft.world.World, net.minecraft.util.math.BlockPos);
    descriptor: (Lxreliquary/api/IPedestal;Lnet/minecraft/world/World;Lnet/minecraft/util/math/BlockPos;)V
    Code:
       0: aload_0
       1: aload_2
       2: aload_3
       3: invokespecial #216                // Method getDisablePositions:(Lnet/minecraft/world/World;Lnet/minecraft/util/math/BlockPos;)Ljava/util/List;
       6: astore        4
       8: aload_2
       9: ldc           #218                // class net/minecraft/entity/item/ItemEntity
      11: new           #224                // class net/minecraft/util/math/AxisAlignedBB
      14: dup
      15: aload_3
      16: invokespecial #592                // Method net/minecraft/util/math/AxisAlignedBB."<init>":(Lnet/minecraft/util/math/BlockPos;)V
      19: aload_0
      20: invokespecial #198                // Method getStandardPullDistance:()D
      23: invokevirtual #228                // Method net/minecraft/util/math/AxisAlignedBB.func_186662_g:(D)Lnet/minecraft/util/math/AxisAlignedBB;
      26: invokevirtual #232                // Method net/minecraft/world/World.func_217357_a:(Ljava/lang/Class;Lnet/minecraft/util/math/AxisAlignedBB;)Ljava/util/List;
      29: astore        5
      31: aload         5
      33: invokeinterface #238,  1          // InterfaceMethod java/util/List.iterator:()Ljava/util/Iterator;
      38: astore        6
      40: aload         6
      42: invokeinterface #243,  1          // InterfaceMethod java/util/Iterator.hasNext:()Z
      47: ifeq          147
      50: aload         6
      52: invokeinterface #247,  1          // InterfaceMethod java/util/Iterator.next:()Ljava/lang/Object;
      57: checkcast     #218                // class net/minecraft/entity/item/ItemEntity
      60: astore        7
      62: aload_0
      63: aload         7
      65: aload         4
      67: iconst_1
      68: invokespecial #251                // Method canPickupItem:(Lnet/minecraft/entity/item/ItemEntity;Ljava/util/List;Z)Z
      71: ifne          77
      74: goto          40
      77: aload_1
      78: aload         7
      80: invokevirtual #255                // Method net/minecraft/entity/item/ItemEntity.func_92059_d:()Lnet/minecraft/item/ItemStack;
      83: invokevirtual #595                // Method net/minecraft/item/ItemStack.func_77946_l:()Lnet/minecraft/item/ItemStack;
      86: invokeinterface #598,  2          // InterfaceMethod xreliquary/api/IPedestal.addToConnectedInventory:(Lnet/minecraft/item/ItemStack;)I
      91: istore        8
      93: iload         8
      95: ifle          136
      98: aload         7
     100: invokevirtual #255                // Method net/minecraft/entity/item/ItemEntity.func_92059_d:()Lnet/minecraft/item/ItemStack;
     103: aload         7
     105: invokevirtual #255                // Method net/minecraft/entity/item/ItemEntity.func_92059_d:()Lnet/minecraft/item/ItemStack;
     108: invokevirtual #446                // Method net/minecraft/item/ItemStack.func_190916_E:()I
     111: iload         8
     113: isub
     114: invokevirtual #601                // Method net/minecraft/item/ItemStack.func_190920_e:(I)V
     117: aload         7
     119: invokevirtual #255                // Method net/minecraft/entity/item/ItemEntity.func_92059_d:()Lnet/minecraft/item/ItemStack;
     122: invokevirtual #446                // Method net/minecraft/item/ItemStack.func_190916_E:()I
     125: ifgt          144
     128: aload         7
     130: invokevirtual #604                // Method net/minecraft/entity/item/ItemEntity.func_70106_y:()V
     133: goto          144
     136: aload_1
     137: bipush        20
     139: invokeinterface #607,  2          // InterfaceMethod xreliquary/api/IPedestal.setActionCoolDown:(I)V
     144: goto          40
     147: return

  private void pickupXp(xreliquary.api.IPedestal, net.minecraft.world.World, net.minecraft.util.math.BlockPos);
    descriptor: (Lxreliquary/api/IPedestal;Lnet/minecraft/world/World;Lnet/minecraft/util/math/BlockPos;)V
    Code:
       0: aload_2
       1: ldc_w         #275                // class net/minecraft/entity/item/ExperienceOrbEntity
       4: new           #224                // class net/minecraft/util/math/AxisAlignedBB
       7: dup
       8: aload_3
       9: invokespecial #592                // Method net/minecraft/util/math/AxisAlignedBB."<init>":(Lnet/minecraft/util/math/BlockPos;)V
      12: aload_0
      13: invokespecial #198                // Method getStandardPullDistance:()D
      16: invokevirtual #228                // Method net/minecraft/util/math/AxisAlignedBB.func_186662_g:(D)Lnet/minecraft/util/math/AxisAlignedBB;
      19: invokevirtual #232                // Method net/minecraft/world/World.func_217357_a:(Ljava/lang/Class;Lnet/minecraft/util/math/AxisAlignedBB;)Ljava/util/List;
      22: astore        4
      24: aload         4
      26: invokeinterface #238,  1          // InterfaceMethod java/util/List.iterator:()Ljava/util/Iterator;
      31: astore        5
      33: aload         5
      35: invokeinterface #243,  1          // InterfaceMethod java/util/Iterator.hasNext:()Z
      40: ifeq          158
      43: aload         5
      45: invokeinterface #247,  1          // InterfaceMethod java/util/Iterator.next:()Ljava/lang/Object;
      50: checkcast     #275                // class net/minecraft/entity/item/ExperienceOrbEntity
      53: astore        6
      55: aload         6
      57: getfield      #613                // Field net/minecraft/entity/item/ExperienceOrbEntity.field_70530_e:I
      60: invokestatic  #618                // Method xreliquary/util/XpHelper.experienceToLiquid:(I)I
      63: istore        7
      65: aload_1
      66: new           #620                // class net/minecraftforge/fluids/FluidStack
      69: dup
      70: getstatic     #625                // Field xreliquary/init/ModFluids.XP_JUICE_STILL:Lnet/minecraftforge/fml/RegistryObject;
      73: invokevirtual #477                // Method net/minecraftforge/fml/RegistryObject.get:()Lnet/minecraftforge/registries/IForgeRegistryEntry;
      76: checkcast     #627                // class net/minecraft/fluid/Fluid
      79: iload         7
      81: invokespecial #630                // Method net/minecraftforge/fluids/FluidStack."<init>":(Lnet/minecraft/fluid/Fluid;I)V
      84: invokeinterface #634,  2          // InterfaceMethod xreliquary/api/IPedestal.fillConnectedTank:(Lnet/minecraftforge/fluids/FluidStack;)I
      89: istore        8
      91: iload         8
      93: ifle          147
      96: aload         6
      98: invokevirtual #635                // Method net/minecraft/entity/item/ExperienceOrbEntity.func_70106_y:()V
     101: iload         7
     103: iload         8
     105: if_icmple     155
     108: aload_2
     109: new           #275                // class net/minecraft/entity/item/ExperienceOrbEntity
     112: dup
     113: aload_2
     114: aload_3
     115: invokevirtual #322                // Method net/minecraft/util/math/BlockPos.func_177958_n:()I
     118: i2d
     119: aload_3
     120: invokevirtual #331                // Method net/minecraft/util/math/BlockPos.func_177956_o:()I
     123: i2d
     124: aload_3
     125: invokevirtual #334                // Method net/minecraft/util/math/BlockPos.func_177952_p:()I
     128: i2d
     129: iload         7
     131: iload         8
     133: isub
     134: invokestatic  #638                // Method xreliquary/util/XpHelper.liquidToExperience:(I)I
     137: invokespecial #641                // Method net/minecraft/entity/item/ExperienceOrbEntity."<init>":(Lnet/minecraft/world/World;DDDI)V
     140: invokevirtual #645                // Method net/minecraft/world/World.func_217376_c:(Lnet/minecraft/entity/Entity;)Z
     143: pop
     144: goto          155
     147: aload_1
     148: bipush        20
     150: invokeinterface #607,  2          // InterfaceMethod xreliquary/api/IPedestal.setActionCoolDown:(I)V
     155: goto          33
     158: return

  public void onRemoved(net.minecraft.item.ItemStack, xreliquary.api.IPedestal);
    descriptor: (Lnet/minecraft/item/ItemStack;Lxreliquary/api/IPedestal;)V
    Code:
       0: return

  public void stop(net.minecraft.item.ItemStack, xreliquary.api.IPedestal);
    descriptor: (Lnet/minecraft/item/ItemStack;Lxreliquary/api/IPedestal;)V
    Code:
       0: return

  public void toggle(net.minecraft.item.ItemStack);
    descriptor: (Lnet/minecraft/item/ItemStack;)V
    Code:
       0: ldc           #176                // String enabled
       2: aload_1
       3: aload_1
       4: invokestatic  #174                // Method isEnabled:(Lnet/minecraft/item/ItemStack;)Z
       7: ifne          14
      10: iconst_1
      11: goto          15
      14: iconst_0
      15: invokestatic  #655                // Method xreliquary/util/NBTHelper.putBoolean:(Ljava/lang/String;Lnet/minecraft/item/ItemStack;Z)V
      18: return

  static {};
    descriptor: ()V
    Code:
       0: new           #658                // class java/util/HashSet
       3: dup
       4: invokespecial #659                // Method java/util/HashSet."<init>":()V
       7: putstatic     #50                 // Field pickupCheckers:Ljava/util/Set;
      10: return
}
