Compiled from "GuiVacuumChest.java"
public class crazypants.enderio.machines.machine.vacuum.chest.GuiVacuumChest extends crazypants.enderio.base.gui.GuiContainerBaseEIO<crazypants.enderio.machines.machine.vacuum.chest.TileVacuumChest> implements crazypants.enderio.machines.machine.vacuum.chest.ContainerVacuumChestProxy {
  private static final int RANGE_LEFT;
    descriptor: I

  private static final int RANGE_TOP;
    descriptor: I

  private static final int RANGE_WIDTH;
    descriptor: I

  private static final int FILTER_LEFT;
    descriptor: I

  private static final int FILTER_TOP;
    descriptor: I

  private static final int ID_RANGE_UP;
    descriptor: I

  private static final int ID_RANGE_DOWN;
    descriptor: I

  private static final int ID_REDSTONE;
    descriptor: I

  private static final int ID_OPEN_FILTER;
    descriptor: I

  private final com.enderio.core.client.gui.widget.GuiToolTip rangeTooltip;
    descriptor: Lcom/enderio/core/client/gui/widget/GuiToolTip;

  private final com.enderio.core.client.gui.button.MultiIconButton rangeUpB;
    descriptor: Lcom/enderio/core/client/gui/button/MultiIconButton;

  private final com.enderio.core.client.gui.button.MultiIconButton rangeDownB;
    descriptor: Lcom/enderio/core/client/gui/button/MultiIconButton;

  private final crazypants.enderio.base.gui.RedstoneModeButton<crazypants.enderio.machines.machine.vacuum.chest.TileVacuumChest> rsB;
    descriptor: Lcrazypants/enderio/base/gui/RedstoneModeButton;

  private final java.lang.String headerChest;
    descriptor: Ljava/lang/String;

  private final java.lang.String headerFilter;
    descriptor: Ljava/lang/String;

  private final java.lang.String headerRange;
    descriptor: Ljava/lang/String;

  private final java.lang.String headerInventory;
    descriptor: Ljava/lang/String;

  private final com.enderio.core.client.gui.button.ToggleButton showRangeB;
    descriptor: Lcom/enderio/core/client/gui/button/ToggleButton;

  private final com.enderio.core.client.gui.button.IconButton openFilterGuiB;
    descriptor: Lcom/enderio/core/client/gui/button/IconButton;

  public crazypants.enderio.machines.machine.vacuum.chest.GuiVacuumChest(net.minecraft.entity.player.InventoryPlayer, crazypants.enderio.machines.machine.vacuum.chest.TileVacuumChest);
    descriptor: (Lnet/minecraft/entity/player/InventoryPlayer;Lcrazypants/enderio/machines/machine/vacuum/chest/TileVacuumChest;)V
    Code:
       0: aload_0
       1: aload_2
       2: new           #53                 // class crazypants/enderio/machines/machine/vacuum/chest/ContainerVacuumChest
       5: dup
       6: aload_1
       7: aload_2
       8: invokespecial #55                 // Method crazypants/enderio/machines/machine/vacuum/chest/ContainerVacuumChest."<init>":(Lnet/minecraft/entity/player/InventoryPlayer;Lcrazypants/enderio/machines/machine/vacuum/chest/TileVacuumChest;)V
      11: iconst_1
      12: anewarray     #57                 // class java/lang/String
      15: dup
      16: iconst_0
      17: ldc           #59                 // String vacuum_chest
      19: aastore
      20: invokespecial #62                 // Method crazypants/enderio/base/gui/GuiContainerBaseEIO."<init>":(Ljava/lang/Object;Lnet/minecraft/inventory/Container;[Ljava/lang/String;)V
      23: aload_0
      24: sipush        206
      27: putfield      #65                 // Field field_147000_g:I
      30: sipush        145
      33: istore_3
      34: bipush        86
      36: istore        4
      38: aload_0
      39: new           #67                 // class com/enderio/core/client/gui/widget/GuiToolTip
      42: dup
      43: new           #69                 // class java/awt/Rectangle
      46: dup
      47: iload_3
      48: iload         4
      50: bipush        16
      52: bipush        16
      54: invokespecial #72                 // Method java/awt/Rectangle."<init>":(IIII)V
      57: iconst_1
      58: anewarray     #57                 // class java/lang/String
      61: dup
      62: iconst_0
      63: getstatic     #78                 // Field crazypants/enderio/machines/lang/Lang.GUI_VACUUM_RANGE_TOOLTIP:Lcrazypants/enderio/machines/lang/Lang;
      66: invokevirtual #82                 // Method crazypants/enderio/machines/lang/Lang.get:()Ljava/lang/String;
      69: aastore
      70: invokespecial #85                 // Method com/enderio/core/client/gui/widget/GuiToolTip."<init>":(Ljava/awt/Rectangle;[Ljava/lang/String;)V
      73: putfield      #87                 // Field rangeTooltip:Lcom/enderio/core/client/gui/widget/GuiToolTip;
      76: iinc          3, 16
      79: aload_0
      80: aload_0
      81: sipush        4711
      84: iload_3
      85: iload         4
      87: invokestatic  #93                 // Method com/enderio/core/client/gui/button/MultiIconButton.createAddButton:(Lcom/enderio/core/api/client/gui/IGuiScreen;III)Lcom/enderio/core/client/gui/button/MultiIconButton;
      90: putfield      #95                 // Field rangeUpB:Lcom/enderio/core/client/gui/button/MultiIconButton;
      93: iinc          4, 8
      96: aload_0
      97: aload_0
      98: sipush        4712
     101: iload_3
     102: iload         4
     104: invokestatic  #98                 // Method com/enderio/core/client/gui/button/MultiIconButton.createMinusButton:(Lcom/enderio/core/api/client/gui/IGuiScreen;III)Lcom/enderio/core/client/gui/button/MultiIconButton;
     107: putfield      #100                // Field rangeDownB:Lcom/enderio/core/client/gui/button/MultiIconButton;
     110: aload_0
     111: getfield      #103                // Field field_146999_f:I
     114: bipush        16
     116: isub
     117: bipush        7
     119: isub
     120: istore_3
     121: bipush        104
     123: istore        4
     125: aload_0
     126: new           #105                // class crazypants/enderio/base/gui/RedstoneModeButton
     129: dup
     130: aload_0
     131: sipush        4715
     134: iload_3
     135: iload         4
     137: aload_2
     138: invokespecial #108                // Method crazypants/enderio/base/gui/RedstoneModeButton."<init>":(Lcom/enderio/core/api/client/gui/IGuiScreen;IIILnet/minecraft/tileentity/TileEntity;)V
     141: putfield      #110                // Field rsB:Lcrazypants/enderio/base/gui/RedstoneModeButton;
     144: iinc          3, -18
     147: aload_0
     148: new           #112                // class com/enderio/core/client/gui/button/ToggleButton
     151: dup
     152: aload_0
     153: iconst_m1
     154: iload_3
     155: iload         4
     157: getstatic     #118                // Field crazypants/enderio/base/gui/IconEIO.SHOW_RANGE:Lcrazypants/enderio/base/gui/IconEIO;
     160: getstatic     #121                // Field crazypants/enderio/base/gui/IconEIO.HIDE_RANGE:Lcrazypants/enderio/base/gui/IconEIO;
     163: invokespecial #124                // Method com/enderio/core/client/gui/button/ToggleButton."<init>":(Lcom/enderio/core/api/client/gui/IGuiScreen;IIILcom/enderio/core/api/client/render/IWidgetIcon;Lcom/enderio/core/api/client/render/IWidgetIcon;)V
     166: putfield      #126                // Field showRangeB:Lcom/enderio/core/client/gui/button/ToggleButton;
     169: aload_0
     170: getfield      #126                // Field showRangeB:Lcom/enderio/core/client/gui/button/ToggleButton;
     173: bipush        16
     175: bipush        16
     177: invokevirtual #130                // Method com/enderio/core/client/gui/button/ToggleButton.setSize:(II)V
     180: aload_0
     181: new           #12                 // class crazypants/enderio/machines/machine/vacuum/chest/GuiVacuumChest$1
     184: dup
     185: aload_0
     186: aload_0
     187: getfield      #126                // Field showRangeB:Lcom/enderio/core/client/gui/button/ToggleButton;
     190: invokevirtual #134                // Method com/enderio/core/client/gui/button/ToggleButton.getBounds:()Ljava/awt/Rectangle;
     193: iconst_1
     194: anewarray     #57                 // class java/lang/String
     197: dup
     198: iconst_0
     199: ldc           #136                // String null
     201: aastore
     202: invokespecial #139                // Method crazypants/enderio/machines/machine/vacuum/chest/GuiVacuumChest$1."<init>":(Lcrazypants/enderio/machines/machine/vacuum/chest/GuiVacuumChest;Ljava/awt/Rectangle;[Ljava/lang/String;)V
     205: invokevirtual #143                // Method addToolTip:(Lcom/enderio/core/client/gui/widget/GuiToolTip;)V
     208: aload_0
     209: new           #145                // class com/enderio/core/client/gui/button/IconButton
     212: dup
     213: aload_0
     214: sipush        4713
     217: bipush        29
     219: bipush        85
     221: getstatic     #148                // Field crazypants/enderio/base/gui/IconEIO.GEAR_LIGHT:Lcrazypants/enderio/base/gui/IconEIO;
     224: invokespecial #151                // Method com/enderio/core/client/gui/button/IconButton."<init>":(Lcom/enderio/core/api/client/gui/IGuiScreen;IIILcom/enderio/core/api/client/render/IWidgetIcon;)V
     227: putfield      #153                // Field openFilterGuiB:Lcom/enderio/core/client/gui/button/IconButton;
     230: aload_0
     231: getfield      #153                // Field openFilterGuiB:Lcom/enderio/core/client/gui/button/IconButton;
     234: iconst_1
     235: anewarray     #57                 // class java/lang/String
     238: dup
     239: iconst_0
     240: getstatic     #159                // Field crazypants/enderio/base/lang/Lang.GUI_EDIT_ITEM_FILTER:Lcrazypants/enderio/base/lang/Lang;
     243: invokevirtual #160                // Method crazypants/enderio/base/lang/Lang.get:()Ljava/lang/String;
     246: aastore
     247: invokevirtual #164                // Method com/enderio/core/client/gui/button/IconButton.setToolTip:([Ljava/lang/String;)V
     250: aload_0
     251: getstatic     #167                // Field crazypants/enderio/machines/lang/Lang.GUI_VACUUM_CHEST:Lcrazypants/enderio/machines/lang/Lang;
     254: invokevirtual #82                 // Method crazypants/enderio/machines/lang/Lang.get:()Ljava/lang/String;
     257: putfield      #169                // Field headerChest:Ljava/lang/String;
     260: aload_0
     261: getstatic     #172                // Field crazypants/enderio/machines/lang/Lang.GUI_VACUUM_FILTER:Lcrazypants/enderio/machines/lang/Lang;
     264: invokevirtual #82                 // Method crazypants/enderio/machines/lang/Lang.get:()Ljava/lang/String;
     267: putfield      #174                // Field headerFilter:Ljava/lang/String;
     270: aload_0
     271: getstatic     #177                // Field crazypants/enderio/machines/lang/Lang.GUI_VACUUM_RANGE:Lcrazypants/enderio/machines/lang/Lang;
     274: invokevirtual #82                 // Method crazypants/enderio/machines/lang/Lang.get:()Ljava/lang/String;
     277: putfield      #179                // Field headerRange:Ljava/lang/String;
     280: aload_0
     281: getstatic     #182                // Field crazypants/enderio/machines/lang/Lang.GUI_VACUUM_INVENTORY:Lcrazypants/enderio/machines/lang/Lang;
     284: invokevirtual #82                 // Method crazypants/enderio/machines/lang/Lang.get:()Ljava/lang/String;
     287: putfield      #184                // Field headerInventory:Ljava/lang/String;
     290: aload_0
     291: getfield      #188                // Field field_147002_h:Lnet/minecraft/inventory/Container;
     294: checkcast     #53                 // class crazypants/enderio/machines/machine/vacuum/chest/ContainerVacuumChest
     297: new           #10                 // class crazypants/enderio/machines/machine/vacuum/chest/GuiVacuumChest$2
     300: dup
     301: aload_0
     302: invokespecial #191                // Method crazypants/enderio/machines/machine/vacuum/chest/GuiVacuumChest$2."<init>":(Lcrazypants/enderio/machines/machine/vacuum/chest/GuiVacuumChest;)V
     305: invokevirtual #195                // Method crazypants/enderio/machines/machine/vacuum/chest/ContainerVacuumChest.setFilterChangedCB:(Ljava/lang/Runnable;)V
     308: return

  public void func_73866_w_();
    descriptor: ()V
    Code:
       0: aload_0
       1: invokespecial #207                // Method crazypants/enderio/base/gui/GuiContainerBaseEIO.func_73866_w_:()V
       4: aload_0
       5: getfield      #153                // Field openFilterGuiB:Lcom/enderio/core/client/gui/button/IconButton;
       8: invokevirtual #210                // Method com/enderio/core/client/gui/button/IconButton.onGuiInit:()V
      11: aload_0
      12: getfield      #95                 // Field rangeUpB:Lcom/enderio/core/client/gui/button/MultiIconButton;
      15: invokevirtual #211                // Method com/enderio/core/client/gui/button/MultiIconButton.onGuiInit:()V
      18: aload_0
      19: getfield      #100                // Field rangeDownB:Lcom/enderio/core/client/gui/button/MultiIconButton;
      22: invokevirtual #211                // Method com/enderio/core/client/gui/button/MultiIconButton.onGuiInit:()V
      25: aload_0
      26: getfield      #110                // Field rsB:Lcrazypants/enderio/base/gui/RedstoneModeButton;
      29: invokevirtual #212                // Method crazypants/enderio/base/gui/RedstoneModeButton.onGuiInit:()V
      32: aload_0
      33: aload_0
      34: getfield      #87                 // Field rangeTooltip:Lcom/enderio/core/client/gui/widget/GuiToolTip;
      37: invokevirtual #143                // Method addToolTip:(Lcom/enderio/core/client/gui/widget/GuiToolTip;)V
      40: aload_0
      41: getfield      #126                // Field showRangeB:Lcom/enderio/core/client/gui/button/ToggleButton;
      44: invokevirtual #213                // Method com/enderio/core/client/gui/button/ToggleButton.onGuiInit:()V
      47: aload_0
      48: getfield      #126                // Field showRangeB:Lcom/enderio/core/client/gui/button/ToggleButton;
      51: aload_0
      52: invokevirtual #217                // Method getOwner:()Ljava/lang/Object;
      55: checkcast     #219                // class crazypants/enderio/machines/machine/vacuum/chest/TileVacuumChest
      58: invokevirtual #223                // Method crazypants/enderio/machines/machine/vacuum/chest/TileVacuumChest.isShowingRange:()Z
      61: invokevirtual #227                // Method com/enderio/core/client/gui/button/ToggleButton.setSelected:(Z)Lcom/enderio/core/client/gui/button/ToggleButton;
      64: pop
      65: aload_0
      66: invokevirtual #230                // Method filterChanged:()V
      69: aload_0
      70: getfield      #188                // Field field_147002_h:Lnet/minecraft/inventory/Container;
      73: checkcast     #53                 // class crazypants/enderio/machines/machine/vacuum/chest/ContainerVacuumChest
      76: aload_0
      77: invokevirtual #234                // Method getGhostSlotHandler:()Lcom/enderio/core/client/gui/GhostSlotHandler;
      80: invokevirtual #240                // Method com/enderio/core/client/gui/GhostSlotHandler.getGhostSlots:()Lcom/enderio/core/common/util/NNList;
      83: invokevirtual #244                // Method crazypants/enderio/machines/machine/vacuum/chest/ContainerVacuumChest.createGhostSlots:(Ljava/util/List;)V
      86: return

  public void func_146284_a(net.minecraft.client.gui.GuiButton);
    descriptor: (Lnet/minecraft/client/gui/GuiButton;)V
    Code:
       0: aload_1
       1: aload_0
       2: getfield      #126                // Field showRangeB:Lcom/enderio/core/client/gui/button/ToggleButton;
       5: if_acmpne     26
       8: aload_0
       9: invokevirtual #217                // Method getOwner:()Ljava/lang/Object;
      12: checkcast     #219                // class crazypants/enderio/machines/machine/vacuum/chest/TileVacuumChest
      15: aload_0
      16: getfield      #126                // Field showRangeB:Lcom/enderio/core/client/gui/button/ToggleButton;
      19: invokevirtual #249                // Method com/enderio/core/client/gui/button/ToggleButton.isSelected:()Z
      22: invokevirtual #253                // Method crazypants/enderio/machines/machine/vacuum/chest/TileVacuumChest.setShowRange:(Z)V
      25: return
      26: aload_1
      27: getfield      #258                // Field net/minecraft/client/gui/GuiButton.field_146127_k:I
      30: tableswitch   { // 4711 to 4713
                  4711: 56
                  4712: 76
                  4713: 96
               default: 101
          }
      56: aload_0
      57: aload_0
      58: invokevirtual #217                // Method getOwner:()Ljava/lang/Object;
      61: checkcast     #219                // class crazypants/enderio/machines/machine/vacuum/chest/TileVacuumChest
      64: invokevirtual #262                // Method crazypants/enderio/machines/machine/vacuum/chest/TileVacuumChest.getRange:()F
      67: fconst_1
      68: fadd
      69: f2i
      70: invokespecial #266                // Method setRange:(I)V
      73: goto          101
      76: aload_0
      77: aload_0
      78: invokevirtual #217                // Method getOwner:()Ljava/lang/Object;
      81: checkcast     #219                // class crazypants/enderio/machines/machine/vacuum/chest/TileVacuumChest
      84: invokevirtual #262                // Method crazypants/enderio/machines/machine/vacuum/chest/TileVacuumChest.getRange:()F
      87: fconst_1
      88: fsub
      89: f2i
      90: invokespecial #266                // Method setRange:(I)V
      93: goto          101
      96: aload_0
      97: iconst_0
      98: invokevirtual #269                // Method doOpenFilterGui:(I)V
     101: return

  private void setRange(int);
    descriptor: (I)V
    Code:
       0: getstatic     #277                // Field crazypants/enderio/machines/network/PacketHandler.INSTANCE:Lcom/enderio/core/common/network/ThreadedNetworkWrapper;
       3: aload_0
       4: invokevirtual #217                // Method getOwner:()Ljava/lang/Object;
       7: checkcast     #219                // class crazypants/enderio/machines/machine/vacuum/chest/TileVacuumChest
      10: iload_1
      11: invokestatic  #282                // Method crazypants/enderio/machines/machine/vacuum/chest/PacketVaccumChest.setRange:(Lcrazypants/enderio/machines/machine/vacuum/chest/TileVacuumChest;I)Lcrazypants/enderio/machines/machine/vacuum/chest/PacketVaccumChest;
      14: invokevirtual #288                // Method com/enderio/core/common/network/ThreadedNetworkWrapper.sendToServer:(Lnet/minecraftforge/fml/common/network/simpleimpl/IMessage;)V
      17: return

  void filterChanged();
    descriptor: ()V
    Code:
       0: aload_0
       1: invokevirtual #217                // Method getOwner:()Ljava/lang/Object;
       4: checkcast     #219                // class crazypants/enderio/machines/machine/vacuum/chest/TileVacuumChest
       7: invokevirtual #292                // Method crazypants/enderio/machines/machine/vacuum/chest/TileVacuumChest.hasItemFilter:()Z
      10: ifeq          24
      13: aload_0
      14: getfield      #153                // Field openFilterGuiB:Lcom/enderio/core/client/gui/button/IconButton;
      17: iconst_1
      18: invokevirtual #295                // Method com/enderio/core/client/gui/button/IconButton.setIsVisible:(Z)V
      21: goto          32
      24: aload_0
      25: getfield      #153                // Field openFilterGuiB:Lcom/enderio/core/client/gui/button/IconButton;
      28: iconst_0
      29: invokevirtual #295                // Method com/enderio/core/client/gui/button/IconButton.setIsVisible:(Z)V
      32: return

  protected void func_146976_a(float, int, int);
    descriptor: (FII)V
    Code:
       0: fconst_1
       1: fconst_1
       2: fconst_1
       3: fconst_1
       4: invokestatic  #303                // Method net/minecraft/client/renderer/GlStateManager.func_179131_c:(FFFF)V
       7: aload_0
       8: invokevirtual #306                // Method bindGuiTexture:()V
      11: aload_0
      12: getfield      #309                // Field field_146294_l:I
      15: aload_0
      16: getfield      #103                // Field field_146999_f:I
      19: isub
      20: iconst_2
      21: idiv
      22: istore        4
      24: aload_0
      25: getfield      #312                // Field field_146295_m:I
      28: aload_0
      29: getfield      #65                 // Field field_147000_g:I
      32: isub
      33: iconst_2
      34: idiv
      35: istore        5
      37: aload_0
      38: iload         4
      40: iload         5
      42: iconst_0
      43: iconst_0
      44: aload_0
      45: getfield      #103                // Field field_146999_f:I
      48: aload_0
      49: getfield      #65                 // Field field_147000_g:I
      52: invokevirtual #316                // Method func_73729_b:(IIIIII)V
      55: ldc_w         #317                // int 4210752
      58: istore        6
      60: aload_0
      61: invokevirtual #321                // Method getFontRenderer:()Lnet/minecraft/client/gui/FontRenderer;
      64: astore        7
      66: aload         7
      68: aload_0
      69: getfield      #169                // Field headerChest:Ljava/lang/String;
      72: iload         4
      74: bipush        7
      76: iadd
      77: iload         5
      79: bipush        6
      81: iadd
      82: iload         6
      84: invokevirtual #327                // Method net/minecraft/client/gui/FontRenderer.func_78276_b:(Ljava/lang/String;III)I
      87: pop
      88: aload         7
      90: aload_0
      91: getfield      #174                // Field headerFilter:Ljava/lang/String;
      94: iload         4
      96: bipush        7
      98: iadd
      99: iload         5
     101: bipush        74
     103: iadd
     104: iload         6
     106: invokevirtual #327                // Method net/minecraft/client/gui/FontRenderer.func_78276_b:(Ljava/lang/String;III)I
     109: pop
     110: aload         7
     112: aload_0
     113: getfield      #179                // Field headerRange:Ljava/lang/String;
     116: iload         4
     118: aload_0
     119: getfield      #103                // Field field_146999_f:I
     122: iadd
     123: bipush        7
     125: isub
     126: aload         7
     128: aload_0
     129: getfield      #179                // Field headerRange:Ljava/lang/String;
     132: invokevirtual #331                // Method net/minecraft/client/gui/FontRenderer.func_78256_a:(Ljava/lang/String;)I
     135: isub
     136: iload         5
     138: bipush        74
     140: iadd
     141: iload         6
     143: invokevirtual #327                // Method net/minecraft/client/gui/FontRenderer.func_78276_b:(Ljava/lang/String;III)I
     146: pop
     147: aload         7
     149: aload_0
     150: getfield      #184                // Field headerInventory:Ljava/lang/String;
     153: iload         4
     155: bipush        7
     157: iadd
     158: iload         5
     160: bipush        111
     162: iadd
     163: iload         6
     165: invokevirtual #327                // Method net/minecraft/client/gui/FontRenderer.func_78276_b:(Ljava/lang/String;III)I
     168: pop
     169: getstatic     #335                // Field crazypants/enderio/base/gui/IconEIO.map:Lcom/enderio/core/api/client/render/IWidgetMap;
     172: getstatic     #341                // Field com/enderio/core/client/render/EnderWidget.BUTTON_DOWN:Lcom/enderio/core/client/render/EnderWidget;
     175: iload         4
     177: sipush        145
     180: iadd
     181: i2d
     182: iload         5
     184: bipush        86
     186: iadd
     187: i2d
     188: ldc2_w        #342                // double 16.0d
     191: ldc2_w        #342                // double 16.0d
     194: dconst_0
     195: iconst_1
     196: invokeinterface #349,  13         // InterfaceMethod com/enderio/core/api/client/render/IWidgetMap.render:(Lcom/enderio/core/api/client/render/IWidgetIcon;DDDDDZ)V
     201: aload_0
     202: invokevirtual #217                // Method getOwner:()Ljava/lang/Object;
     205: checkcast     #219                // class crazypants/enderio/machines/machine/vacuum/chest/TileVacuumChest
     208: invokevirtual #262                // Method crazypants/enderio/machines/machine/vacuum/chest/TileVacuumChest.getRange:()F
     211: f2i
     212: invokestatic  #355                // Method java/lang/Integer.toString:(I)Ljava/lang/String;
     215: astore        8
     217: aload         7
     219: aload         8
     221: invokevirtual #331                // Method net/minecraft/client/gui/FontRenderer.func_78256_a:(Ljava/lang/String;)I
     224: istore        9
     226: aload         7
     228: aload         8
     230: iload         4
     232: sipush        145
     235: iadd
     236: bipush        16
     238: iadd
     239: iload         9
     241: isub
     242: iconst_5
     243: isub
     244: iload         5
     246: bipush        86
     248: iadd
     249: iconst_5
     250: iadd
     251: getstatic     #361                // Field java/awt/Color.black:Ljava/awt/Color;
     254: invokestatic  #367                // Method com/enderio/core/client/render/ColorUtil.getRGB:(Ljava/awt/Color;)I
     257: invokevirtual #327                // Method net/minecraft/client/gui/FontRenderer.func_78276_b:(Ljava/lang/String;III)I
     260: pop
     261: aload_0
     262: fload_1
     263: iload_2
     264: iload_3
     265: invokespecial #369                // Method crazypants/enderio/base/gui/GuiContainerBaseEIO.func_146976_a:(FII)V
     268: return

  static com.enderio.core.client.gui.button.ToggleButton access$000(crazypants.enderio.machines.machine.vacuum.chest.GuiVacuumChest);
    descriptor: (Lcrazypants/enderio/machines/machine/vacuum/chest/GuiVacuumChest;)Lcom/enderio/core/client/gui/button/ToggleButton;
    Code:
       0: aload_0
       1: getfield      #126                // Field showRangeB:Lcom/enderio/core/client/gui/button/ToggleButton;
       4: areturn
}
