Compiled from "PacketFortuneCoinTogglePressed.java"
public final class xreliquary.network.PacketFortuneCoinTogglePressed$InventoryType extends java.lang.Enum<xreliquary.network.PacketFortuneCoinTogglePressed$InventoryType> {
  public static final xreliquary.network.PacketFortuneCoinTogglePressed$InventoryType MAIN;
    descriptor: Lxreliquary/network/PacketFortuneCoinTogglePressed$InventoryType;

  public static final xreliquary.network.PacketFortuneCoinTogglePressed$InventoryType OFF_HAND;
    descriptor: Lxreliquary/network/PacketFortuneCoinTogglePressed$InventoryType;

  public static final xreliquary.network.PacketFortuneCoinTogglePressed$InventoryType CURIOS;
    descriptor: Lxreliquary/network/PacketFortuneCoinTogglePressed$InventoryType;

  private static final xreliquary.network.PacketFortuneCoinTogglePressed$InventoryType[] $VALUES;
    descriptor: [Lxreliquary/network/PacketFortuneCoinTogglePressed$InventoryType;

  public static xreliquary.network.PacketFortuneCoinTogglePressed$InventoryType[] values();
    descriptor: ()[Lxreliquary/network/PacketFortuneCoinTogglePressed$InventoryType;
    Code:
       0: getstatic     #19                 // Field $VALUES:[Lxreliquary/network/PacketFortuneCoinTogglePressed$InventoryType;
       3: invokevirtual #24                 // Method "[Lxreliquary/network/PacketFortuneCoinTogglePressed$InventoryType;".clone:()Ljava/lang/Object;
       6: checkcast     #20                 // class "[Lxreliquary/network/PacketFortuneCoinTogglePressed$InventoryType;"
       9: areturn

  public static xreliquary.network.PacketFortuneCoinTogglePressed$InventoryType valueOf(java.lang.String);
    descriptor: (Ljava/lang/String;)Lxreliquary/network/PacketFortuneCoinTogglePressed$InventoryType;
    Code:
       0: ldc           #2                  // class xreliquary/network/PacketFortuneCoinTogglePressed$InventoryType
       2: aload_0
       3: invokestatic  #29                 // Method java/lang/Enum.valueOf:(Ljava/lang/Class;Ljava/lang/String;)Ljava/lang/Enum;
       6: checkcast     #2                  // class xreliquary/network/PacketFortuneCoinTogglePressed$InventoryType
       9: areturn

  private xreliquary.network.PacketFortuneCoinTogglePressed$InventoryType();
    descriptor: (Ljava/lang/String;I)V
    Code:
       0: aload_0
       1: aload_1
       2: iload_2
       3: invokespecial #36                 // Method java/lang/Enum."<init>":(Ljava/lang/String;I)V
       6: return

  static {};
    descriptor: ()V
    Code:
       0: new           #2                  // class xreliquary/network/PacketFortuneCoinTogglePressed$InventoryType
       3: dup
       4: ldc           #39                 // String MAIN
       6: iconst_0
       7: invokespecial #40                 // Method "<init>":(Ljava/lang/String;I)V
      10: putstatic     #42                 // Field MAIN:Lxreliquary/network/PacketFortuneCoinTogglePressed$InventoryType;
      13: new           #2                  // class xreliquary/network/PacketFortuneCoinTogglePressed$InventoryType
      16: dup
      17: ldc           #43                 // String OFF_HAND
      19: iconst_1
      20: invokespecial #40                 // Method "<init>":(Ljava/lang/String;I)V
      23: putstatic     #45                 // Field OFF_HAND:Lxreliquary/network/PacketFortuneCoinTogglePressed$InventoryType;
      26: new           #2                  // class xreliquary/network/PacketFortuneCoinTogglePressed$InventoryType
      29: dup
      30: ldc           #46                 // String CURIOS
      32: iconst_2
      33: invokespecial #40                 // Method "<init>":(Ljava/lang/String;I)V
      36: putstatic     #48                 // Field CURIOS:Lxreliquary/network/PacketFortuneCoinTogglePressed$InventoryType;
      39: iconst_3
      40: anewarray     #2                  // class xreliquary/network/PacketFortuneCoinTogglePressed$InventoryType
      43: dup
      44: iconst_0
      45: getstatic     #42                 // Field MAIN:Lxreliquary/network/PacketFortuneCoinTogglePressed$InventoryType;
      48: aastore
      49: dup
      50: iconst_1
      51: getstatic     #45                 // Field OFF_HAND:Lxreliquary/network/PacketFortuneCoinTogglePressed$InventoryType;
      54: aastore
      55: dup
      56: iconst_2
      57: getstatic     #48                 // Field CURIOS:Lxreliquary/network/PacketFortuneCoinTogglePressed$InventoryType;
      60: aastore
      61: putstatic     #19                 // Field $VALUES:[Lxreliquary/network/PacketFortuneCoinTogglePressed$InventoryType;
      64: return
}
