Compiled from "Main.java"
public class cool.furry.mc.forge.projectexpansion.Main {
  public static final java.lang.String MOD_ID;
    descriptor: Ljava/lang/String;

  public static net.minecraft.world.item.CreativeModeTab tab;
    descriptor: Lnet/minecraft/world/item/CreativeModeTab;

  public static final org.apache.logging.log4j.Logger Logger;
    descriptor: Lorg/apache/logging/log4j/Logger;

  public cool.furry.mc.forge.projectexpansion.Main();
    descriptor: ()V
    Code:
       0: aload_0
       1: invokespecial #39                 // Method java/lang/Object."<init>":()V
       4: new           #10                 // class cool/furry/mc/forge/projectexpansion/Main$1
       7: dup
       8: aload_0
       9: ldc           #31                 // String projectexpansion
      11: invokespecial #42                 // Method cool/furry/mc/forge/projectexpansion/Main$1."<init>":(Lcool/furry/mc/forge/projectexpansion/Main;Ljava/lang/String;)V
      14: putstatic     #44                 // Field tab:Lnet/minecraft/world/item/CreativeModeTab;
      17: invokestatic  #49                 // Method cool/furry/mc/forge/projectexpansion/net/PacketHandler.register:()V
      20: invokestatic  #55                 // Method net/minecraftforge/fml/javafmlmod/FMLJavaModLoadingContext.get:()Lnet/minecraftforge/fml/javafmlmod/FMLJavaModLoadingContext;
      23: invokevirtual #59                 // Method net/minecraftforge/fml/javafmlmod/FMLJavaModLoadingContext.getModEventBus:()Lnet/minecraftforge/eventbus/api/IEventBus;
      26: astore_1
      27: getstatic     #65                 // Field cool/furry/mc/forge/projectexpansion/registries/BlockEntityTypes.Registry:Lnet/minecraftforge/registries/DeferredRegister;
      30: aload_1
      31: invokevirtual #70                 // Method net/minecraftforge/registries/DeferredRegister.register:(Lnet/minecraftforge/eventbus/api/IEventBus;)V
      34: getstatic     #73                 // Field cool/furry/mc/forge/projectexpansion/registries/Blocks.Registry:Lnet/minecraftforge/registries/DeferredRegister;
      37: aload_1
      38: invokevirtual #70                 // Method net/minecraftforge/registries/DeferredRegister.register:(Lnet/minecraftforge/eventbus/api/IEventBus;)V
      41: getstatic     #76                 // Field cool/furry/mc/forge/projectexpansion/registries/Enchantments.Registry:Lnet/minecraftforge/registries/DeferredRegister;
      44: aload_1
      45: invokevirtual #70                 // Method net/minecraftforge/registries/DeferredRegister.register:(Lnet/minecraftforge/eventbus/api/IEventBus;)V
      48: getstatic     #79                 // Field cool/furry/mc/forge/projectexpansion/registries/Items.Registry:Lnet/minecraftforge/registries/DeferredRegister;
      51: aload_1
      52: invokevirtual #70                 // Method net/minecraftforge/registries/DeferredRegister.register:(Lnet/minecraftforge/eventbus/api/IEventBus;)V
      55: getstatic     #82                 // Field cool/furry/mc/forge/projectexpansion/registries/SoundEvents.Registry:Lnet/minecraftforge/registries/DeferredRegister;
      58: aload_1
      59: invokevirtual #70                 // Method net/minecraftforge/registries/DeferredRegister.register:(Lnet/minecraftforge/eventbus/api/IEventBus;)V
      62: getstatic     #85                 // Field cool/furry/mc/forge/projectexpansion/registries/MenuTypes.Registry:Lnet/minecraftforge/registries/DeferredRegister;
      65: aload_1
      66: invokevirtual #70                 // Method net/minecraftforge/registries/DeferredRegister.register:(Lnet/minecraftforge/eventbus/api/IEventBus;)V
      69: getstatic     #91                 // Field net/minecraftforge/common/MinecraftForge.EVENT_BUS:Lnet/minecraftforge/eventbus/api/IEventBus;
      72: aload_0
      73: invokedynamic #110,  0            // InvokeDynamic #0:accept:(Lcool/furry/mc/forge/projectexpansion/Main;)Ljava/util/function/Consumer;
      78: invokeinterface #116,  2          // InterfaceMethod net/minecraftforge/eventbus/api/IEventBus.addListener:(Ljava/util/function/Consumer;)V
      83: aload_1
      84: aload_0
      85: invokedynamic #123,  0            // InvokeDynamic #1:accept:(Lcool/furry/mc/forge/projectexpansion/Main;)Ljava/util/function/Consumer;
      90: invokeinterface #116,  2          // InterfaceMethod net/minecraftforge/eventbus/api/IEventBus.addListener:(Ljava/util/function/Consumer;)V
      95: invokestatic  #128                // Method net/minecraftforge/fml/ModLoadingContext.get:()Lnet/minecraftforge/fml/ModLoadingContext;
      98: getstatic     #132                // Field net/minecraftforge/fml/config/ModConfig$Type.COMMON:Lnet/minecraftforge/fml/config/ModConfig$Type;
     101: getstatic     #138                // Field cool/furry/mc/forge/projectexpansion/config/Config.Spec:Lnet/minecraftforge/common/ForgeConfigSpec;
     104: ldc           #140                // String project-expansion.toml
     106: invokevirtual #144                // Method net/minecraftforge/fml/ModLoadingContext.registerConfig:(Lnet/minecraftforge/fml/config/ModConfig$Type;Lnet/minecraftforge/fml/config/IConfigSpec;Ljava/lang/String;)V
     109: invokestatic  #149                // Method cool/furry/mc/forge/projectexpansion/util/Fuel.registerAll:()V
     112: invokestatic  #152                // Method cool/furry/mc/forge/projectexpansion/util/Matter.registerAll:()V
     115: invokestatic  #155                // Method cool/furry/mc/forge/projectexpansion/util/Star.registerAll:()V
     118: invokestatic  #158                // Method cool/furry/mc/forge/projectexpansion/util/AdvancedAlchemicalChest.register:()V
     121: return

  private void registerCapabilities(net.minecraftforge.common.capabilities.RegisterCapabilitiesEvent);
    descriptor: (Lnet/minecraftforge/common/capabilities/RegisterCapabilitiesEvent;)V
    Code:
       0: aload_1
       1: ldc           #163                // class cool/furry/mc/forge/projectexpansion/capability/IAlchemicalBookLocationsProvider
       3: invokevirtual #168                // Method net/minecraftforge/common/capabilities/RegisterCapabilitiesEvent.register:(Ljava/lang/Class;)V
       6: return

  private void serverTick(net.minecraftforge.event.TickEvent$ServerTickEvent);
    descriptor: (Lnet/minecraftforge/event/TickEvent$ServerTickEvent;)V
    Code:
       0: aload_1
       1: getfield      #174                // Field net/minecraftforge/event/TickEvent$ServerTickEvent.phase:Lnet/minecraftforge/event/TickEvent$Phase;
       4: getstatic     #177                // Field net/minecraftforge/event/TickEvent$Phase.END:Lnet/minecraftforge/event/TickEvent$Phase;
       7: if_acmpeq     11
      10: return
      11: invokestatic  #182                // Method cool/furry/mc/forge/projectexpansion/util/AlchemicalCollectionCollector.process:()V
      14: invokestatic  #188                // Method net/minecraftforge/server/ServerLifecycleHooks.getCurrentServer:()Lnet/minecraft/server/MinecraftServer;
      17: invokevirtual #194                // Method net/minecraft/server/MinecraftServer.m_6846_:()Lnet/minecraft/server/players/PlayerList;
      20: invokevirtual #200                // Method net/minecraft/server/players/PlayerList.m_11314_:()Ljava/util/List;
      23: invokeinterface #206,  1          // InterfaceMethod java/util/List.iterator:()Ljava/util/Iterator;
      28: astore_2
      29: aload_2
      30: invokeinterface #212,  1          // InterfaceMethod java/util/Iterator.hasNext:()Z
      35: ifeq          173
      38: aload_2
      39: invokeinterface #216,  1          // InterfaceMethod java/util/Iterator.next:()Ljava/lang/Object;
      44: checkcast     #218                // class net/minecraft/server/level/ServerPlayer
      47: astore_3
      48: iconst_0
      49: istore        4
      51: iload         4
      53: aload_3
      54: invokevirtual #222                // Method net/minecraft/server/level/ServerPlayer.m_150109_:()Lnet/minecraft/world/entity/player/Inventory;
      57: invokevirtual #228                // Method net/minecraft/world/entity/player/Inventory.m_6643_:()I
      60: if_icmpge     170
      63: aload_3
      64: invokevirtual #222                // Method net/minecraft/server/level/ServerPlayer.m_150109_:()Lnet/minecraft/world/entity/player/Inventory;
      67: iload         4
      69: invokevirtual #232                // Method net/minecraft/world/entity/player/Inventory.m_8020_:(I)Lnet/minecraft/world/item/ItemStack;
      72: astore        5
      74: aload         5
      76: invokevirtual #238                // Method net/minecraft/world/item/ItemStack.m_41720_:()Lnet/minecraft/world/item/Item;
      79: getstatic     #242                // Field cool/furry/mc/forge/projectexpansion/registries/Items.INFINITE_FUEL:Lnet/minecraftforge/registries/RegistryObject;
      82: invokevirtual #246                // Method net/minecraftforge/registries/RegistryObject.get:()Ljava/lang/Object;
      85: invokevirtual #250                // Method java/lang/Object.equals:(Ljava/lang/Object;)Z
      88: ifeq          109
      91: aload         5
      93: invokevirtual #254                // Method net/minecraft/world/item/ItemStack.m_41784_:()Lnet/minecraft/nbt/CompoundTag;
      96: getstatic     #259                // Field cool/furry/mc/forge/projectexpansion/util/TagNames.OWNER:Ljava/lang/String;
      99: aload_3
     100: invokevirtual #263                // Method net/minecraft/server/level/ServerPlayer.m_142081_:()Ljava/util/UUID;
     103: invokevirtual #269                // Method net/minecraft/nbt/CompoundTag.m_128362_:(Ljava/lang/String;Ljava/util/UUID;)V
     106: goto          164
     109: getstatic     #272                // Field cool/furry/mc/forge/projectexpansion/registries/Enchantments.ALCHEMICAL_COLLECTION:Lnet/minecraftforge/registries/RegistryObject;
     112: invokevirtual #246                // Method net/minecraftforge/registries/RegistryObject.get:()Ljava/lang/Object;
     115: checkcast     #274                // class net/minecraft/world/item/enchantment/Enchantment
     118: aload         5
     120: invokestatic  #280                // Method net/minecraft/world/item/enchantment/EnchantmentHelper.m_44843_:(Lnet/minecraft/world/item/enchantment/Enchantment;Lnet/minecraft/world/item/ItemStack;)I
     123: ifle          130
     126: iconst_1
     127: goto          131
     130: iconst_0
     131: istore        6
     133: iload         6
     135: ifeq          164
     138: aload         5
     140: invokevirtual #254                // Method net/minecraft/world/item/ItemStack.m_41784_:()Lnet/minecraft/nbt/CompoundTag;
     143: getstatic     #283                // Field cool/furry/mc/forge/projectexpansion/util/TagNames.ALCHEMICAL_COLLECTION_ENABLED:Ljava/lang/String;
     146: invokevirtual #287                // Method net/minecraft/nbt/CompoundTag.m_128441_:(Ljava/lang/String;)Z
     149: ifne          164
     152: aload         5
     154: invokevirtual #254                // Method net/minecraft/world/item/ItemStack.m_41784_:()Lnet/minecraft/nbt/CompoundTag;
     157: getstatic     #283                // Field cool/furry/mc/forge/projectexpansion/util/TagNames.ALCHEMICAL_COLLECTION_ENABLED:Ljava/lang/String;
     160: iconst_1
     161: invokevirtual #291                // Method net/minecraft/nbt/CompoundTag.m_128379_:(Ljava/lang/String;Z)V
     164: iinc          4, 1
     167: goto          51
     170: goto          29
     173: return

  public static net.minecraft.resources.ResourceLocation rl(java.lang.String);
    descriptor: (Ljava/lang/String;)Lnet/minecraft/resources/ResourceLocation;
    Code:
       0: new           #304                // class net/minecraft/resources/ResourceLocation
       3: dup
       4: ldc           #31                 // String projectexpansion
       6: aload_0
       7: invokespecial #307                // Method net/minecraft/resources/ResourceLocation."<init>":(Ljava/lang/String;Ljava/lang/String;)V
      10: areturn

  static {};
    descriptor: ()V
    Code:
       0: invokestatic  #315                // Method org/apache/logging/log4j/LogManager.getLogger:()Lorg/apache/logging/log4j/Logger;
       3: putstatic     #317                // Field Logger:Lorg/apache/logging/log4j/Logger;
       6: return
}
