Compiled from "BlockAdvancedAlchemicalChest.java"
public class cool.furry.mc.forge.projectexpansion.block.BlockAdvancedAlchemicalChest extends net.minecraft.world.level.block.HorizontalDirectionalBlock implements net.minecraft.world.level.block.EntityBlock,net.minecraft.world.level.block.SimpleWaterloggedBlock,cool.furry.mc.forge.projectexpansion.util.IHasColor {
  public static final net.minecraft.world.level.block.state.properties.BooleanProperty WATERLOGGED;
    descriptor: Lnet/minecraft/world/level/block/state/properties/BooleanProperty;

  private static final net.minecraft.world.phys.shapes.VoxelShape SHAPE;
    descriptor: Lnet/minecraft/world/phys/shapes/VoxelShape;

  private final net.minecraft.world.item.DyeColor color;
    descriptor: Lnet/minecraft/world/item/DyeColor;

  public cool.furry.mc.forge.projectexpansion.block.BlockAdvancedAlchemicalChest(net.minecraft.world.item.DyeColor);
    descriptor: (Lnet/minecraft/world/item/DyeColor;)V
    Code:
       0: aload_0
       1: getstatic     #53                 // Field net/minecraft/world/level/material/Material.f_76278_:Lnet/minecraft/world/level/material/Material;
       4: invokestatic  #57                 // Method net/minecraft/world/level/block/state/BlockBehaviour$Properties.m_60939_:(Lnet/minecraft/world/level/material/Material;)Lnet/minecraft/world/level/block/state/BlockBehaviour$Properties;
       7: invokevirtual #61                 // Method net/minecraft/world/level/block/state/BlockBehaviour$Properties.m_60999_:()Lnet/minecraft/world/level/block/state/BlockBehaviour$Properties;
      10: ldc           #62                 // float 10.0f
      12: ldc           #63                 // float 3600000.0f
      14: invokevirtual #67                 // Method net/minecraft/world/level/block/state/BlockBehaviour$Properties.m_60913_:(FF)Lnet/minecraft/world/level/block/state/BlockBehaviour$Properties;
      17: invokedynamic #86,  0             // InvokeDynamic #0:applyAsInt:()Ljava/util/function/ToIntFunction;
      22: invokevirtual #90                 // Method net/minecraft/world/level/block/state/BlockBehaviour$Properties.m_60953_:(Ljava/util/function/ToIntFunction;)Lnet/minecraft/world/level/block/state/BlockBehaviour$Properties;
      25: invokespecial #93                 // Method net/minecraft/world/level/block/HorizontalDirectionalBlock."<init>":(Lnet/minecraft/world/level/block/state/BlockBehaviour$Properties;)V
      28: aload_0
      29: aload_0
      30: getfield      #97                 // Field f_49792_:Lnet/minecraft/world/level/block/state/StateDefinition;
      33: invokevirtual #101                // Method net/minecraft/world/level/block/state/StateDefinition.m_61090_:()Lnet/minecraft/world/level/block/state/StateHolder;
      36: checkcast     #103                // class net/minecraft/world/level/block/state/BlockState
      39: getstatic     #107                // Field f_54117_:Lnet/minecraft/world/level/block/state/properties/DirectionProperty;
      42: getstatic     #113                // Field net/minecraft/core/Direction.NORTH:Lnet/minecraft/core/Direction;
      45: invokevirtual #117                // Method net/minecraft/world/level/block/state/BlockState.m_61124_:(Lnet/minecraft/world/level/block/state/properties/Property;Ljava/lang/Comparable;)Ljava/lang/Object;
      48: checkcast     #103                // class net/minecraft/world/level/block/state/BlockState
      51: getstatic     #119                // Field WATERLOGGED:Lnet/minecraft/world/level/block/state/properties/BooleanProperty;
      54: getstatic     #125                // Field java/lang/Boolean.FALSE:Ljava/lang/Boolean;
      57: invokevirtual #117                // Method net/minecraft/world/level/block/state/BlockState.m_61124_:(Lnet/minecraft/world/level/block/state/properties/Property;Ljava/lang/Comparable;)Ljava/lang/Object;
      60: checkcast     #103                // class net/minecraft/world/level/block/state/BlockState
      63: invokevirtual #129                // Method m_49959_:(Lnet/minecraft/world/level/block/state/BlockState;)V
      66: aload_0
      67: aload_1
      68: putfield      #131                // Field color:Lnet/minecraft/world/item/DyeColor;
      71: return

  public net.minecraft.world.item.DyeColor getColor();
    descriptor: ()Lnet/minecraft/world/item/DyeColor;
    Code:
       0: aload_0
       1: getfield      #131                // Field color:Lnet/minecraft/world/item/DyeColor;
       4: areturn

  public void m_5871_(net.minecraft.world.item.ItemStack, net.minecraft.world.level.BlockGetter, java.util.List<net.minecraft.network.chat.Component>, net.minecraft.world.item.TooltipFlag);
    descriptor: (Lnet/minecraft/world/item/ItemStack;Lnet/minecraft/world/level/BlockGetter;Ljava/util/List;Lnet/minecraft/world/item/TooltipFlag;)V
    Code:
       0: aload_0
       1: aload_1
       2: aload_2
       3: aload_3
       4: aload         4
       6: invokespecial #146                // Method net/minecraft/world/level/block/HorizontalDirectionalBlock.m_5871_:(Lnet/minecraft/world/item/ItemStack;Lnet/minecraft/world/level/BlockGetter;Ljava/util/List;Lnet/minecraft/world/item/TooltipFlag;)V
       9: aload_3
      10: getstatic     #150                // Field cool/furry/mc/forge/projectexpansion/util/Lang$Blocks.ADVANCED_ALCHEMICAL_CHEST_TOOLTIP:Lcool/furry/mc/forge/projectexpansion/util/Lang$Blocks;
      13: getstatic     #156                // Field net/minecraft/ChatFormatting.GRAY:Lnet/minecraft/ChatFormatting;
      16: iconst_0
      17: anewarray     #158                // class java/lang/Object
      20: invokevirtual #162                // Method cool/furry/mc/forge/projectexpansion/util/Lang$Blocks.translateColored:(Lnet/minecraft/ChatFormatting;[Ljava/lang/Object;)Lnet/minecraft/network/chat/MutableComponent;
      23: invokeinterface #168,  2          // InterfaceMethod java/util/List.add:(Ljava/lang/Object;)Z
      28: pop
      29: aload_3
      30: getstatic     #172                // Field cool/furry/mc/forge/projectexpansion/util/Lang.SEE_WIKI:Lcool/furry/mc/forge/projectexpansion/util/Lang;
      33: getstatic     #175                // Field net/minecraft/ChatFormatting.AQUA:Lnet/minecraft/ChatFormatting;
      36: iconst_0
      37: anewarray     #158                // class java/lang/Object
      40: invokevirtual #176                // Method cool/furry/mc/forge/projectexpansion/util/Lang.translateColored:(Lnet/minecraft/ChatFormatting;[Ljava/lang/Object;)Lnet/minecraft/network/chat/MutableComponent;
      43: invokeinterface #168,  2          // InterfaceMethod java/util/List.add:(Ljava/lang/Object;)Z
      48: pop
      49: return

  public net.minecraft.world.level.block.RenderShape m_7514_(net.minecraft.world.level.block.state.BlockState);
    descriptor: (Lnet/minecraft/world/level/block/state/BlockState;)Lnet/minecraft/world/level/block/RenderShape;
    Code:
       0: getstatic     #193                // Field net/minecraft/world/level/block/RenderShape.ENTITYBLOCK_ANIMATED:Lnet/minecraft/world/level/block/RenderShape;
       3: areturn

  public net.minecraft.world.level.block.entity.BlockEntity m_142194_(net.minecraft.core.BlockPos, net.minecraft.world.level.block.state.BlockState);
    descriptor: (Lnet/minecraft/core/BlockPos;Lnet/minecraft/world/level/block/state/BlockState;)Lnet/minecraft/world/level/block/entity/BlockEntity;
    Code:
       0: new           #199                // class cool/furry/mc/forge/projectexpansion/block/entity/BlockEntityAdvancedAlchemicalChest
       3: dup
       4: aload_1
       5: aload_2
       6: aload_0
       7: getfield      #131                // Field color:Lnet/minecraft/world/item/DyeColor;
      10: invokestatic  #205                // Method cool/furry/mc/forge/projectexpansion/util/AdvancedAlchemicalChest.getBlockEntityType:(Lnet/minecraft/world/item/DyeColor;)Lnet/minecraft/world/level/block/entity/BlockEntityType;
      13: aload_0
      14: getfield      #131                // Field color:Lnet/minecraft/world/item/DyeColor;
      17: invokespecial #208                // Method cool/furry/mc/forge/projectexpansion/block/entity/BlockEntityAdvancedAlchemicalChest."<init>":(Lnet/minecraft/core/BlockPos;Lnet/minecraft/world/level/block/state/BlockState;Lnet/minecraft/world/level/block/entity/BlockEntityType;Lnet/minecraft/world/item/DyeColor;)V
      20: areturn

  public net.minecraft.world.InteractionResult m_6227_(net.minecraft.world.level.block.state.BlockState, net.minecraft.world.level.Level, net.minecraft.core.BlockPos, net.minecraft.world.entity.player.Player, net.minecraft.world.InteractionHand, net.minecraft.world.phys.BlockHitResult);
    descriptor: (Lnet/minecraft/world/level/block/state/BlockState;Lnet/minecraft/world/level/Level;Lnet/minecraft/core/BlockPos;Lnet/minecraft/world/entity/player/Player;Lnet/minecraft/world/InteractionHand;Lnet/minecraft/world/phys/BlockHitResult;)Lnet/minecraft/world/InteractionResult;
    Code:
       0: aload_2
       1: getfield      #219                // Field net/minecraft/world/level/Level.f_46443_:Z
       4: ifeq          11
       7: getstatic     #225                // Field net/minecraft/world/InteractionResult.SUCCESS:Lnet/minecraft/world/InteractionResult;
      10: areturn
      11: aload_2
      12: aload_3
      13: invokevirtual #229                // Method net/minecraft/world/level/Level.m_7702_:(Lnet/minecraft/core/BlockPos;)Lnet/minecraft/world/level/block/entity/BlockEntity;
      16: astore        7
      18: aload         7
      20: instanceof    #199                // class cool/furry/mc/forge/projectexpansion/block/entity/BlockEntityAdvancedAlchemicalChest
      23: ifeq          117
      26: aload         7
      28: checkcast     #199                // class cool/furry/mc/forge/projectexpansion/block/entity/BlockEntityAdvancedAlchemicalChest
      31: astore        8
      33: aload         4
      35: invokevirtual #235                // Method net/minecraft/world/entity/player/Player.m_6047_:()Z
      38: ifeq          57
      41: aload         4
      43: iconst_1
      44: invokestatic  #241                // Method net/minecraft/world/entity/monster/piglin/PiglinAi.m_34873_:(Lnet/minecraft/world/entity/player/Player;Z)V
      47: aload         8
      49: aload         4
      51: aload         5
      53: invokevirtual #245                // Method cool/furry/mc/forge/projectexpansion/block/entity/BlockEntityAdvancedAlchemicalChest.handleActivation:(Lnet/minecraft/world/entity/player/Player;Lnet/minecraft/world/InteractionHand;)Lnet/minecraft/world/InteractionResult;
      56: areturn
      57: aload         8
      59: aload         4
      61: getstatic     #251                // Field cool/furry/mc/forge/projectexpansion/block/entity/BlockEntityOwnable$ActivationType.CHECK_OWNERSHIP:Lcool/furry/mc/forge/projectexpansion/block/entity/BlockEntityOwnable$ActivationType;
      64: invokevirtual #254                // Method cool/furry/mc/forge/projectexpansion/block/entity/BlockEntityAdvancedAlchemicalChest.handleActivation:(Lnet/minecraft/world/entity/player/Player;Lcool/furry/mc/forge/projectexpansion/block/entity/BlockEntityOwnable$ActivationType;)Z
      67: ifeq          117
      70: aload         4
      72: checkcast     #256                // class net/minecraft/server/level/ServerPlayer
      75: new           #13                 // class cool/furry/mc/forge/projectexpansion/block/BlockAdvancedAlchemicalChest$ContainerProvider
      78: dup
      79: aload         8
      81: aload         5
      83: invokespecial #259                // Method cool/furry/mc/forge/projectexpansion/block/BlockAdvancedAlchemicalChest$ContainerProvider."<init>":(Lcool/furry/mc/forge/projectexpansion/block/entity/BlockEntityAdvancedAlchemicalChest;Lnet/minecraft/world/InteractionHand;)V
      86: aload         5
      88: aload         4
      90: aload_3
      91: invokedynamic #272,  0            // InvokeDynamic #1:accept:(Lnet/minecraft/world/InteractionHand;Lnet/minecraft/world/entity/player/Player;Lnet/minecraft/core/BlockPos;)Ljava/util/function/Consumer;
      96: invokestatic  #278                // Method net/minecraftforge/network/NetworkHooks.openGui:(Lnet/minecraft/server/level/ServerPlayer;Lnet/minecraft/world/MenuProvider;Ljava/util/function/Consumer;)V
      99: aload         4
     101: getstatic     #284                // Field net/minecraft/stats/Stats.f_12968_:Lnet/minecraft/resources/ResourceLocation;
     104: invokevirtual #288                // Method net/minecraft/world/entity/player/Player.m_36220_:(Lnet/minecraft/resources/ResourceLocation;)V
     107: aload         4
     109: iconst_1
     110: invokestatic  #241                // Method net/minecraft/world/entity/monster/piglin/PiglinAi.m_34873_:(Lnet/minecraft/world/entity/player/Player;Z)V
     113: getstatic     #291                // Field net/minecraft/world/InteractionResult.CONSUME:Lnet/minecraft/world/InteractionResult;
     116: areturn
     117: getstatic     #294                // Field net/minecraft/world/InteractionResult.FAIL:Lnet/minecraft/world/InteractionResult;
     120: areturn

  public void m_6402_(net.minecraft.world.level.Level, net.minecraft.core.BlockPos, net.minecraft.world.level.block.state.BlockState, net.minecraft.world.entity.LivingEntity, net.minecraft.world.item.ItemStack);
    descriptor: (Lnet/minecraft/world/level/Level;Lnet/minecraft/core/BlockPos;Lnet/minecraft/world/level/block/state/BlockState;Lnet/minecraft/world/entity/LivingEntity;Lnet/minecraft/world/item/ItemStack;)V
    Code:
       0: aload_1
       1: aload_2
       2: invokevirtual #229                // Method net/minecraft/world/level/Level.m_7702_:(Lnet/minecraft/core/BlockPos;)Lnet/minecraft/world/level/block/entity/BlockEntity;
       5: astore        6
       7: aload         6
       9: instanceof    #199                // class cool/furry/mc/forge/projectexpansion/block/entity/BlockEntityAdvancedAlchemicalChest
      12: ifeq          31
      15: aload         6
      17: checkcast     #199                // class cool/furry/mc/forge/projectexpansion/block/entity/BlockEntityAdvancedAlchemicalChest
      20: astore        7
      22: aload         7
      24: aload         4
      26: aload         5
      28: invokevirtual #311                // Method cool/furry/mc/forge/projectexpansion/block/entity/BlockEntityAdvancedAlchemicalChest.handlePlace:(Lnet/minecraft/world/entity/LivingEntity;Lnet/minecraft/world/item/ItemStack;)V
      31: return

  public <T extends net.minecraft.world.level.block.entity.BlockEntity> net.minecraft.world.level.block.entity.BlockEntityTicker<T> m_142354_(net.minecraft.world.level.Level, net.minecraft.world.level.block.state.BlockState, net.minecraft.world.level.block.entity.BlockEntityType<T>);
    descriptor: (Lnet/minecraft/world/level/Level;Lnet/minecraft/world/level/block/state/BlockState;Lnet/minecraft/world/level/block/entity/BlockEntityType;)Lnet/minecraft/world/level/block/entity/BlockEntityTicker;
    Code:
       0: aload_3
       1: aload_0
       2: getfield      #131                // Field color:Lnet/minecraft/world/item/DyeColor;
       5: invokestatic  #205                // Method cool/furry/mc/forge/projectexpansion/util/AdvancedAlchemicalChest.getBlockEntityType:(Lnet/minecraft/world/item/DyeColor;)Lnet/minecraft/world/level/block/entity/BlockEntityType;
       8: if_acmpne     24
      11: aload_1
      12: getfield      #219                // Field net/minecraft/world/level/Level.f_46443_:Z
      15: ifeq          24
      18: invokedynamic #326,  0            // InvokeDynamic #2:m_155252_:()Lnet/minecraft/world/level/block/entity/BlockEntityTicker;
      23: areturn
      24: aconst_null
      25: areturn

  public net.minecraft.world.phys.shapes.VoxelShape m_5940_(net.minecraft.world.level.block.state.BlockState, net.minecraft.world.level.BlockGetter, net.minecraft.core.BlockPos, net.minecraft.world.phys.shapes.CollisionContext);
    descriptor: (Lnet/minecraft/world/level/block/state/BlockState;Lnet/minecraft/world/level/BlockGetter;Lnet/minecraft/core/BlockPos;Lnet/minecraft/world/phys/shapes/CollisionContext;)Lnet/minecraft/world/phys/shapes/VoxelShape;
    Code:
       0: getstatic     #333                // Field SHAPE:Lnet/minecraft/world/phys/shapes/VoxelShape;
       3: areturn

  public void m_7458_(net.minecraft.world.level.block.state.BlockState, net.minecraft.server.level.ServerLevel, net.minecraft.core.BlockPos, java.util.Random);
    descriptor: (Lnet/minecraft/world/level/block/state/BlockState;Lnet/minecraft/server/level/ServerLevel;Lnet/minecraft/core/BlockPos;Ljava/util/Random;)V
    Code:
       0: aload_2
       1: aload_3
       2: invokevirtual #343                // Method net/minecraft/server/level/ServerLevel.m_7702_:(Lnet/minecraft/core/BlockPos;)Lnet/minecraft/world/level/block/entity/BlockEntity;
       5: astore        5
       7: aload         5
       9: instanceof    #199                // class cool/furry/mc/forge/projectexpansion/block/entity/BlockEntityAdvancedAlchemicalChest
      12: ifeq          27
      15: aload         5
      17: checkcast     #199                // class cool/furry/mc/forge/projectexpansion/block/entity/BlockEntityAdvancedAlchemicalChest
      20: astore        6
      22: aload         6
      24: invokevirtual #347                // Method cool/furry/mc/forge/projectexpansion/block/entity/BlockEntityAdvancedAlchemicalChest.recheckOpen:()V
      27: return

  protected void m_7926_(net.minecraft.world.level.block.state.StateDefinition$Builder<net.minecraft.world.level.block.Block, net.minecraft.world.level.block.state.BlockState>);
    descriptor: (Lnet/minecraft/world/level/block/state/StateDefinition$Builder;)V
    Code:
       0: aload_0
       1: aload_1
       2: invokespecial #355                // Method net/minecraft/world/level/block/HorizontalDirectionalBlock.m_7926_:(Lnet/minecraft/world/level/block/state/StateDefinition$Builder;)V
       5: aload_1
       6: iconst_2
       7: anewarray     #357                // class net/minecraft/world/level/block/state/properties/Property
      10: dup
      11: iconst_0
      12: getstatic     #107                // Field f_54117_:Lnet/minecraft/world/level/block/state/properties/DirectionProperty;
      15: aastore
      16: dup
      17: iconst_1
      18: getstatic     #119                // Field WATERLOGGED:Lnet/minecraft/world/level/block/state/properties/BooleanProperty;
      21: aastore
      22: invokevirtual #361                // Method net/minecraft/world/level/block/state/StateDefinition$Builder.m_61104_:([Lnet/minecraft/world/level/block/state/properties/Property;)Lnet/minecraft/world/level/block/state/StateDefinition$Builder;
      25: pop
      26: return

  public boolean m_7357_(net.minecraft.world.level.block.state.BlockState, net.minecraft.world.level.BlockGetter, net.minecraft.core.BlockPos, net.minecraft.world.level.pathfinder.PathComputationType);
    descriptor: (Lnet/minecraft/world/level/block/state/BlockState;Lnet/minecraft/world/level/BlockGetter;Lnet/minecraft/core/BlockPos;Lnet/minecraft/world/level/pathfinder/PathComputationType;)Z
    Code:
       0: iconst_0
       1: ireturn

  public boolean m_7278_(net.minecraft.world.level.block.state.BlockState);
    descriptor: (Lnet/minecraft/world/level/block/state/BlockState;)Z
    Code:
       0: iconst_1
       1: ireturn

  public int m_6782_(net.minecraft.world.level.block.state.BlockState, net.minecraft.world.level.Level, net.minecraft.core.BlockPos);
    descriptor: (Lnet/minecraft/world/level/block/state/BlockState;Lnet/minecraft/world/level/Level;Lnet/minecraft/core/BlockPos;)I
    Code:
       0: aload_2
       1: aload_3
       2: invokevirtual #229                // Method net/minecraft/world/level/Level.m_7702_:(Lnet/minecraft/core/BlockPos;)Lnet/minecraft/world/level/block/entity/BlockEntity;
       5: astore        4
       7: aload         4
       9: instanceof    #199                // class cool/furry/mc/forge/projectexpansion/block/entity/BlockEntityAdvancedAlchemicalChest
      12: ifeq          52
      15: aload         4
      17: checkcast     #199                // class cool/furry/mc/forge/projectexpansion/block/entity/BlockEntityAdvancedAlchemicalChest
      20: astore        5
      22: aload         5
      24: getstatic     #381                // Field net/minecraftforge/items/CapabilityItemHandler.ITEM_HANDLER_CAPABILITY:Lnet/minecraftforge/common/capabilities/Capability;
      27: invokevirtual #385                // Method cool/furry/mc/forge/projectexpansion/block/entity/BlockEntityAdvancedAlchemicalChest.getCapability:(Lnet/minecraftforge/common/capabilities/Capability;)Lnet/minecraftforge/common/util/LazyOptional;
      30: invokedynamic #400,  0            // InvokeDynamic #3:apply:()Lnet/minecraftforge/common/util/NonNullFunction;
      35: invokevirtual #406                // Method net/minecraftforge/common/util/LazyOptional.map:(Lnet/minecraftforge/common/util/NonNullFunction;)Ljava/util/Optional;
      38: iconst_0
      39: invokestatic  #412                // Method java/lang/Integer.valueOf:(I)Ljava/lang/Integer;
      42: invokevirtual #417                // Method java/util/Optional.orElse:(Ljava/lang/Object;)Ljava/lang/Object;
      45: checkcast     #408                // class java/lang/Integer
      48: invokevirtual #421                // Method java/lang/Integer.intValue:()I
      51: ireturn
      52: iconst_0
      53: ireturn

  public net.minecraft.world.level.block.state.BlockState m_5573_(net.minecraft.world.item.context.BlockPlaceContext);
    descriptor: (Lnet/minecraft/world/item/context/BlockPlaceContext;)Lnet/minecraft/world/level/block/state/BlockState;
    Code:
       0: aload_0
       1: aload_1
       2: invokespecial #426                // Method net/minecraft/world/level/block/HorizontalDirectionalBlock.m_5573_:(Lnet/minecraft/world/item/context/BlockPlaceContext;)Lnet/minecraft/world/level/block/state/BlockState;
       5: invokestatic  #431                // Method java/util/Objects.requireNonNull:(Ljava/lang/Object;)Ljava/lang/Object;
       8: checkcast     #103                // class net/minecraft/world/level/block/state/BlockState
      11: getstatic     #107                // Field f_54117_:Lnet/minecraft/world/level/block/state/properties/DirectionProperty;
      14: aload_1
      15: invokevirtual #437                // Method net/minecraft/world/item/context/BlockPlaceContext.m_43723_:()Lnet/minecraft/world/entity/player/Player;
      18: ifnonnull     27
      21: getstatic     #113                // Field net/minecraft/core/Direction.NORTH:Lnet/minecraft/core/Direction;
      24: goto          37
      27: aload_1
      28: invokevirtual #437                // Method net/minecraft/world/item/context/BlockPlaceContext.m_43723_:()Lnet/minecraft/world/entity/player/Player;
      31: invokevirtual #443                // Method net/minecraft/world/entity/player/Player.m_6350_:()Lnet/minecraft/core/Direction;
      34: invokevirtual #446                // Method net/minecraft/core/Direction.m_122424_:()Lnet/minecraft/core/Direction;
      37: invokevirtual #117                // Method net/minecraft/world/level/block/state/BlockState.m_61124_:(Lnet/minecraft/world/level/block/state/properties/Property;Ljava/lang/Comparable;)Ljava/lang/Object;
      40: checkcast     #103                // class net/minecraft/world/level/block/state/BlockState
      43: getstatic     #451                // Field net/minecraft/world/level/block/state/properties/BlockStateProperties.f_61362_:Lnet/minecraft/world/level/block/state/properties/BooleanProperty;
      46: aload_1
      47: invokevirtual #455                // Method net/minecraft/world/item/context/BlockPlaceContext.m_43725_:()Lnet/minecraft/world/level/Level;
      50: aload_1
      51: invokevirtual #459                // Method net/minecraft/world/item/context/BlockPlaceContext.m_8083_:()Lnet/minecraft/core/BlockPos;
      54: invokevirtual #463                // Method net/minecraft/world/level/Level.m_6425_:(Lnet/minecraft/core/BlockPos;)Lnet/minecraft/world/level/material/FluidState;
      57: invokevirtual #469                // Method net/minecraft/world/level/material/FluidState.m_76152_:()Lnet/minecraft/world/level/material/Fluid;
      60: getstatic     #475                // Field net/minecraft/world/level/material/Fluids.f_76193_:Lnet/minecraft/world/level/material/FlowingFluid;
      63: if_acmpne     70
      66: iconst_1
      67: goto          71
      70: iconst_0
      71: invokestatic  #480                // Method java/lang/Boolean.valueOf:(Z)Ljava/lang/Boolean;
      74: invokevirtual #117                // Method net/minecraft/world/level/block/state/BlockState.m_61124_:(Lnet/minecraft/world/level/block/state/properties/Property;Ljava/lang/Comparable;)Ljava/lang/Object;
      77: checkcast     #103                // class net/minecraft/world/level/block/state/BlockState
      80: areturn

  public net.minecraft.world.level.material.FluidState m_5888_(net.minecraft.world.level.block.state.BlockState);
    descriptor: (Lnet/minecraft/world/level/block/state/BlockState;)Lnet/minecraft/world/level/material/FluidState;
    Code:
       0: aload_1
       1: getstatic     #451                // Field net/minecraft/world/level/block/state/properties/BlockStateProperties.f_61362_:Lnet/minecraft/world/level/block/state/properties/BooleanProperty;
       4: invokevirtual #488                // Method net/minecraft/world/level/block/state/BlockState.m_61143_:(Lnet/minecraft/world/level/block/state/properties/Property;)Ljava/lang/Comparable;
       7: checkcast     #121                // class java/lang/Boolean
      10: invokevirtual #491                // Method java/lang/Boolean.booleanValue:()Z
      13: ifeq          26
      16: getstatic     #475                // Field net/minecraft/world/level/material/Fluids.f_76193_:Lnet/minecraft/world/level/material/FlowingFluid;
      19: iconst_0
      20: invokevirtual #497                // Method net/minecraft/world/level/material/FlowingFluid.m_76068_:(Z)Lnet/minecraft/world/level/material/FluidState;
      23: goto          31
      26: aload_0
      27: aload_1
      28: invokespecial #499                // Method net/minecraft/world/level/block/HorizontalDirectionalBlock.m_5888_:(Lnet/minecraft/world/level/block/state/BlockState;)Lnet/minecraft/world/level/material/FluidState;
      31: areturn

  public net.minecraft.world.level.block.state.BlockState m_7417_(net.minecraft.world.level.block.state.BlockState, net.minecraft.core.Direction, net.minecraft.world.level.block.state.BlockState, net.minecraft.world.level.LevelAccessor, net.minecraft.core.BlockPos, net.minecraft.core.BlockPos);
    descriptor: (Lnet/minecraft/world/level/block/state/BlockState;Lnet/minecraft/core/Direction;Lnet/minecraft/world/level/block/state/BlockState;Lnet/minecraft/world/level/LevelAccessor;Lnet/minecraft/core/BlockPos;Lnet/minecraft/core/BlockPos;)Lnet/minecraft/world/level/block/state/BlockState;
    Code:
       0: aload_1
       1: getstatic     #451                // Field net/minecraft/world/level/block/state/properties/BlockStateProperties.f_61362_:Lnet/minecraft/world/level/block/state/properties/BooleanProperty;
       4: invokevirtual #488                // Method net/minecraft/world/level/block/state/BlockState.m_61143_:(Lnet/minecraft/world/level/block/state/properties/Property;)Ljava/lang/Comparable;
       7: checkcast     #121                // class java/lang/Boolean
      10: invokevirtual #491                // Method java/lang/Boolean.booleanValue:()Z
      13: ifeq          36
      16: aload         4
      18: aload         5
      20: getstatic     #475                // Field net/minecraft/world/level/material/Fluids.f_76193_:Lnet/minecraft/world/level/material/FlowingFluid;
      23: getstatic     #475                // Field net/minecraft/world/level/material/Fluids.f_76193_:Lnet/minecraft/world/level/material/FlowingFluid;
      26: aload         4
      28: invokevirtual #505                // Method net/minecraft/world/level/material/FlowingFluid.m_6718_:(Lnet/minecraft/world/level/LevelReader;)I
      31: invokeinterface #511,  4          // InterfaceMethod net/minecraft/world/level/LevelAccessor.m_186469_:(Lnet/minecraft/core/BlockPos;Lnet/minecraft/world/level/material/Fluid;I)V
      36: aload_0
      37: aload_1
      38: aload_2
      39: aload_3
      40: aload         4
      42: aload         5
      44: aload         6
      46: invokespecial #513                // Method net/minecraft/world/level/block/HorizontalDirectionalBlock.m_7417_:(Lnet/minecraft/world/level/block/state/BlockState;Lnet/minecraft/core/Direction;Lnet/minecraft/world/level/block/state/BlockState;Lnet/minecraft/world/level/LevelAccessor;Lnet/minecraft/core/BlockPos;Lnet/minecraft/core/BlockPos;)Lnet/minecraft/world/level/block/state/BlockState;
      49: areturn

  public boolean m_8133_(net.minecraft.world.level.block.state.BlockState, net.minecraft.world.level.Level, net.minecraft.core.BlockPos, int, int);
    descriptor: (Lnet/minecraft/world/level/block/state/BlockState;Lnet/minecraft/world/level/Level;Lnet/minecraft/core/BlockPos;II)Z
    Code:
       0: aload_0
       1: aload_1
       2: aload_2
       3: aload_3
       4: iload         4
       6: iload         5
       8: invokespecial #522                // Method net/minecraft/world/level/block/HorizontalDirectionalBlock.m_8133_:(Lnet/minecraft/world/level/block/state/BlockState;Lnet/minecraft/world/level/Level;Lnet/minecraft/core/BlockPos;II)Z
      11: pop
      12: aload_2
      13: aload_3
      14: invokevirtual #229                // Method net/minecraft/world/level/Level.m_7702_:(Lnet/minecraft/core/BlockPos;)Lnet/minecraft/world/level/block/entity/BlockEntity;
      17: astore        6
      19: aload         6
      21: ifnull        40
      24: aload         6
      26: iload         4
      28: iload         5
      30: invokevirtual #526                // Method net/minecraft/world/level/block/entity/BlockEntity.m_7531_:(II)Z
      33: ifeq          40
      36: iconst_1
      37: goto          41
      40: iconst_0
      41: ireturn

  public net.minecraft.world.level.material.MaterialColor getMapColor(net.minecraft.world.level.block.state.BlockState, net.minecraft.world.level.BlockGetter, net.minecraft.core.BlockPos, net.minecraft.world.level.material.MaterialColor);
    descriptor: (Lnet/minecraft/world/level/block/state/BlockState;Lnet/minecraft/world/level/BlockGetter;Lnet/minecraft/core/BlockPos;Lnet/minecraft/world/level/material/MaterialColor;)Lnet/minecraft/world/level/material/MaterialColor;
    Code:
       0: aload_0
       1: getfield      #131                // Field color:Lnet/minecraft/world/item/DyeColor;
       4: invokevirtual #536                // Method net/minecraft/world/item/DyeColor.m_41060_:()I
       7: invokestatic  #542                // Method net/minecraft/world/level/material/MaterialColor.m_192919_:(I)Lnet/minecraft/world/level/material/MaterialColor;
      10: areturn

  private static void lambda$use$1(net.minecraft.world.InteractionHand, net.minecraft.world.entity.player.Player, net.minecraft.core.BlockPos, net.minecraft.network.FriendlyByteBuf);
    descriptor: (Lnet/minecraft/world/InteractionHand;Lnet/minecraft/world/entity/player/Player;Lnet/minecraft/core/BlockPos;Lnet/minecraft/network/FriendlyByteBuf;)V
    Code:
       0: aload_3
       1: aload_0
       2: invokevirtual #550                // Method net/minecraft/network/FriendlyByteBuf.m_130068_:(Ljava/lang/Enum;)Lnet/minecraft/network/FriendlyByteBuf;
       5: pop
       6: aload_3
       7: aload_1
       8: invokevirtual #554                // Method net/minecraft/world/entity/player/Player.m_150109_:()Lnet/minecraft/world/entity/player/Inventory;
      11: getfield      #559                // Field net/minecraft/world/entity/player/Inventory.f_35977_:I
      14: invokevirtual #563                // Method net/minecraft/network/FriendlyByteBuf.writeByte:(I)Lio/netty/buffer/ByteBuf;
      17: pop
      18: aload_3
      19: iconst_0
      20: invokevirtual #567                // Method net/minecraft/network/FriendlyByteBuf.writeBoolean:(Z)Lio/netty/buffer/ByteBuf;
      23: pop
      24: aload_3
      25: aload_2
      26: invokevirtual #571                // Method net/minecraft/network/FriendlyByteBuf.m_130064_:(Lnet/minecraft/core/BlockPos;)Lnet/minecraft/network/FriendlyByteBuf;
      29: pop
      30: return

  private static int lambda$new$0(net.minecraft.world.level.block.state.BlockState);
    descriptor: (Lnet/minecraft/world/level/block/state/BlockState;)I
    Code:
       0: bipush        10
       2: ireturn

  static {};
    descriptor: ()V
    Code:
       0: getstatic     #451                // Field net/minecraft/world/level/block/state/properties/BlockStateProperties.f_61362_:Lnet/minecraft/world/level/block/state/properties/BooleanProperty;
       3: putstatic     #119                // Field WATERLOGGED:Lnet/minecraft/world/level/block/state/properties/BooleanProperty;
       6: dconst_1
       7: dconst_0
       8: dconst_1
       9: ldc2_w        #575                // double 15.0d
      12: ldc2_w        #577                // double 14.0d
      15: ldc2_w        #575                // double 15.0d
      18: invokestatic  #584                // Method net/minecraft/world/level/block/Block.m_49796_:(DDDDDD)Lnet/minecraft/world/phys/shapes/VoxelShape;
      21: putstatic     #333                // Field SHAPE:Lnet/minecraft/world/phys/shapes/VoxelShape;
      24: return
}
