Compiled from "PacketFortuneCoinTogglePressed.java"
public class reliquary.network.PacketFortuneCoinTogglePressed {
  private final reliquary.network.PacketFortuneCoinTogglePressed$InventoryType inventoryType;
    descriptor: Lreliquary/network/PacketFortuneCoinTogglePressed$InventoryType;

  private final int slot;
    descriptor: I

  private final java.lang.String identifier;
    descriptor: Ljava/lang/String;

  public reliquary.network.PacketFortuneCoinTogglePressed(reliquary.network.PacketFortuneCoinTogglePressed$InventoryType, int);
    descriptor: (Lreliquary/network/PacketFortuneCoinTogglePressed$InventoryType;I)V
    Code:
       0: aload_0
       1: aload_1
       2: ldc           #30                 // String
       4: iload_2
       5: invokespecial #33                 // Method "<init>":(Lreliquary/network/PacketFortuneCoinTogglePressed$InventoryType;Ljava/lang/String;I)V
       8: return

  public reliquary.network.PacketFortuneCoinTogglePressed(reliquary.network.PacketFortuneCoinTogglePressed$InventoryType, java.lang.String, int);
    descriptor: (Lreliquary/network/PacketFortuneCoinTogglePressed$InventoryType;Ljava/lang/String;I)V
    Code:
       0: aload_0
       1: invokespecial #38                 // Method java/lang/Object."<init>":()V
       4: aload_0
       5: aload_1
       6: putfield      #40                 // Field inventoryType:Lreliquary/network/PacketFortuneCoinTogglePressed$InventoryType;
       9: aload_0
      10: aload_2
      11: putfield      #42                 // Field identifier:Ljava/lang/String;
      14: aload_0
      15: iload_3
      16: putfield      #44                 // Field slot:I
      19: return

  static void encode(reliquary.network.PacketFortuneCoinTogglePressed, net.minecraft.network.FriendlyByteBuf);
    descriptor: (Lreliquary/network/PacketFortuneCoinTogglePressed;Lnet/minecraft/network/FriendlyByteBuf;)V
    Code:
       0: aload_1
       1: aload_0
       2: getfield      #40                 // Field inventoryType:Lreliquary/network/PacketFortuneCoinTogglePressed$InventoryType;
       5: invokevirtual #50                 // Method reliquary/network/PacketFortuneCoinTogglePressed$InventoryType.ordinal:()I
       8: invokevirtual #56                 // Method net/minecraft/network/FriendlyByteBuf.writeByte:(I)Lio/netty/buffer/ByteBuf;
      11: pop
      12: aload_1
      13: aload_0
      14: getfield      #42                 // Field identifier:Ljava/lang/String;
      17: invokevirtual #60                 // Method net/minecraft/network/FriendlyByteBuf.m_130070_:(Ljava/lang/String;)Lnet/minecraft/network/FriendlyByteBuf;
      20: pop
      21: aload_1
      22: aload_0
      23: getfield      #44                 // Field slot:I
      26: invokevirtual #63                 // Method net/minecraft/network/FriendlyByteBuf.writeInt:(I)Lio/netty/buffer/ByteBuf;
      29: pop
      30: return

  static reliquary.network.PacketFortuneCoinTogglePressed decode(net.minecraft.network.FriendlyByteBuf);
    descriptor: (Lnet/minecraft/network/FriendlyByteBuf;)Lreliquary/network/PacketFortuneCoinTogglePressed;
    Code:
       0: new           #2                  // class reliquary/network/PacketFortuneCoinTogglePressed
       3: dup
       4: invokestatic  #72                 // Method reliquary/network/PacketFortuneCoinTogglePressed$InventoryType.values:()[Lreliquary/network/PacketFortuneCoinTogglePressed$InventoryType;
       7: aload_0
       8: invokevirtual #76                 // Method net/minecraft/network/FriendlyByteBuf.readByte:()B
      11: aaload
      12: aload_0
      13: invokevirtual #80                 // Method net/minecraft/network/FriendlyByteBuf.m_130277_:()Ljava/lang/String;
      16: aload_0
      17: invokevirtual #83                 // Method net/minecraft/network/FriendlyByteBuf.readInt:()I
      20: invokespecial #33                 // Method "<init>":(Lreliquary/network/PacketFortuneCoinTogglePressed$InventoryType;Ljava/lang/String;I)V
      23: areturn

  static void onMessage(reliquary.network.PacketFortuneCoinTogglePressed, java.util.function.Supplier<net.minecraftforge.network.NetworkEvent$Context>);
    descriptor: (Lreliquary/network/PacketFortuneCoinTogglePressed;Ljava/util/function/Supplier;)V
    Code:
       0: aload_1
       1: invokeinterface #92,  1           // InterfaceMethod java/util/function/Supplier.get:()Ljava/lang/Object;
       6: checkcast     #12                 // class net/minecraftforge/network/NetworkEvent$Context
       9: astore_2
      10: aload_2
      11: aload_0
      12: aload_2
      13: invokedynamic #109,  0            // InvokeDynamic #0:run:(Lreliquary/network/PacketFortuneCoinTogglePressed;Lnet/minecraftforge/network/NetworkEvent$Context;)Ljava/lang/Runnable;
      18: invokevirtual #113                // Method net/minecraftforge/network/NetworkEvent$Context.enqueueWork:(Ljava/lang/Runnable;)Ljava/util/concurrent/CompletableFuture;
      21: pop
      22: aload_2
      23: iconst_1
      24: invokevirtual #117                // Method net/minecraftforge/network/NetworkEvent$Context.setPacketHandled:(Z)V
      27: return

  private static void handleMessage(reliquary.network.PacketFortuneCoinTogglePressed, net.minecraft.server.level.ServerPlayer);
    descriptor: (Lreliquary/network/PacketFortuneCoinTogglePressed;Lnet/minecraft/server/level/ServerPlayer;)V
    Code:
       0: aload_1
       1: ifnonnull     5
       4: return
       5: getstatic     #129                // Field reliquary/network/PacketFortuneCoinTogglePressed$1.$SwitchMap$reliquary$network$PacketFortuneCoinTogglePressed$InventoryType:[I
       8: aload_0
       9: getfield      #40                 // Field inventoryType:Lreliquary/network/PacketFortuneCoinTogglePressed$InventoryType;
      12: invokevirtual #50                 // Method reliquary/network/PacketFortuneCoinTogglePressed$InventoryType.ordinal:()I
      15: iaload
      16: tableswitch   { // 1 to 3
                     1: 44
                     2: 96
                     3: 145
               default: 155
          }
      44: aload_1
      45: invokevirtual #135                // Method net/minecraft/server/level/ServerPlayer.m_150109_:()Lnet/minecraft/world/entity/player/Inventory;
      48: getfield      #141                // Field net/minecraft/world/entity/player/Inventory.f_35974_:Lnet/minecraft/core/NonNullList;
      51: aload_0
      52: getfield      #44                 // Field slot:I
      55: invokevirtual #146                // Method net/minecraft/core/NonNullList.get:(I)Ljava/lang/Object;
      58: checkcast     #148                // class net/minecraft/world/item/ItemStack
      61: astore_2
      62: aload_2
      63: invokevirtual #152                // Method net/minecraft/world/item/ItemStack.m_41720_:()Lnet/minecraft/world/item/Item;
      66: getstatic     #158                // Field reliquary/init/ModItems.FORTUNE_COIN:Lnet/minecraftforge/registries/RegistryObject;
      69: invokevirtual #161                // Method net/minecraftforge/registries/RegistryObject.get:()Ljava/lang/Object;
      72: if_acmpne     93
      75: getstatic     #158                // Field reliquary/init/ModItems.FORTUNE_COIN:Lnet/minecraftforge/registries/RegistryObject;
      78: invokevirtual #161                // Method net/minecraftforge/registries/RegistryObject.get:()Ljava/lang/Object;
      81: checkcast     #163                // class reliquary/items/FortuneCoinItem
      84: aload_2
      85: invokevirtual #167                // Method reliquary/items/FortuneCoinItem.toggle:(Lnet/minecraft/world/item/ItemStack;)V
      88: aload_1
      89: aload_2
      90: invokestatic  #171                // Method showMessage:(Lnet/minecraft/server/level/ServerPlayer;Lnet/minecraft/world/item/ItemStack;)V
      93: goto          155
      96: aload_1
      97: invokevirtual #135                // Method net/minecraft/server/level/ServerPlayer.m_150109_:()Lnet/minecraft/world/entity/player/Inventory;
     100: getfield      #174                // Field net/minecraft/world/entity/player/Inventory.f_35976_:Lnet/minecraft/core/NonNullList;
     103: iconst_0
     104: invokevirtual #146                // Method net/minecraft/core/NonNullList.get:(I)Ljava/lang/Object;
     107: checkcast     #148                // class net/minecraft/world/item/ItemStack
     110: astore_2
     111: aload_2
     112: invokevirtual #152                // Method net/minecraft/world/item/ItemStack.m_41720_:()Lnet/minecraft/world/item/Item;
     115: getstatic     #158                // Field reliquary/init/ModItems.FORTUNE_COIN:Lnet/minecraftforge/registries/RegistryObject;
     118: invokevirtual #161                // Method net/minecraftforge/registries/RegistryObject.get:()Ljava/lang/Object;
     121: if_acmpne     142
     124: getstatic     #158                // Field reliquary/init/ModItems.FORTUNE_COIN:Lnet/minecraftforge/registries/RegistryObject;
     127: invokevirtual #161                // Method net/minecraftforge/registries/RegistryObject.get:()Ljava/lang/Object;
     130: checkcast     #163                // class reliquary/items/FortuneCoinItem
     133: aload_2
     134: invokevirtual #167                // Method reliquary/items/FortuneCoinItem.toggle:(Lnet/minecraft/world/item/ItemStack;)V
     137: aload_1
     138: aload_2
     139: invokestatic  #171                // Method showMessage:(Lnet/minecraft/server/level/ServerPlayer;Lnet/minecraft/world/item/ItemStack;)V
     142: goto          155
     145: aload_1
     146: aload_0
     147: invokedynamic #185,  0            // InvokeDynamic #1:get:(Lnet/minecraft/server/level/ServerPlayer;Lreliquary/network/PacketFortuneCoinTogglePressed;)Ljava/util/function/Supplier;
     152: invokestatic  #188                // Method run:(Ljava/util/function/Supplier;)V
     155: return

  private static void showMessage(net.minecraft.server.level.ServerPlayer, net.minecraft.world.item.ItemStack);
    descriptor: (Lnet/minecraft/server/level/ServerPlayer;Lnet/minecraft/world/item/ItemStack;)V
    Code:
       0: aload_0
       1: ldc           #196                // String chat.reliquary.fortune_coin.toggle
       3: iconst_1
       4: anewarray     #4                  // class java/lang/Object
       7: dup
       8: iconst_0
       9: aload_1
      10: invokestatic  #200                // Method reliquary/items/FortuneCoinItem.isEnabled:(Lnet/minecraft/world/item/ItemStack;)Z
      13: ifeq          30
      16: ldc           #202                // String chat.reliquary.fortune_coin.on
      18: invokestatic  #208                // InterfaceMethod net/minecraft/network/chat/Component.m_237115_:(Ljava/lang/String;)Lnet/minecraft/network/chat/MutableComponent;
      21: getstatic     #214                // Field net/minecraft/ChatFormatting.GREEN:Lnet/minecraft/ChatFormatting;
      24: invokevirtual #220                // Method net/minecraft/network/chat/MutableComponent.m_130940_:(Lnet/minecraft/ChatFormatting;)Lnet/minecraft/network/chat/MutableComponent;
      27: goto          41
      30: ldc           #226                // String chat.reliquary.fortune_coin.off
      32: invokestatic  #208                // InterfaceMethod net/minecraft/network/chat/Component.m_237115_:(Ljava/lang/String;)Lnet/minecraft/network/chat/MutableComponent;
      35: getstatic     #229                // Field net/minecraft/ChatFormatting.RED:Lnet/minecraft/ChatFormatting;
      38: invokevirtual #220                // Method net/minecraft/network/chat/MutableComponent.m_130940_:(Lnet/minecraft/ChatFormatting;)Lnet/minecraft/network/chat/MutableComponent;
      41: aastore
      42: invokestatic  #233                // InterfaceMethod net/minecraft/network/chat/Component.m_237110_:(Ljava/lang/String;[Ljava/lang/Object;)Lnet/minecraft/network/chat/MutableComponent;
      45: iconst_1
      46: invokevirtual #237                // Method net/minecraft/server/level/ServerPlayer.m_5661_:(Lnet/minecraft/network/chat/Component;Z)V
      49: return

  private static void run(java.util.function.Supplier<java.lang.Runnable>);
    descriptor: (Ljava/util/function/Supplier;)V
    Code:
       0: aload_0
       1: invokeinterface #92,  1           // InterfaceMethod java/util/function/Supplier.get:()Ljava/lang/Object;
       6: checkcast     #241                // class java/lang/Runnable
       9: invokeinterface #243,  1          // InterfaceMethod java/lang/Runnable.run:()V
      14: return

  private static java.lang.Runnable lambda$handleMessage$3(net.minecraft.server.level.ServerPlayer, reliquary.network.PacketFortuneCoinTogglePressed);
    descriptor: (Lnet/minecraft/server/level/ServerPlayer;Lreliquary/network/PacketFortuneCoinTogglePressed;)Ljava/lang/Runnable;
    Code:
       0: aload_0
       1: aload_1
       2: invokedynamic #252,  0            // InvokeDynamic #2:run:(Lnet/minecraft/server/level/ServerPlayer;Lreliquary/network/PacketFortuneCoinTogglePressed;)Ljava/lang/Runnable;
       7: areturn

  private static void lambda$handleMessage$2(net.minecraft.server.level.ServerPlayer, reliquary.network.PacketFortuneCoinTogglePressed);
    descriptor: (Lnet/minecraft/server/level/ServerPlayer;Lreliquary/network/PacketFortuneCoinTogglePressed;)V
    Code:
       0: aload_0
       1: aload_1
       2: getfield      #42                 // Field identifier:Ljava/lang/String;
       5: aload_1
       6: getfield      #44                 // Field slot:I
       9: invokestatic  #258                // Method reliquary/compat/curios/CuriosCompat.getStackInSlot:(Lnet/minecraft/world/entity/LivingEntity;Ljava/lang/String;I)Ljava/util/Optional;
      12: aload_0
      13: aload_1
      14: invokedynamic #270,  0            // InvokeDynamic #3:accept:(Lnet/minecraft/server/level/ServerPlayer;Lreliquary/network/PacketFortuneCoinTogglePressed;)Ljava/util/function/Consumer;
      19: invokevirtual #276                // Method java/util/Optional.ifPresent:(Ljava/util/function/Consumer;)V
      22: return

  private static void lambda$handleMessage$1(net.minecraft.server.level.ServerPlayer, reliquary.network.PacketFortuneCoinTogglePressed, net.minecraft.world.item.ItemStack);
    descriptor: (Lnet/minecraft/server/level/ServerPlayer;Lreliquary/network/PacketFortuneCoinTogglePressed;Lnet/minecraft/world/item/ItemStack;)V
    Code:
       0: aload_2
       1: invokevirtual #152                // Method net/minecraft/world/item/ItemStack.m_41720_:()Lnet/minecraft/world/item/Item;
       4: getstatic     #158                // Field reliquary/init/ModItems.FORTUNE_COIN:Lnet/minecraftforge/registries/RegistryObject;
       7: invokevirtual #161                // Method net/minecraftforge/registries/RegistryObject.get:()Ljava/lang/Object;
      10: if_acmpne     44
      13: getstatic     #158                // Field reliquary/init/ModItems.FORTUNE_COIN:Lnet/minecraftforge/registries/RegistryObject;
      16: invokevirtual #161                // Method net/minecraftforge/registries/RegistryObject.get:()Ljava/lang/Object;
      19: checkcast     #163                // class reliquary/items/FortuneCoinItem
      22: aload_2
      23: invokevirtual #167                // Method reliquary/items/FortuneCoinItem.toggle:(Lnet/minecraft/world/item/ItemStack;)V
      26: aload_0
      27: aload_2
      28: invokestatic  #171                // Method showMessage:(Lnet/minecraft/server/level/ServerPlayer;Lnet/minecraft/world/item/ItemStack;)V
      31: aload_0
      32: aload_1
      33: getfield      #42                 // Field identifier:Ljava/lang/String;
      36: aload_1
      37: getfield      #44                 // Field slot:I
      40: aload_2
      41: invokestatic  #280                // Method reliquary/compat/curios/CuriosCompat.setStackInSlot:(Lnet/minecraft/world/entity/LivingEntity;Ljava/lang/String;ILnet/minecraft/world/item/ItemStack;)V
      44: return

  private static void lambda$onMessage$0(reliquary.network.PacketFortuneCoinTogglePressed, net.minecraftforge.network.NetworkEvent$Context);
    descriptor: (Lreliquary/network/PacketFortuneCoinTogglePressed;Lnet/minecraftforge/network/NetworkEvent$Context;)V
    Code:
       0: aload_0
       1: aload_1
       2: invokevirtual #285                // Method net/minecraftforge/network/NetworkEvent$Context.getSender:()Lnet/minecraft/server/level/ServerPlayer;
       5: invokestatic  #287                // Method handleMessage:(Lreliquary/network/PacketFortuneCoinTogglePressed;Lnet/minecraft/server/level/ServerPlayer;)V
       8: return
}
