Compiled from "BotaniaCompat.java"
public class xreliquary.compat.botania.BotaniaCompat implements xreliquary.compat.ICompat {
  public xreliquary.compat.botania.BotaniaCompat();
    descriptor: ()V
    Code:
       0: aload_0
       1: invokespecial #21                 // Method java/lang/Object."<init>":()V
       4: return

  public void setup();
    descriptor: ()V
    Code:
       0: invokedynamic #41,  0             // InvokeDynamic #0:canPickup:()Lxreliquary/items/FortuneCoinItem$IFortuneCoinPickupChecker;
       5: invokestatic  #45                 // Method xreliquary/items/FortuneCoinItem.addFortuneCoinPickupChecker:(Lxreliquary/items/FortuneCoinItem$IFortuneCoinPickupChecker;)V
       8: return

  private static boolean lambda$setup$0(net.minecraft.entity.item.ItemEntity);
    descriptor: (Lnet/minecraft/entity/item/ItemEntity;)Z
    Code:
       0: invokestatic  #51                 // InterfaceMethod vazkii/botania/api/BotaniaAPI.instance:()Lvazkii/botania/api/BotaniaAPI;
       3: aload_0
       4: invokeinterface #55,  2           // InterfaceMethod vazkii/botania/api/BotaniaAPI.hasSolegnoliaAround:(Lnet/minecraft/entity/Entity;)Z
       9: ifne          16
      12: iconst_1
      13: goto          17
      16: iconst_0
      17: ireturn
}
