Compiled from "ChestRenderer.java"
public class cool.furry.mc.forge.projectexpansion.rendering.ChestRenderer extends net.minecraft.client.renderer.tileentity.TileEntityRenderer<cool.furry.mc.forge.projectexpansion.tile.TileAdvancedAlchemicalChest> {
  private final net.minecraft.client.renderer.model.ModelRenderer lid;
    descriptor: Lnet/minecraft/client/renderer/model/ModelRenderer;

  private final net.minecraft.client.renderer.model.ModelRenderer base;
    descriptor: Lnet/minecraft/client/renderer/model/ModelRenderer;

  private final net.minecraft.client.renderer.model.ModelRenderer latch;
    descriptor: Lnet/minecraft/client/renderer/model/ModelRenderer;

  private final java.util.function.Predicate<net.minecraft.block.Block> blockChecker;
    descriptor: Ljava/util/function/Predicate;

  private final net.minecraft.util.ResourceLocation texture;
    descriptor: Lnet/minecraft/util/ResourceLocation;

  public cool.furry.mc.forge.projectexpansion.rendering.ChestRenderer(net.minecraft.client.renderer.tileentity.TileEntityRendererDispatcher, net.minecraft.util.ResourceLocation, java.util.function.Predicate<net.minecraft.block.Block>);
    descriptor: (Lnet/minecraft/client/renderer/tileentity/TileEntityRendererDispatcher;Lnet/minecraft/util/ResourceLocation;Ljava/util/function/Predicate;)V
    Code:
       0: aload_0
       1: aload_1
       2: invokespecial #21                 // Method net/minecraft/client/renderer/tileentity/TileEntityRenderer."<init>":(Lnet/minecraft/client/renderer/tileentity/TileEntityRendererDispatcher;)V
       5: aload_0
       6: aload_2
       7: putfield      #23                 // Field texture:Lnet/minecraft/util/ResourceLocation;
      10: aload_0
      11: aload_3
      12: putfield      #25                 // Field blockChecker:Ljava/util/function/Predicate;
      15: aload_0
      16: new           #27                 // class net/minecraft/client/renderer/model/ModelRenderer
      19: dup
      20: bipush        64
      22: bipush        64
      24: iconst_0
      25: bipush        19
      27: invokespecial #30                 // Method net/minecraft/client/renderer/model/ModelRenderer."<init>":(IIII)V
      30: putfield      #32                 // Field base:Lnet/minecraft/client/renderer/model/ModelRenderer;
      33: aload_0
      34: getfield      #32                 // Field base:Lnet/minecraft/client/renderer/model/ModelRenderer;
      37: fconst_1
      38: fconst_0
      39: fconst_1
      40: ldc           #33                 // float 14.0f
      42: ldc           #34                 // float 10.0f
      44: ldc           #33                 // float 14.0f
      46: fconst_0
      47: invokevirtual #38                 // Method net/minecraft/client/renderer/model/ModelRenderer.func_228301_a_:(FFFFFFF)V
      50: aload_0
      51: new           #27                 // class net/minecraft/client/renderer/model/ModelRenderer
      54: dup
      55: bipush        64
      57: bipush        64
      59: iconst_0
      60: iconst_0
      61: invokespecial #30                 // Method net/minecraft/client/renderer/model/ModelRenderer."<init>":(IIII)V
      64: putfield      #40                 // Field lid:Lnet/minecraft/client/renderer/model/ModelRenderer;
      67: aload_0
      68: getfield      #40                 // Field lid:Lnet/minecraft/client/renderer/model/ModelRenderer;
      71: fconst_1
      72: fconst_0
      73: fconst_0
      74: ldc           #33                 // float 14.0f
      76: ldc           #41                 // float 5.0f
      78: ldc           #33                 // float 14.0f
      80: fconst_0
      81: invokevirtual #38                 // Method net/minecraft/client/renderer/model/ModelRenderer.func_228301_a_:(FFFFFFF)V
      84: aload_0
      85: getfield      #40                 // Field lid:Lnet/minecraft/client/renderer/model/ModelRenderer;
      88: ldc           #42                 // float 9.0f
      90: putfield      #46                 // Field net/minecraft/client/renderer/model/ModelRenderer.field_78797_d:F
      93: aload_0
      94: getfield      #40                 // Field lid:Lnet/minecraft/client/renderer/model/ModelRenderer;
      97: fconst_1
      98: putfield      #49                 // Field net/minecraft/client/renderer/model/ModelRenderer.field_78798_e:F
     101: aload_0
     102: new           #27                 // class net/minecraft/client/renderer/model/ModelRenderer
     105: dup
     106: bipush        64
     108: bipush        64
     110: iconst_0
     111: iconst_0
     112: invokespecial #30                 // Method net/minecraft/client/renderer/model/ModelRenderer."<init>":(IIII)V
     115: putfield      #51                 // Field latch:Lnet/minecraft/client/renderer/model/ModelRenderer;
     118: aload_0
     119: getfield      #51                 // Field latch:Lnet/minecraft/client/renderer/model/ModelRenderer;
     122: ldc           #52                 // float 7.0f
     124: ldc           #53                 // float -1.0f
     126: ldc           #54                 // float 15.0f
     128: fconst_2
     129: ldc           #55                 // float 4.0f
     131: fconst_1
     132: fconst_0
     133: invokevirtual #38                 // Method net/minecraft/client/renderer/model/ModelRenderer.func_228301_a_:(FFFFFFF)V
     136: aload_0
     137: getfield      #51                 // Field latch:Lnet/minecraft/client/renderer/model/ModelRenderer;
     140: ldc           #56                 // float 8.0f
     142: putfield      #46                 // Field net/minecraft/client/renderer/model/ModelRenderer.field_78797_d:F
     145: return

  public void render(cool.furry.mc.forge.projectexpansion.tile.TileAdvancedAlchemicalChest, float, com.mojang.blaze3d.matrix.MatrixStack, net.minecraft.client.renderer.IRenderTypeBuffer, int, int);
    descriptor: (Lcool/furry/mc/forge/projectexpansion/tile/TileAdvancedAlchemicalChest;FLcom/mojang/blaze3d/matrix/MatrixStack;Lnet/minecraft/client/renderer/IRenderTypeBuffer;II)V
    Code:
       0: aload_3
       1: invokevirtual #69                 // Method com/mojang/blaze3d/matrix/MatrixStack.func_227860_a_:()V
       4: aload_1
       5: invokevirtual #75                 // Method cool/furry/mc/forge/projectexpansion/tile/TileAdvancedAlchemicalChest.func_145831_w:()Lnet/minecraft/world/World;
       8: ifnull        99
      11: aload_1
      12: invokevirtual #79                 // Method cool/furry/mc/forge/projectexpansion/tile/TileAdvancedAlchemicalChest.func_145837_r:()Z
      15: ifne          99
      18: aload_1
      19: invokevirtual #75                 // Method cool/furry/mc/forge/projectexpansion/tile/TileAdvancedAlchemicalChest.func_145831_w:()Lnet/minecraft/world/World;
      22: aload_1
      23: invokevirtual #83                 // Method cool/furry/mc/forge/projectexpansion/tile/TileAdvancedAlchemicalChest.func_174877_v:()Lnet/minecraft/util/math/BlockPos;
      26: invokevirtual #89                 // Method net/minecraft/world/World.func_180495_p:(Lnet/minecraft/util/math/BlockPos;)Lnet/minecraft/block/BlockState;
      29: astore        7
      31: aload_0
      32: getfield      #25                 // Field blockChecker:Ljava/util/function/Predicate;
      35: aload         7
      37: invokevirtual #95                 // Method net/minecraft/block/BlockState.func_177230_c:()Lnet/minecraft/block/Block;
      40: invokeinterface #101,  2          // InterfaceMethod java/util/function/Predicate.test:(Ljava/lang/Object;)Z
      45: ifeq          99
      48: aload_3
      49: ldc2_w        #102                // double 0.5d
      52: ldc2_w        #102                // double 0.5d
      55: ldc2_w        #102                // double 0.5d
      58: invokevirtual #107                // Method com/mojang/blaze3d/matrix/MatrixStack.func_227861_a_:(DDD)V
      61: aload_3
      62: getstatic     #113                // Field net/minecraft/util/math/vector/Vector3f.field_229181_d_:Lnet/minecraft/util/math/vector/Vector3f;
      65: aload         7
      67: getstatic     #119                // Field net/minecraft/state/properties/BlockStateProperties.field_208157_J:Lnet/minecraft/state/DirectionProperty;
      70: invokevirtual #123                // Method net/minecraft/block/BlockState.func_177229_b:(Lnet/minecraft/state/Property;)Ljava/lang/Comparable;
      73: checkcast     #125                // class net/minecraft/util/Direction
      76: invokevirtual #129                // Method net/minecraft/util/Direction.func_185119_l:()F
      79: fneg
      80: invokevirtual #133                // Method net/minecraft/util/math/vector/Vector3f.func_229187_a_:(F)Lnet/minecraft/util/math/vector/Quaternion;
      83: invokevirtual #137                // Method com/mojang/blaze3d/matrix/MatrixStack.func_227863_a_:(Lnet/minecraft/util/math/vector/Quaternion;)V
      86: aload_3
      87: ldc2_w        #138                // double -0.5d
      90: ldc2_w        #138                // double -0.5d
      93: ldc2_w        #138                // double -0.5d
      96: invokevirtual #107                // Method com/mojang/blaze3d/matrix/MatrixStack.func_227861_a_:(DDD)V
      99: fconst_1
     100: aload_1
     101: fload_2
     102: invokevirtual #143                // Method cool/furry/mc/forge/projectexpansion/tile/TileAdvancedAlchemicalChest.getLidAngle:(F)F
     105: fsub
     106: fstore        7
     108: fconst_1
     109: fload         7
     111: fload         7
     113: fmul
     114: fload         7
     116: fmul
     117: fsub
     118: fstore        7
     120: aload         4
     122: aload_0
     123: getfield      #23                 // Field texture:Lnet/minecraft/util/ResourceLocation;
     126: invokestatic  #149                // Method net/minecraft/client/renderer/RenderType.func_228638_b_:(Lnet/minecraft/util/ResourceLocation;)Lnet/minecraft/client/renderer/RenderType;
     129: invokeinterface #155,  2          // InterfaceMethod net/minecraft/client/renderer/IRenderTypeBuffer.getBuffer:(Lnet/minecraft/client/renderer/RenderType;)Lcom/mojang/blaze3d/vertex/IVertexBuilder;
     134: astore        8
     136: aload_0
     137: getfield      #40                 // Field lid:Lnet/minecraft/client/renderer/model/ModelRenderer;
     140: fload         7
     142: ldc           #156                // float 1.5707964f
     144: fmul
     145: fneg
     146: putfield      #159                // Field net/minecraft/client/renderer/model/ModelRenderer.field_78795_f:F
     149: aload_0
     150: getfield      #51                 // Field latch:Lnet/minecraft/client/renderer/model/ModelRenderer;
     153: aload_0
     154: getfield      #40                 // Field lid:Lnet/minecraft/client/renderer/model/ModelRenderer;
     157: getfield      #159                // Field net/minecraft/client/renderer/model/ModelRenderer.field_78795_f:F
     160: putfield      #159                // Field net/minecraft/client/renderer/model/ModelRenderer.field_78795_f:F
     163: aload_0
     164: getfield      #40                 // Field lid:Lnet/minecraft/client/renderer/model/ModelRenderer;
     167: aload_3
     168: aload         8
     170: iload         5
     172: iload         6
     174: invokevirtual #163                // Method net/minecraft/client/renderer/model/ModelRenderer.func_228308_a_:(Lcom/mojang/blaze3d/matrix/MatrixStack;Lcom/mojang/blaze3d/vertex/IVertexBuilder;II)V
     177: aload_0
     178: getfield      #51                 // Field latch:Lnet/minecraft/client/renderer/model/ModelRenderer;
     181: aload_3
     182: aload         8
     184: iload         5
     186: iload         6
     188: invokevirtual #163                // Method net/minecraft/client/renderer/model/ModelRenderer.func_228308_a_:(Lcom/mojang/blaze3d/matrix/MatrixStack;Lcom/mojang/blaze3d/vertex/IVertexBuilder;II)V
     191: aload_0
     192: getfield      #32                 // Field base:Lnet/minecraft/client/renderer/model/ModelRenderer;
     195: aload_3
     196: aload         8
     198: iload         5
     200: iload         6
     202: invokevirtual #163                // Method net/minecraft/client/renderer/model/ModelRenderer.func_228308_a_:(Lcom/mojang/blaze3d/matrix/MatrixStack;Lcom/mojang/blaze3d/vertex/IVertexBuilder;II)V
     205: aload_3
     206: invokevirtual #166                // Method com/mojang/blaze3d/matrix/MatrixStack.func_227865_b_:()V
     209: return

  public void func_225616_a_(net.minecraft.tileentity.TileEntity, float, com.mojang.blaze3d.matrix.MatrixStack, net.minecraft.client.renderer.IRenderTypeBuffer, int, int);
    descriptor: (Lnet/minecraft/tileentity/TileEntity;FLcom/mojang/blaze3d/matrix/MatrixStack;Lnet/minecraft/client/renderer/IRenderTypeBuffer;II)V
    Code:
       0: aload_0
       1: aload_1
       2: checkcast     #71                 // class cool/furry/mc/forge/projectexpansion/tile/TileAdvancedAlchemicalChest
       5: fload_2
       6: aload_3
       7: aload         4
       9: iload         5
      11: iload         6
      13: invokevirtual #185                // Method render:(Lcool/furry/mc/forge/projectexpansion/tile/TileAdvancedAlchemicalChest;FLcom/mojang/blaze3d/matrix/MatrixStack;Lnet/minecraft/client/renderer/IRenderTypeBuffer;II)V
      16: return
}
