Compiled from "RenderingEvent.java"
public class cool.furry.mc.forge.projectexpansion.events.RenderingEvent {
  public cool.furry.mc.forge.projectexpansion.events.RenderingEvent();
    descriptor: ()V
    Code:
       0: aload_0
       1: invokespecial #31                 // Method java/lang/Object."<init>":()V
       4: return

  public static void clientSetup(net.minecraftforge.fml.event.lifecycle.FMLClientSetupEvent);
    descriptor: (Lnet/minecraftforge/fml/event/lifecycle/FMLClientSetupEvent;)V
    Code:
       0: invokestatic  #42                 // Method net/minecraftforge/fml/ModLoadingContext.get:()Lnet/minecraftforge/fml/ModLoadingContext;
       3: getstatic     #48                 // Field net/minecraftforge/fml/ExtensionPoint.CONFIGGUIFACTORY:Lnet/minecraftforge/fml/ExtensionPoint;
       6: invokedynamic #66,  0             // InvokeDynamic #0:get:()Ljava/util/function/Supplier;
      11: invokevirtual #70                 // Method net/minecraftforge/fml/ModLoadingContext.registerExtensionPoint:(Lnet/minecraftforge/fml/ExtensionPoint;Ljava/util/function/Supplier;)V
      14: invokestatic  #76                 // Method net/minecraft/item/DyeColor.values:()[Lnet/minecraft/item/DyeColor;
      17: astore_1
      18: aload_1
      19: arraylength
      20: istore_2
      21: iconst_0
      22: istore_3
      23: iload_3
      24: iload_2
      25: if_icmpge     67
      28: aload_1
      29: iload_3
      30: aaload
      31: astore        4
      33: aload         4
      35: invokestatic  #84                 // Method cool/furry/mc/forge/projectexpansion/util/AdvancedAlchemicalChest.getRegistryBlock:(Lnet/minecraft/item/DyeColor;)Lnet/minecraftforge/fml/RegistryObject;
      38: astore        5
      40: aload         4
      42: invokestatic  #88                 // Method cool/furry/mc/forge/projectexpansion/util/AdvancedAlchemicalChest.getBlockEntityType:(Lnet/minecraft/item/DyeColor;)Lnet/minecraft/tileentity/TileEntityType;
      45: astore        6
      47: aload         6
      49: aload         4
      51: aload         5
      53: invokedynamic #101,  0            // InvokeDynamic #1:apply:(Lnet/minecraft/item/DyeColor;Lnet/minecraftforge/fml/RegistryObject;)Ljava/util/function/Function;
      58: invokestatic  #107                // Method net/minecraftforge/fml/client/registry/ClientRegistry.bindTileEntityRenderer:(Lnet/minecraft/tileentity/TileEntityType;Ljava/util/function/Function;)V
      61: iinc          3, 1
      64: goto          23
      67: return

  private static net.minecraft.client.renderer.tileentity.TileEntityRenderer lambda$clientSetup$3(net.minecraft.item.DyeColor, net.minecraftforge.fml.RegistryObject, net.minecraft.client.renderer.tileentity.TileEntityRendererDispatcher);
    descriptor: (Lnet/minecraft/item/DyeColor;Lnet/minecraftforge/fml/RegistryObject;Lnet/minecraft/client/renderer/tileentity/TileEntityRendererDispatcher;)Lnet/minecraft/client/renderer/tileentity/TileEntityRenderer;
    Code:
       0: new           #119                // class cool/furry/mc/forge/projectexpansion/rendering/ChestRenderer
       3: dup
       4: aload_2
       5: ldc           #121                // String textures/block/advanced_alchemical_chest/%s.png
       7: iconst_1
       8: anewarray     #4                  // class java/lang/Object
      11: dup
      12: iconst_0
      13: aload_0
      14: invokevirtual #125                // Method net/minecraft/item/DyeColor.func_176762_d:()Ljava/lang/String;
      17: aastore
      18: invokestatic  #131                // Method java/lang/String.format:(Ljava/lang/String;[Ljava/lang/Object;)Ljava/lang/String;
      21: invokestatic  #137                // Method cool/furry/mc/forge/projectexpansion/Main.rl:(Ljava/lang/String;)Lnet/minecraft/util/ResourceLocation;
      24: aload_1
      25: invokedynamic #150,  0            // InvokeDynamic #2:test:(Lnet/minecraftforge/fml/RegistryObject;)Ljava/util/function/Predicate;
      30: invokespecial #153                // Method cool/furry/mc/forge/projectexpansion/rendering/ChestRenderer."<init>":(Lnet/minecraft/client/renderer/tileentity/TileEntityRendererDispatcher;Lnet/minecraft/util/ResourceLocation;Ljava/util/function/Predicate;)V
      33: areturn

  private static boolean lambda$null$2(net.minecraftforge.fml.RegistryObject, net.minecraft.block.Block);
    descriptor: (Lnet/minecraftforge/fml/RegistryObject;Lnet/minecraft/block/Block;)Z
    Code:
       0: aload_1
       1: aload_0
       2: invokevirtual #160                // Method net/minecraftforge/fml/RegistryObject.get:()Lnet/minecraftforge/registries/IForgeRegistryEntry;
       5: if_acmpne     12
       8: iconst_1
       9: goto          13
      12: iconst_0
      13: ireturn

  private static java.util.function.BiFunction lambda$clientSetup$1();
    descriptor: ()Ljava/util/function/BiFunction;
    Code:
       0: invokedynamic #172,  0            // InvokeDynamic #3:apply:()Ljava/util/function/BiFunction;
       5: areturn

  private static net.minecraft.client.gui.screen.Screen lambda$null$0(net.minecraft.client.Minecraft, net.minecraft.client.gui.screen.Screen);
    descriptor: (Lnet/minecraft/client/Minecraft;Lnet/minecraft/client/gui/screen/Screen;)Lnet/minecraft/client/gui/screen/Screen;
    Code:
       0: new           #174                // class cool/furry/mc/forge/projectexpansion/config/ConfigMenu
       3: dup
       4: aload_1
       5: invokespecial #177                // Method cool/furry/mc/forge/projectexpansion/config/ConfigMenu."<init>":(Lnet/minecraft/client/gui/screen/Screen;)V
       8: areturn
}
