Compiled from "Main.java"
class cool.furry.mc.forge.projectexpansion.Main$1 extends net.minecraft.world.item.CreativeModeTab {
  final cool.furry.mc.forge.projectexpansion.Main this$0;
    descriptor: Lcool/furry/mc/forge/projectexpansion/Main;

  cool.furry.mc.forge.projectexpansion.Main$1(cool.furry.mc.forge.projectexpansion.Main, java.lang.String);
    descriptor: (Lcool/furry/mc/forge/projectexpansion/Main;Ljava/lang/String;)V
    Code:
       0: aload_0
       1: aload_1
       2: putfield      #15                 // Field this$0:Lcool/furry/mc/forge/projectexpansion/Main;
       5: aload_0
       6: aload_2
       7: invokespecial #18                 // Method net/minecraft/world/item/CreativeModeTab."<init>":(Ljava/lang/String;)V
      10: return

  public net.minecraft.world.item.ItemStack m_6976_();
    descriptor: ()Lnet/minecraft/world/item/ItemStack;
    Code:
       0: new           #31                 // class net/minecraft/world/item/ItemStack
       3: dup
       4: getstatic     #37                 // Field cool/furry/mc/forge/projectexpansion/registries/Items.FINAL_STAR:Lnet/minecraftforge/registries/RegistryObject;
       7: invokevirtual #43                 // Method net/minecraftforge/registries/RegistryObject.get:()Ljava/lang/Object;
      10: checkcast     #45                 // class net/minecraft/world/level/ItemLike
      13: invokespecial #48                 // Method net/minecraft/world/item/ItemStack."<init>":(Lnet/minecraft/world/level/ItemLike;)V
      16: areturn
}
