Compiled from "FortuneCoinToggler.java"
public class xreliquary.items.FortuneCoinToggler {
  private static xreliquary.items.FortuneCoinToggler coinToggler;
    descriptor: Lxreliquary/items/FortuneCoinToggler;

  public xreliquary.items.FortuneCoinToggler();
    descriptor: ()V
    Code:
       0: aload_0
       1: invokespecial #25                 // Method java/lang/Object."<init>":()V
       4: return

  public static void setCoinToggler(xreliquary.items.FortuneCoinToggler);
    descriptor: (Lxreliquary/items/FortuneCoinToggler;)V
    Code:
       0: aload_0
       1: putstatic     #30                 // Field coinToggler:Lxreliquary/items/FortuneCoinToggler;
       4: return

  public static void handleKeyInputEvent(net.minecraftforge.event.TickEvent$ClientTickEvent);
    descriptor: (Lnet/minecraftforge/event/TickEvent$ClientTickEvent;)V
    Code:
       0: getstatic     #39                 // Field xreliquary/client/ClientProxy.FORTUNE_COIN_TOGGLE_KEYBIND:Lnet/minecraft/client/settings/KeyBinding;
       3: invokevirtual #45                 // Method net/minecraft/client/settings/KeyBinding.func_151468_f:()Z
       6: ifeq          16
       9: getstatic     #30                 // Field coinToggler:Lxreliquary/items/FortuneCoinToggler;
      12: invokevirtual #48                 // Method findAndToggle:()Z
      15: pop
      16: return

  public boolean findAndToggle();
    descriptor: ()Z
    Code:
       0: invokestatic  #56                 // Method net/minecraft/client/Minecraft.func_71410_x:()Lnet/minecraft/client/Minecraft;
       3: getfield      #60                 // Field net/minecraft/client/Minecraft.field_71439_g:Lnet/minecraft/client/entity/player/ClientPlayerEntity;
       6: astore_1
       7: iconst_0
       8: istore_2
       9: iload_2
      10: aload_1
      11: getfield      #66                 // Field net/minecraft/entity/player/PlayerEntity.field_71071_by:Lnet/minecraft/entity/player/PlayerInventory;
      14: getfield      #72                 // Field net/minecraft/entity/player/PlayerInventory.field_70462_a:Lnet/minecraft/util/NonNullList;
      17: invokevirtual #78                 // Method net/minecraft/util/NonNullList.size:()I
      20: if_icmpge     86
      23: aload_1
      24: getfield      #66                 // Field net/minecraft/entity/player/PlayerEntity.field_71071_by:Lnet/minecraft/entity/player/PlayerInventory;
      27: getfield      #72                 // Field net/minecraft/entity/player/PlayerInventory.field_70462_a:Lnet/minecraft/util/NonNullList;
      30: iload_2
      31: invokevirtual #82                 // Method net/minecraft/util/NonNullList.get:(I)Ljava/lang/Object;
      34: checkcast     #84                 // class net/minecraft/item/ItemStack
      37: astore_3
      38: aload_3
      39: invokevirtual #88                 // Method net/minecraft/item/ItemStack.func_77973_b:()Lnet/minecraft/item/Item;
      42: getstatic     #94                 // Field xreliquary/init/ModItems.FORTUNE_COIN:Lnet/minecraftforge/fml/RegistryObject;
      45: invokevirtual #99                 // Method net/minecraftforge/fml/RegistryObject.get:()Lnet/minecraftforge/registries/IForgeRegistryEntry;
      48: if_acmpne     80
      51: new           #18                 // class xreliquary/network/PacketFortuneCoinTogglePressed
      54: dup
      55: getstatic     #103                // Field xreliquary/network/PacketFortuneCoinTogglePressed$InventoryType.MAIN:Lxreliquary/network/PacketFortuneCoinTogglePressed$InventoryType;
      58: iload_2
      59: invokespecial #106                // Method xreliquary/network/PacketFortuneCoinTogglePressed."<init>":(Lxreliquary/network/PacketFortuneCoinTogglePressed$InventoryType;I)V
      62: invokestatic  #112                // Method xreliquary/network/PacketHandler.sendToServer:(Ljava/lang/Object;)V
      65: getstatic     #94                 // Field xreliquary/init/ModItems.FORTUNE_COIN:Lnet/minecraftforge/fml/RegistryObject;
      68: invokevirtual #99                 // Method net/minecraftforge/fml/RegistryObject.get:()Lnet/minecraftforge/registries/IForgeRegistryEntry;
      71: checkcast     #114                // class xreliquary/items/FortuneCoinItem
      74: aload_3
      75: invokevirtual #118                // Method xreliquary/items/FortuneCoinItem.toggle:(Lnet/minecraft/item/ItemStack;)V
      78: iconst_1
      79: ireturn
      80: iinc          2, 1
      83: goto          9
      86: aload_1
      87: getfield      #66                 // Field net/minecraft/entity/player/PlayerEntity.field_71071_by:Lnet/minecraft/entity/player/PlayerInventory;
      90: getfield      #121                // Field net/minecraft/entity/player/PlayerInventory.field_184439_c:Lnet/minecraft/util/NonNullList;
      93: iconst_0
      94: invokevirtual #82                 // Method net/minecraft/util/NonNullList.get:(I)Ljava/lang/Object;
      97: checkcast     #84                 // class net/minecraft/item/ItemStack
     100: invokevirtual #88                 // Method net/minecraft/item/ItemStack.func_77973_b:()Lnet/minecraft/item/Item;
     103: getstatic     #94                 // Field xreliquary/init/ModItems.FORTUNE_COIN:Lnet/minecraftforge/fml/RegistryObject;
     106: invokevirtual #99                 // Method net/minecraftforge/fml/RegistryObject.get:()Lnet/minecraftforge/registries/IForgeRegistryEntry;
     109: if_acmpne     154
     112: new           #18                 // class xreliquary/network/PacketFortuneCoinTogglePressed
     115: dup
     116: getstatic     #124                // Field xreliquary/network/PacketFortuneCoinTogglePressed$InventoryType.OFF_HAND:Lxreliquary/network/PacketFortuneCoinTogglePressed$InventoryType;
     119: iconst_0
     120: invokespecial #106                // Method xreliquary/network/PacketFortuneCoinTogglePressed."<init>":(Lxreliquary/network/PacketFortuneCoinTogglePressed$InventoryType;I)V
     123: invokestatic  #112                // Method xreliquary/network/PacketHandler.sendToServer:(Ljava/lang/Object;)V
     126: getstatic     #94                 // Field xreliquary/init/ModItems.FORTUNE_COIN:Lnet/minecraftforge/fml/RegistryObject;
     129: invokevirtual #99                 // Method net/minecraftforge/fml/RegistryObject.get:()Lnet/minecraftforge/registries/IForgeRegistryEntry;
     132: checkcast     #114                // class xreliquary/items/FortuneCoinItem
     135: aload_1
     136: getfield      #66                 // Field net/minecraft/entity/player/PlayerEntity.field_71071_by:Lnet/minecraft/entity/player/PlayerInventory;
     139: getfield      #121                // Field net/minecraft/entity/player/PlayerInventory.field_184439_c:Lnet/minecraft/util/NonNullList;
     142: iconst_0
     143: invokevirtual #82                 // Method net/minecraft/util/NonNullList.get:(I)Ljava/lang/Object;
     146: checkcast     #84                 // class net/minecraft/item/ItemStack
     149: invokevirtual #118                // Method xreliquary/items/FortuneCoinItem.toggle:(Lnet/minecraft/item/ItemStack;)V
     152: iconst_1
     153: ireturn
     154: iconst_0
     155: ireturn

  static {};
    descriptor: ()V
    Code:
       0: new           #2                  // class xreliquary/items/FortuneCoinToggler
       3: dup
       4: invokespecial #132                // Method "<init>":()V
       7: putstatic     #30                 // Field coinToggler:Lxreliquary/items/FortuneCoinToggler;
      10: return
}
