Compiled from "PacketFortuneCoinTogglePressed.java"
class xreliquary.network.PacketFortuneCoinTogglePressed$1 {
  static final int[] $SwitchMap$xreliquary$network$PacketFortuneCoinTogglePressed$InventoryType;
    descriptor: [I

  static {};
    descriptor: ()V
    Code:
       0: invokestatic  #20                 // Method xreliquary/network/PacketFortuneCoinTogglePressed$InventoryType.values:()[Lxreliquary/network/PacketFortuneCoinTogglePressed$InventoryType;
       3: arraylength
       4: newarray       int
       6: putstatic     #22                 // Field $SwitchMap$xreliquary$network$PacketFortuneCoinTogglePressed$InventoryType:[I
       9: getstatic     #22                 // Field $SwitchMap$xreliquary$network$PacketFortuneCoinTogglePressed$InventoryType:[I
      12: getstatic     #26                 // Field xreliquary/network/PacketFortuneCoinTogglePressed$InventoryType.MAIN:Lxreliquary/network/PacketFortuneCoinTogglePressed$InventoryType;
      15: invokevirtual #30                 // Method xreliquary/network/PacketFortuneCoinTogglePressed$InventoryType.ordinal:()I
      18: iconst_1
      19: iastore
      20: goto          24
      23: astore_0
      24: getstatic     #22                 // Field $SwitchMap$xreliquary$network$PacketFortuneCoinTogglePressed$InventoryType:[I
      27: getstatic     #33                 // Field xreliquary/network/PacketFortuneCoinTogglePressed$InventoryType.OFF_HAND:Lxreliquary/network/PacketFortuneCoinTogglePressed$InventoryType;
      30: invokevirtual #30                 // Method xreliquary/network/PacketFortuneCoinTogglePressed$InventoryType.ordinal:()I
      33: iconst_2
      34: iastore
      35: goto          39
      38: astore_0
      39: getstatic     #22                 // Field $SwitchMap$xreliquary$network$PacketFortuneCoinTogglePressed$InventoryType:[I
      42: getstatic     #36                 // Field xreliquary/network/PacketFortuneCoinTogglePressed$InventoryType.BAUBLES:Lxreliquary/network/PacketFortuneCoinTogglePressed$InventoryType;
      45: invokevirtual #30                 // Method xreliquary/network/PacketFortuneCoinTogglePressed$InventoryType.ordinal:()I
      48: iconst_3
      49: iastore
      50: goto          54
      53: astore_0
      54: return
    Exception table:
       from    to  target type
           9    20    23   Class java/lang/NoSuchFieldError
          24    35    38   Class java/lang/NoSuchFieldError
          39    50    53   Class java/lang/NoSuchFieldError
}
