Compiled from "BlockEMCLink.java"
public class cool.furry.mc.forge.projectexpansion.block.BlockEMCLink extends net.minecraft.world.level.block.Block implements cool.furry.mc.forge.projectexpansion.util.IHasMatter,net.minecraft.world.level.block.EntityBlock {
  private final cool.furry.mc.forge.projectexpansion.util.Matter matter;
    descriptor: Lcool/furry/mc/forge/projectexpansion/util/Matter;

  public cool.furry.mc.forge.projectexpansion.block.BlockEMCLink(cool.furry.mc.forge.projectexpansion.util.Matter);
    descriptor: (Lcool/furry/mc/forge/projectexpansion/util/Matter;)V
    Code:
       0: aload_0
       1: getstatic     #39                 // Field net/minecraft/world/level/material/Material.f_76278_:Lnet/minecraft/world/level/material/Material;
       4: invokestatic  #43                 // Method net/minecraft/world/level/block/state/BlockBehaviour$Properties.m_60939_:(Lnet/minecraft/world/level/material/Material;)Lnet/minecraft/world/level/block/state/BlockBehaviour$Properties;
       7: ldc           #44                 // float 1.5f
       9: ldc           #45                 // float 30.0f
      11: invokevirtual #49                 // Method net/minecraft/world/level/block/state/BlockBehaviour$Properties.m_60913_:(FF)Lnet/minecraft/world/level/block/state/BlockBehaviour$Properties;
      14: invokevirtual #53                 // Method net/minecraft/world/level/block/state/BlockBehaviour$Properties.m_60999_:()Lnet/minecraft/world/level/block/state/BlockBehaviour$Properties;
      17: aload_1
      18: invokedynamic #73,  0             // InvokeDynamic #0:applyAsInt:(Lcool/furry/mc/forge/projectexpansion/util/Matter;)Ljava/util/function/ToIntFunction;
      23: invokevirtual #77                 // Method net/minecraft/world/level/block/state/BlockBehaviour$Properties.m_60953_:(Ljava/util/function/ToIntFunction;)Lnet/minecraft/world/level/block/state/BlockBehaviour$Properties;
      26: invokespecial #80                 // Method net/minecraft/world/level/block/Block."<init>":(Lnet/minecraft/world/level/block/state/BlockBehaviour$Properties;)V
      29: aload_0
      30: aload_1
      31: putfield      #82                 // Field matter:Lcool/furry/mc/forge/projectexpansion/util/Matter;
      34: aload_0
      35: aload_0
      36: getfield      #86                 // Field f_49792_:Lnet/minecraft/world/level/block/state/StateDefinition;
      39: invokevirtual #90                 // Method net/minecraft/world/level/block/state/StateDefinition.m_61090_:()Lnet/minecraft/world/level/block/state/StateHolder;
      42: checkcast     #92                 // class net/minecraft/world/level/block/state/BlockState
      45: getstatic     #98                 // Field cool/furry/mc/forge/projectexpansion/block/entity/BlockEntityNBTFilterable.FILTER:Lnet/minecraft/world/level/block/state/properties/BooleanProperty;
      48: iconst_1
      49: invokestatic  #104                // Method java/lang/Boolean.valueOf:(Z)Ljava/lang/Boolean;
      52: invokevirtual #108                // Method net/minecraft/world/level/block/state/BlockState.m_61124_:(Lnet/minecraft/world/level/block/state/properties/Property;Ljava/lang/Comparable;)Ljava/lang/Object;
      55: checkcast     #92                 // class net/minecraft/world/level/block/state/BlockState
      58: invokevirtual #112                // Method m_49959_:(Lnet/minecraft/world/level/block/state/BlockState;)V
      61: return

  public net.minecraft.world.level.block.entity.BlockEntity m_142194_(net.minecraft.core.BlockPos, net.minecraft.world.level.block.state.BlockState);
    descriptor: (Lnet/minecraft/core/BlockPos;Lnet/minecraft/world/level/block/state/BlockState;)Lnet/minecraft/world/level/block/entity/BlockEntity;
    Code:
       0: new           #119                // class cool/furry/mc/forge/projectexpansion/block/entity/BlockEntityEMCLink
       3: dup
       4: aload_1
       5: aload_2
       6: invokespecial #122                // Method cool/furry/mc/forge/projectexpansion/block/entity/BlockEntityEMCLink."<init>":(Lnet/minecraft/core/BlockPos;Lnet/minecraft/world/level/block/state/BlockState;)V
       9: areturn

  public void m_5871_(net.minecraft.world.item.ItemStack, net.minecraft.world.level.BlockGetter, java.util.List<net.minecraft.network.chat.Component>, net.minecraft.world.item.TooltipFlag);
    descriptor: (Lnet/minecraft/world/item/ItemStack;Lnet/minecraft/world/level/BlockGetter;Ljava/util/List;Lnet/minecraft/world/item/TooltipFlag;)V
    Code:
       0: aload_0
       1: aload_1
       2: aload_2
       3: aload_3
       4: aload         4
       6: invokespecial #135                // Method net/minecraft/world/level/block/Block.m_5871_:(Lnet/minecraft/world/item/ItemStack;Lnet/minecraft/world/level/BlockGetter;Ljava/util/List;Lnet/minecraft/world/item/TooltipFlag;)V
       9: aload_3
      10: getstatic     #139                // Field cool/furry/mc/forge/projectexpansion/util/Lang$Blocks.EMC_LINK_TOOLTIP:Lcool/furry/mc/forge/projectexpansion/util/Lang$Blocks;
      13: getstatic     #145                // Field net/minecraft/ChatFormatting.GRAY:Lnet/minecraft/ChatFormatting;
      16: iconst_0
      17: anewarray     #147                // class java/lang/Object
      20: invokevirtual #151                // Method cool/furry/mc/forge/projectexpansion/util/Lang$Blocks.translateColored:(Lnet/minecraft/ChatFormatting;[Ljava/lang/Object;)Lnet/minecraft/network/chat/MutableComponent;
      23: invokeinterface #157,  2          // InterfaceMethod java/util/List.add:(Ljava/lang/Object;)Z
      28: pop
      29: aload_3
      30: getstatic     #160                // Field cool/furry/mc/forge/projectexpansion/util/Lang$Blocks.EMC_LINK_LIMIT_ITEMS:Lcool/furry/mc/forge/projectexpansion/util/Lang$Blocks;
      33: getstatic     #145                // Field net/minecraft/ChatFormatting.GRAY:Lnet/minecraft/ChatFormatting;
      36: iconst_1
      37: anewarray     #147                // class java/lang/Object
      40: dup
      41: iconst_0
      42: aload_0
      43: invokevirtual #164                // Method getMatter:()Lcool/furry/mc/forge/projectexpansion/util/Matter;
      46: invokevirtual #170                // Method cool/furry/mc/forge/projectexpansion/util/Matter.getEMCLinkItemLimitComponent:()Lnet/minecraft/network/chat/MutableComponent;
      49: aastore
      50: invokevirtual #151                // Method cool/furry/mc/forge/projectexpansion/util/Lang$Blocks.translateColored:(Lnet/minecraft/ChatFormatting;[Ljava/lang/Object;)Lnet/minecraft/network/chat/MutableComponent;
      53: invokeinterface #157,  2          // InterfaceMethod java/util/List.add:(Ljava/lang/Object;)Z
      58: pop
      59: aload_3
      60: getstatic     #173                // Field cool/furry/mc/forge/projectexpansion/util/Lang$Blocks.EMC_LINK_LIMIT_FLUIDS:Lcool/furry/mc/forge/projectexpansion/util/Lang$Blocks;
      63: getstatic     #145                // Field net/minecraft/ChatFormatting.GRAY:Lnet/minecraft/ChatFormatting;
      66: iconst_1
      67: anewarray     #147                // class java/lang/Object
      70: dup
      71: iconst_0
      72: aload_0
      73: invokevirtual #164                // Method getMatter:()Lcool/furry/mc/forge/projectexpansion/util/Matter;
      76: invokevirtual #176                // Method cool/furry/mc/forge/projectexpansion/util/Matter.getEMCLinkFluidLimitComponent:()Lnet/minecraft/network/chat/MutableComponent;
      79: aastore
      80: invokevirtual #151                // Method cool/furry/mc/forge/projectexpansion/util/Lang$Blocks.translateColored:(Lnet/minecraft/ChatFormatting;[Ljava/lang/Object;)Lnet/minecraft/network/chat/MutableComponent;
      83: invokeinterface #157,  2          // InterfaceMethod java/util/List.add:(Ljava/lang/Object;)Z
      88: pop
      89: aload_3
      90: getstatic     #179                // Field cool/furry/mc/forge/projectexpansion/util/Lang$Blocks.EMC_LINK_FLUID_EXPORT_EFFICIENCY:Lcool/furry/mc/forge/projectexpansion/util/Lang$Blocks;
      93: getstatic     #145                // Field net/minecraft/ChatFormatting.GRAY:Lnet/minecraft/ChatFormatting;
      96: iconst_1
      97: anewarray     #147                // class java/lang/Object
     100: dup
     101: iconst_0
     102: new           #181                // class net/minecraft/network/chat/TextComponent
     105: dup
     106: aload_0
     107: invokevirtual #164                // Method getMatter:()Lcool/furry/mc/forge/projectexpansion/util/Matter;
     110: invokevirtual #185                // Method cool/furry/mc/forge/projectexpansion/util/Matter.getFluidEfficiencyPercentage:()I
     113: invokedynamic #197,  0            // InvokeDynamic #1:makeConcatWithConstants:(I)Ljava/lang/String;
     118: invokespecial #200                // Method net/minecraft/network/chat/TextComponent."<init>":(Ljava/lang/String;)V
     121: getstatic     #206                // Field cool/furry/mc/forge/projectexpansion/util/ColorStyle.GREEN:Lnet/minecraft/network/chat/Style;
     124: invokevirtual #210                // Method net/minecraft/network/chat/TextComponent.m_6270_:(Lnet/minecraft/network/chat/Style;)Lnet/minecraft/network/chat/MutableComponent;
     127: aastore
     128: invokevirtual #151                // Method cool/furry/mc/forge/projectexpansion/util/Lang$Blocks.translateColored:(Lnet/minecraft/ChatFormatting;[Ljava/lang/Object;)Lnet/minecraft/network/chat/MutableComponent;
     131: invokeinterface #157,  2          // InterfaceMethod java/util/List.add:(Ljava/lang/Object;)Z
     136: pop
     137: aload_3
     138: getstatic     #213                // Field cool/furry/mc/forge/projectexpansion/util/Lang$Blocks.EMC_LINK_LIMIT_EMC:Lcool/furry/mc/forge/projectexpansion/util/Lang$Blocks;
     141: getstatic     #145                // Field net/minecraft/ChatFormatting.GRAY:Lnet/minecraft/ChatFormatting;
     144: iconst_1
     145: anewarray     #147                // class java/lang/Object
     148: dup
     149: iconst_0
     150: aload_0
     151: invokevirtual #164                // Method getMatter:()Lcool/furry/mc/forge/projectexpansion/util/Matter;
     154: invokevirtual #216                // Method cool/furry/mc/forge/projectexpansion/util/Matter.getEMCLinkEMCLimitComponent:()Lnet/minecraft/network/chat/MutableComponent;
     157: aastore
     158: invokevirtual #151                // Method cool/furry/mc/forge/projectexpansion/util/Lang$Blocks.translateColored:(Lnet/minecraft/ChatFormatting;[Ljava/lang/Object;)Lnet/minecraft/network/chat/MutableComponent;
     161: invokeinterface #157,  2          // InterfaceMethod java/util/List.add:(Ljava/lang/Object;)Z
     166: pop
     167: aload_3
     168: getstatic     #220                // Field cool/furry/mc/forge/projectexpansion/util/Lang.SEE_WIKI:Lcool/furry/mc/forge/projectexpansion/util/Lang;
     171: getstatic     #223                // Field net/minecraft/ChatFormatting.AQUA:Lnet/minecraft/ChatFormatting;
     174: iconst_0
     175: anewarray     #147                // class java/lang/Object
     178: invokevirtual #224                // Method cool/furry/mc/forge/projectexpansion/util/Lang.translateColored:(Lnet/minecraft/ChatFormatting;[Ljava/lang/Object;)Lnet/minecraft/network/chat/MutableComponent;
     181: invokeinterface #157,  2          // InterfaceMethod java/util/List.add:(Ljava/lang/Object;)Z
     186: pop
     187: return

  public net.minecraft.world.InteractionResult m_6227_(net.minecraft.world.level.block.state.BlockState, net.minecraft.world.level.Level, net.minecraft.core.BlockPos, net.minecraft.world.entity.player.Player, net.minecraft.world.InteractionHand, net.minecraft.world.phys.BlockHitResult);
    descriptor: (Lnet/minecraft/world/level/block/state/BlockState;Lnet/minecraft/world/level/Level;Lnet/minecraft/core/BlockPos;Lnet/minecraft/world/entity/player/Player;Lnet/minecraft/world/InteractionHand;Lnet/minecraft/world/phys/BlockHitResult;)Lnet/minecraft/world/InteractionResult;
    Code:
       0: aload_2
       1: getfield      #241                // Field net/minecraft/world/level/Level.f_46443_:Z
       4: ifeq          11
       7: getstatic     #247                // Field net/minecraft/world/InteractionResult.SUCCESS:Lnet/minecraft/world/InteractionResult;
      10: areturn
      11: aload_2
      12: aload_3
      13: invokevirtual #251                // Method net/minecraft/world/level/Level.m_7702_:(Lnet/minecraft/core/BlockPos;)Lnet/minecraft/world/level/block/entity/BlockEntity;
      16: astore        7
      18: aload         7
      20: instanceof    #119                // class cool/furry/mc/forge/projectexpansion/block/entity/BlockEntityEMCLink
      23: ifeq          43
      26: aload         7
      28: checkcast     #119                // class cool/furry/mc/forge/projectexpansion/block/entity/BlockEntityEMCLink
      31: astore        8
      33: aload         8
      35: aload         4
      37: aload         5
      39: invokevirtual #255                // Method cool/furry/mc/forge/projectexpansion/block/entity/BlockEntityEMCLink.handleActivation:(Lnet/minecraft/world/entity/player/Player;Lnet/minecraft/world/InteractionHand;)Lnet/minecraft/world/InteractionResult;
      42: areturn
      43: getstatic     #260                // Field net/minecraft/world/InteractionResult.PASS:Lnet/minecraft/world/InteractionResult;
      46: areturn

  public void m_6402_(net.minecraft.world.level.Level, net.minecraft.core.BlockPos, net.minecraft.world.level.block.state.BlockState, net.minecraft.world.entity.LivingEntity, net.minecraft.world.item.ItemStack);
    descriptor: (Lnet/minecraft/world/level/Level;Lnet/minecraft/core/BlockPos;Lnet/minecraft/world/level/block/state/BlockState;Lnet/minecraft/world/entity/LivingEntity;Lnet/minecraft/world/item/ItemStack;)V
    Code:
       0: aload_1
       1: aload_2
       2: invokevirtual #251                // Method net/minecraft/world/level/Level.m_7702_:(Lnet/minecraft/core/BlockPos;)Lnet/minecraft/world/level/block/entity/BlockEntity;
       5: astore        6
       7: aload         6
       9: instanceof    #119                // class cool/furry/mc/forge/projectexpansion/block/entity/BlockEntityEMCLink
      12: ifeq          31
      15: aload         6
      17: checkcast     #119                // class cool/furry/mc/forge/projectexpansion/block/entity/BlockEntityEMCLink
      20: astore        7
      22: aload         7
      24: aload         4
      26: aload         5
      28: invokevirtual #277                // Method cool/furry/mc/forge/projectexpansion/block/entity/BlockEntityEMCLink.handlePlace:(Lnet/minecraft/world/entity/LivingEntity;Lnet/minecraft/world/item/ItemStack;)V
      31: return

  public cool.furry.mc.forge.projectexpansion.util.Matter getMatter();
    descriptor: ()Lcool/furry/mc/forge/projectexpansion/util/Matter;
    Code:
       0: aload_0
       1: getfield      #82                 // Field matter:Lcool/furry/mc/forge/projectexpansion/util/Matter;
       4: areturn

  protected void m_7926_(net.minecraft.world.level.block.state.StateDefinition$Builder<net.minecraft.world.level.block.Block, net.minecraft.world.level.block.state.BlockState>);
    descriptor: (Lnet/minecraft/world/level/block/state/StateDefinition$Builder;)V
    Code:
       0: aload_1
       1: iconst_1
       2: anewarray     #285                // class net/minecraft/world/level/block/state/properties/Property
       5: dup
       6: iconst_0
       7: getstatic     #98                 // Field cool/furry/mc/forge/projectexpansion/block/entity/BlockEntityNBTFilterable.FILTER:Lnet/minecraft/world/level/block/state/properties/BooleanProperty;
      10: aastore
      11: invokevirtual #289                // Method net/minecraft/world/level/block/state/StateDefinition$Builder.m_61104_:([Lnet/minecraft/world/level/block/state/properties/Property;)Lnet/minecraft/world/level/block/state/StateDefinition$Builder;
      14: pop
      15: aload_0
      16: aload_1
      17: invokespecial #291                // Method net/minecraft/world/level/block/Block.m_7926_:(Lnet/minecraft/world/level/block/state/StateDefinition$Builder;)V
      20: return

  public <T extends net.minecraft.world.level.block.entity.BlockEntity> net.minecraft.world.level.block.entity.BlockEntityTicker<T> m_142354_(net.minecraft.world.level.Level, net.minecraft.world.level.block.state.BlockState, net.minecraft.world.level.block.entity.BlockEntityType<T>);
    descriptor: (Lnet/minecraft/world/level/Level;Lnet/minecraft/world/level/block/state/BlockState;Lnet/minecraft/world/level/block/entity/BlockEntityType;)Lnet/minecraft/world/level/block/entity/BlockEntityTicker;
    Code:
       0: aload_3
       1: getstatic     #303                // Field cool/furry/mc/forge/projectexpansion/registries/BlockEntityTypes.EMC_LINK:Lnet/minecraftforge/registries/RegistryObject;
       4: invokevirtual #309                // Method net/minecraftforge/registries/RegistryObject.get:()Ljava/lang/Object;
       7: if_acmpne     23
      10: aload_1
      11: getfield      #241                // Field net/minecraft/world/level/Level.f_46443_:Z
      14: ifne          23
      17: invokedynamic #319,  0            // InvokeDynamic #2:m_155252_:()Lnet/minecraft/world/level/block/entity/BlockEntityTicker;
      22: areturn
      23: aconst_null
      24: areturn

  public net.minecraft.world.level.material.PushReaction m_5537_(net.minecraft.world.level.block.state.BlockState);
    descriptor: (Lnet/minecraft/world/level/block/state/BlockState;)Lnet/minecraft/world/level/material/PushReaction;
    Code:
       0: getstatic     #330                // Field net/minecraft/world/level/material/PushReaction.BLOCK:Lnet/minecraft/world/level/material/PushReaction;
       3: areturn

  public net.minecraft.world.level.material.MaterialColor getMapColor(net.minecraft.world.level.block.state.BlockState, net.minecraft.world.level.BlockGetter, net.minecraft.core.BlockPos, net.minecraft.world.level.material.MaterialColor);
    descriptor: (Lnet/minecraft/world/level/block/state/BlockState;Lnet/minecraft/world/level/BlockGetter;Lnet/minecraft/core/BlockPos;Lnet/minecraft/world/level/material/MaterialColor;)Lnet/minecraft/world/level/material/MaterialColor;
    Code:
       0: aload_0
       1: getfield      #82                 // Field matter:Lcool/furry/mc/forge/projectexpansion/util/Matter;
       4: getfield      #336                // Field cool/furry/mc/forge/projectexpansion/util/Matter.materialColor:Ljava/util/function/Supplier;
       7: ifnonnull     14
      10: aconst_null
      11: goto          29
      14: aload_0
      15: getfield      #82                 // Field matter:Lcool/furry/mc/forge/projectexpansion/util/Matter;
      18: getfield      #336                // Field cool/furry/mc/forge/projectexpansion/util/Matter.materialColor:Ljava/util/function/Supplier;
      21: invokeinterface #339,  1          // InterfaceMethod java/util/function/Supplier.get:()Ljava/lang/Object;
      26: checkcast     #341                // class net/minecraft/world/level/material/MaterialColor
      29: astore        5
      31: aload         5
      33: ifnull        41
      36: aload         5
      38: goto          50
      41: aload_0
      42: aload_1
      43: aload_2
      44: aload_3
      45: aload         4
      47: invokespecial #343                // Method net/minecraft/world/level/block/Block.getMapColor:(Lnet/minecraft/world/level/block/state/BlockState;Lnet/minecraft/world/level/BlockGetter;Lnet/minecraft/core/BlockPos;Lnet/minecraft/world/level/material/MaterialColor;)Lnet/minecraft/world/level/material/MaterialColor;
      50: areturn

  private static int lambda$new$0(cool.furry.mc.forge.projectexpansion.util.Matter, net.minecraft.world.level.block.state.BlockState);
    descriptor: (Lcool/furry/mc/forge/projectexpansion/util/Matter;Lnet/minecraft/world/level/block/state/BlockState;)I
    Code:
       0: aload_0
       1: invokevirtual #349                // Method cool/furry/mc/forge/projectexpansion/util/Matter.ordinal:()I
       4: bipush        15
       6: invokestatic  #355                // Method java/lang/Math.min:(II)I
       9: ireturn
}
