Compiled from "BasicDataComponentTypes.java"
public final class cool.furry.mc.neoforge.projectexpansion.util.BasicDataComponentTypes$StringValue extends java.lang.Record {
  private final java.lang.String value;
    descriptor: Ljava/lang/String;

  public static final com.mojang.serialization.Codec<cool.furry.mc.neoforge.projectexpansion.util.BasicDataComponentTypes$StringValue> CODEC;
    descriptor: Lcom/mojang/serialization/Codec;

  public static final net.minecraft.network.codec.StreamCodec<net.minecraft.network.RegistryFriendlyByteBuf, cool.furry.mc.neoforge.projectexpansion.util.BasicDataComponentTypes$StringValue> STREAM_CODEC;
    descriptor: Lnet/minecraft/network/codec/StreamCodec;

  public cool.furry.mc.neoforge.projectexpansion.util.BasicDataComponentTypes$StringValue(java.lang.String);
    descriptor: (Ljava/lang/String;)V
    Code:
       0: aload_0
       1: invokespecial #1                  // Method java/lang/Record."<init>":()V
       4: aload_0
       5: aload_1
       6: putfield      #7                  // Field value:Ljava/lang/String;
       9: return

  public final java.lang.String toString();
    descriptor: ()Ljava/lang/String;
    Code:
       0: aload_0
       1: invokedynamic #51,  0             // InvokeDynamic #2:toString:(Lcool/furry/mc/neoforge/projectexpansion/util/BasicDataComponentTypes$StringValue;)Ljava/lang/String;
       6: areturn

  public final int hashCode();
    descriptor: ()I
    Code:
       0: aload_0
       1: invokedynamic #55,  0             // InvokeDynamic #2:hashCode:(Lcool/furry/mc/neoforge/projectexpansion/util/BasicDataComponentTypes$StringValue;)I
       6: ireturn

  public final boolean equals(java.lang.Object);
    descriptor: (Ljava/lang/Object;)Z
    Code:
       0: aload_0
       1: aload_1
       2: invokedynamic #59,  0             // InvokeDynamic #2:equals:(Lcool/furry/mc/neoforge/projectexpansion/util/BasicDataComponentTypes$StringValue;Ljava/lang/Object;)Z
       7: ireturn

  public java.lang.String value();
    descriptor: ()Ljava/lang/String;
    Code:
       0: aload_0
       1: getfield      #7                  // Field value:Ljava/lang/String;
       4: areturn

  private static com.mojang.datafixers.kinds.App lambda$static$0(com.mojang.serialization.codecs.RecordCodecBuilder$Instance);
    descriptor: (Lcom/mojang/serialization/codecs/RecordCodecBuilder$Instance;)Lcom/mojang/datafixers/kinds/App;
    Code:
       0: aload_0
       1: getstatic     #13                 // Field com/mojang/serialization/Codec.STRING:Lcom/mojang/serialization/codecs/PrimitiveCodec;
       4: ldc           #21                 // String Value
       6: invokeinterface #23,  2           // InterfaceMethod com/mojang/serialization/codecs/PrimitiveCodec.fieldOf:(Ljava/lang/String;)Lcom/mojang/serialization/MapCodec;
      11: invokedynamic #29,  0             // InvokeDynamic #0:apply:()Ljava/util/function/Function;
      16: invokevirtual #33                 // Method com/mojang/serialization/MapCodec.forGetter:(Ljava/util/function/Function;)Lcom/mojang/serialization/codecs/RecordCodecBuilder;
      19: invokevirtual #39                 // Method com/mojang/serialization/codecs/RecordCodecBuilder$Instance.group:(Lcom/mojang/datafixers/kinds/App;)Lcom/mojang/datafixers/Products$P1;
      22: aload_0
      23: invokedynamic #45,  0             // InvokeDynamic #1:apply:()Ljava/util/function/Function;
      28: invokevirtual #46                 // Method com/mojang/datafixers/Products$P1.apply:(Lcom/mojang/datafixers/kinds/Applicative;Ljava/util/function/Function;)Lcom/mojang/datafixers/kinds/App;
      31: areturn

  static {};
    descriptor: ()V
    Code:
       0: invokedynamic #63,  0             // InvokeDynamic #3:apply:()Ljava/util/function/Function;
       5: invokestatic  #64                 // Method com/mojang/serialization/codecs/RecordCodecBuilder.create:(Ljava/util/function/Function;)Lcom/mojang/serialization/Codec;
       8: putstatic     #70                 // Field CODEC:Lcom/mojang/serialization/Codec;
      11: getstatic     #74                 // Field net/minecraft/network/codec/ByteBufCodecs.STRING_UTF8:Lnet/minecraft/network/codec/StreamCodec;
      14: invokedynamic #29,  0             // InvokeDynamic #0:apply:()Ljava/util/function/Function;
      19: invokedynamic #45,  0             // InvokeDynamic #1:apply:()Ljava/util/function/Function;
      24: invokestatic  #80                 // InterfaceMethod net/minecraft/network/codec/StreamCodec.composite:(Lnet/minecraft/network/codec/StreamCodec;Ljava/util/function/Function;Ljava/util/function/Function;)Lnet/minecraft/network/codec/StreamCodec;
      27: putstatic     #86                 // Field STREAM_CODEC:Lnet/minecraft/network/codec/StreamCodec;
      30: return
}
