Compiled from "BlockAdvancedAlchemicalChest.java"
public class cool.furry.mc.neoforge.projectexpansion.block.BlockAdvancedAlchemicalChest extends net.minecraft.world.level.block.HorizontalDirectionalBlock implements net.minecraft.world.level.block.EntityBlock,net.minecraft.world.level.block.SimpleWaterloggedBlock,cool.furry.mc.neoforge.projectexpansion.util.IHasColor {
  public static final net.minecraft.world.level.block.state.properties.BooleanProperty WATERLOGGED;
    descriptor: Lnet/minecraft/world/level/block/state/properties/BooleanProperty;

  private static final net.minecraft.world.phys.shapes.VoxelShape SHAPE;
    descriptor: Lnet/minecraft/world/phys/shapes/VoxelShape;

  private final net.minecraft.world.item.DyeColor color;
    descriptor: Lnet/minecraft/world/item/DyeColor;

  public cool.furry.mc.neoforge.projectexpansion.block.BlockAdvancedAlchemicalChest(net.minecraft.world.level.block.state.BlockBehaviour$Properties, net.minecraft.world.item.DyeColor);
    descriptor: (Lnet/minecraft/world/level/block/state/BlockBehaviour$Properties;Lnet/minecraft/world/item/DyeColor;)V
    Code:
       0: aload_0
       1: aload_1
       2: invokespecial #1                  // Method net/minecraft/world/level/block/HorizontalDirectionalBlock."<init>":(Lnet/minecraft/world/level/block/state/BlockBehaviour$Properties;)V
       5: aload_0
       6: aload_0
       7: getfield      #7                  // Field stateDefinition:Lnet/minecraft/world/level/block/state/StateDefinition;
      10: invokevirtual #13                 // Method net/minecraft/world/level/block/state/StateDefinition.any:()Lnet/minecraft/world/level/block/state/StateHolder;
      13: checkcast     #19                 // class net/minecraft/world/level/block/state/BlockState
      16: getstatic     #21                 // Field FACING:Lnet/minecraft/world/level/block/state/properties/DirectionProperty;
      19: getstatic     #25                 // Field net/minecraft/core/Direction.NORTH:Lnet/minecraft/core/Direction;
      22: invokevirtual #31                 // Method net/minecraft/world/level/block/state/BlockState.setValue:(Lnet/minecraft/world/level/block/state/properties/Property;Ljava/lang/Comparable;)Ljava/lang/Object;
      25: checkcast     #19                 // class net/minecraft/world/level/block/state/BlockState
      28: getstatic     #35                 // Field WATERLOGGED:Lnet/minecraft/world/level/block/state/properties/BooleanProperty;
      31: iconst_0
      32: invokestatic  #39                 // Method java/lang/Boolean.valueOf:(Z)Ljava/lang/Boolean;
      35: invokevirtual #31                 // Method net/minecraft/world/level/block/state/BlockState.setValue:(Lnet/minecraft/world/level/block/state/properties/Property;Ljava/lang/Comparable;)Ljava/lang/Object;
      38: checkcast     #19                 // class net/minecraft/world/level/block/state/BlockState
      41: invokevirtual #45                 // Method registerDefaultState:(Lnet/minecraft/world/level/block/state/BlockState;)V
      44: aload_0
      45: aload_2
      46: putfield      #49                 // Field color:Lnet/minecraft/world/item/DyeColor;
      49: return

  public static net.minecraft.world.level.block.state.BlockBehaviour$Properties getProperties();
    descriptor: ()Lnet/minecraft/world/level/block/state/BlockBehaviour$Properties;
    Code:
       0: invokestatic  #53                 // Method net/minecraft/world/level/block/state/BlockBehaviour$Properties.of:()Lnet/minecraft/world/level/block/state/BlockBehaviour$Properties;
       3: invokevirtual #59                 // Method net/minecraft/world/level/block/state/BlockBehaviour$Properties.requiresCorrectToolForDrops:()Lnet/minecraft/world/level/block/state/BlockBehaviour$Properties;
       6: ldc           #62                 // float 10.0f
       8: ldc           #63                 // float 3600000.0f
      10: invokevirtual #64                 // Method net/minecraft/world/level/block/state/BlockBehaviour$Properties.strength:(FF)Lnet/minecraft/world/level/block/state/BlockBehaviour$Properties;
      13: invokedynamic #68,  0             // InvokeDynamic #0:applyAsInt:()Ljava/util/function/ToIntFunction;
      18: invokevirtual #72                 // Method net/minecraft/world/level/block/state/BlockBehaviour$Properties.lightLevel:(Ljava/util/function/ToIntFunction;)Lnet/minecraft/world/level/block/state/BlockBehaviour$Properties;
      21: areturn

  public net.minecraft.world.item.DyeColor getColor();
    descriptor: ()Lnet/minecraft/world/item/DyeColor;
    Code:
       0: aload_0
       1: getfield      #49                 // Field color:Lnet/minecraft/world/item/DyeColor;
       4: areturn

  public void appendHoverText(net.minecraft.world.item.ItemStack, net.minecraft.world.item.Item$TooltipContext, java.util.List<net.minecraft.network.chat.Component>, net.minecraft.world.item.TooltipFlag);
    descriptor: (Lnet/minecraft/world/item/ItemStack;Lnet/minecraft/world/item/Item$TooltipContext;Ljava/util/List;Lnet/minecraft/world/item/TooltipFlag;)V
    Code:
       0: aload_0
       1: aload_1
       2: aload_2
       3: aload_3
       4: aload         4
       6: invokespecial #76                 // Method net/minecraft/world/level/block/HorizontalDirectionalBlock.appendHoverText:(Lnet/minecraft/world/item/ItemStack;Lnet/minecraft/world/item/Item$TooltipContext;Ljava/util/List;Lnet/minecraft/world/item/TooltipFlag;)V
       9: aload_3
      10: getstatic     #80                 // Field cool/furry/mc/neoforge/projectexpansion/util/Lang$Blocks.ADVANCED_ALCHEMICAL_CHEST_TOOLTIP:Lcool/furry/mc/neoforge/projectexpansion/util/Lang$Blocks;
      13: getstatic     #86                 // Field net/minecraft/ChatFormatting.GRAY:Lnet/minecraft/ChatFormatting;
      16: invokevirtual #92                 // Method cool/furry/mc/neoforge/projectexpansion/util/Lang$Blocks.translateColored:(Lnet/minecraft/ChatFormatting;)Lnet/minecraft/network/chat/MutableComponent;
      19: invokeinterface #96,  2           // InterfaceMethod java/util/List.add:(Ljava/lang/Object;)Z
      24: pop
      25: aload_3
      26: getstatic     #102                // Field cool/furry/mc/neoforge/projectexpansion/util/Lang.SEE_WIKI:Lcool/furry/mc/neoforge/projectexpansion/util/Lang;
      29: getstatic     #108                // Field net/minecraft/ChatFormatting.AQUA:Lnet/minecraft/ChatFormatting;
      32: invokevirtual #111                // Method cool/furry/mc/neoforge/projectexpansion/util/Lang.translateColored:(Lnet/minecraft/ChatFormatting;)Lnet/minecraft/network/chat/MutableComponent;
      35: invokeinterface #96,  2           // InterfaceMethod java/util/List.add:(Ljava/lang/Object;)Z
      40: pop
      41: return

  public net.minecraft.world.level.block.RenderShape getRenderShape(net.minecraft.world.level.block.state.BlockState);
    descriptor: (Lnet/minecraft/world/level/block/state/BlockState;)Lnet/minecraft/world/level/block/RenderShape;
    Code:
       0: getstatic     #112                // Field net/minecraft/world/level/block/RenderShape.ENTITYBLOCK_ANIMATED:Lnet/minecraft/world/level/block/RenderShape;
       3: areturn

  public net.minecraft.world.phys.shapes.VoxelShape getShape(net.minecraft.world.level.block.state.BlockState, net.minecraft.world.level.BlockGetter, net.minecraft.core.BlockPos, net.minecraft.world.phys.shapes.CollisionContext);
    descriptor: (Lnet/minecraft/world/level/block/state/BlockState;Lnet/minecraft/world/level/BlockGetter;Lnet/minecraft/core/BlockPos;Lnet/minecraft/world/phys/shapes/CollisionContext;)Lnet/minecraft/world/phys/shapes/VoxelShape;
    Code:
       0: getstatic     #118                // Field SHAPE:Lnet/minecraft/world/phys/shapes/VoxelShape;
       3: areturn

  public net.minecraft.world.level.block.entity.BlockEntity newBlockEntity(net.minecraft.core.BlockPos, net.minecraft.world.level.block.state.BlockState);
    descriptor: (Lnet/minecraft/core/BlockPos;Lnet/minecraft/world/level/block/state/BlockState;)Lnet/minecraft/world/level/block/entity/BlockEntity;
    Code:
       0: new           #122                // class cool/furry/mc/neoforge/projectexpansion/block/entity/BlockEntityAdvancedAlchemicalChest
       3: dup
       4: aload_1
       5: aload_2
       6: invokespecial #124                // Method cool/furry/mc/neoforge/projectexpansion/block/entity/BlockEntityAdvancedAlchemicalChest."<init>":(Lnet/minecraft/core/BlockPos;Lnet/minecraft/world/level/block/state/BlockState;)V
       9: areturn

  protected net.minecraft.world.InteractionResult useWithoutItem(net.minecraft.world.level.block.state.BlockState, net.minecraft.world.level.Level, net.minecraft.core.BlockPos, net.minecraft.world.entity.player.Player, net.minecraft.world.phys.BlockHitResult);
    descriptor: (Lnet/minecraft/world/level/block/state/BlockState;Lnet/minecraft/world/level/Level;Lnet/minecraft/core/BlockPos;Lnet/minecraft/world/entity/player/Player;Lnet/minecraft/world/phys/BlockHitResult;)Lnet/minecraft/world/InteractionResult;
    Code:
       0: aload_2
       1: getfield      #127                // Field net/minecraft/world/level/Level.isClientSide:Z
       4: ifeq          11
       7: getstatic     #133                // Field net/minecraft/world/InteractionResult.SUCCESS:Lnet/minecraft/world/InteractionResult;
      10: areturn
      11: ldc           #122                // class cool/furry/mc/neoforge/projectexpansion/block/entity/BlockEntityAdvancedAlchemicalChest
      13: aload_2
      14: aload_3
      15: invokestatic  #139                // Method moze_intel/projecte/utils/WorldHelper.getBlockEntity:(Ljava/lang/Class;Lnet/minecraft/world/level/BlockGetter;Lnet/minecraft/core/BlockPos;)Lnet/minecraft/world/level/block/entity/BlockEntity;
      18: checkcast     #122                // class cool/furry/mc/neoforge/projectexpansion/block/entity/BlockEntityAdvancedAlchemicalChest
      21: astore        6
      23: aload         6
      25: ifnonnull     32
      28: getstatic     #145                // Field net/minecraft/world/InteractionResult.FAIL:Lnet/minecraft/world/InteractionResult;
      31: areturn
      32: aload         4
      34: invokevirtual #148                // Method net/minecraft/world/entity/player/Player.getUsedItemHand:()Lnet/minecraft/world/InteractionHand;
      37: astore        7
      39: aload         4
      41: new           #154                // class cool/furry/mc/neoforge/projectexpansion/block/BlockAdvancedAlchemicalChest$ContainerProvider
      44: dup
      45: aload         6
      47: aload         7
      49: invokespecial #156                // Method cool/furry/mc/neoforge/projectexpansion/block/BlockAdvancedAlchemicalChest$ContainerProvider."<init>":(Lcool/furry/mc/neoforge/projectexpansion/block/entity/BlockEntityAdvancedAlchemicalChest;Lnet/minecraft/world/InteractionHand;)V
      52: aload         7
      54: aload         4
      56: aload_3
      57: invokedynamic #159,  0            // InvokeDynamic #1:accept:(Lnet/minecraft/world/InteractionHand;Lnet/minecraft/world/entity/player/Player;Lnet/minecraft/core/BlockPos;)Ljava/util/function/Consumer;
      62: invokevirtual #163                // Method net/minecraft/world/entity/player/Player.openMenu:(Lnet/minecraft/world/MenuProvider;Ljava/util/function/Consumer;)Ljava/util/OptionalInt;
      65: pop
      66: aload         4
      68: getstatic     #167                // Field net/minecraft/stats/Stats.OPEN_CHEST:Lnet/minecraft/resources/ResourceLocation;
      71: invokevirtual #173                // Method net/minecraft/world/entity/player/Player.awardStat:(Lnet/minecraft/resources/ResourceLocation;)V
      74: aload         4
      76: iconst_1
      77: invokestatic  #177                // Method net/minecraft/world/entity/monster/piglin/PiglinAi.angerNearbyPiglins:(Lnet/minecraft/world/entity/player/Player;Z)V
      80: getstatic     #183                // Field net/minecraft/world/InteractionResult.CONSUME:Lnet/minecraft/world/InteractionResult;
      83: areturn

  protected net.minecraft.world.ItemInteractionResult useItemOn(net.minecraft.world.item.ItemStack, net.minecraft.world.level.block.state.BlockState, net.minecraft.world.level.Level, net.minecraft.core.BlockPos, net.minecraft.world.entity.player.Player, net.minecraft.world.InteractionHand, net.minecraft.world.phys.BlockHitResult);
    descriptor: (Lnet/minecraft/world/item/ItemStack;Lnet/minecraft/world/level/block/state/BlockState;Lnet/minecraft/world/level/Level;Lnet/minecraft/core/BlockPos;Lnet/minecraft/world/entity/player/Player;Lnet/minecraft/world/InteractionHand;Lnet/minecraft/world/phys/BlockHitResult;)Lnet/minecraft/world/ItemInteractionResult;
    Code:
       0: aload_3
       1: getfield      #127                // Field net/minecraft/world/level/Level.isClientSide:Z
       4: ifeq          11
       7: getstatic     #186                // Field net/minecraft/world/ItemInteractionResult.SUCCESS:Lnet/minecraft/world/ItemInteractionResult;
      10: areturn
      11: ldc           #122                // class cool/furry/mc/neoforge/projectexpansion/block/entity/BlockEntityAdvancedAlchemicalChest
      13: aload_3
      14: aload         4
      16: invokestatic  #139                // Method moze_intel/projecte/utils/WorldHelper.getBlockEntity:(Ljava/lang/Class;Lnet/minecraft/world/level/BlockGetter;Lnet/minecraft/core/BlockPos;)Lnet/minecraft/world/level/block/entity/BlockEntity;
      19: checkcast     #122                // class cool/furry/mc/neoforge/projectexpansion/block/entity/BlockEntityAdvancedAlchemicalChest
      22: astore        8
      24: aload         8
      26: ifnonnull     33
      29: getstatic     #191                // Field net/minecraft/world/ItemInteractionResult.FAIL:Lnet/minecraft/world/ItemInteractionResult;
      32: areturn
      33: aload         5
      35: invokevirtual #193                // Method net/minecraft/world/entity/player/Player.isCrouching:()Z
      38: ifeq          56
      41: aload         5
      43: iconst_1
      44: invokestatic  #177                // Method net/minecraft/world/entity/monster/piglin/PiglinAi.angerNearbyPiglins:(Lnet/minecraft/world/entity/player/Player;Z)V
      47: aload         8
      49: aload         5
      51: aload_1
      52: invokevirtual #197                // Method cool/furry/mc/neoforge/projectexpansion/block/entity/BlockEntityAdvancedAlchemicalChest.handleItemActivation:(Lnet/minecraft/world/entity/player/Player;Lnet/minecraft/world/item/ItemStack;)Lnet/minecraft/world/ItemInteractionResult;
      55: areturn
      56: aload_0
      57: aload_1
      58: aload_2
      59: aload_3
      60: aload         4
      62: aload         5
      64: aload         6
      66: aload         7
      68: invokespecial #201                // Method net/minecraft/world/level/block/HorizontalDirectionalBlock.useItemOn:(Lnet/minecraft/world/item/ItemStack;Lnet/minecraft/world/level/block/state/BlockState;Lnet/minecraft/world/level/Level;Lnet/minecraft/core/BlockPos;Lnet/minecraft/world/entity/player/Player;Lnet/minecraft/world/InteractionHand;Lnet/minecraft/world/phys/BlockHitResult;)Lnet/minecraft/world/ItemInteractionResult;
      71: areturn

  public void setPlacedBy(net.minecraft.world.level.Level, net.minecraft.core.BlockPos, net.minecraft.world.level.block.state.BlockState, net.minecraft.world.entity.LivingEntity, net.minecraft.world.item.ItemStack);
    descriptor: (Lnet/minecraft/world/level/Level;Lnet/minecraft/core/BlockPos;Lnet/minecraft/world/level/block/state/BlockState;Lnet/minecraft/world/entity/LivingEntity;Lnet/minecraft/world/item/ItemStack;)V
    Code:
       0: ldc           #122                // class cool/furry/mc/neoforge/projectexpansion/block/entity/BlockEntityAdvancedAlchemicalChest
       2: aload_1
       3: aload_2
       4: invokestatic  #139                // Method moze_intel/projecte/utils/WorldHelper.getBlockEntity:(Ljava/lang/Class;Lnet/minecraft/world/level/BlockGetter;Lnet/minecraft/core/BlockPos;)Lnet/minecraft/world/level/block/entity/BlockEntity;
       7: checkcast     #122                // class cool/furry/mc/neoforge/projectexpansion/block/entity/BlockEntityAdvancedAlchemicalChest
      10: astore        6
      12: aload         6
      14: ifnonnull     18
      17: return
      18: aload         6
      20: aload         4
      22: aload         5
      24: invokevirtual #205                // Method cool/furry/mc/neoforge/projectexpansion/block/entity/BlockEntityAdvancedAlchemicalChest.handlePlace:(Lnet/minecraft/world/entity/LivingEntity;Lnet/minecraft/world/item/ItemStack;)V
      27: return

  public <T extends net.minecraft.world.level.block.entity.BlockEntity> net.minecraft.world.level.block.entity.BlockEntityTicker<T> getTicker(net.minecraft.world.level.Level, net.minecraft.world.level.block.state.BlockState, net.minecraft.world.level.block.entity.BlockEntityType<T>);
    descriptor: (Lnet/minecraft/world/level/Level;Lnet/minecraft/world/level/block/state/BlockState;Lnet/minecraft/world/level/block/entity/BlockEntityType;)Lnet/minecraft/world/level/block/entity/BlockEntityTicker;
    Code:
       0: aload_3
       1: getstatic     #209                // Field cool/furry/mc/neoforge/projectexpansion/registries/BlockEntityTypes.ADVANCED_ALCHEMICAL_CHEST:Lnet/neoforged/neoforge/registries/DeferredHolder;
       4: invokevirtual #215                // Method net/neoforged/neoforge/registries/DeferredHolder.get:()Ljava/lang/Object;
       7: if_acmpne     23
      10: aload_1
      11: getfield      #127                // Field net/minecraft/world/level/Level.isClientSide:Z
      14: ifeq          23
      17: invokedynamic #221,  0            // InvokeDynamic #2:tick:()Lnet/minecraft/world/level/block/entity/BlockEntityTicker;
      22: areturn
      23: aconst_null
      24: areturn

  public void tick(net.minecraft.world.level.block.state.BlockState, net.minecraft.server.level.ServerLevel, net.minecraft.core.BlockPos, net.minecraft.util.RandomSource);
    descriptor: (Lnet/minecraft/world/level/block/state/BlockState;Lnet/minecraft/server/level/ServerLevel;Lnet/minecraft/core/BlockPos;Lnet/minecraft/util/RandomSource;)V
    Code:
       0: aload_2
       1: aload_3
       2: invokevirtual #225                // Method net/minecraft/server/level/ServerLevel.getBlockEntity:(Lnet/minecraft/core/BlockPos;)Lnet/minecraft/world/level/block/entity/BlockEntity;
       5: astore        5
       7: aload         5
       9: instanceof    #122                // class cool/furry/mc/neoforge/projectexpansion/block/entity/BlockEntityAdvancedAlchemicalChest
      12: ifeq          27
      15: aload         5
      17: checkcast     #122                // class cool/furry/mc/neoforge/projectexpansion/block/entity/BlockEntityAdvancedAlchemicalChest
      20: astore        6
      22: aload         6
      24: invokevirtual #230                // Method cool/furry/mc/neoforge/projectexpansion/block/entity/BlockEntityAdvancedAlchemicalChest.recheckOpen:()V
      27: return

  protected void createBlockStateDefinition(net.minecraft.world.level.block.state.StateDefinition$Builder<net.minecraft.world.level.block.Block, net.minecraft.world.level.block.state.BlockState>);
    descriptor: (Lnet/minecraft/world/level/block/state/StateDefinition$Builder;)V
    Code:
       0: aload_0
       1: aload_1
       2: invokespecial #234                // Method net/minecraft/world/level/block/HorizontalDirectionalBlock.createBlockStateDefinition:(Lnet/minecraft/world/level/block/state/StateDefinition$Builder;)V
       5: aload_1
       6: iconst_2
       7: anewarray     #238                // class net/minecraft/world/level/block/state/properties/Property
      10: dup
      11: iconst_0
      12: getstatic     #21                 // Field FACING:Lnet/minecraft/world/level/block/state/properties/DirectionProperty;
      15: aastore
      16: dup
      17: iconst_1
      18: getstatic     #35                 // Field WATERLOGGED:Lnet/minecraft/world/level/block/state/properties/BooleanProperty;
      21: aastore
      22: invokevirtual #240                // Method net/minecraft/world/level/block/state/StateDefinition$Builder.add:([Lnet/minecraft/world/level/block/state/properties/Property;)Lnet/minecraft/world/level/block/state/StateDefinition$Builder;
      25: pop
      26: return

  protected boolean isPathfindable(net.minecraft.world.level.block.state.BlockState, net.minecraft.world.level.pathfinder.PathComputationType);
    descriptor: (Lnet/minecraft/world/level/block/state/BlockState;Lnet/minecraft/world/level/pathfinder/PathComputationType;)Z
    Code:
       0: iconst_0
       1: ireturn

  public boolean hasAnalogOutputSignal(net.minecraft.world.level.block.state.BlockState);
    descriptor: (Lnet/minecraft/world/level/block/state/BlockState;)Z
    Code:
       0: iconst_1
       1: ireturn

  public int getAnalogOutputSignal(net.minecraft.world.level.block.state.BlockState, net.minecraft.world.level.Level, net.minecraft.core.BlockPos);
    descriptor: (Lnet/minecraft/world/level/block/state/BlockState;Lnet/minecraft/world/level/Level;Lnet/minecraft/core/BlockPos;)I
    Code:
       0: ldc           #122                // class cool/furry/mc/neoforge/projectexpansion/block/entity/BlockEntityAdvancedAlchemicalChest
       2: aload_2
       3: aload_3
       4: invokestatic  #139                // Method moze_intel/projecte/utils/WorldHelper.getBlockEntity:(Ljava/lang/Class;Lnet/minecraft/world/level/BlockGetter;Lnet/minecraft/core/BlockPos;)Lnet/minecraft/world/level/block/entity/BlockEntity;
       7: checkcast     #122                // class cool/furry/mc/neoforge/projectexpansion/block/entity/BlockEntityAdvancedAlchemicalChest
      10: astore        4
      12: aload         4
      14: ifnonnull     25
      17: aload_0
      18: aload_1
      19: aload_2
      20: aload_3
      21: invokespecial #245                // Method net/minecraft/world/level/block/HorizontalDirectionalBlock.getAnalogOutputSignal:(Lnet/minecraft/world/level/block/state/BlockState;Lnet/minecraft/world/level/Level;Lnet/minecraft/core/BlockPos;)I
      24: ireturn
      25: aload_2
      26: getstatic     #249                // Field net/neoforged/neoforge/capabilities/Capabilities$ItemHandler.BLOCK:Lnet/neoforged/neoforge/capabilities/BlockCapability;
      29: aload_3
      30: aload_1
      31: aload         4
      33: getstatic     #255                // Field net/minecraft/core/Direction.UP:Lnet/minecraft/core/Direction;
      36: invokestatic  #258                // Method moze_intel/projecte/utils/WorldHelper.getCapability:(Lnet/minecraft/world/level/Level;Lnet/neoforged/neoforge/capabilities/BlockCapability;Lnet/minecraft/core/BlockPos;Lnet/minecraft/world/level/block/state/BlockState;Lnet/minecraft/world/level/block/entity/BlockEntity;Ljava/lang/Object;)Ljava/lang/Object;
      39: checkcast     #262                // class net/neoforged/neoforge/items/IItemHandler
      42: astore        5
      44: aload         5
      46: ifnonnull     57
      49: aload_0
      50: aload_1
      51: aload_2
      52: aload_3
      53: invokespecial #245                // Method net/minecraft/world/level/block/HorizontalDirectionalBlock.getAnalogOutputSignal:(Lnet/minecraft/world/level/block/state/BlockState;Lnet/minecraft/world/level/Level;Lnet/minecraft/core/BlockPos;)I
      56: ireturn
      57: aload         5
      59: invokestatic  #264                // Method net/neoforged/neoforge/items/ItemHandlerHelper.calcRedstoneFromInventory:(Lnet/neoforged/neoforge/items/IItemHandler;)I
      62: ireturn

  public net.minecraft.world.level.block.state.BlockState getStateForPlacement(net.minecraft.world.item.context.BlockPlaceContext);
    descriptor: (Lnet/minecraft/world/item/context/BlockPlaceContext;)Lnet/minecraft/world/level/block/state/BlockState;
    Code:
       0: aload_0
       1: aload_1
       2: invokespecial #270                // Method net/minecraft/world/level/block/HorizontalDirectionalBlock.getStateForPlacement:(Lnet/minecraft/world/item/context/BlockPlaceContext;)Lnet/minecraft/world/level/block/state/BlockState;
       5: invokestatic  #274                // Method java/util/Objects.requireNonNull:(Ljava/lang/Object;)Ljava/lang/Object;
       8: checkcast     #19                 // class net/minecraft/world/level/block/state/BlockState
      11: getstatic     #21                 // Field FACING:Lnet/minecraft/world/level/block/state/properties/DirectionProperty;
      14: aload_1
      15: invokevirtual #280                // Method net/minecraft/world/item/context/BlockPlaceContext.getHorizontalDirection:()Lnet/minecraft/core/Direction;
      18: invokevirtual #286                // Method net/minecraft/core/Direction.getOpposite:()Lnet/minecraft/core/Direction;
      21: invokevirtual #31                 // Method net/minecraft/world/level/block/state/BlockState.setValue:(Lnet/minecraft/world/level/block/state/properties/Property;Ljava/lang/Comparable;)Ljava/lang/Object;
      24: checkcast     #19                 // class net/minecraft/world/level/block/state/BlockState
      27: getstatic     #289                // Field net/minecraft/world/level/block/state/properties/BlockStateProperties.WATERLOGGED:Lnet/minecraft/world/level/block/state/properties/BooleanProperty;
      30: aload_1
      31: invokevirtual #292                // Method net/minecraft/world/item/context/BlockPlaceContext.getLevel:()Lnet/minecraft/world/level/Level;
      34: aload_1
      35: invokevirtual #296                // Method net/minecraft/world/item/context/BlockPlaceContext.getClickedPos:()Lnet/minecraft/core/BlockPos;
      38: invokevirtual #300                // Method net/minecraft/world/level/Level.getFluidState:(Lnet/minecraft/core/BlockPos;)Lnet/minecraft/world/level/material/FluidState;
      41: invokevirtual #304                // Method net/minecraft/world/level/material/FluidState.getType:()Lnet/minecraft/world/level/material/Fluid;
      44: getstatic     #310                // Field net/minecraft/world/level/material/Fluids.WATER:Lnet/minecraft/world/level/material/FlowingFluid;
      47: if_acmpne     54
      50: iconst_1
      51: goto          55
      54: iconst_0
      55: invokestatic  #39                 // Method java/lang/Boolean.valueOf:(Z)Ljava/lang/Boolean;
      58: invokevirtual #31                 // Method net/minecraft/world/level/block/state/BlockState.setValue:(Lnet/minecraft/world/level/block/state/properties/Property;Ljava/lang/Comparable;)Ljava/lang/Object;
      61: checkcast     #19                 // class net/minecraft/world/level/block/state/BlockState
      64: areturn

  public net.minecraft.world.level.material.FluidState getFluidState(net.minecraft.world.level.block.state.BlockState);
    descriptor: (Lnet/minecraft/world/level/block/state/BlockState;)Lnet/minecraft/world/level/material/FluidState;
    Code:
       0: aload_1
       1: getstatic     #289                // Field net/minecraft/world/level/block/state/properties/BlockStateProperties.WATERLOGGED:Lnet/minecraft/world/level/block/state/properties/BooleanProperty;
       4: invokevirtual #316                // Method net/minecraft/world/level/block/state/BlockState.getValue:(Lnet/minecraft/world/level/block/state/properties/Property;)Ljava/lang/Comparable;
       7: checkcast     #40                 // class java/lang/Boolean
      10: invokevirtual #320                // Method java/lang/Boolean.booleanValue:()Z
      13: ifeq          26
      16: getstatic     #310                // Field net/minecraft/world/level/material/Fluids.WATER:Lnet/minecraft/world/level/material/FlowingFluid;
      19: iconst_0
      20: invokevirtual #323                // Method net/minecraft/world/level/material/FlowingFluid.getSource:(Z)Lnet/minecraft/world/level/material/FluidState;
      23: goto          31
      26: aload_0
      27: aload_1
      28: invokespecial #329                // Method net/minecraft/world/level/block/HorizontalDirectionalBlock.getFluidState:(Lnet/minecraft/world/level/block/state/BlockState;)Lnet/minecraft/world/level/material/FluidState;
      31: areturn

  public net.minecraft.world.level.block.state.BlockState updateShape(net.minecraft.world.level.block.state.BlockState, net.minecraft.core.Direction, net.minecraft.world.level.block.state.BlockState, net.minecraft.world.level.LevelAccessor, net.minecraft.core.BlockPos, net.minecraft.core.BlockPos);
    descriptor: (Lnet/minecraft/world/level/block/state/BlockState;Lnet/minecraft/core/Direction;Lnet/minecraft/world/level/block/state/BlockState;Lnet/minecraft/world/level/LevelAccessor;Lnet/minecraft/core/BlockPos;Lnet/minecraft/core/BlockPos;)Lnet/minecraft/world/level/block/state/BlockState;
    Code:
       0: aload_1
       1: getstatic     #289                // Field net/minecraft/world/level/block/state/properties/BlockStateProperties.WATERLOGGED:Lnet/minecraft/world/level/block/state/properties/BooleanProperty;
       4: invokevirtual #316                // Method net/minecraft/world/level/block/state/BlockState.getValue:(Lnet/minecraft/world/level/block/state/properties/Property;)Ljava/lang/Comparable;
       7: checkcast     #40                 // class java/lang/Boolean
      10: invokevirtual #320                // Method java/lang/Boolean.booleanValue:()Z
      13: ifeq          36
      16: aload         4
      18: aload         5
      20: getstatic     #310                // Field net/minecraft/world/level/material/Fluids.WATER:Lnet/minecraft/world/level/material/FlowingFluid;
      23: getstatic     #310                // Field net/minecraft/world/level/material/Fluids.WATER:Lnet/minecraft/world/level/material/FlowingFluid;
      26: aload         4
      28: invokevirtual #332                // Method net/minecraft/world/level/material/FlowingFluid.getTickDelay:(Lnet/minecraft/world/level/LevelReader;)I
      31: invokeinterface #336,  4          // InterfaceMethod net/minecraft/world/level/LevelAccessor.scheduleTick:(Lnet/minecraft/core/BlockPos;Lnet/minecraft/world/level/material/Fluid;I)V
      36: aload_0
      37: aload_1
      38: aload_2
      39: aload_3
      40: aload         4
      42: aload         5
      44: aload         6
      46: invokespecial #342                // Method net/minecraft/world/level/block/HorizontalDirectionalBlock.updateShape:(Lnet/minecraft/world/level/block/state/BlockState;Lnet/minecraft/core/Direction;Lnet/minecraft/world/level/block/state/BlockState;Lnet/minecraft/world/level/LevelAccessor;Lnet/minecraft/core/BlockPos;Lnet/minecraft/core/BlockPos;)Lnet/minecraft/world/level/block/state/BlockState;
      49: areturn

  public boolean triggerEvent(net.minecraft.world.level.block.state.BlockState, net.minecraft.world.level.Level, net.minecraft.core.BlockPos, int, int);
    descriptor: (Lnet/minecraft/world/level/block/state/BlockState;Lnet/minecraft/world/level/Level;Lnet/minecraft/core/BlockPos;II)Z
    Code:
       0: aload_0
       1: aload_1
       2: aload_2
       3: aload_3
       4: iload         4
       6: iload         5
       8: invokespecial #346                // Method net/minecraft/world/level/block/HorizontalDirectionalBlock.triggerEvent:(Lnet/minecraft/world/level/block/state/BlockState;Lnet/minecraft/world/level/Level;Lnet/minecraft/core/BlockPos;II)Z
      11: pop
      12: ldc           #122                // class cool/furry/mc/neoforge/projectexpansion/block/entity/BlockEntityAdvancedAlchemicalChest
      14: aload_2
      15: aload_3
      16: invokestatic  #139                // Method moze_intel/projecte/utils/WorldHelper.getBlockEntity:(Ljava/lang/Class;Lnet/minecraft/world/level/BlockGetter;Lnet/minecraft/core/BlockPos;)Lnet/minecraft/world/level/block/entity/BlockEntity;
      19: astore        6
      21: aload         6
      23: ifnull        42
      26: aload         6
      28: iload         4
      30: iload         5
      32: invokevirtual #350                // Method net/minecraft/world/level/block/entity/BlockEntity.triggerEvent:(II)Z
      35: ifeq          42
      38: iconst_1
      39: goto          43
      42: iconst_0
      43: ireturn

  public net.minecraft.world.level.material.MapColor getMapColor(net.minecraft.world.level.block.state.BlockState, net.minecraft.world.level.BlockGetter, net.minecraft.core.BlockPos, net.minecraft.world.level.material.MapColor);
    descriptor: (Lnet/minecraft/world/level/block/state/BlockState;Lnet/minecraft/world/level/BlockGetter;Lnet/minecraft/core/BlockPos;Lnet/minecraft/world/level/material/MapColor;)Lnet/minecraft/world/level/material/MapColor;
    Code:
       0: aload_0
       1: getfield      #49                 // Field color:Lnet/minecraft/world/item/DyeColor;
       4: invokevirtual #355                // Method net/minecraft/world/item/DyeColor.getId:()I
       7: invokestatic  #361                // Method net/minecraft/world/level/material/MapColor.byId:(I)Lnet/minecraft/world/level/material/MapColor;
      10: areturn

  protected com.mojang.serialization.MapCodec<? extends net.minecraft.world.level.block.HorizontalDirectionalBlock> codec();
    descriptor: ()Lcom/mojang/serialization/MapCodec;
    Code:
       0: getstatic     #367                // Field cool/furry/mc/neoforge/projectexpansion/registries/BlockTypes.ADVANCED_ALCHEMICAL_CHEST:Lnet/neoforged/neoforge/registries/DeferredHolder;
       3: invokevirtual #215                // Method net/neoforged/neoforge/registries/DeferredHolder.get:()Ljava/lang/Object;
       6: checkcast     #370                // class com/mojang/serialization/MapCodec
       9: areturn

  private static void lambda$useWithoutItem$1(net.minecraft.world.InteractionHand, net.minecraft.world.entity.player.Player, net.minecraft.core.BlockPos, net.minecraft.network.RegistryFriendlyByteBuf);
    descriptor: (Lnet/minecraft/world/InteractionHand;Lnet/minecraft/world/entity/player/Player;Lnet/minecraft/core/BlockPos;Lnet/minecraft/network/RegistryFriendlyByteBuf;)V
    Code:
       0: aload_3
       1: aload_0
       2: invokevirtual #372                // Method net/minecraft/network/RegistryFriendlyByteBuf.writeEnum:(Ljava/lang/Enum;)Lnet/minecraft/network/FriendlyByteBuf;
       5: pop
       6: aload_3
       7: aload_1
       8: invokevirtual #378                // Method net/minecraft/world/entity/player/Player.getInventory:()Lnet/minecraft/world/entity/player/Inventory;
      11: getfield      #382                // Field net/minecraft/world/entity/player/Inventory.selected:I
      14: invokevirtual #388                // Method net/minecraft/network/RegistryFriendlyByteBuf.writeByte:(I)Lnet/minecraft/network/FriendlyByteBuf;
      17: pop
      18: aload_3
      19: iconst_0
      20: invokevirtual #392                // Method net/minecraft/network/RegistryFriendlyByteBuf.writeBoolean:(Z)Lnet/minecraft/network/FriendlyByteBuf;
      23: pop
      24: aload_3
      25: aload_2
      26: invokevirtual #396                // Method net/minecraft/network/RegistryFriendlyByteBuf.writeBlockPos:(Lnet/minecraft/core/BlockPos;)Lnet/minecraft/network/FriendlyByteBuf;
      29: pop
      30: return

  private static int lambda$getProperties$0(net.minecraft.world.level.block.state.BlockState);
    descriptor: (Lnet/minecraft/world/level/block/state/BlockState;)I
    Code:
       0: bipush        10
       2: ireturn

  static {};
    descriptor: ()V
    Code:
       0: getstatic     #289                // Field net/minecraft/world/level/block/state/properties/BlockStateProperties.WATERLOGGED:Lnet/minecraft/world/level/block/state/properties/BooleanProperty;
       3: putstatic     #35                 // Field WATERLOGGED:Lnet/minecraft/world/level/block/state/properties/BooleanProperty;
       6: dconst_1
       7: dconst_0
       8: dconst_1
       9: ldc2_w        #400                // double 15.0d
      12: ldc2_w        #402                // double 14.0d
      15: ldc2_w        #400                // double 15.0d
      18: invokestatic  #404                // Method net/minecraft/world/level/block/Block.box:(DDDDDD)Lnet/minecraft/world/phys/shapes/VoxelShape;
      21: putstatic     #118                // Field SHAPE:Lnet/minecraft/world/phys/shapes/VoxelShape;
      24: return
}
