Compiled from "MagnetItem.java"
public abstract class com.supermartijn642.simplemagnets.MagnetItem extends com.supermartijn642.core.item.BaseItem implements net.minecraftforge.common.capabilities.ICapabilityProvider {
  public com.supermartijn642.simplemagnets.MagnetItem();
    descriptor: ()V
    Code:
       0: aload_0
       1: invokestatic  #34                 // Method com/supermartijn642/core/item/ItemProperties.create:()Lcom/supermartijn642/core/item/ItemProperties;
       4: getstatic     #40                 // Field com/supermartijn642/simplemagnets/SimpleMagnets.GROUP:Lcom/supermartijn642/core/item/CreativeItemGroup;
       7: invokevirtual #44                 // Method com/supermartijn642/core/item/ItemProperties.group:(Lnet/minecraft/creativetab/CreativeTabs;)Lcom/supermartijn642/core/item/ItemProperties;
      10: iconst_1
      11: invokevirtual #48                 // Method com/supermartijn642/core/item/ItemProperties.maxStackSize:(I)Lcom/supermartijn642/core/item/ItemProperties;
      14: invokespecial #51                 // Method com/supermartijn642/core/item/BaseItem."<init>":(Lcom/supermartijn642/core/item/ItemProperties;)V
      17: return

  public com.supermartijn642.core.item.BaseItem$ItemUseResult interact(net.minecraft.item.ItemStack, net.minecraft.entity.player.EntityPlayer, net.minecraft.util.EnumHand, net.minecraft.world.World);
    descriptor: (Lnet/minecraft/item/ItemStack;Lnet/minecraft/entity/player/EntityPlayer;Lnet/minecraft/util/EnumHand;Lnet/minecraft/world/World;)Lcom/supermartijn642/core/item/BaseItem$ItemUseResult;
    Code:
       0: aload_2
       1: aload_1
       2: invokestatic  #63                 // Method toggleMagnet:(Lnet/minecraft/entity/player/EntityPlayer;Lnet/minecraft/item/ItemStack;)V
       5: aload_1
       6: invokestatic  #67                 // Method com/supermartijn642/core/item/BaseItem$ItemUseResult.success:(Lnet/minecraft/item/ItemStack;)Lcom/supermartijn642/core/item/BaseItem$ItemUseResult;
       9: areturn

  public static void toggleMagnet(net.minecraft.entity.player.EntityPlayer, net.minecraft.item.ItemStack);
    descriptor: (Lnet/minecraft/entity/player/EntityPlayer;Lnet/minecraft/item/ItemStack;)V
    Code:
       0: aload_0
       1: getfield      #76                 // Field net/minecraft/entity/player/EntityPlayer.field_70170_p:Lnet/minecraft/world/World;
       4: getfield      #82                 // Field net/minecraft/world/World.field_72995_K:Z
       7: ifne          101
      10: aload_1
      11: invokevirtual #88                 // Method net/minecraft/item/ItemStack.func_77973_b:()Lnet/minecraft/item/Item;
      14: instanceof    #2                  // class com/supermartijn642/simplemagnets/MagnetItem
      17: ifeq          101
      20: aload_1
      21: invokevirtual #92                 // Method net/minecraft/item/ItemStack.func_77942_o:()Z
      24: ifeq          34
      27: aload_1
      28: invokevirtual #96                 // Method net/minecraft/item/ItemStack.func_77978_p:()Lnet/minecraft/nbt/NBTTagCompound;
      31: goto          41
      34: new           #98                 // class net/minecraft/nbt/NBTTagCompound
      37: dup
      38: invokespecial #100                // Method net/minecraft/nbt/NBTTagCompound."<init>":()V
      41: astore_2
      42: aload_2
      43: ldc           #102                // String active
      45: invokevirtual #106                // Method net/minecraft/nbt/NBTTagCompound.func_74764_b:(Ljava/lang/String;)Z
      48: ifeq          64
      51: aload_2
      52: ldc           #102                // String active
      54: invokevirtual #109                // Method net/minecraft/nbt/NBTTagCompound.func_74767_n:(Ljava/lang/String;)Z
      57: ifeq          64
      60: iconst_1
      61: goto          65
      64: iconst_0
      65: istore_3
      66: aload_2
      67: ldc           #102                // String active
      69: iload_3
      70: ifne          77
      73: iconst_1
      74: goto          78
      77: iconst_0
      78: invokevirtual #115                // Method net/minecraft/nbt/NBTTagCompound.func_74757_a:(Ljava/lang/String;Z)V
      81: aload_1
      82: aload_2
      83: invokevirtual #119                // Method net/minecraft/item/ItemStack.func_77982_d:(Lnet/minecraft/nbt/NBTTagCompound;)V
      86: getstatic     #123                // Field com/supermartijn642/simplemagnets/SimpleMagnets.CHANNEL:Lcom/supermartijn642/core/network/PacketChannel;
      89: aload_0
      90: new           #125                // class com/supermartijn642/simplemagnets/packets/magnet/PacketToggleMagnetMessage
      93: dup
      94: iload_3
      95: invokespecial #128                // Method com/supermartijn642/simplemagnets/packets/magnet/PacketToggleMagnetMessage."<init>":(Z)V
      98: invokevirtual #134                // Method com/supermartijn642/core/network/PacketChannel.sendToPlayer:(Lnet/minecraft/entity/player/EntityPlayer;Lcom/supermartijn642/core/network/BasePacket;)V
     101: return

  public void func_77663_a(net.minecraft.item.ItemStack, net.minecraft.world.World, net.minecraft.entity.Entity, int, boolean);
    descriptor: (Lnet/minecraft/item/ItemStack;Lnet/minecraft/world/World;Lnet/minecraft/entity/Entity;IZ)V
    Code:
       0: aload_3
       1: instanceof    #73                 // class net/minecraft/entity/player/EntityPlayer
       4: ifeq          18
       7: aload_3
       8: checkcast     #73                 // class net/minecraft/entity/player/EntityPlayer
      11: invokevirtual #144                // Method net/minecraft/entity/player/EntityPlayer.func_175149_v:()Z
      14: ifeq          18
      17: return
      18: aload_1
      19: invokevirtual #92                 // Method net/minecraft/item/ItemStack.func_77942_o:()Z
      22: ifeq          32
      25: aload_1
      26: invokevirtual #96                 // Method net/minecraft/item/ItemStack.func_77978_p:()Lnet/minecraft/nbt/NBTTagCompound;
      29: goto          39
      32: new           #98                 // class net/minecraft/nbt/NBTTagCompound
      35: dup
      36: invokespecial #100                // Method net/minecraft/nbt/NBTTagCompound."<init>":()V
      39: astore        6
      41: aload         6
      43: ldc           #102                // String active
      45: invokevirtual #106                // Method net/minecraft/nbt/NBTTagCompound.func_74764_b:(Ljava/lang/String;)Z
      48: ifeq          295
      51: aload         6
      53: ldc           #102                // String active
      55: invokevirtual #109                // Method net/minecraft/nbt/NBTTagCompound.func_74767_n:(Ljava/lang/String;)Z
      58: ifeq          295
      61: aload_0
      62: aload         6
      64: invokevirtual #148                // Method canPickupItems:(Lnet/minecraft/nbt/NBTTagCompound;)Z
      67: ifeq          190
      70: aload_0
      71: aload         6
      73: invokevirtual #152                // Method getRangeItems:(Lnet/minecraft/nbt/NBTTagCompound;)I
      76: istore        7
      78: new           #154                // class net/minecraft/util/math/AxisAlignedBB
      81: dup
      82: aload_3
      83: invokevirtual #160                // Method net/minecraft/entity/Entity.func_174791_d:()Lnet/minecraft/util/math/Vec3d;
      86: iload         7
      88: ineg
      89: i2d
      90: iload         7
      92: ineg
      93: i2d
      94: iload         7
      96: ineg
      97: i2d
      98: invokevirtual #166                // Method net/minecraft/util/math/Vec3d.func_72441_c:(DDD)Lnet/minecraft/util/math/Vec3d;
     101: aload_3
     102: invokevirtual #160                // Method net/minecraft/entity/Entity.func_174791_d:()Lnet/minecraft/util/math/Vec3d;
     105: iload         7
     107: i2d
     108: iload         7
     110: i2d
     111: iload         7
     113: i2d
     114: invokevirtual #166                // Method net/minecraft/util/math/Vec3d.func_72441_c:(DDD)Lnet/minecraft/util/math/Vec3d;
     117: invokespecial #169                // Method net/minecraft/util/math/AxisAlignedBB."<init>":(Lnet/minecraft/util/math/Vec3d;Lnet/minecraft/util/math/Vec3d;)V
     120: astore        8
     122: aload_2
     123: ldc           #171                // class net/minecraft/entity/item/EntityItem
     125: aload         8
     127: aload_0
     128: aload_2
     129: aload_3
     130: aload         6
     132: invokedynamic #191,  0            // InvokeDynamic #0:apply:(Lcom/supermartijn642/simplemagnets/MagnetItem;Lnet/minecraft/world/World;Lnet/minecraft/entity/Entity;Lnet/minecraft/nbt/NBTTagCompound;)Lcom/google/common/base/Predicate;
     137: invokevirtual #195                // Method net/minecraft/world/World.func_175647_a:(Ljava/lang/Class;Lnet/minecraft/util/math/AxisAlignedBB;Lcom/google/common/base/Predicate;)Ljava/util/List;
     140: astore        9
     142: aload         9
     144: aload_3
     145: invokedynamic #208,  0            // InvokeDynamic #1:accept:(Lnet/minecraft/entity/Entity;)Ljava/util/function/Consumer;
     150: invokeinterface #214,  2          // InterfaceMethod java/util/List.forEach:(Ljava/util/function/Consumer;)V
     155: aload_2
     156: getfield      #82                 // Field net/minecraft/world/World.field_72995_K:Z
     159: ifne          190
     162: aload_3
     163: instanceof    #73                 // class net/minecraft/entity/player/EntityPlayer
     166: ifeq          190
     169: ldc           #216                // String itemphysic
     171: invokestatic  #221                // Method com/supermartijn642/core/CommonUtils.isModLoaded:(Ljava/lang/String;)Z
     174: ifeq          190
     177: aload         9
     179: aload_3
     180: invokedynamic #226,  0            // InvokeDynamic #2:accept:(Lnet/minecraft/entity/Entity;)Ljava/util/function/Consumer;
     185: invokeinterface #214,  2          // InterfaceMethod java/util/List.forEach:(Ljava/util/function/Consumer;)V
     190: aload_2
     191: getfield      #82                 // Field net/minecraft/world/World.field_72995_K:Z
     194: ifne          295
     197: aload_0
     198: aload         6
     200: invokevirtual #229                // Method canPickupXp:(Lnet/minecraft/nbt/NBTTagCompound;)Z
     203: ifeq          295
     206: aload_3
     207: instanceof    #73                 // class net/minecraft/entity/player/EntityPlayer
     210: ifeq          295
     213: aload_0
     214: aload         6
     216: invokevirtual #232                // Method getRangeXp:(Lnet/minecraft/nbt/NBTTagCompound;)I
     219: istore        7
     221: new           #154                // class net/minecraft/util/math/AxisAlignedBB
     224: dup
     225: aload_3
     226: invokevirtual #160                // Method net/minecraft/entity/Entity.func_174791_d:()Lnet/minecraft/util/math/Vec3d;
     229: iload         7
     231: ineg
     232: i2d
     233: iload         7
     235: ineg
     236: i2d
     237: iload         7
     239: ineg
     240: i2d
     241: invokevirtual #166                // Method net/minecraft/util/math/Vec3d.func_72441_c:(DDD)Lnet/minecraft/util/math/Vec3d;
     244: aload_3
     245: invokevirtual #160                // Method net/minecraft/entity/Entity.func_174791_d:()Lnet/minecraft/util/math/Vec3d;
     248: iload         7
     250: i2d
     251: iload         7
     253: i2d
     254: iload         7
     256: i2d
     257: invokevirtual #166                // Method net/minecraft/util/math/Vec3d.func_72441_c:(DDD)Lnet/minecraft/util/math/Vec3d;
     260: invokespecial #169                // Method net/minecraft/util/math/AxisAlignedBB."<init>":(Lnet/minecraft/util/math/Vec3d;Lnet/minecraft/util/math/Vec3d;)V
     263: astore        8
     265: aload_3
     266: checkcast     #73                 // class net/minecraft/entity/player/EntityPlayer
     269: astore        9
     271: aload_2
     272: ldc           #234                // class net/minecraft/entity/item/EntityXPOrb
     274: aload         8
     276: invokevirtual #238                // Method net/minecraft/world/World.func_72872_a:(Ljava/lang/Class;Lnet/minecraft/util/math/AxisAlignedBB;)Ljava/util/List;
     279: astore        10
     281: aload         10
     283: aload         9
     285: invokedynamic #248,  0            // InvokeDynamic #3:accept:(Lnet/minecraft/entity/player/EntityPlayer;)Ljava/util/function/Consumer;
     290: invokeinterface #214,  2          // InterfaceMethod java/util/List.forEach:(Ljava/util/function/Consumer;)V
     295: aload_1
     296: aload         6
     298: invokevirtual #119                // Method net/minecraft/item/ItemStack.func_77982_d:(Lnet/minecraft/nbt/NBTTagCompound;)V
     301: return

  private static void playerTouch(net.minecraft.entity.item.EntityItem, net.minecraft.entity.player.EntityPlayer);
    descriptor: (Lnet/minecraft/entity/item/EntityItem;Lnet/minecraft/entity/player/EntityPlayer;)V
    Code:
       0: aload_0
       1: getfield      #262                // Field net/minecraft/entity/item/EntityItem.field_70170_p:Lnet/minecraft/world/World;
       4: getfield      #82                 // Field net/minecraft/world/World.field_72995_K:Z
       7: ifne          192
      10: aload_0
      11: invokevirtual #265                // Method net/minecraft/entity/item/EntityItem.func_174874_s:()Z
      14: ifeq          18
      17: return
      18: aload_0
      19: invokevirtual #269                // Method net/minecraft/entity/item/EntityItem.func_92059_d:()Lnet/minecraft/item/ItemStack;
      22: astore_2
      23: aload_2
      24: invokevirtual #88                 // Method net/minecraft/item/ItemStack.func_77973_b:()Lnet/minecraft/item/Item;
      27: astore_3
      28: aload_2
      29: invokevirtual #273                // Method net/minecraft/item/ItemStack.func_190916_E:()I
      32: istore        4
      34: aload_0
      35: aload_1
      36: invokestatic  #279                // Method net/minecraftforge/event/ForgeEventFactory.onItemPickup:(Lnet/minecraft/entity/item/EntityItem;Lnet/minecraft/entity/player/EntityPlayer;)I
      39: istore        5
      41: iload         5
      43: ifge          47
      46: return
      47: aload_2
      48: invokevirtual #284                // Method net/minecraft/item/ItemStack.func_77946_l:()Lnet/minecraft/item/ItemStack;
      51: astore        6
      53: aload_0
      54: invokevirtual #265                // Method net/minecraft/entity/item/EntityItem.func_174874_s:()Z
      57: ifne          192
      60: aload_0
      61: invokevirtual #288                // Method net/minecraft/entity/item/EntityItem.func_145798_i:()Ljava/lang/String;
      64: ifnull        96
      67: aload_0
      68: getfield      #291                // Field net/minecraft/entity/item/EntityItem.lifespan:I
      71: aload_0
      72: invokevirtual #294                // Method net/minecraft/entity/item/EntityItem.func_174872_o:()I
      75: isub
      76: sipush        200
      79: if_icmple     96
      82: aload_0
      83: invokevirtual #288                // Method net/minecraft/entity/item/EntityItem.func_145798_i:()Ljava/lang/String;
      86: aload_1
      87: invokevirtual #297                // Method net/minecraft/entity/player/EntityPlayer.func_70005_c_:()Ljava/lang/String;
      90: invokevirtual #300                // Method java/lang/String.equals:(Ljava/lang/Object;)Z
      93: ifeq          192
      96: iload         5
      98: iconst_1
      99: if_icmpeq     133
     102: iload         4
     104: ifle          133
     107: aload_1
     108: getfield      #304                // Field net/minecraft/entity/player/EntityPlayer.field_71071_by:Lnet/minecraft/entity/player/InventoryPlayer;
     111: aload_2
     112: invokevirtual #310                // Method net/minecraft/entity/player/InventoryPlayer.func_70441_a:(Lnet/minecraft/item/ItemStack;)Z
     115: ifne          133
     118: aload         6
     120: invokevirtual #273                // Method net/minecraft/item/ItemStack.func_190916_E:()I
     123: aload_0
     124: invokevirtual #269                // Method net/minecraft/entity/item/EntityItem.func_92059_d:()Lnet/minecraft/item/ItemStack;
     127: invokevirtual #273                // Method net/minecraft/item/ItemStack.func_190916_E:()I
     130: if_icmple     192
     133: aload         6
     135: aload         6
     137: invokevirtual #273                // Method net/minecraft/item/ItemStack.func_190916_E:()I
     140: aload_2
     141: invokevirtual #273                // Method net/minecraft/item/ItemStack.func_190916_E:()I
     144: isub
     145: invokevirtual #314                // Method net/minecraft/item/ItemStack.func_190920_e:(I)V
     148: invokestatic  #320                // Method net/minecraftforge/fml/common/FMLCommonHandler.instance:()Lnet/minecraftforge/fml/common/FMLCommonHandler;
     151: aload_1
     152: aload_0
     153: aload         6
     155: invokevirtual #324                // Method net/minecraftforge/fml/common/FMLCommonHandler.firePlayerItemPickupEvent:(Lnet/minecraft/entity/player/EntityPlayer;Lnet/minecraft/entity/item/EntityItem;Lnet/minecraft/item/ItemStack;)V
     158: aload_2
     159: invokevirtual #327                // Method net/minecraft/item/ItemStack.func_190926_b:()Z
     162: ifeq          182
     165: aload_1
     166: aload_0
     167: iload         4
     169: invokevirtual #331                // Method net/minecraft/entity/player/EntityPlayer.func_71001_a:(Lnet/minecraft/entity/Entity;I)V
     172: aload_0
     173: invokevirtual #334                // Method net/minecraft/entity/item/EntityItem.func_70106_y:()V
     176: aload_2
     177: iload         4
     179: invokevirtual #314                // Method net/minecraft/item/ItemStack.func_190920_e:(I)V
     182: aload_1
     183: aload_3
     184: invokestatic  #340                // Method net/minecraft/stats/StatList.func_188056_d:(Lnet/minecraft/item/Item;)Lnet/minecraft/stats/StatBase;
     187: iload         4
     189: invokevirtual #344                // Method net/minecraft/entity/player/EntityPlayer.func_71064_a:(Lnet/minecraft/stats/StatBase;I)V
     192: return

  protected abstract boolean canPickupItems(net.minecraft.nbt.NBTTagCompound);
    descriptor: (Lnet/minecraft/nbt/NBTTagCompound;)Z

  protected abstract boolean canPickupStack(net.minecraft.nbt.NBTTagCompound, net.minecraft.item.ItemStack);
    descriptor: (Lnet/minecraft/nbt/NBTTagCompound;Lnet/minecraft/item/ItemStack;)Z

  protected abstract boolean canPickupXp(net.minecraft.nbt.NBTTagCompound);
    descriptor: (Lnet/minecraft/nbt/NBTTagCompound;)Z

  protected abstract int getRangeItems(net.minecraft.nbt.NBTTagCompound);
    descriptor: (Lnet/minecraft/nbt/NBTTagCompound;)I

  protected abstract int getRangeXp(net.minecraft.nbt.NBTTagCompound);
    descriptor: (Lnet/minecraft/nbt/NBTTagCompound;)I

  public boolean func_77636_d(net.minecraft.item.ItemStack);
    descriptor: (Lnet/minecraft/item/ItemStack;)Z
    Code:
       0: aload_1
       1: invokevirtual #92                 // Method net/minecraft/item/ItemStack.func_77942_o:()Z
       4: ifeq          35
       7: aload_1
       8: invokevirtual #96                 // Method net/minecraft/item/ItemStack.func_77978_p:()Lnet/minecraft/nbt/NBTTagCompound;
      11: ldc           #102                // String active
      13: invokevirtual #106                // Method net/minecraft/nbt/NBTTagCompound.func_74764_b:(Ljava/lang/String;)Z
      16: ifeq          35
      19: aload_1
      20: invokevirtual #96                 // Method net/minecraft/item/ItemStack.func_77978_p:()Lnet/minecraft/nbt/NBTTagCompound;
      23: ldc           #102                // String active
      25: invokevirtual #109                // Method net/minecraft/nbt/NBTTagCompound.func_74767_n:(Ljava/lang/String;)Z
      28: ifeq          35
      31: iconst_1
      32: goto          36
      35: iconst_0
      36: ireturn

  public net.minecraftforge.common.capabilities.ICapabilityProvider initCapabilities(net.minecraft.item.ItemStack, net.minecraft.nbt.NBTTagCompound);
    descriptor: (Lnet/minecraft/item/ItemStack;Lnet/minecraft/nbt/NBTTagCompound;)Lnet/minecraftforge/common/capabilities/ICapabilityProvider;
    Code:
       0: aload_0
       1: areturn

  public boolean hasCapability(net.minecraftforge.common.capabilities.Capability<?>, net.minecraft.util.EnumFacing);
    descriptor: (Lnet/minecraftforge/common/capabilities/Capability;Lnet/minecraft/util/EnumFacing;)Z
    Code:
       0: getstatic     #368                // Field com/supermartijn642/simplemagnets/SimpleMagnets.baubles:Lcom/supermartijn642/simplemagnets/integration/BaublesInactive;
       3: aload_1
       4: invokevirtual #374                // Method com/supermartijn642/simplemagnets/integration/BaublesInactive.isBaubleCapability:(Lnet/minecraftforge/common/capabilities/Capability;)Z
       7: ireturn

  public <T> T getCapability(net.minecraftforge.common.capabilities.Capability<T>, net.minecraft.util.EnumFacing);
    descriptor: (Lnet/minecraftforge/common/capabilities/Capability;Lnet/minecraft/util/EnumFacing;)Ljava/lang/Object;
    Code:
       0: getstatic     #368                // Field com/supermartijn642/simplemagnets/SimpleMagnets.baubles:Lcom/supermartijn642/simplemagnets/integration/BaublesInactive;
       3: aload_1
       4: invokevirtual #374                // Method com/supermartijn642/simplemagnets/integration/BaublesInactive.isBaubleCapability:(Lnet/minecraftforge/common/capabilities/Capability;)Z
       7: ifeq          21
      10: getstatic     #368                // Field com/supermartijn642/simplemagnets/SimpleMagnets.baubles:Lcom/supermartijn642/simplemagnets/integration/BaublesInactive;
      13: aload_1
      14: aload_0
      15: invokevirtual #384                // Method com/supermartijn642/simplemagnets/integration/BaublesInactive.getBaubleCapability:(Lnet/minecraftforge/common/capabilities/Capability;Lnet/minecraft/item/Item;)Ljava/lang/Object;
      18: goto          22
      21: aconst_null
      22: areturn

  protected void appendItemInformation(net.minecraft.item.ItemStack, net.minecraft.world.IBlockAccess, java.util.function.Consumer<net.minecraft.util.text.ITextComponent>, boolean);
    descriptor: (Lnet/minecraft/item/ItemStack;Lnet/minecraft/world/IBlockAccess;Ljava/util/function/Consumer;Z)V
    Code:
       0: aload_3
       1: aload_0
       2: invokevirtual #396                // Method getTooltip:()Lnet/minecraft/util/text/ITextComponent;
       5: invokeinterface #400,  2          // InterfaceMethod java/util/function/Consumer.accept:(Ljava/lang/Object;)V
      10: return

  protected abstract net.minecraft.util.text.ITextComponent getTooltip();
    descriptor: ()Lnet/minecraft/util/text/ITextComponent;

  public static void onItemToss(net.minecraftforge.event.entity.item.ItemTossEvent);
    descriptor: (Lnet/minecraftforge/event/entity/item/ItemTossEvent;)V
    Code:
       0: aload_0
       1: invokevirtual #413                // Method net/minecraftforge/event/entity/item/ItemTossEvent.getEntityItem:()Lnet/minecraft/entity/item/EntityItem;
       4: ifnull        47
       7: aload_0
       8: invokevirtual #413                // Method net/minecraftforge/event/entity/item/ItemTossEvent.getEntityItem:()Lnet/minecraft/entity/item/EntityItem;
      11: getfield      #262                // Field net/minecraft/entity/item/EntityItem.field_70170_p:Lnet/minecraft/world/World;
      14: getfield      #82                 // Field net/minecraft/world/World.field_72995_K:Z
      17: ifne          47
      20: aload_0
      21: invokevirtual #417                // Method net/minecraftforge/event/entity/item/ItemTossEvent.getPlayer:()Lnet/minecraft/entity/player/EntityPlayer;
      24: ifnull        47
      27: aload_0
      28: invokevirtual #413                // Method net/minecraftforge/event/entity/item/ItemTossEvent.getEntityItem:()Lnet/minecraft/entity/item/EntityItem;
      31: invokevirtual #420                // Method net/minecraft/entity/item/EntityItem.getEntityData:()Lnet/minecraft/nbt/NBTTagCompound;
      34: ldc_w         #422                // String simplemagnets:throwerId
      37: aload_0
      38: invokevirtual #417                // Method net/minecraftforge/event/entity/item/ItemTossEvent.getPlayer:()Lnet/minecraft/entity/player/EntityPlayer;
      41: invokevirtual #426                // Method net/minecraft/entity/player/EntityPlayer.func_110124_au:()Ljava/util/UUID;
      44: invokevirtual #430                // Method net/minecraft/nbt/NBTTagCompound.func_186854_a:(Ljava/lang/String;Ljava/util/UUID;)V
      47: return

  public static void onStartTracking(net.minecraftforge.event.entity.player.PlayerEvent$StartTracking);
    descriptor: (Lnet/minecraftforge/event/entity/player/PlayerEvent$StartTracking;)V
    Code:
       0: aload_0
       1: invokevirtual #436                // Method net/minecraftforge/event/entity/player/PlayerEvent$StartTracking.getEntityPlayer:()Lnet/minecraft/entity/player/EntityPlayer;
       4: getfield      #76                 // Field net/minecraft/entity/player/EntityPlayer.field_70170_p:Lnet/minecraft/world/World;
       7: getfield      #82                 // Field net/minecraft/world/World.field_72995_K:Z
      10: ifne          63
      13: aload_0
      14: invokevirtual #440                // Method net/minecraftforge/event/entity/player/PlayerEvent$StartTracking.getTarget:()Lnet/minecraft/entity/Entity;
      17: instanceof    #171                // class net/minecraft/entity/item/EntityItem
      20: ifeq          63
      23: aload_0
      24: invokevirtual #440                // Method net/minecraftforge/event/entity/player/PlayerEvent$StartTracking.getTarget:()Lnet/minecraft/entity/Entity;
      27: invokevirtual #441                // Method net/minecraft/entity/Entity.getEntityData:()Lnet/minecraft/nbt/NBTTagCompound;
      30: ldc_w         #443                // String simplemagnets:throwerIdMost
      33: invokevirtual #106                // Method net/minecraft/nbt/NBTTagCompound.func_74764_b:(Ljava/lang/String;)Z
      36: ifeq          63
      39: getstatic     #123                // Field com/supermartijn642/simplemagnets/SimpleMagnets.CHANNEL:Lcom/supermartijn642/core/network/PacketChannel;
      42: aload_0
      43: invokevirtual #436                // Method net/minecraftforge/event/entity/player/PlayerEvent$StartTracking.getEntityPlayer:()Lnet/minecraft/entity/player/EntityPlayer;
      46: new           #445                // class com/supermartijn642/simplemagnets/packets/magnet/PacketItemInfo
      49: dup
      50: aload_0
      51: invokevirtual #440                // Method net/minecraftforge/event/entity/player/PlayerEvent$StartTracking.getTarget:()Lnet/minecraft/entity/Entity;
      54: checkcast     #171                // class net/minecraft/entity/item/EntityItem
      57: invokespecial #447                // Method com/supermartijn642/simplemagnets/packets/magnet/PacketItemInfo."<init>":(Lnet/minecraft/entity/item/EntityItem;)V
      60: invokevirtual #134                // Method com/supermartijn642/core/network/PacketChannel.sendToPlayer:(Lnet/minecraft/entity/player/EntityPlayer;Lcom/supermartijn642/core/network/BasePacket;)V
      63: return

  private static void lambda$onUpdate$3(net.minecraft.entity.player.EntityPlayer, net.minecraft.entity.item.EntityXPOrb);
    descriptor: (Lnet/minecraft/entity/player/EntityPlayer;Lnet/minecraft/entity/item/EntityXPOrb;)V
    Code:
       0: aload_1
       1: iconst_0
       2: putfield      #452                // Field net/minecraft/entity/item/EntityXPOrb.field_70532_c:I
       5: aload_0
       6: iconst_0
       7: putfield      #455                // Field net/minecraft/entity/player/EntityPlayer.field_71090_bL:I
      10: aload_1
      11: aload_0
      12: invokevirtual #459                // Method net/minecraft/entity/item/EntityXPOrb.func_70100_b_:(Lnet/minecraft/entity/player/EntityPlayer;)V
      15: return

  private static void lambda$onUpdate$2(net.minecraft.entity.Entity, net.minecraft.entity.item.EntityItem);
    descriptor: (Lnet/minecraft/entity/Entity;Lnet/minecraft/entity/item/EntityItem;)V
    Code:
       0: aload_1
       1: aload_0
       2: checkcast     #73                 // class net/minecraft/entity/player/EntityPlayer
       5: invokestatic  #462                // Method playerTouch:(Lnet/minecraft/entity/item/EntityItem;Lnet/minecraft/entity/player/EntityPlayer;)V
       8: return

  private static void lambda$onUpdate$1(net.minecraft.entity.Entity, net.minecraft.entity.item.EntityItem);
    descriptor: (Lnet/minecraft/entity/Entity;Lnet/minecraft/entity/item/EntityItem;)V
    Code:
       0: aload_1
       1: aload_0
       2: getfield      #466                // Field net/minecraft/entity/Entity.field_70165_t:D
       5: aload_0
       6: getfield      #469                // Field net/minecraft/entity/Entity.field_70163_u:D
       9: aload_0
      10: getfield      #472                // Field net/minecraft/entity/Entity.field_70161_v:D
      13: invokevirtual #476                // Method net/minecraft/entity/item/EntityItem.func_70107_b:(DDD)V
      16: return

  private boolean lambda$onUpdate$0(net.minecraft.world.World, net.minecraft.entity.Entity, net.minecraft.nbt.NBTTagCompound, net.minecraft.entity.item.EntityItem);
    descriptor: (Lnet/minecraft/world/World;Lnet/minecraft/entity/Entity;Lnet/minecraft/nbt/NBTTagCompound;Lnet/minecraft/entity/item/EntityItem;)Z
    Code:
       0: aload         4
       2: invokevirtual #479                // Method net/minecraft/entity/item/EntityItem.func_70089_S:()Z
       5: ifeq          109
       8: aload_1
       9: getfield      #82                 // Field net/minecraft/world/World.field_72995_K:Z
      12: ifeq          24
      15: aload         4
      17: getfield      #482                // Field net/minecraft/entity/item/EntityItem.field_70173_aa:I
      20: iconst_1
      21: if_icmple     109
      24: aload         4
      26: invokevirtual #420                // Method net/minecraft/entity/item/EntityItem.getEntityData:()Lnet/minecraft/nbt/NBTTagCompound;
      29: ldc_w         #443                // String simplemagnets:throwerIdMost
      32: invokevirtual #106                // Method net/minecraft/nbt/NBTTagCompound.func_74764_b:(Ljava/lang/String;)Z
      35: ifeq          67
      38: aload         4
      40: invokevirtual #420                // Method net/minecraft/entity/item/EntityItem.getEntityData:()Lnet/minecraft/nbt/NBTTagCompound;
      43: ldc_w         #422                // String simplemagnets:throwerId
      46: invokevirtual #486                // Method net/minecraft/nbt/NBTTagCompound.func_186857_a:(Ljava/lang/String;)Ljava/util/UUID;
      49: aload_2
      50: invokevirtual #487                // Method net/minecraft/entity/Entity.func_110124_au:()Ljava/util/UUID;
      53: invokevirtual #490                // Method java/util/UUID.equals:(Ljava/lang/Object;)Z
      56: ifeq          67
      59: aload         4
      61: invokevirtual #265                // Method net/minecraft/entity/item/EntityItem.func_174874_s:()Z
      64: ifne          109
      67: aload         4
      69: invokevirtual #269                // Method net/minecraft/entity/item/EntityItem.func_92059_d:()Lnet/minecraft/item/ItemStack;
      72: invokevirtual #327                // Method net/minecraft/item/ItemStack.func_190926_b:()Z
      75: ifne          109
      78: aload         4
      80: invokevirtual #420                // Method net/minecraft/entity/item/EntityItem.getEntityData:()Lnet/minecraft/nbt/NBTTagCompound;
      83: ldc_w         #492                // String PreventRemoteMovement
      86: invokevirtual #106                // Method net/minecraft/nbt/NBTTagCompound.func_74764_b:(Ljava/lang/String;)Z
      89: ifne          109
      92: aload_0
      93: aload_3
      94: aload         4
      96: invokevirtual #269                // Method net/minecraft/entity/item/EntityItem.func_92059_d:()Lnet/minecraft/item/ItemStack;
      99: invokevirtual #494                // Method canPickupStack:(Lnet/minecraft/nbt/NBTTagCompound;Lnet/minecraft/item/ItemStack;)Z
     102: ifeq          109
     105: iconst_1
     106: goto          110
     109: iconst_0
     110: ireturn
}
