Compiled from "ArmsModel.java"
class artifacts.client.item.model.ArmsModel$1 extends artifacts.client.item.model.ArmsModel {
  artifacts.client.item.model.ArmsModel$1(net.minecraft.client.model.geom.ModelPart);
    descriptor: (Lnet/minecraft/client/model/geom/ModelPart;)V
    Code:
       0: aload_0
       1: aload_1
       2: invokespecial #13                 // Method artifacts/client/item/model/ArmsModel."<init>":(Lnet/minecraft/client/model/geom/ModelPart;)V
       5: return

  public void m_6973_(net.minecraft.world.entity.LivingEntity, float, float, float, float, float);
    descriptor: (Lnet/minecraft/world/entity/LivingEntity;FFFFF)V
    Code:
       0: aload_0
       1: aload_1
       2: fload_2
       3: fload_3
       4: fload         4
       6: fload         5
       8: fload         6
      10: invokespecial #26                 // Method artifacts/client/item/model/ArmsModel.m_6973_:(Lnet/minecraft/world/entity/LivingEntity;FFFFF)V
      13: aload_1
      14: aload_1
      15: getfield      #32                 // Field net/minecraft/world/entity/LivingEntity.f_20912_:Lnet/minecraft/world/InteractionHand;
      18: invokestatic  #38                 // Method artifacts/client/item/RendererUtil.getArmSide:(Lnet/minecraft/world/entity/LivingEntity;Lnet/minecraft/world/InteractionHand;)Lnet/minecraft/world/entity/HumanoidArm;
      21: astore        7
      23: aload_0
      24: aload         7
      26: invokevirtual #44                 // Method net/minecraft/world/entity/HumanoidArm.m_20828_:()Lnet/minecraft/world/entity/HumanoidArm;
      29: invokevirtual #48                 // Method getPistonHead:(Lnet/minecraft/world/entity/HumanoidArm;)Lnet/minecraft/client/model/geom/ModelPart;
      32: fconst_0
      33: putfield      #54                 // Field net/minecraft/client/model/geom/ModelPart.f_104201_:F
      36: aload_0
      37: aload         7
      39: invokevirtual #48                 // Method getPistonHead:(Lnet/minecraft/world/entity/HumanoidArm;)Lnet/minecraft/client/model/geom/ModelPart;
      42: aload_1
      43: checkcast     #56                 // class artifacts/extensions/pocketpiston/LivingEntityExtensions
      46: invokeinterface #60,  1           // InterfaceMethod artifacts/extensions/pocketpiston/LivingEntityExtensions.artifacts$getPocketPistonLength:()F
      51: fconst_2
      52: fmul
      53: putfield      #54                 // Field net/minecraft/client/model/geom/ModelPart.f_104201_:F
      56: return

  private net.minecraft.client.model.geom.ModelPart getPistonHead(net.minecraft.world.entity.HumanoidArm);
    descriptor: (Lnet/minecraft/world/entity/HumanoidArm;)Lnet/minecraft/client/model/geom/ModelPart;
    Code:
       0: aload_0
       1: aload_1
       2: invokevirtual #67                 // Method m_102851_:(Lnet/minecraft/world/entity/HumanoidArm;)Lnet/minecraft/client/model/geom/ModelPart;
       5: ldc           #69                 // String artifact
       7: invokevirtual #73                 // Method net/minecraft/client/model/geom/ModelPart.m_171324_:(Ljava/lang/String;)Lnet/minecraft/client/model/geom/ModelPart;
      10: ldc           #75                 // String piston_head
      12: invokevirtual #73                 // Method net/minecraft/client/model/geom/ModelPart.m_171324_:(Ljava/lang/String;)Lnet/minecraft/client/model/geom/ModelPart;
      15: areturn

  public void m_6973_(net.minecraft.world.entity.Entity, float, float, float, float, float);
    descriptor: (Lnet/minecraft/world/entity/Entity;FFFFF)V
    Code:
       0: aload_0
       1: aload_1
       2: checkcast     #28                 // class net/minecraft/world/entity/LivingEntity
       5: fload_2
       6: fload_3
       7: fload         4
       9: fload         5
      11: fload         6
      13: invokevirtual #77                 // Method m_6973_:(Lnet/minecraft/world/entity/LivingEntity;FFFFF)V
      16: return
}
