Compiled from "Language.java"
public class artifacts.neoforge.data.Language extends net.neoforged.neoforge.common.data.LanguageProvider {
  public artifacts.neoforge.data.Language(net.minecraft.data.PackOutput);
    descriptor: (Lnet/minecraft/data/PackOutput;)V
    Code:
       0: aload_0
       1: aload_1
       2: ldc           #20                 // String artifacts
       4: ldc           #22                 // String en_us
       6: invokespecial #25                 // Method net/neoforged/neoforge/common/data/LanguageProvider."<init>":(Lnet/minecraft/data/PackOutput;Ljava/lang/String;Ljava/lang/String;)V
       9: return

  protected void addTranslations();
    descriptor: ()V
    Code:
       0: getstatic     #36                 // Field artifacts/Artifacts.CONFIG:Lartifacts/config/ModConfig;
       3: invokevirtual #41                 // Method artifacts/config/ModConfig.setup:()V
       6: aload_0
       7: invokevirtual #44                 // Method addMiscTranslations:()V
      10: aload_0
      11: invokevirtual #47                 // Method addAbilities:()V
      14: aload_0
      15: invokevirtual #50                 // Method addAttributes:()V
      18: aload_0
      19: invokevirtual #53                 // Method addEntities:()V
      22: aload_0
      23: invokevirtual #56                 // Method addConfigs:()V
      26: aload_0
      27: invokevirtual #59                 // Method addItems:()V
      30: aload_0
      31: invokevirtual #62                 // Method addTags:()V
      34: aload_0
      35: invokevirtual #65                 // Method addTooltips:()V
      38: aload_0
      39: invokevirtual #68                 // Method addEffects:()V
      42: getstatic     #74                 // Field artifacts/neoforge/data/Advancements.TRANSLATIONS:Ljava/util/Map;
      45: aload_0
      46: invokedynamic #93,  0             // InvokeDynamic #0:accept:(Lartifacts/neoforge/data/Language;)Ljava/util/function/BiConsumer;
      51: invokeinterface #99,  2           // InterfaceMethod java/util/Map.forEach:(Ljava/util/function/BiConsumer;)V
      56: return

  public void override(java.lang.String, java.lang.String);
    descriptor: (Ljava/lang/String;Ljava/lang/String;)V
    Code:
       0: aload_0
       1: aload_1
       2: aload_2
       3: invokevirtual #105                // Method add:(Ljava/lang/String;Ljava/lang/String;)V
       6: goto          10
       9: astore_3
      10: return
    Exception table:
       from    to  target type
           0     6     9   Class java/lang/IllegalStateException

  private void addMiscTranslations();
    descriptor: ()V
    Code:
       0: aload_0
       1: ldc           #108                // String artifacts.creative_tab
       3: ldc           #110                // String Artifacts
       5: invokevirtual #105                // Method add:(Ljava/lang/String;Ljava/lang/String;)V
       8: aload_0
       9: invokedynamic #121,  0            // InvokeDynamic #1:accept:(Lartifacts/neoforge/data/Language;)Ljava/util/function/Consumer;
      14: invokestatic  #127                // Method artifacts/registry/ModKeyMappings.register:(Ljava/util/function/Consumer;)V
      17: aload_0
      18: ldc           #129                // String artifacts.key_category
      20: ldc           #110                // String Artifacts
      22: invokevirtual #105                // Method add:(Ljava/lang/String;Ljava/lang/String;)V
      25: aload_0
      26: getstatic     #135                // Field artifacts/registry/ModSoundEvents.FART:Lnet/minecraft/core/Holder;
      29: invokeinterface #140,  1          // InterfaceMethod net/minecraft/core/Holder.value:()Ljava/lang/Object;
      34: checkcast     #142                // class net/minecraft/sounds/SoundEvent
      37: ldc           #144                // String Fart
      39: invokevirtual #147                // Method add:(Lnet/minecraft/sounds/SoundEvent;Ljava/lang/String;)V
      42: aload_0
      43: ldc           #149                // String curios.identifier.feet
      45: ldc           #151                // String Feet
      47: invokevirtual #105                // Method add:(Ljava/lang/String;Ljava/lang/String;)V
      50: aload_0
      51: ldc           #153                // String curios.modifiers.feet
      53: ldc           #155                // String When on feet:
      55: invokevirtual #105                // Method add:(Ljava/lang/String;Ljava/lang/String;)V
      58: return

  private void addAbilities();
    descriptor: ()V
    Code:
       0: aload_0
       1: getstatic     #161                // Field artifacts/registry/ModDataComponents.POST_DAMAGE_EFFECTS:Ljava/util/function/Supplier;
       4: invokeinterface #166,  1          // InterfaceMethod java/util/function/Supplier.get:()Ljava/lang/Object;
       9: checkcast     #168                // class net/minecraft/core/component/DataComponentType
      12: getstatic     #173                // Field net/minecraft/world/effect/MobEffects.FIRE_RESISTANCE:Lnet/minecraft/core/Holder;
      15: iconst_1
      16: anewarray     #175                // class java/lang/String
      19: dup
      20: iconst_0
      21: ldc           #177                // String Applies a temporary fire resistance effect after taking fire damage
      23: aastore
      24: invokevirtual #181                // Method addAbilityTooltip:(Lnet/minecraft/core/component/DataComponentType;Lnet/minecraft/core/Holder;[Ljava/lang/String;)V
      27: aload_0
      28: getstatic     #161                // Field artifacts/registry/ModDataComponents.POST_DAMAGE_EFFECTS:Ljava/util/function/Supplier;
      31: invokeinterface #166,  1          // InterfaceMethod java/util/function/Supplier.get:()Ljava/lang/Object;
      36: checkcast     #168                // class net/minecraft/core/component/DataComponentType
      39: getstatic     #184                // Field net/minecraft/world/effect/MobEffects.MOVEMENT_SPEED:Lnet/minecraft/core/Holder;
      42: iconst_1
      43: anewarray     #175                // class java/lang/String
      46: dup
      47: iconst_0
      48: ldc           #186                // String Increases the wearer\'s movement speed after taking damage
      50: aastore
      51: invokevirtual #181                // Method addAbilityTooltip:(Lnet/minecraft/core/component/DataComponentType;Lnet/minecraft/core/Holder;[Ljava/lang/String;)V
      54: aload_0
      55: getstatic     #189                // Field artifacts/registry/ModDataComponents.POST_EATING_EFFECTS:Ljava/util/function/Supplier;
      58: invokeinterface #166,  1          // InterfaceMethod java/util/function/Supplier.get:()Ljava/lang/Object;
      63: checkcast     #168                // class net/minecraft/core/component/DataComponentType
      66: getstatic     #192                // Field net/minecraft/world/effect/MobEffects.DIG_SPEED:Lnet/minecraft/core/Holder;
      69: iconst_1
      70: anewarray     #175                // class java/lang/String
      73: dup
      74: iconst_0
      75: ldc           #194                // String Grants a temporary boost to mining speed after eating food
      77: aastore
      78: invokevirtual #181                // Method addAbilityTooltip:(Lnet/minecraft/core/component/DataComponentType;Lnet/minecraft/core/Holder;[Ljava/lang/String;)V
      81: aload_0
      82: getstatic     #197                // Field artifacts/registry/ModDataComponents.DAMAGE_ABSORPTION:Ljava/util/function/Supplier;
      85: invokeinterface #166,  1          // InterfaceMethod java/util/function/Supplier.get:()Ljava/lang/Object;
      90: checkcast     #168                // class net/minecraft/core/component/DataComponentType
      93: iconst_2
      94: anewarray     #175                // class java/lang/String
      97: dup
      98: iconst_0
      99: ldc           #199                // String chance
     101: aastore
     102: dup
     103: iconst_1
     104: ldc           #201                // String The wearer\'s melee attacks have a %s%% chance to absorb health
     106: aastore
     107: invokevirtual #204                // Method addAbilityTooltip:(Lnet/minecraft/core/component/DataComponentType;[Ljava/lang/String;)V
     110: aload_0
     111: getstatic     #197                // Field artifacts/registry/ModDataComponents.DAMAGE_ABSORPTION:Ljava/util/function/Supplier;
     114: invokeinterface #166,  1          // InterfaceMethod java/util/function/Supplier.get:()Ljava/lang/Object;
     119: checkcast     #168                // class net/minecraft/core/component/DataComponentType
     122: iconst_2
     123: anewarray     #175                // class java/lang/String
     126: dup
     127: iconst_0
     128: ldc           #206                // String constant
     130: aastore
     131: dup
     132: iconst_1
     133: ldc           #208                // String Causes the wearer\'s melee attacks to absorb health
     135: aastore
     136: invokevirtual #204                // Method addAbilityTooltip:(Lnet/minecraft/core/component/DataComponentType;[Ljava/lang/String;)V
     139: aload_0
     140: getstatic     #211                // Field artifacts/registry/ModDataComponents.ATTACK_EFFECTS:Ljava/util/function/Supplier;
     143: invokeinterface #166,  1          // InterfaceMethod java/util/function/Supplier.get:()Ljava/lang/Object;
     148: checkcast     #168                // class net/minecraft/core/component/DataComponentType
     151: getstatic     #214                // Field net/minecraft/world/effect/MobEffects.WITHER:Lnet/minecraft/core/Holder;
     154: iconst_2
     155: anewarray     #175                // class java/lang/String
     158: dup
     159: iconst_0
     160: ldc           #199                // String chance
     162: aastore
     163: dup
     164: iconst_1
     165: ldc           #216                // String Melee attacks have a chance to inflict a wither effect
     167: aastore
     168: invokevirtual #181                // Method addAbilityTooltip:(Lnet/minecraft/core/component/DataComponentType;Lnet/minecraft/core/Holder;[Ljava/lang/String;)V
     171: aload_0
     172: getstatic     #211                // Field artifacts/registry/ModDataComponents.ATTACK_EFFECTS:Ljava/util/function/Supplier;
     175: invokeinterface #166,  1          // InterfaceMethod java/util/function/Supplier.get:()Ljava/lang/Object;
     180: checkcast     #168                // class net/minecraft/core/component/DataComponentType
     183: getstatic     #214                // Field net/minecraft/world/effect/MobEffects.WITHER:Lnet/minecraft/core/Holder;
     186: iconst_2
     187: anewarray     #175                // class java/lang/String
     190: dup
     191: iconst_0
     192: ldc           #206                // String constant
     194: aastore
     195: dup
     196: iconst_1
     197: ldc           #218                // String Causes the wearer\'s melee attacks to inflict a wither effect
     199: aastore
     200: invokevirtual #181                // Method addAbilityTooltip:(Lnet/minecraft/core/component/DataComponentType;Lnet/minecraft/core/Holder;[Ljava/lang/String;)V
     203: aload_0
     204: getstatic     #221                // Field artifacts/registry/ModDataComponents.ATTRIBUTE_MODIFIERS:Ljava/util/function/Supplier;
     207: invokeinterface #166,  1          // InterfaceMethod java/util/function/Supplier.get:()Ljava/lang/Object;
     212: checkcast     #168                // class net/minecraft/core/component/DataComponentType
     215: getstatic     #226                // Field artifacts/registry/ModAttributes.ATTACK_BURNING_DURATION:Lnet/minecraft/core/Holder;
     218: iconst_1
     219: anewarray     #175                // class java/lang/String
     222: dup
     223: iconst_0
     224: ldc           #228                // String Causes the wearer\'s melee attacks to deal fire damage
     226: aastore
     227: invokevirtual #181                // Method addAbilityTooltip:(Lnet/minecraft/core/component/DataComponentType;Lnet/minecraft/core/Holder;[Ljava/lang/String;)V
     230: aload_0
     231: getstatic     #221                // Field artifacts/registry/ModDataComponents.ATTRIBUTE_MODIFIERS:Ljava/util/function/Supplier;
     234: invokeinterface #166,  1          // InterfaceMethod java/util/function/Supplier.get:()Ljava/lang/Object;
     239: checkcast     #168                // class net/minecraft/core/component/DataComponentType
     242: getstatic     #233                // Field net/minecraft/world/entity/ai/attributes/Attributes.ATTACK_DAMAGE:Lnet/minecraft/core/Holder;
     245: iconst_1
     246: anewarray     #175                // class java/lang/String
     249: dup
     250: iconst_0
     251: ldc           #235                // String Increases damage dealt by the wearer
     253: aastore
     254: invokevirtual #181                // Method addAbilityTooltip:(Lnet/minecraft/core/component/DataComponentType;Lnet/minecraft/core/Holder;[Ljava/lang/String;)V
     257: aload_0
     258: getstatic     #221                // Field artifacts/registry/ModDataComponents.ATTRIBUTE_MODIFIERS:Ljava/util/function/Supplier;
     261: invokeinterface #166,  1          // InterfaceMethod java/util/function/Supplier.get:()Ljava/lang/Object;
     266: checkcast     #168                // class net/minecraft/core/component/DataComponentType
     269: getstatic     #238                // Field net/minecraft/world/entity/ai/attributes/Attributes.ATTACK_KNOCKBACK:Lnet/minecraft/core/Holder;
     272: iconst_1
     273: anewarray     #175                // class java/lang/String
     276: dup
     277: iconst_0
     278: ldc           #240                // String Increases knockback dealt by the wearer
     280: aastore
     281: invokevirtual #181                // Method addAbilityTooltip:(Lnet/minecraft/core/component/DataComponentType;Lnet/minecraft/core/Holder;[Ljava/lang/String;)V
     284: aload_0
     285: getstatic     #221                // Field artifacts/registry/ModDataComponents.ATTRIBUTE_MODIFIERS:Ljava/util/function/Supplier;
     288: invokeinterface #166,  1          // InterfaceMethod java/util/function/Supplier.get:()Ljava/lang/Object;
     293: checkcast     #168                // class net/minecraft/core/component/DataComponentType
     296: getstatic     #243                // Field net/minecraft/world/entity/ai/attributes/Attributes.ATTACK_SPEED:Lnet/minecraft/core/Holder;
     299: iconst_1
     300: anewarray     #175                // class java/lang/String
     303: dup
     304: iconst_0
     305: ldc           #245                // String Increases the wearer\'s attack speed
     307: aastore
     308: invokevirtual #181                // Method addAbilityTooltip:(Lnet/minecraft/core/component/DataComponentType;Lnet/minecraft/core/Holder;[Ljava/lang/String;)V
     311: aload_0
     312: getstatic     #221                // Field artifacts/registry/ModDataComponents.ATTRIBUTE_MODIFIERS:Ljava/util/function/Supplier;
     315: invokeinterface #166,  1          // InterfaceMethod java/util/function/Supplier.get:()Ljava/lang/Object;
     320: checkcast     #168                // class net/minecraft/core/component/DataComponentType
     323: getstatic     #248                // Field artifacts/registry/ModAttributes.DRINKING_SPEED:Lnet/minecraft/core/Holder;
     326: iconst_1
     327: anewarray     #175                // class java/lang/String
     330: dup
     331: iconst_0
     332: ldc           #250                // String Decreases the time it takes to drink items
     334: aastore
     335: invokevirtual #181                // Method addAbilityTooltip:(Lnet/minecraft/core/component/DataComponentType;Lnet/minecraft/core/Holder;[Ljava/lang/String;)V
     338: aload_0
     339: getstatic     #221                // Field artifacts/registry/ModDataComponents.ATTRIBUTE_MODIFIERS:Ljava/util/function/Supplier;
     342: invokeinterface #166,  1          // InterfaceMethod java/util/function/Supplier.get:()Ljava/lang/Object;
     347: checkcast     #168                // class net/minecraft/core/component/DataComponentType
     350: getstatic     #253                // Field artifacts/registry/ModAttributes.EATING_SPEED:Lnet/minecraft/core/Holder;
     353: iconst_1
     354: anewarray     #175                // class java/lang/String
     357: dup
     358: iconst_0
     359: ldc           #255                // String Decreases the time it takes to eat items
     361: aastore
     362: invokevirtual #181                // Method addAbilityTooltip:(Lnet/minecraft/core/component/DataComponentType;Lnet/minecraft/core/Holder;[Ljava/lang/String;)V
     365: aload_0
     366: getstatic     #221                // Field artifacts/registry/ModDataComponents.ATTRIBUTE_MODIFIERS:Ljava/util/function/Supplier;
     369: invokeinterface #166,  1          // InterfaceMethod java/util/function/Supplier.get:()Ljava/lang/Object;
     374: checkcast     #168                // class net/minecraft/core/component/DataComponentType
     377: getstatic     #258                // Field net/minecraft/world/entity/ai/attributes/Attributes.FALL_DAMAGE_MULTIPLIER:Lnet/minecraft/core/Holder;
     380: iconst_1
     381: anewarray     #175                // class java/lang/String
     384: dup
     385: iconst_0
     386: ldc_w         #260                // String Reduces fall damage taken by the wearer
     389: aastore
     390: invokevirtual #181                // Method addAbilityTooltip:(Lnet/minecraft/core/component/DataComponentType;Lnet/minecraft/core/Holder;[Ljava/lang/String;)V
     393: aload_0
     394: getstatic     #221                // Field artifacts/registry/ModDataComponents.ATTRIBUTE_MODIFIERS:Ljava/util/function/Supplier;
     397: invokeinterface #166,  1          // InterfaceMethod java/util/function/Supplier.get:()Ljava/lang/Object;
     402: checkcast     #168                // class net/minecraft/core/component/DataComponentType
     405: getstatic     #263                // Field artifacts/registry/ModAttributes.FLATULENCE:Lnet/minecraft/core/Holder;
     408: iconst_1
     409: anewarray     #175                // class java/lang/String
     412: dup
     413: iconst_0
     414: ldc_w         #265                // String Increases the wearer\'s flatulence
     417: aastore
     418: invokevirtual #181                // Method addAbilityTooltip:(Lnet/minecraft/core/component/DataComponentType;Lnet/minecraft/core/Holder;[Ljava/lang/String;)V
     421: aload_0
     422: getstatic     #221                // Field artifacts/registry/ModDataComponents.ATTRIBUTE_MODIFIERS:Ljava/util/function/Supplier;
     425: invokeinterface #166,  1          // InterfaceMethod java/util/function/Supplier.get:()Ljava/lang/Object;
     430: checkcast     #168                // class net/minecraft/core/component/DataComponentType
     433: getstatic     #268                // Field artifacts/registry/ModAttributes.INVINCIBILITY_TICKS:Lnet/minecraft/core/Holder;
     436: iconst_1
     437: anewarray     #175                // class java/lang/String
     440: dup
     441: iconst_0
     442: ldc_w         #270                // String Increases the length of invincibility after taking damage
     445: aastore
     446: invokevirtual #181                // Method addAbilityTooltip:(Lnet/minecraft/core/component/DataComponentType;Lnet/minecraft/core/Holder;[Ljava/lang/String;)V
     449: aload_0
     450: getstatic     #221                // Field artifacts/registry/ModDataComponents.ATTRIBUTE_MODIFIERS:Ljava/util/function/Supplier;
     453: invokeinterface #166,  1          // InterfaceMethod java/util/function/Supplier.get:()Ljava/lang/Object;
     458: checkcast     #168                // class net/minecraft/core/component/DataComponentType
     461: getstatic     #273                // Field net/minecraft/world/entity/ai/attributes/Attributes.JUMP_STRENGTH:Lnet/minecraft/core/Holder;
     464: iconst_1
     465: anewarray     #175                // class java/lang/String
     468: dup
     469: iconst_0
     470: ldc_w         #275                // String Increases the wearer\'s jump height
     473: aastore
     474: invokevirtual #181                // Method addAbilityTooltip:(Lnet/minecraft/core/component/DataComponentType;Lnet/minecraft/core/Holder;[Ljava/lang/String;)V
     477: aload_0
     478: getstatic     #221                // Field artifacts/registry/ModDataComponents.ATTRIBUTE_MODIFIERS:Ljava/util/function/Supplier;
     481: invokeinterface #166,  1          // InterfaceMethod java/util/function/Supplier.get:()Ljava/lang/Object;
     486: checkcast     #168                // class net/minecraft/core/component/DataComponentType
     489: getstatic     #278                // Field net/minecraft/world/entity/ai/attributes/Attributes.KNOCKBACK_RESISTANCE:Lnet/minecraft/core/Holder;
     492: iconst_1
     493: anewarray     #175                // class java/lang/String
     496: dup
     497: iconst_0
     498: ldc_w         #280                // String Grants immunity to knockback
     501: aastore
     502: invokevirtual #181                // Method addAbilityTooltip:(Lnet/minecraft/core/component/DataComponentType;Lnet/minecraft/core/Holder;[Ljava/lang/String;)V
     505: aload_0
     506: getstatic     #221                // Field artifacts/registry/ModDataComponents.ATTRIBUTE_MODIFIERS:Ljava/util/function/Supplier;
     509: invokeinterface #166,  1          // InterfaceMethod java/util/function/Supplier.get:()Ljava/lang/Object;
     514: checkcast     #168                // class net/minecraft/core/component/DataComponentType
     517: getstatic     #283                // Field net/minecraft/world/entity/ai/attributes/Attributes.MAX_HEALTH:Lnet/minecraft/core/Holder;
     520: iconst_1
     521: anewarray     #175                // class java/lang/String
     524: dup
     525: iconst_0
     526: ldc_w         #285                // String Increases the wearer\'s maximum health
     529: aastore
     530: invokevirtual #181                // Method addAbilityTooltip:(Lnet/minecraft/core/component/DataComponentType;Lnet/minecraft/core/Holder;[Ljava/lang/String;)V
     533: aload_0
     534: getstatic     #221                // Field artifacts/registry/ModDataComponents.ATTRIBUTE_MODIFIERS:Ljava/util/function/Supplier;
     537: invokeinterface #166,  1          // InterfaceMethod java/util/function/Supplier.get:()Ljava/lang/Object;
     542: checkcast     #168                // class net/minecraft/core/component/DataComponentType
     545: getstatic     #288                // Field artifacts/registry/ModAttributes.MOUNT_SPEED:Lnet/minecraft/core/Holder;
     548: iconst_1
     549: anewarray     #175                // class java/lang/String
     552: dup
     553: iconst_0
     554: ldc_w         #290                // String Increases the speed of ridden mounts
     557: aastore
     558: invokevirtual #181                // Method addAbilityTooltip:(Lnet/minecraft/core/component/DataComponentType;Lnet/minecraft/core/Holder;[Ljava/lang/String;)V
     561: aload_0
     562: getstatic     #221                // Field artifacts/registry/ModDataComponents.ATTRIBUTE_MODIFIERS:Ljava/util/function/Supplier;
     565: invokeinterface #166,  1          // InterfaceMethod java/util/function/Supplier.get:()Ljava/lang/Object;
     570: checkcast     #168                // class net/minecraft/core/component/DataComponentType
     573: getstatic     #293                // Field net/minecraft/world/entity/ai/attributes/Attributes.SAFE_FALL_DISTANCE:Lnet/minecraft/core/Holder;
     576: iconst_1
     577: anewarray     #175                // class java/lang/String
     580: dup
     581: iconst_0
     582: ldc_w         #295                // String Increases the wearer\'s maximum safe fall distance
     585: aastore
     586: invokevirtual #181                // Method addAbilityTooltip:(Lnet/minecraft/core/component/DataComponentType;Lnet/minecraft/core/Holder;[Ljava/lang/String;)V
     589: aload_0
     590: getstatic     #221                // Field artifacts/registry/ModDataComponents.ATTRIBUTE_MODIFIERS:Ljava/util/function/Supplier;
     593: invokeinterface #166,  1          // InterfaceMethod java/util/function/Supplier.get:()Ljava/lang/Object;
     598: checkcast     #168                // class net/minecraft/core/component/DataComponentType
     601: getstatic     #298                // Field net/minecraft/world/entity/ai/attributes/Attributes.SCALE:Lnet/minecraft/core/Holder;
     604: iconst_1
     605: anewarray     #175                // class java/lang/String
     608: dup
     609: iconst_0
     610: ldc_w         #300                // String Shrinks the wearer
     613: aastore
     614: invokevirtual #181                // Method addAbilityTooltip:(Lnet/minecraft/core/component/DataComponentType;Lnet/minecraft/core/Holder;[Ljava/lang/String;)V
     617: aload_0
     618: getstatic     #221                // Field artifacts/registry/ModDataComponents.ATTRIBUTE_MODIFIERS:Ljava/util/function/Supplier;
     621: invokeinterface #166,  1          // InterfaceMethod java/util/function/Supplier.get:()Ljava/lang/Object;
     626: checkcast     #168                // class net/minecraft/core/component/DataComponentType
     629: getstatic     #303                // Field artifacts/registry/ModAttributes.SLIP_RESISTANCE:Lnet/minecraft/core/Holder;
     632: iconst_1
     633: anewarray     #175                // class java/lang/String
     636: dup
     637: iconst_0
     638: ldc_w         #305                // String Makes ice less slippery to walk on
     641: aastore
     642: invokevirtual #181                // Method addAbilityTooltip:(Lnet/minecraft/core/component/DataComponentType;Lnet/minecraft/core/Holder;[Ljava/lang/String;)V
     645: aload_0
     646: getstatic     #221                // Field artifacts/registry/ModDataComponents.ATTRIBUTE_MODIFIERS:Ljava/util/function/Supplier;
     649: invokeinterface #166,  1          // InterfaceMethod java/util/function/Supplier.get:()Ljava/lang/Object;
     654: checkcast     #168                // class net/minecraft/core/component/DataComponentType
     657: getstatic     #308                // Field artifacts/registry/ModAttributes.MOVEMENT_SPEED_ON_SNOW:Lnet/minecraft/core/Holder;
     660: iconst_1
     661: anewarray     #175                // class java/lang/String
     664: dup
     665: iconst_0
     666: ldc_w         #310                // String Increases the wearer\'s walking speed on snow
     669: aastore
     670: invokevirtual #181                // Method addAbilityTooltip:(Lnet/minecraft/core/component/DataComponentType;Lnet/minecraft/core/Holder;[Ljava/lang/String;)V
     673: aload_0
     674: getstatic     #221                // Field artifacts/registry/ModDataComponents.ATTRIBUTE_MODIFIERS:Ljava/util/function/Supplier;
     677: invokeinterface #166,  1          // InterfaceMethod java/util/function/Supplier.get:()Ljava/lang/Object;
     682: checkcast     #168                // class net/minecraft/core/component/DataComponentType
     685: getstatic     #313                // Field artifacts/registry/ModAttributes.SPRINTING_SPEED:Lnet/minecraft/core/Holder;
     688: iconst_1
     689: anewarray     #175                // class java/lang/String
     692: dup
     693: iconst_0
     694: ldc_w         #315                // String Increases the wearer\'s movement speed while sprinting
     697: aastore
     698: invokevirtual #181                // Method addAbilityTooltip:(Lnet/minecraft/core/component/DataComponentType;Lnet/minecraft/core/Holder;[Ljava/lang/String;)V
     701: aload_0
     702: getstatic     #221                // Field artifacts/registry/ModDataComponents.ATTRIBUTE_MODIFIERS:Ljava/util/function/Supplier;
     705: invokeinterface #166,  1          // InterfaceMethod java/util/function/Supplier.get:()Ljava/lang/Object;
     710: checkcast     #168                // class net/minecraft/core/component/DataComponentType
     713: getstatic     #318                // Field artifacts/registry/ModAttributes.SPRINTING_STEP_HEIGHT:Lnet/minecraft/core/Holder;
     716: iconst_1
     717: anewarray     #175                // class java/lang/String
     720: dup
     721: iconst_0
     722: ldc_w         #320                // String Increases the wearer\'s step height while sprinting
     725: aastore
     726: invokevirtual #181                // Method addAbilityTooltip:(Lnet/minecraft/core/component/DataComponentType;Lnet/minecraft/core/Holder;[Ljava/lang/String;)V
     729: aload_0
     730: getstatic     #221                // Field artifacts/registry/ModDataComponents.ATTRIBUTE_MODIFIERS:Ljava/util/function/Supplier;
     733: invokeinterface #166,  1          // InterfaceMethod java/util/function/Supplier.get:()Ljava/lang/Object;
     738: checkcast     #168                // class net/minecraft/core/component/DataComponentType
     741: iconst_2
     742: anewarray     #175                // class java/lang/String
     745: dup
     746: iconst_0
     747: ldc_w         #322                // String generic.swim_speed
     750: aastore
     751: dup
     752: iconst_1
     753: ldc_w         #324                // String Improves agility in water
     756: aastore
     757: invokevirtual #204                // Method addAbilityTooltip:(Lnet/minecraft/core/component/DataComponentType;[Ljava/lang/String;)V
     760: aload_0
     761: getstatic     #221                // Field artifacts/registry/ModDataComponents.ATTRIBUTE_MODIFIERS:Ljava/util/function/Supplier;
     764: invokeinterface #166,  1          // InterfaceMethod java/util/function/Supplier.get:()Ljava/lang/Object;
     769: checkcast     #168                // class net/minecraft/core/component/DataComponentType
     772: getstatic     #327                // Field net/minecraft/world/entity/ai/attributes/Attributes.BLOCK_BREAK_SPEED:Lnet/minecraft/core/Holder;
     775: iconst_1
     776: anewarray     #175                // class java/lang/String
     779: dup
     780: iconst_0
     781: ldc_w         #329                // String Increases the wearer\'s mining speed
     784: aastore
     785: invokevirtual #181                // Method addAbilityTooltip:(Lnet/minecraft/core/component/DataComponentType;Lnet/minecraft/core/Holder;[Ljava/lang/String;)V
     788: aload_0
     789: getstatic     #221                // Field artifacts/registry/ModDataComponents.ATTRIBUTE_MODIFIERS:Ljava/util/function/Supplier;
     792: invokeinterface #166,  1          // InterfaceMethod java/util/function/Supplier.get:()Ljava/lang/Object;
     797: checkcast     #168                // class net/minecraft/core/component/DataComponentType
     800: getstatic     #332                // Field artifacts/registry/ModAttributes.ENTITY_EXPERIENCE:Lnet/minecraft/core/Holder;
     803: iconst_1
     804: anewarray     #175                // class java/lang/String
     807: dup
     808: iconst_0
     809: ldc_w         #334                // String Increases experience dropped by creatures
     812: aastore
     813: invokevirtual #181                // Method addAbilityTooltip:(Lnet/minecraft/core/component/DataComponentType;Lnet/minecraft/core/Holder;[Ljava/lang/String;)V
     816: aload_0
     817: getstatic     #221                // Field artifacts/registry/ModDataComponents.ATTRIBUTE_MODIFIERS:Ljava/util/function/Supplier;
     820: invokeinterface #166,  1          // InterfaceMethod java/util/function/Supplier.get:()Ljava/lang/Object;
     825: checkcast     #168                // class net/minecraft/core/component/DataComponentType
     828: getstatic     #337                // Field artifacts/registry/ModAttributes.VILLAGER_REPUTATION:Lnet/minecraft/core/Holder;
     831: iconst_1
     832: anewarray     #175                // class java/lang/String
     835: dup
     836: iconst_0
     837: ldc_w         #339                // String Decreases the trading prices of villagers
     840: aastore
     841: invokevirtual #181                // Method addAbilityTooltip:(Lnet/minecraft/core/component/DataComponentType;Lnet/minecraft/core/Holder;[Ljava/lang/String;)V
     844: aload_0
     845: getstatic     #221                // Field artifacts/registry/ModDataComponents.ATTRIBUTE_MODIFIERS:Ljava/util/function/Supplier;
     848: invokeinterface #166,  1          // InterfaceMethod java/util/function/Supplier.get:()Ljava/lang/Object;
     853: checkcast     #168                // class net/minecraft/core/component/DataComponentType
     856: getstatic     #342                // Field net/minecraft/world/entity/ai/attributes/Attributes.OXYGEN_BONUS:Lnet/minecraft/core/Holder;
     859: iconst_1
     860: anewarray     #175                // class java/lang/String
     863: dup
     864: iconst_0
     865: ldc_w         #344                // String Increases the time the wearer can stay underwater
     868: aastore
     869: invokevirtual #181                // Method addAbilityTooltip:(Lnet/minecraft/core/component/DataComponentType;Lnet/minecraft/core/Holder;[Ljava/lang/String;)V
     872: aload_0
     873: getstatic     #347                // Field artifacts/registry/ModDataComponents.DAMAGE_IMMUNITY:Ljava/util/function/Supplier;
     876: invokeinterface #166,  1          // InterfaceMethod java/util/function/Supplier.get:()Ljava/lang/Object;
     881: checkcast     #168                // class net/minecraft/core/component/DataComponentType
     884: iconst_2
     885: anewarray     #175                // class java/lang/String
     888: dup
     889: iconst_0
     890: getstatic     #353                // Field artifacts/registry/ModTags.IS_HOT_FLOOR:Lnet/minecraft/tags/TagKey;
     893: invokevirtual #359                // Method net/minecraft/tags/TagKey.location:()Lnet/minecraft/resources/ResourceLocation;
     896: invokevirtual #365                // Method net/minecraft/resources/ResourceLocation.getPath:()Ljava/lang/String;
     899: aastore
     900: dup
     901: iconst_1
     902: ldc_w         #367                // String Grants protection against hot floor damage
     905: aastore
     906: invokevirtual #204                // Method addAbilityTooltip:(Lnet/minecraft/core/component/DataComponentType;[Ljava/lang/String;)V
     909: aload_0
     910: getstatic     #347                // Field artifacts/registry/ModDataComponents.DAMAGE_IMMUNITY:Ljava/util/function/Supplier;
     913: invokeinterface #166,  1          // InterfaceMethod java/util/function/Supplier.get:()Ljava/lang/Object;
     918: checkcast     #168                // class net/minecraft/core/component/DataComponentType
     921: iconst_2
     922: anewarray     #175                // class java/lang/String
     925: dup
     926: iconst_0
     927: getstatic     #372                // Field net/minecraft/tags/DamageTypeTags.IS_LIGHTNING:Lnet/minecraft/tags/TagKey;
     930: invokevirtual #359                // Method net/minecraft/tags/TagKey.location:()Lnet/minecraft/resources/ResourceLocation;
     933: invokevirtual #365                // Method net/minecraft/resources/ResourceLocation.getPath:()Ljava/lang/String;
     936: aastore
     937: dup
     938: iconst_1
     939: ldc_w         #374                // String Grants protection against lightning strikes
     942: aastore
     943: invokevirtual #204                // Method addAbilityTooltip:(Lnet/minecraft/core/component/DataComponentType;[Ljava/lang/String;)V
     946: aload_0
     947: getstatic     #377                // Field artifacts/registry/ModDataComponents.DOUBLE_JUMP:Ljava/util/function/Supplier;
     950: invokeinterface #166,  1          // InterfaceMethod java/util/function/Supplier.get:()Ljava/lang/Object;
     955: checkcast     #168                // class net/minecraft/core/component/DataComponentType
     958: iconst_1
     959: anewarray     #175                // class java/lang/String
     962: dup
     963: iconst_0
     964: ldc_w         #379                // String Allows the wearer to double jump
     967: aastore
     968: invokevirtual #204                // Method addAbilityTooltip:(Lnet/minecraft/core/component/DataComponentType;[Ljava/lang/String;)V
     971: aload_0
     972: getstatic     #382                // Field artifacts/registry/ModDataComponents.ENDER_PEARL_HUNGER_COST:Ljava/util/function/Supplier;
     975: invokeinterface #166,  1          // InterfaceMethod java/util/function/Supplier.get:()Ljava/lang/Object;
     980: checkcast     #168                // class net/minecraft/core/component/DataComponentType
     983: iconst_2
     984: anewarray     #175                // class java/lang/String
     987: dup
     988: iconst_0
     989: ldc_w         #384                // String free
     992: aastore
     993: dup
     994: iconst_1
     995: ldc_w         #386                // String Ender Pearls are not consumed when thrown
     998: aastore
     999: invokevirtual #204                // Method addAbilityTooltip:(Lnet/minecraft/core/component/DataComponentType;[Ljava/lang/String;)V
    1002: aload_0
    1003: getstatic     #382                // Field artifacts/registry/ModDataComponents.ENDER_PEARL_HUNGER_COST:Ljava/util/function/Supplier;
    1006: invokeinterface #166,  1          // InterfaceMethod java/util/function/Supplier.get:()Ljava/lang/Object;
    1011: checkcast     #168                // class net/minecraft/core/component/DataComponentType
    1014: iconst_2
    1015: anewarray     #175                // class java/lang/String
    1018: dup
    1019: iconst_0
    1020: ldc_w         #388                // String cost
    1023: aastore
    1024: dup
    1025: iconst_1
    1026: ldc_w         #390                // String Ender Pearls are not consumed, but cost hunger instead
    1029: aastore
    1030: invokevirtual #204                // Method addAbilityTooltip:(Lnet/minecraft/core/component/DataComponentType;[Ljava/lang/String;)V
    1033: aload_0
    1034: getstatic     #393                // Field artifacts/registry/ModDataComponents.POST_EATING_PLANT_GROWTH:Ljava/util/function/Supplier;
    1037: invokeinterface #166,  1          // InterfaceMethod java/util/function/Supplier.get:()Ljava/lang/Object;
    1042: checkcast     #168                // class net/minecraft/core/component/DataComponentType
    1045: iconst_1
    1046: anewarray     #175                // class java/lang/String
    1049: dup
    1050: iconst_0
    1051: ldc_w         #395                // String Plants grow after eating when standing on grass
    1054: aastore
    1055: invokevirtual #204                // Method addAbilityTooltip:(Lnet/minecraft/core/component/DataComponentType;[Ljava/lang/String;)V
    1058: aload_0
    1059: getstatic     #398                // Field artifacts/registry/ModDataComponents.ENCHANTMENT_LEVEL_MODIFIERS:Ljava/util/function/Supplier;
    1062: invokeinterface #166,  1          // InterfaceMethod java/util/function/Supplier.get:()Ljava/lang/Object;
    1067: checkcast     #168                // class net/minecraft/core/component/DataComponentType
    1070: iconst_3
    1071: anewarray     #175                // class java/lang/String
    1074: dup
    1075: iconst_0
    1076: ldc_w         #400                // String fortune
    1079: aastore
    1080: dup
    1081: iconst_1
    1082: ldc_w         #402                // String multiple_levels
    1085: aastore
    1086: dup
    1087: iconst_2
    1088: ldc_w         #404                // String Applies %s extra levels of fortune to mined blocks
    1091: aastore
    1092: invokevirtual #204                // Method addAbilityTooltip:(Lnet/minecraft/core/component/DataComponentType;[Ljava/lang/String;)V
    1095: aload_0
    1096: getstatic     #398                // Field artifacts/registry/ModDataComponents.ENCHANTMENT_LEVEL_MODIFIERS:Ljava/util/function/Supplier;
    1099: invokeinterface #166,  1          // InterfaceMethod java/util/function/Supplier.get:()Ljava/lang/Object;
    1104: checkcast     #168                // class net/minecraft/core/component/DataComponentType
    1107: iconst_3
    1108: anewarray     #175                // class java/lang/String
    1111: dup
    1112: iconst_0
    1113: ldc_w         #400                // String fortune
    1116: aastore
    1117: dup
    1118: iconst_1
    1119: ldc_w         #406                // String single_level
    1122: aastore
    1123: dup
    1124: iconst_2
    1125: ldc_w         #408                // String Applies an extra level of fortune to mined blocks
    1128: aastore
    1129: invokevirtual #204                // Method addAbilityTooltip:(Lnet/minecraft/core/component/DataComponentType;[Ljava/lang/String;)V
    1132: aload_0
    1133: getstatic     #398                // Field artifacts/registry/ModDataComponents.ENCHANTMENT_LEVEL_MODIFIERS:Ljava/util/function/Supplier;
    1136: invokeinterface #166,  1          // InterfaceMethod java/util/function/Supplier.get:()Ljava/lang/Object;
    1141: checkcast     #168                // class net/minecraft/core/component/DataComponentType
    1144: iconst_3
    1145: anewarray     #175                // class java/lang/String
    1148: dup
    1149: iconst_0
    1150: ldc_w         #410                // String looting
    1153: aastore
    1154: dup
    1155: iconst_1
    1156: ldc_w         #402                // String multiple_levels
    1159: aastore
    1160: dup
    1161: iconst_2
    1162: ldc_w         #412                // String Applies %s extra levels of looting to killed entities
    1165: aastore
    1166: invokevirtual #204                // Method addAbilityTooltip:(Lnet/minecraft/core/component/DataComponentType;[Ljava/lang/String;)V
    1169: aload_0
    1170: getstatic     #398                // Field artifacts/registry/ModDataComponents.ENCHANTMENT_LEVEL_MODIFIERS:Ljava/util/function/Supplier;
    1173: invokeinterface #166,  1          // InterfaceMethod java/util/function/Supplier.get:()Ljava/lang/Object;
    1178: checkcast     #168                // class net/minecraft/core/component/DataComponentType
    1181: iconst_3
    1182: anewarray     #175                // class java/lang/String
    1185: dup
    1186: iconst_0
    1187: ldc_w         #410                // String looting
    1190: aastore
    1191: dup
    1192: iconst_1
    1193: ldc_w         #406                // String single_level
    1196: aastore
    1197: dup
    1198: iconst_2
    1199: ldc_w         #414                // String Applies an extra level of looting to killed entities
    1202: aastore
    1203: invokevirtual #204                // Method addAbilityTooltip:(Lnet/minecraft/core/component/DataComponentType;[Ljava/lang/String;)V
    1206: aload_0
    1207: getstatic     #398                // Field artifacts/registry/ModDataComponents.ENCHANTMENT_LEVEL_MODIFIERS:Ljava/util/function/Supplier;
    1210: invokeinterface #166,  1          // InterfaceMethod java/util/function/Supplier.get:()Ljava/lang/Object;
    1215: checkcast     #168                // class net/minecraft/core/component/DataComponentType
    1218: iconst_3
    1219: anewarray     #175                // class java/lang/String
    1222: dup
    1223: iconst_0
    1224: ldc_w         #416                // String luck_of_the_sea
    1227: aastore
    1228: dup
    1229: iconst_1
    1230: ldc_w         #402                // String multiple_levels
    1233: aastore
    1234: dup
    1235: iconst_2
    1236: ldc_w         #418                // String Applies %s extra levels of Luck of the Sea when fishing
    1239: aastore
    1240: invokevirtual #204                // Method addAbilityTooltip:(Lnet/minecraft/core/component/DataComponentType;[Ljava/lang/String;)V
    1243: aload_0
    1244: getstatic     #398                // Field artifacts/registry/ModDataComponents.ENCHANTMENT_LEVEL_MODIFIERS:Ljava/util/function/Supplier;
    1247: invokeinterface #166,  1          // InterfaceMethod java/util/function/Supplier.get:()Ljava/lang/Object;
    1252: checkcast     #168                // class net/minecraft/core/component/DataComponentType
    1255: iconst_3
    1256: anewarray     #175                // class java/lang/String
    1259: dup
    1260: iconst_0
    1261: ldc_w         #416                // String luck_of_the_sea
    1264: aastore
    1265: dup
    1266: iconst_1
    1267: ldc_w         #406                // String single_level
    1270: aastore
    1271: dup
    1272: iconst_2
    1273: ldc_w         #420                // String Applies an extra Luck of the Sea when fishing
    1276: aastore
    1277: invokevirtual #204                // Method addAbilityTooltip:(Lnet/minecraft/core/component/DataComponentType;[Ljava/lang/String;)V
    1280: aload_0
    1281: getstatic     #398                // Field artifacts/registry/ModDataComponents.ENCHANTMENT_LEVEL_MODIFIERS:Ljava/util/function/Supplier;
    1284: invokeinterface #166,  1          // InterfaceMethod java/util/function/Supplier.get:()Ljava/lang/Object;
    1289: checkcast     #168                // class net/minecraft/core/component/DataComponentType
    1292: iconst_3
    1293: anewarray     #175                // class java/lang/String
    1296: dup
    1297: iconst_0
    1298: ldc_w         #422                // String lure
    1301: aastore
    1302: dup
    1303: iconst_1
    1304: ldc_w         #402                // String multiple_levels
    1307: aastore
    1308: dup
    1309: iconst_2
    1310: ldc_w         #424                // String Applies %s extra levels of Lure when fishing
    1313: aastore
    1314: invokevirtual #204                // Method addAbilityTooltip:(Lnet/minecraft/core/component/DataComponentType;[Ljava/lang/String;)V
    1317: aload_0
    1318: getstatic     #398                // Field artifacts/registry/ModDataComponents.ENCHANTMENT_LEVEL_MODIFIERS:Ljava/util/function/Supplier;
    1321: invokeinterface #166,  1          // InterfaceMethod java/util/function/Supplier.get:()Ljava/lang/Object;
    1326: checkcast     #168                // class net/minecraft/core/component/DataComponentType
    1329: iconst_3
    1330: anewarray     #175                // class java/lang/String
    1333: dup
    1334: iconst_0
    1335: ldc_w         #422                // String lure
    1338: aastore
    1339: dup
    1340: iconst_1
    1341: ldc_w         #406                // String single_level
    1344: aastore
    1345: dup
    1346: iconst_2
    1347: ldc_w         #426                // String Applies an extra level of Lure when fishing
    1350: aastore
    1351: invokevirtual #204                // Method addAbilityTooltip:(Lnet/minecraft/core/component/DataComponentType;[Ljava/lang/String;)V
    1354: aload_0
    1355: getstatic     #429                // Field artifacts/registry/ModDataComponents.MOB_EFFECTS:Ljava/util/function/Supplier;
    1358: invokeinterface #166,  1          // InterfaceMethod java/util/function/Supplier.get:()Ljava/lang/Object;
    1363: checkcast     #168                // class net/minecraft/core/component/DataComponentType
    1366: iconst_3
    1367: anewarray     #175                // class java/lang/String
    1370: dup
    1371: iconst_0
    1372: ldc_w         #431                // String water_breathing
    1375: aastore
    1376: dup
    1377: iconst_1
    1378: ldc_w         #433                // String infinite
    1381: aastore
    1382: dup
    1383: iconst_2
    1384: ldc_w         #435                // String Allows the wearer to breathe underwater
    1387: aastore
    1388: invokevirtual #204                // Method addAbilityTooltip:(Lnet/minecraft/core/component/DataComponentType;[Ljava/lang/String;)V
    1391: aload_0
    1392: getstatic     #429                // Field artifacts/registry/ModDataComponents.MOB_EFFECTS:Ljava/util/function/Supplier;
    1395: invokeinterface #166,  1          // InterfaceMethod java/util/function/Supplier.get:()Ljava/lang/Object;
    1400: checkcast     #168                // class net/minecraft/core/component/DataComponentType
    1403: iconst_3
    1404: anewarray     #175                // class java/lang/String
    1407: dup
    1408: iconst_0
    1409: ldc_w         #431                // String water_breathing
    1412: aastore
    1413: dup
    1414: iconst_1
    1415: ldc_w         #437                // String limited
    1418: aastore
    1419: dup
    1420: iconst_2
    1421: ldc_w         #439                // String Allows the wearer to breathe underwater for a limited amount of time
    1424: aastore
    1425: invokevirtual #204                // Method addAbilityTooltip:(Lnet/minecraft/core/component/DataComponentType;[Ljava/lang/String;)V
    1428: aload_0
    1429: getstatic     #429                // Field artifacts/registry/ModDataComponents.MOB_EFFECTS:Ljava/util/function/Supplier;
    1432: invokeinterface #166,  1          // InterfaceMethod java/util/function/Supplier.get:()Ljava/lang/Object;
    1437: checkcast     #168                // class net/minecraft/core/component/DataComponentType
    1440: iconst_2
    1441: anewarray     #175                // class java/lang/String
    1444: dup
    1445: iconst_0
    1446: ldc_w         #441                // String invisibility
    1449: aastore
    1450: dup
    1451: iconst_1
    1452: ldc_w         #443                // String Turns the wearer invisible
    1455: aastore
    1456: invokevirtual #204                // Method addAbilityTooltip:(Lnet/minecraft/core/component/DataComponentType;[Ljava/lang/String;)V
    1459: aload_0
    1460: getstatic     #429                // Field artifacts/registry/ModDataComponents.MOB_EFFECTS:Ljava/util/function/Supplier;
    1463: invokeinterface #166,  1          // InterfaceMethod java/util/function/Supplier.get:()Ljava/lang/Object;
    1468: checkcast     #168                // class net/minecraft/core/component/DataComponentType
    1471: iconst_2
    1472: anewarray     #175                // class java/lang/String
    1475: dup
    1476: iconst_0
    1477: ldc_w         #445                // String magnetism
    1480: aastore
    1481: dup
    1482: iconst_1
    1483: ldc_w         #447                // String Attracts nearby items
    1486: aastore
    1487: invokevirtual #204                // Method addAbilityTooltip:(Lnet/minecraft/core/component/DataComponentType;[Ljava/lang/String;)V
    1490: aload_0
    1491: getstatic     #429                // Field artifacts/registry/ModDataComponents.MOB_EFFECTS:Ljava/util/function/Supplier;
    1494: invokeinterface #166,  1          // InterfaceMethod java/util/function/Supplier.get:()Ljava/lang/Object;
    1499: checkcast     #168                // class net/minecraft/core/component/DataComponentType
    1502: iconst_3
    1503: anewarray     #175                // class java/lang/String
    1506: dup
    1507: iconst_0
    1508: ldc_w         #449                // String night_vision
    1511: aastore
    1512: dup
    1513: iconst_1
    1514: ldc_w         #451                // String full
    1517: aastore
    1518: dup
    1519: iconst_2
    1520: ldc_w         #453                // String Allows the wearer to see in the dark
    1523: aastore
    1524: invokevirtual #204                // Method addAbilityTooltip:(Lnet/minecraft/core/component/DataComponentType;[Ljava/lang/String;)V
    1527: aload_0
    1528: getstatic     #429                // Field artifacts/registry/ModDataComponents.MOB_EFFECTS:Ljava/util/function/Supplier;
    1531: invokeinterface #166,  1          // InterfaceMethod java/util/function/Supplier.get:()Ljava/lang/Object;
    1536: checkcast     #168                // class net/minecraft/core/component/DataComponentType
    1539: iconst_3
    1540: anewarray     #175                // class java/lang/String
    1543: dup
    1544: iconst_0
    1545: ldc_w         #449                // String night_vision
    1548: aastore
    1549: dup
    1550: iconst_1
    1551: ldc_w         #455                // String partial
    1554: aastore
    1555: dup
    1556: iconst_2
    1557: ldc_w         #457                // String Allows the wearer to see in the dark slightly
    1560: aastore
    1561: invokevirtual #204                // Method addAbilityTooltip:(Lnet/minecraft/core/component/DataComponentType;[Ljava/lang/String;)V
    1564: aload_0
    1565: getstatic     #460                // Field artifacts/registry/ModDataComponents.ENDER_PEARL_DAMAGE_IMMUNITY:Ljava/util/function/Supplier;
    1568: invokeinterface #166,  1          // InterfaceMethod java/util/function/Supplier.get:()Ljava/lang/Object;
    1573: checkcast     #168                // class net/minecraft/core/component/DataComponentType
    1576: iconst_1
    1577: anewarray     #175                // class java/lang/String
    1580: dup
    1581: iconst_0
    1582: ldc_w         #462                // String Ender Pearls deal no damage
    1585: aastore
    1586: invokevirtual #204                // Method addAbilityTooltip:(Lnet/minecraft/core/component/DataComponentType;[Ljava/lang/String;)V
    1589: aload_0
    1590: getstatic     #465                // Field artifacts/registry/ModDataComponents.CURE_EFFECTS:Ljava/util/function/Supplier;
    1593: invokeinterface #166,  1          // InterfaceMethod java/util/function/Supplier.get:()Ljava/lang/Object;
    1598: checkcast     #168                // class net/minecraft/core/component/DataComponentType
    1601: iconst_1
    1602: anewarray     #175                // class java/lang/String
    1605: dup
    1606: iconst_0
    1607: ldc_w         #467                // String Greatly reduces the duration of negative effects
    1610: aastore
    1611: invokevirtual #204                // Method addAbilityTooltip:(Lnet/minecraft/core/component/DataComponentType;[Ljava/lang/String;)V
    1614: aload_0
    1615: getstatic     #470                // Field artifacts/registry/ModDataComponents.REPLENISH_HUNGER_ON_GRASS:Ljava/util/function/Supplier;
    1618: invokeinterface #166,  1          // InterfaceMethod java/util/function/Supplier.get:()Ljava/lang/Object;
    1623: checkcast     #168                // class net/minecraft/core/component/DataComponentType
    1626: iconst_1
    1627: anewarray     #175                // class java/lang/String
    1630: dup
    1631: iconst_0
    1632: ldc_w         #472                // String Slowly replenishes hunger while walking on grass
    1635: aastore
    1636: invokevirtual #204                // Method addAbilityTooltip:(Lnet/minecraft/core/component/DataComponentType;[Ljava/lang/String;)V
    1639: aload_0
    1640: getstatic     #475                // Field artifacts/registry/ModDataComponents.CREEPER_REPELLENT:Ljava/util/function/Supplier;
    1643: invokeinterface #166,  1          // InterfaceMethod java/util/function/Supplier.get:()Ljava/lang/Object;
    1648: checkcast     #168                // class net/minecraft/core/component/DataComponentType
    1651: iconst_1
    1652: anewarray     #175                // class java/lang/String
    1655: dup
    1656: iconst_0
    1657: ldc_w         #477                // String Creepers avoid the wearer
    1660: aastore
    1661: invokevirtual #204                // Method addAbilityTooltip:(Lnet/minecraft/core/component/DataComponentType;[Ljava/lang/String;)V
    1664: aload_0
    1665: getstatic     #480                // Field artifacts/registry/ModDataComponents.PHANTOM_REPELLENT:Ljava/util/function/Supplier;
    1668: invokeinterface #166,  1          // InterfaceMethod java/util/function/Supplier.get:()Ljava/lang/Object;
    1673: checkcast     #168                // class net/minecraft/core/component/DataComponentType
    1676: iconst_1
    1677: anewarray     #175                // class java/lang/String
    1680: dup
    1681: iconst_0
    1682: ldc_w         #482                // String Hisses at attacking phantoms
    1685: aastore
    1686: invokevirtual #204                // Method addAbilityTooltip:(Lnet/minecraft/core/component/DataComponentType;[Ljava/lang/String;)V
    1689: aload_0
    1690: getstatic     #485                // Field artifacts/registry/ModDataComponents.RETALIATION_EFFECTS:Ljava/util/function/Supplier;
    1693: invokeinterface #166,  1          // InterfaceMethod java/util/function/Supplier.get:()Ljava/lang/Object;
    1698: checkcast     #168                // class net/minecraft/core/component/DataComponentType
    1701: iconst_3
    1702: anewarray     #175                // class java/lang/String
    1705: dup
    1706: iconst_0
    1707: ldc_w         #487                // String fire
    1710: aastore
    1711: dup
    1712: iconst_1
    1713: ldc_w         #489                // String fire_resistance
    1716: aastore
    1717: dup
    1718: iconst_2
    1719: ldc_w         #491                // String Grants fire resistance after lighting an attacker on fire
    1722: aastore
    1723: invokevirtual #204                // Method addAbilityTooltip:(Lnet/minecraft/core/component/DataComponentType;[Ljava/lang/String;)V
    1726: aload_0
    1727: getstatic     #485                // Field artifacts/registry/ModDataComponents.RETALIATION_EFFECTS:Ljava/util/function/Supplier;
    1730: invokeinterface #166,  1          // InterfaceMethod java/util/function/Supplier.get:()Ljava/lang/Object;
    1735: checkcast     #168                // class net/minecraft/core/component/DataComponentType
    1738: iconst_3
    1739: anewarray     #175                // class java/lang/String
    1742: dup
    1743: iconst_0
    1744: ldc_w         #487                // String fire
    1747: aastore
    1748: dup
    1749: iconst_1
    1750: ldc           #199                // String chance
    1752: aastore
    1753: dup
    1754: iconst_2
    1755: ldc_w         #493                // String Has a %s%% chance to light attackers on fire
    1758: aastore
    1759: invokevirtual #204                // Method addAbilityTooltip:(Lnet/minecraft/core/component/DataComponentType;[Ljava/lang/String;)V
    1762: aload_0
    1763: getstatic     #485                // Field artifacts/registry/ModDataComponents.RETALIATION_EFFECTS:Ljava/util/function/Supplier;
    1766: invokeinterface #166,  1          // InterfaceMethod java/util/function/Supplier.get:()Ljava/lang/Object;
    1771: checkcast     #168                // class net/minecraft/core/component/DataComponentType
    1774: iconst_3
    1775: anewarray     #175                // class java/lang/String
    1778: dup
    1779: iconst_0
    1780: ldc_w         #487                // String fire
    1783: aastore
    1784: dup
    1785: iconst_1
    1786: ldc           #206                // String constant
    1788: aastore
    1789: dup
    1790: iconst_2
    1791: ldc_w         #495                // String Attacking entities are lit on fire
    1794: aastore
    1795: invokevirtual #204                // Method addAbilityTooltip:(Lnet/minecraft/core/component/DataComponentType;[Ljava/lang/String;)V
    1798: aload_0
    1799: getstatic     #498                // Field artifacts/registry/ModDataComponents.SINKING:Ljava/util/function/Supplier;
    1802: invokeinterface #166,  1          // InterfaceMethod java/util/function/Supplier.get:()Ljava/lang/Object;
    1807: checkcast     #168                // class net/minecraft/core/component/DataComponentType
    1810: iconst_1
    1811: anewarray     #175                // class java/lang/String
    1814: dup
    1815: iconst_0
    1816: ldc_w         #500                // String Allows the wearer to move freely in water
    1819: aastore
    1820: invokevirtual #204                // Method addAbilityTooltip:(Lnet/minecraft/core/component/DataComponentType;[Ljava/lang/String;)V
    1823: aload_0
    1824: getstatic     #503                // Field artifacts/registry/ModDataComponents.AUTO_SMELT:Ljava/util/function/Supplier;
    1827: invokeinterface #166,  1          // InterfaceMethod java/util/function/Supplier.get:()Ljava/lang/Object;
    1832: checkcast     #168                // class net/minecraft/core/component/DataComponentType
    1835: iconst_1
    1836: anewarray     #175                // class java/lang/String
    1839: dup
    1840: iconst_0
    1841: ldc_w         #505                // String Automatically smelts mined ores
    1844: aastore
    1845: invokevirtual #204                // Method addAbilityTooltip:(Lnet/minecraft/core/component/DataComponentType;[Ljava/lang/String;)V
    1848: aload_0
    1849: getstatic     #508                // Field artifacts/registry/ModDataComponents.FLUID_COLLISION:Ljava/util/function/Supplier;
    1852: invokeinterface #166,  1          // InterfaceMethod java/util/function/Supplier.get:()Ljava/lang/Object;
    1857: checkcast     #168                // class net/minecraft/core/component/DataComponentType
    1860: iconst_3
    1861: anewarray     #175                // class java/lang/String
    1864: dup
    1865: iconst_0
    1866: ldc_w         #510                // String sneaking
    1869: aastore
    1870: dup
    1871: iconst_1
    1872: ldc_w         #512                // String lava
    1875: aastore
    1876: dup
    1877: iconst_2
    1878: ldc_w         #514                // String Allows the wearer to stand on lava while sneaking
    1881: aastore
    1882: invokevirtual #204                // Method addAbilityTooltip:(Lnet/minecraft/core/component/DataComponentType;[Ljava/lang/String;)V
    1885: aload_0
    1886: getstatic     #508                // Field artifacts/registry/ModDataComponents.FLUID_COLLISION:Ljava/util/function/Supplier;
    1889: invokeinterface #166,  1          // InterfaceMethod java/util/function/Supplier.get:()Ljava/lang/Object;
    1894: checkcast     #168                // class net/minecraft/core/component/DataComponentType
    1897: iconst_2
    1898: anewarray     #175                // class java/lang/String
    1901: dup
    1902: iconst_0
    1903: ldc_w         #516                // String sprinting
    1906: aastore
    1907: dup
    1908: iconst_1
    1909: ldc_w         #518                // String Allows the wearer to walk on fluids while sprinting
    1912: aastore
    1913: invokevirtual #204                // Method addAbilityTooltip:(Lnet/minecraft/core/component/DataComponentType;[Ljava/lang/String;)V
    1916: aload_0
    1917: getstatic     #485                // Field artifacts/registry/ModDataComponents.RETALIATION_EFFECTS:Ljava/util/function/Supplier;
    1920: invokeinterface #166,  1          // InterfaceMethod java/util/function/Supplier.get:()Ljava/lang/Object;
    1925: checkcast     #168                // class net/minecraft/core/component/DataComponentType
    1928: iconst_3
    1929: anewarray     #175                // class java/lang/String
    1932: dup
    1933: iconst_0
    1934: ldc_w         #520                // String lightning
    1937: aastore
    1938: dup
    1939: iconst_1
    1940: ldc           #199                // String chance
    1942: aastore
    1943: dup
    1944: iconst_2
    1945: ldc_w         #522                // String Has a %s%% chance to strike attackers with lightning
    1948: aastore
    1949: invokevirtual #204                // Method addAbilityTooltip:(Lnet/minecraft/core/component/DataComponentType;[Ljava/lang/String;)V
    1952: aload_0
    1953: getstatic     #485                // Field artifacts/registry/ModDataComponents.RETALIATION_EFFECTS:Ljava/util/function/Supplier;
    1956: invokeinterface #166,  1          // InterfaceMethod java/util/function/Supplier.get:()Ljava/lang/Object;
    1961: checkcast     #168                // class net/minecraft/core/component/DataComponentType
    1964: iconst_3
    1965: anewarray     #175                // class java/lang/String
    1968: dup
    1969: iconst_0
    1970: ldc_w         #520                // String lightning
    1973: aastore
    1974: dup
    1975: iconst_1
    1976: ldc           #206                // String constant
    1978: aastore
    1979: dup
    1980: iconst_2
    1981: ldc_w         #524                // String Attacking entities are struck by lightning
    1984: aastore
    1985: invokevirtual #204                // Method addAbilityTooltip:(Lnet/minecraft/core/component/DataComponentType;[Ljava/lang/String;)V
    1988: aload_0
    1989: getstatic     #527                // Field artifacts/registry/ModDataComponents.SWIM_IN_AIR:Ljava/util/function/Supplier;
    1992: invokeinterface #166,  1          // InterfaceMethod java/util/function/Supplier.get:()Ljava/lang/Object;
    1997: checkcast     #168                // class net/minecraft/core/component/DataComponentType
    2000: iconst_2
    2001: anewarray     #175                // class java/lang/String
    2004: dup
    2005: iconst_0
    2006: ldc_w         #529                // String keymapping
    2009: aastore
    2010: dup
    2011: iconst_1
    2012: ldc_w         #531                // String Press %s while in the air to start swimming
    2015: aastore
    2016: invokevirtual #204                // Method addAbilityTooltip:(Lnet/minecraft/core/component/DataComponentType;[Ljava/lang/String;)V
    2019: aload_0
    2020: getstatic     #527                // Field artifacts/registry/ModDataComponents.SWIM_IN_AIR:Ljava/util/function/Supplier;
    2023: invokeinterface #166,  1          // InterfaceMethod java/util/function/Supplier.get:()Ljava/lang/Object;
    2028: checkcast     #168                // class net/minecraft/core/component/DataComponentType
    2031: iconst_2
    2032: anewarray     #175                // class java/lang/String
    2035: dup
    2036: iconst_0
    2037: ldc_w         #533                // String swimming
    2040: aastore
    2041: dup
    2042: iconst_1
    2043: ldc_w         #535                // String Allows the wearer to swim in the air for a limited period of time
    2046: aastore
    2047: invokevirtual #204                // Method addAbilityTooltip:(Lnet/minecraft/core/component/DataComponentType;[Ljava/lang/String;)V
    2050: aload_0
    2051: getstatic     #538                // Field artifacts/registry/ModDataComponents.DEATH_PROTECTION_TELEPORT:Ljava/util/function/Supplier;
    2054: invokeinterface #166,  1          // InterfaceMethod java/util/function/Supplier.get:()Ljava/lang/Object;
    2059: checkcast     #168                // class net/minecraft/core/component/DataComponentType
    2062: iconst_2
    2063: anewarray     #175                // class java/lang/String
    2066: dup
    2067: iconst_0
    2068: ldc           #199                // String chance
    2070: aastore
    2071: dup
    2072: iconst_1
    2073: ldc_w         #540                // String A fatal hit has a %s%% chance to teleport you somewhere else instead
    2076: aastore
    2077: invokevirtual #204                // Method addAbilityTooltip:(Lnet/minecraft/core/component/DataComponentType;[Ljava/lang/String;)V
    2080: aload_0
    2081: getstatic     #538                // Field artifacts/registry/ModDataComponents.DEATH_PROTECTION_TELEPORT:Ljava/util/function/Supplier;
    2084: invokeinterface #166,  1          // InterfaceMethod java/util/function/Supplier.get:()Ljava/lang/Object;
    2089: checkcast     #168                // class net/minecraft/core/component/DataComponentType
    2092: iconst_2
    2093: anewarray     #175                // class java/lang/String
    2096: dup
    2097: iconst_0
    2098: ldc           #206                // String constant
    2100: aastore
    2101: dup
    2102: iconst_1
    2103: ldc_w         #542                // String A fatal hit teleports you somewhere else instead
    2106: aastore
    2107: invokevirtual #204                // Method addAbilityTooltip:(Lnet/minecraft/core/component/DataComponentType;[Ljava/lang/String;)V
    2110: aload_0
    2111: getstatic     #538                // Field artifacts/registry/ModDataComponents.DEATH_PROTECTION_TELEPORT:Ljava/util/function/Supplier;
    2114: invokeinterface #166,  1          // InterfaceMethod java/util/function/Supplier.get:()Ljava/lang/Object;
    2119: checkcast     #168                // class net/minecraft/core/component/DataComponentType
    2122: iconst_2
    2123: anewarray     #175                // class java/lang/String
    2126: dup
    2127: iconst_0
    2128: ldc_w         #544                // String not_consumed
    2131: aastore
    2132: dup
    2133: iconst_1
    2134: ldc_w         #546                // String Not consumed on use
    2137: aastore
    2138: invokevirtual #204                // Method addAbilityTooltip:(Lnet/minecraft/core/component/DataComponentType;[Ljava/lang/String;)V
    2141: aload_0
    2142: getstatic     #485                // Field artifacts/registry/ModDataComponents.RETALIATION_EFFECTS:Ljava/util/function/Supplier;
    2145: invokeinterface #166,  1          // InterfaceMethod java/util/function/Supplier.get:()Ljava/lang/Object;
    2150: checkcast     #168                // class net/minecraft/core/component/DataComponentType
    2153: iconst_3
    2154: anewarray     #175                // class java/lang/String
    2157: dup
    2158: iconst_0
    2159: ldc_w         #548                // String thorns
    2162: aastore
    2163: dup
    2164: iconst_1
    2165: ldc           #199                // String chance
    2167: aastore
    2168: dup
    2169: iconst_2
    2170: ldc_w         #550                // String Has a %s%% chance to damage attackers
    2173: aastore
    2174: invokevirtual #204                // Method addAbilityTooltip:(Lnet/minecraft/core/component/DataComponentType;[Ljava/lang/String;)V
    2177: aload_0
    2178: getstatic     #485                // Field artifacts/registry/ModDataComponents.RETALIATION_EFFECTS:Ljava/util/function/Supplier;
    2181: invokeinterface #166,  1          // InterfaceMethod java/util/function/Supplier.get:()Ljava/lang/Object;
    2186: checkcast     #168                // class net/minecraft/core/component/DataComponentType
    2189: iconst_3
    2190: anewarray     #175                // class java/lang/String
    2193: dup
    2194: iconst_0
    2195: ldc_w         #548                // String thorns
    2198: aastore
    2199: dup
    2200: iconst_1
    2201: ldc           #206                // String constant
    2203: aastore
    2204: dup
    2205: iconst_2
    2206: ldc_w         #552                // String Attacking entities are damaged as well
    2209: aastore
    2210: invokevirtual #204                // Method addAbilityTooltip:(Lnet/minecraft/core/component/DataComponentType;[Ljava/lang/String;)V
    2213: aload_0
    2214: getstatic     #555                // Field artifacts/registry/ModDataComponents.TOOL_TIER_UPGRADE:Ljava/util/function/Supplier;
    2217: invokeinterface #166,  1          // InterfaceMethod java/util/function/Supplier.get:()Ljava/lang/Object;
    2222: checkcast     #168                // class net/minecraft/core/component/DataComponentType
    2225: iconst_1
    2226: anewarray     #175                // class java/lang/String
    2229: dup
    2230: iconst_0
    2231: ldc_w         #557                // String Increases the wearer\'s base mining level to %s
    2234: aastore
    2235: invokevirtual #204                // Method addAbilityTooltip:(Lnet/minecraft/core/component/DataComponentType;[Ljava/lang/String;)V
    2238: aload_0
    2239: getstatic     #560                // Field artifacts/registry/ModDataComponents.WALK_ON_POWDER_SNOW:Ljava/util/function/Supplier;
    2242: invokeinterface #166,  1          // InterfaceMethod java/util/function/Supplier.get:()Ljava/lang/Object;
    2247: checkcast     #168                // class net/minecraft/core/component/DataComponentType
    2250: iconst_1
    2251: anewarray     #175                // class java/lang/String
    2254: dup
    2255: iconst_0
    2256: ldc_w         #562                // String Allows the wearer to walk on Powder Snow
    2259: aastore
    2260: invokevirtual #204                // Method addAbilityTooltip:(Lnet/minecraft/core/component/DataComponentType;[Ljava/lang/String;)V
    2263: return

  private void addAttributes();
    descriptor: ()V
    Code:
       0: getstatic     #566                // Field artifacts/registry/ModAttributes.ATTRIBUTES:Lartifacts/registry/Register;
       3: invokevirtual #572                // Method artifacts/registry/Register.getEntries:()Ljava/util/Collection;
       6: invokeinterface #578,  1          // InterfaceMethod java/util/Collection.iterator:()Ljava/util/Iterator;
      11: astore_1
      12: aload_1
      13: invokeinterface #584,  1          // InterfaceMethod java/util/Iterator.hasNext:()Z
      18: ifeq          75
      21: aload_1
      22: invokeinterface #587,  1          // InterfaceMethod java/util/Iterator.next:()Ljava/lang/Object;
      27: checkcast     #589                // class artifacts/registry/RegistryHolder
      30: astore_2
      31: aload_0
      32: aload_2
      33: invokevirtual #590                // Method artifacts/registry/RegistryHolder.get:()Ljava/lang/Object;
      36: checkcast     #592                // class net/minecraft/world/entity/ai/attributes/Attribute
      39: invokevirtual #595                // Method net/minecraft/world/entity/ai/attributes/Attribute.getDescriptionId:()Ljava/lang/String;
      42: aload_2
      43: invokevirtual #599                // Method artifacts/registry/RegistryHolder.unwrapKey:()Ljava/util/Optional;
      46: invokevirtual #604                // Method java/util/Optional.orElseThrow:()Ljava/lang/Object;
      49: checkcast     #606                // class net/minecraft/resources/ResourceKey
      52: invokevirtual #607                // Method net/minecraft/resources/ResourceKey.location:()Lnet/minecraft/resources/ResourceLocation;
      55: invokevirtual #365                // Method net/minecraft/resources/ResourceLocation.getPath:()Ljava/lang/String;
      58: ldc_w         #609                // String \\.
      61: invokevirtual #613                // Method java/lang/String.split:(Ljava/lang/String;)[Ljava/lang/String;
      64: iconst_1
      65: aaload
      66: invokestatic  #617                // Method fromSnakeCasedString:(Ljava/lang/String;)Ljava/lang/String;
      69: invokevirtual #105                // Method add:(Ljava/lang/String;Ljava/lang/String;)V
      72: goto          12
      75: aload_0
      76: ldc_w         #322                // String generic.swim_speed
      79: ldc_w         #619                // String Swim Speed
      82: invokevirtual #105                // Method add:(Ljava/lang/String;Ljava/lang/String;)V
      85: return

  private void addEntities();
    descriptor: ()V
    Code:
       0: getstatic     #627                // Field artifacts/registry/ModEntityTypes.ENTITY_TYPES:Lartifacts/registry/Register;
       3: invokevirtual #572                // Method artifacts/registry/Register.getEntries:()Ljava/util/Collection;
       6: invokeinterface #578,  1          // InterfaceMethod java/util/Collection.iterator:()Ljava/util/Iterator;
      11: astore_1
      12: aload_1
      13: invokeinterface #584,  1          // InterfaceMethod java/util/Iterator.hasNext:()Z
      18: ifeq          67
      21: aload_1
      22: invokeinterface #587,  1          // InterfaceMethod java/util/Iterator.next:()Ljava/lang/Object;
      27: checkcast     #589                // class artifacts/registry/RegistryHolder
      30: astore_2
      31: aload_0
      32: aload_2
      33: invokevirtual #590                // Method artifacts/registry/RegistryHolder.get:()Ljava/lang/Object;
      36: checkcast     #629                // class net/minecraft/world/entity/EntityType
      39: invokevirtual #630                // Method net/minecraft/world/entity/EntityType.getDescriptionId:()Ljava/lang/String;
      42: aload_2
      43: invokevirtual #599                // Method artifacts/registry/RegistryHolder.unwrapKey:()Ljava/util/Optional;
      46: invokevirtual #604                // Method java/util/Optional.orElseThrow:()Ljava/lang/Object;
      49: checkcast     #606                // class net/minecraft/resources/ResourceKey
      52: invokevirtual #607                // Method net/minecraft/resources/ResourceKey.location:()Lnet/minecraft/resources/ResourceLocation;
      55: invokevirtual #365                // Method net/minecraft/resources/ResourceLocation.getPath:()Ljava/lang/String;
      58: invokestatic  #617                // Method fromSnakeCasedString:(Ljava/lang/String;)Ljava/lang/String;
      61: invokevirtual #105                // Method add:(Ljava/lang/String;Ljava/lang/String;)V
      64: goto          12
      67: aload_0
      68: getstatic     #633                // Field artifacts/registry/ModSoundEvents.MIMIC_CLOSE:Lnet/minecraft/core/Holder;
      71: invokeinterface #140,  1          // InterfaceMethod net/minecraft/core/Holder.value:()Ljava/lang/Object;
      76: checkcast     #142                // class net/minecraft/sounds/SoundEvent
      79: ldc_w         #635                // String Mimic closes
      82: invokevirtual #147                // Method add:(Lnet/minecraft/sounds/SoundEvent;Ljava/lang/String;)V
      85: aload_0
      86: getstatic     #638                // Field artifacts/registry/ModSoundEvents.MIMIC_DEATH:Lnet/minecraft/core/Holder;
      89: invokeinterface #140,  1          // InterfaceMethod net/minecraft/core/Holder.value:()Ljava/lang/Object;
      94: checkcast     #142                // class net/minecraft/sounds/SoundEvent
      97: ldc_w         #640                // String Mimic dies
     100: invokevirtual #147                // Method add:(Lnet/minecraft/sounds/SoundEvent;Ljava/lang/String;)V
     103: aload_0
     104: getstatic     #643                // Field artifacts/registry/ModSoundEvents.MIMIC_HURT:Lnet/minecraft/core/Holder;
     107: invokeinterface #140,  1          // InterfaceMethod net/minecraft/core/Holder.value:()Ljava/lang/Object;
     112: checkcast     #142                // class net/minecraft/sounds/SoundEvent
     115: ldc_w         #645                // String Mimic hurts
     118: invokevirtual #147                // Method add:(Lnet/minecraft/sounds/SoundEvent;Ljava/lang/String;)V
     121: aload_0
     122: getstatic     #648                // Field artifacts/registry/ModSoundEvents.MIMIC_OPEN:Lnet/minecraft/core/Holder;
     125: invokeinterface #140,  1          // InterfaceMethod net/minecraft/core/Holder.value:()Ljava/lang/Object;
     130: checkcast     #142                // class net/minecraft/sounds/SoundEvent
     133: ldc_w         #650                // String Mimic hops
     136: invokevirtual #147                // Method add:(Lnet/minecraft/sounds/SoundEvent;Ljava/lang/String;)V
     139: return

  private void addConfigs();
    descriptor: ()V
    Code:
       0: aload_0
       1: iconst_0
       2: anewarray     #175                // class java/lang/String
       5: invokestatic  #656                // Method configTitle:([Ljava/lang/String;)Ljava/lang/String;
       8: ldc_w         #658                // String Artifacts Config
      11: invokevirtual #105                // Method add:(Ljava/lang/String;Ljava/lang/String;)V
      14: aload_0
      15: ldc_w         #660                // String artifacts.config.enabled.title
      18: ldc_w         #662                // String Enabled
      21: invokevirtual #105                // Method add:(Ljava/lang/String;Ljava/lang/String;)V
      24: aload_0
      25: ldc_w         #664                // String artifacts.config.cooldown.title
      28: ldc_w         #666                // String Cooldown
      31: invokevirtual #105                // Method add:(Ljava/lang/String;Ljava/lang/String;)V
      34: aload_0
      35: ldc_w         #668                // String artifacts.config.generateAsLoot.title
      38: ldc_w         #670                // String Generate as loot
      41: invokevirtual #105                // Method add:(Ljava/lang/String;Ljava/lang/String;)V
      44: aload_0
      45: ldc_w         #672                // String artifacts.config.generateAsLoot.description
      48: ldc_w         #674                // String Whether this item can be found in structures or drop from entities
      51: invokevirtual #105                // Method add:(Ljava/lang/String;Ljava/lang/String;)V
      54: getstatic     #36                 // Field artifacts/Artifacts.CONFIG:Lartifacts/config/ModConfig;
      57: getfield      #678                // Field artifacts/config/ModConfig.configs:Ljava/util/List;
      60: invokeinterface #681,  1          // InterfaceMethod java/util/List.iterator:()Ljava/util/Iterator;
      65: astore_1
      66: aload_1
      67: invokeinterface #584,  1          // InterfaceMethod java/util/Iterator.hasNext:()Z
      72: ifeq          123
      75: aload_1
      76: invokeinterface #587,  1          // InterfaceMethod java/util/Iterator.next:()Ljava/lang/Object;
      81: checkcast     #683                // class artifacts/config/ConfigManager
      84: astore_2
      85: aload_0
      86: iconst_1
      87: anewarray     #175                // class java/lang/String
      90: dup
      91: iconst_0
      92: aload_2
      93: invokevirtual #686                // Method artifacts/config/ConfigManager.getName:()Ljava/lang/String;
      96: aastore
      97: invokestatic  #656                // Method configTitle:([Ljava/lang/String;)Ljava/lang/String;
     100: aload_2
     101: invokevirtual #686                // Method artifacts/config/ConfigManager.getName:()Ljava/lang/String;
     104: invokestatic  #689                // Method fromCamelCasedString:(Ljava/lang/String;)Ljava/lang/String;
     107: invokevirtual #105                // Method add:(Ljava/lang/String;Ljava/lang/String;)V
     110: aload_0
     111: aload_2
     112: invokevirtual #693                // Method addConfigNames:(Lartifacts/config/ConfigManager;)V
     115: aload_0
     116: aload_2
     117: invokevirtual #696                // Method addConfigTooltips:(Lartifacts/config/ConfigManager;)V
     120: goto          66
     123: return

  private void addConfigNames(artifacts.config.ConfigManager);
    descriptor: (Lartifacts/config/ConfigManager;)V
    Code:
       0: aload_1
       1: invokevirtual #702                // Method artifacts/config/ConfigManager.getValues:()Ljava/util/Map;
       4: aload_0
       5: aload_1
       6: invokedynamic #712,  0            // InvokeDynamic #2:accept:(Lartifacts/neoforge/data/Language;Lartifacts/config/ConfigManager;)Ljava/util/function/BiConsumer;
      11: invokeinterface #99,  2           // InterfaceMethod java/util/Map.forEach:(Ljava/util/function/BiConsumer;)V
      16: return

  private void addConfigTooltips(artifacts.config.ConfigManager);
    descriptor: (Lartifacts/config/ConfigManager;)V
    Code:
       0: aload_1
       1: invokevirtual #702                // Method artifacts/config/ConfigManager.getValues:()Ljava/util/Map;
       4: aload_0
       5: aload_1
       6: invokedynamic #717,  0            // InvokeDynamic #3:accept:(Lartifacts/neoforge/data/Language;Lartifacts/config/ConfigManager;)Ljava/util/function/BiConsumer;
      11: invokeinterface #99,  2           // InterfaceMethod java/util/Map.forEach:(Ljava/util/function/BiConsumer;)V
      16: return

  private void addItems();
    descriptor: ()V
    Code:
       0: getstatic     #722                // Field artifacts/registry/ModItems.ITEMS:Lartifacts/registry/Register;
       3: invokevirtual #572                // Method artifacts/registry/Register.getEntries:()Ljava/util/Collection;
       6: invokeinterface #578,  1          // InterfaceMethod java/util/Collection.iterator:()Ljava/util/Iterator;
      11: astore_1
      12: aload_1
      13: invokeinterface #584,  1          // InterfaceMethod java/util/Iterator.hasNext:()Z
      18: ifeq          68
      21: aload_1
      22: invokeinterface #587,  1          // InterfaceMethod java/util/Iterator.next:()Ljava/lang/Object;
      27: checkcast     #137                // class net/minecraft/core/Holder
      30: astore_2
      31: aload_0
      32: aload_2
      33: invokeinterface #140,  1          // InterfaceMethod net/minecraft/core/Holder.value:()Ljava/lang/Object;
      38: checkcast     #724                // class net/minecraft/world/item/Item
      41: aload_2
      42: invokeinterface #725,  1          // InterfaceMethod net/minecraft/core/Holder.unwrapKey:()Ljava/util/Optional;
      47: invokevirtual #604                // Method java/util/Optional.orElseThrow:()Ljava/lang/Object;
      50: checkcast     #606                // class net/minecraft/resources/ResourceKey
      53: invokevirtual #607                // Method net/minecraft/resources/ResourceKey.location:()Lnet/minecraft/resources/ResourceLocation;
      56: invokevirtual #365                // Method net/minecraft/resources/ResourceLocation.getPath:()Ljava/lang/String;
      59: invokestatic  #617                // Method fromSnakeCasedString:(Ljava/lang/String;)Ljava/lang/String;
      62: invokevirtual #728                // Method add:(Lnet/minecraft/world/item/Item;Ljava/lang/String;)V
      65: goto          12
      68: aload_0
      69: getstatic     #731                // Field artifacts/registry/ModItems.ANGLERS_HAT:Lnet/minecraft/core/Holder;
      72: invokeinterface #140,  1          // InterfaceMethod net/minecraft/core/Holder.value:()Ljava/lang/Object;
      77: checkcast     #724                // class net/minecraft/world/item/Item
      80: invokevirtual #732                // Method net/minecraft/world/item/Item.getDescriptionId:()Ljava/lang/String;
      83: ldc_w         #734                // String Angler\'s Hat
      86: invokevirtual #736                // Method override:(Ljava/lang/String;Ljava/lang/String;)V
      89: aload_0
      90: getstatic     #739                // Field artifacts/registry/ModItems.AQUA_DASHERS:Lnet/minecraft/core/Holder;
      93: invokeinterface #140,  1          // InterfaceMethod net/minecraft/core/Holder.value:()Ljava/lang/Object;
      98: checkcast     #724                // class net/minecraft/world/item/Item
     101: invokevirtual #732                // Method net/minecraft/world/item/Item.getDescriptionId:()Ljava/lang/String;
     104: ldc_w         #741                // String Aqua-Dashers
     107: invokevirtual #736                // Method override:(Ljava/lang/String;Ljava/lang/String;)V
     110: return

  private void addTags();
    descriptor: ()V
    Code:
       0: aload_0
       1: getstatic     #748                // Field artifacts/neoforge/data/tags/ItemTags.ARTIFACTS:Lnet/minecraft/tags/TagKey;
       4: ldc           #110                // String Artifacts
       6: invokevirtual #751                // Method add:(Lnet/minecraft/tags/TagKey;Ljava/lang/String;)V
       9: aload_0
      10: getstatic     #754                // Field artifacts/neoforge/data/tags/ItemTags.ALL:Lnet/minecraft/tags/TagKey;
      13: ldc_w         #756                // String Any Slot Equipable Artifacts
      16: invokevirtual #751                // Method add:(Lnet/minecraft/tags/TagKey;Ljava/lang/String;)V
      19: aload_0
      20: getstatic     #759                // Field artifacts/neoforge/data/tags/ItemTags.BELT:Lnet/minecraft/tags/TagKey;
      23: ldc_w         #761                // String Belt Slot Equipable Artifacts
      26: invokevirtual #751                // Method add:(Lnet/minecraft/tags/TagKey;Ljava/lang/String;)V
      29: aload_0
      30: getstatic     #764                // Field artifacts/neoforge/data/tags/ItemTags.FACE:Lnet/minecraft/tags/TagKey;
      33: ldc_w         #766                // String Face Slot Equipable Artifacts
      36: invokevirtual #751                // Method add:(Lnet/minecraft/tags/TagKey;Ljava/lang/String;)V
      39: aload_0
      40: getstatic     #769                // Field artifacts/neoforge/data/tags/ItemTags.FEET:Lnet/minecraft/tags/TagKey;
      43: ldc_w         #771                // String Feet Slot Equipable Artifacts
      46: invokevirtual #751                // Method add:(Lnet/minecraft/tags/TagKey;Ljava/lang/String;)V
      49: aload_0
      50: getstatic     #774                // Field artifacts/neoforge/data/tags/ItemTags.HANDS:Lnet/minecraft/tags/TagKey;
      53: ldc_w         #776                // String Hands Slot Equipable Artifacts
      56: invokevirtual #751                // Method add:(Lnet/minecraft/tags/TagKey;Ljava/lang/String;)V
      59: aload_0
      60: getstatic     #779                // Field artifacts/neoforge/data/tags/ItemTags.HEAD:Lnet/minecraft/tags/TagKey;
      63: ldc_w         #781                // String Head Slot Equipable Artifacts
      66: invokevirtual #751                // Method add:(Lnet/minecraft/tags/TagKey;Ljava/lang/String;)V
      69: aload_0
      70: getstatic     #784                // Field artifacts/neoforge/data/tags/ItemTags.NECKLACE:Lnet/minecraft/tags/TagKey;
      73: ldc_w         #786                // String Necklace Slot Equipable Artifacts
      76: invokevirtual #751                // Method add:(Lnet/minecraft/tags/TagKey;Ljava/lang/String;)V
      79: aload_0
      80: getstatic     #789                // Field artifacts/registry/ModTags.ANTIDOTE_VESSEL_CANCELLABLE:Lnet/minecraft/tags/TagKey;
      83: ldc_w         #791                // String Antidote Vessel Cancellable
      86: invokevirtual #751                // Method add:(Lnet/minecraft/tags/TagKey;Ljava/lang/String;)V
      89: aload_0
      90: getstatic     #794                // Field artifacts/registry/ModTags.CAMPSITE_CHESTS:Lnet/minecraft/tags/TagKey;
      93: ldc_w         #796                // String Campsite Chests
      96: invokevirtual #751                // Method add:(Lnet/minecraft/tags/TagKey;Ljava/lang/String;)V
      99: aload_0
     100: getstatic     #799                // Field artifacts/registry/ModTags.CREEPERS:Lnet/minecraft/tags/TagKey;
     103: ldc_w         #801                // String Creepers
     106: invokevirtual #751                // Method add:(Lnet/minecraft/tags/TagKey;Ljava/lang/String;)V
     109: aload_0
     110: getstatic     #804                // Field artifacts/registry/ModTags.MINEABLE_WITH_DIGGING_CLAWS:Lnet/minecraft/tags/TagKey;
     113: ldc_w         #806                // String Mineable With Digging Claws
     116: invokevirtual #751                // Method add:(Lnet/minecraft/tags/TagKey;Ljava/lang/String;)V
     119: aload_0
     120: getstatic     #809                // Field artifacts/registry/ModTags.ROOTED_BOOTS_GRASS:Lnet/minecraft/tags/TagKey;
     123: ldc_w         #811                // String Rooted Boots Grass
     126: invokevirtual #751                // Method add:(Lnet/minecraft/tags/TagKey;Ljava/lang/String;)V
     129: aload_0
     130: getstatic     #814                // Field artifacts/registry/ModTags.SNOW_LAYERS:Lnet/minecraft/tags/TagKey;
     133: ldc_w         #816                // String Snow Layers
     136: invokevirtual #751                // Method add:(Lnet/minecraft/tags/TagKey;Ljava/lang/String;)V
     139: return

  private void addTooltips();
    descriptor: ()V
    Code:
       0: aload_0
       1: ldc_w         #818                // String attacks_inflict
       4: ldc_w         #820                // String Attacks inflict:
       7: invokevirtual #823                // Method tooltip:(Ljava/lang/String;Ljava/lang/String;)V
      10: aload_0
      11: ldc_w         #825                // String cooldown
      14: ldc_w         #827                // String +Cooldown (%s)
      17: invokevirtual #823                // Method tooltip:(Ljava/lang/String;Ljava/lang/String;)V
      20: aload_0
      21: ldc_w         #829                // String cosmetic
      24: ldc_w         #831                // String Cosmetic
      27: invokevirtual #823                // Method tooltip:(Ljava/lang/String;Ljava/lang/String;)V
      30: aload_0
      31: ldc_w         #833                // String cosmetics_disabled
      34: ldc_w         #835                // String Cosmetics disabled (right-click to toggle)
      37: invokevirtual #823                // Method tooltip:(Ljava/lang/String;Ljava/lang/String;)V
      40: aload_0
      41: ldc_w         #837                // String cosmetics_enabled
      44: ldc_w         #839                // String Cosmetics enabled (right-click to toggle)
      47: invokevirtual #823                // Method tooltip:(Ljava/lang/String;Ljava/lang/String;)V
      50: aload_0
      51: ldc_w         #841                // String item.everlasting_food
      54: ldc_w         #843                // String Not consumed when eaten
      57: invokevirtual #823                // Method tooltip:(Ljava/lang/String;Ljava/lang/String;)V
      60: aload_0
      61: ldc_w         #845                // String item.novelty_drinking_hat
      64: ldc_w         #847                // String \'Hey! I\'m #1, and I let gravity do my drinking!\'
      67: invokevirtual #823                // Method tooltip:(Ljava/lang/String;Ljava/lang/String;)V
      70: aload_0
      71: ldc_w         #849                // String item.umbrella.glider
      74: ldc_w         #851                // String Slows your fall when held
      77: invokevirtual #823                // Method tooltip:(Ljava/lang/String;Ljava/lang/String;)V
      80: aload_0
      81: ldc_w         #853                // String item.umbrella.shield
      84: ldc_w         #855                // String Can be used as a shield
      87: invokevirtual #823                // Method tooltip:(Ljava/lang/String;Ljava/lang/String;)V
      90: aload_0
      91: ldc_w         #857                // String missing_dependency
      94: ldc_w         #859                // String Install Curios, Trinkets or Accessories to use this item
      97: invokevirtual #823                // Method tooltip:(Ljava/lang/String;Ljava/lang/String;)V
     100: aload_0
     101: ldc_w         #861                // String per_food_point_restored
     104: ldc_w         #863                // String For every food point restored:
     107: invokevirtual #823                // Method tooltip:(Ljava/lang/String;Ljava/lang/String;)V
     110: aload_0
     111: ldc_w         #865                // String plus_mob_effect
     114: ldc_w         #867                // String +%s
     117: invokevirtual #823                // Method tooltip:(Ljava/lang/String;Ljava/lang/String;)V
     120: aload_0
     121: ldc_w         #869                // String plus_mob_effect_chance
     124: ldc_w         #871                // String +%s (%s%%)
     127: invokevirtual #823                // Method tooltip:(Ljava/lang/String;Ljava/lang/String;)V
     130: aload_0
     131: ldc_w         #873                // String toggle_keymapping
     134: ldc_w         #875                // String Press %s to toggle
     137: invokevirtual #823                // Method tooltip:(Ljava/lang/String;Ljava/lang/String;)V
     140: aload_0
     141: ldc_w         #877                // String tool_tier.none
     144: ldc_w         #879                // String none
     147: invokevirtual #823                // Method tooltip:(Ljava/lang/String;Ljava/lang/String;)V
     150: aload_0
     151: ldc_w         #881                // String tool_tier.wood
     154: ldc_w         #883                // String wood
     157: invokevirtual #823                // Method tooltip:(Ljava/lang/String;Ljava/lang/String;)V
     160: aload_0
     161: ldc_w         #885                // String tool_tier.stone
     164: ldc_w         #887                // String stone
     167: invokevirtual #823                // Method tooltip:(Ljava/lang/String;Ljava/lang/String;)V
     170: aload_0
     171: ldc_w         #889                // String tool_tier.iron
     174: ldc_w         #891                // String iron
     177: invokevirtual #823                // Method tooltip:(Ljava/lang/String;Ljava/lang/String;)V
     180: aload_0
     181: ldc_w         #893                // String tool_tier.diamond
     184: ldc_w         #895                // String diamond
     187: invokevirtual #823                // Method tooltip:(Ljava/lang/String;Ljava/lang/String;)V
     190: aload_0
     191: ldc_w         #897                // String tool_tier.netherite
     194: ldc_w         #899                // String netherite
     197: invokevirtual #823                // Method tooltip:(Ljava/lang/String;Ljava/lang/String;)V
     200: aload_0
     201: ldc_w         #901                // String when_hurt
     204: ldc_w         #903                // String When hurt:
     207: invokevirtual #823                // Method tooltip:(Ljava/lang/String;Ljava/lang/String;)V
     210: aload_0
     211: ldc_w         #905                // String when_hurt.is_fire
     214: ldc_w         #907                // String When hurt by Fire:
     217: invokevirtual #823                // Method tooltip:(Ljava/lang/String;Ljava/lang/String;)V
     220: return

  private void add(net.minecraft.sounds.SoundEvent, java.lang.String);
    descriptor: (Lnet/minecraft/sounds/SoundEvent;Ljava/lang/String;)V
    Code:
       0: aload_0
       1: ldc_w         #910                // String %s.subtitles.%s
       4: getstatic     #916                // Field net/minecraft/core/registries/BuiltInRegistries.SOUND_EVENT:Lnet/minecraft/core/Registry;
       7: aload_1
       8: invokeinterface #922,  2          // InterfaceMethod net/minecraft/core/Registry.getKey:(Ljava/lang/Object;)Lnet/minecraft/resources/ResourceLocation;
      13: aload_2
      14: invokevirtual #925                // Method add:(Ljava/lang/String;Lnet/minecraft/resources/ResourceLocation;Ljava/lang/String;)V
      17: return

  private void add(java.lang.String, net.minecraft.resources.ResourceLocation, java.lang.String);
    descriptor: (Ljava/lang/String;Lnet/minecraft/resources/ResourceLocation;Ljava/lang/String;)V
    Code:
       0: aload_0
       1: aload_1
       2: iconst_2
       3: anewarray     #929                // class java/lang/Object
       6: dup
       7: iconst_0
       8: aload_2
       9: invokevirtual #932                // Method net/minecraft/resources/ResourceLocation.getNamespace:()Ljava/lang/String;
      12: aastore
      13: dup
      14: iconst_1
      15: aload_2
      16: invokevirtual #365                // Method net/minecraft/resources/ResourceLocation.getPath:()Ljava/lang/String;
      19: aastore
      20: invokevirtual #936                // Method java/lang/String.formatted:([Ljava/lang/Object;)Ljava/lang/String;
      23: aload_3
      24: invokevirtual #105                // Method add:(Ljava/lang/String;Ljava/lang/String;)V
      27: return

  private void addAbilityTooltip(net.minecraft.core.component.DataComponentType<?>, net.minecraft.core.Holder<?>, java.lang.String...);
    descriptor: (Lnet/minecraft/core/component/DataComponentType;Lnet/minecraft/core/Holder;[Ljava/lang/String;)V
    Code:
       0: new           #943                // class java/util/ArrayList
       3: dup
       4: aload_3
       5: invokestatic  #947                // InterfaceMethod java/util/List.of:([Ljava/lang/Object;)Ljava/util/List;
       8: invokespecial #950                // Method java/util/ArrayList."<init>":(Ljava/util/Collection;)V
      11: astore        4
      13: aload         4
      15: aload_2
      16: invokeinterface #725,  1          // InterfaceMethod net/minecraft/core/Holder.unwrapKey:()Ljava/util/Optional;
      21: invokevirtual #604                // Method java/util/Optional.orElseThrow:()Ljava/lang/Object;
      24: checkcast     #606                // class net/minecraft/resources/ResourceKey
      27: invokevirtual #607                // Method net/minecraft/resources/ResourceKey.location:()Lnet/minecraft/resources/ResourceLocation;
      30: invokevirtual #365                // Method net/minecraft/resources/ResourceLocation.getPath:()Ljava/lang/String;
      33: invokeinterface #953,  2          // InterfaceMethod java/util/List.addFirst:(Ljava/lang/Object;)V
      38: aload_0
      39: aload_1
      40: aload         4
      42: invokedynamic #965,  0            // InvokeDynamic #4:apply:()Ljava/util/function/IntFunction;
      47: invokeinterface #969,  2          // InterfaceMethod java/util/List.toArray:(Ljava/util/function/IntFunction;)[Ljava/lang/Object;
      52: checkcast     #971                // class "[Ljava/lang/String;"
      55: invokevirtual #204                // Method addAbilityTooltip:(Lnet/minecraft/core/component/DataComponentType;[Ljava/lang/String;)V
      58: return

  private void addAbilityTooltip(net.minecraft.core.component.DataComponentType<?>, java.lang.String...);
    descriptor: (Lnet/minecraft/core/component/DataComponentType;[Ljava/lang/String;)V
    Code:
       0: new           #979                // class java/lang/StringBuilder
       3: dup
       4: ldc_w         #981                // String %s.tooltip.ability.%s
       7: invokespecial #984                // Method java/lang/StringBuilder."<init>":(Ljava/lang/String;)V
      10: astore_3
      11: iconst_0
      12: istore        4
      14: iload         4
      16: aload_2
      17: arraylength
      18: iconst_1
      19: isub
      20: if_icmpge     43
      23: aload_3
      24: bipush        46
      26: invokevirtual #988                // Method java/lang/StringBuilder.append:(C)Ljava/lang/StringBuilder;
      29: aload_2
      30: iload         4
      32: aaload
      33: invokevirtual #991                // Method java/lang/StringBuilder.append:(Ljava/lang/String;)Ljava/lang/StringBuilder;
      36: pop
      37: iinc          4, 1
      40: goto          14
      43: aload_0
      44: aload_3
      45: invokevirtual #994                // Method java/lang/StringBuilder.toString:()Ljava/lang/String;
      48: getstatic     #997                // Field net/minecraft/core/registries/BuiltInRegistries.DATA_COMPONENT_TYPE:Lnet/minecraft/core/Registry;
      51: aload_1
      52: invokeinterface #922,  2          // InterfaceMethod net/minecraft/core/Registry.getKey:(Ljava/lang/Object;)Lnet/minecraft/resources/ResourceLocation;
      57: invokestatic  #1003               // Method java/util/Objects.requireNonNull:(Ljava/lang/Object;)Ljava/lang/Object;
      60: checkcast     #361                // class net/minecraft/resources/ResourceLocation
      63: aload_2
      64: aload_2
      65: arraylength
      66: iconst_1
      67: isub
      68: aaload
      69: invokevirtual #925                // Method add:(Ljava/lang/String;Lnet/minecraft/resources/ResourceLocation;Ljava/lang/String;)V
      72: return

  private void addEffects();
    descriptor: ()V
    Code:
       0: aload_0
       1: getstatic     #1011               // Field artifacts/registry/ModMobEffects.MAGNETISM:Lnet/minecraft/core/Holder;
       4: dup
       5: invokestatic  #1003               // Method java/util/Objects.requireNonNull:(Ljava/lang/Object;)Ljava/lang/Object;
       8: pop
       9: invokedynamic #1018,  0           // InvokeDynamic #5:get:(Lnet/minecraft/core/Holder;)Ljava/util/function/Supplier;
      14: ldc_w         #1020               // String Magnetism
      17: invokevirtual #1024               // Method addEffect:(Ljava/util/function/Supplier;Ljava/lang/String;)V
      20: return

  private void tooltip(java.lang.String, java.lang.String);
    descriptor: (Ljava/lang/String;Ljava/lang/String;)V
    Code:
       0: aload_0
       1: ldc_w         #1026               // String %s.tooltip.%s
       4: iconst_2
       5: anewarray     #929                // class java/lang/Object
       8: dup
       9: iconst_0
      10: ldc           #20                 // String artifacts
      12: aastore
      13: dup
      14: iconst_1
      15: aload_1
      16: aastore
      17: invokevirtual #936                // Method java/lang/String.formatted:([Ljava/lang/Object;)Ljava/lang/String;
      20: aload_2
      21: invokevirtual #105                // Method add:(Ljava/lang/String;Ljava/lang/String;)V
      24: return

  private static java.lang.String fromCamelCasedString(java.lang.String);
    descriptor: (Ljava/lang/String;)Ljava/lang/String;
    Code:
       0: getstatic     #1033               // Field com/google/common/base/CaseFormat.LOWER_CAMEL:Lcom/google/common/base/CaseFormat;
       3: getstatic     #1036               // Field com/google/common/base/CaseFormat.LOWER_UNDERSCORE:Lcom/google/common/base/CaseFormat;
       6: aload_0
       7: invokevirtual #1040               // Method com/google/common/base/CaseFormat.to:(Lcom/google/common/base/CaseFormat;Ljava/lang/String;)Ljava/lang/String;
      10: invokestatic  #617                // Method fromSnakeCasedString:(Ljava/lang/String;)Ljava/lang/String;
      13: areturn

  private static java.lang.String fromSnakeCasedString(java.lang.String);
    descriptor: (Ljava/lang/String;)Ljava/lang/String;
    Code:
       0: aload_0
       1: ldc_w         #1042               // String _
       4: invokevirtual #613                // Method java/lang/String.split:(Ljava/lang/String;)[Ljava/lang/String;
       7: astore_1
       8: iconst_0
       9: istore_2
      10: iload_2
      11: aload_1
      12: arraylength
      13: if_icmpge     47
      16: aload_1
      17: iload_2
      18: aload_1
      19: iload_2
      20: aaload
      21: iconst_0
      22: invokevirtual #1046               // Method java/lang/String.charAt:(I)C
      25: invokestatic  #1052               // Method java/lang/Character.toUpperCase:(C)C
      28: aload_1
      29: iload_2
      30: aaload
      31: iconst_1
      32: invokevirtual #1056               // Method java/lang/String.substring:(I)Ljava/lang/String;
      35: invokedynamic #1068,  0           // InvokeDynamic #6:makeConcatWithConstants:(CLjava/lang/String;)Ljava/lang/String;
      40: aastore
      41: iinc          2, 1
      44: goto          10
      47: aload_1
      48: ldc_w         #1070               // String
      51: invokestatic  #1076               // Method joptsimple/internal/Strings.join:([Ljava/lang/String;Ljava/lang/String;)Ljava/lang/String;
      54: ldc_w         #1078               // String  A
      57: ldc_w         #1080               // String  a
      60: invokevirtual #1084               // Method java/lang/String.replace:(Ljava/lang/CharSequence;Ljava/lang/CharSequence;)Ljava/lang/String;
      63: ldc_w         #1086               // String  An
      66: ldc_w         #1088               // String  an
      69: invokevirtual #1084               // Method java/lang/String.replace:(Ljava/lang/CharSequence;Ljava/lang/CharSequence;)Ljava/lang/String;
      72: ldc_w         #1090               // String  In
      75: ldc_w         #1092               // String  in
      78: invokevirtual #1096               // Method java/lang/String.replaceFirst:(Ljava/lang/String;Ljava/lang/String;)Ljava/lang/String;
      81: ldc_w         #1098               // String  Of
      84: ldc_w         #1100               // String  of
      87: invokevirtual #1084               // Method java/lang/String.replace:(Ljava/lang/CharSequence;Ljava/lang/CharSequence;)Ljava/lang/String;
      90: ldc_w         #1102               // String  On
      93: ldc_w         #1104               // String  on
      96: invokevirtual #1084               // Method java/lang/String.replace:(Ljava/lang/CharSequence;Ljava/lang/CharSequence;)Ljava/lang/String;
      99: ldc_w         #1106               // String  Per
     102: ldc_w         #1108               // String  per
     105: invokevirtual #1096               // Method java/lang/String.replaceFirst:(Ljava/lang/String;Ljava/lang/String;)Ljava/lang/String;
     108: ldc_w         #1110               // String  The
     111: ldc_w         #1112               // String  the
     114: invokevirtual #1084               // Method java/lang/String.replace:(Ljava/lang/CharSequence;Ljava/lang/CharSequence;)Ljava/lang/String;
     117: areturn

  private static java.lang.String configDescription(java.lang.String...);
    descriptor: ([Ljava/lang/String;)Ljava/lang/String;
    Code:
       0: iconst_3
       1: anewarray     #175                // class java/lang/String
       4: dup
       5: iconst_0
       6: ldc_w         #1116               // String config
       9: aastore
      10: dup
      11: iconst_1
      12: aload_0
      13: invokestatic  #1119               // Method concat:([Ljava/lang/String;)Ljava/lang/String;
      16: aastore
      17: dup
      18: iconst_2
      19: ldc_w         #1121               // String description
      22: aastore
      23: invokestatic  #1123               // Method key:([Ljava/lang/String;)Ljava/lang/String;
      26: areturn

  private static java.lang.String configTitle(java.lang.String...);
    descriptor: ([Ljava/lang/String;)Ljava/lang/String;
    Code:
       0: iconst_3
       1: anewarray     #175                // class java/lang/String
       4: dup
       5: iconst_0
       6: ldc_w         #1116               // String config
       9: aastore
      10: dup
      11: iconst_1
      12: aload_0
      13: invokestatic  #1119               // Method concat:([Ljava/lang/String;)Ljava/lang/String;
      16: aastore
      17: dup
      18: iconst_2
      19: ldc_w         #1125               // String title
      22: aastore
      23: invokestatic  #1123               // Method key:([Ljava/lang/String;)Ljava/lang/String;
      26: areturn

  private static java.lang.String key(java.lang.String...);
    descriptor: ([Ljava/lang/String;)Ljava/lang/String;
    Code:
       0: iconst_2
       1: anewarray     #175                // class java/lang/String
       4: dup
       5: iconst_0
       6: ldc           #20                 // String artifacts
       8: aastore
       9: dup
      10: iconst_1
      11: aload_0
      12: invokestatic  #1119               // Method concat:([Ljava/lang/String;)Ljava/lang/String;
      15: aastore
      16: invokestatic  #1119               // Method concat:([Ljava/lang/String;)Ljava/lang/String;
      19: areturn

  private static java.lang.String concat(java.lang.String...);
    descriptor: ([Ljava/lang/String;)Ljava/lang/String;
    Code:
       0: aload_0
       1: arraylength
       2: ifne          9
       5: ldc_w         #1127               // String
       8: areturn
       9: new           #979                // class java/lang/StringBuilder
      12: dup
      13: aload_0
      14: iconst_0
      15: aaload
      16: invokespecial #984                // Method java/lang/StringBuilder."<init>":(Ljava/lang/String;)V
      19: astore_1
      20: iconst_1
      21: istore_2
      22: iload_2
      23: aload_0
      24: arraylength
      25: if_icmpge     59
      28: aload_0
      29: iload_2
      30: aaload
      31: invokevirtual #1130               // Method java/lang/String.isEmpty:()Z
      34: ifeq          40
      37: goto          53
      40: aload_1
      41: bipush        46
      43: invokevirtual #988                // Method java/lang/StringBuilder.append:(C)Ljava/lang/StringBuilder;
      46: aload_0
      47: iload_2
      48: aaload
      49: invokevirtual #991                // Method java/lang/StringBuilder.append:(Ljava/lang/String;)Ljava/lang/StringBuilder;
      52: pop
      53: iinc          2, 1
      56: goto          22
      59: aload_1
      60: invokevirtual #994                // Method java/lang/StringBuilder.toString:()Ljava/lang/String;
      63: areturn

  private static java.lang.String[] lambda$addAbilityTooltip$3(int);
    descriptor: (I)[Ljava/lang/String;
    Code:
       0: iload_0
       1: anewarray     #175                // class java/lang/String
       4: areturn

  private void lambda$addConfigTooltips$2(artifacts.config.ConfigManager, java.lang.String, artifacts.config.value.Value$ConfigValue);
    descriptor: (Lartifacts/config/ConfigManager;Ljava/lang/String;Lartifacts/config/value/Value$ConfigValue;)V
    Code:
       0: aload_2
       1: ldc_w         #1134               // String generateAsLoot
       4: invokevirtual #1138               // Method java/lang/String.endsWith:(Ljava/lang/String;)Z
       7: ifeq          11
      10: return
      11: aload_1
      12: aload_2
      13: invokevirtual #1142               // Method artifacts/config/ConfigManager.getDescription:(Ljava/lang/String;)Ljava/util/List;
      16: astore        4
      18: aload_1
      19: invokevirtual #686                // Method artifacts/config/ConfigManager.getName:()Ljava/lang/String;
      22: aload_2
      23: invokedynamic #1146,  0           // InvokeDynamic #7:makeConcatWithConstants:(Ljava/lang/String;Ljava/lang/String;)Ljava/lang/String;
      28: astore_2
      29: aload         4
      31: invokeinterface #1150,  1         // InterfaceMethod java/util/List.size:()I
      36: iconst_1
      37: if_icmpne     68
      40: aload_0
      41: iconst_1
      42: anewarray     #175                // class java/lang/String
      45: dup
      46: iconst_0
      47: aload_2
      48: aastore
      49: invokestatic  #1152               // Method configDescription:([Ljava/lang/String;)Ljava/lang/String;
      52: aload         4
      54: invokeinterface #1155,  1         // InterfaceMethod java/util/List.getFirst:()Ljava/lang/Object;
      59: checkcast     #175                // class java/lang/String
      62: invokevirtual #105                // Method add:(Ljava/lang/String;Ljava/lang/String;)V
      65: goto          134
      68: iconst_0
      69: istore        5
      71: iload         5
      73: aload         4
      75: invokeinterface #1150,  1         // InterfaceMethod java/util/List.size:()I
      80: if_icmpge     134
      83: aload_0
      84: iconst_2
      85: anewarray     #175                // class java/lang/String
      88: dup
      89: iconst_0
      90: iconst_1
      91: anewarray     #175                // class java/lang/String
      94: dup
      95: iconst_0
      96: aload_2
      97: aastore
      98: invokestatic  #1152               // Method configDescription:([Ljava/lang/String;)Ljava/lang/String;
     101: aastore
     102: dup
     103: iconst_1
     104: iload         5
     106: invokestatic  #1159               // Method java/lang/Integer.toString:(I)Ljava/lang/String;
     109: aastore
     110: invokestatic  #1119               // Method concat:([Ljava/lang/String;)Ljava/lang/String;
     113: aload         4
     115: iload         5
     117: invokeinterface #1161,  2         // InterfaceMethod java/util/List.get:(I)Ljava/lang/Object;
     122: checkcast     #175                // class java/lang/String
     125: invokevirtual #105                // Method add:(Ljava/lang/String;Ljava/lang/String;)V
     128: iinc          5, 1
     131: goto          71
     134: return

  private void lambda$addConfigNames$1(artifacts.config.ConfigManager, java.lang.String, artifacts.config.value.Value$ConfigValue);
    descriptor: (Lartifacts/config/ConfigManager;Ljava/lang/String;Lartifacts/config/value/Value$ConfigValue;)V
    Code:
       0: aload_2
       1: ldc_w         #609                // String \\.
       4: invokevirtual #613                // Method java/lang/String.split:(Ljava/lang/String;)[Ljava/lang/String;
       7: astore        4
       9: aload         4
      11: aload         4
      13: arraylength
      14: iconst_1
      15: isub
      16: aaload
      17: astore        5
      19: aload         5
      21: ldc_w         #825                // String cooldown
      24: invokevirtual #1167               // Method java/lang/String.equals:(Ljava/lang/Object;)Z
      27: ifne          181
      30: aload         5
      32: ldc_w         #1169               // String enabled
      35: invokevirtual #1167               // Method java/lang/String.equals:(Ljava/lang/Object;)Z
      38: ifne          181
      41: aload         5
      43: ldc_w         #1134               // String generateAsLoot
      46: invokevirtual #1167               // Method java/lang/String.equals:(Ljava/lang/Object;)Z
      49: ifne          181
      52: aload         5
      54: invokestatic  #689                // Method fromCamelCasedString:(Ljava/lang/String;)Ljava/lang/String;
      57: astore        6
      59: aload_1
      60: invokevirtual #686                // Method artifacts/config/ConfigManager.getName:()Ljava/lang/String;
      63: aload_2
      64: invokedynamic #1146,  0           // InvokeDynamic #7:makeConcatWithConstants:(Ljava/lang/String;Ljava/lang/String;)Ljava/lang/String;
      69: astore_2
      70: aload_0
      71: iconst_1
      72: anewarray     #175                // class java/lang/String
      75: dup
      76: iconst_0
      77: aload_2
      78: aastore
      79: invokestatic  #656                // Method configTitle:([Ljava/lang/String;)Ljava/lang/String;
      82: aload         6
      84: invokevirtual #105                // Method add:(Ljava/lang/String;Ljava/lang/String;)V
      87: new           #979                // class java/lang/StringBuilder
      90: dup
      91: aload_1
      92: invokevirtual #686                // Method artifacts/config/ConfigManager.getName:()Ljava/lang/String;
      95: invokespecial #984                // Method java/lang/StringBuilder."<init>":(Ljava/lang/String;)V
      98: astore        7
     100: iconst_0
     101: istore        8
     103: iload         8
     105: aload         4
     107: arraylength
     108: iconst_1
     109: isub
     110: if_icmpge     181
     113: aload         7
     115: bipush        46
     117: invokevirtual #988                // Method java/lang/StringBuilder.append:(C)Ljava/lang/StringBuilder;
     120: aload         4
     122: iload         8
     124: aaload
     125: invokevirtual #991                // Method java/lang/StringBuilder.append:(Ljava/lang/String;)Ljava/lang/StringBuilder;
     128: pop
     129: getstatic     #1173               // Field net/minecraft/core/registries/BuiltInRegistries.ITEM:Lnet/minecraft/core/DefaultedRegistry;
     132: aload         4
     134: iload         8
     136: aaload
     137: invokestatic  #1176               // Method artifacts/Artifacts.id:(Ljava/lang/String;)Lnet/minecraft/resources/ResourceLocation;
     140: invokeinterface #1182,  2         // InterfaceMethod net/minecraft/core/DefaultedRegistry.containsKey:(Lnet/minecraft/resources/ResourceLocation;)Z
     145: ifne          175
     148: aload_0
     149: iconst_1
     150: anewarray     #175                // class java/lang/String
     153: dup
     154: iconst_0
     155: aload         7
     157: invokevirtual #994                // Method java/lang/StringBuilder.toString:()Ljava/lang/String;
     160: aastore
     161: invokestatic  #656                // Method configTitle:([Ljava/lang/String;)Ljava/lang/String;
     164: aload         4
     166: iload         8
     168: aaload
     169: invokestatic  #617                // Method fromSnakeCasedString:(Ljava/lang/String;)Ljava/lang/String;
     172: invokevirtual #736                // Method override:(Ljava/lang/String;Ljava/lang/String;)V
     175: iinc          8, 1
     178: goto          103
     181: return

  private void lambda$addMiscTranslations$0(net.minecraft.client.KeyMapping);
    descriptor: (Lnet/minecraft/client/KeyMapping;)V
    Code:
       0: aload_1
       1: invokevirtual #1189               // Method net/minecraft/client/KeyMapping.getName:()Ljava/lang/String;
       4: ldc_w         #609                // String \\.
       7: invokevirtual #613                // Method java/lang/String.split:(Ljava/lang/String;)[Ljava/lang/String;
      10: invokestatic  #1194               // Method java/util/Arrays.asList:([Ljava/lang/Object;)Ljava/util/List;
      13: astore_2
      14: aload_2
      15: invokeinterface #1197,  1         // InterfaceMethod java/util/List.getLast:()Ljava/lang/Object;
      20: checkcast     #175                // class java/lang/String
      23: invokestatic  #617                // Method fromSnakeCasedString:(Ljava/lang/String;)Ljava/lang/String;
      26: astore_3
      27: aload_2
      28: aload_2
      29: invokeinterface #1150,  1         // InterfaceMethod java/util/List.size:()I
      34: iconst_2
      35: isub
      36: invokeinterface #1161,  2         // InterfaceMethod java/util/List.get:(I)Ljava/lang/Object;
      41: checkcast     #175                // class java/lang/String
      44: invokestatic  #617                // Method fromSnakeCasedString:(Ljava/lang/String;)Ljava/lang/String;
      47: astore        4
      49: aload_0
      50: aload_1
      51: invokevirtual #1189               // Method net/minecraft/client/KeyMapping.getName:()Ljava/lang/String;
      54: ldc_w         #1199               // String %s %s
      57: iconst_2
      58: anewarray     #929                // class java/lang/Object
      61: dup
      62: iconst_0
      63: aload_3
      64: aastore
      65: dup
      66: iconst_1
      67: aload         4
      69: aastore
      70: invokevirtual #936                // Method java/lang/String.formatted:([Ljava/lang/Object;)Ljava/lang/String;
      73: invokevirtual #105                // Method add:(Ljava/lang/String;Ljava/lang/String;)V
      76: return
}
