Compiled from "LootModifiers.java"
public class artifacts.neoforge.data.LootModifiers$Builder {
  private final net.minecraft.resources.ResourceKey<net.minecraft.world.level.storage.loot.LootTable> lootTable;
    descriptor: Lnet/minecraft/resources/ResourceKey;

  private final net.minecraft.world.level.storage.loot.LootPool$Builder lootPool;
    descriptor: Lnet/minecraft/world/level/storage/loot/LootPool$Builder;

  private final java.util.List<net.minecraft.world.level.storage.loot.predicates.LootItemCondition> conditions;
    descriptor: Ljava/util/List;

  private boolean replace;
    descriptor: Z

  private net.minecraft.world.level.storage.loot.parameters.LootContextParamSet paramSet;
    descriptor: Lnet/minecraft/world/level/storage/loot/parameters/LootContextParamSet;

  private artifacts.neoforge.data.LootModifiers$Builder(net.minecraft.resources.ResourceKey<net.minecraft.world.level.storage.loot.LootTable>);
    descriptor: (Lnet/minecraft/resources/ResourceKey;)V
    Code:
       0: aload_0
       1: invokespecial #72                 // Method java/lang/Object."<init>":()V
       4: aload_0
       5: invokestatic  #75                 // Method net/minecraft/world/level/storage/loot/LootPool.lootPool:()Lnet/minecraft/world/level/storage/loot/LootPool$Builder;
       8: putfield      #77                 // Field lootPool:Lnet/minecraft/world/level/storage/loot/LootPool$Builder;
      11: aload_0
      12: iconst_0
      13: putfield      #79                 // Field replace:Z
      16: aload_0
      17: getstatic     #84                 // Field net/minecraft/world/level/storage/loot/parameters/LootContextParamSets.CHEST:Lnet/minecraft/world/level/storage/loot/parameters/LootContextParamSet;
      20: putfield      #86                 // Field paramSet:Lnet/minecraft/world/level/storage/loot/parameters/LootContextParamSet;
      23: aload_0
      24: aload_1
      25: putfield      #88                 // Field lootTable:Lnet/minecraft/resources/ResourceKey;
      28: aload_0
      29: new           #90                 // class java/util/ArrayList
      32: dup
      33: invokespecial #91                 // Method java/util/ArrayList."<init>":()V
      36: putfield      #93                 // Field conditions:Ljava/util/List;
      39: return

  private artifacts.neoforge.loot.RollLootTableModifier build();
    descriptor: ()Lartifacts/neoforge/loot/RollLootTableModifier;
    Code:
       0: new           #99                 // class artifacts/neoforge/loot/RollLootTableModifier
       3: dup
       4: aload_0
       5: getfield      #93                 // Field conditions:Ljava/util/List;
       8: iconst_0
       9: anewarray     #20                 // class net/minecraft/world/level/storage/loot/predicates/LootItemCondition
      12: invokeinterface #105,  2          // InterfaceMethod java/util/List.toArray:([Ljava/lang/Object;)[Ljava/lang/Object;
      17: checkcast     #107                // class "[Lnet/minecraft/world/level/storage/loot/predicates/LootItemCondition;"
      20: getstatic     #112                // Field net/minecraft/core/registries/Registries.LOOT_TABLE:Lnet/minecraft/resources/ResourceKey;
      23: aload_0
      24: getfield      #88                 // Field lootTable:Lnet/minecraft/resources/ResourceKey;
      27: invokevirtual #118                // Method net/minecraft/resources/ResourceKey.location:()Lnet/minecraft/resources/ResourceLocation;
      30: invokevirtual #124                // Method net/minecraft/resources/ResourceLocation.getPath:()Ljava/lang/String;
      33: invokedynamic #136,  0            // InvokeDynamic #0:makeConcatWithConstants:(Ljava/lang/String;)Ljava/lang/String;
      38: invokestatic  #142                // Method artifacts/Artifacts.key:(Lnet/minecraft/resources/ResourceKey;Ljava/lang/String;)Lnet/minecraft/resources/ResourceKey;
      41: aload_0
      42: getfield      #79                 // Field replace:Z
      45: invokespecial #145                // Method artifacts/neoforge/loot/RollLootTableModifier."<init>":([Lnet/minecraft/world/level/storage/loot/predicates/LootItemCondition;Lnet/minecraft/resources/ResourceKey;Z)V
      48: areturn

  protected net.minecraft.world.level.storage.loot.LootTable$Builder createLootTable();
    descriptor: ()Lnet/minecraft/world/level/storage/loot/LootTable$Builder;
    Code:
       0: new           #14                 // class net/minecraft/world/level/storage/loot/LootTable$Builder
       3: dup
       4: invokespecial #148                // Method net/minecraft/world/level/storage/loot/LootTable$Builder."<init>":()V
       7: aload_0
       8: getfield      #77                 // Field lootPool:Lnet/minecraft/world/level/storage/loot/LootPool$Builder;
      11: invokevirtual #152                // Method net/minecraft/world/level/storage/loot/LootTable$Builder.withPool:(Lnet/minecraft/world/level/storage/loot/LootPool$Builder;)Lnet/minecraft/world/level/storage/loot/LootTable$Builder;
      14: areturn

  public net.minecraft.world.level.storage.loot.parameters.LootContextParamSet getParameterSet();
    descriptor: ()Lnet/minecraft/world/level/storage/loot/parameters/LootContextParamSet;
    Code:
       0: aload_0
       1: getfield      #86                 // Field paramSet:Lnet/minecraft/world/level/storage/loot/parameters/LootContextParamSet;
       4: areturn

  protected java.lang.String getName();
    descriptor: ()Ljava/lang/String;
    Code:
       0: aload_0
       1: getfield      #88                 // Field lootTable:Lnet/minecraft/resources/ResourceKey;
       4: invokevirtual #118                // Method net/minecraft/resources/ResourceKey.location:()Lnet/minecraft/resources/ResourceLocation;
       7: invokevirtual #124                // Method net/minecraft/resources/ResourceLocation.getPath:()Ljava/lang/String;
      10: areturn

  private artifacts.neoforge.data.LootModifiers$Builder parameterSet(net.minecraft.world.level.storage.loot.parameters.LootContextParamSet);
    descriptor: (Lnet/minecraft/world/level/storage/loot/parameters/LootContextParamSet;)Lartifacts/neoforge/data/LootModifiers$Builder;
    Code:
       0: aload_0
       1: aload_1
       2: putfield      #86                 // Field paramSet:Lnet/minecraft/world/level/storage/loot/parameters/LootContextParamSet;
       5: aload_0
       6: areturn

  public artifacts.neoforge.data.LootModifiers$Builder replace();
    descriptor: ()Lartifacts/neoforge/data/LootModifiers$Builder;
    Code:
       0: aload_0
       1: iconst_1
       2: putfield      #79                 // Field replace:Z
       5: aload_0
       6: areturn

  private artifacts.neoforge.data.LootModifiers$Builder lootPoolCondition(net.minecraft.world.level.storage.loot.predicates.LootItemCondition$Builder);
    descriptor: (Lnet/minecraft/world/level/storage/loot/predicates/LootItemCondition$Builder;)Lartifacts/neoforge/data/LootModifiers$Builder;
    Code:
       0: aload_0
       1: getfield      #77                 // Field lootPool:Lnet/minecraft/world/level/storage/loot/LootPool$Builder;
       4: aload_1
       5: invokevirtual #165                // Method net/minecraft/world/level/storage/loot/LootPool$Builder.when:(Lnet/minecraft/world/level/storage/loot/predicates/LootItemCondition$Builder;)Lnet/minecraft/world/level/storage/loot/LootPool$Builder;
       8: pop
       9: aload_0
      10: areturn

  private artifacts.neoforge.data.LootModifiers$Builder lootModifierCondition(net.minecraft.world.level.storage.loot.predicates.LootItemCondition$Builder);
    descriptor: (Lnet/minecraft/world/level/storage/loot/predicates/LootItemCondition$Builder;)Lartifacts/neoforge/data/LootModifiers$Builder;
    Code:
       0: aload_0
       1: getfield      #93                 // Field conditions:Ljava/util/List;
       4: aload_1
       5: invokeinterface #170,  1          // InterfaceMethod net/minecraft/world/level/storage/loot/predicates/LootItemCondition$Builder.build:()Lnet/minecraft/world/level/storage/loot/predicates/LootItemCondition;
      10: invokeinterface #174,  2          // InterfaceMethod java/util/List.add:(Ljava/lang/Object;)Z
      15: pop
      16: aload_0
      17: areturn

  private artifacts.neoforge.data.LootModifiers$Builder item(net.minecraft.world.item.Item, int);
    descriptor: (Lnet/minecraft/world/item/Item;I)Lartifacts/neoforge/data/LootModifiers$Builder;
    Code:
       0: aload_0
       1: getfield      #77                 // Field lootPool:Lnet/minecraft/world/level/storage/loot/LootPool$Builder;
       4: aload_1
       5: iload_2
       6: invokestatic  #182                // Method artifacts/neoforge/data/LootTables.item:(Lnet/minecraft/world/item/Item;I)Lnet/minecraft/world/level/storage/loot/entries/LootPoolSingletonContainer$Builder;
       9: invokevirtual #185                // Method net/minecraft/world/level/storage/loot/LootPool$Builder.add:(Lnet/minecraft/world/level/storage/loot/entries/LootPoolEntryContainer$Builder;)Lnet/minecraft/world/level/storage/loot/LootPool$Builder;
      12: pop
      13: aload_0
      14: areturn

  private artifacts.neoforge.data.LootModifiers$Builder item(net.minecraft.world.item.Item);
    descriptor: (Lnet/minecraft/world/item/Item;)Lartifacts/neoforge/data/LootModifiers$Builder;
    Code:
       0: aload_0
       1: aload_1
       2: iconst_1
       3: invokevirtual #190                // Method item:(Lnet/minecraft/world/item/Item;I)Lartifacts/neoforge/data/LootModifiers$Builder;
       6: areturn

  private artifacts.neoforge.data.LootModifiers$Builder artifact(int);
    descriptor: (I)Lartifacts/neoforge/data/LootModifiers$Builder;
    Code:
       0: aload_0
       1: getfield      #77                 // Field lootPool:Lnet/minecraft/world/level/storage/loot/LootPool$Builder;
       4: iload_1
       5: invokestatic  #195                // Method artifacts/neoforge/data/LootTables.artifact:(I)Lnet/minecraft/world/level/storage/loot/entries/LootPoolEntryContainer$Builder;
       8: invokevirtual #185                // Method net/minecraft/world/level/storage/loot/LootPool$Builder.add:(Lnet/minecraft/world/level/storage/loot/entries/LootPoolEntryContainer$Builder;)Lnet/minecraft/world/level/storage/loot/LootPool$Builder;
      11: pop
      12: aload_0
      13: areturn

  private artifacts.neoforge.data.LootModifiers$Builder drinkingHat(int);
    descriptor: (I)Lartifacts/neoforge/data/LootModifiers$Builder;
    Code:
       0: aload_0
       1: getfield      #77                 // Field lootPool:Lnet/minecraft/world/level/storage/loot/LootPool$Builder;
       4: iload_1
       5: invokestatic  #198                // Method artifacts/neoforge/data/LootTables.drinkingHat:(I)Lnet/minecraft/world/level/storage/loot/entries/LootPoolEntryContainer$Builder;
       8: invokevirtual #185                // Method net/minecraft/world/level/storage/loot/LootPool$Builder.add:(Lnet/minecraft/world/level/storage/loot/entries/LootPoolEntryContainer$Builder;)Lnet/minecraft/world/level/storage/loot/LootPool$Builder;
      11: pop
      12: aload_0
      13: areturn

  private artifacts.neoforge.data.LootModifiers$Builder everlastingBeef();
    descriptor: ()Lartifacts/neoforge/data/LootModifiers$Builder;
    Code:
       0: aload_0
       1: getfield      #77                 // Field lootPool:Lnet/minecraft/world/level/storage/loot/LootPool$Builder;
       4: getstatic     #205                // Field artifacts/registry/ModItems.EVERLASTING_BEEF:Lnet/minecraft/core/Holder;
       7: invokeinterface #211,  1          // InterfaceMethod net/minecraft/core/Holder.value:()Ljava/lang/Object;
      12: checkcast     #213                // class net/minecraft/world/item/Item
      15: iconst_1
      16: invokestatic  #182                // Method artifacts/neoforge/data/LootTables.item:(Lnet/minecraft/world/item/Item;I)Lnet/minecraft/world/level/storage/loot/entries/LootPoolSingletonContainer$Builder;
      19: invokestatic  #219                // Method net/minecraft/world/level/storage/loot/functions/SmeltItemFunction.smelted:()Lnet/minecraft/world/level/storage/loot/functions/LootItemConditionalFunction$Builder;
      22: getstatic     #223                // Field net/minecraft/world/level/storage/loot/LootContext$EntityTarget.THIS:Lnet/minecraft/world/level/storage/loot/LootContext$EntityTarget;
      25: invokestatic  #227                // Method net/minecraft/advancements/critereon/EntityPredicate$Builder.entity:()Lnet/minecraft/advancements/critereon/EntityPredicate$Builder;
      28: invokestatic  #231                // Method net/minecraft/advancements/critereon/EntityFlagsPredicate$Builder.flags:()Lnet/minecraft/advancements/critereon/EntityFlagsPredicate$Builder;
      31: iconst_1
      32: invokestatic  #237                // Method java/lang/Boolean.valueOf:(Z)Ljava/lang/Boolean;
      35: invokevirtual #241                // Method net/minecraft/advancements/critereon/EntityFlagsPredicate$Builder.setOnFire:(Ljava/lang/Boolean;)Lnet/minecraft/advancements/critereon/EntityFlagsPredicate$Builder;
      38: invokevirtual #244                // Method net/minecraft/advancements/critereon/EntityPredicate$Builder.flags:(Lnet/minecraft/advancements/critereon/EntityFlagsPredicate$Builder;)Lnet/minecraft/advancements/critereon/EntityPredicate$Builder;
      41: invokestatic  #250                // Method net/minecraft/world/level/storage/loot/predicates/LootItemEntityPropertyCondition.hasProperties:(Lnet/minecraft/world/level/storage/loot/LootContext$EntityTarget;Lnet/minecraft/advancements/critereon/EntityPredicate$Builder;)Lnet/minecraft/world/level/storage/loot/predicates/LootItemCondition$Builder;
      44: invokevirtual #253                // Method net/minecraft/world/level/storage/loot/functions/LootItemConditionalFunction$Builder.when:(Lnet/minecraft/world/level/storage/loot/predicates/LootItemCondition$Builder;)Lnet/minecraft/world/level/storage/loot/functions/LootItemConditionalFunction$Builder;
      47: invokevirtual #257                // Method net/minecraft/world/level/storage/loot/entries/LootPoolSingletonContainer$Builder.apply:(Lnet/minecraft/world/level/storage/loot/functions/LootItemFunction$Builder;)Lnet/minecraft/world/level/storage/loot/entries/LootPoolSingletonContainer$Builder;
      50: invokevirtual #185                // Method net/minecraft/world/level/storage/loot/LootPool$Builder.add:(Lnet/minecraft/world/level/storage/loot/entries/LootPoolEntryContainer$Builder;)Lnet/minecraft/world/level/storage/loot/LootPool$Builder;
      53: pop
      54: aload_0
      55: areturn
}
