Compiled from "ArtifactHooksNeoForge.java"
public class artifacts.neoforge.event.ArtifactHooksNeoForge {
  public artifacts.neoforge.event.ArtifactHooksNeoForge();
    descriptor: ()V
    Code:
       0: aload_0
       1: invokespecial #39                 // Method java/lang/Object."<init>":()V
       4: return

  public static void register();
    descriptor: ()V
    Code:
       0: invokestatic  #48                 // Method net/neoforged/fml/ModList.get:()Lnet/neoforged/fml/ModList;
       3: ldc           #50                 // String expandability
       5: invokevirtual #54                 // Method net/neoforged/fml/ModList.isLoaded:(Ljava/lang/String;)Z
       8: ifeq          37
      11: getstatic     #60                 // Field net/neoforged/neoforge/common/NeoForge.EVENT_BUS:Lnet/neoforged/bus/api/IEventBus;
      14: invokedynamic #79,  0             // InvokeDynamic #0:accept:()Ljava/util/function/Consumer;
      19: invokeinterface #85,  2           // InterfaceMethod net/neoforged/bus/api/IEventBus.addListener:(Ljava/util/function/Consumer;)V
      24: getstatic     #60                 // Field net/neoforged/neoforge/common/NeoForge.EVENT_BUS:Lnet/neoforged/bus/api/IEventBus;
      27: invokedynamic #92,  0             // InvokeDynamic #1:accept:()Ljava/util/function/Consumer;
      32: invokeinterface #85,  2           // InterfaceMethod net/neoforged/bus/api/IEventBus.addListener:(Ljava/util/function/Consumer;)V
      37: getstatic     #60                 // Field net/neoforged/neoforge/common/NeoForge.EVENT_BUS:Lnet/neoforged/bus/api/IEventBus;
      40: getstatic     #98                 // Field net/neoforged/bus/api/EventPriority.LOWEST:Lnet/neoforged/bus/api/EventPriority;
      43: invokedynamic #105,  0            // InvokeDynamic #2:accept:()Ljava/util/function/Consumer;
      48: invokeinterface #108,  3          // InterfaceMethod net/neoforged/bus/api/IEventBus.addListener:(Lnet/neoforged/bus/api/EventPriority;Ljava/util/function/Consumer;)V
      53: getstatic     #60                 // Field net/neoforged/neoforge/common/NeoForge.EVENT_BUS:Lnet/neoforged/bus/api/IEventBus;
      56: invokedynamic #115,  0            // InvokeDynamic #3:accept:()Ljava/util/function/Consumer;
      61: invokeinterface #85,  2           // InterfaceMethod net/neoforged/bus/api/IEventBus.addListener:(Ljava/util/function/Consumer;)V
      66: getstatic     #60                 // Field net/neoforged/neoforge/common/NeoForge.EVENT_BUS:Lnet/neoforged/bus/api/IEventBus;
      69: invokedynamic #122,  0            // InvokeDynamic #4:accept:()Ljava/util/function/Consumer;
      74: invokeinterface #85,  2           // InterfaceMethod net/neoforged/bus/api/IEventBus.addListener:(Ljava/util/function/Consumer;)V
      79: getstatic     #60                 // Field net/neoforged/neoforge/common/NeoForge.EVENT_BUS:Lnet/neoforged/bus/api/IEventBus;
      82: invokedynamic #129,  0            // InvokeDynamic #5:accept:()Ljava/util/function/Consumer;
      87: invokeinterface #85,  2           // InterfaceMethod net/neoforged/bus/api/IEventBus.addListener:(Ljava/util/function/Consumer;)V
      92: getstatic     #60                 // Field net/neoforged/neoforge/common/NeoForge.EVENT_BUS:Lnet/neoforged/bus/api/IEventBus;
      95: invokedynamic #136,  0            // InvokeDynamic #6:accept:()Ljava/util/function/Consumer;
     100: invokeinterface #85,  2           // InterfaceMethod net/neoforged/bus/api/IEventBus.addListener:(Ljava/util/function/Consumer;)V
     105: getstatic     #60                 // Field net/neoforged/neoforge/common/NeoForge.EVENT_BUS:Lnet/neoforged/bus/api/IEventBus;
     108: invokedynamic #143,  0            // InvokeDynamic #7:accept:()Ljava/util/function/Consumer;
     113: invokeinterface #85,  2           // InterfaceMethod net/neoforged/bus/api/IEventBus.addListener:(Ljava/util/function/Consumer;)V
     118: getstatic     #60                 // Field net/neoforged/neoforge/common/NeoForge.EVENT_BUS:Lnet/neoforged/bus/api/IEventBus;
     121: invokedynamic #150,  0            // InvokeDynamic #8:accept:()Ljava/util/function/Consumer;
     126: invokeinterface #85,  2           // InterfaceMethod net/neoforged/bus/api/IEventBus.addListener:(Ljava/util/function/Consumer;)V
     131: getstatic     #60                 // Field net/neoforged/neoforge/common/NeoForge.EVENT_BUS:Lnet/neoforged/bus/api/IEventBus;
     134: invokedynamic #157,  0            // InvokeDynamic #9:accept:()Ljava/util/function/Consumer;
     139: invokeinterface #85,  2           // InterfaceMethod net/neoforged/bus/api/IEventBus.addListener:(Ljava/util/function/Consumer;)V
     144: getstatic     #60                 // Field net/neoforged/neoforge/common/NeoForge.EVENT_BUS:Lnet/neoforged/bus/api/IEventBus;
     147: invokedynamic #164,  0            // InvokeDynamic #10:accept:()Ljava/util/function/Consumer;
     152: invokeinterface #85,  2           // InterfaceMethod net/neoforged/bus/api/IEventBus.addListener:(Ljava/util/function/Consumer;)V
     157: return

  private static void onEntityAdded(net.neoforged.neoforge.event.entity.EntityJoinLevelEvent);
    descriptor: (Lnet/neoforged/neoforge/event/entity/EntityJoinLevelEvent;)V
    Code:
       0: aload_0
       1: invokevirtual #171                // Method net/neoforged/neoforge/event/entity/EntityJoinLevelEvent.getEntity:()Lnet/minecraft/world/entity/Entity;
       4: invokestatic  #176                // Method artifacts/event/ArtifactHooks.onEntityAdded:(Lnet/minecraft/world/entity/Entity;)V
       7: return

  private static void onLivingDamage(net.neoforged.neoforge.event.entity.living.LivingDamageEvent$Pre);
    descriptor: (Lnet/neoforged/neoforge/event/entity/living/LivingDamageEvent$Pre;)V
    Code:
       0: aload_0
       1: invokevirtual #180                // Method net/neoforged/neoforge/event/entity/living/LivingDamageEvent$Pre.getEntity:()Lnet/minecraft/world/entity/LivingEntity;
       4: aload_0
       5: invokevirtual #184                // Method net/neoforged/neoforge/event/entity/living/LivingDamageEvent$Pre.getSource:()Lnet/minecraft/world/damagesource/DamageSource;
       8: aload_0
       9: invokevirtual #188                // Method net/neoforged/neoforge/event/entity/living/LivingDamageEvent$Pre.getNewDamage:()F
      12: invokestatic  #192                // Method artifacts/event/ArtifactHooks.onLivingDamaged:(Lnet/minecraft/world/entity/LivingEntity;Lnet/minecraft/world/damagesource/DamageSource;F)V
      15: return

  private static void onLivingUpdate(net.neoforged.neoforge.event.tick.EntityTickEvent$Post);
    descriptor: (Lnet/neoforged/neoforge/event/tick/EntityTickEvent$Post;)V
    Code:
       0: aload_0
       1: invokevirtual #194                // Method net/neoforged/neoforge/event/tick/EntityTickEvent$Post.getEntity:()Lnet/minecraft/world/entity/Entity;
       4: astore_2
       5: aload_2
       6: instanceof    #196                // class net/minecraft/world/entity/LivingEntity
       9: ifeq          25
      12: aload_2
      13: checkcast     #196                // class net/minecraft/world/entity/LivingEntity
      16: astore_1
      17: aload_1
      18: invokestatic  #200                // Method onKittySlippersLivingUpdate:(Lnet/minecraft/world/entity/LivingEntity;)V
      21: aload_1
      22: invokestatic  #203                // Method artifacts/event/ArtifactHooks.livingUpdate:(Lnet/minecraft/world/entity/LivingEntity;)V
      25: return

  private static void onDrinkingHatItemUse(net.neoforged.neoforge.event.entity.living.LivingEntityUseItemEvent$Start);
    descriptor: (Lnet/neoforged/neoforge/event/entity/living/LivingEntityUseItemEvent$Start;)V
    Code:
       0: aload_0
       1: aload_0
       2: invokevirtual #210                // Method net/neoforged/neoforge/event/entity/living/LivingEntityUseItemEvent$Start.getDuration:()I
       5: aload_0
       6: invokevirtual #214                // Method net/neoforged/neoforge/event/entity/living/LivingEntityUseItemEvent$Start.getItem:()Lnet/minecraft/world/item/ItemStack;
       9: aload_0
      10: invokevirtual #215                // Method net/neoforged/neoforge/event/entity/living/LivingEntityUseItemEvent$Start.getEntity:()Lnet/minecraft/world/entity/LivingEntity;
      13: invokestatic  #219                // Method artifacts/event/ArtifactHooks.modifyUseDuration:(ILnet/minecraft/world/item/ItemStack;Lnet/minecraft/world/entity/LivingEntity;)I
      16: invokevirtual #223                // Method net/neoforged/neoforge/event/entity/living/LivingEntityUseItemEvent$Start.setDuration:(I)V
      19: return

  private static void onGoldenHookExperienceDrop(net.neoforged.neoforge.event.entity.living.LivingExperienceDropEvent);
    descriptor: (Lnet/neoforged/neoforge/event/entity/living/LivingExperienceDropEvent;)V
    Code:
       0: aload_0
       1: invokevirtual #229                // Method net/neoforged/neoforge/event/entity/living/LivingExperienceDropEvent.getDroppedExperience:()I
       4: istore_1
       5: iload_1
       6: aload_0
       7: invokevirtual #230                // Method net/neoforged/neoforge/event/entity/living/LivingExperienceDropEvent.getEntity:()Lnet/minecraft/world/entity/LivingEntity;
      10: aload_0
      11: invokevirtual #234                // Method net/neoforged/neoforge/event/entity/living/LivingExperienceDropEvent.getAttackingPlayer:()Lnet/minecraft/world/entity/player/Player;
      14: invokestatic  #238                // Method artifacts/event/ArtifactHooks.modifyExperience:(ILnet/minecraft/world/entity/LivingEntity;Lnet/minecraft/world/entity/player/Player;)I
      17: istore_2
      18: aload_0
      19: iload_2
      20: invokevirtual #241                // Method net/neoforged/neoforge/event/entity/living/LivingExperienceDropEvent.setDroppedExperience:(I)V
      23: return

  private static void onKittySlippersChangeTarget(net.neoforged.neoforge.event.entity.living.LivingChangeTargetEvent);
    descriptor: (Lnet/neoforged/neoforge/event/entity/living/LivingChangeTargetEvent;)V
    Code:
       0: aload_0
       1: invokevirtual #250                // Method net/neoforged/neoforge/event/entity/living/LivingChangeTargetEvent.getNewAboutToBeSetTarget:()Lnet/minecraft/world/entity/LivingEntity;
       4: astore_1
       5: aload_0
       6: invokevirtual #251                // Method net/neoforged/neoforge/event/entity/living/LivingChangeTargetEvent.getEntity:()Lnet/minecraft/world/entity/LivingEntity;
       9: invokevirtual #255                // Method net/minecraft/world/entity/LivingEntity.getType:()Lnet/minecraft/world/entity/EntityType;
      12: getstatic     #261                // Field artifacts/registry/ModTags.CREEPERS:Lnet/minecraft/tags/TagKey;
      15: invokevirtual #267                // Method net/minecraft/world/entity/EntityType.is:(Lnet/minecraft/tags/TagKey;)Z
      18: ifeq          45
      21: getstatic     #273                // Field artifacts/registry/ModDataComponents.CREEPER_REPELLENT:Ljava/util/function/Supplier;
      24: invokeinterface #278,  1          // InterfaceMethod java/util/function/Supplier.get:()Ljava/lang/Object;
      29: checkcast     #280                // class net/minecraft/core/component/DataComponentType
      32: aload_1
      33: iconst_1
      34: invokestatic  #286                // Method artifacts/equipment/EquipmentHelper.hasAbilityActive:(Lnet/minecraft/core/component/DataComponentType;Lnet/minecraft/world/entity/LivingEntity;Z)Z
      37: ifeq          45
      40: aload_0
      41: iconst_1
      42: invokevirtual #290                // Method net/neoforged/neoforge/event/entity/living/LivingChangeTargetEvent.setCanceled:(Z)V
      45: return

  private static void onKittySlippersLivingUpdate(net.minecraft.world.entity.LivingEntity);
    descriptor: (Lnet/minecraft/world/entity/LivingEntity;)V
    Code:
       0: aload_0
       1: invokevirtual #295                // Method net/minecraft/world/entity/LivingEntity.getLastHurtByMob:()Lnet/minecraft/world/entity/LivingEntity;
       4: ifnull        47
       7: getstatic     #273                // Field artifacts/registry/ModDataComponents.CREEPER_REPELLENT:Ljava/util/function/Supplier;
      10: invokeinterface #278,  1          // InterfaceMethod java/util/function/Supplier.get:()Ljava/lang/Object;
      15: checkcast     #280                // class net/minecraft/core/component/DataComponentType
      18: aload_0
      19: invokevirtual #295                // Method net/minecraft/world/entity/LivingEntity.getLastHurtByMob:()Lnet/minecraft/world/entity/LivingEntity;
      22: iconst_1
      23: invokestatic  #286                // Method artifacts/equipment/EquipmentHelper.hasAbilityActive:(Lnet/minecraft/core/component/DataComponentType;Lnet/minecraft/world/entity/LivingEntity;Z)Z
      26: ifeq          47
      29: aload_0
      30: invokevirtual #255                // Method net/minecraft/world/entity/LivingEntity.getType:()Lnet/minecraft/world/entity/EntityType;
      33: getstatic     #261                // Field artifacts/registry/ModTags.CREEPERS:Lnet/minecraft/tags/TagKey;
      36: invokevirtual #267                // Method net/minecraft/world/entity/EntityType.is:(Lnet/minecraft/tags/TagKey;)Z
      39: ifeq          47
      42: aload_0
      43: aconst_null
      44: invokevirtual #298                // Method net/minecraft/world/entity/LivingEntity.setLastHurtByMob:(Lnet/minecraft/world/entity/LivingEntity;)V
      47: return

  private static void onDiggingClawsHarvestCheck(net.neoforged.neoforge.event.entity.player.PlayerEvent$HarvestCheck);
    descriptor: (Lnet/neoforged/neoforge/event/entity/player/PlayerEvent$HarvestCheck;)V
    Code:
       0: aload_0
       1: aload_0
       2: invokevirtual #302                // Method net/neoforged/neoforge/event/entity/player/PlayerEvent$HarvestCheck.canHarvest:()Z
       5: ifne          22
       8: aload_0
       9: invokevirtual #304                // Method net/neoforged/neoforge/event/entity/player/PlayerEvent$HarvestCheck.getEntity:()Lnet/minecraft/world/entity/player/Player;
      12: aload_0
      13: invokevirtual #308                // Method net/neoforged/neoforge/event/entity/player/PlayerEvent$HarvestCheck.getTargetBlock:()Lnet/minecraft/world/level/block/state/BlockState;
      16: invokestatic  #314                // Method artifacts/component/ability/ToolTierUpgrade.canHarvestWithTier:(Lnet/minecraft/world/entity/LivingEntity;Lnet/minecraft/world/level/block/state/BlockState;)Z
      19: ifeq          26
      22: iconst_1
      23: goto          27
      26: iconst_0
      27: invokevirtual #317                // Method net/neoforged/neoforge/event/entity/player/PlayerEvent$HarvestCheck.setCanHarvest:(Z)V
      30: return

  private static void onBlockDrops(net.neoforged.neoforge.event.level.BlockDropsEvent);
    descriptor: (Lnet/neoforged/neoforge/event/level/BlockDropsEvent;)V
    Code:
       0: aload_0
       1: invokevirtual #324                // Method net/neoforged/neoforge/event/level/BlockDropsEvent.getDrops:()Ljava/util/List;
       4: astore_1
       5: new           #326                // class org/apache/commons/lang3/mutable/MutableInt
       8: dup
       9: iconst_0
      10: invokespecial #328                // Method org/apache/commons/lang3/mutable/MutableInt."<init>":(I)V
      13: astore_2
      14: aload_1
      15: aload_0
      16: aload_2
      17: invokedynamic #338,  0            // InvokeDynamic #11:accept:(Lnet/neoforged/neoforge/event/level/BlockDropsEvent;Lorg/apache/commons/lang3/mutable/MutableInt;)Ljava/util/function/Consumer;
      22: invokeinterface #343,  2          // InterfaceMethod java/util/List.forEach:(Ljava/util/function/Consumer;)V
      27: aload_0
      28: aload_0
      29: invokevirtual #344                // Method net/neoforged/neoforge/event/level/BlockDropsEvent.getDroppedExperience:()I
      32: aload_2
      33: invokevirtual #348                // Method org/apache/commons/lang3/mutable/MutableInt.getValue:()Ljava/lang/Integer;
      36: invokevirtual #353                // Method java/lang/Integer.intValue:()I
      39: iadd
      40: invokevirtual #354                // Method net/neoforged/neoforge/event/level/BlockDropsEvent.setDroppedExperience:(I)V
      43: return

  private static void addAttributeTooltips(net.neoforged.neoforge.client.event.AddAttributeTooltipsEvent);
    descriptor: (Lnet/neoforged/neoforge/client/event/AddAttributeTooltipsEvent;)V
    Code:
       0: aload_0
       1: dup
       2: invokestatic  #366                // Method java/util/Objects.requireNonNull:(Ljava/lang/Object;)Ljava/lang/Object;
       5: pop
       6: invokedynamic #376,  0            // InvokeDynamic #12:accept:(Lnet/neoforged/neoforge/client/event/AddAttributeTooltipsEvent;)Ljava/util/function/Consumer;
      11: aload_0
      12: invokevirtual #381                // Method net/neoforged/neoforge/client/event/AddAttributeTooltipsEvent.getStack:()Lnet/minecraft/world/item/ItemStack;
      15: aload_0
      16: invokevirtual #385                // Method net/neoforged/neoforge/client/event/AddAttributeTooltipsEvent.getContext:()Lnet/neoforged/neoforge/common/util/AttributeTooltipContext;
      19: invokestatic  #390                // Method artifacts/util/TooltipHelper.addAttributeTooltips:(Ljava/util/function/Consumer;Lnet/minecraft/world/item/ItemStack;Lnet/minecraft/world/item/Item$TooltipContext;)V
      22: return

  public static void onPlayerSwim(be.florens.expandability.api.forge.PlayerSwimEvent);
    descriptor: (Lbe/florens/expandability/api/forge/PlayerSwimEvent;)V
    Code:
       0: aload_0
       1: invokevirtual #397                // Method be/florens/expandability/api/forge/PlayerSwimEvent.getResult:()Lbe/florens/expandability/api/EventResult;
       4: getstatic     #403                // Field be/florens/expandability/api/EventResult.PASS:Lbe/florens/expandability/api/EventResult;
       7: if_acmpne     21
      10: aload_0
      11: aload_0
      12: invokevirtual #404                // Method be/florens/expandability/api/forge/PlayerSwimEvent.getEntity:()Lnet/minecraft/world/entity/player/Player;
      15: invokestatic  #407                // Method artifacts/event/ArtifactHooks.onPlayerSwim:(Lnet/minecraft/world/entity/player/Player;)Lbe/florens/expandability/api/EventResult;
      18: invokevirtual #411                // Method be/florens/expandability/api/forge/PlayerSwimEvent.setResult:(Lbe/florens/expandability/api/EventResult;)V
      21: return

  private static void onAquaDashersFluidCollision(be.florens.expandability.api.forge.LivingFluidCollisionEvent);
    descriptor: (Lbe/florens/expandability/api/forge/LivingFluidCollisionEvent;)V
    Code:
       0: aload_0
       1: invokevirtual #415                // Method be/florens/expandability/api/forge/LivingFluidCollisionEvent.getEntity:()Lnet/minecraft/world/entity/LivingEntity;
       4: aload_0
       5: invokevirtual #419                // Method be/florens/expandability/api/forge/LivingFluidCollisionEvent.getFluidState:()Lnet/minecraft/world/level/material/FluidState;
       8: invokestatic  #423                // Method artifacts/event/ArtifactHooks.onFluidCollision:(Lnet/minecraft/world/entity/LivingEntity;Lnet/minecraft/world/level/material/FluidState;)Z
      11: ifeq          19
      14: aload_0
      15: iconst_1
      16: invokevirtual #426                // Method be/florens/expandability/api/forge/LivingFluidCollisionEvent.setColliding:(Z)V
      19: return

  private static void lambda$addAttributeTooltips$1(net.neoforged.neoforge.client.event.AddAttributeTooltipsEvent, net.minecraft.network.chat.Component);
    descriptor: (Lnet/neoforged/neoforge/client/event/AddAttributeTooltipsEvent;Lnet/minecraft/network/chat/Component;)V
    Code:
       0: aload_0
       1: iconst_1
       2: anewarray     #431                // class net/minecraft/network/chat/Component
       5: dup
       6: iconst_0
       7: aload_1
       8: aastore
       9: invokevirtual #435                // Method net/neoforged/neoforge/client/event/AddAttributeTooltipsEvent.addTooltipLines:([Lnet/minecraft/network/chat/Component;)V
      12: return

  private static void lambda$onBlockDrops$0(net.neoforged.neoforge.event.level.BlockDropsEvent, org.apache.commons.lang3.mutable.MutableInt, net.minecraft.world.entity.item.ItemEntity);
    descriptor: (Lnet/neoforged/neoforge/event/level/BlockDropsEvent;Lorg/apache/commons/lang3/mutable/MutableInt;Lnet/minecraft/world/entity/item/ItemEntity;)V
    Code:
       0: aload_2
       1: aload_2
       2: invokevirtual #440                // Method net/minecraft/world/entity/item/ItemEntity.getItem:()Lnet/minecraft/world/item/ItemStack;
       5: aload_0
       6: invokevirtual #443                // Method net/neoforged/neoforge/event/level/BlockDropsEvent.getBreaker:()Lnet/minecraft/world/entity/Entity;
       9: aload_0
      10: invokevirtual #446                // Method net/neoforged/neoforge/event/level/BlockDropsEvent.getState:()Lnet/minecraft/world/level/block/state/BlockState;
      13: aload_1
      14: dup
      15: invokestatic  #366                // Method java/util/Objects.requireNonNull:(Ljava/lang/Object;)Ljava/lang/Object;
      18: pop
      19: invokedynamic #456,  0            // InvokeDynamic #13:accept:(Lorg/apache/commons/lang3/mutable/MutableInt;)Ljava/util/function/Consumer;
      24: invokestatic  #460                // Method artifacts/event/ArtifactHooks.applySmeltOresAbility:(Lnet/minecraft/world/item/ItemStack;Lnet/minecraft/world/entity/Entity;Lnet/minecraft/world/level/block/state/BlockState;Ljava/util/function/Consumer;)Lnet/minecraft/world/item/ItemStack;
      27: invokevirtual #464                // Method net/minecraft/world/entity/item/ItemEntity.setItem:(Lnet/minecraft/world/item/ItemStack;)V
      30: return
}
