Compiled from "ItemInfinityBackpack.java"
public class com.buuz135.industrial.item.infinity.item.ItemInfinityBackpack extends com.buuz135.industrial.item.infinity.ItemInfinity {
  public static int POWER_CONSUMPTION;
    descriptor: I

  public static int FUEL_CONSUMPTION;
    descriptor: I

  public com.buuz135.industrial.item.infinity.item.ItemInfinityBackpack();
    descriptor: ()V
    Code:
       0: aload_0
       1: ldc           #1                  // String infinity_backpack
       3: getstatic     #3                  // Field com/buuz135/industrial/module/ModuleTool.TAB_TOOL:Lcom/hrznstudio/titanium/tab/TitaniumTab;
       6: new           #9                  // class net/minecraft/world/item/Item$Properties
       9: dup
      10: invokespecial #11                 // Method net/minecraft/world/item/Item$Properties."<init>":()V
      13: iconst_1
      14: invokevirtual #15                 // Method net/minecraft/world/item/Item$Properties.stacksTo:(I)Lnet/minecraft/world/item/Item$Properties;
      17: getstatic     #19                 // Field POWER_CONSUMPTION:I
      20: getstatic     #25                 // Field FUEL_CONSUMPTION:I
      23: iconst_0
      24: invokespecial #28                 // Method com/buuz135/industrial/item/infinity/ItemInfinity."<init>":(Ljava/lang/String;Lcom/hrznstudio/titanium/tab/TitaniumTab;Lnet/minecraft/world/item/Item$Properties;IIZ)V
      27: aload_0
      28: invokevirtual #33                 // Method disableArea:()V
      31: ldc           #36                 // class net/neoforged/neoforge/event/entity/player/ItemEntityPickupEvent$Pre
      33: invokestatic  #38                 // Method com/hrznstudio/titanium/event/handler/EventManager.forge:(Ljava/lang/Class;)Lcom/hrznstudio/titanium/event/handler/EventManager$FilteredEventManager;
      36: invokedynamic #44,  0             // InvokeDynamic #0:test:()Ljava/util/function/Predicate;
      41: invokevirtual #48                 // Method com/hrznstudio/titanium/event/handler/EventManager$FilteredEventManager.filter:(Ljava/util/function/Predicate;)Lcom/hrznstudio/titanium/event/handler/EventManager$FilteredEventManager;
      44: invokedynamic #54,  0             // InvokeDynamic #1:accept:()Ljava/util/function/Consumer;
      49: invokevirtual #58                 // Method com/hrznstudio/titanium/event/handler/EventManager$FilteredEventManager.process:(Ljava/util/function/Consumer;)Lcom/hrznstudio/titanium/event/handler/EventManager$FilteredEventManager;
      52: invokevirtual #62                 // Method com/hrznstudio/titanium/event/handler/EventManager$FilteredEventManager.subscribe:()V
      55: ldc           #65                 // class net/neoforged/neoforge/event/entity/player/PlayerXpEvent$PickupXp
      57: invokestatic  #38                 // Method com/hrznstudio/titanium/event/handler/EventManager.forge:(Ljava/lang/Class;)Lcom/hrznstudio/titanium/event/handler/EventManager$FilteredEventManager;
      60: invokedynamic #67,  0             // InvokeDynamic #2:test:()Ljava/util/function/Predicate;
      65: invokevirtual #48                 // Method com/hrznstudio/titanium/event/handler/EventManager$FilteredEventManager.filter:(Ljava/util/function/Predicate;)Lcom/hrznstudio/titanium/event/handler/EventManager$FilteredEventManager;
      68: invokedynamic #68,  0             // InvokeDynamic #3:accept:()Ljava/util/function/Consumer;
      73: invokevirtual #58                 // Method com/hrznstudio/titanium/event/handler/EventManager$FilteredEventManager.process:(Ljava/util/function/Consumer;)Lcom/hrznstudio/titanium/event/handler/EventManager$FilteredEventManager;
      76: invokevirtual #62                 // Method com/hrznstudio/titanium/event/handler/EventManager$FilteredEventManager.subscribe:()V
      79: return

  public static int getSlotSize(net.minecraft.world.item.ItemStack);
    descriptor: (Lnet/minecraft/world/item/ItemStack;)I
    Code:
       0: aload_0
       1: invokestatic  #69                 // Method getPowerFromStack:(Lnet/minecraft/world/item/ItemStack;)J
       4: invokestatic  #73                 // Method com/buuz135/industrial/item/infinity/InfinityTier.getTierBraquet:(J)Lorg/apache/commons/lang3/tuple/Pair;
       7: invokevirtual #79                 // Method org/apache/commons/lang3/tuple/Pair.getLeft:()Ljava/lang/Object;
      10: checkcast     #74                 // class com/buuz135/industrial/item/infinity/InfinityTier
      13: astore_1
      14: aload_1
      15: getstatic     #85                 // Field com/buuz135/industrial/item/infinity/InfinityTier.ARTIFACT:Lcom/buuz135/industrial/item/infinity/InfinityTier;
      18: if_acmpne     26
      21: ldc           #91                 // int 2147483647
      23: goto          42
      26: ldc2_w        #92                 // double 2048.0d
      29: ldc2_w        #94                 // double 8.0d
      32: aload_1
      33: invokevirtual #96                 // Method com/buuz135/industrial/item/infinity/InfinityTier.getRadius:()I
      36: i2d
      37: invokestatic  #100                // Method java/lang/Math.pow:(DD)D
      40: dmul
      41: d2i
      42: ireturn

  public static void sync(net.minecraft.world.level.Level, java.lang.String, net.minecraft.server.level.ServerPlayer);
    descriptor: (Lnet/minecraft/world/level/Level;Ljava/lang/String;Lnet/minecraft/server/level/ServerPlayer;)V
    Code:
       0: aload_0
       1: invokestatic  #106                // Method com/buuz135/industrial/worlddata/BackpackDataManager.getData:(Lnet/minecraft/world/level/LevelAccessor;)Lcom/buuz135/industrial/worlddata/BackpackDataManager;
       4: astore_3
       5: aload_3
       6: ifnull        45
       9: aload_3
      10: aload_1
      11: invokevirtual #112                // Method com/buuz135/industrial/worlddata/BackpackDataManager.getBackpack:(Ljava/lang/String;)Lcom/buuz135/industrial/worlddata/BackpackDataManager$BackpackItemHandler;
      14: astore        4
      16: aload         4
      18: ifnull        45
      21: getstatic     #116                // Field com/buuz135/industrial/IndustrialForegoing.NETWORK:Lcom/hrznstudio/titanium/network/NetworkHandler;
      24: new           #122                // class com/buuz135/industrial/proxy/network/BackpackSyncMessage
      27: dup
      28: aload_1
      29: aload         4
      31: aload_0
      32: invokevirtual #124                // Method net/minecraft/world/level/Level.registryAccess:()Lnet/minecraft/core/RegistryAccess;
      35: invokevirtual #130                // Method com/buuz135/industrial/worlddata/BackpackDataManager$BackpackItemHandler.serializeNBT:(Lnet/minecraft/core/HolderLookup$Provider;)Lnet/minecraft/nbt/CompoundTag;
      38: invokespecial #136                // Method com/buuz135/industrial/proxy/network/BackpackSyncMessage."<init>":(Ljava/lang/String;Lnet/minecraft/nbt/CompoundTag;)V
      41: aload_2
      42: invokevirtual #139                // Method com/hrznstudio/titanium/network/NetworkHandler.sendTo:(Lcom/hrznstudio/titanium/network/Message;Lnet/minecraft/server/level/ServerPlayer;)V
      45: return

  public static boolean isMagnetEnabled(net.minecraft.world.item.ItemStack);
    descriptor: (Lnet/minecraft/world/item/ItemStack;)Z
    Code:
       0: aload_0
       1: getstatic     #145                // Field com/buuz135/industrial/utils/IFAttachments.INFINITY_MAGNET_ENABLED:Ljava/util/function/Supplier;
       4: iconst_1
       5: invokestatic  #151                // Method java/lang/Boolean.valueOf:(Z)Ljava/lang/Boolean;
       8: invokevirtual #157                // Method net/minecraft/world/item/ItemStack.getOrDefault:(Ljava/util/function/Supplier;Ljava/lang/Object;)Ljava/lang/Object;
      11: checkcast     #152                // class java/lang/Boolean
      14: invokevirtual #163                // Method java/lang/Boolean.booleanValue:()Z
      17: ireturn

  public static void setMagnet(net.minecraft.world.item.ItemStack, boolean);
    descriptor: (Lnet/minecraft/world/item/ItemStack;Z)V
    Code:
       0: aload_0
       1: getstatic     #145                // Field com/buuz135/industrial/utils/IFAttachments.INFINITY_MAGNET_ENABLED:Ljava/util/function/Supplier;
       4: iload_1
       5: invokestatic  #151                // Method java/lang/Boolean.valueOf:(Z)Ljava/lang/Boolean;
       8: invokevirtual #167                // Method net/minecraft/world/item/ItemStack.set:(Ljava/util/function/Supplier;Ljava/lang/Object;)Ljava/lang/Object;
      11: pop
      12: return

  public static int getPickUpMode(net.minecraft.world.item.ItemStack);
    descriptor: (Lnet/minecraft/world/item/ItemStack;)I
    Code:
       0: aload_0
       1: getstatic     #170                // Field com/buuz135/industrial/utils/IFAttachments.INFINITY_BACKPACK_PICKUP_MODE:Ljava/util/function/Supplier;
       4: iconst_0
       5: invokestatic  #173                // Method java/lang/Integer.valueOf:(I)Ljava/lang/Integer;
       8: invokevirtual #157                // Method net/minecraft/world/item/ItemStack.getOrDefault:(Ljava/util/function/Supplier;Ljava/lang/Object;)Ljava/lang/Object;
      11: checkcast     #89                 // class java/lang/Integer
      14: invokevirtual #176                // Method java/lang/Integer.intValue:()I
      17: ireturn

  public static void setPickUpMode(net.minecraft.world.item.ItemStack, int);
    descriptor: (Lnet/minecraft/world/item/ItemStack;I)V
    Code:
       0: aload_0
       1: getstatic     #170                // Field com/buuz135/industrial/utils/IFAttachments.INFINITY_BACKPACK_PICKUP_MODE:Ljava/util/function/Supplier;
       4: iload_1
       5: invokestatic  #173                // Method java/lang/Integer.valueOf:(I)Ljava/lang/Integer;
       8: invokevirtual #167                // Method net/minecraft/world/item/ItemStack.set:(Ljava/util/function/Supplier;Ljava/lang/Object;)Ljava/lang/Object;
      11: pop
      12: return

  public static java.util.List<com.hrznstudio.titanium.network.locator.PlayerInventoryFinder$Target> findAllBackpacks(net.minecraft.world.entity.player.Player);
    descriptor: (Lnet/minecraft/world/entity/player/Player;)Ljava/util/List;
    Code:
       0: new           #179                // class java/util/ArrayList
       3: dup
       4: invokespecial #181                // Method java/util/ArrayList."<init>":()V
       7: astore_1
       8: getstatic     #182                // Field com/hrznstudio/titanium/network/locator/PlayerInventoryFinder.FINDERS:Ljava/util/HashMap;
      11: invokevirtual #188                // Method java/util/HashMap.keySet:()Ljava/util/Set;
      14: invokeinterface #194,  1          // InterfaceMethod java/util/Set.iterator:()Ljava/util/Iterator;
      19: astore_2
      20: aload_2
      21: invokeinterface #200,  1          // InterfaceMethod java/util/Iterator.hasNext:()Z
      26: ifeq          132
      29: aload_2
      30: invokeinterface #205,  1          // InterfaceMethod java/util/Iterator.next:()Ljava/lang/Object;
      35: checkcast     #208                // class java/lang/String
      38: astore_3
      39: getstatic     #182                // Field com/hrznstudio/titanium/network/locator/PlayerInventoryFinder.FINDERS:Ljava/util/HashMap;
      42: aload_3
      43: invokevirtual #210                // Method java/util/HashMap.get:(Ljava/lang/Object;)Ljava/lang/Object;
      46: checkcast     #183                // class com/hrznstudio/titanium/network/locator/PlayerInventoryFinder
      49: astore        4
      51: iconst_0
      52: istore        5
      54: iload         5
      56: aload         4
      58: invokevirtual #214                // Method com/hrznstudio/titanium/network/locator/PlayerInventoryFinder.getSlotAmountGetter:()Ljava/util/function/Function;
      61: aload_0
      62: invokeinterface #218,  2          // InterfaceMethod java/util/function/Function.apply:(Ljava/lang/Object;)Ljava/lang/Object;
      67: checkcast     #89                 // class java/lang/Integer
      70: invokevirtual #176                // Method java/lang/Integer.intValue:()I
      73: if_icmpge     129
      76: aload         4
      78: invokevirtual #223                // Method com/hrznstudio/titanium/network/locator/PlayerInventoryFinder.getStackGetter:()Ljava/util/function/BiFunction;
      81: aload_0
      82: iload         5
      84: invokestatic  #173                // Method java/lang/Integer.valueOf:(I)Ljava/lang/Integer;
      87: invokeinterface #227,  3          // InterfaceMethod java/util/function/BiFunction.apply:(Ljava/lang/Object;Ljava/lang/Object;)Ljava/lang/Object;
      92: checkcast     #158                // class net/minecraft/world/item/ItemStack
      95: invokevirtual #232                // Method net/minecraft/world/item/ItemStack.getItem:()Lnet/minecraft/world/item/Item;
      98: instanceof    #20                 // class com/buuz135/industrial/item/infinity/item/ItemInfinityBackpack
     101: ifeq          123
     104: aload_1
     105: new           #236                // class com/hrznstudio/titanium/network/locator/PlayerInventoryFinder$Target
     108: dup
     109: aload_3
     110: aload         4
     112: iload         5
     114: invokespecial #238                // Method com/hrznstudio/titanium/network/locator/PlayerInventoryFinder$Target."<init>":(Ljava/lang/String;Lcom/hrznstudio/titanium/network/locator/PlayerInventoryFinder;I)V
     117: invokeinterface #241,  2          // InterfaceMethod java/util/List.add:(Ljava/lang/Object;)Z
     122: pop
     123: iinc          5, 1
     126: goto          54
     129: goto          20
     132: aload_1
     133: invokestatic  #247                // Method java/util/Collections.unmodifiableList:(Ljava/util/List;)Ljava/util/List;
     136: areturn

  public static java.util.Optional<com.hrznstudio.titanium.network.locator.PlayerInventoryFinder$Target> findFirstBackpack(net.minecraft.world.entity.player.Player);
    descriptor: (Lnet/minecraft/world/entity/player/Player;)Ljava/util/Optional;
    Code:
       0: getstatic     #182                // Field com/hrznstudio/titanium/network/locator/PlayerInventoryFinder.FINDERS:Ljava/util/HashMap;
       3: invokevirtual #188                // Method java/util/HashMap.keySet:()Ljava/util/Set;
       6: invokeinterface #194,  1          // InterfaceMethod java/util/Set.iterator:()Ljava/util/Iterator;
      11: astore_1
      12: aload_1
      13: invokeinterface #200,  1          // InterfaceMethod java/util/Iterator.hasNext:()Z
      18: ifeq          117
      21: aload_1
      22: invokeinterface #205,  1          // InterfaceMethod java/util/Iterator.next:()Ljava/lang/Object;
      27: checkcast     #208                // class java/lang/String
      30: astore_2
      31: getstatic     #182                // Field com/hrznstudio/titanium/network/locator/PlayerInventoryFinder.FINDERS:Ljava/util/HashMap;
      34: aload_2
      35: invokevirtual #210                // Method java/util/HashMap.get:(Ljava/lang/Object;)Ljava/lang/Object;
      38: checkcast     #183                // class com/hrznstudio/titanium/network/locator/PlayerInventoryFinder
      41: astore_3
      42: iconst_0
      43: istore        4
      45: iload         4
      47: aload_3
      48: invokevirtual #214                // Method com/hrznstudio/titanium/network/locator/PlayerInventoryFinder.getSlotAmountGetter:()Ljava/util/function/Function;
      51: aload_0
      52: invokeinterface #218,  2          // InterfaceMethod java/util/function/Function.apply:(Ljava/lang/Object;)Ljava/lang/Object;
      57: checkcast     #89                 // class java/lang/Integer
      60: invokevirtual #176                // Method java/lang/Integer.intValue:()I
      63: if_icmpge     114
      66: aload_3
      67: invokevirtual #223                // Method com/hrznstudio/titanium/network/locator/PlayerInventoryFinder.getStackGetter:()Ljava/util/function/BiFunction;
      70: aload_0
      71: iload         4
      73: invokestatic  #173                // Method java/lang/Integer.valueOf:(I)Ljava/lang/Integer;
      76: invokeinterface #227,  3          // InterfaceMethod java/util/function/BiFunction.apply:(Ljava/lang/Object;Ljava/lang/Object;)Ljava/lang/Object;
      81: checkcast     #158                // class net/minecraft/world/item/ItemStack
      84: invokevirtual #232                // Method net/minecraft/world/item/ItemStack.getItem:()Lnet/minecraft/world/item/Item;
      87: instanceof    #20                 // class com/buuz135/industrial/item/infinity/item/ItemInfinityBackpack
      90: ifeq          108
      93: new           #236                // class com/hrznstudio/titanium/network/locator/PlayerInventoryFinder$Target
      96: dup
      97: aload_2
      98: aload_3
      99: iload         4
     101: invokespecial #238                // Method com/hrznstudio/titanium/network/locator/PlayerInventoryFinder$Target."<init>":(Ljava/lang/String;Lcom/hrznstudio/titanium/network/locator/PlayerInventoryFinder;I)V
     104: invokestatic  #253                // Method java/util/Optional.of:(Ljava/lang/Object;)Ljava/util/Optional;
     107: areturn
     108: iinc          4, 1
     111: goto          45
     114: goto          12
     117: invokestatic  #259                // Method java/util/Optional.empty:()Ljava/util/Optional;
     120: areturn

  private static void updateBlockEntityComponents(net.minecraft.world.level.Level, net.minecraft.core.BlockPos, net.minecraft.world.item.ItemStack);
    descriptor: (Lnet/minecraft/world/level/Level;Lnet/minecraft/core/BlockPos;Lnet/minecraft/world/item/ItemStack;)V
    Code:
       0: aload_0
       1: aload_1
       2: invokevirtual #263                // Method net/minecraft/world/level/Level.getBlockEntity:(Lnet/minecraft/core/BlockPos;)Lnet/minecraft/world/level/block/entity/BlockEntity;
       5: astore_3
       6: aload_3
       7: ifnull        19
      10: aload_3
      11: aload_2
      12: invokevirtual #267                // Method net/minecraft/world/level/block/entity/BlockEntity.applyComponentsFromItemStack:(Lnet/minecraft/world/item/ItemStack;)V
      15: aload_3
      16: invokevirtual #273                // Method net/minecraft/world/level/block/entity/BlockEntity.setChanged:()V
      19: return

  public net.minecraft.world.InteractionResultHolder<net.minecraft.world.item.ItemStack> use(net.minecraft.world.level.Level, net.minecraft.world.entity.player.Player, net.minecraft.world.InteractionHand);
    descriptor: (Lnet/minecraft/world/level/Level;Lnet/minecraft/world/entity/player/Player;Lnet/minecraft/world/InteractionHand;)Lnet/minecraft/world/InteractionResultHolder;
    Code:
       0: aload_2
       1: aload_3
       2: invokevirtual #276                // Method net/minecraft/world/entity/player/Player.getItemInHand:(Lnet/minecraft/world/InteractionHand;)Lnet/minecraft/world/item/ItemStack;
       5: astore        4
       7: aload_2
       8: instanceof    #282                // class net/minecraft/server/level/ServerPlayer
      11: ifeq          127
      14: aload_2
      15: checkcast     #282                // class net/minecraft/server/level/ServerPlayer
      18: astore        5
      20: aload         4
      22: getstatic     #284                // Field com/buuz135/industrial/utils/IFAttachments.INFINITY_BACKPACK_ID:Ljava/util/function/Supplier;
      25: invokevirtual #287                // Method net/minecraft/world/item/ItemStack.has:(Ljava/util/function/Supplier;)Z
      28: ifne          59
      31: invokestatic  #291                // Method java/util/UUID.randomUUID:()Ljava/util/UUID;
      34: astore        6
      36: aload_1
      37: invokestatic  #106                // Method com/buuz135/industrial/worlddata/BackpackDataManager.getData:(Lnet/minecraft/world/level/LevelAccessor;)Lcom/buuz135/industrial/worlddata/BackpackDataManager;
      40: aload         6
      42: invokevirtual #297                // Method com/buuz135/industrial/worlddata/BackpackDataManager.createBackPack:(Ljava/util/UUID;)V
      45: aload         4
      47: getstatic     #284                // Field com/buuz135/industrial/utils/IFAttachments.INFINITY_BACKPACK_ID:Ljava/util/function/Supplier;
      50: aload         6
      52: invokevirtual #301                // Method java/util/UUID.toString:()Ljava/lang/String;
      55: invokevirtual #167                // Method net/minecraft/world/item/ItemStack.set:(Ljava/util/function/Supplier;Ljava/lang/Object;)Ljava/lang/Object;
      58: pop
      59: aload         4
      61: getstatic     #284                // Field com/buuz135/industrial/utils/IFAttachments.INFINITY_BACKPACK_ID:Ljava/util/function/Supplier;
      64: invokevirtual #305                // Method net/minecraft/world/item/ItemStack.get:(Ljava/util/function/Supplier;)Ljava/lang/Object;
      67: checkcast     #208                // class java/lang/String
      70: astore        6
      72: getstatic     #116                // Field com/buuz135/industrial/IndustrialForegoing.NETWORK:Lcom/hrznstudio/titanium/network/NetworkHandler;
      75: new           #308                // class com/buuz135/industrial/proxy/network/BackpackOpenedMessage
      78: dup
      79: aload_2
      80: invokevirtual #310                // Method net/minecraft/world/entity/player/Player.getInventory:()Lnet/minecraft/world/entity/player/Inventory;
      83: getfield      #314                // Field net/minecraft/world/entity/player/Inventory.selected:I
      86: getstatic     #319                // Field com/hrznstudio/titanium/network/locator/PlayerInventoryFinder.MAIN:Ljava/lang/String;
      89: invokespecial #323                // Method com/buuz135/industrial/proxy/network/BackpackOpenedMessage."<init>":(ILjava/lang/String;)V
      92: aload         5
      94: invokevirtual #139                // Method com/hrznstudio/titanium/network/NetworkHandler.sendTo:(Lcom/hrznstudio/titanium/network/Message;Lnet/minecraft/server/level/ServerPlayer;)V
      97: aload_1
      98: aload         6
     100: aload         5
     102: invokestatic  #326                // Method sync:(Lnet/minecraft/world/level/Level;Ljava/lang/String;Lnet/minecraft/server/level/ServerPlayer;)V
     105: aload         5
     107: aload_0
     108: aload_3
     109: invokedynamic #330,  0            // InvokeDynamic #4:accept:(Lnet/minecraft/world/InteractionHand;)Ljava/util/function/Consumer;
     114: invokevirtual #333                // Method net/minecraft/server/level/ServerPlayer.openMenu:(Lnet/minecraft/world/MenuProvider;Ljava/util/function/Consumer;)Ljava/util/OptionalInt;
     117: pop
     118: aload_2
     119: aload_3
     120: invokevirtual #276                // Method net/minecraft/world/entity/player/Player.getItemInHand:(Lnet/minecraft/world/InteractionHand;)Lnet/minecraft/world/item/ItemStack;
     123: invokestatic  #337                // Method net/minecraft/world/InteractionResultHolder.success:(Ljava/lang/Object;)Lnet/minecraft/world/InteractionResultHolder;
     126: areturn
     127: getstatic     #343                // Field com/buuz135/industrial/IndustrialForegoing.CAT_EARS:Lcom/hrznstudio/titanium/reward/Reward;
     130: invokevirtual #347                // Method com/hrznstudio/titanium/reward/Reward.getPlayers:()Ljava/util/List;
     133: aload_2
     134: invokevirtual #353                // Method net/minecraft/world/entity/player/Player.getUUID:()Ljava/util/UUID;
     137: invokeinterface #356,  2          // InterfaceMethod java/util/List.contains:(Ljava/lang/Object;)Z
     142: ifeq          161
     145: aload_2
     146: aload_3
     147: invokevirtual #276                // Method net/minecraft/world/entity/player/Player.getItemInHand:(Lnet/minecraft/world/InteractionHand;)Lnet/minecraft/world/item/ItemStack;
     150: getstatic     #359                // Field com/buuz135/industrial/utils/IFAttachments.INFINITY_ITEM_SPECIAL:Ljava/util/function/Supplier;
     153: iconst_1
     154: invokestatic  #151                // Method java/lang/Boolean.valueOf:(Z)Ljava/lang/Boolean;
     157: invokevirtual #167                // Method net/minecraft/world/item/ItemStack.set:(Ljava/util/function/Supplier;Ljava/lang/Object;)Ljava/lang/Object;
     160: pop
     161: aload_0
     162: aload_1
     163: aload_2
     164: aload_3
     165: invokespecial #362                // Method com/buuz135/industrial/item/infinity/ItemInfinity.use:(Lnet/minecraft/world/level/Level;Lnet/minecraft/world/entity/player/Player;Lnet/minecraft/world/InteractionHand;)Lnet/minecraft/world/InteractionResultHolder;
     168: areturn

  public void inventoryTick(net.minecraft.world.item.ItemStack, net.minecraft.world.level.Level, net.minecraft.world.entity.Entity, int, boolean);
    descriptor: (Lnet/minecraft/world/item/ItemStack;Lnet/minecraft/world/level/Level;Lnet/minecraft/world/entity/Entity;IZ)V
    Code:
       0: aload_1
       1: invokestatic  #366                // Method isMagnetEnabled:(Lnet/minecraft/world/item/ItemStack;)Z
       4: ifeq          202
       7: aload_3
       8: invokevirtual #370                // Method net/minecraft/world/entity/Entity.level:()Lnet/minecraft/world/level/Level;
      11: ldc_w         #376                // class net/minecraft/world/entity/item/ItemEntity
      14: new           #378                // class net/minecraft/world/phys/AABB
      17: dup
      18: aload_3
      19: invokevirtual #380                // Method net/minecraft/world/entity/Entity.getX:()D
      22: aload_3
      23: invokevirtual #384                // Method net/minecraft/world/entity/Entity.getY:()D
      26: aload_3
      27: invokevirtual #384                // Method net/minecraft/world/entity/Entity.getY:()D
      30: aload_3
      31: invokevirtual #380                // Method net/minecraft/world/entity/Entity.getX:()D
      34: aload_3
      35: invokevirtual #384                // Method net/minecraft/world/entity/Entity.getY:()D
      38: aload_3
      39: invokevirtual #387                // Method net/minecraft/world/entity/Entity.getZ:()D
      42: invokespecial #390                // Method net/minecraft/world/phys/AABB."<init>":(DDDDDD)V
      45: ldc2_w        #393                // double 5.0d
      48: invokevirtual #395                // Method net/minecraft/world/phys/AABB.inflate:(D)Lnet/minecraft/world/phys/AABB;
      51: invokevirtual #399                // Method net/minecraft/world/level/Level.getEntitiesOfClass:(Ljava/lang/Class;Lnet/minecraft/world/phys/AABB;)Ljava/util/List;
      54: invokeinterface #403,  1          // InterfaceMethod java/util/List.iterator:()Ljava/util/Iterator;
      59: astore        6
      61: aload         6
      63: invokeinterface #200,  1          // InterfaceMethod java/util/Iterator.hasNext:()Z
      68: ifeq          202
      71: aload         6
      73: invokeinterface #205,  1          // InterfaceMethod java/util/Iterator.next:()Ljava/lang/Object;
      78: checkcast     #376                // class net/minecraft/world/entity/item/ItemEntity
      81: astore        7
      83: aload_3
      84: invokevirtual #370                // Method net/minecraft/world/entity/Entity.level:()Lnet/minecraft/world/level/Level;
      87: getfield      #404                // Field net/minecraft/world/level/Level.isClientSide:Z
      90: ifeq          161
      93: aload_0
      94: aload_1
      95: invokevirtual #408                // Method enoughFuel:(Lnet/minecraft/world/item/ItemStack;)Z
      98: ifeq          161
     101: aload         7
     103: invokevirtual #411                // Method net/minecraft/world/entity/item/ItemEntity.onGround:()Z
     106: ifeq          199
     109: aload_2
     110: getfield      #414                // Field net/minecraft/world/level/Level.random:Lnet/minecraft/util/RandomSource;
     113: iconst_5
     114: invokeinterface #418,  2          // InterfaceMethod net/minecraft/util/RandomSource.nextInt:(I)I
     119: iconst_1
     120: if_icmpge     199
     123: aload         7
     125: invokevirtual #424                // Method net/minecraft/world/entity/item/ItemEntity.level:()Lnet/minecraft/world/level/Level;
     128: getstatic     #425                // Field net/minecraft/core/particles/ParticleTypes.PORTAL:Lnet/minecraft/core/particles/SimpleParticleType;
     131: aload         7
     133: invokevirtual #431                // Method net/minecraft/world/entity/item/ItemEntity.getX:()D
     136: aload         7
     138: invokevirtual #432                // Method net/minecraft/world/entity/item/ItemEntity.getY:()D
     141: ldc2_w        #433                // double 0.5d
     144: dadd
     145: aload         7
     147: invokevirtual #435                // Method net/minecraft/world/entity/item/ItemEntity.getZ:()D
     150: dconst_0
     151: ldc2_w        #436                // double -0.5d
     154: dconst_0
     155: invokevirtual #438                // Method net/minecraft/world/level/Level.addParticle:(Lnet/minecraft/core/particles/ParticleOptions;DDDDDD)V
     158: goto          199
     161: aload         7
     163: invokevirtual #442                // Method net/minecraft/world/entity/item/ItemEntity.hasPickUpDelay:()Z
     166: ifne          199
     169: aload_0
     170: aload_1
     171: invokevirtual #408                // Method enoughFuel:(Lnet/minecraft/world/item/ItemStack;)Z
     174: ifeq          199
     177: aload         7
     179: aload_3
     180: invokevirtual #380                // Method net/minecraft/world/entity/Entity.getX:()D
     183: aload_3
     184: invokevirtual #384                // Method net/minecraft/world/entity/Entity.getY:()D
     187: aload_3
     188: invokevirtual #387                // Method net/minecraft/world/entity/Entity.getZ:()D
     191: invokevirtual #445                // Method net/minecraft/world/entity/item/ItemEntity.teleportTo:(DDD)V
     194: aload_0
     195: aload_1
     196: invokevirtual #449                // Method consumeFuel:(Lnet/minecraft/world/item/ItemStack;)V
     199: goto          61
     202: aload_3
     203: invokevirtual #370                // Method net/minecraft/world/entity/Entity.level:()Lnet/minecraft/world/level/Level;
     206: getfield      #404                // Field net/minecraft/world/level/Level.isClientSide:Z
     209: ifne          653
     212: aload_3
     213: instanceof    #277                // class net/minecraft/world/entity/player/Player
     216: ifeq          653
     219: aload_0
     220: aload_1
     221: invokevirtual #408                // Method enoughFuel:(Lnet/minecraft/world/item/ItemStack;)Z
     224: ifeq          369
     227: aload_1
     228: getstatic     #452                // Field net/neoforged/neoforge/capabilities/Capabilities$FluidHandler.ITEM:Lnet/neoforged/neoforge/capabilities/ItemCapability;
     231: invokevirtual #458                // Method net/minecraft/world/item/ItemStack.getCapability:(Lnet/neoforged/neoforge/capabilities/ItemCapability;)Ljava/lang/Object;
     234: checkcast     #462                // class net/neoforged/neoforge/fluids/capability/IFluidHandlerItem
     237: astore        6
     239: aload_3
     240: checkcast     #277                // class net/minecraft/world/entity/player/Player
     243: invokevirtual #464                // Method net/minecraft/world/entity/player/Player.getFoodData:()Lnet/minecraft/world/food/FoodData;
     246: invokevirtual #468                // Method net/minecraft/world/food/FoodData.needsFood:()Z
     249: ifne          269
     252: aload_3
     253: checkcast     #277                // class net/minecraft/world/entity/player/Player
     256: invokevirtual #464                // Method net/minecraft/world/entity/player/Player.getFoodData:()Lnet/minecraft/world/food/FoodData;
     259: invokevirtual #473                // Method net/minecraft/world/food/FoodData.getSaturationLevel:()F
     262: ldc_w         #477                // float 10.0f
     265: fcmpg
     266: ifge          369
     269: aload         6
     271: ifnull        369
     274: iconst_0
     275: istore        7
     277: iload         7
     279: aload         6
     281: invokeinterface #478,  1          // InterfaceMethod net/neoforged/neoforge/fluids/capability/IFluidHandlerItem.getTanks:()I
     286: if_icmpge     369
     289: aload         6
     291: iload         7
     293: invokeinterface #481,  2          // InterfaceMethod net/neoforged/neoforge/fluids/capability/IFluidHandlerItem.getFluidInTank:(I)Lnet/neoforged/neoforge/fluids/FluidStack;
     298: astore        8
     300: aload         8
     302: invokevirtual #485                // Method net/neoforged/neoforge/fluids/FluidStack.isEmpty:()Z
     305: ifne          363
     308: aload         8
     310: invokevirtual #490                // Method net/neoforged/neoforge/fluids/FluidStack.getAmount:()I
     313: sipush        400
     316: if_icmplt     363
     319: aload         6
     321: new           #486                // class net/neoforged/neoforge/fluids/FluidStack
     324: dup
     325: getstatic     #493                // Field com/buuz135/industrial/module/ModuleCore.MEAT:Lcom/hrznstudio/titanium/fluid/TitaniumFluidInstance;
     328: invokevirtual #499                // Method com/hrznstudio/titanium/fluid/TitaniumFluidInstance.getSourceFluid:()Lnet/neoforged/neoforge/registries/DeferredHolder;
     331: sipush        400
     334: invokespecial #505                // Method net/neoforged/neoforge/fluids/FluidStack."<init>":(Lnet/minecraft/core/Holder;I)V
     337: getstatic     #508                // Field net/neoforged/neoforge/fluids/capability/IFluidHandler$FluidAction.EXECUTE:Lnet/neoforged/neoforge/fluids/capability/IFluidHandler$FluidAction;
     340: invokeinterface #514,  3          // InterfaceMethod net/neoforged/neoforge/fluids/capability/IFluidHandlerItem.drain:(Lnet/neoforged/neoforge/fluids/FluidStack;Lnet/neoforged/neoforge/fluids/capability/IFluidHandler$FluidAction;)Lnet/neoforged/neoforge/fluids/FluidStack;
     345: pop
     346: aload_3
     347: checkcast     #277                // class net/minecraft/world/entity/player/Player
     350: invokevirtual #464                // Method net/minecraft/world/entity/player/Player.getFoodData:()Lnet/minecraft/world/food/FoodData;
     353: iconst_1
     354: fconst_1
     355: invokevirtual #518                // Method net/minecraft/world/food/FoodData.eat:(IF)V
     358: aload_0
     359: aload_1
     360: invokevirtual #449                // Method consumeFuel:(Lnet/minecraft/world/item/ItemStack;)V
     363: iinc          7, 1
     366: goto          277
     369: aload_3
     370: invokevirtual #370                // Method net/minecraft/world/entity/Entity.level:()Lnet/minecraft/world/level/Level;
     373: invokevirtual #522                // Method net/minecraft/world/level/Level.getGameTime:()J
     376: ldc2_w        #526                // long 10l
     379: lrem
     380: lconst_0
     381: lcmp
     382: ifne          653
     385: aload_3
     386: invokevirtual #370                // Method net/minecraft/world/entity/Entity.level:()Lnet/minecraft/world/level/Level;
     389: invokestatic  #106                // Method com/buuz135/industrial/worlddata/BackpackDataManager.getData:(Lnet/minecraft/world/level/LevelAccessor;)Lcom/buuz135/industrial/worlddata/BackpackDataManager;
     392: astore        6
     394: aload         6
     396: ifnull        653
     399: aload_1
     400: getstatic     #284                // Field com/buuz135/industrial/utils/IFAttachments.INFINITY_BACKPACK_ID:Ljava/util/function/Supplier;
     403: invokevirtual #287                // Method net/minecraft/world/item/ItemStack.has:(Ljava/util/function/Supplier;)Z
     406: ifeq          653
     409: aload         6
     411: aload_1
     412: getstatic     #284                // Field com/buuz135/industrial/utils/IFAttachments.INFINITY_BACKPACK_ID:Ljava/util/function/Supplier;
     415: invokevirtual #305                // Method net/minecraft/world/item/ItemStack.get:(Ljava/util/function/Supplier;)Ljava/lang/Object;
     418: checkcast     #208                // class java/lang/String
     421: invokevirtual #112                // Method com/buuz135/industrial/worlddata/BackpackDataManager.getBackpack:(Ljava/lang/String;)Lcom/buuz135/industrial/worlddata/BackpackDataManager$BackpackItemHandler;
     424: astore        7
     426: aload         7
     428: ifnull        653
     431: aload_1
     432: invokestatic  #528                // Method getSlotSize:(Lnet/minecraft/world/item/ItemStack;)I
     435: aload         7
     437: iconst_0
     438: invokevirtual #532                // Method com/buuz135/industrial/worlddata/BackpackDataManager$BackpackItemHandler.getSlotLimit:(I)I
     441: if_icmpeq     453
     444: aload         7
     446: aload_1
     447: invokestatic  #528                // Method getSlotSize:(Lnet/minecraft/world/item/ItemStack;)I
     450: invokevirtual #535                // Method com/buuz135/industrial/worlddata/BackpackDataManager$BackpackItemHandler.setMaxAmount:(I)V
     453: aload_0
     454: aload_1
     455: invokevirtual #408                // Method enoughFuel:(Lnet/minecraft/world/item/ItemStack;)Z
     458: ifeq          653
     461: iconst_0
     462: istore        8
     464: iload         8
     466: bipush        32
     468: if_icmpge     653
     471: aload         7
     473: iload         8
     475: invokevirtual #539                // Method com/buuz135/industrial/worlddata/BackpackDataManager$BackpackItemHandler.getStackInSlot:(I)Lnet/minecraft/world/item/ItemStack;
     478: invokevirtual #543                // Method net/minecraft/world/item/ItemStack.isEmpty:()Z
     481: ifne          647
     484: aload         7
     486: iload         8
     488: invokevirtual #544                // Method com/buuz135/industrial/worlddata/BackpackDataManager$BackpackItemHandler.getSlotDefinition:(I)Lcom/buuz135/industrial/worlddata/BackpackDataManager$SlotDefinition;
     491: invokevirtual #548                // Method com/buuz135/industrial/worlddata/BackpackDataManager$SlotDefinition.isRefillItems:()Z
     494: ifeq          647
     497: aload_3
     498: checkcast     #277                // class net/minecraft/world/entity/player/Player
     501: invokevirtual #310                // Method net/minecraft/world/entity/player/Player.getInventory:()Lnet/minecraft/world/entity/player/Inventory;
     504: astore        9
     506: iconst_0
     507: istore        10
     509: iload         10
     511: bipush        35
     513: if_icmpgt     647
     516: aload         9
     518: iload         10
     520: invokevirtual #553                // Method net/minecraft/world/entity/player/Inventory.getItem:(I)Lnet/minecraft/world/item/ItemStack;
     523: astore        11
     525: aload         11
     527: invokevirtual #543                // Method net/minecraft/world/item/ItemStack.isEmpty:()Z
     530: ifne          641
     533: aload         11
     535: invokevirtual #555                // Method net/minecraft/world/item/ItemStack.getCount:()I
     538: aload         11
     540: invokevirtual #558                // Method net/minecraft/world/item/ItemStack.getMaxStackSize:()I
     543: if_icmpge     641
     546: aload         7
     548: iload         8
     550: aload         11
     552: invokevirtual #561                // Method com/buuz135/industrial/worlddata/BackpackDataManager$BackpackItemHandler.isItemValid:(ILnet/minecraft/world/item/ItemStack;)Z
     555: ifeq          641
     558: aload_0
     559: aload_1
     560: invokevirtual #408                // Method enoughFuel:(Lnet/minecraft/world/item/ItemStack;)Z
     563: ifeq          641
     566: aload         11
     568: invokevirtual #558                // Method net/minecraft/world/item/ItemStack.getMaxStackSize:()I
     571: aload         11
     573: invokevirtual #555                // Method net/minecraft/world/item/ItemStack.getCount:()I
     576: isub
     577: istore        12
     579: aload         7
     581: iload         8
     583: iload         12
     585: iconst_0
     586: invokevirtual #565                // Method com/buuz135/industrial/worlddata/BackpackDataManager$BackpackItemHandler.extractItem:(IIZ)Lnet/minecraft/world/item/ItemStack;
     589: astore        13
     591: aload         11
     593: aload         11
     595: invokevirtual #555                // Method net/minecraft/world/item/ItemStack.getCount:()I
     598: aload         13
     600: invokevirtual #555                // Method net/minecraft/world/item/ItemStack.getCount:()I
     603: iadd
     604: invokevirtual #569                // Method net/minecraft/world/item/ItemStack.setCount:(I)V
     607: aload_3
     608: instanceof    #282                // class net/minecraft/server/level/ServerPlayer
     611: ifeq          635
     614: aload_3
     615: invokevirtual #370                // Method net/minecraft/world/entity/Entity.level:()Lnet/minecraft/world/level/Level;
     618: aload_1
     619: getstatic     #284                // Field com/buuz135/industrial/utils/IFAttachments.INFINITY_BACKPACK_ID:Ljava/util/function/Supplier;
     622: invokevirtual #305                // Method net/minecraft/world/item/ItemStack.get:(Ljava/util/function/Supplier;)Ljava/lang/Object;
     625: checkcast     #208                // class java/lang/String
     628: aload_3
     629: checkcast     #282                // class net/minecraft/server/level/ServerPlayer
     632: invokestatic  #326                // Method sync:(Lnet/minecraft/world/level/Level;Ljava/lang/String;Lnet/minecraft/server/level/ServerPlayer;)V
     635: aload_0
     636: aload_1
     637: invokevirtual #449                // Method consumeFuel:(Lnet/minecraft/world/item/ItemStack;)V
     640: return
     641: iinc          10, 1
     644: goto          509
     647: iinc          8, 1
     650: goto          464
     653: aload_0
     654: aload_1
     655: aload_2
     656: aload_3
     657: iload         4
     659: iload         5
     661: invokespecial #572                // Method com/buuz135/industrial/item/infinity/ItemInfinity.inventoryTick:(Lnet/minecraft/world/item/ItemStack;Lnet/minecraft/world/level/Level;Lnet/minecraft/world/entity/Entity;IZ)V
     664: return

  public com.hrznstudio.titanium.api.IFactory<com.buuz135.industrial.item.infinity.InfinityTankStorage> getTankConstructor(net.minecraft.world.item.ItemStack);
    descriptor: (Lnet/minecraft/world/item/ItemStack;)Lcom/hrznstudio/titanium/api/IFactory;
    Code:
       0: bipush        88
       2: istore_2
       3: aload_1
       4: iload_2
       5: invokedynamic #576,  0            // InvokeDynamic #5:create:(Lnet/minecraft/world/item/ItemStack;I)Lcom/hrznstudio/titanium/api/IFactory;
      10: areturn

  public com.hrznstudio.titanium.api.IFactory<com.buuz135.industrial.item.infinity.InfinityEnergyStorage> getEnergyConstructor(net.minecraft.world.item.ItemStack);
    descriptor: (Lnet/minecraft/world/item/ItemStack;)Lcom/hrznstudio/titanium/api/IFactory;
    Code:
       0: aload_0
       1: aload_1
       2: invokedynamic #580,  0            // InvokeDynamic #6:create:(Lcom/buuz135/industrial/item/infinity/item/ItemInfinityBackpack;Lnet/minecraft/world/item/ItemStack;)Lcom/hrznstudio/titanium/api/IFactory;
       7: areturn

  public void handleButtonMessage(int, net.minecraft.world.entity.player.Player, net.minecraft.nbt.CompoundTag, net.minecraft.world.item.ItemStack);
    descriptor: (ILnet/minecraft/world/entity/player/Player;Lnet/minecraft/nbt/CompoundTag;Lnet/minecraft/world/item/ItemStack;)V
    Code:
       0: iload_1
       1: iconst_4
       2: if_icmpne     464
       5: aload_2
       6: instanceof    #282                // class net/minecraft/server/level/ServerPlayer
       9: ifeq          464
      12: aload_3
      13: ldc_w         #583                // String Id
      16: invokevirtual #585                // Method net/minecraft/nbt/CompoundTag.getString:(Ljava/lang/String;)Ljava/lang/String;
      19: astore        5
      21: aload_2
      22: getfield      #591                // Field net/minecraft/world/entity/player/Player.containerMenu:Lnet/minecraft/world/inventory/AbstractContainerMenu;
      25: invokevirtual #595                // Method net/minecraft/world/inventory/AbstractContainerMenu.getCarried:()Lnet/minecraft/world/item/ItemStack;
      28: astore        6
      30: aload_3
      31: ldc_w         #601                // String Shift
      34: invokevirtual #603                // Method net/minecraft/nbt/CompoundTag.getBoolean:(Ljava/lang/String;)Z
      37: istore        7
      39: aload_3
      40: ldc_w         #607                // String Ctrl
      43: invokevirtual #603                // Method net/minecraft/nbt/CompoundTag.getBoolean:(Ljava/lang/String;)Z
      46: istore        8
      48: aload_3
      49: ldc_w         #609                // String Button
      52: invokevirtual #611                // Method net/minecraft/nbt/CompoundTag.getInt:(Ljava/lang/String;)I
      55: istore        9
      57: aload_3
      58: ldc_w         #615                // String Slot
      61: invokevirtual #611                // Method net/minecraft/nbt/CompoundTag.getInt:(Ljava/lang/String;)I
      64: istore        10
      66: aload_2
      67: invokevirtual #617                // Method net/minecraft/world/entity/player/Player.level:()Lnet/minecraft/world/level/Level;
      70: invokestatic  #106                // Method com/buuz135/industrial/worlddata/BackpackDataManager.getData:(Lnet/minecraft/world/level/LevelAccessor;)Lcom/buuz135/industrial/worlddata/BackpackDataManager;
      73: astore        11
      75: aload         11
      77: aload         5
      79: invokevirtual #112                // Method com/buuz135/industrial/worlddata/BackpackDataManager.getBackpack:(Ljava/lang/String;)Lcom/buuz135/industrial/worlddata/BackpackDataManager$BackpackItemHandler;
      82: astore        12
      84: getstatic     #618                // Field net/minecraft/world/item/ItemStack.EMPTY:Lnet/minecraft/world/item/ItemStack;
      87: astore        13
      89: iconst_0
      90: istore        14
      92: iload         9
      94: iconst_2
      95: if_icmpne     164
      98: aload         12
     100: iload         10
     102: iconst_1
     103: iconst_1
     104: invokevirtual #565                // Method com/buuz135/industrial/worlddata/BackpackDataManager$BackpackItemHandler.extractItem:(IIZ)Lnet/minecraft/world/item/ItemStack;
     107: astore        15
     109: aload         15
     111: invokevirtual #543                // Method net/minecraft/world/item/ItemStack.isEmpty:()Z
     114: ifne          161
     117: aload         6
     119: invokevirtual #543                // Method net/minecraft/world/item/ItemStack.isEmpty:()Z
     122: ifne          135
     125: aload         15
     127: aload         6
     129: invokestatic  #622                // Method net/minecraft/world/item/ItemStack.isSameItemSameComponents:(Lnet/minecraft/world/item/ItemStack;Lnet/minecraft/world/item/ItemStack;)Z
     132: ifeq          161
     135: aload         12
     137: iload         10
     139: iconst_1
     140: iconst_0
     141: invokevirtual #565                // Method com/buuz135/industrial/worlddata/BackpackDataManager$BackpackItemHandler.extractItem:(IIZ)Lnet/minecraft/world/item/ItemStack;
     144: astore        13
     146: aload         13
     148: aload         6
     150: invokevirtual #555                // Method net/minecraft/world/item/ItemStack.getCount:()I
     153: iconst_1
     154: iadd
     155: invokevirtual #569                // Method net/minecraft/world/item/ItemStack.setCount:(I)V
     158: iconst_1
     159: istore        14
     161: goto          427
     164: aload         6
     166: invokevirtual #543                // Method net/minecraft/world/item/ItemStack.isEmpty:()Z
     169: ifeq          365
     172: aload         12
     174: iload         10
     176: invokevirtual #539                // Method com/buuz135/industrial/worlddata/BackpackDataManager$BackpackItemHandler.getStackInSlot:(I)Lnet/minecraft/world/item/ItemStack;
     179: invokevirtual #558                // Method net/minecraft/world/item/ItemStack.getMaxStackSize:()I
     182: istore        15
     184: iload         9
     186: ifne          304
     189: iload         8
     191: ifeq          224
     194: aload         12
     196: iload         10
     198: invokevirtual #544                // Method com/buuz135/industrial/worlddata/BackpackDataManager$BackpackItemHandler.getSlotDefinition:(I)Lcom/buuz135/industrial/worlddata/BackpackDataManager$SlotDefinition;
     201: astore        16
     203: aload         16
     205: aload         16
     207: invokevirtual #626                // Method com/buuz135/industrial/worlddata/BackpackDataManager$SlotDefinition.isVoidItems:()Z
     210: ifne          217
     213: iconst_1
     214: goto          218
     217: iconst_0
     218: invokevirtual #629                // Method com/buuz135/industrial/worlddata/BackpackDataManager$SlotDefinition.setVoidItems:(Z)V
     221: goto          362
     224: iload         7
     226: ifeq          286
     229: aload         12
     231: iload         10
     233: invokevirtual #544                // Method com/buuz135/industrial/worlddata/BackpackDataManager$BackpackItemHandler.getSlotDefinition:(I)Lcom/buuz135/industrial/worlddata/BackpackDataManager$SlotDefinition;
     236: invokevirtual #633                // Method com/buuz135/industrial/worlddata/BackpackDataManager$SlotDefinition.getAmount:()I
     239: ifne          269
     242: aload         12
     244: iload         10
     246: invokevirtual #544                // Method com/buuz135/industrial/worlddata/BackpackDataManager$BackpackItemHandler.getSlotDefinition:(I)Lcom/buuz135/industrial/worlddata/BackpackDataManager$SlotDefinition;
     249: getstatic     #618                // Field net/minecraft/world/item/ItemStack.EMPTY:Lnet/minecraft/world/item/ItemStack;
     252: invokevirtual #634                // Method com/buuz135/industrial/worlddata/BackpackDataManager$SlotDefinition.setStack:(Lnet/minecraft/world/item/ItemStack;)V
     255: aload         12
     257: iload         10
     259: invokevirtual #544                // Method com/buuz135/industrial/worlddata/BackpackDataManager$BackpackItemHandler.getSlotDefinition:(I)Lcom/buuz135/industrial/worlddata/BackpackDataManager$SlotDefinition;
     262: iconst_0
     263: invokevirtual #637                // Method com/buuz135/industrial/worlddata/BackpackDataManager$SlotDefinition.setAmount:(I)V
     266: goto          362
     269: aload_2
     270: aload         12
     272: iload         10
     274: iload         15
     276: iconst_0
     277: invokevirtual #565                // Method com/buuz135/industrial/worlddata/BackpackDataManager$BackpackItemHandler.extractItem:(IIZ)Lnet/minecraft/world/item/ItemStack;
     280: invokestatic  #640                // Method net/neoforged/neoforge/items/ItemHandlerHelper.giveItemToPlayer:(Lnet/minecraft/world/entity/player/Player;Lnet/minecraft/world/item/ItemStack;)V
     283: goto          362
     286: aload         12
     288: iload         10
     290: iload         15
     292: iconst_0
     293: invokevirtual #565                // Method com/buuz135/industrial/worlddata/BackpackDataManager$BackpackItemHandler.extractItem:(IIZ)Lnet/minecraft/world/item/ItemStack;
     296: astore        13
     298: iconst_1
     299: istore        14
     301: goto          362
     304: iload         9
     306: iconst_1
     307: if_icmpne     362
     310: iload         8
     312: ifeq          345
     315: aload         12
     317: iload         10
     319: invokevirtual #544                // Method com/buuz135/industrial/worlddata/BackpackDataManager$BackpackItemHandler.getSlotDefinition:(I)Lcom/buuz135/industrial/worlddata/BackpackDataManager$SlotDefinition;
     322: astore        16
     324: aload         16
     326: aload         16
     328: invokevirtual #548                // Method com/buuz135/industrial/worlddata/BackpackDataManager$SlotDefinition.isRefillItems:()Z
     331: ifne          338
     334: iconst_1
     335: goto          339
     338: iconst_0
     339: invokevirtual #646                // Method com/buuz135/industrial/worlddata/BackpackDataManager$SlotDefinition.setRefillItems:(Z)V
     342: goto          362
     345: aload         12
     347: iload         10
     349: iload         15
     351: iconst_2
     352: idiv
     353: iconst_0
     354: invokevirtual #565                // Method com/buuz135/industrial/worlddata/BackpackDataManager$BackpackItemHandler.extractItem:(IIZ)Lnet/minecraft/world/item/ItemStack;
     357: astore        13
     359: iconst_1
     360: istore        14
     362: goto          427
     365: iload         9
     367: ifne          388
     370: aload         12
     372: iload         10
     374: aload         6
     376: iconst_0
     377: invokevirtual #649                // Method com/buuz135/industrial/worlddata/BackpackDataManager$BackpackItemHandler.insertItem:(ILnet/minecraft/world/item/ItemStack;Z)Lnet/minecraft/world/item/ItemStack;
     380: astore        13
     382: iconst_1
     383: istore        14
     385: goto          427
     388: iload         9
     390: iconst_1
     391: if_icmpne     427
     394: aload         12
     396: iload         10
     398: aload         6
     400: iconst_1
     401: invokevirtual #653                // Method net/minecraft/world/item/ItemStack.copyWithCount:(I)Lnet/minecraft/world/item/ItemStack;
     404: iconst_0
     405: invokevirtual #649                // Method com/buuz135/industrial/worlddata/BackpackDataManager$BackpackItemHandler.insertItem:(ILnet/minecraft/world/item/ItemStack;Z)Lnet/minecraft/world/item/ItemStack;
     408: invokevirtual #543                // Method net/minecraft/world/item/ItemStack.isEmpty:()Z
     411: ifeq          427
     414: aload         6
     416: iconst_1
     417: invokevirtual #656                // Method net/minecraft/world/item/ItemStack.shrink:(I)V
     420: aload         6
     422: astore        13
     424: iconst_1
     425: istore        14
     427: iload         14
     429: ifeq          451
     432: aload_2
     433: getfield      #591                // Field net/minecraft/world/entity/player/Player.containerMenu:Lnet/minecraft/world/inventory/AbstractContainerMenu;
     436: aload         13
     438: invokevirtual #659                // Method net/minecraft/world/inventory/AbstractContainerMenu.setCarried:(Lnet/minecraft/world/item/ItemStack;)V
     441: aload_2
     442: checkcast     #282                // class net/minecraft/server/level/ServerPlayer
     445: getfield      #662                // Field net/minecraft/server/level/ServerPlayer.containerMenu:Lnet/minecraft/world/inventory/AbstractContainerMenu;
     448: invokevirtual #663                // Method net/minecraft/world/inventory/AbstractContainerMenu.broadcastChanges:()V
     451: aload_2
     452: invokevirtual #617                // Method net/minecraft/world/entity/player/Player.level:()Lnet/minecraft/world/level/Level;
     455: aload         5
     457: aload_2
     458: checkcast     #282                // class net/minecraft/server/level/ServerPlayer
     461: invokestatic  #326                // Method sync:(Lnet/minecraft/world/level/Level;Ljava/lang/String;Lnet/minecraft/server/level/ServerPlayer;)V
     464: iload_1
     465: bipush        10
     467: if_icmpne     488
     470: aload         4
     472: aload         4
     474: invokestatic  #366                // Method isMagnetEnabled:(Lnet/minecraft/world/item/ItemStack;)Z
     477: ifne          484
     480: iconst_1
     481: goto          485
     484: iconst_0
     485: invokestatic  #666                // Method setMagnet:(Lnet/minecraft/world/item/ItemStack;Z)V
     488: iload_1
     489: bipush        11
     491: if_icmpne     508
     494: aload         4
     496: aload         4
     498: invokestatic  #670                // Method getPickUpMode:(Lnet/minecraft/world/item/ItemStack;)I
     501: iconst_1
     502: iadd
     503: iconst_4
     504: irem
     505: invokestatic  #673                // Method setPickUpMode:(Lnet/minecraft/world/item/ItemStack;I)V
     508: iload_1
     509: iconst_3
     510: if_icmpne     532
     513: aload_0
     514: aload         4
     516: aload         4
     518: invokestatic  #677                // Method canCharge:(Lnet/minecraft/world/item/ItemStack;)Z
     521: ifne          528
     524: iconst_1
     525: goto          529
     528: iconst_0
     529: invokevirtual #680                // Method setCanCharge:(Lnet/minecraft/world/item/ItemStack;Z)V
     532: iload_1
     533: bipush        -10
     535: if_icmpne     558
     538: aload_0
     539: aload         4
     541: aload_0
     542: aload         4
     544: invokevirtual #683                // Method isSpecialEnabled:(Lnet/minecraft/world/item/ItemStack;)Z
     547: ifne          554
     550: iconst_1
     551: goto          555
     554: iconst_0
     555: invokevirtual #686                // Method setSpecialEnabled:(Lnet/minecraft/world/item/ItemStack;Z)V
     558: return

  public void handleButtonMessage(int, net.minecraft.world.entity.player.Player, net.minecraft.nbt.CompoundTag);
    descriptor: (ILnet/minecraft/world/entity/player/Player;Lnet/minecraft/nbt/CompoundTag;)V
    Code:
       0: aload_2
       1: invokestatic  #689                // Method findFirstBackpack:(Lnet/minecraft/world/entity/player/Player;)Ljava/util/Optional;
       4: aload_0
       5: aload_2
       6: iload_1
       7: aload_3
       8: invokedynamic #693,  0            // InvokeDynamic #7:accept:(Lcom/buuz135/industrial/item/infinity/item/ItemInfinityBackpack;Lnet/minecraft/world/entity/player/Player;ILnet/minecraft/nbt/CompoundTag;)Ljava/util/function/Consumer;
      13: invokevirtual #696                // Method java/util/Optional.ifPresent:(Ljava/util/function/Consumer;)V
      16: return

  public void addTooltipDetails(com.hrznstudio.titanium.item.BasicItem$Key, net.minecraft.world.item.ItemStack, java.util.List<net.minecraft.network.chat.Component>, boolean);
    descriptor: (Lcom/hrznstudio/titanium/item/BasicItem$Key;Lnet/minecraft/world/item/ItemStack;Ljava/util/List;Z)V
    Code:
       0: aload_3
       1: getstatic     #700                // Field net/minecraft/ChatFormatting.GRAY:Lnet/minecraft/ChatFormatting;
       4: invokestatic  #706                // Method java/lang/String.valueOf:(Ljava/lang/Object;)Ljava/lang/String;
       7: ldc_w         #709                // String text.industrialforegoing.tooltip.can_hold
      10: invokestatic  #711                // InterfaceMethod net/minecraft/network/chat/Component.translatable:(Ljava/lang/String;)Lnet/minecraft/network/chat/MutableComponent;
      13: invokevirtual #717                // Method net/minecraft/network/chat/MutableComponent.getString:()Ljava/lang/String;
      16: getstatic     #721                // Field net/minecraft/ChatFormatting.DARK_AQUA:Lnet/minecraft/ChatFormatting;
      19: invokestatic  #706                // Method java/lang/String.valueOf:(Ljava/lang/Object;)Ljava/lang/String;
      22: getstatic     #724                // Field java/util/Locale.ROOT:Ljava/util/Locale;
      25: invokestatic  #730                // Method java/text/NumberFormat.getInstance:(Ljava/util/Locale;)Ljava/text/NumberFormat;
      28: aload_2
      29: invokestatic  #528                // Method getSlotSize:(Lnet/minecraft/world/item/ItemStack;)I
      32: i2l
      33: invokevirtual #736                // Method java/text/NumberFormat.format:(J)Ljava/lang/String;
      36: getstatic     #700                // Field net/minecraft/ChatFormatting.GRAY:Lnet/minecraft/ChatFormatting;
      39: invokestatic  #706                // Method java/lang/String.valueOf:(Ljava/lang/Object;)Ljava/lang/String;
      42: ldc_w         #740                // String text.industrialforegoing.tooltip.items
      45: invokestatic  #711                // InterfaceMethod net/minecraft/network/chat/Component.translatable:(Ljava/lang/String;)Lnet/minecraft/network/chat/MutableComponent;
      48: invokevirtual #717                // Method net/minecraft/network/chat/MutableComponent.getString:()Ljava/lang/String;
      51: invokedynamic #742,  0            // InvokeDynamic #8:makeConcatWithConstants:(Ljava/lang/String;Ljava/lang/String;Ljava/lang/String;Ljava/lang/String;Ljava/lang/String;Ljava/lang/String;)Ljava/lang/String;
      56: invokestatic  #746                // InterfaceMethod net/minecraft/network/chat/Component.literal:(Ljava/lang/String;)Lnet/minecraft/network/chat/MutableComponent;
      59: invokeinterface #241,  2          // InterfaceMethod java/util/List.add:(Ljava/lang/Object;)Z
      64: pop
      65: aload_0
      66: aload_1
      67: aload_2
      68: aload_3
      69: iload         4
      71: invokespecial #749                // Method com/buuz135/industrial/item/infinity/ItemInfinity.addTooltipDetails:(Lcom/hrznstudio/titanium/item/BasicItem$Key;Lnet/minecraft/world/item/ItemStack;Ljava/util/List;Z)V
      74: return

  public void addNbt(net.minecraft.world.item.ItemStack, long, int, boolean);
    descriptor: (Lnet/minecraft/world/item/ItemStack;JIZ)V
    Code:
       0: aload_1
       1: getstatic     #753                // Field com/buuz135/industrial/utils/IFAttachments.INFINITY_ITEM_POWER:Ljava/util/function/Supplier;
       4: lload_2
       5: invokestatic  #756                // Method java/lang/Long.valueOf:(J)Ljava/lang/Long;
       8: invokevirtual #167                // Method net/minecraft/world/item/ItemStack.set:(Ljava/util/function/Supplier;Ljava/lang/Object;)Ljava/lang/Object;
      11: pop
      12: aload_1
      13: getstatic     #359                // Field com/buuz135/industrial/utils/IFAttachments.INFINITY_ITEM_SPECIAL:Ljava/util/function/Supplier;
      16: iload         5
      18: invokestatic  #151                // Method java/lang/Boolean.valueOf:(Z)Ljava/lang/Boolean;
      21: invokevirtual #167                // Method net/minecraft/world/item/ItemStack.set:(Ljava/util/function/Supplier;Ljava/lang/Object;)Ljava/lang/Object;
      24: pop
      25: aload_1
      26: getstatic     #761                // Field com/buuz135/industrial/utils/IFAttachments.INFINITY_ITEM_SELECTED_TIER:Ljava/util/function/Supplier;
      29: lload_2
      30: invokestatic  #73                 // Method com/buuz135/industrial/item/infinity/InfinityTier.getTierBraquet:(J)Lorg/apache/commons/lang3/tuple/Pair;
      33: invokevirtual #79                 // Method org/apache/commons/lang3/tuple/Pair.getLeft:()Ljava/lang/Object;
      36: checkcast     #74                 // class com/buuz135/industrial/item/infinity/InfinityTier
      39: invokevirtual #167                // Method net/minecraft/world/item/ItemStack.set:(Ljava/util/function/Supplier;Ljava/lang/Object;)Ljava/lang/Object;
      42: pop
      43: aload_1
      44: getstatic     #764                // Field com/buuz135/industrial/utils/IFAttachments.INFINITY_ITEM_CAN_CHARGE:Ljava/util/function/Supplier;
      47: iconst_1
      48: invokestatic  #151                // Method java/lang/Boolean.valueOf:(Z)Ljava/lang/Boolean;
      51: invokevirtual #167                // Method net/minecraft/world/item/ItemStack.set:(Ljava/util/function/Supplier;Ljava/lang/Object;)Ljava/lang/Object;
      54: pop
      55: return

  public void verifyComponentsAfterLoad(net.minecraft.world.item.ItemStack);
    descriptor: (Lnet/minecraft/world/item/ItemStack;)V
    Code:
       0: aload_0
       1: aload_1
       2: invokespecial #767                // Method com/buuz135/industrial/item/infinity/ItemInfinity.verifyComponentsAfterLoad:(Lnet/minecraft/world/item/ItemStack;)V
       5: return

  public boolean enoughFuel(net.minecraft.world.item.ItemStack);
    descriptor: (Lnet/minecraft/world/item/ItemStack;)Z
    Code:
       0: invokestatic  #770                // Method com/buuz135/industrial/utils/IFAttachments.registryAccess:()Lnet/minecraft/core/RegistryAccess;
       3: getstatic     #771                // Field net/minecraft/world/item/enchantment/Enchantments.UNBREAKING:Lnet/minecraft/resources/ResourceKey;
       6: invokeinterface #777,  2          // InterfaceMethod net/minecraft/core/RegistryAccess.holderOrThrow:(Lnet/minecraft/resources/ResourceKey;)Lnet/minecraft/core/Holder;
      11: aload_1
      12: invokestatic  #783                // Method net/minecraft/world/item/enchantment/EnchantmentHelper.getItemEnchantmentLevel:(Lnet/minecraft/core/Holder;Lnet/minecraft/world/item/ItemStack;)I
      15: istore_2
      16: aload_0
      17: aload_1
      18: invokevirtual #789                // Method getFuelFromStack:(Lnet/minecraft/world/item/ItemStack;)I
      21: getstatic     #25                 // Field FUEL_CONSUMPTION:I
      24: iconst_1
      25: iload_2
      26: iconst_1
      27: iadd
      28: idiv
      29: imul
      30: if_icmplt     37
      33: iconst_1
      34: goto          38
      37: iconst_0
      38: ireturn

  public void consumeFuel(net.minecraft.world.item.ItemStack);
    descriptor: (Lnet/minecraft/world/item/ItemStack;)V
    Code:
       0: invokestatic  #770                // Method com/buuz135/industrial/utils/IFAttachments.registryAccess:()Lnet/minecraft/core/RegistryAccess;
       3: getstatic     #771                // Field net/minecraft/world/item/enchantment/Enchantments.UNBREAKING:Lnet/minecraft/resources/ResourceKey;
       6: invokeinterface #777,  2          // InterfaceMethod net/minecraft/core/RegistryAccess.holderOrThrow:(Lnet/minecraft/resources/ResourceKey;)Lnet/minecraft/core/Holder;
      11: aload_1
      12: invokestatic  #783                // Method net/minecraft/world/item/enchantment/EnchantmentHelper.getItemEnchantmentLevel:(Lnet/minecraft/core/Holder;Lnet/minecraft/world/item/ItemStack;)I
      15: istore_2
      16: aload_0
      17: aload_1
      18: invokevirtual #789                // Method getFuelFromStack:(Lnet/minecraft/world/item/ItemStack;)I
      21: getstatic     #25                 // Field FUEL_CONSUMPTION:I
      24: iconst_1
      25: iload_2
      26: iconst_1
      27: iadd
      28: idiv
      29: imul
      30: if_icmplt     121
      33: aload_1
      34: getstatic     #452                // Field net/neoforged/neoforge/capabilities/Capabilities$FluidHandler.ITEM:Lnet/neoforged/neoforge/capabilities/ItemCapability;
      37: invokevirtual #458                // Method net/minecraft/world/item/ItemStack.getCapability:(Lnet/neoforged/neoforge/capabilities/ItemCapability;)Ljava/lang/Object;
      40: checkcast     #462                // class net/neoforged/neoforge/fluids/capability/IFluidHandlerItem
      43: astore_3
      44: aload_3
      45: ifnull        121
      48: iconst_0
      49: istore        4
      51: iload         4
      53: aload_3
      54: invokeinterface #478,  1          // InterfaceMethod net/neoforged/neoforge/fluids/capability/IFluidHandlerItem.getTanks:()I
      59: if_icmpge     121
      62: aload_3
      63: iload         4
      65: invokeinterface #481,  2          // InterfaceMethod net/neoforged/neoforge/fluids/capability/IFluidHandlerItem.getFluidInTank:(I)Lnet/neoforged/neoforge/fluids/FluidStack;
      70: getstatic     #792                // Field com/buuz135/industrial/module/ModuleCore.BIOFUEL:Lcom/hrznstudio/titanium/fluid/TitaniumFluidInstance;
      73: invokevirtual #499                // Method com/hrznstudio/titanium/fluid/TitaniumFluidInstance.getSourceFluid:()Lnet/neoforged/neoforge/registries/DeferredHolder;
      76: invokevirtual #795                // Method net/neoforged/neoforge/fluids/FluidStack.is:(Lnet/minecraft/core/Holder;)Z
      79: ifeq          115
      82: aload_3
      83: new           #486                // class net/neoforged/neoforge/fluids/FluidStack
      86: dup
      87: getstatic     #792                // Field com/buuz135/industrial/module/ModuleCore.BIOFUEL:Lcom/hrznstudio/titanium/fluid/TitaniumFluidInstance;
      90: invokevirtual #499                // Method com/hrznstudio/titanium/fluid/TitaniumFluidInstance.getSourceFluid:()Lnet/neoforged/neoforge/registries/DeferredHolder;
      93: getstatic     #25                 // Field FUEL_CONSUMPTION:I
      96: iconst_1
      97: iload_2
      98: iconst_1
      99: iadd
     100: idiv
     101: imul
     102: invokespecial #505                // Method net/neoforged/neoforge/fluids/FluidStack."<init>":(Lnet/minecraft/core/Holder;I)V
     105: getstatic     #508                // Field net/neoforged/neoforge/fluids/capability/IFluidHandler$FluidAction.EXECUTE:Lnet/neoforged/neoforge/fluids/capability/IFluidHandler$FluidAction;
     108: invokeinterface #514,  3          // InterfaceMethod net/neoforged/neoforge/fluids/capability/IFluidHandlerItem.drain:(Lnet/neoforged/neoforge/fluids/FluidStack;Lnet/neoforged/neoforge/fluids/capability/IFluidHandler$FluidAction;)Lnet/neoforged/neoforge/fluids/FluidStack;
     113: pop
     114: return
     115: iinc          4, 1
     118: goto          51
     121: return

  public boolean isEnchantable(net.minecraft.world.item.ItemStack);
    descriptor: (Lnet/minecraft/world/item/ItemStack;)Z
    Code:
       0: iconst_1
       1: ireturn

  public float getDestroySpeed(net.minecraft.world.item.ItemStack, net.minecraft.world.level.block.state.BlockState);
    descriptor: (Lnet/minecraft/world/item/ItemStack;Lnet/minecraft/world/level/block/state/BlockState;)F
    Code:
       0: fconst_1
       1: freturn

  public net.minecraft.world.item.component.ItemAttributeModifiers getDefaultAttributeModifiers(net.minecraft.world.item.ItemStack);
    descriptor: (Lnet/minecraft/world/item/ItemStack;)Lnet/minecraft/world/item/component/ItemAttributeModifiers;
    Code:
       0: getstatic     #799                // Field net/minecraft/world/item/component/ItemAttributeModifiers.EMPTY:Lnet/minecraft/world/item/component/ItemAttributeModifiers;
       3: areturn

  public net.minecraft.world.inventory.AbstractContainerMenu createMenu(int, net.minecraft.world.entity.player.Inventory, net.minecraft.world.entity.player.Player);
    descriptor: (ILnet/minecraft/world/entity/player/Inventory;Lnet/minecraft/world/entity/player/Player;)Lnet/minecraft/world/inventory/AbstractContainerMenu;
    Code:
       0: aload_3
       1: invokestatic  #689                // Method findFirstBackpack:(Lnet/minecraft/world/entity/player/Player;)Ljava/util/Optional;
       4: aload_0
       5: aload_3
       6: iload_1
       7: invokedynamic #804,  0            // InvokeDynamic #9:apply:(Lcom/buuz135/industrial/item/infinity/item/ItemInfinityBackpack;Lnet/minecraft/world/entity/player/Player;I)Ljava/util/function/Function;
      12: invokevirtual #807                // Method java/util/Optional.map:(Ljava/util/function/Function;)Ljava/util/Optional;
      15: aconst_null
      16: invokevirtual #811                // Method java/util/Optional.orElse:(Ljava/lang/Object;)Ljava/lang/Object;
      19: checkcast     #596                // class net/minecraft/world/inventory/AbstractContainerMenu
      22: areturn

  public java.util.List<com.hrznstudio.titanium.api.IFactory<? extends com.hrznstudio.titanium.api.client.IScreenAddon>> getScreenAddons(java.util.function.Supplier<net.minecraft.world.item.ItemStack>);
    descriptor: (Ljava/util/function/Supplier;)Ljava/util/List;
    Code:
       0: new           #179                // class java/util/ArrayList
       3: dup
       4: invokespecial #181                // Method java/util/ArrayList."<init>":()V
       7: astore_2
       8: iconst_0
       9: istore_3
      10: iload_3
      11: bipush        32
      13: if_icmpge     57
      16: iload_3
      17: bipush        8
      19: irem
      20: istore        4
      22: iload_3
      23: bipush        8
      25: idiv
      26: istore        5
      28: iload_3
      29: istore        6
      31: aload_2
      32: aload_0
      33: iload         4
      35: iload         5
      37: iload         6
      39: aload_1
      40: invokedynamic #814,  0            // InvokeDynamic #10:create:(Lcom/buuz135/industrial/item/infinity/item/ItemInfinityBackpack;IIILjava/util/function/Supplier;)Lcom/hrznstudio/titanium/api/IFactory;
      45: invokeinterface #241,  2          // InterfaceMethod java/util/List.add:(Ljava/lang/Object;)Z
      50: pop
      51: iinc          3, 1
      54: goto          10
      57: aload_2
      58: invokedynamic #817,  0            // InvokeDynamic #11:create:()Lcom/hrznstudio/titanium/api/IFactory;
      63: invokeinterface #241,  2          // InterfaceMethod java/util/List.add:(Ljava/lang/Object;)Z
      68: pop
      69: aload_2
      70: invokedynamic #820,  0            // InvokeDynamic #12:create:()Lcom/hrznstudio/titanium/api/IFactory;
      75: invokeinterface #241,  2          // InterfaceMethod java/util/List.add:(Ljava/lang/Object;)Z
      80: pop
      81: sipush        181
      84: istore_3
      85: bipush        19
      87: istore        4
      89: aload_2
      90: aload_0
      91: iload_3
      92: iload         4
      94: aload_1
      95: invokedynamic #821,  0            // InvokeDynamic #13:create:(Lcom/buuz135/industrial/item/infinity/item/ItemInfinityBackpack;IILjava/util/function/Supplier;)Lcom/hrznstudio/titanium/api/IFactory;
     100: invokeinterface #241,  2          // InterfaceMethod java/util/List.add:(Ljava/lang/Object;)Z
     105: pop
     106: aload_2
     107: aload_0
     108: iload_3
     109: iload         4
     111: aload_1
     112: invokedynamic #824,  0            // InvokeDynamic #14:create:(Lcom/buuz135/industrial/item/infinity/item/ItemInfinityBackpack;IILjava/util/function/Supplier;)Lcom/hrznstudio/titanium/api/IFactory;
     117: invokeinterface #241,  2          // InterfaceMethod java/util/List.add:(Ljava/lang/Object;)Z
     122: pop
     123: aload_2
     124: aload_0
     125: iload_3
     126: iload         4
     128: aload_1
     129: invokedynamic #825,  0            // InvokeDynamic #15:create:(Lcom/buuz135/industrial/item/infinity/item/ItemInfinityBackpack;IILjava/util/function/Supplier;)Lcom/hrznstudio/titanium/api/IFactory;
     134: invokeinterface #241,  2          // InterfaceMethod java/util/List.add:(Ljava/lang/Object;)Z
     139: pop
     140: aload_0
     141: aload_1
     142: invokeinterface #826,  1          // InterfaceMethod java/util/function/Supplier.get:()Ljava/lang/Object;
     147: checkcast     #158                // class net/minecraft/world/item/ItemStack
     150: invokevirtual #830                // Method isSpecial:(Lnet/minecraft/world/item/ItemStack;)Z
     153: ifeq          173
     156: aload_2
     157: aload_0
     158: iload_3
     159: iload         4
     161: aload_1
     162: invokedynamic #833,  0            // InvokeDynamic #16:create:(Lcom/buuz135/industrial/item/infinity/item/ItemInfinityBackpack;IILjava/util/function/Supplier;)Lcom/hrznstudio/titanium/api/IFactory;
     167: invokeinterface #241,  2          // InterfaceMethod java/util/List.add:(Ljava/lang/Object;)Z
     172: pop
     173: aload_2
     174: areturn

  public void registerRecipe(net.minecraft.data.recipes.RecipeOutput);
    descriptor: (Lnet/minecraft/data/recipes/RecipeOutput;)V
    Code:
       0: aload_0
       1: invokestatic  #834                // Method com/hrznstudio/titanium/recipe/generator/TitaniumShapedRecipeBuilder.shapedRecipe:(Lnet/minecraft/world/level/ItemLike;)Lcom/hrznstudio/titanium/recipe/generator/TitaniumShapedRecipeBuilder;
       4: ldc_w         #840                // String CDC
       7: invokevirtual #842                // Method com/hrznstudio/titanium/recipe/generator/TitaniumShapedRecipeBuilder.pattern:(Ljava/lang/String;)Lnet/minecraft/data/recipes/ShapedRecipeBuilder;
      10: ldc_w         #846                // String BPB
      13: invokevirtual #848                // Method net/minecraft/data/recipes/ShapedRecipeBuilder.pattern:(Ljava/lang/String;)Lnet/minecraft/data/recipes/ShapedRecipeBuilder;
      16: ldc_w         #851                // String GGG
      19: invokevirtual #848                // Method net/minecraft/data/recipes/ShapedRecipeBuilder.pattern:(Ljava/lang/String;)Lnet/minecraft/data/recipes/ShapedRecipeBuilder;
      22: bipush        67
      24: invokestatic  #853                // Method java/lang/Character.valueOf:(C)Ljava/lang/Character;
      27: getstatic     #858                // Field net/neoforged/neoforge/common/Tags$Items.CHESTS_WOODEN:Lnet/minecraft/tags/TagKey;
      30: invokevirtual #864                // Method net/minecraft/data/recipes/ShapedRecipeBuilder.define:(Ljava/lang/Character;Lnet/minecraft/tags/TagKey;)Lnet/minecraft/data/recipes/ShapedRecipeBuilder;
      33: bipush        68
      35: invokestatic  #853                // Method java/lang/Character.valueOf:(C)Ljava/lang/Character;
      38: getstatic     #868                // Field com/buuz135/industrial/utils/IndustrialTags$Items.GEAR_DIAMOND:Lnet/minecraft/tags/TagKey;
      41: invokevirtual #864                // Method net/minecraft/data/recipes/ShapedRecipeBuilder.define:(Ljava/lang/Character;Lnet/minecraft/tags/TagKey;)Lnet/minecraft/data/recipes/ShapedRecipeBuilder;
      44: bipush        66
      46: invokestatic  #853                // Method java/lang/Character.valueOf:(C)Ljava/lang/Character;
      49: getstatic     #873                // Field net/minecraft/world/item/Items.BUCKET:Lnet/minecraft/world/item/Item;
      52: invokevirtual #879                // Method net/minecraft/data/recipes/ShapedRecipeBuilder.define:(Ljava/lang/Character;Lnet/minecraft/world/level/ItemLike;)Lnet/minecraft/data/recipes/ShapedRecipeBuilder;
      55: bipush        80
      57: invokestatic  #853                // Method java/lang/Character.valueOf:(C)Ljava/lang/Character;
      60: getstatic     #882                // Field net/minecraft/world/item/Items.ENDER_PEARL:Lnet/minecraft/world/item/Item;
      63: invokevirtual #879                // Method net/minecraft/data/recipes/ShapedRecipeBuilder.define:(Ljava/lang/Character;Lnet/minecraft/world/level/ItemLike;)Lnet/minecraft/data/recipes/ShapedRecipeBuilder;
      66: bipush        71
      68: invokestatic  #853                // Method java/lang/Character.valueOf:(C)Ljava/lang/Character;
      71: getstatic     #885                // Field com/buuz135/industrial/utils/IndustrialTags$Items.GEAR_GOLD:Lnet/minecraft/tags/TagKey;
      74: invokevirtual #864                // Method net/minecraft/data/recipes/ShapedRecipeBuilder.define:(Ljava/lang/Character;Lnet/minecraft/tags/TagKey;)Lnet/minecraft/data/recipes/ShapedRecipeBuilder;
      77: aload_1
      78: invokevirtual #888                // Method net/minecraft/data/recipes/ShapedRecipeBuilder.save:(Lnet/minecraft/data/recipes/RecipeOutput;)V
      81: return

  public net.minecraft.world.InteractionResult useOn(net.minecraft.world.item.context.UseOnContext);
    descriptor: (Lnet/minecraft/world/item/context/UseOnContext;)Lnet/minecraft/world/InteractionResult;
    Code:
       0: aload_0
       1: new           #892                // class net/minecraft/world/item/context/BlockPlaceContext
       4: dup
       5: aload_1
       6: invokespecial #894                // Method net/minecraft/world/item/context/BlockPlaceContext."<init>":(Lnet/minecraft/world/item/context/UseOnContext;)V
       9: invokevirtual #897                // Method place:(Lnet/minecraft/world/item/context/BlockPlaceContext;)Lnet/minecraft/world/InteractionResult;
      12: astore_2
      13: aload_2
      14: invokevirtual #901                // Method net/minecraft/world/InteractionResult.consumesAction:()Z
      17: ifne          68
      20: aload_1
      21: invokevirtual #906                // Method net/minecraft/world/item/context/UseOnContext.getItemInHand:()Lnet/minecraft/world/item/ItemStack;
      24: getstatic     #910                // Field net/minecraft/core/component/DataComponents.FOOD:Lnet/minecraft/core/component/DataComponentType;
      27: invokevirtual #916                // Method net/minecraft/world/item/ItemStack.has:(Lnet/minecraft/core/component/DataComponentType;)Z
      30: ifeq          68
      33: aload_0
      34: aload_1
      35: invokevirtual #919                // Method net/minecraft/world/item/context/UseOnContext.getLevel:()Lnet/minecraft/world/level/Level;
      38: aload_1
      39: invokevirtual #922                // Method net/minecraft/world/item/context/UseOnContext.getPlayer:()Lnet/minecraft/world/entity/player/Player;
      42: aload_1
      43: invokevirtual #926                // Method net/minecraft/world/item/context/UseOnContext.getHand:()Lnet/minecraft/world/InteractionHand;
      46: invokespecial #362                // Method com/buuz135/industrial/item/infinity/ItemInfinity.use:(Lnet/minecraft/world/level/Level;Lnet/minecraft/world/entity/player/Player;Lnet/minecraft/world/InteractionHand;)Lnet/minecraft/world/InteractionResultHolder;
      49: invokevirtual #930                // Method net/minecraft/world/InteractionResultHolder.getResult:()Lnet/minecraft/world/InteractionResult;
      52: astore_3
      53: aload_3
      54: getstatic     #934                // Field net/minecraft/world/InteractionResult.CONSUME:Lnet/minecraft/world/InteractionResult;
      57: if_acmpne     66
      60: getstatic     #938                // Field net/minecraft/world/InteractionResult.CONSUME_PARTIAL:Lnet/minecraft/world/InteractionResult;
      63: goto          67
      66: aload_3
      67: areturn
      68: aload_2
      69: areturn

  public net.minecraft.world.InteractionResult place(net.minecraft.world.item.context.BlockPlaceContext);
    descriptor: (Lnet/minecraft/world/item/context/BlockPlaceContext;)Lnet/minecraft/world/InteractionResult;
    Code:
       0: aload_1
       1: invokevirtual #941                // Method net/minecraft/world/item/context/BlockPlaceContext.getPlayer:()Lnet/minecraft/world/entity/player/Player;
       4: invokevirtual #942                // Method net/minecraft/world/entity/player/Player.isShiftKeyDown:()Z
       7: ifne          14
      10: getstatic     #945                // Field net/minecraft/world/InteractionResult.PASS:Lnet/minecraft/world/InteractionResult;
      13: areturn
      14: aload_1
      15: invokevirtual #948                // Method net/minecraft/world/item/context/BlockPlaceContext.canPlace:()Z
      18: ifne          25
      21: getstatic     #951                // Field net/minecraft/world/InteractionResult.FAIL:Lnet/minecraft/world/InteractionResult;
      24: areturn
      25: aload_0
      26: aload_1
      27: invokevirtual #954                // Method updatePlacementContext:(Lnet/minecraft/world/item/context/BlockPlaceContext;)Lnet/minecraft/world/item/context/BlockPlaceContext;
      30: astore_2
      31: aload_2
      32: ifnonnull     39
      35: getstatic     #951                // Field net/minecraft/world/InteractionResult.FAIL:Lnet/minecraft/world/InteractionResult;
      38: areturn
      39: aload_0
      40: aload_2
      41: invokevirtual #958                // Method getPlacementState:(Lnet/minecraft/world/item/context/BlockPlaceContext;)Lnet/minecraft/world/level/block/state/BlockState;
      44: astore_3
      45: aload_3
      46: ifnonnull     53
      49: getstatic     #951                // Field net/minecraft/world/InteractionResult.FAIL:Lnet/minecraft/world/InteractionResult;
      52: areturn
      53: aload_0
      54: aload_2
      55: aload_3
      56: invokevirtual #962                // Method placeBlock:(Lnet/minecraft/world/item/context/BlockPlaceContext;Lnet/minecraft/world/level/block/state/BlockState;)Z
      59: ifne          66
      62: getstatic     #951                // Field net/minecraft/world/InteractionResult.FAIL:Lnet/minecraft/world/InteractionResult;
      65: areturn
      66: aload_2
      67: invokevirtual #966                // Method net/minecraft/world/item/context/BlockPlaceContext.getClickedPos:()Lnet/minecraft/core/BlockPos;
      70: astore        4
      72: aload_2
      73: invokevirtual #970                // Method net/minecraft/world/item/context/BlockPlaceContext.getLevel:()Lnet/minecraft/world/level/Level;
      76: astore        5
      78: aload_2
      79: invokevirtual #941                // Method net/minecraft/world/item/context/BlockPlaceContext.getPlayer:()Lnet/minecraft/world/entity/player/Player;
      82: astore        6
      84: aload_2
      85: invokevirtual #971                // Method net/minecraft/world/item/context/BlockPlaceContext.getItemInHand:()Lnet/minecraft/world/item/ItemStack;
      88: astore        7
      90: aload         5
      92: aload         4
      94: invokevirtual #972                // Method net/minecraft/world/level/Level.getBlockState:(Lnet/minecraft/core/BlockPos;)Lnet/minecraft/world/level/block/state/BlockState;
      97: astore        8
      99: aload         8
     101: aload_3
     102: invokevirtual #976                // Method net/minecraft/world/level/block/state/BlockState.getBlock:()Lnet/minecraft/world/level/block/Block;
     105: invokevirtual #982                // Method net/minecraft/world/level/block/state/BlockState.is:(Lnet/minecraft/world/level/block/Block;)Z
     108: ifeq          174
     111: aload_0
     112: aload         5
     114: aload         6
     116: aload         4
     118: aload         7
     120: invokevirtual #985                // Method updateCustomBlockEntityTag:(Lnet/minecraft/world/level/Level;Lnet/minecraft/world/entity/player/Player;Lnet/minecraft/core/BlockPos;Lnet/minecraft/world/item/ItemStack;)Z
     123: pop
     124: aload         5
     126: aload         4
     128: aload         7
     130: invokestatic  #989                // Method updateBlockEntityComponents:(Lnet/minecraft/world/level/Level;Lnet/minecraft/core/BlockPos;Lnet/minecraft/world/item/ItemStack;)V
     133: aload         8
     135: invokevirtual #976                // Method net/minecraft/world/level/block/state/BlockState.getBlock:()Lnet/minecraft/world/level/block/Block;
     138: aload         5
     140: aload         4
     142: aload         8
     144: aload         6
     146: aload         7
     148: invokevirtual #993                // Method net/minecraft/world/level/block/Block.setPlacedBy:(Lnet/minecraft/world/level/Level;Lnet/minecraft/core/BlockPos;Lnet/minecraft/world/level/block/state/BlockState;Lnet/minecraft/world/entity/LivingEntity;Lnet/minecraft/world/item/ItemStack;)V
     151: aload         6
     153: instanceof    #282                // class net/minecraft/server/level/ServerPlayer
     156: ifeq          174
     159: getstatic     #999                // Field net/minecraft/advancements/CriteriaTriggers.PLACED_BLOCK:Lnet/minecraft/advancements/critereon/ItemUsedOnLocationTrigger;
     162: aload         6
     164: checkcast     #282                // class net/minecraft/server/level/ServerPlayer
     167: aload         4
     169: aload         7
     171: invokevirtual #1005               // Method net/minecraft/advancements/critereon/ItemUsedOnLocationTrigger.trigger:(Lnet/minecraft/server/level/ServerPlayer;Lnet/minecraft/core/BlockPos;Lnet/minecraft/world/item/ItemStack;)V
     174: aload         8
     176: aload         5
     178: aload         4
     180: aload_1
     181: invokevirtual #941                // Method net/minecraft/world/item/context/BlockPlaceContext.getPlayer:()Lnet/minecraft/world/entity/player/Player;
     184: invokevirtual #1011               // Method net/minecraft/world/level/block/state/BlockState.getSoundType:(Lnet/minecraft/world/level/LevelReader;Lnet/minecraft/core/BlockPos;Lnet/minecraft/world/entity/Entity;)Lnet/minecraft/world/level/block/SoundType;
     187: astore        9
     189: aload         5
     191: aload         6
     193: aload         4
     195: aload_0
     196: aload         8
     198: aload         5
     200: aload         4
     202: aload_1
     203: invokevirtual #941                // Method net/minecraft/world/item/context/BlockPlaceContext.getPlayer:()Lnet/minecraft/world/entity/player/Player;
     206: invokevirtual #1015               // Method getPlaceSound:(Lnet/minecraft/world/level/block/state/BlockState;Lnet/minecraft/world/level/Level;Lnet/minecraft/core/BlockPos;Lnet/minecraft/world/entity/player/Player;)Lnet/minecraft/sounds/SoundEvent;
     209: getstatic     #1019               // Field net/minecraft/sounds/SoundSource.BLOCKS:Lnet/minecraft/sounds/SoundSource;
     212: aload         9
     214: invokevirtual #1025               // Method net/minecraft/world/level/block/SoundType.getVolume:()F
     217: fconst_1
     218: fadd
     219: fconst_2
     220: fdiv
     221: aload         9
     223: invokevirtual #1030               // Method net/minecraft/world/level/block/SoundType.getPitch:()F
     226: ldc_w         #1033               // float 0.8f
     229: fmul
     230: invokevirtual #1034               // Method net/minecraft/world/level/Level.playSound:(Lnet/minecraft/world/entity/player/Player;Lnet/minecraft/core/BlockPos;Lnet/minecraft/sounds/SoundEvent;Lnet/minecraft/sounds/SoundSource;FF)V
     233: aload         5
     235: getstatic     #1038               // Field net/minecraft/world/level/gameevent/GameEvent.BLOCK_PLACE:Lnet/minecraft/core/Holder$Reference;
     238: aload         4
     240: aload         6
     242: aload         8
     244: invokestatic  #1044               // Method net/minecraft/world/level/gameevent/GameEvent$Context.of:(Lnet/minecraft/world/entity/Entity;Lnet/minecraft/world/level/block/state/BlockState;)Lnet/minecraft/world/level/gameevent/GameEvent$Context;
     247: invokevirtual #1049               // Method net/minecraft/world/level/Level.gameEvent:(Lnet/minecraft/core/Holder;Lnet/minecraft/core/BlockPos;Lnet/minecraft/world/level/gameevent/GameEvent$Context;)V
     250: aload         7
     252: iconst_1
     253: aload         6
     255: invokevirtual #1053               // Method net/minecraft/world/item/ItemStack.consume:(ILnet/minecraft/world/entity/LivingEntity;)V
     258: aload         5
     260: getfield      #404                // Field net/minecraft/world/level/Level.isClientSide:Z
     263: invokestatic  #1057               // Method net/minecraft/world/InteractionResult.sidedSuccess:(Z)Lnet/minecraft/world/InteractionResult;
     266: areturn

  protected net.minecraft.sounds.SoundEvent getPlaceSound(net.minecraft.world.level.block.state.BlockState);
    descriptor: (Lnet/minecraft/world/level/block/state/BlockState;)Lnet/minecraft/sounds/SoundEvent;
    Code:
       0: aload_1
       1: invokevirtual #1061               // Method net/minecraft/world/level/block/state/BlockState.getSoundType:()Lnet/minecraft/world/level/block/SoundType;
       4: invokevirtual #1064               // Method net/minecraft/world/level/block/SoundType.getPlaceSound:()Lnet/minecraft/sounds/SoundEvent;
       7: areturn

  protected net.minecraft.sounds.SoundEvent getPlaceSound(net.minecraft.world.level.block.state.BlockState, net.minecraft.world.level.Level, net.minecraft.core.BlockPos, net.minecraft.world.entity.player.Player);
    descriptor: (Lnet/minecraft/world/level/block/state/BlockState;Lnet/minecraft/world/level/Level;Lnet/minecraft/core/BlockPos;Lnet/minecraft/world/entity/player/Player;)Lnet/minecraft/sounds/SoundEvent;
    Code:
       0: aload_1
       1: aload_2
       2: aload_3
       3: aload         4
       5: invokevirtual #1011               // Method net/minecraft/world/level/block/state/BlockState.getSoundType:(Lnet/minecraft/world/level/LevelReader;Lnet/minecraft/core/BlockPos;Lnet/minecraft/world/entity/Entity;)Lnet/minecraft/world/level/block/SoundType;
       8: invokevirtual #1064               // Method net/minecraft/world/level/block/SoundType.getPlaceSound:()Lnet/minecraft/sounds/SoundEvent;
      11: areturn

  public net.minecraft.world.item.context.BlockPlaceContext updatePlacementContext(net.minecraft.world.item.context.BlockPlaceContext);
    descriptor: (Lnet/minecraft/world/item/context/BlockPlaceContext;)Lnet/minecraft/world/item/context/BlockPlaceContext;
    Code:
       0: aload_1
       1: areturn

  public net.minecraft.world.level.block.Block getBlock();
    descriptor: ()Lnet/minecraft/world/level/block/Block;
    Code:
       0: getstatic     #1067               // Field com/buuz135/industrial/module/ModuleTool.INFINITY_BACKPACK_BLOCK:Lcom/hrznstudio/titanium/module/BlockWithTile;
       3: invokevirtual #1071               // Method com/hrznstudio/titanium/module/BlockWithTile.getBlock:()Lnet/minecraft/world/level/block/Block;
       6: areturn

  protected net.minecraft.world.level.block.state.BlockState getPlacementState(net.minecraft.world.item.context.BlockPlaceContext);
    descriptor: (Lnet/minecraft/world/item/context/BlockPlaceContext;)Lnet/minecraft/world/level/block/state/BlockState;
    Code:
       0: aload_0
       1: invokevirtual #1074               // Method getBlock:()Lnet/minecraft/world/level/block/Block;
       4: aload_1
       5: invokevirtual #1075               // Method net/minecraft/world/level/block/Block.getStateForPlacement:(Lnet/minecraft/world/item/context/BlockPlaceContext;)Lnet/minecraft/world/level/block/state/BlockState;
       8: astore_2
       9: aload_2
      10: ifnull        26
      13: aload_0
      14: aload_1
      15: aload_2
      16: invokevirtual #1078               // Method canPlace:(Lnet/minecraft/world/item/context/BlockPlaceContext;Lnet/minecraft/world/level/block/state/BlockState;)Z
      19: ifeq          26
      22: aload_2
      23: goto          27
      26: aconst_null
      27: areturn

  protected boolean canPlace(net.minecraft.world.item.context.BlockPlaceContext, net.minecraft.world.level.block.state.BlockState);
    descriptor: (Lnet/minecraft/world/item/context/BlockPlaceContext;Lnet/minecraft/world/level/block/state/BlockState;)Z
    Code:
       0: aload_1
       1: invokevirtual #941                // Method net/minecraft/world/item/context/BlockPlaceContext.getPlayer:()Lnet/minecraft/world/entity/player/Player;
       4: astore_3
       5: aload_3
       6: ifnonnull     15
       9: invokestatic  #1080               // InterfaceMethod net/minecraft/world/phys/shapes/CollisionContext.empty:()Lnet/minecraft/world/phys/shapes/CollisionContext;
      12: goto          19
      15: aload_3
      16: invokestatic  #1085               // InterfaceMethod net/minecraft/world/phys/shapes/CollisionContext.of:(Lnet/minecraft/world/entity/Entity;)Lnet/minecraft/world/phys/shapes/CollisionContext;
      19: astore        4
      21: aload_0
      22: invokevirtual #1088               // Method mustSurvive:()Z
      25: ifeq          43
      28: aload_2
      29: aload_1
      30: invokevirtual #970                // Method net/minecraft/world/item/context/BlockPlaceContext.getLevel:()Lnet/minecraft/world/level/Level;
      33: aload_1
      34: invokevirtual #966                // Method net/minecraft/world/item/context/BlockPlaceContext.getClickedPos:()Lnet/minecraft/core/BlockPos;
      37: invokevirtual #1091               // Method net/minecraft/world/level/block/state/BlockState.canSurvive:(Lnet/minecraft/world/level/LevelReader;Lnet/minecraft/core/BlockPos;)Z
      40: ifeq          64
      43: aload_1
      44: invokevirtual #970                // Method net/minecraft/world/item/context/BlockPlaceContext.getLevel:()Lnet/minecraft/world/level/Level;
      47: aload_2
      48: aload_1
      49: invokevirtual #966                // Method net/minecraft/world/item/context/BlockPlaceContext.getClickedPos:()Lnet/minecraft/core/BlockPos;
      52: aload         4
      54: invokevirtual #1095               // Method net/minecraft/world/level/Level.isUnobstructed:(Lnet/minecraft/world/level/block/state/BlockState;Lnet/minecraft/core/BlockPos;Lnet/minecraft/world/phys/shapes/CollisionContext;)Z
      57: ifeq          64
      60: iconst_1
      61: goto          65
      64: iconst_0
      65: ireturn

  protected boolean mustSurvive();
    descriptor: ()Z
    Code:
       0: iconst_1
       1: ireturn

  protected boolean placeBlock(net.minecraft.world.item.context.BlockPlaceContext, net.minecraft.world.level.block.state.BlockState);
    descriptor: (Lnet/minecraft/world/item/context/BlockPlaceContext;Lnet/minecraft/world/level/block/state/BlockState;)Z
    Code:
       0: aload_1
       1: invokevirtual #970                // Method net/minecraft/world/item/context/BlockPlaceContext.getLevel:()Lnet/minecraft/world/level/Level;
       4: aload_1
       5: invokevirtual #966                // Method net/minecraft/world/item/context/BlockPlaceContext.getClickedPos:()Lnet/minecraft/core/BlockPos;
       8: aload_2
       9: bipush        11
      11: invokevirtual #1099               // Method net/minecraft/world/level/Level.setBlock:(Lnet/minecraft/core/BlockPos;Lnet/minecraft/world/level/block/state/BlockState;I)Z
      14: ireturn

  public boolean updateCustomBlockEntityTag(net.minecraft.world.level.Level, net.minecraft.world.entity.player.Player, net.minecraft.core.BlockPos, net.minecraft.world.item.ItemStack);
    descriptor: (Lnet/minecraft/world/level/Level;Lnet/minecraft/world/entity/player/Player;Lnet/minecraft/core/BlockPos;Lnet/minecraft/world/item/ItemStack;)Z
    Code:
       0: aload_1
       1: invokevirtual #1103               // Method net/minecraft/world/level/Level.getServer:()Lnet/minecraft/server/MinecraftServer;
       4: astore        5
       6: aload         5
       8: ifnonnull     13
      11: iconst_0
      12: ireturn
      13: aload_1
      14: aload_3
      15: invokevirtual #263                // Method net/minecraft/world/level/Level.getBlockEntity:(Lnet/minecraft/core/BlockPos;)Lnet/minecraft/world/level/block/entity/BlockEntity;
      18: astore        6
      20: aload         6
      22: instanceof    #1107               // class com/buuz135/industrial/block/tool/tile/InfinityBackpackTile
      25: ifeq          45
      28: aload         6
      30: checkcast     #1107               // class com/buuz135/industrial/block/tool/tile/InfinityBackpackTile
      33: astore        7
      35: aload         7
      37: aload         4
      39: invokevirtual #1109               // Method net/minecraft/world/item/ItemStack.copy:()Lnet/minecraft/world/item/ItemStack;
      42: invokevirtual #1112               // Method com/buuz135/industrial/block/tool/tile/InfinityBackpackTile.setBackpack:(Lnet/minecraft/world/item/ItemStack;)V
      45: aload         4
      47: getstatic     #1115               // Field net/minecraft/core/component/DataComponents.BLOCK_ENTITY_DATA:Lnet/minecraft/core/component/DataComponentType;
      50: getstatic     #1118               // Field net/minecraft/world/item/component/CustomData.EMPTY:Lnet/minecraft/world/item/component/CustomData;
      53: invokevirtual #1123               // Method net/minecraft/world/item/ItemStack.getOrDefault:(Lnet/minecraft/core/component/DataComponentType;Ljava/lang/Object;)Ljava/lang/Object;
      56: checkcast     #1119               // class net/minecraft/world/item/component/CustomData
      59: astore        7
      61: aload         7
      63: invokevirtual #1126               // Method net/minecraft/world/item/component/CustomData.isEmpty:()Z
      66: ifne          114
      69: aload         6
      71: ifnull        114
      74: aload_1
      75: getfield      #404                // Field net/minecraft/world/level/Level.isClientSide:Z
      78: ifne          102
      81: aload         6
      83: invokevirtual #1127               // Method net/minecraft/world/level/block/entity/BlockEntity.onlyOpCanSetNbt:()Z
      86: ifeq          102
      89: aload_2
      90: ifnull        100
      93: aload_2
      94: invokevirtual #1130               // Method net/minecraft/world/entity/player/Player.canUseGameMasterBlocks:()Z
      97: ifne          102
     100: iconst_0
     101: ireturn
     102: aload         7
     104: aload         6
     106: aload_1
     107: invokevirtual #124                // Method net/minecraft/world/level/Level.registryAccess:()Lnet/minecraft/core/RegistryAccess;
     110: invokevirtual #1133               // Method net/minecraft/world/item/component/CustomData.loadInto:(Lnet/minecraft/world/level/block/entity/BlockEntity;Lnet/minecraft/core/HolderLookup$Provider;)Z
     113: ireturn
     114: iconst_0
     115: ireturn

  private com.hrznstudio.titanium.api.client.IScreenAddon lambda$getScreenAddons$19(int, int, java.util.function.Supplier);
    descriptor: (IILjava/util/function/Supplier;)Lcom/hrznstudio/titanium/api/client/IScreenAddon;
    Code:
       0: new           #1137               // class com/buuz135/industrial/item/infinity/item/ItemInfinityBackpack$7
       3: dup
       4: aload_0
       5: new           #1139               // class com/hrznstudio/titanium/component/button/ButtonComponent
       8: dup
       9: iload_1
      10: bipush        16
      12: iload_2
      13: iconst_3
      14: imul
      15: iadd
      16: bipush        14
      18: bipush        14
      20: invokespecial #1141               // Method com/hrznstudio/titanium/component/button/ButtonComponent."<init>":(IIII)V
      23: bipush        -10
      25: invokevirtual #1144               // Method com/hrznstudio/titanium/component/button/ButtonComponent.setId:(I)Lcom/hrznstudio/titanium/component/button/ButtonComponent;
      28: iconst_2
      29: anewarray     #1148               // class com/hrznstudio/titanium/client/screen/addon/StateButtonInfo
      32: dup
      33: iconst_0
      34: new           #1148               // class com/hrznstudio/titanium/client/screen/addon/StateButtonInfo
      37: dup
      38: iconst_0
      39: getstatic     #1150               // Field com/hrznstudio/titanium/api/client/AssetTypes.BUTTON_SIDENESS_ENABLED:Lcom/hrznstudio/titanium/api/client/IAssetType;
      42: iconst_1
      43: anewarray     #208                // class java/lang/String
      46: dup
      47: iconst_0
      48: getstatic     #1156               // Field net/minecraft/ChatFormatting.GOLD:Lnet/minecraft/ChatFormatting;
      51: invokestatic  #706                // Method java/lang/String.valueOf:(Ljava/lang/Object;)Ljava/lang/String;
      54: ldc_w         #1159               // String text.industrialforegoing.display.special
      57: invokestatic  #711                // InterfaceMethod net/minecraft/network/chat/Component.translatable:(Ljava/lang/String;)Lnet/minecraft/network/chat/MutableComponent;
      60: invokevirtual #717                // Method net/minecraft/network/chat/MutableComponent.getString:()Ljava/lang/String;
      63: invokedynamic #1161,  0           // InvokeDynamic #17:makeConcatWithConstants:(Ljava/lang/String;Ljava/lang/String;)Ljava/lang/String;
      68: aastore
      69: invokespecial #1164               // Method com/hrznstudio/titanium/client/screen/addon/StateButtonInfo."<init>":(ILcom/hrznstudio/titanium/api/client/IAssetType;[Ljava/lang/String;)V
      72: aastore
      73: dup
      74: iconst_1
      75: new           #1148               // class com/hrznstudio/titanium/client/screen/addon/StateButtonInfo
      78: dup
      79: iconst_1
      80: getstatic     #1167               // Field com/hrznstudio/titanium/api/client/AssetTypes.BUTTON_SIDENESS_DISABLED:Lcom/hrznstudio/titanium/api/client/IAssetType;
      83: iconst_1
      84: anewarray     #208                // class java/lang/String
      87: dup
      88: iconst_0
      89: getstatic     #1156               // Field net/minecraft/ChatFormatting.GOLD:Lnet/minecraft/ChatFormatting;
      92: invokestatic  #706                // Method java/lang/String.valueOf:(Ljava/lang/Object;)Ljava/lang/String;
      95: ldc_w         #1159               // String text.industrialforegoing.display.special
      98: invokestatic  #711                // InterfaceMethod net/minecraft/network/chat/Component.translatable:(Ljava/lang/String;)Lnet/minecraft/network/chat/MutableComponent;
     101: invokevirtual #717                // Method net/minecraft/network/chat/MutableComponent.getString:()Ljava/lang/String;
     104: invokedynamic #1161,  0           // InvokeDynamic #17:makeConcatWithConstants:(Ljava/lang/String;Ljava/lang/String;)Ljava/lang/String;
     109: aastore
     110: invokespecial #1164               // Method com/hrznstudio/titanium/client/screen/addon/StateButtonInfo."<init>":(ILcom/hrznstudio/titanium/api/client/IAssetType;[Ljava/lang/String;)V
     113: aastore
     114: aload_3
     115: invokespecial #1170               // Method com/buuz135/industrial/item/infinity/item/ItemInfinityBackpack$7."<init>":(Lcom/buuz135/industrial/item/infinity/item/ItemInfinityBackpack;Lcom/hrznstudio/titanium/component/button/ButtonComponent;[Lcom/hrznstudio/titanium/client/screen/addon/StateButtonInfo;Ljava/util/function/Supplier;)V
     118: areturn

  private com.hrznstudio.titanium.api.client.IScreenAddon lambda$getScreenAddons$18(int, int, java.util.function.Supplier);
    descriptor: (IILjava/util/function/Supplier;)Lcom/hrznstudio/titanium/api/client/IScreenAddon;
    Code:
       0: new           #1173               // class com/buuz135/industrial/item/infinity/item/ItemInfinityBackpack$6
       3: dup
       4: aload_0
       5: new           #1139               // class com/hrznstudio/titanium/component/button/ButtonComponent
       8: dup
       9: iload_1
      10: bipush        16
      12: iload_2
      13: iconst_2
      14: imul
      15: iadd
      16: bipush        14
      18: bipush        14
      20: invokespecial #1141               // Method com/hrznstudio/titanium/component/button/ButtonComponent."<init>":(IIII)V
      23: iconst_3
      24: invokevirtual #1144               // Method com/hrznstudio/titanium/component/button/ButtonComponent.setId:(I)Lcom/hrznstudio/titanium/component/button/ButtonComponent;
      27: iconst_2
      28: anewarray     #1148               // class com/hrznstudio/titanium/client/screen/addon/StateButtonInfo
      31: dup
      32: iconst_0
      33: new           #1148               // class com/hrznstudio/titanium/client/screen/addon/StateButtonInfo
      36: dup
      37: iconst_0
      38: getstatic     #1150               // Field com/hrznstudio/titanium/api/client/AssetTypes.BUTTON_SIDENESS_ENABLED:Lcom/hrznstudio/titanium/api/client/IAssetType;
      41: iconst_1
      42: anewarray     #208                // class java/lang/String
      45: dup
      46: iconst_0
      47: getstatic     #1175               // Field net/minecraft/ChatFormatting.GREEN:Lnet/minecraft/ChatFormatting;
      50: invokestatic  #706                // Method java/lang/String.valueOf:(Ljava/lang/Object;)Ljava/lang/String;
      53: ldc_w         #1178               // String text.industrialforegoing.display.charging
      56: invokestatic  #711                // InterfaceMethod net/minecraft/network/chat/Component.translatable:(Ljava/lang/String;)Lnet/minecraft/network/chat/MutableComponent;
      59: invokevirtual #717                // Method net/minecraft/network/chat/MutableComponent.getString:()Ljava/lang/String;
      62: ldc_w         #1180               // String text.industrialforegoing.display.enabled
      65: invokestatic  #711                // InterfaceMethod net/minecraft/network/chat/Component.translatable:(Ljava/lang/String;)Lnet/minecraft/network/chat/MutableComponent;
      68: invokevirtual #717                // Method net/minecraft/network/chat/MutableComponent.getString:()Ljava/lang/String;
      71: invokedynamic #1182,  0           // InvokeDynamic #18:makeConcatWithConstants:(Ljava/lang/String;Ljava/lang/String;Ljava/lang/String;)Ljava/lang/String;
      76: aastore
      77: invokespecial #1164               // Method com/hrznstudio/titanium/client/screen/addon/StateButtonInfo."<init>":(ILcom/hrznstudio/titanium/api/client/IAssetType;[Ljava/lang/String;)V
      80: aastore
      81: dup
      82: iconst_1
      83: new           #1148               // class com/hrznstudio/titanium/client/screen/addon/StateButtonInfo
      86: dup
      87: iconst_1
      88: getstatic     #1167               // Field com/hrznstudio/titanium/api/client/AssetTypes.BUTTON_SIDENESS_DISABLED:Lcom/hrznstudio/titanium/api/client/IAssetType;
      91: iconst_1
      92: anewarray     #208                // class java/lang/String
      95: dup
      96: iconst_0
      97: getstatic     #1185               // Field net/minecraft/ChatFormatting.RED:Lnet/minecraft/ChatFormatting;
     100: invokestatic  #706                // Method java/lang/String.valueOf:(Ljava/lang/Object;)Ljava/lang/String;
     103: ldc_w         #1178               // String text.industrialforegoing.display.charging
     106: invokestatic  #711                // InterfaceMethod net/minecraft/network/chat/Component.translatable:(Ljava/lang/String;)Lnet/minecraft/network/chat/MutableComponent;
     109: invokevirtual #717                // Method net/minecraft/network/chat/MutableComponent.getString:()Ljava/lang/String;
     112: ldc_w         #1188               // String text.industrialforegoing.display.disabled
     115: invokestatic  #711                // InterfaceMethod net/minecraft/network/chat/Component.translatable:(Ljava/lang/String;)Lnet/minecraft/network/chat/MutableComponent;
     118: invokevirtual #717                // Method net/minecraft/network/chat/MutableComponent.getString:()Ljava/lang/String;
     121: invokedynamic #1182,  0           // InvokeDynamic #18:makeConcatWithConstants:(Ljava/lang/String;Ljava/lang/String;Ljava/lang/String;)Ljava/lang/String;
     126: aastore
     127: invokespecial #1164               // Method com/hrznstudio/titanium/client/screen/addon/StateButtonInfo."<init>":(ILcom/hrznstudio/titanium/api/client/IAssetType;[Ljava/lang/String;)V
     130: aastore
     131: aload_3
     132: invokespecial #1190               // Method com/buuz135/industrial/item/infinity/item/ItemInfinityBackpack$6."<init>":(Lcom/buuz135/industrial/item/infinity/item/ItemInfinityBackpack;Lcom/hrznstudio/titanium/component/button/ButtonComponent;[Lcom/hrznstudio/titanium/client/screen/addon/StateButtonInfo;Ljava/util/function/Supplier;)V
     135: areturn

  private com.hrznstudio.titanium.api.client.IScreenAddon lambda$getScreenAddons$17(int, int, java.util.function.Supplier);
    descriptor: (IILjava/util/function/Supplier;)Lcom/hrznstudio/titanium/api/client/IScreenAddon;
    Code:
       0: new           #1191               // class com/buuz135/industrial/item/infinity/item/ItemInfinityBackpack$5
       3: dup
       4: aload_0
       5: new           #1139               // class com/hrznstudio/titanium/component/button/ButtonComponent
       8: dup
       9: iload_1
      10: bipush        16
      12: iload_2
      13: iconst_1
      14: imul
      15: iadd
      16: bipush        14
      18: bipush        14
      20: invokespecial #1141               // Method com/hrznstudio/titanium/component/button/ButtonComponent."<init>":(IIII)V
      23: bipush        11
      25: invokevirtual #1144               // Method com/hrznstudio/titanium/component/button/ButtonComponent.setId:(I)Lcom/hrznstudio/titanium/component/button/ButtonComponent;
      28: iconst_4
      29: anewarray     #1148               // class com/hrznstudio/titanium/client/screen/addon/StateButtonInfo
      32: dup
      33: iconst_0
      34: new           #1148               // class com/hrznstudio/titanium/client/screen/addon/StateButtonInfo
      37: dup
      38: iconst_0
      39: getstatic     #1150               // Field com/hrznstudio/titanium/api/client/AssetTypes.BUTTON_SIDENESS_ENABLED:Lcom/hrznstudio/titanium/api/client/IAssetType;
      42: iconst_3
      43: anewarray     #208                // class java/lang/String
      46: dup
      47: iconst_0
      48: getstatic     #1175               // Field net/minecraft/ChatFormatting.GREEN:Lnet/minecraft/ChatFormatting;
      51: invokestatic  #706                // Method java/lang/String.valueOf:(Ljava/lang/Object;)Ljava/lang/String;
      54: ldc_w         #1193               // String tooltip.industrialforegoing.backpack.pickup_all
      57: invokestatic  #711                // InterfaceMethod net/minecraft/network/chat/Component.translatable:(Ljava/lang/String;)Lnet/minecraft/network/chat/MutableComponent;
      60: invokevirtual #717                // Method net/minecraft/network/chat/MutableComponent.getString:()Ljava/lang/String;
      63: invokedynamic #1161,  0           // InvokeDynamic #17:makeConcatWithConstants:(Ljava/lang/String;Ljava/lang/String;)Ljava/lang/String;
      68: aastore
      69: dup
      70: iconst_1
      71: getstatic     #700                // Field net/minecraft/ChatFormatting.GRAY:Lnet/minecraft/ChatFormatting;
      74: invokestatic  #706                // Method java/lang/String.valueOf:(Ljava/lang/Object;)Ljava/lang/String;
      77: ldc_w         #1195               // String tooltip.industrialforegoing.backpack.pickup_extra
      80: invokestatic  #711                // InterfaceMethod net/minecraft/network/chat/Component.translatable:(Ljava/lang/String;)Lnet/minecraft/network/chat/MutableComponent;
      83: invokevirtual #717                // Method net/minecraft/network/chat/MutableComponent.getString:()Ljava/lang/String;
      86: invokedynamic #1161,  0           // InvokeDynamic #17:makeConcatWithConstants:(Ljava/lang/String;Ljava/lang/String;)Ljava/lang/String;
      91: aastore
      92: dup
      93: iconst_2
      94: getstatic     #700                // Field net/minecraft/ChatFormatting.GRAY:Lnet/minecraft/ChatFormatting;
      97: invokestatic  #706                // Method java/lang/String.valueOf:(Ljava/lang/Object;)Ljava/lang/String;
     100: ldc_w         #1197               // String tooltip.industrialforegoing.backpack.pickup_extra_1
     103: invokestatic  #711                // InterfaceMethod net/minecraft/network/chat/Component.translatable:(Ljava/lang/String;)Lnet/minecraft/network/chat/MutableComponent;
     106: invokevirtual #717                // Method net/minecraft/network/chat/MutableComponent.getString:()Ljava/lang/String;
     109: invokedynamic #1161,  0           // InvokeDynamic #17:makeConcatWithConstants:(Ljava/lang/String;Ljava/lang/String;)Ljava/lang/String;
     114: aastore
     115: invokespecial #1164               // Method com/hrznstudio/titanium/client/screen/addon/StateButtonInfo."<init>":(ILcom/hrznstudio/titanium/api/client/IAssetType;[Ljava/lang/String;)V
     118: aastore
     119: dup
     120: iconst_1
     121: new           #1148               // class com/hrznstudio/titanium/client/screen/addon/StateButtonInfo
     124: dup
     125: iconst_1
     126: getstatic     #1199               // Field com/hrznstudio/titanium/api/client/AssetTypes.BUTTON_SIDENESS_PULL:Lcom/hrznstudio/titanium/api/client/IAssetType;
     129: iconst_3
     130: anewarray     #208                // class java/lang/String
     133: dup
     134: iconst_0
     135: getstatic     #1175               // Field net/minecraft/ChatFormatting.GREEN:Lnet/minecraft/ChatFormatting;
     138: invokestatic  #706                // Method java/lang/String.valueOf:(Ljava/lang/Object;)Ljava/lang/String;
     141: ldc_w         #1202               // String tooltip.industrialforegoing.backpack.item_pickup_enabled
     144: invokestatic  #711                // InterfaceMethod net/minecraft/network/chat/Component.translatable:(Ljava/lang/String;)Lnet/minecraft/network/chat/MutableComponent;
     147: invokevirtual #717                // Method net/minecraft/network/chat/MutableComponent.getString:()Ljava/lang/String;
     150: invokedynamic #1161,  0           // InvokeDynamic #17:makeConcatWithConstants:(Ljava/lang/String;Ljava/lang/String;)Ljava/lang/String;
     155: aastore
     156: dup
     157: iconst_1
     158: getstatic     #700                // Field net/minecraft/ChatFormatting.GRAY:Lnet/minecraft/ChatFormatting;
     161: invokestatic  #706                // Method java/lang/String.valueOf:(Ljava/lang/Object;)Ljava/lang/String;
     164: ldc_w         #1195               // String tooltip.industrialforegoing.backpack.pickup_extra
     167: invokestatic  #711                // InterfaceMethod net/minecraft/network/chat/Component.translatable:(Ljava/lang/String;)Lnet/minecraft/network/chat/MutableComponent;
     170: invokevirtual #717                // Method net/minecraft/network/chat/MutableComponent.getString:()Ljava/lang/String;
     173: invokedynamic #1161,  0           // InvokeDynamic #17:makeConcatWithConstants:(Ljava/lang/String;Ljava/lang/String;)Ljava/lang/String;
     178: aastore
     179: dup
     180: iconst_2
     181: getstatic     #700                // Field net/minecraft/ChatFormatting.GRAY:Lnet/minecraft/ChatFormatting;
     184: invokestatic  #706                // Method java/lang/String.valueOf:(Ljava/lang/Object;)Ljava/lang/String;
     187: ldc_w         #1197               // String tooltip.industrialforegoing.backpack.pickup_extra_1
     190: invokestatic  #711                // InterfaceMethod net/minecraft/network/chat/Component.translatable:(Ljava/lang/String;)Lnet/minecraft/network/chat/MutableComponent;
     193: invokevirtual #717                // Method net/minecraft/network/chat/MutableComponent.getString:()Ljava/lang/String;
     196: invokedynamic #1161,  0           // InvokeDynamic #17:makeConcatWithConstants:(Ljava/lang/String;Ljava/lang/String;)Ljava/lang/String;
     201: aastore
     202: invokespecial #1164               // Method com/hrznstudio/titanium/client/screen/addon/StateButtonInfo."<init>":(ILcom/hrznstudio/titanium/api/client/IAssetType;[Ljava/lang/String;)V
     205: aastore
     206: dup
     207: iconst_2
     208: new           #1148               // class com/hrznstudio/titanium/client/screen/addon/StateButtonInfo
     211: dup
     212: iconst_2
     213: getstatic     #1204               // Field com/hrznstudio/titanium/api/client/AssetTypes.BUTTON_SIDENESS_PUSH:Lcom/hrznstudio/titanium/api/client/IAssetType;
     216: iconst_3
     217: anewarray     #208                // class java/lang/String
     220: dup
     221: iconst_0
     222: getstatic     #1175               // Field net/minecraft/ChatFormatting.GREEN:Lnet/minecraft/ChatFormatting;
     225: invokestatic  #706                // Method java/lang/String.valueOf:(Ljava/lang/Object;)Ljava/lang/String;
     228: ldc_w         #1207               // String tooltip.industrialforegoing.backpack.xp_pickup_enabled
     231: invokestatic  #711                // InterfaceMethod net/minecraft/network/chat/Component.translatable:(Ljava/lang/String;)Lnet/minecraft/network/chat/MutableComponent;
     234: invokevirtual #717                // Method net/minecraft/network/chat/MutableComponent.getString:()Ljava/lang/String;
     237: invokedynamic #1161,  0           // InvokeDynamic #17:makeConcatWithConstants:(Ljava/lang/String;Ljava/lang/String;)Ljava/lang/String;
     242: aastore
     243: dup
     244: iconst_1
     245: getstatic     #700                // Field net/minecraft/ChatFormatting.GRAY:Lnet/minecraft/ChatFormatting;
     248: invokestatic  #706                // Method java/lang/String.valueOf:(Ljava/lang/Object;)Ljava/lang/String;
     251: ldc_w         #1195               // String tooltip.industrialforegoing.backpack.pickup_extra
     254: invokestatic  #711                // InterfaceMethod net/minecraft/network/chat/Component.translatable:(Ljava/lang/String;)Lnet/minecraft/network/chat/MutableComponent;
     257: invokevirtual #717                // Method net/minecraft/network/chat/MutableComponent.getString:()Ljava/lang/String;
     260: invokedynamic #1161,  0           // InvokeDynamic #17:makeConcatWithConstants:(Ljava/lang/String;Ljava/lang/String;)Ljava/lang/String;
     265: aastore
     266: dup
     267: iconst_2
     268: getstatic     #700                // Field net/minecraft/ChatFormatting.GRAY:Lnet/minecraft/ChatFormatting;
     271: invokestatic  #706                // Method java/lang/String.valueOf:(Ljava/lang/Object;)Ljava/lang/String;
     274: ldc_w         #1197               // String tooltip.industrialforegoing.backpack.pickup_extra_1
     277: invokestatic  #711                // InterfaceMethod net/minecraft/network/chat/Component.translatable:(Ljava/lang/String;)Lnet/minecraft/network/chat/MutableComponent;
     280: invokevirtual #717                // Method net/minecraft/network/chat/MutableComponent.getString:()Ljava/lang/String;
     283: invokedynamic #1161,  0           // InvokeDynamic #17:makeConcatWithConstants:(Ljava/lang/String;Ljava/lang/String;)Ljava/lang/String;
     288: aastore
     289: invokespecial #1164               // Method com/hrznstudio/titanium/client/screen/addon/StateButtonInfo."<init>":(ILcom/hrznstudio/titanium/api/client/IAssetType;[Ljava/lang/String;)V
     292: aastore
     293: dup
     294: iconst_3
     295: new           #1148               // class com/hrznstudio/titanium/client/screen/addon/StateButtonInfo
     298: dup
     299: iconst_3
     300: getstatic     #1167               // Field com/hrznstudio/titanium/api/client/AssetTypes.BUTTON_SIDENESS_DISABLED:Lcom/hrznstudio/titanium/api/client/IAssetType;
     303: iconst_3
     304: anewarray     #208                // class java/lang/String
     307: dup
     308: iconst_0
     309: getstatic     #1185               // Field net/minecraft/ChatFormatting.RED:Lnet/minecraft/ChatFormatting;
     312: invokestatic  #706                // Method java/lang/String.valueOf:(Ljava/lang/Object;)Ljava/lang/String;
     315: ldc_w         #1209               // String tooltip.industrialforegoing.backpack.pickup_disabled
     318: invokestatic  #711                // InterfaceMethod net/minecraft/network/chat/Component.translatable:(Ljava/lang/String;)Lnet/minecraft/network/chat/MutableComponent;
     321: invokevirtual #717                // Method net/minecraft/network/chat/MutableComponent.getString:()Ljava/lang/String;
     324: invokedynamic #1161,  0           // InvokeDynamic #17:makeConcatWithConstants:(Ljava/lang/String;Ljava/lang/String;)Ljava/lang/String;
     329: aastore
     330: dup
     331: iconst_1
     332: getstatic     #700                // Field net/minecraft/ChatFormatting.GRAY:Lnet/minecraft/ChatFormatting;
     335: invokestatic  #706                // Method java/lang/String.valueOf:(Ljava/lang/Object;)Ljava/lang/String;
     338: ldc_w         #1195               // String tooltip.industrialforegoing.backpack.pickup_extra
     341: invokestatic  #711                // InterfaceMethod net/minecraft/network/chat/Component.translatable:(Ljava/lang/String;)Lnet/minecraft/network/chat/MutableComponent;
     344: invokevirtual #717                // Method net/minecraft/network/chat/MutableComponent.getString:()Ljava/lang/String;
     347: invokedynamic #1161,  0           // InvokeDynamic #17:makeConcatWithConstants:(Ljava/lang/String;Ljava/lang/String;)Ljava/lang/String;
     352: aastore
     353: dup
     354: iconst_2
     355: getstatic     #700                // Field net/minecraft/ChatFormatting.GRAY:Lnet/minecraft/ChatFormatting;
     358: invokestatic  #706                // Method java/lang/String.valueOf:(Ljava/lang/Object;)Ljava/lang/String;
     361: ldc_w         #1197               // String tooltip.industrialforegoing.backpack.pickup_extra_1
     364: invokestatic  #711                // InterfaceMethod net/minecraft/network/chat/Component.translatable:(Ljava/lang/String;)Lnet/minecraft/network/chat/MutableComponent;
     367: invokevirtual #717                // Method net/minecraft/network/chat/MutableComponent.getString:()Ljava/lang/String;
     370: invokedynamic #1161,  0           // InvokeDynamic #17:makeConcatWithConstants:(Ljava/lang/String;Ljava/lang/String;)Ljava/lang/String;
     375: aastore
     376: invokespecial #1164               // Method com/hrznstudio/titanium/client/screen/addon/StateButtonInfo."<init>":(ILcom/hrznstudio/titanium/api/client/IAssetType;[Ljava/lang/String;)V
     379: aastore
     380: aload_3
     381: invokespecial #1211               // Method com/buuz135/industrial/item/infinity/item/ItemInfinityBackpack$5."<init>":(Lcom/buuz135/industrial/item/infinity/item/ItemInfinityBackpack;Lcom/hrznstudio/titanium/component/button/ButtonComponent;[Lcom/hrznstudio/titanium/client/screen/addon/StateButtonInfo;Ljava/util/function/Supplier;)V
     384: areturn

  private com.hrznstudio.titanium.api.client.IScreenAddon lambda$getScreenAddons$16(int, int, java.util.function.Supplier);
    descriptor: (IILjava/util/function/Supplier;)Lcom/hrznstudio/titanium/api/client/IScreenAddon;
    Code:
       0: new           #1212               // class com/buuz135/industrial/item/infinity/item/ItemInfinityBackpack$4
       3: dup
       4: aload_0
       5: new           #1139               // class com/hrznstudio/titanium/component/button/ButtonComponent
       8: dup
       9: iload_1
      10: bipush        16
      12: iload_2
      13: iconst_0
      14: imul
      15: iadd
      16: bipush        14
      18: bipush        14
      20: invokespecial #1141               // Method com/hrznstudio/titanium/component/button/ButtonComponent."<init>":(IIII)V
      23: bipush        10
      25: invokevirtual #1144               // Method com/hrznstudio/titanium/component/button/ButtonComponent.setId:(I)Lcom/hrznstudio/titanium/component/button/ButtonComponent;
      28: iconst_2
      29: anewarray     #1148               // class com/hrznstudio/titanium/client/screen/addon/StateButtonInfo
      32: dup
      33: iconst_0
      34: new           #1148               // class com/hrznstudio/titanium/client/screen/addon/StateButtonInfo
      37: dup
      38: iconst_0
      39: getstatic     #1150               // Field com/hrznstudio/titanium/api/client/AssetTypes.BUTTON_SIDENESS_ENABLED:Lcom/hrznstudio/titanium/api/client/IAssetType;
      42: iconst_2
      43: anewarray     #208                // class java/lang/String
      46: dup
      47: iconst_0
      48: getstatic     #1175               // Field net/minecraft/ChatFormatting.GREEN:Lnet/minecraft/ChatFormatting;
      51: invokestatic  #706                // Method java/lang/String.valueOf:(Ljava/lang/Object;)Ljava/lang/String;
      54: ldc_w         #1214               // String tooltip.industrialforegoing.backpack.magnet_enabled
      57: invokestatic  #711                // InterfaceMethod net/minecraft/network/chat/Component.translatable:(Ljava/lang/String;)Lnet/minecraft/network/chat/MutableComponent;
      60: invokevirtual #717                // Method net/minecraft/network/chat/MutableComponent.getString:()Ljava/lang/String;
      63: invokedynamic #1161,  0           // InvokeDynamic #17:makeConcatWithConstants:(Ljava/lang/String;Ljava/lang/String;)Ljava/lang/String;
      68: aastore
      69: dup
      70: iconst_1
      71: getstatic     #1216               // Field net/minecraft/ChatFormatting.DARK_GRAY:Lnet/minecraft/ChatFormatting;
      74: invokestatic  #706                // Method java/lang/String.valueOf:(Ljava/lang/Object;)Ljava/lang/String;
      77: ldc_w         #1219               // String tooltip.industrialforegoing.backpack.needs_biofuel
      80: invokestatic  #711                // InterfaceMethod net/minecraft/network/chat/Component.translatable:(Ljava/lang/String;)Lnet/minecraft/network/chat/MutableComponent;
      83: invokevirtual #717                // Method net/minecraft/network/chat/MutableComponent.getString:()Ljava/lang/String;
      86: invokedynamic #1161,  0           // InvokeDynamic #17:makeConcatWithConstants:(Ljava/lang/String;Ljava/lang/String;)Ljava/lang/String;
      91: aastore
      92: invokespecial #1164               // Method com/hrznstudio/titanium/client/screen/addon/StateButtonInfo."<init>":(ILcom/hrznstudio/titanium/api/client/IAssetType;[Ljava/lang/String;)V
      95: aastore
      96: dup
      97: iconst_1
      98: new           #1148               // class com/hrznstudio/titanium/client/screen/addon/StateButtonInfo
     101: dup
     102: iconst_1
     103: getstatic     #1167               // Field com/hrznstudio/titanium/api/client/AssetTypes.BUTTON_SIDENESS_DISABLED:Lcom/hrznstudio/titanium/api/client/IAssetType;
     106: iconst_1
     107: anewarray     #208                // class java/lang/String
     110: dup
     111: iconst_0
     112: getstatic     #1185               // Field net/minecraft/ChatFormatting.RED:Lnet/minecraft/ChatFormatting;
     115: invokestatic  #706                // Method java/lang/String.valueOf:(Ljava/lang/Object;)Ljava/lang/String;
     118: ldc_w         #1221               // String tooltip.industrialforegoing.backpack.magnet_disabled
     121: invokestatic  #711                // InterfaceMethod net/minecraft/network/chat/Component.translatable:(Ljava/lang/String;)Lnet/minecraft/network/chat/MutableComponent;
     124: invokevirtual #717                // Method net/minecraft/network/chat/MutableComponent.getString:()Ljava/lang/String;
     127: invokedynamic #1161,  0           // InvokeDynamic #17:makeConcatWithConstants:(Ljava/lang/String;Ljava/lang/String;)Ljava/lang/String;
     132: aastore
     133: invokespecial #1164               // Method com/hrznstudio/titanium/client/screen/addon/StateButtonInfo."<init>":(ILcom/hrznstudio/titanium/api/client/IAssetType;[Ljava/lang/String;)V
     136: aastore
     137: aload_3
     138: invokespecial #1223               // Method com/buuz135/industrial/item/infinity/item/ItemInfinityBackpack$4."<init>":(Lcom/buuz135/industrial/item/infinity/item/ItemInfinityBackpack;Lcom/hrznstudio/titanium/component/button/ButtonComponent;[Lcom/hrznstudio/titanium/client/screen/addon/StateButtonInfo;Ljava/util/function/Supplier;)V
     141: areturn

  private static com.hrznstudio.titanium.api.client.IScreenAddon lambda$getScreenAddons$15();
    descriptor: ()Lcom/hrznstudio/titanium/api/client/IScreenAddon;
    Code:
       0: new           #1224               // class com/hrznstudio/titanium/client/screen/addon/AssetScreenAddon
       3: dup
       4: getstatic     #1226               // Field com/hrznstudio/titanium/api/client/AssetTypes.AUGMENT_BACKGROUND:Lcom/hrznstudio/titanium/api/client/IAssetType;
       7: sipush        175
      10: bipush        10
      12: iconst_1
      13: invokespecial #1229               // Method com/hrznstudio/titanium/client/screen/addon/AssetScreenAddon."<init>":(Lcom/hrznstudio/titanium/api/client/IAssetType;IIZ)V
      16: areturn

  private static com.hrznstudio.titanium.api.client.IScreenAddon lambda$getScreenAddons$14();
    descriptor: ()Lcom/hrznstudio/titanium/api/client/IScreenAddon;
    Code:
       0: new           #1224               // class com/hrznstudio/titanium/client/screen/addon/AssetScreenAddon
       3: dup
       4: getstatic     #1232               // Field com/hrznstudio/titanium/api/client/AssetTypes.AUGMENT_BACKGROUND_LEFT_TALL:Lcom/hrznstudio/titanium/api/client/IAssetType;
       7: bipush        -27
       9: bipush        10
      11: iconst_1
      12: invokespecial #1229               // Method com/hrznstudio/titanium/client/screen/addon/AssetScreenAddon."<init>":(Lcom/hrznstudio/titanium/api/client/IAssetType;IIZ)V
      15: areturn

  private com.hrznstudio.titanium.api.client.IScreenAddon lambda$getScreenAddons$13(int, int, int, java.util.function.Supplier);
    descriptor: (IIILjava/util/function/Supplier;)Lcom/hrznstudio/titanium/api/client/IScreenAddon;
    Code:
       0: new           #1235               // class com/buuz135/industrial/item/infinity/item/ItemInfinityBackpack$3
       3: dup
       4: aload_0
       5: new           #1139               // class com/hrznstudio/titanium/component/button/ButtonComponent
       8: dup
       9: bipush        17
      11: bipush        18
      13: iload_1
      14: imul
      15: iadd
      16: bipush        22
      18: bipush        18
      20: iload_2
      21: imul
      22: iadd
      23: bipush        17
      25: bipush        17
      27: invokespecial #1141               // Method com/hrznstudio/titanium/component/button/ButtonComponent."<init>":(IIII)V
      30: iconst_4
      31: invokevirtual #1144               // Method com/hrznstudio/titanium/component/button/ButtonComponent.setId:(I)Lcom/hrznstudio/titanium/component/button/ButtonComponent;
      34: iload_3
      35: aload         4
      37: invokespecial #1237               // Method com/buuz135/industrial/item/infinity/item/ItemInfinityBackpack$3."<init>":(Lcom/buuz135/industrial/item/infinity/item/ItemInfinityBackpack;Lcom/hrznstudio/titanium/component/button/ButtonComponent;ILjava/util/function/Supplier;)V
      40: areturn

  private com.buuz135.industrial.container.BackpackContainer lambda$createMenu$12(net.minecraft.world.entity.player.Player, int, com.hrznstudio.titanium.network.locator.PlayerInventoryFinder$Target);
    descriptor: (Lnet/minecraft/world/entity/player/Player;ILcom/hrznstudio/titanium/network/locator/PlayerInventoryFinder$Target;)Lcom/buuz135/industrial/container/BackpackContainer;
    Code:
       0: aload_3
       1: invokevirtual #1240               // Method com/hrznstudio/titanium/network/locator/PlayerInventoryFinder$Target.getFinder:()Lcom/hrznstudio/titanium/network/locator/PlayerInventoryFinder;
       4: invokevirtual #223                // Method com/hrznstudio/titanium/network/locator/PlayerInventoryFinder.getStackGetter:()Ljava/util/function/BiFunction;
       7: aload_1
       8: aload_3
       9: invokevirtual #1244               // Method com/hrznstudio/titanium/network/locator/PlayerInventoryFinder$Target.getSlot:()I
      12: invokestatic  #173                // Method java/lang/Integer.valueOf:(I)Ljava/lang/Integer;
      15: invokeinterface #227,  3          // InterfaceMethod java/util/function/BiFunction.apply:(Ljava/lang/Object;Ljava/lang/Object;)Ljava/lang/Object;
      20: checkcast     #158                // class net/minecraft/world/item/ItemStack
      23: astore        4
      25: aload         4
      27: invokevirtual #543                // Method net/minecraft/world/item/ItemStack.isEmpty:()Z
      30: ifne          147
      33: aload         4
      35: getstatic     #284                // Field com/buuz135/industrial/utils/IFAttachments.INFINITY_BACKPACK_ID:Ljava/util/function/Supplier;
      38: invokevirtual #287                // Method net/minecraft/world/item/ItemStack.has:(Ljava/util/function/Supplier;)Z
      41: ifne          75
      44: invokestatic  #291                // Method java/util/UUID.randomUUID:()Ljava/util/UUID;
      47: astore        5
      49: aload_1
      50: invokevirtual #617                // Method net/minecraft/world/entity/player/Player.level:()Lnet/minecraft/world/level/Level;
      53: invokestatic  #106                // Method com/buuz135/industrial/worlddata/BackpackDataManager.getData:(Lnet/minecraft/world/level/LevelAccessor;)Lcom/buuz135/industrial/worlddata/BackpackDataManager;
      56: aload         5
      58: invokevirtual #297                // Method com/buuz135/industrial/worlddata/BackpackDataManager.createBackPack:(Ljava/util/UUID;)V
      61: aload         4
      63: getstatic     #284                // Field com/buuz135/industrial/utils/IFAttachments.INFINITY_BACKPACK_ID:Ljava/util/function/Supplier;
      66: aload         5
      68: invokevirtual #301                // Method java/util/UUID.toString:()Ljava/lang/String;
      71: invokevirtual #167                // Method net/minecraft/world/item/ItemStack.set:(Ljava/util/function/Supplier;Ljava/lang/Object;)Ljava/lang/Object;
      74: pop
      75: aload         4
      77: getstatic     #284                // Field com/buuz135/industrial/utils/IFAttachments.INFINITY_BACKPACK_ID:Ljava/util/function/Supplier;
      80: invokevirtual #305                // Method net/minecraft/world/item/ItemStack.get:(Ljava/util/function/Supplier;)Ljava/lang/Object;
      83: checkcast     #208                // class java/lang/String
      86: astore        5
      88: new           #1247               // class com/buuz135/industrial/container/BackpackContainer
      91: dup
      92: invokestatic  #1249               // Method com/hrznstudio/titanium/itemstack/ItemStackHarnessRegistry.getHarnessCreators:()Ljava/util/Map;
      95: getstatic     #1255               // Field com/buuz135/industrial/module/ModuleTool.INFINITY_BACKPACK:Lnet/neoforged/neoforge/registries/DeferredHolder;
      98: invokeinterface #1259,  2         // InterfaceMethod java/util/Map.get:(Ljava/lang/Object;)Ljava/lang/Object;
     103: checkcast     #219                // class java/util/function/Function
     106: aload         4
     108: invokeinterface #218,  2          // InterfaceMethod java/util/function/Function.apply:(Ljava/lang/Object;)Ljava/lang/Object;
     113: new           #1262               // class com/hrznstudio/titanium/network/locator/instance/InventoryStackLocatorInstance
     116: dup
     117: aload_3
     118: invokevirtual #1264               // Method com/hrznstudio/titanium/network/locator/PlayerInventoryFinder$Target.getName:()Ljava/lang/String;
     121: aload_3
     122: invokevirtual #1244               // Method com/hrznstudio/titanium/network/locator/PlayerInventoryFinder$Target.getSlot:()I
     125: invokespecial #1267               // Method com/hrznstudio/titanium/network/locator/instance/InventoryStackLocatorInstance."<init>":(Ljava/lang/String;I)V
     128: new           #1270               // class com/buuz135/industrial/item/infinity/item/ItemInfinityBackpack$2
     131: dup
     132: aload_0
     133: invokespecial #1272               // Method com/buuz135/industrial/item/infinity/item/ItemInfinityBackpack$2."<init>":(Lcom/buuz135/industrial/item/infinity/item/ItemInfinityBackpack;)V
     136: aload_1
     137: invokevirtual #310                // Method net/minecraft/world/entity/player/Player.getInventory:()Lnet/minecraft/world/entity/player/Inventory;
     140: iload_2
     141: aload         5
     143: invokespecial #1275               // Method com/buuz135/industrial/container/BackpackContainer."<init>":(Ljava/lang/Object;Lcom/hrznstudio/titanium/network/locator/LocatorInstance;Lnet/minecraft/world/inventory/ContainerLevelAccess;Lnet/minecraft/world/entity/player/Inventory;ILjava/lang/String;)V
     146: areturn
     147: aconst_null
     148: areturn

  private void lambda$handleButtonMessage$11(net.minecraft.world.entity.player.Player, int, net.minecraft.nbt.CompoundTag, com.hrznstudio.titanium.network.locator.PlayerInventoryFinder$Target);
    descriptor: (Lnet/minecraft/world/entity/player/Player;ILnet/minecraft/nbt/CompoundTag;Lcom/hrznstudio/titanium/network/locator/PlayerInventoryFinder$Target;)V
    Code:
       0: aload         4
       2: invokevirtual #1240               // Method com/hrznstudio/titanium/network/locator/PlayerInventoryFinder$Target.getFinder:()Lcom/hrznstudio/titanium/network/locator/PlayerInventoryFinder;
       5: invokevirtual #223                // Method com/hrznstudio/titanium/network/locator/PlayerInventoryFinder.getStackGetter:()Ljava/util/function/BiFunction;
       8: aload_1
       9: aload         4
      11: invokevirtual #1244               // Method com/hrznstudio/titanium/network/locator/PlayerInventoryFinder$Target.getSlot:()I
      14: invokestatic  #173                // Method java/lang/Integer.valueOf:(I)Ljava/lang/Integer;
      17: invokeinterface #227,  3          // InterfaceMethod java/util/function/BiFunction.apply:(Ljava/lang/Object;Ljava/lang/Object;)Ljava/lang/Object;
      22: checkcast     #158                // class net/minecraft/world/item/ItemStack
      25: astore        5
      27: aload         5
      29: invokevirtual #543                // Method net/minecraft/world/item/ItemStack.isEmpty:()Z
      32: ifne          44
      35: aload_0
      36: iload_2
      37: aload_1
      38: aload_3
      39: aload         5
      41: invokevirtual #1278               // Method handleButtonMessage:(ILnet/minecraft/world/entity/player/Player;Lnet/minecraft/nbt/CompoundTag;Lnet/minecraft/world/item/ItemStack;)V
      44: return

  private com.buuz135.industrial.item.infinity.InfinityEnergyStorage lambda$getEnergyConstructor$10(net.minecraft.world.item.ItemStack);
    descriptor: (Lnet/minecraft/world/item/ItemStack;)Lcom/buuz135/industrial/item/infinity/InfinityEnergyStorage;
    Code:
       0: new           #1282               // class com/buuz135/industrial/item/infinity/item/ItemInfinityBackpack$1
       3: dup
       4: aload_0
       5: getstatic     #85                 // Field com/buuz135/industrial/item/infinity/InfinityTier.ARTIFACT:Lcom/buuz135/industrial/item/infinity/InfinityTier;
       8: invokevirtual #1284               // Method com/buuz135/industrial/item/infinity/InfinityTier.getPowerNeeded:()J
      11: bipush        -21
      13: bipush        24
      15: aload_1
      16: invokespecial #1287               // Method com/buuz135/industrial/item/infinity/item/ItemInfinityBackpack$1."<init>":(Lcom/buuz135/industrial/item/infinity/item/ItemInfinityBackpack;JIILnet/minecraft/world/item/ItemStack;)V
      19: areturn

  private static com.buuz135.industrial.item.infinity.InfinityTankStorage lambda$getTankConstructor$9(net.minecraft.world.item.ItemStack, int);
    descriptor: (Lnet/minecraft/world/item/ItemStack;I)Lcom/buuz135/industrial/item/infinity/InfinityTankStorage;
    Code:
       0: new           #1290               // class com/buuz135/industrial/item/infinity/InfinityTankStorage
       3: dup
       4: aload_0
       5: iconst_3
       6: anewarray     #1292               // class com/buuz135/industrial/item/infinity/InfinityTankStorage$TankDefinition
       9: dup
      10: iconst_0
      11: new           #1292               // class com/buuz135/industrial/item/infinity/InfinityTankStorage$TankDefinition
      14: dup
      15: ldc_w         #1294               // String biofuel
      18: ldc_w         #1296               // int 1000000
      21: bipush        -21
      23: iload_1
      24: iconst_0
      25: iadd
      26: invokedynamic #1297,  0           // InvokeDynamic #19:test:()Ljava/util/function/Predicate;
      31: iconst_1
      32: iconst_1
      33: getstatic     #1298               // Field com/hrznstudio/titanium/component/fluid/FluidTankComponent$Type.SMALL:Lcom/hrznstudio/titanium/component/fluid/FluidTankComponent$Type;
      36: new           #486                // class net/neoforged/neoforge/fluids/FluidStack
      39: dup
      40: getstatic     #792                // Field com/buuz135/industrial/module/ModuleCore.BIOFUEL:Lcom/hrznstudio/titanium/fluid/TitaniumFluidInstance;
      43: invokevirtual #499                // Method com/hrznstudio/titanium/fluid/TitaniumFluidInstance.getSourceFluid:()Lnet/neoforged/neoforge/registries/DeferredHolder;
      46: invokevirtual #1304               // Method net/neoforged/neoforge/registries/DeferredHolder.get:()Ljava/lang/Object;
      49: checkcast     #1307               // class net/minecraft/world/level/material/Fluid
      52: sipush        1000
      55: invokespecial #1309               // Method net/neoforged/neoforge/fluids/FluidStack."<init>":(Lnet/minecraft/world/level/material/Fluid;I)V
      58: invokespecial #1312               // Method com/buuz135/industrial/item/infinity/InfinityTankStorage$TankDefinition."<init>":(Ljava/lang/String;IIILjava/util/function/Predicate;ZZLcom/hrznstudio/titanium/component/fluid/FluidTankComponent$Type;Lnet/neoforged/neoforge/fluids/FluidStack;)V
      61: aastore
      62: dup
      63: iconst_1
      64: new           #1292               // class com/buuz135/industrial/item/infinity/InfinityTankStorage$TankDefinition
      67: dup
      68: ldc_w         #1315               // String essence
      71: ldc_w         #1296               // int 1000000
      74: bipush        -21
      76: iload_1
      77: bipush        25
      79: iadd
      80: invokedynamic #1317,  0           // InvokeDynamic #20:test:()Ljava/util/function/Predicate;
      85: iconst_1
      86: iconst_1
      87: getstatic     #1298               // Field com/hrznstudio/titanium/component/fluid/FluidTankComponent$Type.SMALL:Lcom/hrznstudio/titanium/component/fluid/FluidTankComponent$Type;
      90: new           #486                // class net/neoforged/neoforge/fluids/FluidStack
      93: dup
      94: getstatic     #1318               // Field com/buuz135/industrial/module/ModuleCore.ESSENCE:Lcom/hrznstudio/titanium/fluid/TitaniumFluidInstance;
      97: invokevirtual #499                // Method com/hrznstudio/titanium/fluid/TitaniumFluidInstance.getSourceFluid:()Lnet/neoforged/neoforge/registries/DeferredHolder;
     100: invokevirtual #1304               // Method net/neoforged/neoforge/registries/DeferredHolder.get:()Ljava/lang/Object;
     103: checkcast     #1307               // class net/minecraft/world/level/material/Fluid
     106: sipush        1000
     109: invokespecial #1309               // Method net/neoforged/neoforge/fluids/FluidStack."<init>":(Lnet/minecraft/world/level/material/Fluid;I)V
     112: invokespecial #1312               // Method com/buuz135/industrial/item/infinity/InfinityTankStorage$TankDefinition."<init>":(Ljava/lang/String;IIILjava/util/function/Predicate;ZZLcom/hrznstudio/titanium/component/fluid/FluidTankComponent$Type;Lnet/neoforged/neoforge/fluids/FluidStack;)V
     115: aastore
     116: dup
     117: iconst_2
     118: new           #1292               // class com/buuz135/industrial/item/infinity/InfinityTankStorage$TankDefinition
     121: dup
     122: ldc_w         #1321               // String meat
     125: ldc_w         #1296               // int 1000000
     128: bipush        -21
     130: iload_1
     131: bipush        50
     133: iadd
     134: invokedynamic #1323,  0           // InvokeDynamic #21:test:()Ljava/util/function/Predicate;
     139: iconst_0
     140: iconst_1
     141: getstatic     #1298               // Field com/hrznstudio/titanium/component/fluid/FluidTankComponent$Type.SMALL:Lcom/hrznstudio/titanium/component/fluid/FluidTankComponent$Type;
     144: new           #486                // class net/neoforged/neoforge/fluids/FluidStack
     147: dup
     148: getstatic     #493                // Field com/buuz135/industrial/module/ModuleCore.MEAT:Lcom/hrznstudio/titanium/fluid/TitaniumFluidInstance;
     151: invokevirtual #499                // Method com/hrznstudio/titanium/fluid/TitaniumFluidInstance.getSourceFluid:()Lnet/neoforged/neoforge/registries/DeferredHolder;
     154: invokevirtual #1304               // Method net/neoforged/neoforge/registries/DeferredHolder.get:()Ljava/lang/Object;
     157: checkcast     #1307               // class net/minecraft/world/level/material/Fluid
     160: sipush        1000
     163: invokespecial #1309               // Method net/neoforged/neoforge/fluids/FluidStack."<init>":(Lnet/minecraft/world/level/material/Fluid;I)V
     166: invokespecial #1312               // Method com/buuz135/industrial/item/infinity/InfinityTankStorage$TankDefinition."<init>":(Ljava/lang/String;IIILjava/util/function/Predicate;ZZLcom/hrznstudio/titanium/component/fluid/FluidTankComponent$Type;Lnet/neoforged/neoforge/fluids/FluidStack;)V
     169: aastore
     170: invokespecial #1324               // Method com/buuz135/industrial/item/infinity/InfinityTankStorage."<init>":(Lnet/minecraft/world/item/ItemStack;[Lcom/buuz135/industrial/item/infinity/InfinityTankStorage$TankDefinition;)V
     173: areturn

  private static boolean lambda$getTankConstructor$8(net.neoforged.neoforge.fluids.FluidStack);
    descriptor: (Lnet/neoforged/neoforge/fluids/FluidStack;)Z
    Code:
       0: aload_0
       1: invokevirtual #1327               // Method net/neoforged/neoforge/fluids/FluidStack.getFluid:()Lnet/minecraft/world/level/material/Fluid;
       4: getstatic     #493                // Field com/buuz135/industrial/module/ModuleCore.MEAT:Lcom/hrznstudio/titanium/fluid/TitaniumFluidInstance;
       7: invokevirtual #499                // Method com/hrznstudio/titanium/fluid/TitaniumFluidInstance.getSourceFluid:()Lnet/neoforged/neoforge/registries/DeferredHolder;
      10: invokevirtual #1304               // Method net/neoforged/neoforge/registries/DeferredHolder.get:()Ljava/lang/Object;
      13: checkcast     #1307               // class net/minecraft/world/level/material/Fluid
      16: invokevirtual #1331               // Method net/minecraft/world/level/material/Fluid.isSame:(Lnet/minecraft/world/level/material/Fluid;)Z
      19: ireturn

  private static boolean lambda$getTankConstructor$7(net.neoforged.neoforge.fluids.FluidStack);
    descriptor: (Lnet/neoforged/neoforge/fluids/FluidStack;)Z
    Code:
       0: aload_0
       1: getstatic     #1335               // Field com/buuz135/industrial/utils/IndustrialTags$Fluids.EXPERIENCE:Lnet/minecraft/tags/TagKey;
       4: invokevirtual #1340               // Method net/neoforged/neoforge/fluids/FluidStack.is:(Lnet/minecraft/tags/TagKey;)Z
       7: ireturn

  private static boolean lambda$getTankConstructor$6(net.neoforged.neoforge.fluids.FluidStack);
    descriptor: (Lnet/neoforged/neoforge/fluids/FluidStack;)Z
    Code:
       0: aload_0
       1: invokevirtual #1327               // Method net/neoforged/neoforge/fluids/FluidStack.getFluid:()Lnet/minecraft/world/level/material/Fluid;
       4: getstatic     #792                // Field com/buuz135/industrial/module/ModuleCore.BIOFUEL:Lcom/hrznstudio/titanium/fluid/TitaniumFluidInstance;
       7: invokevirtual #499                // Method com/hrznstudio/titanium/fluid/TitaniumFluidInstance.getSourceFluid:()Lnet/neoforged/neoforge/registries/DeferredHolder;
      10: invokevirtual #1304               // Method net/neoforged/neoforge/registries/DeferredHolder.get:()Ljava/lang/Object;
      13: checkcast     #1307               // class net/minecraft/world/level/material/Fluid
      16: invokevirtual #1331               // Method net/minecraft/world/level/material/Fluid.isSame:(Lnet/minecraft/world/level/material/Fluid;)Z
      19: ireturn

  private static void lambda$use$5(net.minecraft.world.InteractionHand, net.minecraft.network.RegistryFriendlyByteBuf);
    descriptor: (Lnet/minecraft/world/InteractionHand;Lnet/minecraft/network/RegistryFriendlyByteBuf;)V
    Code:
       0: aload_1
       1: new           #1343               // class com/hrznstudio/titanium/network/locator/instance/HeldStackLocatorInstance
       4: dup
       5: aload_0
       6: getstatic     #1345               // Field net/minecraft/world/InteractionHand.MAIN_HAND:Lnet/minecraft/world/InteractionHand;
       9: if_acmpne     16
      12: iconst_1
      13: goto          17
      16: iconst_0
      17: invokespecial #1351               // Method com/hrznstudio/titanium/network/locator/instance/HeldStackLocatorInstance."<init>":(Z)V
      20: invokestatic  #1353               // Method com/hrznstudio/titanium/network/locator/LocatorFactory.writePacketBuffer:(Lnet/minecraft/network/RegistryFriendlyByteBuf;Lcom/hrznstudio/titanium/network/locator/LocatorInstance;)V
      23: return

  private static void lambda$new$4(net.neoforged.neoforge.event.entity.player.PlayerXpEvent$PickupXp);
    descriptor: (Lnet/neoforged/neoforge/event/entity/player/PlayerXpEvent$PickupXp;)V
    Code:
       0: aload_0
       1: invokevirtual #1359               // Method net/neoforged/neoforge/event/entity/player/PlayerXpEvent$PickupXp.getEntity:()Lnet/minecraft/world/entity/player/Player;
       4: invokestatic  #689                // Method findFirstBackpack:(Lnet/minecraft/world/entity/player/Player;)Ljava/util/Optional;
       7: aload_0
       8: invokedynamic #1362,  0           // InvokeDynamic #22:accept:(Lnet/neoforged/neoforge/event/entity/player/PlayerXpEvent$PickupXp;)Ljava/util/function/Consumer;
      13: invokevirtual #696                // Method java/util/Optional.ifPresent:(Ljava/util/function/Consumer;)V
      16: return

  private static void lambda$new$3(net.neoforged.neoforge.event.entity.player.PlayerXpEvent$PickupXp, com.hrznstudio.titanium.network.locator.PlayerInventoryFinder$Target);
    descriptor: (Lnet/neoforged/neoforge/event/entity/player/PlayerXpEvent$PickupXp;Lcom/hrznstudio/titanium/network/locator/PlayerInventoryFinder$Target;)V
    Code:
       0: aload_1
       1: invokevirtual #1240               // Method com/hrznstudio/titanium/network/locator/PlayerInventoryFinder$Target.getFinder:()Lcom/hrznstudio/titanium/network/locator/PlayerInventoryFinder;
       4: invokevirtual #223                // Method com/hrznstudio/titanium/network/locator/PlayerInventoryFinder.getStackGetter:()Ljava/util/function/BiFunction;
       7: aload_0
       8: invokevirtual #1359               // Method net/neoforged/neoforge/event/entity/player/PlayerXpEvent$PickupXp.getEntity:()Lnet/minecraft/world/entity/player/Player;
      11: aload_1
      12: invokevirtual #1244               // Method com/hrznstudio/titanium/network/locator/PlayerInventoryFinder$Target.getSlot:()I
      15: invokestatic  #173                // Method java/lang/Integer.valueOf:(I)Ljava/lang/Integer;
      18: invokeinterface #227,  3          // InterfaceMethod java/util/function/BiFunction.apply:(Ljava/lang/Object;Ljava/lang/Object;)Ljava/lang/Object;
      23: checkcast     #158                // class net/minecraft/world/item/ItemStack
      26: astore_2
      27: aload_2
      28: invokevirtual #543                // Method net/minecraft/world/item/ItemStack.isEmpty:()Z
      31: ifne          169
      34: aload_2
      35: invokevirtual #232                // Method net/minecraft/world/item/ItemStack.getItem:()Lnet/minecraft/world/item/Item;
      38: instanceof    #20                 // class com/buuz135/industrial/item/infinity/item/ItemInfinityBackpack
      41: ifeq          169
      44: aload_2
      45: invokestatic  #670                // Method getPickUpMode:(Lnet/minecraft/world/item/ItemStack;)I
      48: iconst_2
      49: if_icmpeq     59
      52: aload_2
      53: invokestatic  #670                // Method getPickUpMode:(Lnet/minecraft/world/item/ItemStack;)I
      56: ifne          169
      59: aload_2
      60: getstatic     #452                // Field net/neoforged/neoforge/capabilities/Capabilities$FluidHandler.ITEM:Lnet/neoforged/neoforge/capabilities/ItemCapability;
      63: invokevirtual #458                // Method net/minecraft/world/item/ItemStack.getCapability:(Lnet/neoforged/neoforge/capabilities/ItemCapability;)Ljava/lang/Object;
      66: checkcast     #462                // class net/neoforged/neoforge/fluids/capability/IFluidHandlerItem
      69: astore_3
      70: aload_3
      71: ifnull        169
      74: aload_0
      75: invokevirtual #1365               // Method net/neoforged/neoforge/event/entity/player/PlayerXpEvent$PickupXp.getOrb:()Lnet/minecraft/world/entity/ExperienceOrb;
      78: astore        4
      80: aload_3
      81: new           #486                // class net/neoforged/neoforge/fluids/FluidStack
      84: dup
      85: getstatic     #1318               // Field com/buuz135/industrial/module/ModuleCore.ESSENCE:Lcom/hrznstudio/titanium/fluid/TitaniumFluidInstance;
      88: invokevirtual #499                // Method com/hrznstudio/titanium/fluid/TitaniumFluidInstance.getSourceFluid:()Lnet/neoforged/neoforge/registries/DeferredHolder;
      91: invokevirtual #1304               // Method net/neoforged/neoforge/registries/DeferredHolder.get:()Ljava/lang/Object;
      94: checkcast     #1307               // class net/minecraft/world/level/material/Fluid
      97: aload         4
      99: invokevirtual #1369               // Method net/minecraft/world/entity/ExperienceOrb.getValue:()I
     102: bipush        20
     104: imul
     105: invokespecial #1309               // Method net/neoforged/neoforge/fluids/FluidStack."<init>":(Lnet/minecraft/world/level/material/Fluid;I)V
     108: getstatic     #1374               // Field net/neoforged/neoforge/fluids/capability/IFluidHandler$FluidAction.SIMULATE:Lnet/neoforged/neoforge/fluids/capability/IFluidHandler$FluidAction;
     111: invokeinterface #1377,  3         // InterfaceMethod net/neoforged/neoforge/fluids/capability/IFluidHandlerItem.fill:(Lnet/neoforged/neoforge/fluids/FluidStack;Lnet/neoforged/neoforge/fluids/capability/IFluidHandler$FluidAction;)I
     116: ifle          169
     119: aload_3
     120: new           #486                // class net/neoforged/neoforge/fluids/FluidStack
     123: dup
     124: getstatic     #1318               // Field com/buuz135/industrial/module/ModuleCore.ESSENCE:Lcom/hrznstudio/titanium/fluid/TitaniumFluidInstance;
     127: invokevirtual #499                // Method com/hrznstudio/titanium/fluid/TitaniumFluidInstance.getSourceFluid:()Lnet/neoforged/neoforge/registries/DeferredHolder;
     130: invokevirtual #1304               // Method net/neoforged/neoforge/registries/DeferredHolder.get:()Ljava/lang/Object;
     133: checkcast     #1307               // class net/minecraft/world/level/material/Fluid
     136: aload         4
     138: invokevirtual #1369               // Method net/minecraft/world/entity/ExperienceOrb.getValue:()I
     141: bipush        20
     143: imul
     144: invokespecial #1309               // Method net/neoforged/neoforge/fluids/FluidStack."<init>":(Lnet/minecraft/world/level/material/Fluid;I)V
     147: getstatic     #508                // Field net/neoforged/neoforge/fluids/capability/IFluidHandler$FluidAction.EXECUTE:Lnet/neoforged/neoforge/fluids/capability/IFluidHandler$FluidAction;
     150: invokeinterface #1377,  3         // InterfaceMethod net/neoforged/neoforge/fluids/capability/IFluidHandlerItem.fill:(Lnet/neoforged/neoforge/fluids/FluidStack;Lnet/neoforged/neoforge/fluids/capability/IFluidHandler$FluidAction;)I
     155: pop
     156: aload         4
     158: getstatic     #1381               // Field net/minecraft/world/entity/Entity$RemovalReason.KILLED:Lnet/minecraft/world/entity/Entity$RemovalReason;
     161: invokevirtual #1387               // Method net/minecraft/world/entity/ExperienceOrb.remove:(Lnet/minecraft/world/entity/Entity$RemovalReason;)V
     164: aload_0
     165: iconst_1
     166: invokevirtual #1391               // Method net/neoforged/neoforge/event/entity/player/PlayerXpEvent$PickupXp.setCanceled:(Z)V
     169: return

  private static boolean lambda$new$2(net.neoforged.neoforge.event.entity.player.PlayerXpEvent$PickupXp);
    descriptor: (Lnet/neoforged/neoforge/event/entity/player/PlayerXpEvent$PickupXp;)Z
    Code:
       0: aload_0
       1: invokevirtual #1365               // Method net/neoforged/neoforge/event/entity/player/PlayerXpEvent$PickupXp.getOrb:()Lnet/minecraft/world/entity/ExperienceOrb;
       4: invokevirtual #1394               // Method net/minecraft/world/entity/ExperienceOrb.isAlive:()Z
       7: ireturn

  private static void lambda$new$1(net.neoforged.neoforge.event.entity.player.ItemEntityPickupEvent$Pre);
    descriptor: (Lnet/neoforged/neoforge/event/entity/player/ItemEntityPickupEvent$Pre;)V
    Code:
       0: aload_0
       1: invokevirtual #1397               // Method net/neoforged/neoforge/event/entity/player/ItemEntityPickupEvent$Pre.getPlayer:()Lnet/minecraft/world/entity/player/Player;
       4: invokestatic  #1398               // Method findAllBackpacks:(Lnet/minecraft/world/entity/player/Player;)Ljava/util/List;
       7: invokeinterface #403,  1          // InterfaceMethod java/util/List.iterator:()Ljava/util/Iterator;
      12: astore_1
      13: aload_1
      14: invokeinterface #200,  1          // InterfaceMethod java/util/Iterator.hasNext:()Z
      19: ifeq          286
      22: aload_1
      23: invokeinterface #205,  1          // InterfaceMethod java/util/Iterator.next:()Ljava/lang/Object;
      28: checkcast     #236                // class com/hrznstudio/titanium/network/locator/PlayerInventoryFinder$Target
      31: astore_2
      32: aload_2
      33: invokevirtual #1240               // Method com/hrznstudio/titanium/network/locator/PlayerInventoryFinder$Target.getFinder:()Lcom/hrznstudio/titanium/network/locator/PlayerInventoryFinder;
      36: invokevirtual #223                // Method com/hrznstudio/titanium/network/locator/PlayerInventoryFinder.getStackGetter:()Ljava/util/function/BiFunction;
      39: aload_0
      40: invokevirtual #1397               // Method net/neoforged/neoforge/event/entity/player/ItemEntityPickupEvent$Pre.getPlayer:()Lnet/minecraft/world/entity/player/Player;
      43: aload_2
      44: invokevirtual #1244               // Method com/hrznstudio/titanium/network/locator/PlayerInventoryFinder$Target.getSlot:()I
      47: invokestatic  #173                // Method java/lang/Integer.valueOf:(I)Ljava/lang/Integer;
      50: invokeinterface #227,  3          // InterfaceMethod java/util/function/BiFunction.apply:(Ljava/lang/Object;Ljava/lang/Object;)Ljava/lang/Object;
      55: checkcast     #158                // class net/minecraft/world/item/ItemStack
      58: astore_3
      59: aload_3
      60: invokevirtual #543                // Method net/minecraft/world/item/ItemStack.isEmpty:()Z
      63: ifne          283
      66: aload_3
      67: invokevirtual #232                // Method net/minecraft/world/item/ItemStack.getItem:()Lnet/minecraft/world/item/Item;
      70: instanceof    #20                 // class com/buuz135/industrial/item/infinity/item/ItemInfinityBackpack
      73: ifeq          283
      76: aload_3
      77: invokestatic  #670                // Method getPickUpMode:(Lnet/minecraft/world/item/ItemStack;)I
      80: iconst_1
      81: if_icmpeq     91
      84: aload_3
      85: invokestatic  #670                // Method getPickUpMode:(Lnet/minecraft/world/item/ItemStack;)I
      88: ifne          283
      91: aload_0
      92: invokevirtual #1402               // Method net/neoforged/neoforge/event/entity/player/ItemEntityPickupEvent$Pre.getItemEntity:()Lnet/minecraft/world/entity/item/ItemEntity;
      95: invokevirtual #424                // Method net/minecraft/world/entity/item/ItemEntity.level:()Lnet/minecraft/world/level/Level;
      98: invokestatic  #106                // Method com/buuz135/industrial/worlddata/BackpackDataManager.getData:(Lnet/minecraft/world/level/LevelAccessor;)Lcom/buuz135/industrial/worlddata/BackpackDataManager;
     101: astore        4
     103: aload         4
     105: ifnull        283
     108: aload_3
     109: getstatic     #284                // Field com/buuz135/industrial/utils/IFAttachments.INFINITY_BACKPACK_ID:Ljava/util/function/Supplier;
     112: invokevirtual #287                // Method net/minecraft/world/item/ItemStack.has:(Ljava/util/function/Supplier;)Z
     115: ifeq          283
     118: aload         4
     120: aload_3
     121: getstatic     #284                // Field com/buuz135/industrial/utils/IFAttachments.INFINITY_BACKPACK_ID:Ljava/util/function/Supplier;
     124: invokevirtual #305                // Method net/minecraft/world/item/ItemStack.get:(Ljava/util/function/Supplier;)Ljava/lang/Object;
     127: checkcast     #208                // class java/lang/String
     130: invokevirtual #112                // Method com/buuz135/industrial/worlddata/BackpackDataManager.getBackpack:(Ljava/lang/String;)Lcom/buuz135/industrial/worlddata/BackpackDataManager$BackpackItemHandler;
     133: astore        5
     135: aload         5
     137: ifnull        283
     140: aload_0
     141: invokevirtual #1402               // Method net/neoforged/neoforge/event/entity/player/ItemEntityPickupEvent$Pre.getItemEntity:()Lnet/minecraft/world/entity/item/ItemEntity;
     144: invokevirtual #1406               // Method net/minecraft/world/entity/item/ItemEntity.getItem:()Lnet/minecraft/world/item/ItemStack;
     147: astore        6
     149: iconst_0
     150: istore        7
     152: iload         7
     154: aload         5
     156: invokevirtual #1408               // Method com/buuz135/industrial/worlddata/BackpackDataManager$BackpackItemHandler.getSlots:()I
     159: if_icmpge     283
     162: aload         5
     164: iload         7
     166: invokevirtual #544                // Method com/buuz135/industrial/worlddata/BackpackDataManager$BackpackItemHandler.getSlotDefinition:(I)Lcom/buuz135/industrial/worlddata/BackpackDataManager$SlotDefinition;
     169: invokevirtual #1411               // Method com/buuz135/industrial/worlddata/BackpackDataManager$SlotDefinition.getStack:()Lnet/minecraft/world/item/ItemStack;
     172: invokevirtual #1109               // Method net/minecraft/world/item/ItemStack.copy:()Lnet/minecraft/world/item/ItemStack;
     175: astore        8
     177: aload         8
     179: iconst_1
     180: invokevirtual #569                // Method net/minecraft/world/item/ItemStack.setCount:(I)V
     183: aload         8
     185: invokevirtual #543                // Method net/minecraft/world/item/ItemStack.isEmpty:()Z
     188: ifne          277
     191: aload         6
     193: aload         8
     195: invokestatic  #622                // Method net/minecraft/world/item/ItemStack.isSameItemSameComponents:(Lnet/minecraft/world/item/ItemStack;Lnet/minecraft/world/item/ItemStack;)Z
     198: ifeq          277
     201: aload         5
     203: iload         7
     205: aload         6
     207: invokevirtual #1109               // Method net/minecraft/world/item/ItemStack.copy:()Lnet/minecraft/world/item/ItemStack;
     210: iconst_0
     211: invokevirtual #649                // Method com/buuz135/industrial/worlddata/BackpackDataManager$BackpackItemHandler.insertItem:(ILnet/minecraft/world/item/ItemStack;Z)Lnet/minecraft/world/item/ItemStack;
     214: astore        9
     216: aload         6
     218: aload         9
     220: invokevirtual #555                // Method net/minecraft/world/item/ItemStack.getCount:()I
     223: invokevirtual #569                // Method net/minecraft/world/item/ItemStack.setCount:(I)V
     226: aload_0
     227: getstatic     #1414               // Field net/neoforged/neoforge/common/util/TriState.FALSE:Lnet/neoforged/neoforge/common/util/TriState;
     230: invokevirtual #1420               // Method net/neoforged/neoforge/event/entity/player/ItemEntityPickupEvent$Pre.setCanPickup:(Lnet/neoforged/neoforge/common/util/TriState;)V
     233: aload_0
     234: invokevirtual #1397               // Method net/neoforged/neoforge/event/entity/player/ItemEntityPickupEvent$Pre.getPlayer:()Lnet/minecraft/world/entity/player/Player;
     237: astore        11
     239: aload         11
     241: instanceof    #282                // class net/minecraft/server/level/ServerPlayer
     244: ifeq          276
     247: aload         11
     249: checkcast     #282                // class net/minecraft/server/level/ServerPlayer
     252: astore        10
     254: aload_0
     255: invokevirtual #1402               // Method net/neoforged/neoforge/event/entity/player/ItemEntityPickupEvent$Pre.getItemEntity:()Lnet/minecraft/world/entity/item/ItemEntity;
     258: invokevirtual #424                // Method net/minecraft/world/entity/item/ItemEntity.level:()Lnet/minecraft/world/level/Level;
     261: aload_3
     262: getstatic     #284                // Field com/buuz135/industrial/utils/IFAttachments.INFINITY_BACKPACK_ID:Ljava/util/function/Supplier;
     265: invokevirtual #305                // Method net/minecraft/world/item/ItemStack.get:(Ljava/util/function/Supplier;)Ljava/lang/Object;
     268: checkcast     #208                // class java/lang/String
     271: aload         10
     273: invokestatic  #326                // Method sync:(Lnet/minecraft/world/level/Level;Ljava/lang/String;Lnet/minecraft/server/level/ServerPlayer;)V
     276: return
     277: iinc          7, 1
     280: goto          152
     283: goto          13
     286: return

  private static boolean lambda$new$0(net.neoforged.neoforge.event.entity.player.ItemEntityPickupEvent$Pre);
    descriptor: (Lnet/neoforged/neoforge/event/entity/player/ItemEntityPickupEvent$Pre;)Z
    Code:
       0: aload_0
       1: invokevirtual #1402               // Method net/neoforged/neoforge/event/entity/player/ItemEntityPickupEvent$Pre.getItemEntity:()Lnet/minecraft/world/entity/item/ItemEntity;
       4: invokevirtual #1406               // Method net/minecraft/world/entity/item/ItemEntity.getItem:()Lnet/minecraft/world/item/ItemStack;
       7: invokevirtual #543                // Method net/minecraft/world/item/ItemStack.isEmpty:()Z
      10: ifne          17
      13: iconst_1
      14: goto          18
      17: iconst_0
      18: ireturn

  static {};
    descriptor: ()V
    Code:
       0: iconst_0
       1: putstatic     #19                 // Field POWER_CONSUMPTION:I
       4: iconst_1
       5: putstatic     #25                 // Field FUEL_CONSUMPTION:I
       8: return
}
