Compiled from "FortuneCoinItem.java"
public class reliquary.item.FortuneCoinItem extends reliquary.item.ItemBase implements reliquary.api.IPedestalActionItem,reliquary.item.util.ICuriosItem {
  private static final java.lang.String PREVENT_REMOTE_MOVEMENT;
    descriptor: Ljava/lang/String;

  private static final java.lang.String ALLOW_MACHINE_MOVEMENT;
    descriptor: Ljava/lang/String;

  private static final java.util.Set<reliquary.item.FortuneCoinItem$IFortuneCoinPickupChecker> pickupCheckers;
    descriptor: Ljava/util/Set;

  public static void addFortuneCoinPickupChecker(reliquary.item.FortuneCoinItem$IFortuneCoinPickupChecker);
    descriptor: (Lreliquary/item/FortuneCoinItem$IFortuneCoinPickupChecker;)V
    Code:
       0: getstatic     #1                  // Field pickupCheckers:Ljava/util/Set;
       3: aload_0
       4: invokeinterface #7,  2            // InterfaceMethod java/util/Set.add:(Ljava/lang/Object;)Z
       9: pop
      10: return

  public reliquary.item.FortuneCoinItem();
    descriptor: ()V
    Code:
       0: aload_0
       1: new           #13                 // class net/minecraft/world/item/Item$Properties
       4: dup
       5: invokespecial #15                 // Method net/minecraft/world/item/Item$Properties."<init>":()V
       8: iconst_1
       9: invokevirtual #19                 // Method net/minecraft/world/item/Item$Properties.stacksTo:(I)Lnet/minecraft/world/item/Item$Properties;
      12: getstatic     #23                 // Field net/minecraft/world/item/Rarity.EPIC:Lnet/minecraft/world/item/Rarity;
      15: invokevirtual #29                 // Method net/minecraft/world/item/Item$Properties.rarity:(Lnet/minecraft/world/item/Rarity;)Lnet/minecraft/world/item/Item$Properties;
      18: invokespecial #33                 // Method reliquary/item/ItemBase."<init>":(Lnet/minecraft/world/item/Item$Properties;)V
      21: return

  public void onEquipped(java.lang.String, net.minecraft.world.entity.LivingEntity);
    descriptor: (Ljava/lang/String;Lnet/minecraft/world/entity/LivingEntity;)V
    Code:
       0: aload_2
       1: invokevirtual #38                 // Method net/minecraft/world/entity/LivingEntity.level:()Lnet/minecraft/world/level/Level;
       4: getfield      #44                 // Field net/minecraft/world/level/Level.isClientSide:Z
       7: ifeq          38
      10: aload_2
      11: getstatic     #50                 // Field net/minecraft/sounds/SoundEvents.EXPERIENCE_ORB_PICKUP:Lnet/minecraft/sounds/SoundEvent;
      14: ldc           #56                 // float 0.1f
      16: ldc           #57                 // float 0.5f
      18: aload_2
      19: invokevirtual #38                 // Method net/minecraft/world/entity/LivingEntity.level:()Lnet/minecraft/world/level/Level;
      22: getfield      #58                 // Field net/minecraft/world/level/Level.random:Lnet/minecraft/util/RandomSource;
      25: invokestatic  #62                 // Method reliquary/util/RandHelper.getRandomMinusOneToOne:(Lnet/minecraft/util/RandomSource;)F
      28: ldc           #68                 // float 0.7f
      30: fmul
      31: ldc           #69                 // float 2.2f
      33: fadd
      34: fmul
      35: invokevirtual #70                 // Method net/minecraft/world/entity/LivingEntity.playSound:(Lnet/minecraft/sounds/SoundEvent;FF)V
      38: return

  public reliquary.item.util.ICuriosItem$Type getCuriosType();
    descriptor: ()Lreliquary/item/util/ICuriosItem$Type;
    Code:
       0: getstatic     #74                 // Field reliquary/item/util/ICuriosItem$Type.NECKLACE:Lreliquary/item/util/ICuriosItem$Type;
       3: areturn

  public void onWornTick(net.minecraft.world.item.ItemStack, net.minecraft.world.entity.LivingEntity);
    descriptor: (Lnet/minecraft/world/item/ItemStack;Lnet/minecraft/world/entity/LivingEntity;)V
    Code:
       0: aload_0
       1: aload_1
       2: aload_2
       3: invokevirtual #38                 // Method net/minecraft/world/entity/LivingEntity.level:()Lnet/minecraft/world/level/Level;
       6: aload_2
       7: iconst_0
       8: iconst_0
       9: invokevirtual #80                 // Method inventoryTick:(Lnet/minecraft/world/item/ItemStack;Lnet/minecraft/world/level/Level;Lnet/minecraft/world/entity/Entity;IZ)V
      12: return

  protected void addMoreInformation(net.minecraft.world.item.ItemStack, net.minecraft.core.HolderLookup$Provider, reliquary.util.TooltipBuilder);
    descriptor: (Lnet/minecraft/world/item/ItemStack;Lnet/minecraft/core/HolderLookup$Provider;Lreliquary/util/TooltipBuilder;)V
    Code:
       0: aload_3
       1: aload_0
       2: ldc           #84                 // String .tooltip2
       4: iconst_0
       5: anewarray     #86                 // class java/lang/Object
       8: invokevirtual #88                 // Method reliquary/util/TooltipBuilder.description:(Lnet/minecraft/world/item/Item;Ljava/lang/String;[Ljava/lang/Object;)Lreliquary/util/TooltipBuilder;
      11: pop
      12: return

  protected boolean hasMoreInformation(net.minecraft.world.item.ItemStack);
    descriptor: (Lnet/minecraft/world/item/ItemStack;)Z
    Code:
       0: iconst_1
       1: ireturn

  public boolean isFoil(net.minecraft.world.item.ItemStack);
    descriptor: (Lnet/minecraft/world/item/ItemStack;)Z
    Code:
       0: aload_1
       1: invokestatic  #94                 // Method isEnabled:(Lnet/minecraft/world/item/ItemStack;)Z
       4: ireturn

  public static boolean isEnabled(net.minecraft.world.item.ItemStack);
    descriptor: (Lnet/minecraft/world/item/ItemStack;)Z
    Code:
       0: aload_0
       1: getstatic     #98                 // Field reliquary/init/ModDataComponents.ENABLED:Ljava/util/function/Supplier;
       4: iconst_0
       5: invokestatic  #104                // Method java/lang/Boolean.valueOf:(Z)Ljava/lang/Boolean;
       8: invokevirtual #110                // Method net/minecraft/world/item/ItemStack.getOrDefault:(Ljava/util/function/Supplier;Ljava/lang/Object;)Ljava/lang/Object;
      11: checkcast     #105                // class java/lang/Boolean
      14: invokevirtual #116                // Method java/lang/Boolean.booleanValue:()Z
      17: ireturn

  public void inventoryTick(net.minecraft.world.item.ItemStack, net.minecraft.world.level.Level, net.minecraft.world.entity.Entity, int, boolean);
    descriptor: (Lnet/minecraft/world/item/ItemStack;Lnet/minecraft/world/level/Level;Lnet/minecraft/world/entity/Entity;IZ)V
    Code:
       0: aload_2
       1: getfield      #44                 // Field net/minecraft/world/level/Level.isClientSide:Z
       4: ifne          41
       7: aload_3
       8: instanceof    #120                // class net/minecraft/world/entity/player/Player
      11: ifeq          41
      14: aload_3
      15: checkcast     #120                // class net/minecraft/world/entity/player/Player
      18: astore        6
      20: aload         6
      22: invokevirtual #122                // Method net/minecraft/world/entity/player/Player.isSpectator:()Z
      25: ifne          41
      28: aload_2
      29: invokevirtual #125                // Method net/minecraft/world/level/Level.getGameTime:()J
      32: ldc2_w        #129                // long 2l
      35: lrem
      36: lconst_0
      37: lcmp
      38: ifeq          42
      41: return
      42: aload_1
      43: invokestatic  #94                 // Method isEnabled:(Lnet/minecraft/world/item/ItemStack;)Z
      46: ifne          50
      49: return
      50: aload_0
      51: aload_2
      52: aload         6
      54: aload_0
      55: invokevirtual #131                // Method getStandardPullDistance:()D
      58: invokevirtual #135                // Method scanForEntitiesInRange:(Lnet/minecraft/world/level/Level;Lnet/minecraft/world/entity/player/Player;D)V
      61: return

  private void scanForEntitiesInRange(net.minecraft.world.level.Level, net.minecraft.world.entity.player.Player, double);
    descriptor: (Lnet/minecraft/world/level/Level;Lnet/minecraft/world/entity/player/Player;D)V
    Code:
       0: aload_0
       1: aload_1
       2: aload_2
       3: invokevirtual #139                // Method net/minecraft/world/entity/player/Player.blockPosition:()Lnet/minecraft/core/BlockPos;
       6: invokevirtual #143                // Method getDisablePositions:(Lnet/minecraft/world/level/Level;Lnet/minecraft/core/BlockPos;)Ljava/util/List;
       9: astore        5
      11: aload_1
      12: ldc           #147                // class net/minecraft/world/entity/item/ItemEntity
      14: aload_2
      15: invokevirtual #149                // Method net/minecraft/world/entity/player/Player.getBoundingBox:()Lnet/minecraft/world/phys/AABB;
      18: dload_3
      19: invokevirtual #153                // Method net/minecraft/world/phys/AABB.inflate:(D)Lnet/minecraft/world/phys/AABB;
      22: invokevirtual #159                // Method net/minecraft/world/level/Level.getEntitiesOfClass:(Ljava/lang/Class;Lnet/minecraft/world/phys/AABB;)Ljava/util/List;
      25: astore        6
      27: aload         6
      29: invokeinterface #163,  1          // InterfaceMethod java/util/List.iterator:()Ljava/util/Iterator;
      34: astore        7
      36: aload         7
      38: invokeinterface #169,  1          // InterfaceMethod java/util/Iterator.hasNext:()Z
      43: ifeq          116
      46: aload         7
      48: invokeinterface #174,  1          // InterfaceMethod java/util/Iterator.next:()Ljava/lang/Object;
      53: checkcast     #147                // class net/minecraft/world/entity/item/ItemEntity
      56: astore        8
      58: aload_0
      59: aload         8
      61: aload         5
      63: iconst_0
      64: invokevirtual #178                // Method canPickupItem:(Lnet/minecraft/world/entity/item/ItemEntity;Ljava/util/List;Z)Z
      67: ifeq          113
      70: aload_0
      71: aload         8
      73: invokevirtual #182                // Method net/minecraft/world/entity/item/ItemEntity.getItem:()Lnet/minecraft/world/item/ItemStack;
      76: aload_2
      77: invokevirtual #186                // Method checkForRoom:(Lnet/minecraft/world/item/ItemStack;Lnet/minecraft/world/entity/player/Player;)Z
      80: ifeq          113
      83: aload         8
      85: iconst_0
      86: invokevirtual #190                // Method net/minecraft/world/entity/item/ItemEntity.setPickUpDelay:(I)V
      89: aload_2
      90: aload         8
      92: invokevirtual #194                // Method net/minecraft/world/entity/player/Player.distanceTo:(Lnet/minecraft/world/entity/Entity;)F
      95: f2d
      96: ldc2_w        #198                // double 1.5d
      99: dcmpl
     100: iflt          113
     103: aload_0
     104: aload         8
     106: aload_2
     107: invokevirtual #200                // Method teleportEntityToPlayer:(Lnet/minecraft/world/entity/Entity;Lnet/minecraft/world/entity/player/Player;)V
     110: goto          116
     113: goto          36
     116: aload_1
     117: ldc           #204                // class net/minecraft/world/entity/ExperienceOrb
     119: aload_2
     120: invokevirtual #149                // Method net/minecraft/world/entity/player/Player.getBoundingBox:()Lnet/minecraft/world/phys/AABB;
     123: dload_3
     124: invokevirtual #153                // Method net/minecraft/world/phys/AABB.inflate:(D)Lnet/minecraft/world/phys/AABB;
     127: invokevirtual #159                // Method net/minecraft/world/level/Level.getEntitiesOfClass:(Ljava/lang/Class;Lnet/minecraft/world/phys/AABB;)Ljava/util/List;
     130: astore        7
     132: aload         7
     134: invokeinterface #163,  1          // InterfaceMethod java/util/List.iterator:()Ljava/util/Iterator;
     139: astore        8
     141: aload         8
     143: invokeinterface #169,  1          // InterfaceMethod java/util/Iterator.hasNext:()Z
     148: ifeq          202
     151: aload         8
     153: invokeinterface #174,  1          // InterfaceMethod java/util/Iterator.next:()Ljava/lang/Object;
     158: checkcast     #204                // class net/minecraft/world/entity/ExperienceOrb
     161: astore        9
     163: aload_2
     164: getfield      #206                // Field net/minecraft/world/entity/player/Player.takeXpDelay:I
     167: ifle          175
     170: aload_2
     171: iconst_0
     172: putfield      #206                // Field net/minecraft/world/entity/player/Player.takeXpDelay:I
     175: aload_2
     176: aload         9
     178: invokevirtual #194                // Method net/minecraft/world/entity/player/Player.distanceTo:(Lnet/minecraft/world/entity/Entity;)F
     181: f2d
     182: ldc2_w        #198                // double 1.5d
     185: dcmpl
     186: iflt          199
     189: aload_0
     190: aload         9
     192: aload_2
     193: invokevirtual #200                // Method teleportEntityToPlayer:(Lnet/minecraft/world/entity/Entity;Lnet/minecraft/world/entity/player/Player;)V
     196: goto          202
     199: goto          141
     202: return

  private boolean canPickupItem(net.minecraft.world.entity.item.ItemEntity, java.util.List<net.minecraft.core.BlockPos>, boolean);
    descriptor: (Lnet/minecraft/world/entity/item/ItemEntity;Ljava/util/List;Z)Z
    Code:
       0: aload_1
       1: invokevirtual #210                // Method net/minecraft/world/entity/item/ItemEntity.getPersistentData:()Lnet/minecraft/nbt/CompoundTag;
       4: astore        4
       6: aload         4
       8: ldc           #214                // String PreventRemoteMovement
      10: invokevirtual #216                // Method net/minecraft/nbt/CompoundTag.getBoolean:(Ljava/lang/String;)Z
      13: ifeq          32
      16: iload_3
      17: ifeq          30
      20: aload         4
      22: ldc           #222                // String AllowMachineRemoteMovement
      24: invokevirtual #216                // Method net/minecraft/nbt/CompoundTag.getBoolean:(Ljava/lang/String;)Z
      27: ifne          32
      30: iconst_0
      31: ireturn
      32: aload_0
      33: aload_1
      34: aload_2
      35: invokevirtual #224                // Method isInDisabledRange:(Lnet/minecraft/world/entity/item/ItemEntity;Ljava/util/List;)Z
      38: ifeq          43
      41: iconst_0
      42: ireturn
      43: getstatic     #1                  // Field pickupCheckers:Ljava/util/Set;
      46: invokeinterface #228,  1          // InterfaceMethod java/util/Set.iterator:()Ljava/util/Iterator;
      51: astore        5
      53: aload         5
      55: invokeinterface #169,  1          // InterfaceMethod java/util/Iterator.hasNext:()Z
      60: ifeq          91
      63: aload         5
      65: invokeinterface #174,  1          // InterfaceMethod java/util/Iterator.next:()Ljava/lang/Object;
      70: checkcast     #229                // class reliquary/item/FortuneCoinItem$IFortuneCoinPickupChecker
      73: astore        6
      75: aload         6
      77: aload_1
      78: invokeinterface #231,  2          // InterfaceMethod reliquary/item/FortuneCoinItem$IFortuneCoinPickupChecker.canPickup:(Lnet/minecraft/world/entity/item/ItemEntity;)Z
      83: ifne          88
      86: iconst_0
      87: ireturn
      88: goto          53
      91: iconst_1
      92: ireturn

  private boolean isInDisabledRange(net.minecraft.world.entity.item.ItemEntity, java.util.List<net.minecraft.core.BlockPos>);
    descriptor: (Lnet/minecraft/world/entity/item/ItemEntity;Ljava/util/List;)Z
    Code:
       0: aload_2
       1: invokeinterface #163,  1          // InterfaceMethod java/util/List.iterator:()Ljava/util/Iterator;
       6: astore_3
       7: aload_3
       8: invokeinterface #169,  1          // InterfaceMethod java/util/Iterator.hasNext:()Z
      13: ifeq          92
      16: aload_3
      17: invokeinterface #174,  1          // InterfaceMethod java/util/Iterator.next:()Ljava/lang/Object;
      22: checkcast     #235                // class net/minecraft/core/BlockPos
      25: astore        4
      27: aload_1
      28: invokevirtual #237                // Method net/minecraft/world/entity/item/ItemEntity.blockPosition:()Lnet/minecraft/core/BlockPos;
      31: invokevirtual #238                // Method net/minecraft/core/BlockPos.getX:()I
      34: aload         4
      36: invokevirtual #238                // Method net/minecraft/core/BlockPos.getX:()I
      39: isub
      40: invokestatic  #242                // Method java/lang/Math.abs:(I)I
      43: iconst_5
      44: if_icmpge     89
      47: aload_1
      48: invokevirtual #237                // Method net/minecraft/world/entity/item/ItemEntity.blockPosition:()Lnet/minecraft/core/BlockPos;
      51: invokevirtual #248                // Method net/minecraft/core/BlockPos.getY:()I
      54: aload         4
      56: invokevirtual #248                // Method net/minecraft/core/BlockPos.getY:()I
      59: isub
      60: invokestatic  #242                // Method java/lang/Math.abs:(I)I
      63: iconst_5
      64: if_icmpge     89
      67: aload_1
      68: invokevirtual #237                // Method net/minecraft/world/entity/item/ItemEntity.blockPosition:()Lnet/minecraft/core/BlockPos;
      71: invokevirtual #251                // Method net/minecraft/core/BlockPos.getZ:()I
      74: aload         4
      76: invokevirtual #251                // Method net/minecraft/core/BlockPos.getZ:()I
      79: isub
      80: invokestatic  #242                // Method java/lang/Math.abs:(I)I
      83: iconst_5
      84: if_icmpge     89
      87: iconst_1
      88: ireturn
      89: goto          7
      92: iconst_0
      93: ireturn

  private java.util.List<net.minecraft.core.BlockPos> getDisablePositions(net.minecraft.world.level.Level, net.minecraft.core.BlockPos);
    descriptor: (Lnet/minecraft/world/level/Level;Lnet/minecraft/core/BlockPos;)Ljava/util/List;
    Code:
       0: new           #254                // class java/util/ArrayList
       3: dup
       4: invokespecial #256                // Method java/util/ArrayList."<init>":()V
       7: astore_3
       8: aload_1
       9: invokevirtual #257                // Method net/minecraft/world/level/Level.dimension:()Lnet/minecraft/resources/ResourceKey;
      12: invokevirtual #261                // Method net/minecraft/resources/ResourceKey.registry:()Lnet/minecraft/resources/ResourceLocation;
      15: aload_2
      16: bipush        10
      18: invokestatic  #267                // Method reliquary/pedestal/PedestalRegistry.getPositionsInRange:(Lnet/minecraft/resources/ResourceLocation;Lnet/minecraft/core/BlockPos;I)Ljava/util/List;
      21: astore        4
      23: aload         4
      25: invokeinterface #163,  1          // InterfaceMethod java/util/List.iterator:()Ljava/util/Iterator;
      30: astore        5
      32: aload         5
      34: invokeinterface #169,  1          // InterfaceMethod java/util/Iterator.hasNext:()Z
      39: ifeq          129
      42: aload         5
      44: invokeinterface #174,  1          // InterfaceMethod java/util/Iterator.next:()Ljava/lang/Object;
      49: checkcast     #235                // class net/minecraft/core/BlockPos
      52: astore        6
      54: aload_1
      55: aload         6
      57: invokevirtual #273                // Method net/minecraft/world/level/Level.getBlockEntity:(Lnet/minecraft/core/BlockPos;)Lnet/minecraft/world/level/block/entity/BlockEntity;
      60: astore        7
      62: aload         7
      64: instanceof    #277                // class reliquary/block/tile/PedestalBlockEntity
      67: ifeq          126
      70: aload         7
      72: checkcast     #277                // class reliquary/block/tile/PedestalBlockEntity
      75: astore        8
      77: aload         8
      79: invokevirtual #279                // Method reliquary/block/tile/PedestalBlockEntity.switchedOn:()Z
      82: ifeq          126
      85: aload         8
      87: invokevirtual #282                // Method reliquary/block/tile/PedestalBlockEntity.getItem:()Lnet/minecraft/world/item/ItemStack;
      90: astore        9
      92: aload         9
      94: invokevirtual #283                // Method net/minecraft/world/item/ItemStack.isEmpty:()Z
      97: ifne          126
     100: aload         9
     102: invokevirtual #286                // Method net/minecraft/world/item/ItemStack.getItem:()Lnet/minecraft/world/item/Item;
     105: aload_0
     106: if_acmpne     126
     109: aload         9
     111: invokestatic  #94                 // Method isEnabled:(Lnet/minecraft/world/item/ItemStack;)Z
     114: ifne          126
     117: aload_3
     118: aload         6
     120: invokeinterface #289,  2          // InterfaceMethod java/util/List.add:(Ljava/lang/Object;)Z
     125: pop
     126: goto          32
     129: aload_3
     130: areturn

  private void teleportEntityToPlayer(net.minecraft.world.entity.Entity, net.minecraft.world.entity.player.Player);
    descriptor: (Lnet/minecraft/world/entity/Entity;Lnet/minecraft/world/entity/player/Player;)V
    Code:
       0: aload_2
       1: invokevirtual #290                // Method net/minecraft/world/entity/player/Player.level:()Lnet/minecraft/world/level/Level;
       4: getstatic     #291                // Field net/minecraft/core/particles/ParticleTypes.ENTITY_EFFECT:Lnet/minecraft/core/particles/ParticleType;
       7: ldc_w         #297                // float 0.9f
      10: ldc_w         #297                // float 0.9f
      13: fconst_0
      14: invokestatic  #298                // Method net/minecraft/core/particles/ColorParticleOption.create:(Lnet/minecraft/core/particles/ParticleType;FFF)Lnet/minecraft/core/particles/ColorParticleOption;
      17: aload_1
      18: invokevirtual #304                // Method net/minecraft/world/entity/Entity.getX:()D
      21: ldc2_w        #308                // double 0.5d
      24: dadd
      25: aload_2
      26: invokevirtual #290                // Method net/minecraft/world/entity/player/Player.level:()Lnet/minecraft/world/level/Level;
      29: getfield      #58                 // Field net/minecraft/world/level/Level.random:Lnet/minecraft/util/RandomSource;
      32: invokeinterface #310,  1          // InterfaceMethod net/minecraft/util/RandomSource.nextGaussian:()D
      37: ldc2_w        #315                // double 8.0d
      40: ddiv
      41: dadd
      42: aload_1
      43: invokevirtual #317                // Method net/minecraft/world/entity/Entity.getY:()D
      46: ldc2_w        #319                // double 0.2d
      49: dadd
      50: aload_1
      51: invokevirtual #321                // Method net/minecraft/world/entity/Entity.getZ:()D
      54: ldc2_w        #308                // double 0.5d
      57: dadd
      58: aload_2
      59: invokevirtual #290                // Method net/minecraft/world/entity/player/Player.level:()Lnet/minecraft/world/level/Level;
      62: getfield      #58                 // Field net/minecraft/world/level/Level.random:Lnet/minecraft/util/RandomSource;
      65: invokeinterface #310,  1          // InterfaceMethod net/minecraft/util/RandomSource.nextGaussian:()D
      70: ldc2_w        #315                // double 8.0d
      73: ddiv
      74: dadd
      75: dconst_0
      76: dconst_0
      77: dconst_0
      78: invokevirtual #323                // Method net/minecraft/world/level/Level.addParticle:(Lnet/minecraft/core/particles/ParticleOptions;DDDDDD)V
      81: aload_2
      82: invokevirtual #327                // Method net/minecraft/world/entity/player/Player.getLookAngle:()Lnet/minecraft/world/phys/Vec3;
      85: pop
      86: aload_2
      87: invokevirtual #331                // Method net/minecraft/world/entity/player/Player.getX:()D
      90: aload_2
      91: invokevirtual #327                // Method net/minecraft/world/entity/player/Player.getLookAngle:()Lnet/minecraft/world/phys/Vec3;
      94: getfield      #332                // Field net/minecraft/world/phys/Vec3.x:D
      97: ldc2_w        #319                // double 0.2d
     100: dmul
     101: dadd
     102: dstore_3
     103: aload_2
     104: invokevirtual #338                // Method net/minecraft/world/entity/player/Player.getY:()D
     107: dstore        5
     109: aload_2
     110: invokevirtual #339                // Method net/minecraft/world/entity/player/Player.getZ:()D
     113: aload_2
     114: invokevirtual #327                // Method net/minecraft/world/entity/player/Player.getLookAngle:()Lnet/minecraft/world/phys/Vec3;
     117: getfield      #340                // Field net/minecraft/world/phys/Vec3.z:D
     120: ldc2_w        #319                // double 0.2d
     123: dmul
     124: dadd
     125: dstore        7
     127: aload_1
     128: dload_3
     129: dload         5
     131: dload         7
     133: invokevirtual #343                // Method net/minecraft/world/entity/Entity.setPos:(DDD)V
     136: return

  private boolean checkForRoom(net.minecraft.world.item.ItemStack, net.minecraft.world.entity.player.Player);
    descriptor: (Lnet/minecraft/world/item/ItemStack;Lnet/minecraft/world/entity/player/Player;)Z
    Code:
       0: aload_1
       1: invokevirtual #347                // Method net/minecraft/world/item/ItemStack.getCount:()I
       4: istore_3
       5: aload_2
       6: invokevirtual #350                // Method net/minecraft/world/entity/player/Player.getInventory:()Lnet/minecraft/world/entity/player/Inventory;
       9: getfield      #354                // Field net/minecraft/world/entity/player/Inventory.items:Lnet/minecraft/core/NonNullList;
      12: invokevirtual #360                // Method net/minecraft/core/NonNullList.iterator:()Ljava/util/Iterator;
      15: astore        4
      17: aload         4
      19: invokeinterface #169,  1          // InterfaceMethod java/util/Iterator.hasNext:()Z
      24: ifeq          167
      27: aload         4
      29: invokeinterface #174,  1          // InterfaceMethod java/util/Iterator.next:()Ljava/lang/Object;
      34: checkcast     #111                // class net/minecraft/world/item/ItemStack
      37: astore        5
      39: aload         5
      41: invokevirtual #283                // Method net/minecraft/world/item/ItemStack.isEmpty:()Z
      44: ifeq          49
      47: iconst_1
      48: ireturn
      49: aload         5
      51: invokevirtual #286                // Method net/minecraft/world/item/ItemStack.getItem:()Lnet/minecraft/world/item/Item;
      54: aload_1
      55: invokevirtual #286                // Method net/minecraft/world/item/ItemStack.getItem:()Lnet/minecraft/world/item/Item;
      58: if_acmpne     107
      61: aload         5
      63: invokevirtual #363                // Method net/minecraft/world/item/ItemStack.getDamageValue:()I
      66: aload_1
      67: invokevirtual #363                // Method net/minecraft/world/item/ItemStack.getDamageValue:()I
      70: if_icmpne     107
      73: aload         5
      75: invokevirtual #347                // Method net/minecraft/world/item/ItemStack.getCount:()I
      78: iload_3
      79: iadd
      80: aload         5
      82: invokevirtual #366                // Method net/minecraft/world/item/ItemStack.getMaxStackSize:()I
      85: if_icmpgt     90
      88: iconst_1
      89: ireturn
      90: iload_3
      91: aload         5
      93: invokevirtual #366                // Method net/minecraft/world/item/ItemStack.getMaxStackSize:()I
      96: aload         5
      98: invokevirtual #347                // Method net/minecraft/world/item/ItemStack.getCount:()I
     101: isub
     102: isub
     103: istore_3
     104: goto          164
     107: aload         5
     109: invokevirtual #286                // Method net/minecraft/world/item/ItemStack.getItem:()Lnet/minecraft/world/item/Item;
     112: getstatic     #369                // Field reliquary/init/ModItems.VOID_TEAR:Ljava/util/function/Supplier;
     115: invokeinterface #374,  1          // InterfaceMethod java/util/function/Supplier.get:()Ljava/lang/Object;
     120: if_acmpne     164
     123: getstatic     #369                // Field reliquary/init/ModItems.VOID_TEAR:Ljava/util/function/Supplier;
     126: invokeinterface #374,  1          // InterfaceMethod java/util/function/Supplier.get:()Ljava/lang/Object;
     131: checkcast     #379                // class reliquary/item/VoidTearItem
     134: aload         5
     136: invokevirtual #381                // Method reliquary/item/VoidTearItem.isEnabled:(Lnet/minecraft/world/item/ItemStack;)Z
     139: ifeq          164
     142: getstatic     #369                // Field reliquary/init/ModItems.VOID_TEAR:Ljava/util/function/Supplier;
     145: invokeinterface #374,  1          // InterfaceMethod java/util/function/Supplier.get:()Ljava/lang/Object;
     150: checkcast     #379                // class reliquary/item/VoidTearItem
     153: aload_1
     154: aload         5
     156: invokevirtual #382                // Method reliquary/item/VoidTearItem.canAbsorbStack:(Lnet/minecraft/world/item/ItemStack;Lnet/minecraft/world/item/ItemStack;)Z
     159: ifeq          164
     162: iconst_1
     163: ireturn
     164: goto          17
     167: iconst_0
     168: ireturn

  public void onUseTick(net.minecraft.world.level.Level, net.minecraft.world.entity.LivingEntity, net.minecraft.world.item.ItemStack, int);
    descriptor: (Lnet/minecraft/world/level/Level;Lnet/minecraft/world/entity/LivingEntity;Lnet/minecraft/world/item/ItemStack;I)V
    Code:
       0: aload_2
       1: instanceof    #120                // class net/minecraft/world/entity/player/Player
       4: ifeq          16
       7: aload_2
       8: checkcast     #120                // class net/minecraft/world/entity/player/Player
      11: astore        5
      13: goto          17
      16: return
      17: aload_0
      18: aload         5
      20: invokevirtual #290                // Method net/minecraft/world/entity/player/Player.level:()Lnet/minecraft/world/level/Level;
      23: aload         5
      25: aload_0
      26: invokevirtual #386                // Method getLongRangePullDistance:()D
      29: invokevirtual #135                // Method scanForEntitiesInRange:(Lnet/minecraft/world/level/Level;Lnet/minecraft/world/entity/player/Player;D)V
      32: return

  private double getLongRangePullDistance();
    descriptor: ()D
    Code:
       0: getstatic     #389                // Field reliquary/reference/Config.COMMON:Lreliquary/reference/Config$Common;
       3: getfield      #395                // Field reliquary/reference/Config$Common.items:Lreliquary/reference/Config$Common$ItemSettings;
       6: getfield      #400                // Field reliquary/reference/Config$Common$ItemSettings.fortuneCoin:Lreliquary/reference/Config$Common$ItemSettings$FortuneCoinSettings;
       9: getfield      #406                // Field reliquary/reference/Config$Common$ItemSettings$FortuneCoinSettings.longRangePullDistance:Lnet/neoforged/neoforge/common/ModConfigSpec$IntValue;
      12: invokevirtual #412                // Method net/neoforged/neoforge/common/ModConfigSpec$IntValue.get:()Ljava/lang/Object;
      15: checkcast     #415                // class java/lang/Integer
      18: invokevirtual #417                // Method java/lang/Integer.intValue:()I
      21: i2d
      22: dreturn

  private double getStandardPullDistance();
    descriptor: ()D
    Code:
       0: getstatic     #389                // Field reliquary/reference/Config.COMMON:Lreliquary/reference/Config$Common;
       3: getfield      #395                // Field reliquary/reference/Config$Common.items:Lreliquary/reference/Config$Common$ItemSettings;
       6: getfield      #400                // Field reliquary/reference/Config$Common$ItemSettings.fortuneCoin:Lreliquary/reference/Config$Common$ItemSettings$FortuneCoinSettings;
       9: getfield      #420                // Field reliquary/reference/Config$Common$ItemSettings$FortuneCoinSettings.standardPullDistance:Lnet/neoforged/neoforge/common/ModConfigSpec$IntValue;
      12: invokevirtual #412                // Method net/neoforged/neoforge/common/ModConfigSpec$IntValue.get:()Ljava/lang/Object;
      15: checkcast     #415                // class java/lang/Integer
      18: invokevirtual #417                // Method java/lang/Integer.intValue:()I
      21: i2d
      22: dreturn

  public int getUseDuration(net.minecraft.world.item.ItemStack, net.minecraft.world.entity.LivingEntity);
    descriptor: (Lnet/minecraft/world/item/ItemStack;Lnet/minecraft/world/entity/LivingEntity;)I
    Code:
       0: bipush        64
       2: ireturn

  public net.minecraft.world.item.UseAnim getUseAnimation(net.minecraft.world.item.ItemStack);
    descriptor: (Lnet/minecraft/world/item/ItemStack;)Lnet/minecraft/world/item/UseAnim;
    Code:
       0: getstatic     #423                // Field net/minecraft/world/item/UseAnim.BLOCK:Lnet/minecraft/world/item/UseAnim;
       3: areturn

  public net.minecraft.world.InteractionResultHolder<net.minecraft.world.item.ItemStack> use(net.minecraft.world.level.Level, net.minecraft.world.entity.player.Player, net.minecraft.world.InteractionHand);
    descriptor: (Lnet/minecraft/world/level/Level;Lnet/minecraft/world/entity/player/Player;Lnet/minecraft/world/InteractionHand;)Lnet/minecraft/world/InteractionResultHolder;
    Code:
       0: aload_2
       1: aload_3
       2: invokevirtual #429                // Method net/minecraft/world/entity/player/Player.getItemInHand:(Lnet/minecraft/world/InteractionHand;)Lnet/minecraft/world/item/ItemStack;
       5: astore        4
       7: aload_2
       8: invokevirtual #433                // Method net/minecraft/world/entity/player/Player.isShiftKeyDown:()Z
      11: ifeq          63
      14: aload_0
      15: aload         4
      17: invokevirtual #436                // Method toggle:(Lnet/minecraft/world/item/ItemStack;)V
      20: aload_2
      21: invokevirtual #290                // Method net/minecraft/world/entity/player/Player.level:()Lnet/minecraft/world/level/Level;
      24: aconst_null
      25: aload_2
      26: invokevirtual #139                // Method net/minecraft/world/entity/player/Player.blockPosition:()Lnet/minecraft/core/BlockPos;
      29: getstatic     #50                 // Field net/minecraft/sounds/SoundEvents.EXPERIENCE_ORB_PICKUP:Lnet/minecraft/sounds/SoundEvent;
      32: getstatic     #440                // Field net/minecraft/sounds/SoundSource.PLAYERS:Lnet/minecraft/sounds/SoundSource;
      35: ldc           #56                 // float 0.1f
      37: ldc           #57                 // float 0.5f
      39: aload_2
      40: invokevirtual #290                // Method net/minecraft/world/entity/player/Player.level:()Lnet/minecraft/world/level/Level;
      43: getfield      #58                 // Field net/minecraft/world/level/Level.random:Lnet/minecraft/util/RandomSource;
      46: invokestatic  #62                 // Method reliquary/util/RandHelper.getRandomMinusOneToOne:(Lnet/minecraft/util/RandomSource;)F
      49: ldc           #68                 // float 0.7f
      51: fmul
      52: ldc_w         #446                // float 1.8f
      55: fadd
      56: fmul
      57: invokevirtual #447                // Method net/minecraft/world/level/Level.playSound:(Lnet/minecraft/world/entity/player/Player;Lnet/minecraft/core/BlockPos;Lnet/minecraft/sounds/SoundEvent;Lnet/minecraft/sounds/SoundSource;FF)V
      60: goto          68
      63: aload_2
      64: aload_3
      65: invokevirtual #450                // Method net/minecraft/world/entity/player/Player.startUsingItem:(Lnet/minecraft/world/InteractionHand;)V
      68: new           #454                // class net/minecraft/world/InteractionResultHolder
      71: dup
      72: getstatic     #456                // Field net/minecraft/world/InteractionResult.SUCCESS:Lnet/minecraft/world/InteractionResult;
      75: aload         4
      77: invokespecial #462                // Method net/minecraft/world/InteractionResultHolder."<init>":(Lnet/minecraft/world/InteractionResult;Ljava/lang/Object;)V
      80: areturn

  public void update(net.minecraft.world.item.ItemStack, net.minecraft.world.level.Level, reliquary.api.IPedestal);
    descriptor: (Lnet/minecraft/world/item/ItemStack;Lnet/minecraft/world/level/Level;Lreliquary/api/IPedestal;)V
    Code:
       0: aload_2
       1: getfield      #44                 // Field net/minecraft/world/level/Level.isClientSide:Z
       4: ifeq          8
       7: return
       8: aload_1
       9: invokestatic  #94                 // Method isEnabled:(Lnet/minecraft/world/item/ItemStack;)Z
      12: ifeq          39
      15: aload_3
      16: invokeinterface #465,  1          // InterfaceMethod reliquary/api/IPedestal.getBlockPosition:()Lnet/minecraft/core/BlockPos;
      21: astore        4
      23: aload_0
      24: aload_3
      25: aload_2
      26: aload         4
      28: invokevirtual #470                // Method pickupItems:(Lreliquary/api/IPedestal;Lnet/minecraft/world/level/Level;Lnet/minecraft/core/BlockPos;)V
      31: aload_0
      32: aload_3
      33: aload_2
      34: aload         4
      36: invokevirtual #474                // Method pickupXp:(Lreliquary/api/IPedestal;Lnet/minecraft/world/level/Level;Lnet/minecraft/core/BlockPos;)V
      39: return

  private void pickupItems(reliquary.api.IPedestal, net.minecraft.world.level.Level, net.minecraft.core.BlockPos);
    descriptor: (Lreliquary/api/IPedestal;Lnet/minecraft/world/level/Level;Lnet/minecraft/core/BlockPos;)V
    Code:
       0: aload_0
       1: aload_2
       2: aload_3
       3: invokevirtual #143                // Method getDisablePositions:(Lnet/minecraft/world/level/Level;Lnet/minecraft/core/BlockPos;)Ljava/util/List;
       6: astore        4
       8: aload_2
       9: ldc           #147                // class net/minecraft/world/entity/item/ItemEntity
      11: new           #154                // class net/minecraft/world/phys/AABB
      14: dup
      15: aload_3
      16: invokespecial #477                // Method net/minecraft/world/phys/AABB."<init>":(Lnet/minecraft/core/BlockPos;)V
      19: aload_0
      20: invokevirtual #131                // Method getStandardPullDistance:()D
      23: invokevirtual #153                // Method net/minecraft/world/phys/AABB.inflate:(D)Lnet/minecraft/world/phys/AABB;
      26: invokevirtual #159                // Method net/minecraft/world/level/Level.getEntitiesOfClass:(Ljava/lang/Class;Lnet/minecraft/world/phys/AABB;)Ljava/util/List;
      29: astore        5
      31: aload         5
      33: invokeinterface #163,  1          // InterfaceMethod java/util/List.iterator:()Ljava/util/Iterator;
      38: astore        6
      40: aload         6
      42: invokeinterface #169,  1          // InterfaceMethod java/util/Iterator.hasNext:()Z
      47: ifeq          148
      50: aload         6
      52: invokeinterface #174,  1          // InterfaceMethod java/util/Iterator.next:()Ljava/lang/Object;
      57: checkcast     #147                // class net/minecraft/world/entity/item/ItemEntity
      60: astore        7
      62: aload_0
      63: aload         7
      65: aload         4
      67: iconst_1
      68: invokevirtual #178                // Method canPickupItem:(Lnet/minecraft/world/entity/item/ItemEntity;Ljava/util/List;Z)Z
      71: ifne          77
      74: goto          40
      77: aload_1
      78: aload_2
      79: aload         7
      81: invokevirtual #182                // Method net/minecraft/world/entity/item/ItemEntity.getItem:()Lnet/minecraft/world/item/ItemStack;
      84: invokevirtual #480                // Method net/minecraft/world/item/ItemStack.copy:()Lnet/minecraft/world/item/ItemStack;
      87: invokeinterface #483,  3          // InterfaceMethod reliquary/api/IPedestal.addToConnectedInventory:(Lnet/minecraft/world/level/Level;Lnet/minecraft/world/item/ItemStack;)I
      92: istore        8
      94: iload         8
      96: ifle          137
      99: aload         7
     101: invokevirtual #182                // Method net/minecraft/world/entity/item/ItemEntity.getItem:()Lnet/minecraft/world/item/ItemStack;
     104: aload         7
     106: invokevirtual #182                // Method net/minecraft/world/entity/item/ItemEntity.getItem:()Lnet/minecraft/world/item/ItemStack;
     109: invokevirtual #347                // Method net/minecraft/world/item/ItemStack.getCount:()I
     112: iload         8
     114: isub
     115: invokevirtual #487                // Method net/minecraft/world/item/ItemStack.setCount:(I)V
     118: aload         7
     120: invokevirtual #182                // Method net/minecraft/world/entity/item/ItemEntity.getItem:()Lnet/minecraft/world/item/ItemStack;
     123: invokevirtual #347                // Method net/minecraft/world/item/ItemStack.getCount:()I
     126: ifgt          145
     129: aload         7
     131: invokevirtual #490                // Method net/minecraft/world/entity/item/ItemEntity.discard:()V
     134: goto          145
     137: aload_1
     138: bipush        20
     140: invokeinterface #493,  2          // InterfaceMethod reliquary/api/IPedestal.setActionCoolDown:(I)V
     145: goto          40
     148: return

  private void pickupXp(reliquary.api.IPedestal, net.minecraft.world.level.Level, net.minecraft.core.BlockPos);
    descriptor: (Lreliquary/api/IPedestal;Lnet/minecraft/world/level/Level;Lnet/minecraft/core/BlockPos;)V
    Code:
       0: aload_2
       1: ldc           #204                // class net/minecraft/world/entity/ExperienceOrb
       3: new           #154                // class net/minecraft/world/phys/AABB
       6: dup
       7: aload_3
       8: invokespecial #477                // Method net/minecraft/world/phys/AABB."<init>":(Lnet/minecraft/core/BlockPos;)V
      11: aload_0
      12: invokevirtual #131                // Method getStandardPullDistance:()D
      15: invokevirtual #153                // Method net/minecraft/world/phys/AABB.inflate:(D)Lnet/minecraft/world/phys/AABB;
      18: invokevirtual #159                // Method net/minecraft/world/level/Level.getEntitiesOfClass:(Ljava/lang/Class;Lnet/minecraft/world/phys/AABB;)Ljava/util/List;
      21: astore        4
      23: aload         4
      25: invokeinterface #163,  1          // InterfaceMethod java/util/List.iterator:()Ljava/util/Iterator;
      30: astore        5
      32: aload         5
      34: invokeinterface #169,  1          // InterfaceMethod java/util/Iterator.hasNext:()Z
      39: ifeq          159
      42: aload         5
      44: invokeinterface #174,  1          // InterfaceMethod java/util/Iterator.next:()Ljava/lang/Object;
      49: checkcast     #204                // class net/minecraft/world/entity/ExperienceOrb
      52: astore        6
      54: aload         6
      56: getfield      #496                // Field net/minecraft/world/entity/ExperienceOrb.value:I
      59: invokestatic  #499                // Method reliquary/util/XpHelper.experienceToLiquid:(I)I
      62: istore        7
      64: aload_1
      65: new           #504                // class net/neoforged/neoforge/fluids/FluidStack
      68: dup
      69: getstatic     #506                // Field reliquary/init/ModFluids.XP_STILL:Ljava/util/function/Supplier;
      72: invokeinterface #374,  1          // InterfaceMethod java/util/function/Supplier.get:()Ljava/lang/Object;
      77: checkcast     #511                // class net/minecraft/world/level/material/Fluid
      80: iload         7
      82: invokespecial #513                // Method net/neoforged/neoforge/fluids/FluidStack."<init>":(Lnet/minecraft/world/level/material/Fluid;I)V
      85: invokeinterface #516,  2          // InterfaceMethod reliquary/api/IPedestal.fillConnectedTank:(Lnet/neoforged/neoforge/fluids/FluidStack;)I
      90: istore        8
      92: iload         8
      94: ifle          148
      97: aload         6
      99: invokevirtual #520                // Method net/minecraft/world/entity/ExperienceOrb.discard:()V
     102: iload         7
     104: iload         8
     106: if_icmple     156
     109: aload_2
     110: new           #204                // class net/minecraft/world/entity/ExperienceOrb
     113: dup
     114: aload_2
     115: aload_3
     116: invokevirtual #238                // Method net/minecraft/core/BlockPos.getX:()I
     119: i2d
     120: aload_3
     121: invokevirtual #248                // Method net/minecraft/core/BlockPos.getY:()I
     124: i2d
     125: aload_3
     126: invokevirtual #251                // Method net/minecraft/core/BlockPos.getZ:()I
     129: i2d
     130: iload         7
     132: iload         8
     134: isub
     135: invokestatic  #521                // Method reliquary/util/XpHelper.liquidToExperience:(I)I
     138: invokespecial #524                // Method net/minecraft/world/entity/ExperienceOrb."<init>":(Lnet/minecraft/world/level/Level;DDDI)V
     141: invokevirtual #527                // Method net/minecraft/world/level/Level.addFreshEntity:(Lnet/minecraft/world/entity/Entity;)Z
     144: pop
     145: goto          156
     148: aload_1
     149: bipush        20
     151: invokeinterface #493,  2          // InterfaceMethod reliquary/api/IPedestal.setActionCoolDown:(I)V
     156: goto          32
     159: return

  public void onRemoved(net.minecraft.world.item.ItemStack, net.minecraft.world.level.Level, reliquary.api.IPedestal);
    descriptor: (Lnet/minecraft/world/item/ItemStack;Lnet/minecraft/world/level/Level;Lreliquary/api/IPedestal;)V
    Code:
       0: return

  public void stop(net.minecraft.world.item.ItemStack, net.minecraft.world.level.Level, reliquary.api.IPedestal);
    descriptor: (Lnet/minecraft/world/item/ItemStack;Lnet/minecraft/world/level/Level;Lreliquary/api/IPedestal;)V
    Code:
       0: return

  public void toggle(net.minecraft.world.item.ItemStack);
    descriptor: (Lnet/minecraft/world/item/ItemStack;)V
    Code:
       0: aload_1
       1: getstatic     #98                 // Field reliquary/init/ModDataComponents.ENABLED:Ljava/util/function/Supplier;
       4: aload_1
       5: invokestatic  #94                 // Method isEnabled:(Lnet/minecraft/world/item/ItemStack;)Z
       8: ifne          15
      11: iconst_1
      12: goto          16
      15: iconst_0
      16: invokestatic  #104                // Method java/lang/Boolean.valueOf:(Z)Ljava/lang/Boolean;
      19: invokevirtual #531                // Method net/minecraft/world/item/ItemStack.set:(Ljava/util/function/Supplier;Ljava/lang/Object;)Ljava/lang/Object;
      22: pop
      23: return

  static {};
    descriptor: ()V
    Code:
       0: new           #534                // class java/util/HashSet
       3: dup
       4: invokespecial #536                // Method java/util/HashSet."<init>":()V
       7: putstatic     #1                  // Field pickupCheckers:Ljava/util/Set;
      10: return
}
